Workbook
Name _: #REF!,#REF!,#REF!,#REF!,#REF!,#REF!,#REF!,#REF!,#REF!,#REF!,#REF!,#REF!,#REF!,#REF!,#REF!
Name _: #REF!,#REF!,#REF!,#REF!,#REF!,#REF!,#REF!,#REF!,#REF!,#REF!,#REF!,#REF!,#REF!,#REF!,#REF!
Name _5a1_: #REF!
Name _5a1_: #REF!
Name _8X1_: #REF!
Name _DAT1: #REF!
Name _DAT10: #REF!
Name _DAT11: #REF!
Name _DAT2: #REF!
Name _DAT3: #REF!
Name _DAT4: #REF!
Name _DAT5: #REF!
Name _DAT6: #REF!
Name _DAT7: #REF!
Name _DAT8: #REF!
Name _DAT9: #REF!
Name \a: #N/A
Name \c: #N/A
Name \d: #N/A
Name ①: [2]評価基準!$AJ$7
Name ②: [2]評価基準!$AJ$9
Name ③: [2]評価基準!$AJ$11
Name ④: [2]評価基準!$AJ$13
Name ⑤: [2]評価基準!$AJ$15
Name ⑥: [2]評価基準!$AJ$17
Name ⑦: [2]評価基準!$AJ$19
Name a: #REF!,#REF!,#REF!,#REF!,#REF!,#REF!,#REF!,#REF!,#REF!,#REF!,#REF!,#REF!,#REF!,#REF!,#REF!
Name a: #REF!,#REF!,#REF!,#REF!,#REF!,#REF!,#REF!,#REF!,#REF!,#REF!,#REF!,#REF!,#REF!,#REF!,#REF!
Name aa: #REF!
Name aaa: #REF!,#REF!,#REF!,#REF!,#REF!,#REF!,#REF!,#REF!,#REF!,#REF!,#REF!,#REF!,#REF!,#REF!,#REF!
Name aaa: #REF!,#REF!,#REF!,#REF!,#REF!,#REF!,#REF!,#REF!,#REF!,#REF!,#REF!,#REF!,#REF!,#REF!,#REF!
Name aaaa: [3]テスト仕様テンプレート!#REF!
Name aaaaa: #REF!,#REF!,#REF!,#REF!,#REF!,#REF!,#REF!,#REF!,#REF!,#REF!,#REF!,#REF!,#REF!,#REF!,#REF!
Name aaaaaa: その他定義!aaaaaa
Name aaaaaa: テーブル定義!aaaaaa
Name aaaaaa: テーブル定義_old!aaaaaa
Name aaaaaa: 変更履歴!aaaaaa
Name aaaaaa: [0]!aaaaaa
Name aaaaaaaaaaaaaaaaaa: #REF!
Name aaaaaaaaaaaaaaaaaa: #REF!
Name AF: #REF!
Name AF: #REF!
Name bbbb: #REF!,#REF!,#REF!,#REF!,#REF!,#REF!,#REF!,#REF!,#REF!,#REF!,#REF!,#REF!,#REF!,#REF!,#REF!
Name BLOCK: #REF!
Name BusMemo0001: #REF!
Name BusMemo0002: #REF!
Name BusMemo0003: #REF!
Name BusMemo0004: #REF!
Name BusMemo0011: #REF!
Name CanBtn: "ボタン 3"
Name CMMi: #REF!
Name DEV: #REF!
Name Dlog_bk_prj_id: "エディット 12"
Name Dlog_bk_prj_name: "エディット 13"
Name Dlog_bk_sht_id: "エディット 14"
Name Dlog_sh_sht_name: "ドロップ 95"
Name eSkill: #REF!
Name f_01: #REF!
Name f_02: #REF!
Name f_03: #REF!

Sheet 変更履歴
A1: システム名 | F1: Dynamics365 for Finance and Operations | W1: タイトル | AR1: 日付 | BA1: 更新者
A2: 文書名 | F2: リース資産台帳 | W2: 変更履歴 | AR2: 作成 | AT2: =A6 -> 45534 | BA2: =AZ6 -> JBS大河原
AR3: 更新 | AT3: {=IF(OR(COUNTA(A:E)=3),"",INDIRECT("A"&COUNTA(A:E)+2))} -> 46093 | BA3: =IF(COUNTA(AZ5:BD100000)=1,"",INDIRECT("変更履歴!AZ"&COUNTA(AZ5:BD100000)+4)) -> JBS井田
A5: 変更年月日 | F5: 変更箇所 | T5: 変更内容 | AZ5: 変更者 | BE5: 版数
A6: 45534 | F6: 新規作成 | T6: 新規作成 | AZ6: JBS大河原 | BE6: 1.0
A7: 45617 | F7: テーブル定義 | T7: 以下のようにNo.6のフィールド物理名を修正 BookTable → BookType | AZ7: JBS山田 | BE7: 1.1
A8: 45797 | F8: テーブル定義 | T8: No.13：担当 を追加 No.15：追加借入利子率 (%) を追加 以下項目を削除 ・暗黙的レート (%) ・除却 ・当期除却償却累計額 ・期首減損損失累計額 ・当期減損損失累計額 ・期末減損損失累計額 ・除却減損損失累計額 ・期首取得価額 ・当期取得価額 ・期末取得価額 | AZ8: JBS秋信 | BE8: 1.2
A9: 45806 | F9: テーブル定義 | T9: No.14：リース満了日 を追加 No.18：指図コード を追加 No.19：指図テキスト を追加 No.20：伺い番号 を追加 以下項目を削除 ・銀行の契約番号 ・契約署名日 ・仕入先 ・契約署名日 ・担当 ・通貨 ・追加借入利子率 (%) | AZ9: JBS秋信 | BE9: 1.3
A10: 46093 | F10: テーブル定義 | T10: No.18：指図コード の桁数を12→150に変更、EDTの変更 ProjectCode→Projectに変更（仕様に合わせて修正） No.19：指図テキストの削除（No.18と内容が重複しているため） | AZ10: JBS井田 | BE10: 1.4

Sheet テーブル定義
B2: プロジェクト名 | E2: 区分 | G2: 作成日時 | H2: =変更履歴!AT2 -> 45534 | L2: 変更日時 | M2: =変更履歴!AT3 -> 46093
B3: 会計システム刷新プロジェクト（LIBRA） | E3: テーブル定義書 | G3: 作成者 | H3: =変更履歴!BA2 -> JBS大河原 | L3: 変更者 | M3: =変更履歴!BA3 -> JBS井田
B4: ﾃｰﾌﾞﾙ名(論理) | D4: ラベルID | E4: ﾃｰﾌﾞﾙ名(物理) | G4: テーブルタイプ | H4: テーブル種別 | L4: 開発区分
B5: リース資産台帳Tmp | D5: - | E5: SJ_AssetLeaseTmp | G5: TempDB | H5: Transaction | L5: アドオン
B7: # | C7: 列名(論理) | D7: ラベルID | E7: 列名(物理) | F7: 型 | G7: 拡張ﾃﾞｰﾀ型/列挙型 | H7: 桁数 | I7: PK | J7: 必須
B8: =ROW()-7 -> 1 | C8: リースID | D8: - | E8: LeaseId | F8: String | G8: AssetLeaseLeaseId | H8: 40 | I8: NO | J8: NO
B9: =ROW()-7 -> 2 | C9: リース資産名称 | D9: - | E9: LeaseDescription | F9: String | G9: AssetLeaseLeaseDescription | H9: 60 | I9: NO | J9: NO
B10: =ROW()-7 -> 3 | C10: リースグループ | D10: - | E10: SignatureDate | F10: String | G10: AssetLeaseGroup | H10: 10 | I10: NO | J10: NO
B11: =ROW()-7 -> 4 | C11: リースグループの名称 | D11: - | E11: Description | F11: String | G11: Name | H11: 60 | I11: NO | J11: NO
B12: =ROW()-7 -> 5 | C12: リース開始日 | D12: - | E12: LeaseStartDate | F12: Date | G12: AssetLeaseLeaseStartDate | H12: 0 | I12: NO | J12: NO
B13: =ROW()-7 -> 6 | C13: 取得価格 | D13: - | E13: L_FairValueOfAsset | F13: Real | G13: SJ_AssetLeaseFairValueOfAsset | H13: 0 | I13: NO | J13: NO
B14: =ROW()-7 -> 7 | C14: 期首償却累計額 | D14: - | E14: BeginningBalOfAccumulatedDep_JP | F14: Real | G14: SJ_BeginningBalOfAccumulatedDep_JP | H14: 0 | I14: NO | J14: NO
B15: =ROW()-7 -> 8 | C15: 期首正味帳簿価額 | D15: - | E15: BeginningBalOfTmpNumerals02 | F15: Real | G15: SJ_BeginningBalOfTmpNumerals02 | H15: 0 | I15: NO | J15: NO
B16: =ROW()-7 -> 9 | C16: 年度償却 | D16: - | E16: AnnualRepayment | F16: Real | G16: SJ_AnnualRepayment | H16: 0 | I16: NO | J16: NO
B17: =ROW()-7 -> 10 | C17: 償却累計額 | D17: - | E17: TermEndAccumulatedDepreciation | F17: Real | G17: SJ_TermEndAccumulatedDepreciation | H17: 0 | I17: NO | J17: NO
B18: =ROW()-7 -> 11 | C18: 正味帳簿価額 | D18: - | E18: TmpNumerals02 | F18: Real | G18: Amount | H18: 0 | I18: NO | J18: NO
B19: =ROW()-7 -> 12 | C19: 資産リース帳簿 | D19: - | E19: BookType | F19: Int64 | G19: AssetLeaseBookRefRecId | H19: 0 | I19: NO | J19: NO
... B27: =ROW()-7 -> 20 | C27: 伺い番号 | D27: - | E27: LocationNumber | F27: String | G27: AssetLeaseLocationNumber | H27: 30 | I27: NO | J27: NO
B28: =ROW()-7 -> 21 | C28: 作成者 | D28: - | E28: CreatedBy | F28: String | G28: CreatedBy | H28: 20 | I28: NO | J28: NO | K28: System項目 CreatedBy:Yes
B29: =ROW()-7 -> 22 | C29: 作成日時 | D29: - | E29: CreatedDateTime | F29: String | G29: CreatedDateTime | H29: 0 | I29: NO | J29: NO | K29: System項目 CreatedDateTime:Yes
B30: =ROW()-7 -> 23 | C30: 更新者 | D30: - | E30: ModifiedBy | F30: String | G30: ModifiedBy | H30: 20 | I30: NO | J30: NO | K30: System項目 ModifiedBy:Yes
B31: =ROW()-7 -> 24 | C31: 更新日時 | D31: - | E31: ModifiedDateTime | F31: String | G31: ModifiedDateTime | H31: 0 | I31: NO | J31: NO | K31: System項目 ModifiedDateTime:Yes
B32: =ROW()-7 -> 25
B33: =ROW()-7 -> 26
B34: =ROW()-7 -> 27

Sheet テーブル定義_old
B2: プロジェクト名 | E2: 区分 | G2: 作成日時 | H2: =変更履歴!AT2 -> 45534 | L2: 変更日時 | M2: =変更履歴!AT3 -> 46093
B3: 会計システム刷新プロジェクト（LIBRA） | E3: テーブル定義書 | G3: 作成者 | H3: =変更履歴!BA2 -> JBS大河原 | L3: 変更者 | M3: =変更履歴!BA3 -> JBS井田
B4: ﾃｰﾌﾞﾙ名(論理) | D4: ラベルID | E4: ﾃｰﾌﾞﾙ名(物理) | G4: テーブルタイプ | H4: テーブル種別 | L4: 開発区分
B5: リース資産台帳Tmp | D5: - | E5: SJ_AssetLeaseTmp | G5: TempDB | H5: Transaction | L5: アドオン
B7: # | C7: 列名(論理) | D7: ラベルID | E7: 列名(物理) | F7: 型 | G7: 拡張ﾃﾞｰﾀ型/列挙型 | H7: 桁数 | I7: PK | J7: 必須
B8: =ROW()-7 -> 1 | C8: リースグループ | D8: - | E8: SignatureDate | F8: String | G8: AssetLeaseGroup | H8: 10 | I8: NO | J8: NO
B9: =ROW()-7 -> 2 | C9: 名前 | D9: - | E9: Description | F9: String | G9: Name | H9: 60 | I9: NO | J9: NO
B10: =ROW()-7 -> 3 | C10: リースID | D10: - | E10: LeaseId | F10: String | G10: AssetLeaseLeaseId | H10: 40 | I10: NO | J10: NO
B11: =ROW()-7 -> 4 | C11: リースの説明 | D11: - | E11: LeaseDescription | F11: String | G11: AssetLeaseLeaseDescription | H11: 60 | I11: NO | J11: NO
B12: =ROW()-7 -> 5 | C12: 銀行の契約番号 | D12: - | E12: ContractNumber | F12: String | G12: AssetLeaseContractNumber | H12: 255 | I12: NO | J12: NO
B13: =ROW()-7 -> 6 | C13: 帳簿タイプ | D13: - | E13: BookType | F13: Int64 | G13: AssetLeaseBookRefRecId | H13: 0 | I13: NO | J13: NO
B14: =ROW()-7 -> 7 | C14: リース状態 | D14: - | E14: LeaseStatus | F14: Enum | G14: AssetLeaseLeaseStatus | H14: 0 | I14: NO | J14: NO
B15: =ROW()-7 -> 8 | C15: 契約署名日 | D15: - | E15: SignatureDate | F15: Date | G15: AssetLeaseDate | H15: 0 | I15: NO | J15: NO
B16: =ROW()-7 -> 9 | C16: リース開始日 | D16: - | E16: LeaseStartDate | F16: Date | G16: AssetLeaseLeaseStartDate | H16: 0 | I16: NO | J16: NO
B17: =ROW()-7 -> 10 | C17: 仕入先 | D17: - | E17: VendAccount | F17: String | G17: VendAccount | H17: 20 | I17: NO | J17: NO
B18: =ROW()-7 -> 11 | C18: 耐用年数（月単位） | D18: - | E18: MonthsOfUsefulLife | F18: Integer | G18: AssetLeaseNumberOfPeriods | H18: 0 | I18: NO | J18: NO
B19: =ROW()-7 -> 12 | C19: 場所のメモ | D19: - | E19: LocationMemo | F19: String | G19: AssetLongDescription | H19: 1000 | I19: NO | J19: NO
... B39: =ROW()-7 -> 32 | C39: 期末取得価格 | D39: - | E39: L_FairValueOfAsset | F39: Real | G39: SJ_AssetLeaseFairValueOfAsset | H39: 0 | I39: NO | J39: NO
B40: =ROW()-7 -> 33 | C40: 作成者 | D40: - | E40: CreatedBy | F40: String | G40: CreatedBy | H40: 20 | I40: NO | J40: NO | K40: System項目 CreatedBy:Yes
B41: =ROW()-7 -> 34 | C41: 作成日時 | D41: - | E41: CreatedDateTime | F41: UtcDateTime | G41: CreatedDateTime | H41: 0 | I41: NO | J41: NO | K41: System項目 CreatedDateTime:Yes
B42: =ROW()-7 -> 35 | C42: 更新者 | D42: - | E42: ModifiedBy | F42: String | G42: ModifiedBy | H42: 20 | I42: NO | J42: NO | K42: System項目 ModifiedBy:Yes
B43: =ROW()-7 -> 36 | C43: 更新日時 | D43: - | E43: ModifiedDateTime | F43: UtcDateTime | G43: ModifiedDateTime | H43: 0 | I43: NO | J43: NO | K43: System項目 ModifiedDateTime:Yes
B44: =ROW()-7 -> 37
B45: =ROW()-7 -> 38
B46: =ROW()-7 -> 39

Sheet その他定義
A1: 【フィールドグループ】
A2: # | C2: グループ名 | M2: ラベル | Q2: フィールド | BB2: その他プロパティ
A3: 1
A4: 2
A5: 3
A6: 4
A7: 5
A8: 【インデックス】
A9: # | C9: インデックス名 | M9: 重複許可 | P9: フィールド | AQ9: その他プロパティ
A10: 1
A11: 2
A12: 3
A13: 4
A14: 5
A15: 【リレーション】
A16: # | C16: リレーション名(テーブル名) | M16: リレーションタイプ | R16: 基数 | W16: 関連テーブル基数 | AB16: リレーション内容
A17: 1
A18: 2
A19: 3
A20: 【Deleteアクション】
A21: # | C21: テーブル | R21: デリートアクション | AB21: リレーション名 | BB21: その他プロパティ
A22: 1
A23: 2
A24: 3
A25: 【メソッド】
A26: No | C26: メソッド名 | M26: 戻り値(型) | U26: 引数(型) | AK26: 処理概要
A27: 1
A28: 2
A29: 3
