Workbook

Sheet 表紙
B3: サンスター株式会社 御中
B10: 会計システム刷新プロジェクト（LIBRA）
B14: To-Be業務一覧
B22: ="第"&IF(COUNTA(変更履歴!BE5:BH10027)=1,"",INDIRECT("変更履歴!BE"&COUNTA(変更履歴!BE5:BH10027)+4))&"版" -> 第1.19版
B24: {=IF(OR(COUNTA(変更履歴!A:E)=3),"",INDIRECT("変更履歴!A"&COUNTA(変更履歴!A:E)+2))} -> 45911
B26: 日本ビジネスシステムズ株式会社
F29: 作成者 | O29: JBS承認者 | V29: 承認者
F30: =変更履歴!AT2 -> 45420 | N30: 45425
F31: =変更履歴!BA2 -> JBS井田 | N31: JBS加藤

Sheet 変更履歴
A1: システム名 | F1: =表紙!B10 -> 会計システム刷新プロジェクト（LIBRA） | W1: タイトル | AR1: 日付 | BA1: 更新者
A2: 文書名 | F2: =表紙!B14 -> To-Be業務一覧 | W2: =MID(CELL("filename",$A$1),FIND("]",CELL("filename",$A$1))+1,31) -> #VALUE! | AR2: 作成 | AT2: =A6 -> 45420 | BA2: =AZ6 -> JBS井田
AR3: 更新 | AT3: {=IF(OR(COUNTA(A:E)=3),"",INDIRECT("A"&COUNTA(A:E)+2))} -> 45911 | BA3: {=IF(COUNTA(AZ5:BD100027)=1,"",INDIRECT("変更履歴!AZ"&COUNTA(AZ5:BD100027)+4))} -> JBS加藤
A5: 変更年月日 | F5: 変更箇所 | T5: 変更内容 | AZ5: 変更者 | BE5: 版数
A6: 45420 | F6: 新規作成 | T6: 新規作成 | AZ6: JBS井田 | BE6: 0.1
A7: 45433 | F7: 初版確定 | T7: 初版確定 | AZ7: JBS井田 | BE7: 1.0
A8: 45586 | F8: 2.グループファイナンス・資金繰り | T8: ２.内部貸付 3利息仕訳計上 自由書式の請求書から一般仕訳帳へ機能を変更 | AZ8: JBS福田 | BE8: 1.1
A9: 45649 | F9: 3.債権 | T9: 1.未収入金計上 3.預り金処理 返金処理 システムをFO⇒JUST.DBに変更修正 | AZ9: JBS秋信 | BE9: 1.2
A10: 45649 | F10: 3.債権 | T10: 2. 外貨取引管理 決算の業務フローを参照のため、削除 | AZ10: JBS秋信 | BE10: 1.2
A11: 45649 | F11: 3.債権 | T11: 3.売掛金振替 【SSJ】 外部システムを「楽楽精算」 ⇒ 「mcframe」 に変更 | AZ11: JBS秋信 | BE11: 1.2
A12: 45649 | F12: 4.債務 | T12: 以下業務フローを新規作成 A．銀行口座マスタ登録 B．相殺契約登録 | AZ12: JBS秋信 | BE12: 1.2
A13: 45649 | F13: 6.予算 | T13: 3.グローバル損益管理 FO外での管理となったため削除 | AZ13: JBS秋信 | BE13: 1.2
A14: 45649 | F14: 6.予算 | T14: 1.SSJ予算作成 2.SEJ予算作成 LIBRA-339 Branch1としての配賦処理の決定 を元に ・配賦処理をFOからJ-BASまたはAzure Synapse Analyticsに記述変更 ・使用しない予算登録エントリの一連の作業を削除 | AZ14: JBS秋信 | BE14: 1.2
A15: 45650 | F15: 7.Branch2 | T15: 「7.Branch2」シートを追加 | AZ15: JBS北井 | BE15: 1.3
A16: 45665 | F16: 1.一般会計・決算 | T16: １.日次振伝処理(決算G) 2.WF送信 を追加 ２.日次振伝処理(事務管理G) 6.WF送信 を追加 | AZ16: JBS福田 | BE16: 1.4
A17: 45740 | F17: 1.一般会計・決算 | T17: 【サンスター】ToBe業務フロー（1.一般会計・決算）のアップデートに伴う修正 プロセス追加 機能名称の変更 番号振り直し等 | AZ17: JBS福田 | BE17: 1.5
... A46: 45911 | F46: 1.一般会計・決算 | T46: 締め処理（元帳カレンダー）をITDXで実施するように変更 | AZ46: JBS加藤 | BE46: 1.19

Sheet 1.一般会計・決算
A1: システム名 | F1: =変更履歴!F1 -> 会計システム刷新プロジェクト（LIBRA） | V1: タイトル | AL1: 日付 | AU1: 更新者
A2: 文書名 | F2: =変更履歴!F2 -> To-Be業務一覧 | V2: =MID(CELL("filename",$A$1),FIND("]",CELL("filename",$A$1))+1,31) -> #VALUE! | AL2: 作成 | AN2: =変更履歴!AT2 -> 45420 | AU2: =変更履歴!BA2 -> JBS井田
AL3: 更新 | AN3: =変更履歴!AT3 -> 45911 | AU3: =変更履歴!BA3 -> JBS加藤
A6: 業務一覧
B8: タイトル | J8: パターン | R8: No | S8: 業務概要 | AF8: 担当 | AT8: システム | BB8: 機能名 | BJ8: 備考
AF9: 各部署 | AH9: 経理/財務 | AJ9: 事務管理G | AL9: 経営計画G | AN9: 決算G | AP9: 監査法人 | AR9: ITDX
B10: 日常業務
B11: 一般会計・決算
B12: １.日次振伝処理(決算G) | J12: １.振伝処理 | R12: 1 | S12: 伝票入力 | AH12: ● | AT12: FO | BB12: 一般仕訳帳
R13: 2 | S13: WF送信 | AH13: ● | AT13: FO | BB13: 一般仕訳帳 WF
R14: 3 | S14: 承認 | AH14: ● | AT14: FO | BB14: 仕訳帳承認対象一覧
R15: 4 | S15: 自動転記バッチ | AR15: ● | AT15: FO | BB15: 自動転記バッチ
R16: 5 | S16: 仕訳伝票照会 | AH16: ● | AT16: FO | BB16: 試算表、伝票トランザクション
B17: ２.日次振伝処理 | J17: １.振伝処理 | R17: 1 | S17: 伝票入力 | AF17: ● | AT17: 楽楽精算 | BB17: ー
B18: (事務管理G) | R18: 2 | S18: 承認申請 | AF18: ● | AT18: 楽楽精算 | BB18: ー
R19: 3 | S19: 部門承認 | AF19: ● | AT19: 楽楽精算 | BB19: ー | BJ19: （責任者）
R20: 4 | S20: 会計伝票情報取込 | AR20: ● | AT20: FO | BB20: 会計伝票情報取込
R21: 5 | S21: 仕訳伝票照会 | AH21: ● | AT21: FO | BB21: 試算表、伝票トランザクション
B22: ３.実績配賦処理 | J22: １. FO→BI実績連携 | R22: 1 | S22: 実績BI連携 | AJ22: ● | AT22: Azure Synapse Analytics | BB22: 実績BI連携 | BJ22: 仮称：PowerBI側機能調査中
J23: ２. 部課振替配賦処理 | R23: 1 | S23: 部課振替配賦処理 | AJ23: ● | AT23: Azure Synapse Analytics | BB23: 配賦処理 | BJ23: 仮称：PowerBI側機能調査中
R24: 2 | S24: 部課別予実帳票出力 | AJ24: ● | AT24: PowerBI | BB24: PowerBIレポート | BJ24: 仮称：PowerBI側機能調査中
J25: ３. 利益センター損益配賦処理 | R25: 1 | S25: 利益センター損益配賦処理 | AL25: ● | AT25: Azure Synapse Analytics | BB25: 配賦処理 | BJ25: 仮称：PowerBI側機能調査中
R26: 2 | S26: 利益センタ別予実帳票出力 | AL26: ● | AT26: PowerBI | BB26: PowerBIレポート | BJ26: 仮称：PowerBI側機能調査中
J27: ４. チャネル別損益用配賦処理 | R27: 1 | S27: チャネル別損益配賦処理 | AL27: ● | AT27: Azure Synapse Analytics | BB27: 配賦処理 | BJ27: 仮称：PowerBI側機能調査中
R28: 2 | S28: チャネル別予実帳票出力 | AL28: ● | AT28: PowerBI | BB28: PowerBIレポート | BJ28: 仮称：PowerBI側機能調査中
J29: ５. ブランド別損益用配賦処理 | R29: 1 | S29: ブランド別損益配賦処理 | AL29: ● | AT29: Azure Synapse Analytics | BB29: 配賦処理 | BJ29: 仮称：PowerBI側機能調査中
R30: 2 | S30: ブランド別予実帳票出力 | AL30: ● | AT30: PowerBI | BB30: PowerBIレポート | BJ30: 仮称：PowerBI側機能調査中
J31: ６. カテゴリ別損益用配賦処理 | R31: 1 | S31: カテゴリ別損益配賦処理 | AL31: ● | AT31: Azure Synapse Analytics | BB31: 配賦処理 | BJ31: 仮称：PowerBI側機能調査中
R32: 2 | S32: カテゴリ別予実帳票出力 | AL32: ● | AT32: PowerBI | BB32: PowerBIレポート | BJ32: 仮称：PowerBI側機能調査中
B33: ４.外貨再評価 | J33: １. 為替レートマスタ登録 | R33: 1 | S33: 為替レート情報取得 | AJ33: ● | AT33: 銀行WEB | BB33: レート照会
R34: 2 | S34: 為替レート登録 | AJ34: ● | AT34: FO | BB34: 為替レートマスタ登録
J35: ２. 売掛金管理モジュール | R35: 1 | S35: AR外貨再評価 シミュレーション | AJ35: ● | AT35: FO | BB35: AR外貨再評価
J36: 外貨再評価 | R36: 2 | S36: シミュレーション 結果確認 | AJ36: ● | AT36: FO | BB36: AR外貨再評価 | BJ36: （責任者）
R37: 3 | S37: AR外貨再評価 | AJ37: ● | AT37: FO | BB37: AR外貨再評価
R38: 4 | S38: 外貨再評価仕訳確認 | AJ38: ● | AT38: FO | BB38: 伝票トランザクション
J39: ３. 買掛金管理モジュール | R39: 1 | S39: AP外貨再評価シミュレーション | AJ39: ● | AT39: FO | BB39: AP外貨再評価
J40: 外貨再評価 | R40: 2 | S40: シミュレーション 結果確認 | AJ40: ● | AT40: FO | BB40: AP外貨再評価 | BJ40: （責任者）
R41: 3 | S41: AP外貨再評価 | AJ41: ● | AT41: FO | BB41: AP外貨再評価
R42: 4 | S42: 外貨再評価仕訳確認 | AJ42: ● | AT42: FO | BB42: 伝票トランザクション
J43: ４. 一般会計モジュール | R43: 1 | S43: 外貨再評価シミュレーション | AJ43: ● | AT43: FO | BB43: GL外貨再評価
J44: 外貨再評価 | R44: 2 | S44: シミュレーション結果確認 | AJ44: ● | AT44: FO | BB44: GL外貨再評価 | BJ44: （責任者）
R45: 3 | S45: 外貨再評価 | AJ45: ● | AT45: FO | BB45: GL外貨再評価
R46: 4 | S46: 外貨再評価仕訳確認 | AJ46: ● | AT46: FO | BB46: 伝票トランザクション
B47: ５.月次決算処理 | J47: １. 月次処理 | R47: 1 | S47: 月次決算伝票入力 | AN47: ● | AT47: FO | BB47: 一般仕訳帳
R48: 2 | S48: WF送信 | AN48: ● | AT48: FO | BB48: 一般仕訳帳 WF
R49: 3 | S49: 承認 | AN49: ● | AT49: FO | BB49: 仕訳帳承認対象一覧
R50: 4 | S50: 自動転記バッチ | AR50: ● | AT50: FO | BB50: 自動転記バッチ
R51: 5 | S51: 残高試算表確認 | AN51: ● | AT51: FO | BB51: 試算表、伝票トランザクション
R52: 6 | S52: 月次締め処理依頼 | AN52: ● | AT52: ー
R53: 7 | S53: 月次締め処理 | AR53: ● | AT53: FO | BB53: 元帳カレンダー
R54: 8 | S54: 月次MR帳票作成 | AN54: ● | AT54: FO | BB54: 財務諸表(MR)
R55: 9 | S55: 財務上 損益計算書 | AN55: ● | AT55: FO | BB55: 財務上 損益計算書
R56: 10 | S56: 各種管理会計帳票出力 | AN56: ● | AT56: FO | BB56: PowerBIレポート
B57: ６.半期決算処理 | J57: １. 1次〆 | R57: 1 | S57: 資産除去債務・償却費 資料作成・共有 | AN57: ● | AT57: ー | BB57: ー
R58: 2 | S58: 資産除去債務・償却費計上 | AN58: ● | AT58: 楽楽精算 | BB58: ー
R59: 3 | S59: 投資有価証券時価洗替 資料作成 | AJ59: ● | AT59: FO | BB59: 試算表、伝票トランザクション
R60: 4 | S60: 投資有価証券時価洗替計上 | AN60: ● | AT60: 楽楽精算 | BB60: ー
R61: 5 | S61: 前払計上･洗替（社宅洗替、各事務所家賃）資料作成 | AF61: ● | AT61: FO | BB61: 試算表、伝票トランザクション
R62: 6 | S62: 前払計上･洗替（社宅洗替、各事務所家賃計上 | AF62: ● | AT62: 楽楽精算 | BB62: ー
R63: 7 | S63: Amazon通販売上計上 | AF63: ● | AT63: 楽楽精算 | BB63: ー
R64: 8 | S64: ECサイト売上計上 | AF64: ● | AT64: 楽楽精算 | BB64: ー
R65: 9 | S65: 締め処理依頼 | AN65: ● | AT65: ー
R66: 10 | S66: 締め処理 | AR66: ● | AT66: FO | BB66: 元帳カレンダー
J67: ２. 2次〆 | R67: 1 | S67: 伝票入力許可処理 | AN67: ● | AT67: FO | BB67: 元帳カレンダー
R68: 2 | S68: 月次帳票出力＆データ保存 | AJ68: ● | AT68: FO | BB68: 財務諸表(MR)
R69: 3 | S69: 勘定残高確認(照合表作成) | AJ69: ● | AT69: FO | BB69: 試算表、伝票トランザクション
R70: 4 | S70: 棚卸報告書回収&チェック | AN70: ● | AT70: ー | BB70: ー
R71: 5 | S71: 投資有価証券棚卸 | AN71: ● | AT71: FO | BB71: 一般仕訳帳
R72: 6 | S72: 売掛金・基本手数料差異表作成 | AJ72: ● | AT72: mcframe | BB72: ー
R73: 7 | S73: 6ヶ月滞留在庫ﾘｽﾄ出力依頼＆まとめ&担当部署へ回覧 | AN73: ● | AT73: mcframe | BB73: ー
R74: 8 | S74: 預り保証金利息の計上・支払(確認のみ) | AJ74: ● | AT74: FO | BB74: 試算表、伝票トランザクション
R75: 9 | S75: 評価減Mtg | AN75: ● | AT75: ー | BB75: ー
R76: 10 | S76: ゴルフ会員権評価損の貸倒引当資料作成 | AN76: ● | AT76: ー | BB76: ー
R77: 11 | S77: ゴルフ会員権評価損の貸倒引当伝票起票 | AN77: ● | AT77: 楽楽精算 | BB77: ー
R78: 12 | S78: 外貨建債権債務洗替チェック | AJ78: ● | AT78: 楽楽精算 | BB78: ー
R79: 13 | S79: 貸倒引当金洗替資料作成 | AJ79: ● | AT79: FO | BB79: 試算表、伝票トランザクション
R80: 14 | S80: 貸倒引当金洗替 | AN80: ● | AT80: FO | BB80: 一般仕訳帳
R81: 15 | S81: 貯蔵品振替 確認資料作成 | AJ81: ● | AT81: FO | BB81: 試算表、伝票トランザクション
R82: 16 | S82: 貯蔵品振替伝票起票 | AJ82: ● | AT82: 楽楽精算 | BB82: ー
R83: 17 | S83: リースに係る処理 | AJ83: ● | AT83: ー | BB83: ー
R84: 18 | S84: 源泉税振替 | AJ84: ● | AT84: 楽楽精算 | BB84: ー
R85: 19 | S85: 固定資産除却損・売却益振替 | AJ85: ● | AT85: 楽楽精算 | BB85: ー
R86: 20 | S86: 建仮・ソフト仮消費税振替 | AJ86: ● | AT86: 楽楽精算 | BB86: ー
R87: 21 | S87: クレーム引当計上 資料作成 | AJ87: ● | AT87: FO | BB87: 試算表、伝票トランザクション
R88: 22 | S88: クレーム引当計上 | AJ88: ● | AT88: 楽楽精算 | BB88: ー
R89: 23 | S89: 減損兆候判定 | AN89: ● | AT89: FO | BB89: 固定資産
R90: 24 | S90: 減損作業 固定資産業務フロー シート「固定資産管理」の 「5．固定資産現物管理（減損処理）」 | AN90: ● | AT90: ー | BB90: ー
R91: 25 | S91: 運中在庫計上 | AJ91: ● | AT91: 楽楽精算 | BB91: ー
R92: 26 | S92: 卸店リベート・販促費予定計上資料作成 | AJ92: ● | AT92: mcframe | BB92: ー
R93: 27 | S93: 卸店リベート・販促費予定計上 | AJ93: ● | AT93: 楽楽精算 | BB93: ー
R94: 28 | S94: 決算伝票入力漏れ確認チェック | AN94: ● | AT94: FO | BB94: 試算表、伝票トランザクション
R95: 29 | S95: 締め処理依頼 | AN95: ● | AT95: ー
R96: 30 | S96: 締め処理 | AR96: ● | AT96: FO | BB96: 元帳カレンダー
J97: ３. 3次〆 | R97: 1 | S97: 伝票入力許可処理 | AN97: ● | AT97: FO | BB97: 元帳カレンダー
R98: 2 | S98: 月次帳票出力＆データ保存(2次〆） | AJ98: ● | AT98: FO | BB98: 財務諸表(MR)
R99: 3 | S99: 勘定残高確認(照合表作成)(2次〆） | AJ99: ● | AT99: FO | BB99: 試算表、伝票トランザクション
R100: 4 | S100: 支店決算書確認 | AJ100: ● | AT100: ー | BB100: ー | BJ100: MRとPowerBIを参照してEXCELで作成
R101: 5 | S101: カテゴリー別損益(事業報告文章編に使用) | AN101: ● | AT101: ー | BB101: ー
R102: 6 | S102: 在庫評価減資料作成 | AN102: ● | AT102: mcframe | BB102: ー
R103: 7 | S103: 交際費データ集計 | AJ103: ● | AT103: 楽楽精算 | BB103: ー
...

Sheet 2.グループファイナンス・資金繰り
A1: システム名 | F1: =変更履歴!F1 -> 会計システム刷新プロジェクト（LIBRA） | V1: タイトル | AN1: 日付 | AU1: 更新者
A2: 文書名 | F2: =変更履歴!F2 -> To-Be業務一覧 | V2: =MID(CELL("filename",$A$1),FIND("]",CELL("filename",$A$1))+1,31) -> #VALUE! | AL2: 作成 | AN2: 作成 | AP2: =変更履歴!AT2 -> 45420 | AU2: =変更履歴!BA2 -> JBS井田
AL3: 更新 | AN3: 更新 | AP3: =変更履歴!AT3 -> 45911 | AU3: =変更履歴!BA3 -> JBS加藤
A6: 業務一覧
B8: タイトル | J8: パターン | R8: No | S8: 業務概要 | AF8: 担当 | AP8: システム | AX8: 機能名 | BF8: 備考
AF9: カスタマーサービスG | AH9: 事務管理G | AJ9: 資金G | AL9: 各チャネル | AN9: ITDX
B10: 日常業務
B11: グループファイナンス・資金繰り
B12: １.日次振伝処理(決算G) | J12: １.振伝処理 | R12: 1 | S12: 伝票入力 | AJ12: ● | AP12: FO | AX12: 一般仕訳帳
R13: 2 | S13: WF送信 | AJ13: ● | AP13: FO | AX13: 一般仕訳帳 WF
R14: 3 | S14: 承認 | AJ14: ● | AP14: FO | AX14: 仕訳帳承認対象一覧
R15: 4 | S15: 自動転記バッチ | AN15: ● | AP15: FO | AX15: 自動転記バッチ
R16: 5 | S16: 仕訳伝票照会 | AJ16: ● | AP16: FO | AX16: 試算表、伝票トランザクション
B17: １.現預金 | J17: １.現金管理 | R17: 1 | S17: 現金集計表 作成 | AH17: ● | AP17: FO | AX17: 試算表
R18: 2 | S18: 現金出帳帳 作成 | AH18: ● | AP18: FO | AX18: 分析コード明細書
J19: ２.引落手数料と決済利息の計上 | R19: 1 | S19: 銀行引落手数料情報出力 | AH19: ● | AP19: 資金集中管理 | AX19: ー
R20: 2 | S20: 銀行引落手数料仕訳計上 | AH20: ● | AP20: FO | AX20: 一般仕訳帳
R21: 3 | S21: 預金決算利息情報出力 | AH21: ● | AP21: 資金集中管理 | AX21: ー
R22: 4 | S22: 預金決算利息仕訳計上 | AH22: ● | AP22: FO | AX22: 一般仕訳帳
J23: 3.残高管理 日別資金繰 | R23: 1 | S23: 現預金残高 確認 | AH23: ● | AP23: FO | AX23: 試算表
R24: 2 | S24: 回収見込情報の収集 | AF24: ● | AP24: mcframe | AX24: ー
R25: 3 | S25: 得意先別回収見込一覧の作成 | AH25: ● | AP25: mcframe | AX25: ー
R26: 4 | S26: 期日支払一覧の作成 | AH26: ● | AP26: FO | AX26: 仕入先トランザクション一覧 | BF26: Excelファイル出力
R27: 5 | S27: 資金移動仕訳計上 | AJ27: ● | AP27: FO | AX27: 一般仕訳帳
R28: 6 | S28: 残高確認 | AJ28: ● | AP28: FO | AX28: 試算表、伝票トランザクション
B29: ２.資金予測 | J29: １.年間資金繰計画 | R29: 1 | S29: ベース損益用データ出力 | AJ29: ● | AP29: FO | AX29: 財務諸表(MR)
B30: ※ | C30: 現行のEXCEL作業が | R30: 2 | S30: ベース損益作成 | AJ30: ● | AP30: ー | AX30: ー
C31: D365標準機能で対応不可のため | R31: 3 | S31: 前提条件設定 | AJ31: ● | AP31: ー | AX31: ー
C32: FOのスコープ外となった | R32: 4 | S32: 各種勘定 前年実績収集 | AJ32: ● | AP32: FO | AX32: 財務諸表(MR)
R33: 5 | S33: 支払/入金予定収集 | AJ33: ● | AP33: FO mcframe | AX33: 債務とランザクション、債権トランザクション | BF33: 売掛金が仕訳情報のみであるため検討。
C34: 年度資金繰計画EXCEL | R34: 6 | S34: チャネル別回収計画 | AL34: ● | AP34: ー | AX34: ー
C35: 月別資金繰実績EXCEL | R35: 7 | S35: 年間資金繰計画作成 | AJ35: ● | AP35: ー | AX35: ー
C36: 日別資金繰実績EXCEL | J36: ２.月次資金繰予実 | R36: 1 | S36: 各種勘定 実績収集 | AJ36: ● | AP36: FO | AX36: 財務諸表(MR)
R37: 2 | S37: 支払/入金 実績収集 | AJ37: ● | AP37: FO mcframe | AX37: 債務とランザクション、債権トランザクション | BF37: ※D365標準機能で出力できる情報 では不足する情報を別途収集する
R38: 3 | S38: 資金繰実績作成 | AJ38: ● | AP38: ー | AX38: ー
R39: 4 | S39: 資金繰予実作成 | AJ39: ● | AP39: ー | AX39: ー
J40: ３.日別資金繰予実 | R40: 1 | S40: 月初見込作成 | AJ40: ● | AP40: ー | AX40: ー
R41: 2 | S41: 銀行口座入出金明細出力 | AJ41: ● | AP41: FO | AX41: 試算表、伝票トランザクション
R42: 3 | S42: 合計日別資金繰実績作成 | AJ42: ● | AP42: ー | AX42: ー
B43: ３.調達・運用・通貨交換 | J43: １.銀行借入 | R43: 1 | S43: 借入金計上 | AJ43: ● | AP43: FO | AX43: 一般仕訳帳 | BF43: ※利息計算機能なし
R44: 2 | S44: 利息額の計算 | AJ44: ● | AP44: ー | AX44: ー | BF44: ※利息計算機能なし
R45: 3 | S45: 利息仕訳の計上 | AJ45: ● | AP45: FO | AX45: 一般仕訳帳 | BF45: ※利息自動計上機能なし
R46: 4 | S46: 長短振替仕訳計上 | AJ46: ● | AP46: FO | AX46: 一般仕訳帳 | BF46: ※自動長短振替機能なし
R47: 5 | S47: 返済仕訳計上 | AJ47: ● | AP47: FO | AX47: 一般仕訳帳 | BF47: ※自動返済仕訳作成機能なし
R48: 6 | S48: 支払手数料仕訳計上 | AJ48: ● | AP48: FO | AX48: 一般仕訳帳 | BF48: ※通貨交換して入出金する際に、銀行に支払うマージンを自動で計算・記録する機能なし
R49: 7 | S49: 借入金残高確認 | AJ49: ● | AP49: FO | AX49: 試算表、伝票トランザクション | BF49: ※将来の残高/返済額/利息額が年別で表示される機能
J50: ２.運用 | R50: 1 | S50: 運用開始仕訳計上 | AJ50: ● | AP50: FO | AX50: 一般仕訳帳 | BF50: ※運用状況を会計システム内で管理する機能なし
R51: 2 | S51: 運用収益額の確認 | AJ51: ● | AP51: ー | AX51: ー | BF51: ※D365標準機能に運用益計算機能なし
R52: 3 | S52: 運用収益仕訳計上 | AJ52: ● | AP52: FO | AX52: 一般仕訳帳
R53: 4 | S53: 運用返済仕訳計上 | AJ53: ● | AP53: FO | AX53: 一般仕訳帳
R54: 5 | S54: 運用残高確認 | AJ54: ● | AP54: FO | AX54: 試算表、伝票トランザクション
J55: ３.通貨交換 | R55: 1 | S55: 通貨交換依頼 | AJ55: ● | AP55: 銀行WEB | AX55: ー
R56: 2 | S56: 通貨交換仕訳計上 | AJ56: ● | AP56: FO | AX56: 一般仕訳帳
B57: ４.グループファイナンス | J57: １.内部借入 | R57: 1 | S57: 借入金計上 | AJ57: ● | AP57: FO | AX57: 一般仕訳帳 | BF57: ※利息計算機能なし
B58: (内部借入・貸付) | R58: 2 | S58: 利息額の計算 | AJ58: ● | AP58: ー | AX58: ー | BF58: ※利息計算機能なし
R59: 3 | S59: 利息仕訳の計上 | AJ59: ● | AP59: FO | AX59: 一般仕訳帳 | BF59: ※利息自動計上機能なし
R60: 4 | S60: 長短振替仕訳計上 | AJ60: ● | AP60: FO | AX60: 一般仕訳帳 | BF60: ※自動長短振替機能なし
R61: 5 | S61: 返済処理 | AJ61: ● | AP61: 銀行WEB | AX61: ー
R62: 6 | S62: 返済仕訳計上 | AJ62: ● | AP62: FO | AX62: 一般仕訳帳 | BF62: ※自動返済仕訳作成機能なし
R63: 7 | S63: 支払手数料仕訳計上 | AJ63: ● | AP63: FO | AX63: 一般仕訳帳 | BF63: ※銀行に支払うマージンを自動で計算・記録する機能なし
R64: 8 | S64: 借入金残高確認 | AJ64: ● | AP64: FO | AX64: 試算表、伝票トランザクション | BF64: ※将来の残高/返済額/利息額が年別で表示される機能
J65: ２.内部貸付 | R65: 1 | S65: 貸付仕訳計上 | AJ65: ● | AP65: FO | AX65: 一般仕訳帳 | BF65: ※金利条件・利息発生タイミング・貸付期間・返済タイミングなどの情報を管理する機能なし
R66: 2 | S66: 利息額の計算 | AJ66: ● | AP66: ー | AX66: ー | BF66: ※貸付利息計算機能なし
R67: 3 | S67: 利息仕訳計上 | AJ67: ● | AP67: FO | AX67: 一般仕訳帳
R68: 4 | S68: 利息の請求書発行 | AJ68: ● | AP68: ー | AX68: ー | BF68: ※EXCEL等FO外機能で対応
R69: 5 | S69: 返済入金確認 | AJ69: ● | AP69: 銀行WEB 口座残高 | AX69: ー
R70: 6 | S70: 返済仕訳計上 | AJ70: ● | AP70: FO | AX70: 一般仕訳帳 | BF70: ※貸付金情報から、自動で返済仕訳を計上する機能なし
R71: 7 | S71: 運用残高確認 | AJ71: ● | AP71: FO EXCEL借入金台帳 | AX71: 試算表、伝票トランザクション
J72: ３.配当金決済 | R72: 1 | S72: 配当金入金確認 | AJ72: ● | AP72: 銀行WEB 口座残高 | AX72: ー
R73: 2 | S73: 配当金仕訳計上 | AJ73: ● | AP73: FO | AX73: 一般仕訳帳
B74: ５.月次グループ管理 | J74: １.借入・預金管理
B75: (借入預金) | J75: ※Excelでローデータを収集
J76: BIツール等でまとめる想定。
B77: ６.四半期グループ管理 | J77: １.グループ間借入・貸付管理
B78: (借入貸付) | J78: ※Excelでローデータを収集
J79: BIツール等でまとめる想定。

Sheet ３.債権
A1: システム名 | F1: =変更履歴!F1 -> 会計システム刷新プロジェクト（LIBRA） | V1: タイトル | AL1: 日付 | AS1: 更新者
A2: 文書名 | F2: =変更履歴!F2 -> To-Be業務一覧 | V2: =MID(CELL("filename",$A$1),FIND("]",CELL("filename",$A$1))+1,31) -> #VALUE! | AL2: 作成 | AN2: =変更履歴!AT2 -> 45420 | AS2: =変更履歴!BA2 -> JBS井田
AL3: 更新 | AN3: =変更履歴!AT3 -> 45911 | AS3: =変更履歴!BA3 -> JBS加藤
A6: 業務一覧
B8: タイトル | J8: パターン | R8: No | S8: 業務概要 | AF8: 担当 | BF8: システム | BN8: 機能名 | BV8: 備考
AF9: 外部 | AH9: カスタマーサービスG 他 | AJ9: カスタマーサービスG | AL9: 事務管理G | AN9: 顧客G・物流 | AP9: 各部門 | AR9: 経営計画G | AT9: 営業部 | AV9: 決算G | AX9: 営業企画部営業推進G | AZ9: 各営業部 | BB9: 財務部 | BD9: ITDX
B10: 日常業務
B11: 債権
B12: １.SSJ・SEJ売上計上・請求処理 (売掛金) | J12: １.売上 | R12: 1 | S12: 売上対象伝票の確認 | AH12: ● | BF12: mcframe SEJホスト | BN12: ー | BV12: SSJ:mcframe,SEJ:AS400 FO（）
R13: 2 | S13: 売上の計上 | AH13: ● | BF13: mcframe SEJホスト | BN13: ー | BV13: SSJ:mcframe,SEJ:AS400 FO（）
J14: ２.都度請求 | R14: 1 | S14: 請求書の 発行 | AH14: ● | BF14: mcframe SEJホスト | BN14: ー
R15: 2 | S15: 請求書 の送付 | AH15: ● | BF15: ー | BN15: ー | BV15: メール送付
R16: 3 | S16: 請求書の受領 | AF16: ● | BF16: ー | BN16: ー
J17: ３.締め請求 | R17: 1 | S17: 請求の締め処理 | AH17: ● | BF17: mcframe SEJホスト | BN17: ー
R18: 2 | S18: 締め処理の確定 | AH18: ● | BF18: mcframe SEJホスト | BN18: ー
R19: 3 | S19: 請求書の発行 | AH19: ● | BF19: mcframe SEJホスト | BN19: ー
R20: 4 | S20: 請求書の送付 | AH20: ● | BF20: ー | BN20: ー | BV20: メール送付
R21: 5 | S21: 請求書の受領 | AF21: ● | BF21: ー | BN21: ー | BV21: メール送付
B22: ２.SLJ売上計上・請求処理 (売掛金) | J22: １.売上 | R22: 1 | S22: 売上対象伝票の確認 | AN22: ● | BF22: ー | BN22: ー
R23: 2 | S23: 売上の計上 | AN23: ● | BF23: SLJ販売管理システム | BN23: ー
J24: ２.売上（FO直接計上） | R24: 1 | S24: 売上データ登録 | AN24: ● | BF24: FO | BN24: 一般仕訳帳
R25: 2 | S25: 伝票承認申請 | AN25: ● | BF25: FO | BN25: 一般仕訳帳 WF
R26: 3 | S26: 伝票承認 | AN26: ● | BF26: FO | BN26: 一般仕訳帳 WF | BV26: （責任者）
R27: 4 | S27: 自動転記バッチ | BD27: ● | BF27: FO | BN27: 自動転記バッチ
J28: ３.都度請求 | R28: 1 | S28: 請求書の 発行 | AN28: ● | BF28: SLJ販売管理システム | BN28: ー
R29: 2 | S29: 請求書 の送付 | AN29: ● | BF29: ー | BN29: ー | BV29: メール送付
R30: 3 | S30: 請求書の受領 | AF30: ● | BF30: ー | BN30: ー
J31: ４.締め請求 | R31: 1 | S31: 請求の締め処理 | AN31: ● | BF31: SLJ販売管理システム | BN31: ー
R32: 2 | S32: 締め処理の確定 | AN32: ● | BF32: SLJ販売管理システム | BN32: ー
R33: 3 | S33: 請求書の発行 | AN33: ● | BF33: SLJ販売管理システム | BN33: ー
R34: 4 | S34: 請求書の送付 | AN34: ● | BF34: ー | BN34: ー | BV34: メール送付
R35: 5 | S35: 請求書の受領 | AF35: ● | BF35: ー | BN35: ー
B36: ３.SSJ・SEJ入金 (売掛金) | J36: １.入金（EB取り込み） | R36: 1 | S36: 入金情報提示 | AF36: ● | BF36: ー | BN36: ー
J37: 売上回収専用口座への入金 | R37: 2 | S37: EBデータダウンロード | AJ37: ● | BF37: 銀行システム | BN37: ー
R38: 3 | S38: EBデータ取り込み | AJ38: ● | BF38: mcframe SEJホスト | BN38: ー
R39: 4 | S39: EBデータ取込結果確認 | AJ39: ● | BF39: mcframe SEJホスト | BN39: ー
R40: 5 | S40: 不明入金調査 | AJ40: ● | BF40: 通販管理プラットフォーム mcframe SEJホスト | BN40: ー
R41: 6 | S41: 入金入力 | AJ41: ● | BF41: mcframe SEJホスト | BN41: ー
J42: ２. 入金（EB取り込み） | R42: 1 | S42: 入金情報提示 | AF42: ● | BF42: ー | BN42: ー
J43: 売上回収専用口座以外への入金 | R43: 2 | S43: 入金確認 | AL43: ● | BF43: 銀行システム | BN43: ー
R44: 3 | S44: 入金連絡 | AL44: ● | BF44: ー | BN44: ー
R45: 4 | S45: 入金入力 | AJ45: ● | BF45: mcframe SEJホスト | BN45: ー
J46: ３.入金（EB取り込み以外） | R46: 1 | S46: 銀行振込確認 | AJ46: ● | BF46: ー | BN46: ー
R47: 2 | S47: 未回収データ確認 | AJ47: ● | BF47: mcframe SEJホスト | BN47: ー
R48: 3 | S48: 入金データ登録 | AJ48: ● | BF48: ー | BN48: ー
R49: 4 | S49: 修正連絡 | AJ49: ● | BF49: ー | BN49: ー
R50: 5 | S50: 再入金 | AF50: ● | BF50: ー | BN50: ー
R51: 6 | S51: 入金データ転記 | AJ51: ● | BF51: mcframe SEJホスト | BN51: ー
J52: ４.入金（前受） | R52: 1 | S52: 銀行振込確認 | AJ52: ● | BF52: ー | BN52: ー
R53: 2 | S53: 入金データ登録 | AJ53: ● | BF53: mcframe SEJホスト | BN53: ー
R54: 3 | S54: 入金データ転記 | AJ54: ● | BF54: mcframe SEJホスト | BN54: ー
J55: ５.入金管理表作成 | R55: 1 | S55: 入金情報抽出 | AH55: ● | BF55: mcframe SEJホスト | BN55: ー
R56: 2 | S56: 入金管理表作成 | AH56: ● | BF56: ー | BN56: ー
B57: ４.SLJ入金 (売掛金) | J57: １.入金（EB取り込み） | R57: 1 | S57: 入金情報提示 | AF57: ● | BF57: ー | BN57: ー
R58: 2 | S58: EBデータダウンロード | AN58: ● | BF58: 銀行システム | BN58: ー
R59: 3 | S59: EBデータ取り込み | AN59: ● | BF59: FO | BN59: 顧客支払仕訳帳
R60: 4 | S60: 伝票承認申請 | AN60: ● | BF60: FO | BN60: 顧客支払仕訳帳 WF
R61: 5 | S61: 伝票承認 | AN61: ● | BF61: FO | BN61: 顧客支払仕訳帳 WF | BV61: （責任者）
R62: 6 | S62: 自動転記バッチ | BD62: ● | BF62: FO | BN62: 自動転記バッチ
J63: ２.入金（EB取り込み以外） | R63: 1 | S63: 銀行振込確認 | AN63: ● | BF63: ー | BN63: ー
R64: 2 | S64: 未回収データ確認 | AN64: ● | BF64: FO | BN64: 期日が超過した顧客請求書
R65: 3 | S65: 債権データの紐づけ | AN65: ● | BF65: FO | BN65: 顧客支払仕訳帳
R66: 4 | S66: 修正連絡 | AN66: ● | BF66: ー | BN66: ー
R67: 5 | S67: 再入金 | AF67: ● | BF67: ー | BN67: ー
R68: 6 | S68: 伝票承認申請 | AN68: ● | BF68: FO | BN68: 顧客支払仕訳帳 WF
R69: 7 | S69: 伝票承認 | AN69: ● | BF69: FO | BN69: 顧客支払仕訳帳 WF | BV69: （責任者）
R70: 8 | S70: 自動転記バッチ | BD70: ● | BF70: FO | BN70: 自動転記バッチ
B71: ５.SSJ・SEJ入金消込 (売掛金) | J71: １.入金消込 | R71: 1 | S71: 入金消込 | AJ71: ● | BF71: mcframe SEJホスト | BN71: ー
J72: ２.前受消込 | R72: 1 | S72: 前受金データ確認 | AJ72: ● | BF72: mcframe SEJホスト | BN72: ー
R73: 2 | S73: 前受入金と受注データの紐づけ・消込 | AJ73: ● | BF73: mcframe SEJホスト | BN73: ー
B74: ６.SLJ入金消込 (売掛金) | J74: １.入金消込 | R74: 1 | S74: 入金消込 | AN74: ● | BF74: FO | BN74: トランザクションの決済
B75: ７.その他取引計上 | J75: １. 未収入金計上 | R75: 1 | S75: 請求書発行依頼書作成 | AP75: ● | BF75: ー | BN75: ー
R76: 2 | S76: 請求書発行依頼 | AP76: ● | BF76: ー | BN76: ー
R77: 3 | S77: 債権登録・承認申請 | AL77: ● | BF77: 楽楽精算 | BN77: ー
R78: 4 | S78: 登録内容確認・承認 | AL78: ● | BF78: 楽楽精算 | BN78: ー
R79: 5 | S79: 請求書の発行 | AL79: ● | BF79: BtoBプラットフォーム | BN79: ー
R80: 6 | S80: 請求書の保存 | AL80: ● | BF80: BtoBプラットフォーム | BN80: ー
R81: 7 | S81: 請求書の送付 | AL81: ● | BF81: ー | BN81: ー
R82: 10 | S82: 請求書の受領 | AF82: ● | BF82: ー | BN82: ー
J83: ２. 預り金処理 台帳作成 | R83: 1 | S83: 預り金情報抽出 | AJ83: ● | BF83: FO | BN83: 試算表、伝票トランザクション
R84: 2 | S84: 預り金台帳作成 | AJ84: ● | BF84: ー | BN84: ー
J85: ３. 預り金処理 返金処理 | R85: 1 | S85: 預り金返金 | AJ85: ● | BF85: mcframe | BN85: ー
R86: 2 | S86: 預り金消込 | AJ86: ● | BF86: 楽楽精算 | BN86: ー
R87: 3 | S87: 預り金台帳更新 | AJ87: ● | BF87: ー | BN87: ー
J88: 4.委託費 | R88: 1 | S88: 業務委託情報抽出 | AJ88: ● | BF88: FO | BN88: 試算表、伝票トランザクション
R89: 2 | S89: 台帳更新 | AJ89: ● | BF89: ー | BN89: ー
R90: 3 | S90: 振替処理 | AJ90: ● | BF90: 楽楽精算 | BN90: ー
J91: 5.グループ間の立替金請求 | R91: 1 | S91: 立替金登録依頼情報作成 | AP91: ● | BF91: ー | BN91: ー
R92: 2 | S92: 登録内容確認・承認 | AP92: ● | BF92: ー | BN92: ー
R93: 3 | S93: 立替金登録・申請 | AL93: ● | BF93: FO | BN93: 一般仕訳帳 WF | BV93: Req003の仕訳インポート機能を使用想定
R94: 4 | S94: 登録内容確認・承認 | AL94: ● | BF94: FO | BN94: 一般仕訳帳 WF | BV94: （責任者）
R95: 5 | S95: 立替金データ転記 | AL95: ● | BF95: FO | BN95: 一般仕訳帳
R96: 6 | S96: 立替金情報抽出 | AL96: ● | BF96: FO | BN96: 試算表、伝票トランザクション | BV96: 月末作業
R97: 7 | S97: 立替金請求書作成・請求 | AL97: ● | BF97: ー | BN97: ー | BV97: 月末作業
J98: 6.家賃収入 収益計上（SLJ） | R98: 1 | S98: 収益計上の振替伝票登録 | AL98: ● | BF98: FO | BN98: 一般仕訳帳アップロード
R99: 2 | S99: 承認依頼 | AL99: ● | BF99: FO | BN99: 一般仕訳帳 WF
R100: 3 | S100: 承認 | AL100: ● | BF100: FO | BN100: 一般仕訳帳 WF、仕訳帳承認対象一覧
R101: 4 | S101: 自動転記バッチ | BD101: ● | BF101: FO | BN101: 自動転記バッチ
B102: ８.入金 (未収入金) | J102: １.入金 | R102: 1 | S102: 入金情報提示 | AF102: ● | BF102: ー | BN102: ー
R103: 2 | S103: EBデータダウンロード | AL103: ● | BF103: 銀行システム | BN103: ー
...

Sheet 4.債務
A1: システム名 | F1: =変更履歴!F1 -> 会計システム刷新プロジェクト（LIBRA） | V1: タイトル | AL1: 日付 | AS1: 更新者
A2: 文書名 | F2: =変更履歴!F2 -> To-Be業務一覧 | V2: =MID(CELL("filename",$A$1),FIND("]",CELL("filename",$A$1))+1,31) -> #VALUE! | AL2: 作成 | AN2: =変更履歴!AT2 -> 45420 | AS2: =変更履歴!BA2 -> JBS井田
AL3: 更新 | AN3: =変更履歴!AT3 -> 45911 | AS3: =変更履歴!BA3 -> JBS加藤
A6: 業務一覧
B8: タイトル | J8: パターン | R8: No | S8: 業務概要 | AF8: 担当 | AX8: システム | BF8: 機能名 | BN8: 備考
AF9: 外部 | AH9: 各工場、購買 | AJ9: 各部門 | AL9: 事務管理G | AN9: 総務部 | AP9: 物流企画 | AR9: 各部署 | AT9: カスタマーサービスG | AV9: ITDX
B10: 日常業務
B11: 債務
B12: 1.仕入計上・請求処理 | J12: １.仕入計上・請求処理 | R12: 1 | S12: 請求書の送付 | AF12: ● | AX12: ー | BF12: ー
R13: 2 | S13: 請求書受領 | AH13: ● | AJ13: ● | AL13: ● | AN13: ● | AP13: ● | AX13: ー | BF13: ー
R14: 3 | S14: 仕入計上 | AH14: ● | AX14: mcframe SEJホスト | BF14: ー
R15: 3 | S15: 仕入計上 | AJ15: ● | AX15: 楽楽精算 BtoBプラットフォーム | BF15: ー
R16: 3 | S16: 仕入計上 | AL16: ● | AX16: 広告費システム | BF16: ー
R17: 3 | S17: 仕入計上 | AN17: ● | AX17: SEJ販売管理 | BF17: ー
R18: 3 | S18: 仕入計上 | AP18: ● | AX18: EDIL | BF18: ー
R19: 4 | S19: 取消仕訳 | AH19: ● | AX19: 楽楽精算 | BF19: ー
R20: 5 | S20: 修正仕訳 | AH20: ● | AX20: 楽楽精算 | BF20: ー
B21: 2.前払 | J21: １.前払（計上） | R21: 1 | S21: 前払登録 | AL21: ● | AX21: 楽楽精算 BtoBプラットフォーム | BF21: ー | BN21: 前払/未払金の仕訳計上する
J22: ２.前払（費用発生時） | R22: 1 | S22: 前払振替登録・申請 | AL22: ● | AX22: FO | BF22: 一般仕訳帳
R23: 2 | S23: 前払振替承認 | AL23: ● | AX23: FO | BF23: 一般仕訳帳 | BN23: 費用/前払の振替処理
R24: 3 | S24: 自動転記バッチ | AV24: ● | AX24: FO | BF24: 自動転記バッチ
B25: ３.経費精算 | J25: １.個別精算 | R25: 1 | S25: 精算内容入力 | AR25: ● | AX25: 楽楽精算 | BF25: ー
R26: 2 | S26: 従業員別債務残高確認 | AL26: ● | AX26: FO | BF26: 試算表
B27: ４.支払予定修正・保留 | J27: １.支払予定修正 | R27: 1 | S27: 支払基準日の変更 | AL27: ● | AX27: FO | BF27: 仕入先トランザクション （トランザクションの決済）
J28: ２.支払保留 | R28: 1 | S28: 支払保留 | AL28: ● | AX28: FO | BF28: 仕入先トランザクション
J29: ３.支払保留解除 | R29: 1 | S29: 支払保留解除 | AL29: ● | AX29: FO | BF29: 仕入先トランザクション
B30: ５.支払前 | J30: １.相殺処理（滋賀ホスト） | R30: 1 | S30: 預かり売掛金振替処理（滋賀ホスト） | AT30: ● | AX30: SEJホスト | BF30: ー
R31: 2 | S31: 相殺依頼（滋賀ホスト） | AT31: ● | AX31: ー | BF31: ー
R32: 3 | S32: 相殺依頼内容確認（滋賀ホスト） | AL32: ● | AX32: ー | BF32: ー
R33: 4 | S33: 買掛金残高確認（滋賀ホスト） | AL33: ● | AX33: FO | BF33: 仕入先残高リスト
R34: 5 | S34: 預かり売掛金相殺登録（滋賀ホスト） | AL34: ● | AX34: FO | BF34: 仕入先支払仕訳帳
R35: 6 | S35: 預かり売掛金相殺承認（滋賀ホスト） | AL35: ● | AX35: FO | BF35: 仕入先支払仕訳帳 | BN35: 買掛金/預かり売掛金
R36: 7 | S36: 転記 | AL36: ● | AX36: FO | BF36: 仕入先支払仕訳帳
J37: ２.支払前 | R37: 1 | S37: 預かり売掛金振替処理（SEJ） | AT37: ● | AX37: SEJホスト | BF37: ー
R38: 2 | S38: 相殺依頼（SEJ） | AT38: ● | AX38: ー | BF38: ー
R39: 3 | S39: 相殺依頼内容確認（SEJ） | AL39: ● | AX39: ー | BF39: ー
R40: 4 | S40: 預かり売掛金相殺登録（SEJ） | AL40: ● | AX40: FO | BF40: 仕入先支払仕訳帳
R41: 5 | S41: 預かり売掛金相殺承認（SEJ） | AL41: ● | AX41: FO | BF41: 仕入先支払仕訳帳 | BN41: 買掛金/預かり売掛金
R42: 6 | S42: 転記 | AL42: ● | AX42: FO | BF42: 仕入先支払仕訳帳
R43: 7 | S43: 相殺完了連絡受領（SEJ） | AT43: ● | AX43: ー
R44: 8 | S44: 未収入金相殺処理 | AL44: ● | AX44: FO | BF44: 顧客と仕入先の残高の相殺決済 | BN44: 買掛金/未収入金
R45: 9 | S45: 支払方法確定処理 | AL45: ● | AX45: FO | BF45: 支払方法・支払サイト更新バッチ
R46: 10 | S46: 支払予定データ確認 | AL46: ● | AX46: FO | BF46: 仕入先未処理トランザクションレポート、 仕入先請求書トランザクションレポート、 仕入先残高リスト
R47: 11 | S47: 支払合計表/明細表確認・出力 | AL47: ● | AX47: FO | BF47: 支払合計表、 仕入先トランザクション一覧、 債務残高明細
B48: ６.支払 | J48: １.支払 | R48: 1 | S48: 債務データの紐づけ | AL48: ● | AX48: FO | BF48: 仕入先支払仕訳帳
B49: （銀行振込・海外送金・小切手） | J49: （銀行振込、海外送金、小切手） | R49: 2 | S49: 支払承認申請 | AL49: ● | AX49: FO | BF49: 仕入先支払仕訳帳 WF
R50: 3 | S50: 支払の承認/変更依頼 | AL50: ● | AX50: FO | BF50: 仕入先支払仕訳帳 WF | BN50: （責任者）
R51: 4 | S51: 不備修正 | AL51: ● | AX51: 各発生元システム | BF51: ー
R52: 5 | S52: EBデータ出力 | AL52: ● | AX52: FO | BF52: 仕入先支払仕訳帳
R53: 6 | S53: EBデータ取り込み | AL53: ● | AX53: 銀行システム | BF53: ー
R54: 7 | S54: 承認 | AL54: ● | AX54: 銀行システム | BF54: ー | BN54: （責任者）
R55: 8 | S55: 支払データ転記 | AL55: ● | AX55: FO | BF55: 仕入先支払仕訳帳
R56: 9 | S56: 帳票（支払案内書）出力 | AL56: ● | AX56: FO | BF56: 支払案内書
R57: 10 | S57: 決済内容の確認 | AL57: ● | AX57: FO | BF57: 債務残高明細
J58: 2．為替差損益の調整仕訳登録 | R58: 1 | S58: 調整仕訳登録 | AL58: ● | AX58: FO | BF58: 一般仕訳帳
R59: 2 | S59: 承認 | AL59: ● | AX59: FO | BF59: 一般仕訳帳
R60: 3 | S60: 自動転記バッチ | AV60: ● | AX60: FO | BF60: 自動転記バッチ
B61: ７.電子記録債務計上・決済 | J61: １.電子記録債務計上 | R61: 1 | S61: 債務データの紐づけ | AL61: ● | AX61: FO | BF61: 支払手形仕訳帳の振出
R62: 2 | S62: 電子記録債務計上承認申請 | AL62: ● | AX62: FO | BF62: 支払手形仕訳帳の振出 WF
R63: 3 | S63: 電子記録債務計上承認/変更依頼 | AL63: ● | AX63: FO | BF63: 支払手形仕訳帳の振出 WF | BN63: （責任者）
R64: 4 | S64: 不備修正 | AL64: ● | AX64: 各発生元システム | BF64: ー
R65: 5 | S65: EBデータ出力 | AL65: ● | AX65: FO | BF65: 支払手形仕訳帳の振出
R66: 6 | S66: EBデータ取り込み | AL66: ● | AX66: 三菱東京銀行 | BF66: ー | BN66: 電債
R67: 6 | S67: EBデータ取り込み | AL67: ● | AX67: 三井住友銀行 | BF67: ー | BN67: でんさい
R68: 7 | S68: 承認 | AL68: ● | AX68: 三菱東京銀行 | BF68: ー | BN68: （責任者）
R69: 7 | S69: 承認 | AL69: ● | AX69: 三井住友銀行 | BF69: ー | BN69: （責任者）
R70: 8 | S70: 電子記録債務計上 | AL70: ● | AX70: FO | BF70: 支払手形仕訳帳の振出
R71: 9 | S71: 電子記録債務の確認 | AL71: ● | AX71: FO | BF71: 電子記録債務管理一覧 支払手形仕訳帳
J72: ２.電子記録債務決済 | R72: 1 | S72: 電子記録債務決済データ抽出 | AL72: ● | AX72: FO | BF72: 支払手形仕訳帳の決済
R73: 2 | S73: 電子記録債務決済承認申請 | AL73: ● | AX73: FO | BF73: 支払手形仕訳帳の決済 WF
R74: 3 | S74: 電子記録債務決済承認/変更依頼 | AL74: ● | AX74: FO | BF74: 支払手形仕訳帳の決済 WF | BN74: （責任者）
R75: 4 | S75: 不備修正 | AL75: ● | AX75: FO | BF75: 支払手形仕訳帳の決済
R76: 5 | S76: 電子記録債務決済計上 | AL76: ● | AX76: FO | BF76: 支払手形仕訳帳の決済
R77: 6 | S77: 電子記録債務の決済確認 | AL77: ● | AX77: FO | BF77: 電子記録債務管理一覧 支払手形仕訳帳
R78: 7 | S78: 決済内容の確認 | AL78: ● | AX78: FO | BF78: 債務残高明細
R79: 8 | S79: 支払金額の確認 | AL79: ● | AX79: FO | BF79: 支払集計表
B80: ８.口座引落 | J80: １.契約内容登録 | R80: 1 | S80: 契約内容登録 | AL80: ● | AX80: FO | BF80: 口座引落契約台帳 | BN80: Excel台帳をインポートし、登録する
J81: ２.口座引落 | R81: 1 | S81: 結果確認 | AL81: ● | AX81: FO | BF81: 引落結果出力 | BN81: 費用/預金（口座引き落とし結果を確認）
R82: 2 | S82: 口座引落契約台帳修正 | AL82: ● | AX82: FO | BF82: 口座引落契約台帳
R83: 3 | S83: 引落データ対象外のステータス更新 | AL83: ● | AX83: FO | BF83: 引落結果出力
R84: 4 | S84: マッチング再実行 | AL84: ● | AX84: FO | BF84: 引落結果出力
B85: A．銀行口座マスタ登録 | J85: １.銀行口座登録 | R85: 1 | S85: 主勘定登録 | AV85: ● | AX85: FO | BF85: 主勘定
R86: 2 | S86: 銀行グループ登録 | AV86: ● | AX86: FO | BF86: 銀行グループ
R87: 3 | S87: 銀行口座登録 | AV87: ● | AX87: FO | BF87: 銀行口座
B88: B．相殺契約登録 | J88: １.契約内容登録 | R88: 1 | S88: 相殺決済契約登録 | AL88: ● | AX88: FO | BF88: 相殺決済契約マスタ
R89: 2 | S89: 有効化 | AL89: ● | AX89: FO | BF89: 相殺決済契約マスタ
B90: C．仕入先マスタ・ | J90: １.仕入先マスタ・ | R90: 1 | S90: 銀行グループの登録 | AV90: ● | AX90: FO | BF90: 銀行グループ
B91: 仕入先の銀行口座 | J91: 仕入先の銀行口座登録 | R91: 2 | S91: 仕入先マスタ・仕入先の銀行口座登録 | AL91: ● | AX91: JUST D.B. SEJホスト | BF91: ー
R92: 3 | S92: 仕入先マスタの更新 | AL92: ● | AX92: FO | BF92: 仕入先
R93: 4 | S93: 仕入先マスタの住所更新 | AL93: ● | AX93: FO | BF93: 仕入先
R94: 5 | S94: 仕入先の銀行口座更新 | AL94: ● | AX94: FO | BF94: 仕入先の銀行口座
R95: 6 | S95: 銀行グループの変更 | AL95: ● | AX95: FO | BF95: 仕入先の銀行口座

Sheet 5.固定資産・リース
A1: システム名 | F1: =変更履歴!F1 -> 会計システム刷新プロジェクト（LIBRA） | V1: タイトル | AH1: 日付 | AO1: 更新者
A2: 文書名 | F2: =変更履歴!F2 -> To-Be業務一覧 | V2: =MID(CELL("filename",$A$1),FIND("]",CELL("filename",$A$1))+1,31) -> #VALUE! | AH2: 作成 | AJ2: =変更履歴!AT2 -> 45420 | AO2: =変更履歴!BA2 -> JBS井田
AH3: 更新 | AJ3: =変更履歴!AT3 -> 45911 | AO3: =変更履歴!BA3 -> JBS加藤
A6: 業務一覧
B8: タイトル | J8: パターン | R8: No | S8: 業務概要 | AP8: システム | AX8: 機能名 | BF8: 備考
AF9: 各部署 | AH9: 決算G | AJ9: 事務管理G | AL9: 社員サポートG | AN9: ITDX
B10: 日常業務
B11: 固定資産
B12: １.固定資産管理 | J12: 1-1．固定資産取得(通常取得：購入と資産計上が同時期に実施される場合) | R12: 1 | S12: 財務分析コード値の更新(指図番号の登録) | AF12: ● | AH12: ● | AJ12: ● | AP12: FO | AX12: 指図（マスタ） | BF12: FOで登録された指図番号が翌日以降に各外部システムへ連携
R13: 2 | S13: 決済勘定へ振替 | AF13: ● | AH13: ● | AJ13: ● | AP13: FO | AX13: 一般仕訳帳 | BF13: 楽楽精算から会計伝票連携される。 仕訳例：建物決済勘定/未払金（設備）
R14: 3 | S14: 固定資産登録 | AF14: ● | AH14: ● | AJ14: ● | AP14: FO | AX14: 固定資産マスタ
R15: 4 | S15: 取得提案 | AF15: ● | AH15: ● | AJ15: ● | AP15: FO | AX15: 取得提案
R16: 5 | S16: 取得承認申請 | AF16: ● | AH16: ● | AJ16: ● | AP16: FO | AX16: 固定資産仕訳帳
R17: 6 | S17: 取得の承認/変更依頼 | AF17: ● | AH17: ● | AJ17: ● | AP17: FO | AX17: 固定資産仕訳帳
R18: 7 | S18: 不備修正 | AF18: ● | AH18: ● | AJ18: ● | AP18: FO | AX18: 固定資産仕訳帳
R19: 8 | S19: 自動転記バッチ | AF19: ● | AH19: ● | AJ19: ● | AP19: FO | AX19: 固定資産仕訳帳
R20: 9 | S20: 取得内容確認 | AH20: ● | AJ20: ● | AP20: FO | AX20: 取得された固定資産
R21: 10 | S21: 仕訳帳全体の取消 | AF21: ● | AP21: FO | AX21: 固定資産仕訳帳
J22: 1-2．固定資産取得(建設仮勘定対応：購入と資産計上の時期にずれがある場合) | R22: 1 | S22: 財務分析コード値の更新(指図番号の登録) | AF22: ● | AH22: ● | AJ22: ● | AP22: FO | AX22: 指図（マスタ）
R23: 2 | S23: 建設仮勘定仕訳入力(毎月) | AF23: ● | AH23: ● | AJ23: ● | AP23: FO | AX23: 一般仕訳帳 | BF23: 楽楽精算から会計伝票連携される。 仕訳例：建物決済勘定/未払金（設備）
R24: 3 | S24: 振替金額の認識 | AF24: ● | AH24: ● | AJ24: ● | AP24: FO | AX24: 試算表
R25: 4 | S25: 決済勘定へ振替 | AF25: ● | AH25: ● | AJ25: ● | AP25: FO | AX25: 一般仕訳帳 | BF25: 楽楽精算から会計伝票連携される。仕訳例：建物決済勘定/建設仮勘定
R26: 5 | S26: 固定資産登録 | AF26: ● | AH26: ● | AJ26: ● | AP26: FO | AX26: 固定資産マスタ
R27: 6 | S27: 取得提案 | AF27: ● | AH27: ● | AJ27: ● | AP27: FO | AX27: 取得提案
R28: 7 | S28: 取得承認申請 | AF28: ● | AH28: ● | AJ28: ● | AP28: FO | AX28: 固定資産仕訳帳
R29: 8 | S29: 取得の承認/変更依頼 | AF29: ● | AH29: ● | AJ29: ● | AP29: FO | AX29: 固定資産仕訳帳
R30: 9 | S30: 不備修正 | AF30: ● | AH30: ● | AJ30: ● | AP30: FO | AX30: 固定資産仕訳帳
R31: 10 | S31: 自動転記バッチ | AF31: ● | AH31: ● | AJ31: ● | AP31: FO | AX31: 固定資産仕訳帳
R32: 11 | S32: 取得内容確認 | AH32: ● | AJ32: ● | AP32: FO | AX32: 取得された固定資産
R33: 12 | S33: 仕訳帳全体の取消 | AF33: ● | AP33: FO | AX33: 固定資産仕訳帳
J34: 2．固定資産現物管理（減価償却） | R34: 1 | S34: 償却提案の実行 | AH34: ● | AJ34: ● | AP34: FO | AX34: 償却提案
R35: 2 | S35: 転記処理 | AH35: ● | AJ35: ● | AP35: FO | AX35: 固定資産仕訳帳
J36: 3．固定資産現物管理（移動） | R36: 1 | S36: 移動伝票の発行 | AF36: ● | AH36: ● | AJ36: ● | AP36: ー | AX36: ー | BF36: それぞれの資産の管理部署が移動処理を行う。
R37: 2 | S37: 固定資産移動処理 | AF37: ● | AH37: ● | AJ37: ● | AP37: FO | AX37: 固定資産移動 | BF37: それぞれの資産の管理部署が売却・処分処理を行う。
J38: 4．固定資産現物管理（売却・処分） | R38: 1 | S38: 売却・処分伝票の発行 | AF38: ● | AH38: ● | AJ38: ● | AP38: ー | AX38: ー
R39: 2 | S39: 売却・処分提案の実行 | AF39: ● | AH39: ● | AJ39: ● | AP39: FO | AX39: 固定資産仕訳帳
R40: 3 | S40: 売却・処分承認申請 | AF40: ● | AH40: ● | AJ40: ● | AP40: FO | AX40: 固定資産仕訳帳
R41: 4 | S41: 売却・処分の承認/変更依頼 | AF41: ● | AH41: ● | AJ41: ● | AP41: FO | AX41: 固定資産仕訳帳
R42: 5 | S42: 不備修正 | AF42: ● | AH42: ● | AJ42: ● | AP42: FO | AX42: 固定資産仕訳帳
R43: 6 | S43: 自動転記バッチ | AF43: ● | AH43: ● | AJ43: ● | AP43: FO | AX43: 固定資産仕訳帳
R44: 7 | S44: 未収入金への振替 | AF44: ● | AH44: ● | AJ44: ● | AP44: FO | AX44: 一般仕訳帳 | BF44: ※SLJのみ処理発生予定 未収入金/売掛金
R45: 8 | S45: 振替承認申請 | AF45: ● | AH45: ● | AJ45: ● | AP45: FO | AX45: 一般仕訳帳
R46: 9 | S46: 振替の承認/変更依頼 | AF46: ● | AH46: ● | AJ46: ● | AP46: FO | AX46: 一般仕訳帳
R47: 10 | S47: 不備修正 | AF47: ● | AH47: ● | AJ47: ● | AP47: FO | AX47: 一般仕訳帳
R48: 11 | S48: 自動転記バッチ | AH48: ● | AJ48: ● | AP48: FO | AX48: 固定資産の処分
R49: 12 | S49: 売却・処分内容確認 | AH49: ● | AJ49: ● | AP49: FO | AX49: 固定資産仕訳帳
R50: 13 | S50: 仕訳帳全体の取消 | AF50: ● | AP50: FO | AX50: 固定資産仕訳帳 一般仕訳帳
R51: 14 | S51: ネッティング仕訳入力 | AH51: ● | AJ51: ● | AP51: FO | AX51: 一般仕訳帳 | BF51: ※売却益になる場合のみ
R52: 15 | S52: ネッティング仕訳承認申請 | AH52: ● | AJ52: ● | AP52: FO | AX52: 一般仕訳帳 | BF52: ※売却益になる場合のみ
R53: 16 | S53: ネッティング仕訳承認/変更依頼 | AH53: ● | AJ53: ● | AP53: FO | AX53: 一般仕訳帳 | BF53: ※売却益になる場合のみ
R54: 17 | S54: 不備修正 | AH54: ● | AJ54: ● | AP54: FO | AX54: 一般仕訳帳
R55: 18 | S55: 自動転記バッチ | AH55: ● | AJ55: ● | AP55: FO | AX55: 一般仕訳帳
R56: 19 | S56: 消費税仕訳入力 | AH56: ● | AJ56: ● | AP56: FO | AX56: 一般仕訳帳
R57: 20 | S57: 消費税仕訳承認申請 | AH57: ● | AJ57: ● | AP57: FO | AX57: 一般仕訳帳
R58: 21 | S58: 消費税仕訳承認/変更依頼 | AH58: ● | AJ58: ● | AP58: FO | AX58: 一般仕訳帳
R59: 22 | S59: 不備修正 | AH59: ● | AJ59: ● | AP59: FO | AX59: 一般仕訳帳
R60: 23 | S60: 自動転記バッチ | AH60: ● | AJ60: ● | AP60: FO | AX60: 一般仕訳帳
J61: 5．固定資産現物管理（減損処理） | R61: 1 | S61: 減損インジケータの更新 | AH61: ● | AJ61: ● | AP61: ー | AX61: ー
R62: 2 | S62: 減損認識テスト | AH62: ● | AJ62: ● | AP62: FO | AX62: 固定資産インジゲータ
R63: 3 | S63: 減損対象の識別 | AH63: ● | AJ63: ● | AP63: FO | AX63: 減損認識テスト
R64: 4 | S64: 減損提案の実行 | AH64: ● | AJ64: ● | AP64: FO | AX64: 減損認識テスト
R65: 5 | S65: 減損承認申請 | AH65: ● | AJ65: ● | AP65: FO | AX65: 固定資産仕訳帳
R66: 6 | S66: 減損の承認/変更依頼 | AH66: ● | AJ66: ● | AP66: FO | AX66: 固定資産仕訳帳
R67: 7 | S67: 不備修正 | AH67: ● | AJ67: ● | AP67: FO | AX67: 固定資産仕訳帳
R68: 8 | S68: 自動転記バッチ | AH68: ● | AJ68: ● | AP68: FO | AX68: 固定資産仕訳帳
J69: 6．固定資産現物管理（分割処理） | R69: 1 | S69: 固定資産登録 | AF69: ● | AH69: ● | AJ69: ● | AP69: FO | AX69: 固定資産インジゲータ
R70: 2 | S70: 分割処理 | AF70: ● | AH70: ● | AJ70: ● | AP70: FO | AX70: 固定資産マスタ
R71: 3 | S71: 分割承認申請 | AF71: ● | AH71: ● | AJ71: ● | AP71: FO | AX71: 固定資産
R72: 4 | S72: 分割の承認/変更依頼 | AF72: ● | AH72: ● | AJ72: ● | AP72: FO | AX72: 固定資産仕訳帳
R73: 5 | S73: 不備修正 | AF73: ● | AH73: ● | AJ73: ● | AP73: FO | AX73: 固定資産仕訳帳
R74: 6 | S74: 自動転記バッチ | AF74: ● | AH74: ● | AJ74: ● | AP74: FO | AX74: 固定資産仕訳帳
J75: 7．固定資産現物管理（圧縮記帳処理ー直接減額方式） | R75: 1 | S75: 圧縮記帳の文書を登録 | AH75: ● | AJ75: ● | AP75: FO | AX75: 圧縮記帳の文書
R76: 2 | S76: 帳簿への文書登録 | AH76: ● | AJ76: ● | AP76: FO | AX76: 固定資産
R77: 3 | S77: 圧縮記帳提案の実行 | AH77: ● | AJ77: ● | AP77: FO | AX77: 固定資産仕訳帳
R78: 4 | S78: 圧縮記帳承認申請 | AH78: ● | AJ78: ● | AP78: FO | AX78: 固定資産仕訳帳
R79: 5 | S79: 圧縮記帳の承認/変更依頼 | AH79: ● | AJ79: ● | AP79: FO | AX79: 固定資産仕訳帳
R80: 6 | S80: 不備修正 | AH80: ● | AJ80: ● | AP80: FO | AX80: 固定資産仕訳帳
R81: 7 | S81: 自動転記バッチ | AH81: ● | AJ81: ● | AP81: FO | AX81: 固定資産仕訳帳
J82: ８．固定資産台帳（随時） | R82: 1 | S82: 固定資産台帳 | AF82: ● | AH82: ● | AJ82: ● | AP82: FO | AX82: 固定資産台帳
J83: 9．償却シミュレーション一覧（適宜） | R83: 1 | S83: 償却シミュレーション一覧 | AH83: ● | AJ83: ● | AP83: FO | AX83: 償却シミュレーション一覧
J84: 10．月次レポート（増減台帳作成） | R84: 1 | S84: 固定資産の取得 | AH84: ● | AJ84: ● | AP84: FO | AX84: 取得された固定資産
R85: 2 | S85: 固定資産の移動 | AH85: ● | AJ85: ● | AP85: FO | AX85: 固定資産の移動
R86: 3 | S86: 固定資産の処分 | AH86: ● | AJ86: ● | AP86: FO | AX86: 固定資産の処分
R87: 4 | S87: 固定資産トランザクション | AH87: ● | AJ87: ● | AP87: FO | AX87: 固定資産トランザクション
R88: 5 | S88: 固定資産トランザクション | AH88: ● | AJ88: ● | AP88: FO | AX88: 試算表・伝票トランザクション
J89: 11．年次レポート（償却資産申告書作成） | R89: 1 | S89: 償却資産申告書（償却資産課税台帳） | AH89: ● | AJ89: ● | AP89: FO | AX89: 申告 26: 償却資産税の元帳レポート
R90: 2 | S90: 種類別明細書（増加資産・全資産用） | AH90: ● | AJ90: ● | AP90: FO | AX90: 申告 26 - 1: 全資産および増加資産のタイプごとの詳細レポート
R91: 3 | S91: 種類別明細書（減少資産用） | AH91: ● | AJ91: ● | AP91: FO | AX91: 申告 26 - 2: 減少資産のタイプごとの詳細レポート
R92: 4 | S92: 固定資産移動一覧 | AH92: ● | AJ92: ● | AP92: FO | AX92: 固定資産移動一覧
J93: 12．年次レポート | R93: 1 | S93: 償却資産税情報出力 | AH93: ● | AJ93: ● | AP93: FO | AX93: 償却資産税情報出力 情報出力
R94: 2 | S94: eLTAX | AH94: ● | AJ94: ● | AP94: ー | AX94: ー
B95: 資産リース
B96: ２.資産リース管理 | J96: １.資産リース取得 | R96: 1 | S96: 自動引落申請書発行 | AF96: ● | AP96: ー | AX96: ー
R97: 2 | S97: 自動引落申請書の受領 | AJ97: ● | AL97: ● | AP97: ー | AX97: ー
R98: 3 | S98: リース資産登録 | AJ98: ● | AL98: ● | AP98: FO | AX98: リースの概要マスタ
R99: 4 | S99: 固定資産登録 | AJ99: ● | AP99: FO | AX99: 固定資産マスタ
R100: 4 | S100: リースに紐づく帳簿の作成 | AJ100: ● | AL100: ● | AP100: FO | AX100: スケジュールの作成バッチ
R101: 5 | S101: 不要な帳簿の削除 | AJ101: ● | AL101: ● | AP101: FO | AX101: 帳簿の詳細
R102: 6 | S102: 消費税額の登録 | AJ102: ● | AP102: FO | AX102: 帳簿の詳細
R103: 7 | S103: 支払スケジュール確定処理 | AJ103: ● | AL103: ● | AP103: FO | AX103: 確認バッチ
...

Sheet 6.予算
A1: システム名 | F1: =変更履歴!F1 -> 会計システム刷新プロジェクト（LIBRA） | V1: タイトル | AL1: 日付 | AS1: 更新者
A2: 文書名 | F2: =変更履歴!F2 -> To-Be業務一覧 | V2: =MID(CELL("filename",$A$1),FIND("]",CELL("filename",$A$1))+1,31) -> #VALUE! | AL2: 作成 | AN2: =変更履歴!AT2 -> 45420 | AS2: =変更履歴!BA2 -> JBS井田
AL3: 更新 | AN3: =変更履歴!AT3 -> 45911 | AS3: =変更履歴!BA3 -> JBS加藤
A6: 業務一覧
B8: タイトル | J8: パターン | R8: No | S8: 業務概要 | AF8: 担当 | AN8: システム | AV8: 機能名 | BD8: 備考
AF9: チャネル/各部署 | AH9: 各部署 | AJ9: 経営計画G | AL9: 事業計画G
B10: 日常業務
B11: 予算
B12: １.SSJ予算作成 | J12: １.毎期事前登録作業 | R12: 1 | S12: 予算サイクル登録 | AL12: ● | AN12: FO | AV12: 予算サイクル
R13: 2 | S13: 予算計画プロセス登録 | AL13: ● | AN13: FO | AV13: 予算計画プロセス
R14: 3 | S14: 予算計画登録 | AL14: ● | AN14: FO | AV14: 予算計画
J15: ２.予算作成 | R15: 1 | S15: 経営計画策定 | AL15: ● | AN15: ー | AV15: ー | BD15: （責任者）
R16: 2 | S16: 予算編成方針策定 | AJ16: ● | AN16: ー | AV16: ー | BD16: （責任者）
R17: 3 | S17: 各チャネル予算 作成依頼 | AJ17: ● | AN17: ー | AV17: ー
R18: 4 | S18: 各チャネル売上/原価予算作成 | AF18: ● | AN18: ー | AV18: ー | BD18: 各チャネル担当者はExcelフォーマットに予算を記入して予算編成担当者へ
R19: 5 | S19: 売上/原価予算登録 | AJ19: ● | AN19: mcframe 新業務くん | AV19: ー | BD19: 経営計画Gで集計して、新業務くん、mcframeへ登録
R20: 6 | S20: 新業務くん/Mcframe予算データ出力 | AJ20: ● | AN20: mcframe 新業務くん | AV20: ー
R21: 7 | S21: 売上・原価予算計画取込 | AJ21: ● | AN21: FO | AV21: 売上・原価予算計画取込
R22: 8 | S22: 各部課別経費予算作成依頼 | AJ22: ● | AN22: ー | AV22: ー
R23: 9 | S23: 各部課別経費予算作成 | AF23: ● | AN23: ー | AV23: ー
R24: 10 | S24: 部門経費予算計画取込 | AL24: ● | AN24: FO | AV24: 部門経費予算計画取込
R25: 11 | S25: MR予算帳票の予算計画名変更 | AL25: ● | AN25: FO | AV25: 財務諸表(MR)
R26: 12 | S26: 配賦前予算計画金額確認 | AL26: ● | AN26: FO | AV26: 財務諸表(MR)
R27: 13 | S27: 予算計画承認 | AL27: ● | AN27: FO | AV27: 予算計画
R28: 14 | S28: 予算計画登録BI連携 | AJ28: ● | AN28: FO | AV28: 予算計画
R29: 15 | S29: 予算配賦 | AJ29: ● | AN29: J-BASまたは Azure Synapse Analytics | AV29: ー
R30: 16 | S30: 配賦後予算金額確認 | AJ30: ● | AN30: Power BI | AV30: Power BI
J31: ３.予実確認 | R31: 1 | S31: 予実確認 | AF31: ● | AJ31: ● | AL31: ● | AN31: Power BI | AV31: Power BI
B32: ２.SEJ予算作成 | J32: １.毎期事前登録作業 | R32: 1 | S32: 予算サイクル登録 | AL32: ● | AN32: FO | AV32: 予算サイクル
R33: 2 | S33: 予算計画プロセス登録 | AL33: ● | AN33: FO | AV33: 予算計画プロセス
R34: 3 | S34: 予算計画登録 | AL34: ● | AN34: FO | AV34: 予算計画
J35: ２.予算作成 | R35: 1 | S35: 経営計画策定 | AL35: ● | AN35: ー | AV35: ー | BD35: （責任者）
R36: 2 | S36: 予算編成方針策定 | AL36: ● | AN36: ー | AV36: ー | BD36: （責任者）
R37: 3 | S37: 各部署予算作成依頼 | AL37: ● | AN37: ー | AV37: ー
R38: 4 | S38: 各部署予算作成 | AH38: ● | AN38: ー | AV38: ー
R39: 5 | S39: 売上/販売費/経費AS400登録 | AL39: ● | AN39: ー | AV39: ー | BD39: 各部署担当者はEXCELフォーマットに予算を記入して予算編成担当者へ
R40: 6 | S40: 生産部門予算登録 | AH40: ● | AN40: AS/400 | AV40: ー
R41: 7 | S41: AS400予算データ出力 | AL41: ● | AN41: AS/400 | AV41: ー
R42: 8 | S42: 売上・原価予算計画取込 | AL42: ● | AN42: FO | AV42: 売上・原価予算計画取込
R43: 9 | S43: 一般経費予算作成 | AH43: ● | AN43: AS/400 | AV43: ー | BD43: 生産部のみ生産部でAS/400へ登録
R44: 10 | S44: 部門経費予算計画取込 | AL44: ● | AN44: FO | AV44: 部門経費予算計画取込
R45: 11 | S45: MR予算帳票の予算計画名変更 | AL45: ● | AN45: FO | AV45: 財務諸表(MR)
R46: 12 | S46: 配賦前予算計画PL確認 | AL46: ● | AN46: FO | AV46: 財務諸表(MR)
R47: 13 | S47: 予算計画承認 | AL47: ● | AN47: FO | AV47: 予算計画
R48: 14 | S48: 予算計画BI連携 | AJ48: ● | AN48: FO | AV48: 予算計画
R49: 15 | S49: 予算配賦 | AJ49: ● | AN49: J-BASまたは Azure Synapse Analytics | AV49: ー
R50: 16 | S50: 配賦後予算金額確認 | AL50: ● | AN50: Power BI | AV50: ー
J51: ３.予実確認 | R51: 1 | S51: 予実確認 | AH51: ● | AJ51: ● | AL51: ● | AN51: Power BI | AV51: ー

Sheet 7.Branch2
A1: システム名 | F1: =[2]変更履歴!F1 -> 会計システム刷新プロジェクト（LIBRA）Branch2 | V1: タイトル | AL1: 日付 | AS1: 更新者
A2: 文書名 | F2: =[2]変更履歴!F2 -> To-Be業務一覧 | V2: =MID(CELL("filename",$A$1),FIND("]",CELL("filename",$A$1))+1,31) -> #VALUE! | AL2: 作成 | AN2: =[2]変更履歴!AT2 -> 45650 | AS2: =[2]変更履歴!BA2 -> JBS北井
AL3: 更新 | AN3: =[2]変更履歴!AT3 -> 45650 | AS3: =[2]変更履歴!BA3 -> JBS北井
A6: 業務一覧
B8: タイトル | J8: パターン | R8: No | S8: 業務概要 | AF8: 担当 | AJ8: システム | AR8: 機能名 | AZ8: 備考
AF9: ITDX | AH9: 他
B10: 日常業務
B11: 1.利益センタ・原価センタマスタ登録
B12: 1.利益センタ・原価センタ | J12: １．利益センタマスタ登録 | R12: 1 | S12: 利益センタマスタの登録（MDM） | AF12: ● | AJ12: MDM | AR12: ー
B13: マスタ登録 | R13: 2 | S13: 利益センタマスタの登録（FO） | AF13: ● | AJ13: FO | AR13: 作業単位
R14: 3 | S14: 機能領域・事業領域の登録 | AF14: ● | AJ14: FO | AR14: 財務分析コード（分析コード値）
R15: 4 | S15: 使用法人の設定 | AF15: ● | AJ15: FO | AR15: 財務分析コード（分析コード値）
R16: 5 | S16: 関連分析コードの設定 | AF16: ● | AJ16: FO | AR16: 財務分析コード（派生分析コード）
J17: ２．原価センタマスタ登録 | R17: 1 | S17: 原価センタマスタの登録 | AF17: ● | AJ17: MDM | AR17: ー
R18: 2 | S18: 原価センタマスタの取込 | AF18: ● | AJ18: FO | AR18: 原価センタマスタ取込
B19: 2.品目マスタ取込
B20: 2.品目マスタ取込 | J20: １．品目マスタ登録 | R20: 1 | S20: 品目マスタの登録 | AF20: ● | AJ20: MDM | AR20: ー
R21: 2 | S21: 単位マスタの登録 | AF21: ● | AJ21: FO | AR21: 単位マスタ
J22: ２．品目マスタ取込 | R22: 1 | S22: 品目マスタの取込 | AF22: ● | AJ22: FO | AR22: 品目マスタ取込
B23: 3.販売実績データ連携
B24: 3.販売実績データ連携 | J24: １．販売実績データ取込 | R24: 1 | S24: 売上対象伝票の確認 | AF24: ● | AJ24: mcframe、SEJホスト | AR24: ー | AZ24: SSJ:mcframe,SEJ:AS400 FO（）
R25: 2 | S25: 売上の計上 | AF25: ● | AJ25: mcframe、SEJホスト | AR25: ー | AZ25: SSJ:mcframe,SEJ:AS400 FO（）
R26: 3 | S26: 販売実績データの取込 | AF26: ● | AJ26: FO | AR26: 販売実績取込
J27: ２．販売実績データ連携 | R27: 1 | S27: 販売実績データの連携 | AF27: ● | AJ27: FO | AR27: 販売実績連携
