Workbook
Name カレンダータイプ: [2]マスタ!$I$27:$I$29
Name ステータス: [2]マスタ!$C$27:$C$29
Name チェックボックス: [2]マスタ!$B$10:$B$11
Name はいいいえ: [2]マスタ!$B$5:$B$6
Name レポートタイプ: [2]マスタ!$K$6:$K$8
Name 為替換算タイプ: [2]マスタ!$U$5:$U$8
Name 演算子: [2]マスタ!$R$5:$R$14
Name 開始・終了: [2]マスタ!$C$237:$C$238
Name 勘定タイプ: [2]マスタ!$E$27:$E$32
Name 丸め方法: [2]マスタ!$Y$5:$Y$7
Name 既定の説明: [2]マスタ!$H$237:$H$351
Name 期間タイプ: [2]マスタ!$B$237:$B$244
Name 検証: [2]マスタ!$O$6:$O$9
Name 作成日: DATE(2000,3,21)
Name 仕訳帳タイプ: [2]マスタ!$B$27:$B$72
Name 借方貸方: [2]マスタ!$L$6:$L$7
Name 主勘定タイプ: [2]マスタ!$J$6:$J$15
Name 主勘定タイプ2: [2]マスタ!$AB$5:$AB$11
Name 場所: [2]マスタ!$S$5
Name 新しい伝票: [2]マスタ!$D$27:$D$29
Name 性別1: [2]マスタ!$Z$5:$Z$6
Name 精算表に残高を転送するフィールド: [2]マスタ!$M$6:$M$8
Name 選択可能値: [2]マスタ!$C$37:$C$43
Name 単位: [2]マスタ!$W$5:$W$7
Name 調整単位: [2]マスタ!$D$237:$D$240
Name 転記タイプ: [2]マスタ!$F$237:$F$389
Name 分析コード形式タイプ: [2]マスタ!$BA$5:$BA$8
Name 領域: [2]マスタ!$F$99:$F$164:'[2]マスタ'!$F$120

Sheet 表紙
B3: サンスター株式会社 御中
B10: 会計システム刷新プロジェクト（LIBRA）
B14: FOパラメータ定義書-SEJ_99.マスタ
B22: 第1.0版
B24: 45546
B26: 日本ビジネスシステムズ株式会社
F29: 作成者 | O29: JBS承認者
F30: 45546 | N30: ＜YYYY/MM/DD＞
F31: JBS石岡 | N31: 氏名

Sheet パラメータ設定一覧
A1: パラメータ設定一覧
B3: No | C3: 該当モジュール | D3: 法人共通/個別 | E3: 設定項目 | F3: GC設定担当者 | G3: GC設定完了日 | H3: 説明 | I3: パス
B4: =ROW()-3 -> 1 | C4: 組織管理 | D4: 共通 | E4: 作業単位 | H4: 作業単位の定義となる。 ※管理対象が多い場合移行対象の想定 | I4: 組織管理＞組織＞作業単位 Organization administration > Organizations > Operating units
B5: =ROW()-3 -> 2 | C5: 組織管理 | D5: 共通 | E5: 住所の設定 | F5: JBS石岡 | G5: 45548 | H5: 住所の定義となる。 ※市区町村や郵便番号については移行対象の想定（郵便番号インポート） ※住所、家のグループ、土地区画、アパートのグループはロシアのみで使用 | I5: 組織管理＞住所＞住所の設定 Organization administration > Addresses > Address setup
B6: =ROW()-3 -> 3 | C6: システム管理 | D6: 共通 | E6: ユーザーをロールに割り当てる | H6: ユーザをロールに紐づける。 アクセス権限の設定をするため、アクセス権限の種類ごとにユーザを紐づける。 ※移行対象 | I6: システム管理＞セキュリティ＞ユーザーをロールに割り当てる System administration > Security > Assign users to roles
B7: =ROW()-3 -> 4 | C7: システム管理 | D7: 共通 | E7: セキュリティロール | F7: 権限設計書参照 | G7: 権限設計書参照 | H7: ロールの定義となる。 ロールの数は、アクセス権限の種類分となる。 ※FO権限設計書で定義（設計書側で管理） | I7: システム管理＞セキュリティ＞セキュリティのコンフィギュレーション System administration > Security > Security configuration
B8: =ROW()-3 -> 5 | C8: システム管理 | D8: 共通 | E8: ユーザーIDへの作業者の割当 | H8: ユーザーIDに対して作業者の割当を設定する。 ※移行対象の | I8: システム管理＞ユーザー＞ユーザー System administration > Users > Users
B9: =ROW()-3 -> 6 | C9: システム管理 | D9: 共通 | E9: ユーザーグループ | H9: ユーザをグループごとに設定する。 ※ワークフローの割り当て時にユーザグループ単位で設定可能 ※各ユーザーグループに所属するユーザーについては移行対象とする | I9: システム管理＞ユーザー＞ユーザーグループ System administration > User > User Group
B10: =ROW()-3 -> 7 | C10: 一般会計 | D10: 共通 | E10: 通貨の為替レート | H10: 為替レートの定義を行う。 ※管理対象が多い場合移行対象の想定 | I10: 一般会計＞通貨＞通貨の為替レート General ledger > Currencies > Currency exchange rates
B11: =ROW()-3 -> 8 | C11: 売掛金管理 | D11: 個別 | E11: 顧客 | H11: 顧客の定義となる。 ※移行対象 | I11: 売掛金管理＞顧客＞すべての顧客 Accounts receivable > Customers > All customers
B12: =ROW()-3 -> 9 | C12: 買掛金管理 | D12: 個別 | E12: 仕入先 | H12: 仕入先の定義となる。 ※移行対象 | I12: 買掛金管理＞仕入先＞すべての仕入先 Accounts payable > Vendors > All vendors
B13: =ROW()-3 -> 10 | C13: 人事管理 | D13: 個別 | E13: 従業員 | H13: 新しい従業員の採用の定義となる。 ※移行対象 | I13: 人事管理＞作業者＞従業員 Human resources > Workers > Employees
B14: =ROW()-3 -> 11 | C14: 人事管理 | D14: 共通 | E14: 部門 | H14: 部門の設定が必要。 ※管理対象が多い場合移行対象の想定（作業単位同様 作業単位側で対応していたら対応不要） | I14: 人事管理＞部門＞部門 Human resources > Departments > Departments
B15: =ROW()-3 -> 12 | C15: 人事管理 | D15: 共通 | E15: 職務 | H15: 職務の設定が必要。 ※管理対象が多い場合移行対象の想定 | I15: 人事管理＞職務＞職務 Human resources > Jobs > Jobs
B16: =ROW()-3 -> 13 | C16: 人事管理 | D16: 共通 | E16: 職位 | H16: 職位の設定 １作業者に対して１職位となる。 ※部門と職務の設定が先に必要（WFで使用する場合などはタイトルの設定も必要） ※移行対象 | I16: 人事管理＞職位＞すべての職位 Human resources > Positions > All Positions

Sheet 作業単位
A1: 作業単位
B2: 組織管理＞組織＞作業単位
B3: Organization administration > Organizations > Operating units
A4: パラメータ設定一覧へ
B5: # | C5: タブ | D5: タブ説明 | E5: 項目分類 | F5: 項目 | G5: 項目説明 | H5: 設定可能値 | I5: デフォルト値 | J5: 備考 | K5: 設定値 | L5: 設定基準
B6: =ROW() - 5 -> 1 | C6: 概要 | E6: 作業単位 | F6: 名前 | H6: 文字列 | I6: ー | K6: 「作業単位-タ設定値」を参照
B7: =ROW() - 5 -> 2 | F7: 原価部門 番号 | G7: 原価部門 固有の英数字 ID | H7: 文字列 | I7: ー | J7: ○○←選択した作業単位のタイプ ※番号順序に順ずる形で採番されるが、手動変更が可能 | K7: 「作業単位-タ設定値」を参照
B8: =ROW() - 5 -> 3 | F8: 作業単位のタイプ | H8: ・部門 ・原価部門 ・バリューストリーム ・事業単位 ・すべての作業単位 ・小売チャンネル | I8: ー | K8: 「作業単位-タ設定値」を参照
B9: =ROW() - 5 -> 4 | C9: 一般 | F9: 検索名 | H9: 文字列 | I9: 作業単位＞名前 の値 | K9: 「作業単位-タ設定値」を参照
B10: =ROW() - 5 -> 5 | F10: メモ | G10: 選択した作業単位に関するメモを入力します。 | H10: 文字列 | I10: ー | K10: 「作業単位-タ設定値」を参照
B11: =ROW() - 5 -> 6 | F11: 階層 | G11: 選択したオプションは、選択した作業単位が組織階層に属していることを示します。 | H11: はい/いいえ | I11: はい | K11: 「作業単位-タ設定値」を参照
B12: =ROW() - 5 -> 7 | F12: DUNS番号 | H12: 文字列 | I12: ー | K12: 「作業単位-タ設定値」を参照
B13: =ROW() - 5 -> 8 | F13: マネージャー | G13: データベースのレコードの固有 ID | H13: 文字列（ユーザー定義） | I13: ー | K13: 「作業単位-タ設定値」を参照
B14: =ROW() - 4 -> 10 | C14: 住所 | F14: 名前または説明 | H14: 文字列 | I14: ー | K14: 「作業単位-タ設定値」を参照
B15: =ROW() - 4 -> 11 | F15: 住所 | H15: 文字列 | I15: ー | J15: 詳細オプションより以下を入力することで反映される ・国/地域 ・郵便番号 ・住所 ・市町村 ・都道府県 | K15: 「作業単位-タ設定値」を参照
B16: =ROW() - 4 -> 12 | F16: 目的 | H16: ・業務 ・委託販売 ・配送 ・固定資産 ・本社 ・ホーム ・請求書 ・船荷 ・その他 ・支払 ・実際の場所 ・採用 ・送金先 ・サービス ・安定した組織 ・ステートメント ・SWIFT ・船降 | I16: ー | K16: 「作業単位-タ設定値」を参照
B17: =ROW() - 4 -> 13 | F17: 主要 | H17: はい/いいえ | I17: ー | K17: 「作業単位-タ設定値」を参照
B18: =ROW() - 4 -> 14 | E18: 詳細オプション | F18: 国/地域 | H18: 国/地域（システム定義） | I18: ー | J18: 「詳細オプション＞詳細」より編集可能 | K18: 「作業単位-タ設定値」を参照
B19: =ROW() - 4 -> 15 | F19: 郵便番号 | H19: 数値 | I19: ー | J19: 「詳細オプション＞詳細」より編集可能 | K19: 「作業単位-タ設定値」を参照
B20: =ROW() - 4 -> 16 | F20: 住所 | H20: 文字列 | I20: ー | J20: 「詳細オプション＞詳細」より編集可能 | K20: 「作業単位-タ設定値」を参照
B21: =ROW() - 4 -> 17 | F21: 住所（カナ） | H21: 文字列 | I21: ー | J21: 「詳細オプション＞詳細」より編集可能 | K21: 「作業単位-タ設定値」を参照
B22: =ROW() - 4 -> 18 | F22: 市町村 | H22: 文字列 | I22: ー | J22: 「詳細オプション＞詳細」より編集可能 | K22: 「作業単位-タ設定値」を参照
B23: =ROW() - 4 -> 19 | F23: 市町村（カナ） | H23: 文字列 | I23: ー | J23: 「詳細オプション＞詳細」より編集可能 | K23: 「作業単位-タ設定値」を参照
B24: =ROW() - 4 -> 20 | F24: 都道府県 | H24: 文字列 | I24: ー | J24: 「詳細オプション＞詳細」より編集可能 | K24: 「作業単位-タ設定値」を参照
B25: =ROW() - 4 -> 21 | F25: 市区群 | H25: 文字列 | I25: ー | J25: 「詳細オプション＞詳細」より編集可能 | K25: 「作業単位-タ設定値」を参照
B26: =ROW() - 4 -> 22 | F26: 主要 | H26: はい/いいえ | I26: ー | J26: 「詳細オプション＞詳細」より編集可能 | K26: 「作業単位-タ設定値」を参照
B27: =ROW() - 4 -> 23 | F27: 国/地域に関する基本事項 | H27: はい/いいえ | I27: ー | J27: 「詳細オプション＞詳細」より編集可能 | K27: 「作業単位-タ設定値」を参照
B28: =ROW() - 4 -> 24 | C28: 連絡先情報 | F28: 説明 | H28: 文字列 | I28: ー | K28: 「作業単位-タ設定値」を参照
B29: =ROW() - 4 -> 25 | F29: タイプ | H29: ・電話 ・電子メールアドレス ・URL ・テレックス ・FAX ・Facebook ・Twitter ・LinkedIn | I29: ー | K29: 「作業単位-タ設定値」を参照
B30: =ROW() - 4 -> 26 | F30: 連絡先の電話番号/住所 | H30: 文字列 | I30: ー | K30: 「作業単位-タ設定値」を参照
B31: =ROW() - 4 -> 27 | F31: 内線 | H31: 文字列 | I31: ー | K31: 「作業単位-タ設定値」を参照
B32: =ROW() - 4 -> 28 | F32: 主要 | H32: チェック有/チェック無 | I32: チェック無 | K32: 「作業単位-タ設定値」を参照

Sheet 作業単位-設定値
A1: 作業単位-設定値 ※基本的には移行データを正とする
A2: ■凡例「必須：システム上必須」「必須(*)：システムで必須ではないが、トランザクション上や業務などで必須」
A3: パラメータ設定一覧へ
B4: # | C4: 概要 | F4: 一般 | K4: 住所 | Y4: 連絡先情報
C5: 作業単位 | K5: 追加 | O5: 詳細オプション
C6: 名前 | D6: 原価部門 番号 | E6: 作業単位タイプ | F6: 検索名 | G6: メモ | H6: 階層 | I6: DUNS番号 | J6: マネージャー | K6: 名前または説明 | L6: 住所 | M6: 目的 | N6: 主要 | O6: 国/地域 | P6: 郵便番号 | Q6: 住所 | R6: 住所（カナ） | S6: 市町村 | T6: 市町村（カナ） | U6: 都道府県 | V6: 市区群 | W6: 主要 | X6: 国/地域に関する基本事項 | Y6: 説明 | Z6: タイプ | AA6: 連絡先の電話番号/住所 | AB6: 内線 | AC6: 主要
C7: 文字列 | D7: 文字列 ※番号順序に順ずる形で採番されるが、手動変更が可能 | E7: 部門 原価部門 バリューストリーム 事業単位 すべての作業単位 小売チャンネル | F7: 文字列 | G7: 文字列 | H7: はい/いいえ | I7: 文字列 | J7: 文字列（ユーザー定義） | K7: 文字列 | L7: 文字列 | N7: はい/いいえ | O7: 国/地域（システム定義） | P7: 数値 | Q7: 文字列 | R7: 文字列 | S7: 文字列 | T7: 文字列 | U7: 文字列 | V7: 文字列 | W7: はい/いいえ | X7: はい/いいえ | Y7: 文字列 | AA7: 文字列 | AB7: 文字列 | AC7: チェック有/チェック無
C8: 必須 | D8: 必須 | E8: 必須
B9: 例 | C9: Dynamics部 | D9: D0001 | E9: 部門 | F9: Dynamics部
B10: =ROW() - 9 -> 1
B11: =ROW() - 9 -> 2
B12: =ROW() - 9 -> 3
B13: =ROW() - 9 -> 4
B14: =ROW() - 9 -> 5
B15: =ROW() - 9 -> 6
B16: =ROW() - 9 -> 7
B17: =ROW() - 9 -> 8
B18: =ROW() - 9 -> 9
B19: =ROW() - 9 -> 10
B20: =ROW() - 9 -> 11
B21: =ROW() - 9 -> 12
... B109: =ROW() - 9 -> 100

Sheet 住所の設定
A1: 住所の設定
B2: 組織管理＞グローバルアドレス帳>住所＞住所の設定
B3: Organization administration > Addresses > Address setup
A4: パラメータ設定一覧へ
B5: # | C5: タブ | D5: タブ説明 | E5: 項目分類 | F5: 項目 | G5: 項目説明 | H5: 設定可能値 | I5: デフォルト値 | J5: 備考 | K5: 設定値 | L5: 設定基準
B6: =ROW() - 5 -> 1 | C6: パラメーター | D6: 住所作成時に検証 | F6: 郵便番号 | H6: はい/いいえ | I6: いいえ | K6: いいえ
B7: =ROW() - 5 -> 2 | F7: 地区 | H7: はい/いいえ | I7: いいえ | K7: いいえ
B8: =ROW() - 5 -> 3 | F8: 市町村 | H8: はい/いいえ | I8: いいえ | K8: いいえ
A9: △ | B9: =ROW() - 5 -> 4 | F9: 市区群 | H9: はい/いいえ | I9: はい | K9: はい
B10: =ROW() - 5 -> 5 | F10: ロシア語の住所形式の検証を無効にする | H10: はい/いいえ | I10: いいえ | K10: いいえ
B11: =ROW() - 5 -> 6 | C11: 住所の設定 | D11: 住所の設定に住所の形式情報を入力します | F11: 住所の形式 | H11: 文字列 | I11: - | J11: 最初に設定して保存した後は変更不可 | K11: 「住所の形式-設定値」を参照
B12: =ROW() - 5 -> 7 | F12: 説明 | H12: 文字列 | I12: - | K12: 「住所の形式-設定値」を参照
B13: =ROW() - 5 -> 8 | F13: プレビュー | H13: - | I13: - | J13: 設定値のプレビューが表示される | K13: 「住所の形式-設定値」を参照
B14: =ROW() - 5 -> 9 | E14: 住所コンポーネントのコンフィギュレーション | F14: 住所アプリケーションオブジェクト | H14: ・郵便番号 ・市町村 ・市区群 ・都道府県 ・国/地域 ・住所 ・地域 ・番地 ・建物名（補足） ・郵便受 ・番地 ・Building ・Apartment ・家のグループ ・アパートのグループ ・OKSM別コード ・住所形式 ・土地区画 | I14: 選択した「住所の形式」により初期値は異なる | K14: 「住所の形式-設定値」を参照
B15: =ROW() - 5 -> 10 | F15: 区切り | H15: 文字列 | I15: - | K15: 「住所の形式-設定値」を参照
B16: =ROW() - 5 -> 11 | F16: 新しいライン | H16: チェック有/チェック無 | I16: - | K16: 「住所の形式-設定値」を参照
B17: =ROW() - 5 -> 12 | F17: データ入力専用 | G17: 住所情報を入力した場合にのみ住所コンポーネントを含めるには、このオプションを選択します。このオプションを選択した場合、住所の印刷時に、住所コンポーネントは表示されません。 | H17: チェック有/チェック無 | I17: - | K17: 「住所の形式-設定値」を参照
B18: =ROW() - 5 -> 13 | F18: 無効 | H18: チェック有/チェック無 | I18: - | K18: 「住所の形式-設定値」を参照
B19: =ROW() - 5 -> 14 | F19: 展開 | G19: 住所の印刷時に、国/地域、都道府県、および国の正式名を表示するには、このオプションを選択します。このオプションをオフにすると、住所の印刷時に、国/地域、都道府県、および国のコードのみが表示されます。 | H19: チェック有/チェック無 | I19: - | K19: 「住所の形式-設定値」を参照
B20: =ROW() - 5 -> 15 | F20: 特別 | G20: 現在の住所コンポーネントの区切り記号が前の住所コンポーネントの区切り記号と同じであることを指定するには、このオプションを選択します。 | H20: チェック有/チェック無 | I20: - | K20: 「住所の形式-設定値」を参照
B21: =ROW() - 5 -> 16 | C21: 国/地域 | D21: 住所の設定に国/地域情報を入力します | F21: 国/地域（リスト） | H21: 世界各国の国と地域(350か国以上) | I21: -
B22: =ROW() - 5 -> 17 | F22: 略称（リスト） | H22: 世界各国の国と地域(350か国以上) | I22: -
B23: =ROW() - 5 -> 18 | F23: 国/地域 | H23: 文字列 | I23: -
B24: =ROW() - 5 -> 19 | F24: 略称 | H24: 文字列 | I24: -
B25: =ROW() - 5 -> 20 | F25: タイムゾーン | H25: 世界各国のタイムゾーン | I25: -
B26: =ROW() - 5 -> 21 | F26: 郵便番号＋４桁コードの検証ルールを使用 | H26: はい/いいえ | I26: -
B27: =ROW() - 5 -> 22 | F27: ISO | H27: 住所の形式 | I27: -
B28: =ROW() - 5 -> 23 | F28: IOR融資ID | H28: 文字列 | I28: -
B29: =ROW() - 5 -> 24 | F29: 正式名称 | H29: 文字列 | I29: -
B30: =ROW() - 5 -> 25 | F30: 住所の形式 | H30: 住所の形式 | I30: -
B31: =ROW() - 5 -> 26 | F31: BACEN code | H31: 文字列 | I31: -
B32: =ROW() - 5 -> 27 | F32: Code by OKSM | H32: - | I32: -
B33: =ROW() - 5 -> 28 | F33: Member of Customs Union | H33: はい/いいえ | I33: いいえ
B34: =ROW() - 5 -> 29 | C34: 都道府県 | D34: 住所の設定に都道府県情報を入力します | F34: 都道府県 | H34: ・京都府 ・北海道 ・大阪府 ・東京都 ・福岡県 ・群馬県 ・長崎県 | I34: - | J34: 「国/地域」が「JPN」の場合 | K34: 「都道府県-設定値」を参照
B35: =ROW() - 5 -> 30 | F35: 説明 | H35: - | I35: - | K35: 「都道府県-設定値」を参照
B36: =ROW() - 5 -> 31 | F36: 国/地域 | H36: - | I36: JPN | K36: 「都道府県-設定値」を参照
B37: =ROW() - 5 -> 32 | F37: 都道府県 | H37: - | I37: - | J37: 「都道府県」で選択した都道府県が自動で入力される | K37: 「都道府県-設定値」を参照
B38: =ROW() - 5 -> 33 | F38: 説明 | H38: 文字列 | I38: - | K38: 「都道府県-設定値」を参照
B39: =ROW() - 5 -> 34 | F39: タイムゾーン | H39: 世界各国のタイムゾーン | I39: - | K39: 「都道府県-設定値」を参照
B40: =ROW() - 5 -> 35 | F40: イントラスタットコード | H40: 文字列 | I40: - | K40: 「都道府県-設定値」を参照
B41: =ROW() - 5 -> 36 | F41: IT州コード | H41: 文字列 | I41: - | K41: 「都道府県-設定値」を参照
B42: =ROW() - 5 -> 37 | F42: 既定の都道府県 | H42: はい/いいえ | I42: いいえ | K42: 「都道府県-設定値」を参照
B43: =ROW() - 5 -> 38 | F43: State code | G43: Enter the state code as defined under the Indian Census 2011. | H43: 文字列 | I43: - | K43: 「都道府県-設定値」を参照
B44: =ROW() - 5 -> 39 | F44: Union territoty | G44: Indicate if the state is union territory. | H44: はい/いいえ | I44: いいえ | K44: 「都道府県-設定値」を参照
B45: =ROW() - 5 -> 40 | C45: 市区郡 | D45: 住所の設定に国情報を入力します | F45: 市区郡 | H45: 市区郡（ユーザー定義） | I45: - | J45: 移行対象の想定 | K45: 「市区郡-設定値」を参照
B46: =ROW() - 5 -> 41 | F46: 説明 | H46: 市区郡（ユーザー定義） | I46: - | J46: 移行対象の想定 | K46: 「市区郡-設定値」を参照
B47: =ROW() - 5 -> 42 | F47: 国/地域 | H47: 世界の国と地域 | I47: JPN | J47: 移行対象の想定 | K47: 「市区郡-設定値」を参照
B48: =ROW() - 5 -> 43 | F48: 都道府県 | H48: ・京都府 ・北海道 ・大阪府 ・東京都 ・福岡県 ・群馬県 ・長崎県 | I48: - | J48: 移行対象の想定 | K48: 「市区郡-設定値」を参照
B49: =ROW() - 5 -> 44 | F49: 市区郡 | H49: - | I49: - | J49: 移行対象の想定 | K49: 「市区郡-設定値」を参照
B50: =ROW() - 5 -> 45 | F50: 説明 | H50: - | I50: - | J50: 移行対象の想定 | K50: 「市区郡-設定値」を参照
B51: =ROW() - 5 -> 46 | F51: IT市区郡コード | H51: - | I51: - | J51: 移行対象の想定 | K51: 「市区郡-設定値」を参照
B52: =ROW() - 5 -> 47 | F52: ES市区郡コード | H52: - | I52: - | J52: 移行対象の想定 | K52: 「市区郡-設定値」を参照
B53: =ROW() - 5 -> 48 | C53: 市町村 | D53: 住所の設定に市町村情報を入力します | F53: 国/地域 | H53: 世界の国と地域 | I53: JPN | J53: 移行対象の想定 | K53: 「市町村-設定値」を参照
B54: =ROW() - 5 -> 49 | F54: 市町村 | H54: 世界各国・地域の市町村 | I54: - | J54: 移行対象の想定 | K54: 「市町村-設定値」を参照
B55: =ROW() - 5 -> 50 | F55: 市町村（カナ） | H55: 文字列 | I55: - | J55: 移行対象の想定 | K55: 「市町村-設定値」を参照
B56: =ROW() - 5 -> 51 | F56: 説明 | H56: - | I56: - | J56: 移行対象の想定 | K56: 「市町村-設定値」を参照
B57: =ROW() - 5 -> 52 | F57: 都道府県 | H57: ・京都府 ・北海道 ・大阪府 ・東京都 ・福岡県 ・群馬県 ・長崎県 | I57: - | J57: 移行対象の想定 | K57: 「市町村-設定値」を参照
B58: =ROW() - 5 -> 53 | F58: 市区郡 | H58: 市区郡（ユーザー定義） | I58: - | J58: 移行対象の想定 | K58: 「市町村-設定値」を参照
B59: =ROW() - 5 -> 54 | F59: IT自治体コード | H59: 文字列 | I59: - | J59: 移行対象の想定 | K59: 「市町村-設定値」を参照
B60: =ROW() - 5 -> 55 | F60: 市町村キー | H60: 文字列文字列（国/地域、都道府県、市町村を入れると自動反映される） | I60: - | J60: 移行対象の想定 | K60: 「市町村-設定値」を参照
B61: =ROW() - 5 -> 56 | C61: 地区 | D61: 住所の設定に地区情報を入力する | F61: 国/地域 | H61: 世界の国と地域 | J61: 移行対象の想定 | K61: 「地区-設定値」を参照
B62: =ROW() - 5 -> 57 | F62: 都道府県 | H62: 都道府県（ユーザー定義） | I62: - | J62: 移行対象の想定 | K62: 「地区-設定値」を参照
B63: =ROW() - 5 -> 58 | F63: 市区郡 | H63: 市区郡（ユーザー定義） | I63: - | J63: 移行対象の想定 | K63: 「地区-設定値」を参照
B64: =ROW() - 5 -> 59 | F64: 市町村 | G64: データベースのレコードの固有 ID | H64: 市町村（ユーザー定義） | I64: - | J64: 移行対象の想定 | K64: 「地区-設定値」を参照
B65: =ROW() - 5 -> 60 | F65: 地区 | H65: 文字列 | I65: - | J65: 移行対象の想定 | K65: 「地区-設定値」を参照
B66: =ROW() - 5 -> 61 | F66: 説明 | H66: 文字列 | I66: - | J66: 移行対象の想定 | K66: 「地区-設定値」を参照
B67: =ROW() - 5 -> 62 | C67: 住所 | D67: 住所の設定に番地情報を入力します | F67: 国/地域 | H67: 世界の国と地域 | J67: ロシアで使用 | K67: 「住所-設定値」を参照
B68: =ROW() - 5 -> 63 | F68: 都道府県 | H68: 都道府県（ユーザー定義） | I68: - | J68: ロシアで使用 | K68: 「住所-設定値」を参照
B69: =ROW() - 5 -> 64 | F69: 市区郡 | H69: 市区郡（ユーザー定義） | I69: - | J69: ロシアで使用 | K69: 「住所-設定値」を参照
B70: =ROW() - 5 -> 65 | F70: 市町村 | G70: データベースのレコードの固有 ID | H70: 市町村（ユーザー定義） | I70: - | J70: ロシアで使用 | K70: 「住所-設定値」を参照
B71: =ROW() - 5 -> 66 | F71: 地区 | G71: データベースのレコードの固有 ID | H71: 数値 | I71: - | J71: ロシアで使用 | K71: 「住所-設定値」を参照
B72: =ROW() - 5 -> 67 | F72: 番地 | H72: 文字列 | I72: - | J72: ロシアで使用 | K72: 「住所-設定値」を参照
B73: =ROW() - 5 -> 68 | F73: 住所 | H73: 文字列 | I73: - | J73: ロシアで使用 | K73: 「住所-設定値」を参照
B74: =ROW() - 5 -> 69 | F74: 省略形コード | H74: 省略形コード（ユーザー定義） | I74: - | J74: ロシアで使用 | K74: 「住所-設定値」を参照
B75: =ROW() - 5 -> 70 | F75: 説明 | H75: 文字列 | I75: - | J75: ロシアで使用 | K75: 「住所-設定値」を参照
B76: =ROW() - 5 -> 71 | F76: 郵便番号 | H76: 郵便番号 | I76: - | J76: ロシアで使用 | K76: 「住所-設定値」を参照
B77: =ROW() - 5 -> 72 | F77: STI code | H77: 数値 | I77: - | J77: ロシアで使用 | K77: 「住所-設定値」を参照
B78: =ROW() - 5 -> 73 | F78: IMNS 地域の数 | H78: 数値 | I78: - | J78: ロシアで使用 | K78: 「住所-設定値」を参照
B79: =ROW() - 5 -> 74 | F79: RCM | H79: 数値 | I79: - | J79: ロシアで使用 | K79: 「住所-設定値」を参照
B80: =ROW() - 5 -> 75 | F80: オブジェクトステータス | H80: ・拠点都市/主要都市ではありません ・市区郡の拠点都市/主要都市 ・都道府県の拠点都市/主要都市 ・都道府県と市区郡の拠点値 | I80: 拠点都市/主要都市ではありません | J80: ロシアで使用 | K80: 「住所-設定値」を参照
B81: =ROW() - 5 -> 76 | C81: 家のグループ | D81: 住所の設定に家の情報を入力します | F81: 国/地域 | H81: 世界の国と地域 | J81: ロシアで使用 | K81: 「家のグループ-設定値」を参照
B82: =ROW() - 5 -> 77 | F82: 都道府県 | H82: 都道府県（ユーザー定義） | I82: - | J82: ロシアで使用 | K82: 「家のグループ-設定値」を参照
B83: =ROW() - 5 -> 78 | F83: 市区郡 | H83: 市区郡（ユーザー定義） | I83: - | J83: ロシアで使用 | K83: 「家のグループ-設定値」を参照
B84: =ROW() - 5 -> 79 | F84: 市町村 | G84: データベースのレコードの固有 ID | H84: 市町村（ユーザー定義） | I84: - | J84: ロシアで使用 | K84: 「家のグループ-設定値」を参照
B85: =ROW() - 5 -> 80 | F85: 地区 | G85: データベースのレコードの固有 ID | H85: 地域（ユーザー定義） | I85: - | J85: ロシアで使用 | K85: 「家のグループ-設定値」を参照
B86: =ROW() - 5 -> 81 | F86: 番地 | G86: データベースのレコードの固有 ID | H86: 番地（ユーザー定義） | I86: - | J86: ロシアで使用 | K86: 「家のグループ-設定値」を参照
B87: =ROW() - 5 -> 82 | F87: 家のグループコード | H87: 文字列 | I87: - | J87: ロシアで使用 | K87: 「家のグループ-設定値」を参照
B88: =ROW() - 5 -> 83 | F88: 建物の番号 | H88: 数値 | I88: - | J88: ロシアで使用 | K88: 「家のグループ-設定値」を参照
B89: =ROW() - 5 -> 84 | F89: 建物 | H89: 文字列 | I89: - | J89: ロシアで使用 | K89: 「家のグループ-設定値」を参照
B90: =ROW() - 5 -> 85 | F90: 省力系コード | H90: 省略形コード | I90: - | J90: ロシアで使用 | K90: 「家のグループ-設定値」を参照
B91: =ROW() - 5 -> 86 | F91: 説明 | H91: - | I91: - | J91: ロシアで使用 | K91: 「家のグループ-設定値」を参照
B92: =ROW() - 5 -> 87 | F92: 郵便番号 | H92: 郵便番号 | I92: - | J92: ロシアで使用 | K92: 「家のグループ-設定値」を参照
B93: =ROW() - 5 -> 88 | F93: STI code | H93: 数値 | I93: - | J93: ロシアで使用 | K93: 「家のグループ-設定値」を参照
B94: =ROW() - 5 -> 89 | F94: IMNS 地域の数 | H94: 数値 | I94: - | J94: ロシアで使用 | K94: 「家のグループ-設定値」を参照
B95: =ROW() - 5 -> 90 | F95: RCM | H95: 数値 | I95: - | J95: ロシアで使用 | K95: 「家のグループ-設定値」を参照
B96: =ROW() - 5 -> 91 | C96: 土地区画 | D96: 住所設定に対する場所情報を入力する | F96: 国/地域 | H96: 世界の国と地域 | J96: ロシアで使用 | K96: 「土地区画-設定値」を参照
B97: =ROW() - 5 -> 92 | F97: 都道府県 | H97: 都道府県（ユーザー定義） | I97: - | J97: ロシアで使用 | K97: 「土地区画-設定値」を参照
B98: =ROW() - 5 -> 93 | F98: 市区郡 | H98: 市区郡（ユーザー定義） | I98: - | J98: ロシアで使用 | K98: 「土地区画-設定値」を参照
B99: =ROW() - 5 -> 94 | F99: 市町村 | G99: データベースのレコードの固有 ID | H99: 市町村（ユーザー定義） | I99: - | J99: ロシアで使用 | K99: 「土地区画-設定値」を参照
B100: =ROW() - 5 -> 95 | F100: 地区 | G100: データベースのレコードの固有 ID | H100: 地域（ユーザー定義） | I100: - | J100: ロシアで使用 | K100: 「土地区画-設定値」を参照
...

Sheet 住所の形式-設定値
A1: 住所の形式-設定値 ※既定値以外の形式を使用する場合新規で登録し、それのみを記載
A2: ■凡例「必須：システム上必須」「必須(*)：システムで必須ではないが、トランザクション上や業務などで必須」
A3: パラメータ設定一覧へ
B4: # | C4: 住所の形式 | D4: 説明 | E4: 住所アプリケーションオブジェクト | F4: 区切り | G4: 新しいライン | H4: データ入力専用 | I4: 無効 | J4: 展開 | K4: 特別
C5: 文字列 | D5: 文字列 | E5: ※「住所の設定」参照 | F5: 文字列 | G5: チェック有/チェック無 | H5: チェック有/チェック無 | I5: チェック有/チェック無 | J5: チェック有/チェック無 | K5: チェック有/チェック無
C6: 必須 | E6: 必須（国/地域は必須）
B7: 例 | C7: JBS-TEST | D7: JBS使用住所形式 | E7: 国/地域 | G7: チェック有
E8: 郵便番号 | G8: チェック有
E9: 都道府県 | G9: チェック有
E10: 市町村 | G10: チェック有
E11: 住所 | G11: チェック有
B12: 1 | C12: JPN1 | D12: 日本式1（郵便番号／都道府県／市区町村／住所／ビル名） | E12: 国/地域 | F12: ー | G12: チェック有
E13: 郵便番号 | F13: ー | G13: チェック有
E14: 都道府県 | F14: ー | G14: チェック有
E15: 市町村 | F15: ー | G15: チェック有
E16: 住所 | F16: ー | G16: チェック有
E17: 建物名 (補足) | F17: ー | G17: チェック有

Sheet 都道府県-設定値
A1: 都道府県-設定値 ※基本的には移行データを正とする（日本の郵便番号インポートでは反映されない）
A2: ■凡例「必須：システム上必須」「必須(*)：システムで必須ではないが、トランザクション上や業務などで必須」
A3: パラメータ設定一覧へ
B4: # | C4: 都道府県
C5: 国/地域 | D5: 都道府県 | E5: 説明 | F5: タイムゾーン | G5: イントラスタットコード | H5: IT州コード | I5: 既定の都道府県 | J5: State code | K5: Union territory
C6: （ユーザー定義） | E6: 文字列 | G6: 文字列 | H6: 文字列 | I6: はい/いいえ | J6: 文字列 | K6: はい/いいえ
C7: 必須 | D7: 必須
B8: =ROW() - 7 -> 1 | C8: JPN | D8: 北海道 | E8: ー | F8: ー | G8: ー | H8: ー | I8: ー | J8: ー | K8: いいえ
B9: =ROW() - 7 -> 2 | C9: JPN | D9: 青森県 | E9: ー | F9: ー | G9: ー | H9: ー | I9: ー | J9: ー | K9: いいえ
B10: =ROW() - 7 -> 3 | C10: JPN | D10: 岩手県 | E10: ー | F10: ー | G10: ー | H10: ー | I10: ー | J10: ー | K10: いいえ
B11: =ROW() - 7 -> 4 | C11: JPN | D11: 宮城県 | E11: ー | F11: ー | G11: ー | H11: ー | I11: ー | J11: ー | K11: いいえ
B12: =ROW() - 7 -> 5 | C12: JPN | D12: 秋田県 | E12: ー | F12: ー | G12: ー | H12: ー | I12: ー | J12: ー | K12: いいえ
B13: =ROW() - 7 -> 6 | C13: JPN | D13: 山形県 | E13: ー | F13: ー | G13: ー | H13: ー | I13: ー | J13: ー | K13: いいえ
B14: =ROW() - 7 -> 7 | C14: JPN | D14: 福島県 | E14: ー | F14: ー | G14: ー | H14: ー | I14: ー | J14: ー | K14: いいえ
B15: =ROW() - 7 -> 8 | C15: JPN | D15: 茨城県 | E15: ー | F15: ー | G15: ー | H15: ー | I15: ー | J15: ー | K15: いいえ
B16: =ROW() - 7 -> 9 | C16: JPN | D16: 栃木県 | E16: ー | F16: ー | G16: ー | H16: ー | I16: ー | J16: ー | K16: いいえ
B17: =ROW() - 7 -> 10 | C17: JPN | D17: 群馬県 | E17: ー | F17: ー | G17: ー | H17: ー | I17: ー | J17: ー | K17: いいえ
B18: =ROW() - 7 -> 11 | C18: JPN | D18: 埼玉県 | E18: ー | F18: ー | G18: ー | H18: ー | I18: ー | J18: ー | K18: いいえ
B19: =ROW() - 7 -> 12 | C19: JPN | D19: 千葉県 | E19: ー | F19: ー | G19: ー | H19: ー | I19: ー | J19: ー | K19: いいえ
... B54: =ROW() - 7 -> 47 | C54: JPN | D54: 沖縄県 | E54: ー | F54: ー | G54: ー | H54: ー | I54: ー | J54: ー | K54: いいえ

Sheet 市区郡-設定値
A1: 市区郡-設定値 ※基本的には移行データを正とする（日本の郵便番号インポートでは反映されない）
A2: ■凡例「必須：システム上必須」「必須(*)：システムで必須ではないが、トランザクション上や業務などで必須」
A3: パラメータ設定一覧へ
B4: # | C4: 市区郡
C5: 国/地域 | D5: 都道府県 | E5: 市区郡 | F5: 説明 | G5: IT市区郡コード | H5: ES市区郡コード
C6: （ユーザー定義） | D6: （ユーザー定義） | E6: 文字列 | F6: 文字列 | G6: 文字列 | H6: 文字列
C7: 必須 | D7: 必須 | E7: 必須
B8: =ROW() - 7 -> 1
B9: =ROW() - 7 -> 2
B10: =ROW() - 7 -> 3

Sheet 市町村-設定値
A1: 市町村-設定値 ※基本的には移行データを正とする（郵便番号インポート）
A2: ■凡例「必須：システム上必須」「必須(*)：システムで必須ではないが、トランザクション上や業務などで必須」
A3: パラメータ設定一覧へ
B4: # | C4: 市町村
C5: 国/地域 | D5: 市町村 | E5: 説明 | F5: City code | G5: 都道府県 | H5: 市区郡 | I5: IT自治体コード | J5: 市町村キー
C6: （ユーザー定義） | D6: （ユーザー定義） | E6: 文字列 | F6: 文字列 | G6: （ユーザー定義） | H6: 文字列 | I6: 文字列 | J6: 文字列（国/地域、都道府県、市町村を入れると自動反映される）
C7: 必須 | D7: 必須 | J7: 必須
B8: =ROW() - 7 -> 1
B9: =ROW() - 7 -> 2
B10: =ROW() - 7 -> 3
B11: =ROW() - 7 -> 4
B12: =ROW() - 7 -> 5
B13: =ROW() - 7 -> 6

Sheet 地区-設定値
A1: 地区-設定値 ※基本的には移行データを正とする（日本の郵便番号インポートでは反映されない）
A2: ■凡例「必須：システム上必須」「必須(*)：システムで必須ではないが、トランザクション上や業務などで必須」
A3: パラメータ設定一覧へ
B4: # | C4: 地域
C5: 国/地域 | D5: 都道府県 | E5: 市区郡 | F5: 市町村 | G5: 地区 | H5: 説明
C6: （ユーザー定義） | D6: （ユーザー定義） | E6: （ユーザー定義） | F6: （ユーザー定義） | G6: 文字列 | H6: 文字列
F7: 必須 | G7: 必須
B8: =ROW() - 7 -> 1
B9: =ROW() - 7 -> 2
B10: =ROW() - 7 -> 3
B11: =ROW() - 7 -> 4
B12: =ROW() - 7 -> 5

Sheet 住所-設定値
A1: 住所-設定値 ※基本的には移行データを正とする（ロシアでのみ使用）
A2: ■凡例「必須：システム上必須」「必須(*)：システムで必須ではないが、トランザクション上や業務などで必須」
A3: パラメータ設定一覧へ
B4: # | C4: 住所
C5: 国/地域 | D5: 都道府県 | E5: 市区郡 | F5: 市町村 | G5: 地区 | H5: 番地 | I5: 住所 | J5: 省略形コード | K5: 説明 | L5: 郵便番号 | M5: STI code | N5: IMNS 地域の数 | O5: RCM | P5: オブジェクト ステータス
C6: （ユーザー定義） | D6: （ユーザー定義） | E6: （ユーザー定義） | F6: （ユーザー定義） | G6: 数値 | H6: 数値 | I6: 文字列 | J6: （ユーザー定義） | K6: 文字列 | L6: （ユーザー定義） | M6: 数値 | N6: 数値 | O6: 数値
C7: ※RUS固定 | H7: 必須
B8: =ROW() - 7 -> 1 | C8: RUS
B9: =ROW() - 7 -> 2 | C9: RUS
B10: =ROW() - 7 -> 3 | C10: RUS
B11: =ROW() - 7 -> 4 | C11: RUS
B12: =ROW() - 7 -> 5 | C12: RUS

Sheet 家のグループ-設定値
A1: 家のグループ-設定値 ※基本的には移行データを正とする（ロシアでのみ使用）
A2: ■凡例「必須：システム上必須」「必須(*)：システムで必須ではないが、トランザクション上や業務などで必須」
A3: パラメータ設定一覧へ
B4: # | C4: 家のグループ
C5: 国/地域 | D5: 都道府県 | E5: 市区郡 | F5: 市町村 | G5: 地区 | H5: 番地 | I5: 家のグループコード | J5: 建物の番号 | K5: 建物 | L5: 省略形コード | M5: 説明 | N5: 郵便番号 | O5: STI code | P5: IMNS地域の数 | Q5: RCOAD
C6: （ユーザー定義） | D6: （ユーザー定義） | E6: （ユーザー定義） | F6: （ユーザー定義） | G6: （ユーザー定義） | H6: （ユーザー定義） | I6: 数値 | J6: 数値 | K6: 文字列 | L6: （ユーザー定義） | M6: 文字列 | N6: 郵便番号 | O6: 数値 | P6: 数値 | Q6: 数値
C7: ※RUS固定 | I7: 必須
B8: =ROW() - 7 -> 1 | C8: RUS
B9: =ROW() - 7 -> 2 | C9: RUS
B10: =ROW() - 7 -> 3 | C10: RUS
B11: =ROW() - 7 -> 4 | C11: RUS
B12: =ROW() - 7 -> 5 | C12: RUS

Sheet 土地区画-設定値
A1: 土地区画-設定値 ※基本的には移行データを正とする（ロシアでのみ使用）
A2: ■凡例「必須：システム上必須」「必須(*)：システムで必須ではないが、トランザクション上や業務などで必須」
A3: パラメータ設定一覧へ
B4: # | C4: 土地区画
C5: 国/地域 | D5: 都道府県 | E5: 市区郡 | F5: 市町村 | G5: 地区 | H5: 番地 | I5: 土地区画コード | J5: 土地区画の番地 | K5: 建物 | L5: 省略形コード | M5: 説明 | N5: 郵便番号 | O5: STI code | P5: IMNS地域の数 | Q5: RCM
C6: （ユーザー定義） | D6: （ユーザー定義） | E6: （ユーザー定義） | F6: （ユーザー定義） | G6: （ユーザー定義） | H6: （ユーザー定義） | I6: 文字列 | J6: 数値 | K6: 文字列 | M6: 文字列 | N6: 郵便番号 | O6: 数値 | P6: 数値 | Q6: 数値
C7: ※RUS固定 | I7: 必須
B8: =ROW() - 7 -> 1 | C8: RUS
B9: =ROW() - 7 -> 2 | C9: RUS
B10: =ROW() - 7 -> 3 | C10: RUS
B11: =ROW() - 7 -> 4 | C11: RUS
B12: =ROW() - 7 -> 5 | C12: RUS

Sheet アパートのグループ-設定値
A1: アパートのグループ-設定値 ※基本的には移行データを正とする（ロシアでのみ使用）
A2: ■凡例「必須：システム上必須」「必須(*)：システムで必須ではないが、トランザクション上や業務などで必須」
A3: パラメータ設定一覧へ
B4: # | C4: アパートのグループ
C5: 国/地域 | D5: 都道府県 | E5: 市区郡 | F5: 市町村 | G5: 地区 | H5: 番地 | I5: 家のグループ | J5: アパートグループのコード | K5: アパートのグループ | L5: エントランス番号 | M5: 省略形コード | N5: 説明 | O5: 郵便番号 | P5: STI code | Q5: IMNS地域の数
C6: （ユーザー定義） | D6: （ユーザー定義） | E6: （ユーザー定義） | F6: （ユーザー定義） | G6: （ユーザー定義） | H6: （ユーザー定義） | I6: （ユーザー定義） | J6: 文字列 | K6: 文字列 | L6: 数値 | N6: 文字列 | O6: 郵便番号 | P6: 数値 | Q6: 数値
C7: ※RUS固定 | I7: 必須 | J7: 必須
B8: =ROW() - 7 -> 1 | C8: RUS
B9: =ROW() - 7 -> 2 | C9: RUS
B10: =ROW() - 7 -> 3 | C10: RUS
B11: =ROW() - 7 -> 4 | C11: RUS
B12: =ROW() - 7 -> 5 | C12: RUS

Sheet 郵便番号-設定値
A1: 郵便番号-設定値 ※基本的には移行データを正とする（郵便番号インポート）
A2: ■凡例「必須：システム上必須」「必須(*)：システムで必須ではないが、トランザクション上や業務などで必須」
A3: パラメータ設定一覧へ
B4: # | C4: 郵便番号 | E4: ※都道府県以降、入力しているとトランザクション等の住所選択時に郵便番号を選択するだけで既定値として自動反映される
C5: 国/地域 | D5: 郵便番号 | E5: 都道府県 | F5: 市区郡 | G5: 市町村 | H5: 地区 | I5: 住所 | J5: 開始日 | K5: 終了 | L5: すべて/偶数/奇数 | M5: タイムゾーン
C6: （ユーザー定義） | D6: （ユーザー定義） | E6: （ユーザー定義） | F6: （ユーザー定義） | G6: （ユーザー定義） | H6: （ユーザー定義） | I6: 文字列 | J6: 数値 | K6: 数値
C7: 必須 | D7: 必須
B8: =ROW() - 7 -> 1
B9: =ROW() - 7 -> 2
B10: =ROW() - 7 -> 3

Sheet 単位
A1: 単位
B2: 組織管理＞設定＞単位＞単位
B3: Organization administration > Setup > Units > Units
A4: パラメータ設定一覧へ
B5: # | C5: タブ | D5: タブ説明 | E5: 項目分類 | F5: 項目 | G5: 項目説明 | H5: 設定可能値 | I5: デフォルト値 | J5: 備考 | K5: 設定値 | L5: 設定基準
B6: =ROW() - 5 -> 1 | C6: 概要 | E6: 単位 | F6: 単位 | H6: 文字列 | I6: ー | K6: 「単位-設定値」を参照
B7: =ROW() - 5 -> 2 | F7: 説明 | H7: 文字列 | I7: ー | K7: 「単位-設定値」を参照
B8: =ROW() - 5 -> 3 | C8: 一般 | E8: 割り当て | F8: 固定単位の割り当て | H8: はい/いいえ | I8: いいえ | K8: 「単位-設定値」を参照
B9: =ROW() - 5 -> 4 | F9: 固定単位 | H9: ・個 ・フィート ・インチ ・ヤード ・センチメートル ・メートル ・ミリメートル ･ガロン ･リットル ・オンス ・トロイオンス ・ポンド ・グラム ・キログラム ・ミリ秒 ・秒 ・分 ・時間 ・日数 ・週 ・月数 ・年 ・Metric tons | I9: 個 | J9: [固定単位の割り当て]を[はい]にすることで設定可能 | K9: 「単位-設定値」を参照
B10: =ROW() - 5 -> 5 | E10: 分類 | F10: 単位クラス | H10: ・数量 ・長さ ・面積 ・液体体積 ・乾燥体積 ・質量 ・時刻 ・金銭情報 ・温度 ・情報エントロピー ・輝度 ・速度 ・加速度 ・角度 ・立体角 ・強制適用 ・抑圧または機械的ストレス ・トルク ・エネルギー ・パワー ・角運動量 ・静電容量 ・密度 ・電流 ・磁場 ・磁束 ・電荷 ・双極子 ・電位差 ・電気抵抗 ・インダクタンス ・動粘性係数 ・動粘性率 ・放射能 ・未定義 | I10: 数量 | K10: 「単位-設定値」を参照
B11: =ROW() - 5 -> 6 | F11: 単位系 | H11: ・なし ・メートル法 ・米国の慣例的単位 | I11: なし | K11: 「単位-設定値」を参照
B12: =ROW() - 5 -> 7 | E12: ロール | F12: 基本分類 | H12: はい/いいえ | I12: いいえ | K12: 「単位-設定値」を参照
B13: =ROW() - 5 -> 8 | F13: システム単位 | H13: はい/いいえ | I13: いいえ | K13: 「単位-設定値」を参照
B14: =ROW() - 4 -> 10 | E14: 丸め | F14: 小数点以下の制度 | H14: 数値 | I14: 0 | K14: 「単位-設定値」を参照
B15: =ROW() - 4 -> 11 | E15: RUSSIAN CLASSIFIERS | F15: Code by OKEI | H15: 文字列 | I15: ー | K15: 「単位-設定値」を参照
B16: =ROW() - 4 -> 12 | C16: 電子請求書 | F16: SAT code | G16: External classification code | H16: 文字列（ユーザー定義） | I16: ー | K16: 「単位-設定値」を参照
B17: =ROW() - 4 -> 13 | F17: SAT customs unit of measure | G17: External classification code | H17: 文字列（ユーザー定義） | I17: ー | K17: 「単位-設定値」を参照

Sheet 単位-設定値
A1: 単位-設定値 ※基本的には移行データを正とする
A2: ■凡例「必須：システム上必須」「必須(*)：システムで必須ではないが、トランザクション上や業務などで必須」
A3: パラメータ設定一覧へ | G3: 変更不可
B4: # | C4: 概要 | E4: 一般 | M4: 電子請求書
C5: 単位 | E5: 割り当て | G5: 分類 | I5: ロール | J5: 追加 | K5: 丸め | L5: RUSSIAN CLASSIFIERS
C6: 単位 | D6: 説明 | E6: 固定単位の割り当て | F6: 固定単位 | G6: 単位クラス | H6: 単位系 | I6: 基本単位系 | J6: システム単位 | K6: 小数点以下の精度 | L6: Code by OKEI | M6: SAT code | N6: SAT customs unit of measure
C7: 文字列 | D7: 文字列 | E7: はい/いいえ | I7: はい/いいえ | J7: はい/いいえ | K7: 数値 | L7: 文字列 | M7: 文字列（ユーザー定義） | N7: 文字列（ユーザー定義）
C8: 必須
B9: =ROW() - 8 -> 1
B10: =ROW() - 8 -> 2
B11: =ROW() - 8 -> 3 | C11: ↓自動生成
B12: =ROW() - 8 -> 4 | C12: ㎏ | E12: いいえ | F12: 個 | G12: 質量 | H12: なし | I12: いいえ | J12: いいえ | K12: 0 | L12: ー | M12: ー | N12: ー
B13: =ROW() - 8 -> 5 | C13: m | E13: いいえ | F13: 個 | G13: 長さ | H13: なし | I13: いいえ | J13: いいえ | K13: 0 | L13: ー | M13: ー | N13: ー
B14: =ROW() - 8 -> 6 | C14: ㎡ | E14: いいえ | F14: 個 | G14: 面積 | H14: なし | I14: いいえ | J14: いいえ | K14: 0 | L14: ー | M14: ー | N14: ー
B15: =ROW() - 8 -> 7 | C15: ｾｯﾄ | E15: いいえ | F15: 個 | G15: 数量 | H15: なし | I15: いいえ | J15: いいえ | K15: 0 | L15: ー | M15: ー | N15: ー
B16: =ROW() - 8 -> 8 | C16: 個 | E16: いいえ | F16: 個 | G16: 数量 | H16: なし | I16: いいえ | J16: いいえ | K16: 0 | L16: ー | M16: ー | N16: ー
B17: =ROW() - 8 -> 9 | C17: 冊 | E17: いいえ | F17: 個 | G17: 数量 | H17: なし | I17: いいえ | J17: いいえ | K17: 0 | L17: ー | M17: ー | N17: ー
B18: =ROW() - 8 -> 10 | C18: 台 | E18: いいえ | F18: 個 | G18: 数量 | H18: なし | I18: いいえ | J18: いいえ | K18: 0 | L18: ー | M18: ー | N18: ー
B19: =ROW() - 8 -> 11 | C19: 巻 | E19: いいえ | F19: 個 | G19: 数量 | H19: なし | I19: いいえ | J19: いいえ | K19: 0 | L19: ー | M19: ー | N19: ー
B20: =ROW() - 8 -> 12 | C20: 式 | E20: いいえ | F20: 個 | G20: 数量 | H20: なし | I20: いいえ | J20: いいえ | K20: 0 | L20: ー | M20: ー | N20: ー
B21: =ROW() - 8 -> 13 | C21: 本 | E21: いいえ | F21: 個 | G21: 数量 | H21: なし | I21: いいえ | J21: いいえ | K21: 0 | L21: ー | M21: ー | N21: ー
B22: =ROW() - 8 -> 14 | C22: 枚 | E22: いいえ | F22: 個 | G22: 数量 | H22: なし | I22: いいえ | J22: いいえ | K22: 0 | L22: ー | M22: ー | N22: ー
B23: =ROW() - 8 -> 15 | C23: 箱 | E23: いいえ | F23: 個 | G23: 数量 | H23: なし | I23: いいえ | J23: いいえ | K23: 0 | L23: ー | M23: ー | N23: ー
... B26: =ROW() - 8 -> 18 | C26: 足 | E26: いいえ | F26: 個 | G26: 数量 | H26: なし | I26: いいえ | J26: いいえ | K26: 1 | L26: ー | M26: ー | N26: ー

Sheet 単位換算
A1: 単位換算
B2: 組織管理＞設定＞単位＞単位換算
B3: Organization administration > Setup > Units > Unit conversions
A4: パラメータ設定一覧へ
B5: # | C5: タブ | D5: タブ説明 | E5: 項目分類 | F5: 項目 | G5: 項目説明 | H5: 設定可能値 | I5: デフォルト値 | J5: 備考 | K5: 設定値 | L5: 設定基準
B6: =ROW() - 5 -> 1 | C6: 標準単位換算 | D6: すべての製品に対する標準変換ルールの設定 | F6: 定義 | H6: システム自動入力 | I6: ー | K6: 「標準換算-設定値」を参照
B7: =ROW() - 5 -> 2 | F7: （開始単位の数値） | H7: 数値（必ず1） | I7: 1 | K7: 「標準換算-設定値」を参照
B8: =ROW() - 5 -> 3 | F8: 開始単位 | H8: 単位（ユーザー定義） | I8: ー | K8: 「標準換算-設定値」を参照
F9: （終了単位の数値） | H9: 数値 | I9: 1.0000000000 | J9: 開始単位の数値１に対してどう換算するかを入力する | K9: 「標準換算-設定値」を参照
B10: =ROW() - 5 -> 5 | F10: 終了単位 | H10: 単位（ユーザー定義） | I10: ー | K10: 「標準換算-設定値」を参照
B11: =ROW() - 5 -> 6 | F11: 丸め | H11: ・四捨五入 ・切り上げ ・切り捨て | I11: 四捨五入 | K11: 「標準換算-設定値」を参照
B12: =ROW() - 5 -> 7 | F12: 式のレイアウト | H12: ・簡易 ・詳細 | I12: 簡易 | K12: 「標準換算-設定値」を参照
B13: =ROW() - 5 -> 8 | C13: クラス内換算 | D13: 同一単位クラス内の測定単位に対して製品固有の変換ルールを設定します | F13: 製品 | H13: 製品（ユーザー定義） | I13: ー | K13: 「クラス内換算-設定値」を参照
B14: =ROW() - 5 -> 9 | F14: 定義 | H14: システム自動入力 | I14: ー | K14: 「クラス内換算-設定値」を参照
B15: =ROW() - 5 -> 10 | F15: （開始単位の数値） | H15: 数値（必ず1） | I15: 1 | K15: 「クラス内換算-設定値」を参照
B16: =ROW() - 5 -> 11 | F16: 開始単位 | H16: 単位（ユーザー定義） | I16: ー | K16: 「クラス内換算-設定値」を参照
B17: =ROW() - 5 -> 12 | F17: （終了単位の数値） | H17: 数値 | I17: 1.0000000000 | J17: 開始単位の数値１に対してどう換算するかを入力する | K17: 「クラス内換算-設定値」を参照
B18: =ROW() - 5 -> 13 | F18: 終了単位 | H18: 単位（ユーザー定義） | I18: ー | K18: 「クラス内換算-設定値」を参照
B19: =ROW() - 5 -> 14 | F19: 丸め | H19: ・四捨五入 ・切り上げ ・切り捨て | I19: 四捨五入 | K19: 「クラス内換算-設定値」を参照
B20: =ROW() - 5 -> 15 | F20: 式のレイアウト | H20: ・簡易 ・詳細 | I20: 簡易 | K20: 「クラス内換算-設定値」を参照
B21: =ROW() - 5 -> 16 | C21: クラス間換算 | D21: 単位クラスが含む測定単位に対して製品固有の変換ルールを設定する | F21: 製品 | H21: 製品（ユーザー定義） | I21: ー | K21: 「クラス間換算-設定値」を参照
B22: =ROW() - 5 -> 17 | F22: 定義 | H22: システム自動入力 | I22: ー | K22: 「クラス間換算-設定値」を参照
B23: =ROW() - 5 -> 18 | F23: （開始単位の数値） | H23: 数値（必ず1） | I23: 1 | K23: 「クラス間換算-設定値」を参照
B24: =ROW() - 5 -> 19 | F24: 開始単位 | H24: 単位（ユーザー定義） | I24: ー | K24: 「クラス間換算-設定値」を参照
B25: =ROW() - 5 -> 20 | F25: （終了単位の数値） | H25: 数値 | I25: 1.0000000000 | J25: 開始単位の数値１に対してどう換算するかを入力する | K25: 「クラス間換算-設定値」を参照
B26: =ROW() - 5 -> 21 | F26: 終了単位 | H26: 単位（ユーザー定義） | I26: ー | K26: 「クラス間換算-設定値」を参照
B27: =ROW() - 5 -> 22 | F27: 終了単位 | H27: 単位（ユーザー定義） | I27: ー | K27: 「クラス間換算-設定値」を参照
B28: =ROW() - 5 -> 23 | F28: 式のレイアウト | H28: ・簡易 ・詳細 | I28: 簡易 | K28: 「クラス間換算-設定値」を参照

Sheet 標準換算-設定値
A1: 標準換算-設定値 ※基本的には移行データを正とする
A2: ■凡例「必須：システム上必須」「必須(*)：システムで必須ではないが、トランザクション上や業務などで必須」
A3: パラメータ設定一覧へ
B4: # | C4: 定義 | D4: （終了単位の数値） | E4: 開始単位 | F4: （終了単位の数値） | G4: 終了単位 | H4: 丸め | I4: 式のレイアウト
C5: （システム自動入力） | D5: 数値（必ず1） | E5: 単位（ユーザー定義） | F5: 数値 | G5: 単位（ユーザー定義） | H5: 四捨五入 切り上げ 切り捨て | I5: 簡易 詳細
C6: ※Excel上関数で反映 | D6: 必須 | E6: 必須 | F6: 必須 | G6: 必須 | H6: 必須 | I6: 必須
B7: 例 | C7: =D7&E7&"="&F7&G7 -> 1箱=12個 | D7: 1 | E7: 箱 | F7: 12 | G7: 個 | H7: 四捨五入 | I7: 簡易
B8: =ROW() - 7 -> 1 | C8: =D8&E8&"="&F8&G8 -> 1= | D8: 1
B9: =ROW() - 7 -> 2 | C9: =D9&E9&"="&F9&G9 -> 1= | D9: 1
B10: =ROW() - 7 -> 3 | C10: =D10&E10&"="&F10&G10 -> 1= | D10: 1
B11: =ROW() - 7 -> 4 | C11: =D11&E11&"="&F11&G11 -> 1= | D11: 1
B12: =ROW() - 7 -> 5 | C12: =D12&E12&"="&F12&G12 -> 1= | D12: 1
B13: =ROW() - 7 -> 6 | C13: =D13&E13&"="&F13&G13 -> 1= | D13: 1
B14: =ROW() - 7 -> 7 | C14: =D14&E14&"="&F14&G14 -> 1= | D14: 1
B15: =ROW() - 7 -> 8 | C15: =D15&E15&"="&F15&G15 -> 1= | D15: 1
B16: =ROW() - 7 -> 9 | C16: =D16&E16&"="&F16&G16 -> 1= | D16: 1
B17: =ROW() - 7 -> 10 | C17: =D17&E17&"="&F17&G17 -> 1= | D17: 1
B18: =ROW() - 7 -> 11 | C18: =D18&E18&"="&F18&G18 -> 1= | D18: 1
B19: =ROW() - 7 -> 12 | C19: =D19&E19&"="&F19&G19 -> 1= | D19: 1
... B27: =ROW() - 7 -> 20 | C27: =D27&E27&"="&F27&G27 -> 1= | D27: 1

Sheet クラス内換算-設定値
A1: クラス内換算-設定値 ※基本的には移行データを正とする
A2: ■凡例「必須：システム上必須」「必須(*)：システムで必須ではないが、トランザクション上や業務などで必須」
A3: パラメータ設定一覧へ
B4: # | C4: 製品 | D4: 定義 | E4: （開始単位の数値） | F4: 開始単位 | G4: （終了単位の数値） | H4: 終了単位 | I4: 式のレイアウト | J4: 丸め
C5: 製品（ユーザー定義） ※製品番号が入る | D5: （システム自動入力） | E5: 数値（必ず1） | F5: 単位（ユーザー定義） | G5: 数値 | H5: 単位（ユーザー定義） | I5: 簡易 詳細 | J5: 四捨五入 切り上げ 切り捨て
C6: 必須 | D6: ※Excel上関数で反映 | E6: 必須 | F6: 必須 | G6: 必須 | H6: 必須 | I6: 必須 | J6: 必須
B7: 例 | C7: TEST_Prod-001 | D7: =E7&F7&"="&G7&H7 -> 1箱=12個 | E7: 1 | F7: 箱 | G7: 12 | H7: 個 | I7: 簡易 | J7: 四捨五入
B8: =ROW() - 7 -> 1 | D8: =E8&F8&"="&G8&H8 -> 1= | E8: 1
B9: =ROW() - 7 -> 2 | D9: =E9&F9&"="&G9&H9 -> 1= | E9: 1
B10: =ROW() - 7 -> 3 | D10: =E10&F10&"="&G10&H10 -> 1= | E10: 1
B11: =ROW() - 7 -> 4 | D11: =E11&F11&"="&G11&H11 -> 1= | E11: 1
B12: =ROW() - 7 -> 5 | D12: =E12&F12&"="&G12&H12 -> 1= | E12: 1
B13: =ROW() - 7 -> 6 | D13: =E13&F13&"="&G13&H13 -> 1= | E13: 1
B14: =ROW() - 7 -> 7 | D14: =E14&F14&"="&G14&H14 -> 1= | E14: 1
B15: =ROW() - 7 -> 8 | D15: =E15&F15&"="&G15&H15 -> 1= | E15: 1
B16: =ROW() - 7 -> 9 | D16: =E16&F16&"="&G16&H16 -> 1= | E16: 1
B17: =ROW() - 7 -> 10 | D17: =E17&F17&"="&G17&H17 -> 1= | E17: 1
B18: =ROW() - 7 -> 11 | D18: =E18&F18&"="&G18&H18 -> 1= | E18: 1
B19: =ROW() - 7 -> 12 | D19: =E19&F19&"="&G19&H19 -> 1= | E19: 1
... B27: =ROW() - 7 -> 20 | D27: =E27&F27&"="&G27&H27 -> 1= | E27: 1

Sheet クラス間換算-設定値
A1: クラス間換算-設定値 ※基本的には移行データを正とする
A2: ■凡例「必須：システム上必須」「必須(*)：システムで必須ではないが、トランザクション上や業務などで必須」
A3: パラメータ設定一覧へ
B4: # | C4: 製品 | D4: 定義 | E4: （開始単位の数値） | F4: 開始単位 | G4: （終了単位の数値） | H4: 終了単位 | I4: 式のレイアウト | J4: 丸め
C5: 製品（ユーザー定義） ※製品番号が入る | D5: （システム自動入力） | E5: 数値（必ず1） | F5: 単位（ユーザー定義） | G5: 数値 | H5: 単位（ユーザー定義） | I5: 簡易 詳細 | J5: 四捨五入 切り上げ 切り捨て
C6: 必須 | D6: ※Excel上関数で反映 | E6: 必須 | F6: 必須 | G6: 必須 | H6: 必須 | I6: 必須 | J6: 必須
B7: 例 | C7: TEST_Prod-001 | D7: =E7&F7&"="&G7&H7 -> 1箱=12個 | E7: 1 | F7: 箱 | G7: 12 | H7: 個 | I7: 簡易 | J7: 四捨五入
B8: =ROW() - 7 -> 1 | D8: =E8&F8&"="&G8&H8 -> 1= | E8: 1
B9: =ROW() - 7 -> 2 | D9: =E9&F9&"="&G9&H9 -> 1= | E9: 1
B10: =ROW() - 7 -> 3 | D10: =E10&F10&"="&G10&H10 -> 1= | E10: 1
B11: =ROW() - 7 -> 4 | D11: =E11&F11&"="&G11&H11 -> 1= | E11: 1
B12: =ROW() - 7 -> 5 | D12: =E12&F12&"="&G12&H12 -> 1= | E12: 1
B13: =ROW() - 7 -> 6 | D13: =E13&F13&"="&G13&H13 -> 1= | E13: 1
B14: =ROW() - 7 -> 7 | D14: =E14&F14&"="&G14&H14 -> 1= | E14: 1
B15: =ROW() - 7 -> 8 | D15: =E15&F15&"="&G15&H15 -> 1= | E15: 1
B16: =ROW() - 7 -> 9 | D16: =E16&F16&"="&G16&H16 -> 1= | E16: 1
B17: =ROW() - 7 -> 10 | D17: =E17&F17&"="&G17&H17 -> 1= | E17: 1
B18: =ROW() - 7 -> 11 | D18: =E18&F18&"="&G18&H18 -> 1= | E18: 1
B19: =ROW() - 7 -> 12 | D19: =E19&F19&"="&G19&H19 -> 1= | E19: 1
... B27: =ROW() - 7 -> 20 | D27: =E27&F27&"="&G27&H27 -> 1= | E27: 1

Sheet ユーザーをロールに割り当てる
A1: ユーザーをロールに割り当てる
B2: システム管理＞セキュリティ＞ユーザーをロールに割り当てる
B3: System administration > Security > Assign users to roles
A4: パラメータ設定一覧へ
B5: # | C5: タブ | D5: タブ説明 | E5: 項目分類 | F5: 項目 | G5: 項目説明 | H5: 設定可能値 | I5: デフォルト値 | J5: 備考 | K5: 設定値 | L5: 設定基準
B6: =ROW() - 5 -> 1 | C6: ユーザーをロールに割り当てる | D6: ロールへのユーザーの動的割り当てルール | F6: メンバーシップ ルール名 | G6: 自動ロールメンバーシップルールの名前 | I6: ー | K6: 「ロールへのユーザーの動的割り当てのルール-設定値」を参照
B7: =ROW() - 5 -> 2 | F7: メンバーシップ ルールの説明 | G7: 自動ロールメンバーシップルールの説明 | I7: ー | K7: 「ロールへのユーザーの動的割り当てのルール-設定値」を参照
B8: =ROW() - 5 -> 3 | F8: クエリプレビュー | G8: ロール自動割り当てルールの基準として使用されるクエリを表示します。 | I8: ー | K8: 「ロールへのユーザーの動的割り当てのルール-設定値」を参照
B9: =ROW() - 5 -> 4 | D9: ロールに割り当てられたユーザー | F9: ID | G9: ユーザーID | I9: ー | K9: ユーザー側の設定に準ずる
B10: =ROW() - 5 -> 5 | F10: ユーザー名 | G10: 名前 | I10: ー | K10: ユーザー側の設定に準ずる
B11: =ROW() - 5 -> 6 | F11: エイリアス | I11: ー | K11: ユーザー側の設定に準ずる
B12: =ROW() - 5 -> 7 | F12: 割り当てモード | I12: ー | K12: ユーザー側の設定に準ずる

Sheet ロールへのユーザーの動的割り当てのルール-設定値
A1: ロールへのユーザーの動的割り当てのルール-設定値 ※基本的には移行データを正とする
A2: ■凡例「必須：システム上必須」「必須(*)：システムで必須ではないが、トランザクション上や業務などで必須」
A3: パラメータ設定一覧へ
B4: # | C4: ロール名 | D4: メンバーシップ ルール名 | E4: メンバーシップ ルールの説明 | F4: クエリプレビュー
C5: （システム自動入力） | D5: （システム自動入力） | E5: 単位（ユーザー定義） | F5: 単位（ユーザー定義）
B6: =ROW() - 5 -> 1
B7: =ROW() - 5 -> 2
B8: =ROW() - 5 -> 3
B9: =ROW() - 5 -> 4
B10: =ROW() - 5 -> 5
B11: =ROW() - 5 -> 6
B12: =ROW() - 5 -> 7
B13: =ROW() - 5 -> 8
B14: =ROW() - 5 -> 9
B15: =ROW() - 5 -> 10
B16: =ROW() - 5 -> 11
B17: =ROW() - 5 -> 12
... B23: =ROW() - 5 -> 18

Sheet ユーザーIDへの作業者の割当
A1: ユーザーIDへの作業者の割当
B2: システム管理＞ユーザー＞ユーザー
B3: System administration > Users > Users
A4: パラメータ設定一覧へ
B5: # | C5: タブ | D5: タブ説明 | E5: 項目分類 | F5: 項目 | G5: 項目説明 | H5: 設定可能値 | I5: デフォルト値 | J5: 備考 | K5: 設定値 | L5: 設定基準
B6: =ROW() - 5 -> 1 | C6: ユーザー | D6: ユーザーの詳細 | F6: ユーザーID | G6: ユーザーID | H6: AADとの連携が必要 | I6: ー | K6: 「ユーザーIDへの作業者の割当-設定値」を参照
B7: =ROW() - 5 -> 2 | F7: ユーザー名 | G7: 名前 | H7: AADとの連携が必要 | I7: ー | K7: 「ユーザーIDへの作業者の割当-設定値」を参照
B8: =ROW() - 5 -> 3 | F8: プロバイダー | I8: ー | K8: 「ユーザーIDへの作業者の割当-設定値」を参照
B9: =ROW() - 5 -> 4 | F9: 電子メール | G9: ユーザーの電子メールアドレス | H9: AADとの連携が必要 | I9: ー | K9: 「ユーザーIDへの作業者の割当-設定値」を参照
B10: =ROW() - 5 -> 5 | F10: テレメトリID | I10: ー | K10: 「ユーザーIDへの作業者の割当-設定値」を参照
B11: =ROW() - 5 -> 6 | F11: 会社 | G11: 選択可能な会社ID（ログイン時のデフォルトの会社ID） | I11: ー | K11: 「ユーザーIDへの作業者の割当-設定値」を参照
B12: =ROW() - 5 -> 7 | F12: 個人 | G12: 従業員（作業者）の割り当て | I12: ー | K12: 「ユーザーIDへの作業者の割当-設定値」を参照
B13: =ROW() - 5 -> 8 | F13: 有効 | G13: FOユーザーとしての有効/無効 | I13: ー | K13: 「ユーザーIDへの作業者の割当-設定値」を参照
B14: =ROW() - 5 -> 9 | D14: ユーザーのロール | F14: ロール | G14: ユーザーに対しての割り当てロール | I14: ー | K14: ユーザー側の設定に準ずる

Sheet ユーザーIDへの作業者の割当-設定値
A1: ユーザーIDへの作業者の割当-設定値 ※基本的には移行データを正とする
A2: ■凡例「必須：システム上必須」「必須(*)：システムで必須ではないが、トランザクション上や業務などで必須」
A3: パラメータ設定一覧へ
B4: # | C4: ユーザーID | D4: ユーザー名 | E4: プロバイダー | F4: 電子メール | G4: テレメトリID | H4: 会社 | I4: 個人 | J4: 有効 | K4: ロール
C5: AADとの連携が必要 ※ユーザーインポート実施時はシステム自動入力 | D5: AADとの連携が必要 ※ユーザーインポート実施時はシステム自動入力 | F5: 単位（ユーザー定義） | G5: （システム自動入力） | H5: ログイン時のデフォルトの会社IDを選択 | I5: 従業員（作業者）マスタから選択 | J5: はい/いいえ | K5: 必要ロールを複数設定
C6: 必須 | D6: 必須 | F6: 必須 | H6: 必須(*) | I6: 必須(*) | J6: 必須 | K6: 必須(*)
B7: 例 | C7: jbsuser001 | D7: JBS User001 | E7: https://sts.windows.net/jbs.com/ | H7: JPMF | J7: はい | K7: システムユーザー システム管理者
B8: =ROW() - 7 -> 1
B9: =ROW() - 7 -> 2
B10: =ROW() - 7 -> 3
B11: =ROW() - 7 -> 4
B12: =ROW() - 7 -> 5
B13: =ROW() - 7 -> 6
B14: =ROW() - 7 -> 7
B15: =ROW() - 7 -> 8
B16: =ROW() - 7 -> 9
B17: =ROW() - 7 -> 10
B18: =ROW() - 7 -> 11
B19: =ROW() - 7 -> 12
... B27: =ROW() - 7 -> 20

Sheet ユーザーグループ
A1: ユーザーグループ ※基本的には移行データを正とする
B2: システム管理＞ユーザー＞ユーザーグループ
B3: System administration > User > User Group
A4: パラメータ設定一覧へ
B5: # | C5: タブ | D5: タブ説明 | E5: 項目分類 | F5: 項目 | G5: Description（標準） | H5: 設定可能値 | I5: デフォルト値 | J5: 備考 | K5: 設定値 | L5: 設定基準
B6: =ROW() - 5 -> 1 | C6: グループ | F6: グループ | H6: 文字列 | I6: - | K6: 「ユーザーグループ-設定値」を参照
B7: =ROW() - 5 -> 2 | F7: ユーザーグループ名 | H7: 文字列 | I7: - | K7: 「ユーザーグループ-設定値」を参照
B8: =ROW() - 5 -> 3 | C8: ユーザー | F8: 選択したユーザー | H8: ユーザー（ユーザー定義） | I8: - | K8: 「ユーザーグループ-設定値」を参照

Sheet ユーザーグループ-設定値
A1: ユーザーグループ-設定値 ※基本的には移行データを正とする
A2: ■凡例「必須：システム上必須」「必須(*)：システムで必須ではないが、トランザクション上や業務などで必須」
A3: パラメータ設定一覧へ
B4: # | C4: グループ | E4: ユーザー
C5: グループ | D5: ユーザーグループ名 | E5: 選択したユーザー
C6: 文字列 | D6: 文字列 | E6: ユーザー（ユーザー定義）
C7: 必須(*) | D7: 必須(*)
B8: 例 | C8: ワークフロー承認者 | D8: ワークフロー承認者用グループ | E8: jbsuser001
E9: jbsuser002
B10: 1
B14: 2
B18: 3
B22: 4
B26: 5

Sheet 通貨の為替レート
A1: 通貨の為替レート
B2: 一般会計＞通貨＞通貨の為替レート
B3: General ledger > Currencies > Currency exchange rates
A4: パラメータ設定一覧へ
B5: # | C5: タブ | D5: タブ説明 | E5: 項目分類 | F5: 項目 | G5: 項目説明 | H5: 設定可能値 | I5: デフォルト値 | J5: 備考 | K5: 設定値 | L5: 設定基準
B6: =ROW() - 5 -> 1 | C6: 通貨の為替レート | F6: 為替レートタイプ | G6: 通貨の為替レートは為替レートの種類を選択します。 | H6: ・予算 ・平均 ・既定 ・終了 | I6: 既定 | J6: 為替レートタイプ（システム定義） ・予算：既定の予算レート ・平均：既定の平均レート ・既定：既定のグローバルレート ・終了：既定の終了レート | K6: 「通貨の為替レート-設定値」を参照
B7: =ROW() - 5 -> 2 | F7: 交換前通貨 | G7: 変換する通貨を選択します。 | H7: 通貨（ユーザー定義） | I7: ー | K7: 「通貨の為替レート-設定値」を参照
B8: =ROW() - 5 -> 3 | F8: 交換後通貨 | G8: 変換する通貨を選択します | H8: 通貨（ユーザー定義） | I8: ー | K8: 「通貨の為替レート-設定値」を参照
B9: =ROW() - 5 -> 4 | F9: 変換係数 | G9: 為替レートのベースとなる他の通貨の単位数を選択します。値は、会計通貨として選択される通貨の通常の規則によって異なります。 | H9: ・1 ・10 ・100 ・1000 ・10000 | I9: 1 | K9: 「通貨の為替レート-設定値」を参照
B10: =ROW() - 5 -> 5 | C10: 為替レートの追加または削除 | F10: 開始日 | G10: 開始日を選択して、グリッドに為替レートを表示します。 | H10: 年月日(yyyy/MM/dd) | I10: 作業日に応じて入る | J10: 参照時のための日付切り替えの機能 | K10: 「通貨の為替レート-設定値」を参照
B11: =ROW() - 5 -> 6 | F11: 終了日 | G11: 終了日を選択して、為替レートをグリッドに表示します。 | H11: 年月日(yyyy/MM/dd) | I11: 作業日に応じて入る | J11: 参照時のための日付切り替えの機能 | K11: 「通貨の為替レート-設定値」を参照
B12: =ROW() - 5 -> 7 | F12: 開始日 | G12: このレコードの有効開始日。 | H12: 年月日(yyyy/MM/dd) | I12: ー | K12: 「通貨の為替レート-設定値」を参照
B13: =ROW() - 5 -> 8 | F13: 為替レート | G13: 現在の為替レートが有効な開始日を選択します。 | H13: 数値 | I13: ー | K13: 「通貨の為替レート-設定値」を参照
B14: =ROW() - 5 -> 9 | F14: 交換価値 | G14: 開始通貨と終了通貨フィールドに表示される通貨の為替レートを入力します。 | H14: システム入力（交換前通貨、交換後通貨、変換係数、為替レートを入力すると自動で反映される） | I14: ー | J14: 例： 交換前通貨：USD 交換後通貨：JPY 変換係数：1 為替レート：109.6100 交換価値：109.61 JPY (1 USD) | K14: 「通貨の為替レート-設定値」を参照

Sheet 通貨の為替レート-設定値
A1: 通貨の為替レート-設定値 ※基本的には移行データを正とする
A2: ■凡例「必須：システム上必須」「必須(*)：システムで必須ではないが、トランザクション上や業務などで必須」
A3: パラメータ設定一覧へ
B4: # | C4: 通貨の為替レート | G4: 為替レートの追加または削除
C5: 為替レートタイプ | D5: 交換前通貨 | E5: 交換後通貨 | F5: 変換係数 | G5: 開始日 | H5: 為替レート | I5: 交換価値
C6: 予算 平均 既定 終了 | D6: 通貨（ユーザー定義） | E6: 通貨（ユーザー定義） | G6: 年月日(yyyy/MM/dd) | H6: 数値 | I6: システム入力（交換前通貨、交換後通貨、変換係数、為替レートを入力すると自動で反映される）
C7: 必須 | D7: 必須 | G7: 必須(*) | H7: 必須 | I7: ※Excel上関数で反映
B8: 例 | C8: 既定 | D8: JPY | E8: USD | F8: 100 | G8: 45017 | H8: 1 | I8: =H8&E8&"（"&D8&F8&"）" -> 1USD（JPY100）
B9: =ROW() - 8 -> 1 | I9: =H9&E9&"（"&D9&F9&"）" -> （）
B10: =ROW() - 8 -> 2 | I10: =H10&E10&"（"&D10&F10&"）" -> （）
B11: =ROW() - 8 -> 3 | I11: =H11&E11&"（"&D11&F11&"）" -> （）
B12: =ROW() - 8 -> 4 | I12: =H12&E12&"（"&D12&F12&"）" -> （）
B13: =ROW() - 8 -> 5 | I13: =H13&E13&"（"&D13&F13&"）" -> （）
B14: =ROW() - 8 -> 6 | I14: =H14&E14&"（"&D14&F14&"）" -> （）
B15: =ROW() - 8 -> 7 | I15: =H15&E15&"（"&D15&F15&"）" -> （）
B16: =ROW() - 8 -> 8 | I16: =H16&E16&"（"&D16&F16&"）" -> （）
B17: =ROW() - 8 -> 9 | I17: =H17&E17&"（"&D17&F17&"）" -> （）
B18: =ROW() - 8 -> 10 | I18: =H18&E18&"（"&D18&F18&"）" -> （）

Sheet 顧客の価格割引グループ
A1: 顧客の価格/割引グループ
B2: 販売とマーケティング ＞ 価格と割引 > 顧客の価格/割引グループ
B3: Sales and marketing > Prices and discounts > Customer price/discount groups
A4: パラメータ設定一覧へ
B5: # | C5: タブ | D5: タブ説明 | E5: 項目分類 | F5: 項目 | G5: Description（標準） | H5: 設定可能値 | I5: デフォルト値 | J5: 備考 | K5: 設定値 | L5: 設定基準
B6: =ROW() - 5 -> 1 | C6: 顧客の価格/割引グループ | F6: 価格グループ | H6: 文字列 | I6: ー | K6: シート「顧客の価格割引グループ-設定値」を参照
B7: =ROW() - 5 -> 2 | F7: 名前 | H7: 文字列 | I7: ー | K7: シート「顧客の価格割引グループ-設定値」を参照
B8: =ROW() - 5 -> 3 | F8: 価格/割引グループ タイプ | H8: 価格グループ 行割引グループ 複数行割引グループ 割引合計グループ | I8: 価格グループ | K8: シート「顧客の価格割引グループ-設定値」を参照

Sheet 顧客の価格割引グループ-設定値
A1: 顧客の価格/割引グループ-設定値 ※基本的には移行データを正とする
A2: ■凡例「必須：システム上必須」「必須(*)：システムで必須ではないが、トランザクション上や業務などで必須」
A3: パラメータ設定一覧へ
B4: # | C4: 顧客の価格/割引グループ
C5: 割引グループ | D5: 名前 | E5: 価格/割引グループ タイプ
C6: 文字列 | D6: 文字列 | E6: 価格グループ 行割引グループ 複数行割引グループ 割引合計グループ
C7: 必須 | E7: 必須
B8: =ROW() - 7 -> 1
B9: =ROW() - 7 -> 2
B10: =ROW() - 7 -> 3
B11: =ROW() - 7 -> 4
B12: =ROW() - 7 -> 5
B13: =ROW() - 7 -> 6
B14: =ROW() - 7 -> 7

Sheet 売買契約仕訳帳名（販売）
A1: 売買契約仕訳帳名（販売）
B2: 販売とマーケティング ＞ 設定 > 価格と割引 ＞ 売買契約仕訳帳名
B3: Sales and marketing> Setup > Prices and discounts > Trade agreement journal names
A4: パラメータ設定一覧へ
B5: # | C5: タブ | D5: タブ説明 | E5: 項目分類 | F5: 項目 | G5: Description（標準） | H5: 設定可能値 | I5: デフォルト値 | J5: 備考 | K5: 設定値 | L5: 設定基準
B6: =ROW() - 5 -> 1 | C6: 売買契約仕訳帳名 | F6: 名前 | H6: 文字列 | I6: ー | K6: シート「売買契約仕訳帳名-設定値」を参照
B7: =ROW() - 5 -> 2 | F7: 説明 | H7: 文字列 | I7: ー | K7: シート「売買契約仕訳帳名-設定値」を参照
B8: =ROW() - 5 -> 3 | F8: 関係 | H8: 価格（購買） 行割引（仕入） 複数行割引（仕入） 割引合計（購買） 価格（販売） 行割引（販売側） 複数行割引（販売側） 割引合計（販売） 送料の割引 | I8: ー | K8: シート「売買契約仕訳帳名-設定値」を参照

Sheet 売買契約仕訳帳名-設定値（販売）
A1: 売買契約仕訳帳名（販売）-設定値
A2: ■凡例「必須：システム上必須」「必須(*)：システムで必須ではないが、トランザクション上や業務などで必須」
A3: パラメータ設定一覧へ
B4: # | C4: 売買契約仕訳帳名
C5: 名前 | D5: 説明 | E5: 関係
C6: 文字列 | D6: 文字列 | E6: 価格（購買） 行割引（仕入） 複数行割引（仕入） 割引合計（購買） 価格（販売） 行割引（販売側） 複数行割引（販売側） 割引合計（販売） 送料の割引
C7: 必須 | E7: 必須
B8: =ROW() - 7 -> 1
B9: =ROW() - 7 -> 2
B10: =ROW() - 7 -> 3
B11: =ROW() - 7 -> 4
B12: =ROW() - 7 -> 5
B13: =ROW() - 7 -> 6
B14: =ROW() - 7 -> 7

Sheet 売買契約仕訳帳（販売）
A1: 売買契約仕訳帳（販売）
B2: 販売とマーケティング ＞ 価格と割引 ＞ 売買契約仕訳帳名
B3: Sales and marketing> Prices and discounts > Trade agreement journal name
A4: パラメータ設定一覧へ
B5: # | C5: タブ | D5: タブ説明 | E5: 項目分類 | F5: 項目 | G5: Description（標準） | H5: 設定可能値 | I5: デフォルト値 | J5: 備考 | K5: 設定値 | L5: 設定基準
B6: =ROW() - 5 -> 1 | C6: 売買契約仕訳帳 | F6: 名前 | H6: 売買仕訳帳名（ユーザー定義） | I6: ー | K6: シート「売買契約仕訳帳-設定値（販売）」を参照
B7: =ROW() - 5 -> 2 | F7: 価格/割引仕訳帳番号 | H7: 自動採番 | I7: ー | J7: 番号順序の設定に準拠する | K7: シート「売買契約仕訳帳-設定値（販売）」を参照
B8: =ROW() - 5 -> 3 | F8: 説明 | H8: 文字列 | I8: ー | K8: シート「売買契約仕訳帳-設定値（販売）」を参照
B9: =ROW() - 5 -> 4 | F9: 転記済 | H9: チェック/チェック無 | I9: ー | J9: 転記したら自動で入る | K9: シート「売買契約仕訳帳-設定値（販売）」を参照
B10: =ROW() - 5 -> 5 | F10: 転記日 | H10: 日付 | I10: ー | J10: 転記したら自動で入る | K10: シート「売買契約仕訳帳-設定値（販売）」を参照
B11: =ROW() - 5 -> 6 | F11: 既定のリレーション | H11: 価格（購買） 行割引（仕入） 複数行割引（仕入） 割引合計（購買） 価格（販売） 行割引（販売側） 複数行割引（販売側） 割引合計（販売） 送料の割引 | I11: 「名前」で売買契約仕訳帳名を選択したら既定値が自動反映される | K11: シート「売買契約仕訳帳-設定値（販売）」を参照
B12: =ROW() - 5 -> 7 | F12: 現在の価格のエクスポート | H12: チェック/チェック無 | I12: チェック無 | K12: シート「売買契約仕訳帳-設定値（販売）」を参照
B13: =ROW() - 5 -> 8 | C13: 仕訳帳明細行 | E13: 概要 | F13: 変更済 | H13: （自動） | I13: ー | J13: 明細の変更によって自動で反映される | K13: シート「売買契約仕訳帳-設定値（販売）」を参照
B14: =ROW() - 5 -> 9 | F14: 関係 | G14: 購買および販売ドキュメントは売買契約を使用し、タイプに応じて価格または割引を適用します。特定の品目、特定の品目グループ、またはすべての品目に対して価格または割引を設定するために、売買契約の仕訳帳明細行を構成することができます。 | H14: 価格（購買） 行割引（仕入） 複数行割引（仕入） 割引合計（購買） 価格（販売） 行割引（販売側） 複数行割引（販売側） 割引合計（販売） 送料の割引 | I14: 「名前」で売買契約仕訳帳名を選択したら既定値が自動反映される | K14: シート「売買契約仕訳帳-設定値（販売）」を参照
B15: =ROW() - 5 -> 10 | F15: 関係者コードタイプ | H15: テーブル グループ すべて | I15: すべて | J15: テーブル：顧客個別に価格を設定する場合に選択 グループ：価格/割引グループ別に価格を設定する場合に選択 すべて：すべての顧客に対して価格を設定する場合に選択 | K15: シート「売買契約仕訳帳-設定値（販売）」を参照
B16: =ROW() - 5 -> 11 | F16: 勘定の選択 | H16: テーブル：顧客（ユーザー定義） グループ：価格/割引グループ（ユーザー定義） すべて：選択不可 | I16: ー | J16: 「関係者コードタイプ」で選択した値によって、価格の設定をする対象を選択 | K16: シート「売買契約仕訳帳-設定値（販売）」を参照
B17: =ROW() - 5 -> 12 | F17: 製品コードタイプ | H17: テーブル グループ すべて | I17: テーブル | J17: テーブル：製品個別に価格を設定する場合に選択 グループ：価格/割引グループ別に価格を設定する場合に選択 すべて：すべての製品に対して価格を設定する場合に選択 | K17: シート「売買契約仕訳帳-設定値（販売）」を参照
B18: =ROW() - 5 -> 13 | F18: 品目関係 | H18: テーブル：製品（ユーザー定義） グループ：価格/割引グループ（ユーザー定義） すべて：選択不可 | I18: ー | J18: 「製品コードタイプ」で選択した値によって、価格の設定をする対象を選択 | K18: シート「売買契約仕訳帳-設定値（販売）」を参照
B19: =ROW() - 5 -> 14 | F19: コンフィギュレーション | G19: [品目コード] フィールドで選択したタイプの品目またはタイプ グループを選択します。 | H19: （製品マスタから反映） | I19: ー | K19: シート「売買契約仕訳帳-設定値（販売）」を参照
B20: =ROW() - 5 -> 15 | F20: サイズ | H20: （製品マスタから反映） | I20: ー | K20: シート「売買契約仕訳帳-設定値（販売）」を参照
B21: =ROW() - 5 -> 16 | F21: 色 | H21: （製品マスタから反映） | I21: ー | K21: シート「売買契約仕訳帳-設定値（販売）」を参照
B22: =ROW() - 5 -> 17 | F22: スタイル | H22: （製品マスタから反映） | I22: ー | K22: シート「売買契約仕訳帳-設定値（販売）」を参照
B23: =ROW() - 5 -> 18 | F23: サイト | H23: サイト（ユーザー定義） | I23: ー | K23: シート「売買契約仕訳帳-設定値（販売）」を参照
B24: =ROW() - 5 -> 19 | F24: 倉庫 | H24: 倉庫（ユーザー定義） | I24: ー | K24: シート「売買契約仕訳帳-設定値（販売）」を参照
B25: =ROW() - 5 -> 20 | F25: 開始数量 | G25: 価格、ライン割引、マルチライン割引が適用される最小数量を入力します。 (ここに入力した数値を含みます。例: この数量が 1 に設定されている場合は、数量が 1 を含むこの値以上の場合に、この契約が適用されます) 。 この値はまた、割引合計のオーダー残高の最小値です。 | H25: 数値 | I25: 0.00 | K25: シート「売買契約仕訳帳-設定値（販売）」を参照
B26: =ROW() - 5 -> 21 | F26: 終了数量 | G26: 価格、ライン割引、マルチライン割引が適用される最大数量を入力します。 (ここに入力した数値は含まれません。例: この数量が 3.00 に設定されている場合は、2.99 までの契約が適用されます)。 この値はまた、割引合計のオーダー残高の上限値です。 | H26: 数値 | I26: ー | K26: シート「売買契約仕訳帳-設定値（販売）」を参照
B27: =ROW() - 5 -> 22 | F27: 単位 | H27: 単位（ユーザー定義） | K27: シート「売買契約仕訳帳-設定値（販売）」を参照
B28: =ROW() - 5 -> 23 | F28: 通貨金額 | H28: 数値 | I28: 0.00 | K28: シート「売買契約仕訳帳-設定値（販売）」を参照
B29: =ROW() - 5 -> 24 | F29: 通貨 | H29: 通貨（ユーザー定義） | J29: ここに設定したい価格を入力する | K29: シート「売買契約仕訳帳-設定値（販売）」を参照
B30: =ROW() - 5 -> 25 | F30: 均一層の金額 | H30: 数値 | I30: 0.00 | K30: シート「売買契約仕訳帳-設定値（販売）」を参照
B31: =ROW() - 5 -> 26 | F31: 属性ベースの価格決定ID | H31: 属性ベースの価格決定データ（ユーザー定義） | I31: ー | K31: シート「売買契約仕訳帳-設定値（販売）」を参照
B32: =ROW() - 5 -> 27 | F32: 分析コードの検証 | H32: （自動） | I32: ー | J32: 検証実施により自動で値が入る | K32: シート「売買契約仕訳帳-設定値（販売）」を参照
B33: =ROW() - 5 -> 28 | F33: 売買契約検証 | H33: （自動） | I33: ー | J33: 検証実施により自動で値が入る | K33: シート「売買契約仕訳帳-設定値（販売）」を参照
B34: =ROW() - 5 -> 29 | E34: 詳細 | F34: 開始日 | H34: 日付 | I34: ー | J34: 価格を使用する開始日を入力する | K34: シート「売買契約仕訳帳-設定値（販売）」を参照
B35: =ROW() - 5 -> 30 | F35: 終了日 | H35: 日付 | I35: ー | J35: 価格を使用する終了日を入力する | K35: シート「売買契約仕訳帳-設定値（販売）」を参照
B36: =ROW() - 5 -> 31 | F36: 諸費用価格 | G36: 価格の固定。これらの請求は請求書ごとに１回、適用されます。 | H36: 数値 | I36: 0.00 | K36: シート「売買契約仕訳帳-設定値（販売）」を参照
B37: =ROW() - 5 -> 32 | F37: 価格単位 | H37: 数値 | I37: 1.00 | K37: シート「売買契約仕訳帳-設定値（販売）」を参照
B38: =ROW() - 5 -> 33 | F38: 割引率１ | G38: 割引率１と割引率２の合計：総額 - パーセンテージ 1% - パーセンテージ 2% | H38: 数値 | I38: 0.00 | K38: シート「売買契約仕訳帳-設定値（販売）」を参照
B39: =ROW() - 5 -> 34 | F39: 割引率２ | G39: 割引率１と割引率２の合計：総額 - パーセンテージ 1% - パーセンテージ 2% | H39: 数値 | I39: 0.00 | K39: シート「売買契約仕訳帳-設定値（販売）」を参照
B40: =ROW() - 5 -> 35 | F40: リードタイム | G40: 日単位のリードタイム | H40: 数値 | I40: 0 | K40: シート「売買契約仕訳帳-設定値（販売）」を参照
B41: =ROW() - 5 -> 36 | F41: 作業日 | H41: はい/いいえ | I41: いいえ | K41: シート「売買契約仕訳帳-設定値（販売）」を参照
B42: =ROW() - 5 -> 37 | F42: リードタイムの無視 | H42: はい/いいえ | I42: はい | K42: シート「売買契約仕訳帳-設定値（販売）」を参照
B43: =ROW() - 5 -> 38 | F43: 一般通貨を含めます | G43: 売買契約を一般通貨から別の通貨に換算できることを保証するため、このオプションを選択します。このフィールドは、[リレーション] フィールドの [価格 (販売)] オプション の値を選択した場合にのみ、および通貨が [売掛金勘定パラメータ] のページの [一般通貨] のフィールドで定義された一般通貨である場合にのみ使用できます。 | H43: はい/いいえ | I43: いいえ | K43: シート「売買契約仕訳帳-設定値（販売）」を参照
B44: =ROW() - 5 -> 39 | F44: 次を検索 | G44: 割引の組み合わせの継続検索に使用されるの基準。 | H44: はい/いいえ | I44: はい | K44: シート「売買契約仕訳帳-設定値（販売）」を参照
B45: =ROW() - 5 -> 40 | E45: エラーログ | F45: ログ | H45: （自動） | I45: ー | J45: エラーが発生した場合に自動で値が入る | K45: シート「売買契約仕訳帳-設定値（販売）」を参照

Sheet 売買契約仕訳帳-設定値（販売）
A1: 売買契約仕訳帳（販売）-設定値 ※基本的には移行データを正とする
A2: ■凡例「必須：システム上必須」「必須(*)：システムで必須ではないが、トランザクション上や業務などで必須」
A3: パラメータ設定一覧へ
B4: # | C4: 売買契約仕訳帳 | J4: 仕訳帳明細行
J5: 概要 | AE5: 詳細 | AP5: エラーログ
C6: 名前 | D6: 価格/割引仕訳帳番号 | E6: 説明 | F6: 転記済 | G6: 転記日 | H6: 既定のリレーション | I6: 現在の価格のエクスポート | J6: 変更済 | K6: 関係 | L6: 関係者コードタイプ | M6: 勘定の選択 | N6: 製品コードタイプ | O6: 品目関係 | P6: コンフィギュレーション | Q6: サイズ | R6: 色 | S6: スタイル | T6: サイト | U6: 倉庫 | V6: 開始数量 | W6: 終了数量 | X6: 単位 | Y6: 通貨金額 | Z6: 通貨 | AA6: 均一層の金額 | AB6: 属性ベースの価格決定ID | AC6: 分析コードの検証 | AD6: 売買契約検証 | AE6: 開始日 | AF6: 終了日 | AG6: 諸費用価格 | AH6: 価格単位 | AI6: 割引率１ | AJ6: 割引率２ | AK6: リードタイム | AL6: 作業日 | AM6: リードタイムの無視 | AN6: 一般通貨を含めます | AO6: 次を検索 | AP6: ログ
C7: 売買仕訳帳名（ユーザー定義） | D7: 自動採番 | E7: 文字列 | F7: チェック/チェック無 | G7: 日付 | H7: 価格（購買） 行割引（仕入） 複数行割引（仕入） 割引合計（購買） 価格（販売） 行割引（販売側） 複数行割引（販売側） 割引合計（販売） 送料の割引 | I7: チェック/チェック無 | J7: （自動） | K7: 価格（購買） 行割引（仕入） 複数行割引（仕入） 割引合計（購買） 価格（販売） 行割引（販売側） 複数行割引（販売側） 割引合計（販売） 送料の割引 | L7: テーブル グループ すべて | M7: テーブル：顧客（ユーザー定義） グループ：価格/割引グループ（ユーザー定義） すべて：選択不可 | N7: テーブル グループ すべて | O7: テーブル：製品（ユーザー定義） グループ：価格/割引グループ（ユーザー定義） すべて：選択不可 | P7: （製品マスタから反映） | Q7: （製品マスタから反映） | R7: （製品マスタから反映） | S7: （製品マスタから反映） | T7: サイト（ユーザー定義） | U7: 倉庫（ユーザー定義） | V7: 数値 | W7: 数値 | X7: 単位（ユーザー定義） | Y7: 数値 | Z7: 通貨（ユーザー定義） | AA7: 数値 | AB7: 属性ベースの価格決定データ（ユーザー定義） | AC7: （自動） | AD7: （自動） | AE7: 日付 | AF7: 日付 | AG7: 数値 | AH7: 数値 | AI7: 数値 | AJ7: 数値 | AK7: 数値 | AL7: はい/いいえ | AM7: はい/いいえ | AN7: はい/いいえ | AO7: はい/いいえ | AP7: （自動）
C8: 必須 | D8: （自動） | F8: （自動） | G8: （自動） | H8: 必須 | J8: （自動） | K8: 必須(*) | L8: 必須(*) | M8: 必須(*) | N8: 必須(*) | O8: 必須(*) | Y8: 必須(*) | Z8: 必須
B9: =ROW() - 8 -> 1
B10: =ROW() - 8 -> 2
B11: =ROW() - 8 -> 3
B12: =ROW() - 8 -> 4
B13: =ROW() - 8 -> 5
B14: =ROW() - 8 -> 6
B15: =ROW() - 8 -> 7
B16: =ROW() - 8 -> 8
B17: =ROW() - 8 -> 9
B18: =ROW() - 8 -> 10
B19: =ROW() - 8 -> 11
B20: =ROW() - 8 -> 12
... B38: =ROW() - 8 -> 30

Sheet 荷渡方法
A1: 荷渡方法
B2: 販売とマーケティング ＞ 設定 > 配分 > 荷渡方法
B3: Sales and marketing > Setup > Distribution > Modes of delivery
A4: パラメータ設定一覧へ
B5: # | C5: タブ | D5: タブ説明 | E5: 項目分類 | F5: 項目 | G5: Description（標準） | H5: 設定可能値 | I5: デフォルト値 | J5: 備考 | K5: 設定値 | L5: 設定基準
B6: =ROW() - 5 -> 1 | C6: 荷渡方法 | F6: 荷渡方法 | G6: 荷渡方法を示すコードを英数字で入力します。コードは最大 10 文字まで入力できます。たとえば、United Parcel Service を UPS と入力し、Federal Express を FedEx と入力します。 | H6: 文字列 | I6: ー | K6: シート「荷渡方法-設定値」を参照
B7: =ROW() - 5 -> 2 | F7: 説明 | G7: 現在の荷渡方法の詳細な説明を入力します。この説明は、販売注文や顧客請求書などの印刷用ページに記載されます。 | H7: 文字列 | I7: ー | K7: シート「荷渡方法-設定値」を参照
B8: =ROW() - 5 -> 3 | F8: 諸掛グループ | H8: 諸掛グループ（ユーザー定義） | I8: ー | K8: シート「荷渡方法-設定値」を参照
B9: =ROW() - 5 -> 4 | F9: 急送 | H9: 急送（ユーザー定義） | I9: ー | K9: シート「荷渡方法-設定値」を参照
B10: =ROW() - 5 -> 5 | C10: 小売チャネル | F10: 名前 | H10: 名前（ユーザー定義） | I10: ー | J10: 組織階層からノードを選択する。 選択したノードの名前がセットされる | K10: シート「荷渡方法-設定値」を参照
B11: =ROW() - 5 -> 6 | F11: 関係者ID | H11: 数値 | I11: ー | J11: 組織階層からノードを選択する。 選択したノードの関係者IDがセットされる | K11: シート「荷渡方法-設定値」を参照
B12: =ROW() - 5 -> 7 | C12: 製品 | F12: カテゴリ | H12: カテゴリ（ユーザー定義） | I12: ー | K12: シート「荷渡方法-設定値」を参照
B13: =ROW() - 5 -> 8 | F13: 製品 | H13: 製品（ユーザー定義） | I13: ー | K13: シート「荷渡方法-設定値」を参照
B14: =ROW() - 5 -> 9 | F14: 製品バリアント | H14: 製品バリアント（ユーザー定義） | I14: ー | K14: シート「荷渡方法-設定値」を参照
F15: 名前 | H15: 文字列 | K15: シート「荷渡方法-設定値」を参照
B16: =ROW() - 5 -> 11 | F16: 行タイプ | G16: Retail では、[製品] や [アドレス] クイック タブで、オンライン店舗で使用される荷渡方法から明細行を追加、または除外するかどうかを選択します。 | H16: 含む 除外 | I16: 含む | K16: シート「荷渡方法-設定値」を参照
B17: =ROW() - 5 -> 12 | C17: 住所 | F17: 国/地域 | H17: 国/地域（ユーザー定義） | I17: ー | K17: シート「荷渡方法-設定値」を参照
B18: =ROW() - 5 -> 13 | F18: 都道府県 | H18: 都道府県（ユーザー定義） | I18: ー | K18: シート「荷渡方法-設定値」を参照
B19: =ROW() - 5 -> 14 | F19: 行タイプ | G19: Retail では、[製品] や [アドレス] クイック タブで、オンライン店舗で使用される荷渡方法から明細行を追加、または除外するかどうかを選択します。 | H19: 含む 除外 | I19: 含む | K19: シート「荷渡方法-設定値」を参照

Sheet 荷渡方法-設定値
A1: 荷渡方法(小売チャネル)-設定値 ※基本的には移行データを正とする
A2: ■凡例「必須：システム上必須」「必須(*)：システムで必須ではないが、トランザクション上や業務などで必須」
A3: パラメータ設定一覧へ
B4: # | C4: 荷渡方法 | G4: 荷渡方法(小売チャネル) | I4: 荷渡方法(製品) | N4: 荷渡方法(住所)
C5: 荷渡方法 | D5: 説明 | E5: 諸掛グループ | F5: 急送 | G5: 名前 | H5: 関係者ID | I5: カテゴリ | J5: 製品 | K5: 製品バリアント | L5: 名前 | M5: 行タイプ | N5: 国/地域 | O5: 都道府県 | P5: 行タイプ
C6: 文字列 | D6: 文字列 | E6: 諸掛グループ（ユーザー定義） | F6: 急送（ユーザー定義） | G6: 名前（ユーザー定義） | H6: 数値 | I6: カテゴリ（ユーザー定義） | J6: 製品（ユーザー定義） | K6: 製品バリアント（ユーザー定義） | L6: 文字列 | M6: 含む/除外 | N6: 国/地域（ユーザー定義） | O6: 都道府県（ユーザー定義） | P6: 含む/除外
C7: 必須
B8: =ROW() - 7 -> 1
B9: =ROW() - 7 -> 2
B10: =ROW() - 7 -> 3
B11: =ROW() - 7 -> 4
B12: =ROW() - 7 -> 5
B13: =ROW() - 7 -> 6
B14: =ROW() - 7 -> 7
B15: =ROW() - 7 -> 8
B16: =ROW() - 7 -> 9
B17: =ROW() - 7 -> 10

Sheet 顧客
A1: 顧客
B2: 売掛金管理＞顧客＞すべての顧客
B3: Accounts receivable > Customers > All customers
A4: パラメータ設定一覧へ
B5: # | C5: タブ | D5: タブ説明 | E5: 項目分類 | F5: 項目 | G5: 項目説明 | H5: 設定可能値 | I5: デフォルト値 | J5: 備考 | K5: 設定値 | L5: 設定基準
B6: =ROW() - 5 -> 1 | C6: 顧客の作成 | E6: 詳細＞タイプ＞組織 | F6: 顧客ID | H6: 文字列 | I6: ー | J6: 番号順序の設定に準拠する | K6: 「顧客-顧客の作成」を参照
B7: =ROW() - 5 -> 2 | F7: タイプ | H7: 組織 個人 | I7: 組織 | K7: 「顧客-顧客の作成」を参照
B8: =ROW() - 5 -> 3 | F8: 名前 | H8: 文字列 | I8: ー | K8: 「顧客-顧客の作成」を参照
B9: =ROW() - 5 -> 4 | F9: 顧客グループ | H9: 顧客グループ（ユーザー定義） | I9: ー | K9: 「顧客-顧客の作成」を参照
B10: =ROW() - 5 -> 5 | F10: 通貨 | H10: 通貨（ユーザー定義） | I10: ー | K10: 「顧客-顧客の作成」を参照
B11: =ROW() - 5 -> 6 | F11: 支払条件 | H11: 支払条件（ユーザー定義） | I11: ー | K11: 「顧客-顧客の作成」を参照
B12: =ROW() - 5 -> 7 | F12: 配送条件 | H12: 配送条件（ユーザー定義） | I12: ー | K12: 「顧客-顧客の作成」を参照
B13: =ROW() - 5 -> 8 | F13: 荷渡方法 | H13: 荷渡方法（ユーザー定義） | I13: ー | K13: 「顧客-顧客の作成」を参照
B14: =ROW() - 5 -> 9 | F14: 消費税グループ | H14: 消費税グループ（ユーザー定義） | I14: ー | K14: 「顧客-顧客の作成」を参照
B15: =ROW() - 5 -> 10 | F15: 課税控除番号 | H15: 課税控除番号（ユーザー定義） | I15: ー | K15: 「顧客-顧客の作成」を参照
B16: =ROW() - 5 -> 11 | F16: ソースコード | H16: ソース コード（ユーザー定義） | I16: ー | K16: 「顧客-顧客の作成」を参照
B17: =ROW() - 5 -> 12 | E17: 詳細＞タイプ＞個人 | F17: 顧客ID | H17: 文字列 | I17: ー | K17: 「顧客-顧客の作成」を参照
B18: =ROW() - 5 -> 13 | F18: タイプ | H18: 組織 個人 | I18: 個人 | K18: 「顧客-顧客の作成」を参照
B19: =ROW() - 5 -> 14 | F19: 名 | H19: 文字列 | I19: ー | K19: 「顧客-顧客の作成」を参照
B20: =ROW() - 5 -> 15 | F20: ミドルネーム | H20: 文字列 | I20: ー | K20: 「顧客-顧客の作成」を参照
B21: =ROW() - 5 -> 16 | F21: 姓の接頭語 | H21: 文字列 | I21: ー | K21: 「顧客-顧客の作成」を参照
B22: =ROW() - 5 -> 17 | F22: 姓 | H22: 文字列 | I22: ー | K22: 「顧客-顧客の作成」を参照
B23: =ROW() - 5 -> 18 | F23: 顧客グループ | H23: 顧客グループ（ユーザー定義） | I23: ー | K23: 「顧客-顧客の作成」を参照
B24: =ROW() - 5 -> 19 | F24: 通貨 | H24: 通貨（ユーザー定義） | I24: ー | K24: 「顧客-顧客の作成」を参照
B25: =ROW() - 5 -> 20 | F25: 支払条件 | H25: 文字列 | I25: ー | K25: 「顧客-顧客の作成」を参照
B26: =ROW() - 5 -> 21 | F26: 配送条件 | H26: 文字列 | I26: ー | K26: 「顧客-顧客の作成」を参照
B27: =ROW() - 5 -> 22 | F27: 荷渡方法 | H27: 文字列 | I27: ー | K27: 「顧客-顧客の作成」を参照
B28: =ROW() - 5 -> 23 | F28: 消費税グループ | H28: 文字列 | I28: ー | K28: 「顧客-顧客の作成」を参照
B29: =ROW() - 5 -> 24 | F29: 課税控除番号 | H29: 文字列 | I29: ー | K29: 「顧客-顧客の作成」を参照
B30: =ROW() - 5 -> 25 | F30: ソースコード | H30: 文字列 | I30: ー | K30: 「顧客-顧客の作成」を参照
B31: =ROW() - 5 -> 26 | E31: 住所 | F31: 国/地域 | H31: 国/地域（システム定義） | I31: JPN | K31: 「顧客-顧客の作成」を参照
B32: =ROW() - 5 -> 27 | F32: 郵便番号 | H32: 文字列 | I32: ー | K32: 「顧客-顧客の作成」を参照
B33: =ROW() - 5 -> 28 | F33: 住所 | H33: 文字列 | I33: ー | K33: 「顧客-顧客の作成」を参照
B34: =ROW() - 5 -> 29 | F34: 市町村 | H34: 文字列 | I34: ー | K34: 「顧客-顧客の作成」を参照
B35: =ROW() - 5 -> 30 | F35: 都道府県 | H35: 文字列 | I35: ー | K35: 「顧客-顧客の作成」を参照
B36: =ROW() - 5 -> 31 | F36: アドレス帳 | H36: アドレス帳（ユーザー定義） | I36: ー | K36: 「顧客-顧客の作成」を参照
B37: =ROW() - 5 -> 32 | E37: 連絡先情報 | F37: 電話 | H37: 文字列 | I37: ー | K37: 「顧客-顧客の作成」を参照
B38: =ROW() - 5 -> 33 | F38: 内線 | H38: 文字列 | I38: ー | K38: 「顧客-顧客の作成」を参照
B39: =ROW() - 5 -> 34 | F39: FAX | H39: 文字列 | I39: ー | K39: 「顧客-顧客の作成」を参照
B40: =ROW() - 5 -> 35 | F40: 電子メールアドレス | H40: 文字列 | I40: ー | K40: 「顧客-顧客の作成」を参照
B41: =ROW() - 5 -> 36 | C41: 一般 | E41: 顧客 | F41: アカウント | H41: 変更不可 | I41: ー | K41: 「顧客-設定値」を参照
B42: =ROW() - 5 -> 37 | F42: タイプ | H42: 変更不可 | I42: ー | K42: 「顧客-設定値」を参照
B43: =ROW() - 5 -> 38 | F43: 名前 | H43: 文字列 | I43: ー | K43: 「顧客-設定値」を参照
B44: =ROW() - 5 -> 39 | F44: 検索名 | H44: 文字列 | I44: ー | J44: 名前と同様のものがデフォルト値として入力される | K44: 「顧客-設定値」を参照
B45: =ROW() - 5 -> 40 | F45: 顧客グループ | H45: 顧客グループ（ユーザー定義） | I45: ー | K45: 「顧客-設定値」を参照
B46: =ROW() - 5 -> 41 | F46: 分類グループ | H46: 顧客分類グループ（ユーザー定義） | I46: ー | K46: 「顧客-設定値」を参照
B47: =ROW() - 5 -> 42 | F47: 支払の優先順位 | H47: 入力不可 | I47: ー | K47: 「顧客-設定値」を参照
B48: =ROW() - 5 -> 43 | E48: 組織の詳細 | F48: 従業員数 | H48: 0 | I48: 0 | K48: 「顧客-設定値」を参照
B49: =ROW() - 5 -> 44 | F49: 組織番号 | H49: 文字列 | K49: 「顧客-設定値」を参照
B50: =ROW() - 5 -> 45 | F50: ABCコード | H50: なし A B C | I50: なし | K50: 「顧客-設定値」を参照
B51: =ROW() - 5 -> 46 | F51: DUNS番号 | H51: 数値 | I51: ー | K51: 「顧客-設定値」を参照
B52: =ROW() - 5 -> 47 | E52: その他の情報 | F52: アドレス帳 | H52: アドレス帳（ユーザー定義） | I52: ー | K52: 「顧客-設定値」を参照
B53: =ROW() - 5 -> 48 | F53: 言語 | H53: 言語（システム定義） | I53: ー | K53: 「顧客-設定値」を参照
B54: =ROW() - 5 -> 49 | F54: カナ名 | H54: 文字列 | I54: ー | K54: 「顧客-設定値」を参照
B55: =ROW() - 5 -> 50 | F55: 呼称 | H55: 文字列 | I55: ー | K55: 「顧客-設定値」を参照
B56: =ROW() - 5 -> 51 | C56: 住所 | E56: 追加 | F56: 名前または説明 | H56: 文字列 | I56: ー | K56: 「顧客-設定値」を参照
B57: =ROW() - 5 -> 52 | F57: 住所 | H57: 文字列 | I57: ー | K57: 「顧客-設定値」を参照
B58: =ROW() - 5 -> 53 | F58: 目的 | H58: 業務 委託販売 配送 固定資産 本社 ホーム 請求書 船荷 その他 支払 実際の場所 採用 送金先 サービス 安定した組織 ステートメント SWIFT 船降 | I58: ー | K58: 「顧客-設定値」を参照
B59: =ROW() - 5 -> 54 | F59: 主要 | H59: チェック有/チェック無 | I59: チェック無 | K59: 「顧客-設定値」を参照
B60: =ROW() - 5 -> 55 | E60: 詳細オプション | F60: 国/地域 | H60: 国/地域（システム定義） | I60: ー | K60: 「顧客-設定値」を参照
B61: =ROW() - 5 -> 56 | F61: 郵便番号 | H61: 数値 | I61: ー | K61: 「顧客-設定値」を参照
B62: =ROW() - 5 -> 57 | F62: 住所 | H62: 文字列 | I62: ー | K62: 「顧客-設定値」を参照
B63: =ROW() - 5 -> 58 | F63: 市町村 | H63: 文字列 | I63: ー | K63: 「顧客-設定値」を参照
B64: =ROW() - 5 -> 59 | F64: 都道府県 | H64: 文字列 | I64: ー | K64: 「顧客-設定値」を参照
F65: 主要 | H65: はい/いいえ | I65: いいえ | K65: 「顧客-設定値」を参照
F66: プライベート | H66: はい/いいえ | I66: いいえ | K66: 「顧客-設定値」を参照
B67: =ROW() - 5 -> 62 | F67: 国/地域に関する基本事項 | H67: はい/いいえ | I67: いいえ | K67: 「顧客-設定値」を参照
B68: =ROW() - 5 -> 63 | C68: 連絡先情報 | F68: 説明 | H68: 文字列 | I68: ー | K68: 「顧客-設定値」を参照
B69: =ROW() - 5 -> 64 | F69: タイプ | H69: 電話 電子メールアドレス URL テレックス FAX Facebook Twitter LinkedIn | I69: ー | K69: 「顧客-設定値」を参照
B70: =ROW() - 5 -> 65 | F70: 連絡先の電話番号/住所 | H70: 文字列 | I70: ー | K70: 「顧客-設定値」を参照
B71: =ROW() - 5 -> 66 | F71: 内線 | H71: 文字列 | I71: ー | J71: タイプで以下を設定した場合に設定 電話 FAX | K71: 「顧客-設定値」を参照
B72: =ROW() - 5 -> 67 | F72: 主要 | H72: チェック有/チェック無 | I72: チェック無 | K72: 「顧客-設定値」を参照
B73: =ROW() - 5 -> 68 | C73: その他の詳細 | F73: 一時顧客 | H73: はい/いいえ | I73: いいえ | K73: 「顧客-設定値」を参照
B74: =ROW() - 5 -> 69 | F74: 統計グループ | H74: 統計グループ（ユーザー定義） | I74: ー | K74: 「顧客-設定値」を参照
B75: =ROW() - 5 -> 70 | F75: 取引明細書 | H75: 常時 四半期 半年毎 毎年 なし | I75: 常時 | K75: 「顧客-設定値」を参照
B76: =ROW() - 5 -> 71 | E76: 顧客セルフサービス | F76: 利用可能履歴 | H76: Web注文 すべての注文 | I76: Web注文 | K76: 「顧客-設定値」を参照
B77: =ROW() - 5 -> 72 | E77: 政府ID | F77: ID番号 | H77: 文字列 | I77: ー | K77: 「顧客-設定値」を参照
B78: =ROW() - 5 -> 73 | F78: 国/地域 | H78: 国/地域（システム定義） | I78: ー | K78: 「顧客-設定値」を参照
B79: =ROW() - 5 -> 74 | F79: 都道府県 | H79: 文字列 | I79: ー | K79: 「顧客-設定値」を参照
B80: =ROW() - 5 -> 75 | E80: 送金 | F80: 仕入先 | H80: 仕入先（ユーザー定義） | I80: ー | K80: 「顧客-設定値」を参照
B81: =ROW() - 5 -> 76 | E81: 通知と取消の自動処理 | F81: 自動的な通知と取消の除外 | H81: はい/いいえ | I81: いいえ | K81: 「顧客-設定値」を参照
B82: =ROW() - 5 -> 77 | E82: 会社間 | F82: 有効 | H82: はい/いいえ | I82: いいえ | K82: 「顧客-設定値」を参照
B83: =ROW() - 5 -> 78 | F83: 会社 | H83: 入力不可 | I83: ー | K83: 「顧客-設定値」を参照
B84: =ROW() - 5 -> 79 | F84: 仕入先 | H84: 入力不可 | I84: ー | K84: 「顧客-設定値」を参照
B85: =ROW() - 5 -> 80 | F85: 会社間注文の作成 | H85: はい/いいえ | I85: いいえ | K85: 「顧客-設定値」を参照
B86: =ROW() - 5 -> 81 | F86: 直納 | H86: はい/いいえ | I86: いいえ | K86: 「顧客-設定値」を参照
B87: =ROW() - 5 -> 82 | F87: 間接注文明細行の作成 | H87: はい/いいえ | I87: いいえ | K87: 「顧客-設定値」を参照
B88: =ROW() - 5 -> 83 | C88: 顧客情報 | F88: 基本連絡先 | H88: 連絡先（ユーザー定義） | I88: ー | K88: 「顧客-設定値」を参照
B89: =ROW() - 5 -> 84 | F89: 業種 | H89: 業種（ユーザー定義） | I89: ー | K89: 「顧客-設定値」を参照
B90: =ROW() - 5 -> 85 | F90: 担当従業員 | H90: 作業者（ユーザー定義） | I90: ー | K90: 「顧客-設定値」を参照
B91: =ROW() - 5 -> 86 | F91: 区分 | H91: 区分（ユーザー定義） | I91: ー | K91: 「顧客-設定値」を参照
B92: =ROW() - 5 -> 87 | F92: 小区分 | H92: 小区分（ユーザー定義） | I92: ー | K92: 「顧客-設定値」を参照
B93: =ROW() - 5 -> 88 | F93: 会社グループ | H93: 会社グループ（ユーザー定義） | I93: ー | K93: 「顧客-設定値」を参照
B94: =ROW() - 5 -> 89 | F94: 販売地域 | H94: 販売地域（ユーザー定義） | I94: ー | K94: 「顧客-設定値」を参照
B95: =ROW() - 5 -> 90 | F95: 通貨 | H95: 通貨（ユーザー定義） | I95: JPY | K95: 「顧客-設定値」を参照
B96: =ROW() - 5 -> 91 | F96: メモ | H96: 文字列 | I96: ー | K96: 「顧客-設定値」を参照
B97: =ROW() - 5 -> 92 | E97: マーケティング | F97: ソースコード | H97: ソースコード（ユーザー定義） | I97: ー | K97: 「顧客-設定値」を参照
B98: =ROW() - 5 -> 93 | F98: 前回注文のソース | H98: ソースコード（ユーザー定義） | I98: ー | K98: 「顧客-設定値」を参照
B99: =ROW() - 5 -> 94 | F99: 前回プロモーションのソース | H99: ソースコード（ユーザー定義） | I99: ー | K99: 「顧客-設定値」を参照
B100: =ROW() - 5 -> 95 | C100: 与信および回収 | E100: 一般 | F100: 信用格付け | H100: 文字列 | I100: ー | K100: 「顧客-設定値」を参照
...

Sheet 顧客-顧客の作成
A1: 顧客-顧客の作成 ※基本的には移行データを正とする
A2: ■凡例「必須：システム上必須」「必須(*)：システムで必須ではないが、トランザクション上や業務などで必須」
A3: パラメータ設定一覧へ
B4: # | C4: 顧客の作成
C5: 詳細 | R5: 住所 | X5: 連絡先情報
C6: 顧客ID | D6: タイプ | E6: 名前 （タイプ：組織） | F6: 名 （タイプ：個人） | G6: ミドルネーム （タイプ：個人） | H6: 姓の接尾語 （タイプ：個人） | I6: 姓 （タイプ：個人） | J6: 顧客グループ | K6: 通貨 | L6: 支払条件 | M6: 配送条件 | N6: 荷渡方法 | O6: 消費税グループ | P6: 課税控除番号 | Q6: ソースコード | R6: 国/地域 | S6: 郵便番号 | T6: 住所 | U6: 市町村 | V6: 都道府県 | W6: アドレス帳 | X6: 電話 | Y6: 内線 | Z6: FAX | AA6: 電子メールアドレス
C7: 文字列（番号順序の設定に準拠するため、手動入力、自動採番どちらも可能） | D7: 組織/個人 | E7: 文字列 | F7: 文字列 | G7: 文字列 | H7: 文字列 | I7: 文字列 | J7: 顧客グループ（ユーザー定義） | K7: 通貨（ユーザー定義） | L7: 支払条件（ユーザー定義） | M7: 配送条件（ユーザー定義） | N7: 荷渡方法（ユーザー定義） | O7: 消費税グループ（ユーザー定義） | P7: 課税控除番号（ユーザー定義） | Q7: ソース コード（ユーザー定義） | R7: 国/地域（システム定義） | S7: 文字列 | T7: 文字列 | U7: 文字列 | V7: 文字列 | W7: アドレス帳（ユーザー定義） | X7: 文字列 | Y7: 文字列 | Z7: 文字列 | AA7: 文字列
C8: 必須 | D8: 必須 | E8: 必須（組織の場合） | F8: 必須（個人の場合） | G8: 必須（個人の場合） | H8: 必須（個人の場合） | I8: 必須（個人の場合） | J8: 必須 | K8: 必須 | L8: 必須(*) | O8: 必須(*) | R8: 必須
B9: 例 | C9: TEST_CUST-001 | D9: 組織 | E9: テスト顧客株式会社 | J9: CG01 ※グループの設定は別途検討 | K9: JPY | L9: 月末締翌月末払い | O9: 国内売上 ※グループの設定は別途検討 | R9: JPN
B10: =ROW() - 9 -> 1
B11: =ROW() - 9 -> 2
B12: =ROW() - 9 -> 3
B13: =ROW() - 9 -> 4
B14: =ROW() - 9 -> 5
B15: =ROW() - 9 -> 6
B16: =ROW() - 9 -> 7
B17: =ROW() - 9 -> 8
B18: =ROW() - 9 -> 9
B19: =ROW() - 9 -> 10
B20: =ROW() - 9 -> 11
B21: =ROW() - 9 -> 12
... B29: =ROW() - 9 -> 20

Sheet 顧客-設定値
A1: 顧客-設定値 ※基本的には移行データを正とする
A2: ■凡例「必須：システム上必須」「必須(*)：システムで必須ではないが、トランザクション上や業務などで必須」
A3: パラメータ設定一覧へ
B4: # | C4: すべての顧客 | R4: 住所 | AD4: 連絡先情報 | AI4: その他の詳細 | AX4: 顧客情報 | BJ4: 与信および回収 | CM4: 販売注文の既定値 | DH4: 支払の既定値 | DZ4: 財務分析コード | EC4: 倉庫 | EG4: 請求書と出荷 | EY4: 輸送管理 | EZ4: 口座引落の委任状 | FG4: コマース
C5: 一般>顧客 | J5: 一般>組織の詳細 | N5: 一般>その他の情報 | AL5: 顧客セルフサービス | AM5: 政府ID | AP5: 送金 | AQ5: 通知と取消の自動処理 | AR5: 会社間 | BG5: マーケティング | BJ5: 一般 | BO5: 合計与信限度額 | BV5: 与信の確認 | BX5: 適格な与信限度額 | CA5: 状態 | CE5: リスク | CG5: メモ | CH5: 取立 | CM5: 販売注文 | CW5: 割引 | DC5: グループ | DF5: 配賦 | DG5: 詳細なメモ | DH5: 支払 | DU5: 中央銀行への通知 | DW5: 小切手の保留 | DY5: 月次締めグループ | DZ5: 既定の財務分析コード ※使用する財務分析コード分列追加 | EC5: ASN | ED5: 倉庫にリリース | EE5: 出荷処理中 | EG5: 請求書 | EK5: 配送日 | EQ5: 消費税 | EU5: 梱包材費用 | EV5: E-INVOICE | EX5: 運賃 | EY5: 船荷証券 | FG5: 小売 | FJ5: レシート | FL5: ロイヤルティ登録 | FM5: プライバシー | FO5: B2B
C6: アカウント | D6: タイプ | E6: 名前 | F6: 検索名 | G6: 顧客グループ | H6: 分類グループ | I6: 支払優先順位 | J6: 従業員数 | K6: 組織番号 | L6: ABCコード | M6: DUNS番号 | N6: アドレス帳 | O6: 言語 | P6: カナ名 | Q6: 呼称 | R6: 名前または説明 | S6: 住所 | T6: 目的 | U6: 主要 | V6: 国/地域 | W6: 郵便番号 | X6: 住所 | Y6: 市町村 | Z6: 都道府県 | AA6: 主要 | AB6: プライベート | AC6: 国/地域に関する基本事項 | AD6: 説明 | AE6: タイプ | AF6: 連絡先の電話番号/住所 | AG6: 内線 | AH6: 主要 | AI6: 一時顧客 | AJ6: 統計グループ | AK6: 取引明細書 | AL6: 利用可能履歴 | AM6: ID番号 | AN6: 国/地域 | AO6: 都道府県 | AP6: 仕入先 | AQ6: 自動的な通知と取消の除外 | AR6: 有効 | AS6: 会社 | AT6: 仕入先 | AU6: 会社間注文の作成 | AV6: 直納 | AW6: 間接注文明細行の作成 | AX6: 基本連絡先 | AY6: 業種 | AZ6: 担当従業員 | BA6: 区分 | BB6: 小区分 | BC6: 会社グループ | BD6: 販売地域 | BE6: 通貨 | BF6: メモ | BG6: ソースコード | BH6: 前回注文のソース | BI6: 前回プロモーションのソース | BJ6: 信用格付け | BK6: 与信限度確認必須 | BL6: 無制限の与信限度額 | BM6: 与信管理から除外 | BN6: 与信管理グループ | BO6: 与信限度額 | BP6: 顧客の通貨 (JPY) での与信限度額 | BQ6: 保険および保証 | BR6: 合計与信限度額 | BS6: 与信限度額の有効期限日 | BT6: 与信限度額の変更日 | BU6: 顧客与信グループ | BV6: 最終確認日 | BW6: 次にスケジュールされた確認日 | BX6: 適格な与信限度額 | BY6: 適格な与信限度額の通貨 | BZ6: 適格な与信限度額の変更日 | CA6: 勘定状態 | CB6: 勘定状態の理由 | CC6: 督促代行業者あり | CD6: 保留されたタイトル | CE6: 事業の設立年 | CF6: 初回購入 | CG6: 注記 | CH6: 請求と出荷は保留中です | CI6: 回収の連絡先 | CJ6: 既定の損金処理の理由 | CK6: 利息を除外します | CL6: 回収手数料を除外 | CM6: 諸掛グループ | CN6: サイト | CO6: 倉庫 | CP6: 品目 - 顧客グループ | CQ6: コミッショングループ | CR6: 売上グループ | CS6: 販売注文管理グループ | CT6: 勘定番号 | CU6: 会社間 | CV6: 注文入力期限 | CW6: 複数割引行 | CX6: 割引合計 | CY6: 価格 | CZ6: 行割引 | DA6: 顧客リベートグループ | DB6: 顧客TWAグループ | DC6: 送料グループ | DD6: 提供品 | DE6: 自動キャンセル | DF6: 優先順位 | DG6: 詳細なメモ グループ | DH6: 支払条件 | DI6: 支払方法 | DJ6: 支払詳細 | DK6: 支払スケジュール | DL6: 支払期日 | DM6: 現金割引 | DN6: 支払期間基準日数 | DO6: 銀行口座 | DP6: 内金の許可 | DQ6: チャネルのフロア制限仕様をブロック | DR6: 適格な分割 | DS6: 銀行口座番号 | DT6: 現金割引の使用 | DU6: 中央銀行目的コード | DV6: メモ | DW6: しきい値 | DX6: 日数 | DY6: 月次締め日 | DZ6: XXXXXX | EA6: XXXXXX | EB6: XXXXXX | EC6: ASNの生成 | ED6: フルフィルメントポリシー | EE6: 出荷全体の入力 | EF6: 既定の在庫状態ID | EG6: 請求先/元 ID | EH6: 請求先住所 | EI6: 番号順序グループ | EJ6: 請求書テンプレート | EK6: UPSゾーン | EL6: 配送条件 | EM6: 荷渡方法 | EN6: 配送理由 | EO6: 出荷先コード | EP6: 入荷カレンダー | EQ6: 消費税グループ | ER6: 課税控除番号 | ES6: 税込価格 | ET6: 梱包税ライセンス番号 | EU6: ライセンス番号 | EV6: eInvoice | EW6: 電子請求書の添付 | EX6: 運賃の見越計上 | EY6: 速達船荷証券の受理 | EZ6: 委任状ID | FA6: 銀行口座 | FB6: 署名日 | FC6: 委任状スキーム | FD6: 支払頻度 | FE6: 委任状の状態 | FF6: 変更日時 | FG6: （転記済金額ではなく）請求金額 | FH6: 出荷として転記する | FI6: 注文番号参照の使用 | FJ6: レシートオプション | FK6: レシートの電子メール | FL6: ロイヤルティ登録に対する顧客のブロック | FM6: 個人用設定の無効化 | FN6: Web活動を追跡しない | FO6: 顧客階層ID | FP6: B2B管理者
C7: システム入力（顧客の作成での入力が引き継がれる） | D7: システム入力（顧客の作成での入力が引き継がれる） | E7: 文字列（顧客の作成での入力が引き継がれる） | F7: 文字列 | G7: 顧客グループ（ユーザー定義）（顧客の作成での入力が引き継がれる） | H7: 顧客分類グループ（ユーザー定義） | I7: 入力不可 | J7: 数値 | K7: 文字列 | L7: なし A B C | M7: 数値 | N7: アドレス帳（ユーザー定義） | O7: 言語（システム定義） | P7: 文字列 | Q7: 文字列 | R7: 文字列 | S7: 文字列 | T7: 業務 委託販売 配送 固定資産 本社 ホーム 請求書 船荷 その他 支払 実際の場所 採用 送金先 サービス 安定した組織 ステートメント SWIFT 船降 | U7: チェック有/チェック無 | V7: 国/地域（システム定義） | W7: 数値 | X7: 文字列 | Y7: 文字列 | Z7: 文字列 | AA7: はい/いいえ | AB7: はい/いいえ | AC7: はい/いいえ | AD7: 文字列 | AE7: 電話 電子メールアドレス URL テレックス FAX Facebook Twitter LinkedIn | AF7: 文字列 | AG7: 文字列 | AH7: チェック有/チェック無 | AI7: はい/いいえ | AJ7: 統計グループ（ユーザー定義） | AK7: 常時 四半期 半年毎 毎年 なし | AL7: Web注文 / すべての注文 | AM7: 文字列 | AN7: 国/地域（システム定義） | AO7: 文字列 | AP7: 仕入先（ユーザー定義） | AQ7: はい/いいえ | AR7: はい/いいえ | AS7: 入力不可 | AT7: 入力不可 | AU7: はい/いいえ | AV7: はい/いいえ | AW7: はい/いいえ | AX7: 連絡先（ユーザー定義） | AY7: 業種（ユーザー定義） | AZ7: 作業者（ユーザー定義） | BA7: 区分（ユーザー定義） | BB7: 小区分（ユーザー定義） | BC7: 会社グループ（ユーザー定義） | BD7: 販売地域（ユーザー定義） | BE7: 通貨（ユーザー定義）（顧客の作成での入力が引き継がれる） | BF7: 文字列 | BG7: ソースコード（ユーザー定義） | BH7: ソースコード（ユーザー定義） | BI7: ソースコード（ユーザー定義） | BJ7: 文字列 | BK7: はい/いいえ | BL7: はい/いいえ | BM7: はい/いいえ | BN7: 与信管理グループ（ユーザー定義） | BO7: 入力不可 | BP7: 入力不可 | BQ7: 入力不可 | BR7: 入力不可 | BS7: 日付 | BT7: 入力不可 | BU7: 入力不可 | BV7: 日付 | BW7: 日付 | BX7: 数値 | BY7: 通貨（ユーザー定義） | BZ7: 入力不可 | CA7: 勘定状態（ユーザー定義） | CB7: 与信管理の理由（ユーザー定義） | CC7: はい/いいえ | CD7: はい/いいえ | CE7: 日付 | CF7: 日付 | CG7: 文字列 | CH7: いいえ 請求書 すべて 支払 要求 なし 発注書 | CI7: 関係者（ユーザー定義） | CJ7: 顧客損金処理理由コード（ユーザー定義） | CK7: はい/いいえ | CL7: はい/いいえ | CM7: 顧客諸掛グループ（ユーザー定義） | CN7: サイト（ユーザー定義） | CO7: 倉庫（ユーザー定義） | CP7: 外部品目説明（ユーザー定義） | CQ7: コミッション顧客グループ（ユーザー定義） | CR7: コミッション売上グループ（ユーザー定義） | CS7: 注文管理グループ（ユーザー定義） | CT7: 文字列 | CU7: 文字列 | CV7: 注文入力期限グループ（ユーザー定義） | CW7: 価格/割引グループ（ユーザー定義） | CX7: 価格/割引グループ（ユーザー定義） | CY7: 価格/割引グループ（ユーザー定義） | CZ7: 価格/割引グループ（ユーザー定義） | DA7: 顧客リベートグループ (複数)（ユーザー定義） | DB7: 顧客TMA グループ（ユーザー定義） | DC7: 価格/割引グループ（ユーザー定義） | DD7: 提供品グループ（ユーザー定義） | DE7: はい/いいえ | DF7: 高-1 高-2 高-3 中-4 中-5 中-6 中-7 低-8 低-9 低-10 | DG7: 詳細なメモ グループ（ユーザー定義） | DH7: 支払条件（ユーザー定義）（顧客の作成での入力が引き継がれる） | DI7: 支払方法（ユーザー定義） | DJ7: 支払詳細（ユーザー定義） | DK7: 支払スケジュール（ユーザー定義） | DL7: 支払期日（ユーザー定義） | DM7: 現金割引（ユーザー定義） | DN7: 数値 | DO7: 銀行口座（ユーザー定義） | DP7: はい/いいえ | DQ7: はい/いいえ | DR7: はい/いいえ | DS7: 文字列 | DT7: 標準 常時 なし | DU7: 支払目的コード（ユーザー定義） | DV7: 文字列 | DW7: 数値 | DX7: 数値 | DY7: 数値 | EC7: はい/いいえ | ED7: フルフィルメント ポリシー（ユーザー定義） | EE7: はい/いいえ | EF7: 在庫状態（ユーザー定義） | EG7: 顧客（ユーザー定義） | EH7: 請求先/元 ID / 注文顧客 | EI7: 番号順序グループ（ユーザー定義） | EJ7: PSAProjInvoice.Report PSAProjInvoice.Report_JP | EK7: 文字列 | EL7: 配送条件（ユーザー定義） | EM7: 荷渡方法（ユーザー定義） | EN7: 配送理由（ユーザー定義） | EO7: 行先コード（ユーザー定義） | EP7: 作業時間カレンダー（ユーザー定義） | EQ7: 消費税グループ（ユーザー定義） | ER7: 課税控除番号（ユーザー定義） | ES7: はい/いいえ | ET7: 文字列 | EU7: 文字列 | EV7: はい/いいえ | EW7: はい/いいえ | EX7: はい/いいえ | EY7: はい/いいえ | EZ7: 変更不可 | FA7: 銀行口座（ユーザー定義） | FB7: 年月日 | FC7: 文字列 | FD7: 繰返し / 一時 | FE7: 文字列 | FF7: 年月日 | FG7: 数値 | FH7: はい/いいえ | FI7: はい/いいえ | FJ7: 標準受領書 電子メール 両方 | FK7: 文字列 | FL7: はい/いいえ | FM7: はい/いいえ | FN7: はい/いいえ | FO7: 入力不可 | FP7: はい/いいえ
C8: 必須 | D8: 必須 | E8: 必須 | G8: 必須 | O8: 必須 | BE8: 必須 | DH8: 必須(*) | DI8: 必須(*)
B9: 例 | C9: ='顧客-顧客の作成'!C9 -> TEST_CUST-001 | D9: ='顧客-顧客の作成'!D9 -> 組織 | E9: ='顧客-顧客の作成'!E9 -> テスト顧客株式会社 | F9: テスト顧客 | G9: ='顧客-顧客の作成'!J9 -> CG01 ※グループの設定は別途検討 | O9: ja | BE9: ='顧客-顧客の作成'!K9 -> JPY | DH9: ='顧客-顧客の作成'!L9 -> 月末締翌月末払い | DI9: 銀行振込
B10: =ROW() - 9 -> 1 | C10: ='顧客-顧客の作成'!C10 -> 0 | D10: ='顧客-顧客の作成'!D10 -> 0 | E10: ='顧客-顧客の作成'!E10 -> 0 | G10: ='顧客-顧客の作成'!J10 -> 0 | BE10: ='顧客-顧客の作成'!K10 -> 0 | DH10: ='顧客-顧客の作成'!L10 -> 0
B11: =ROW() - 9 -> 2 | C11: ='顧客-顧客の作成'!C11 -> 0 | D11: ='顧客-顧客の作成'!D11 -> 0 | E11: ='顧客-顧客の作成'!E11 -> 0 | G11: ='顧客-顧客の作成'!J11 -> 0 | BE11: ='顧客-顧客の作成'!K11 -> 0 | DH11: ='顧客-顧客の作成'!L11 -> 0
B12: =ROW() - 9 -> 3 | C12: ='顧客-顧客の作成'!C12 -> 0 | D12: ='顧客-顧客の作成'!D12 -> 0 | E12: ='顧客-顧客の作成'!E12 -> 0 | G12: ='顧客-顧客の作成'!J12 -> 0 | BE12: ='顧客-顧客の作成'!K12 -> 0 | DH12: ='顧客-顧客の作成'!L12 -> 0
B13: =ROW() - 9 -> 4 | C13: ='顧客-顧客の作成'!C13 -> 0 | D13: ='顧客-顧客の作成'!D13 -> 0 | E13: ='顧客-顧客の作成'!E13 -> 0 | G13: ='顧客-顧客の作成'!J13 -> 0 | BE13: ='顧客-顧客の作成'!K13 -> 0 | DH13: ='顧客-顧客の作成'!L13 -> 0
B14: =ROW() - 9 -> 5 | C14: ='顧客-顧客の作成'!C14 -> 0 | D14: ='顧客-顧客の作成'!D14 -> 0 | E14: ='顧客-顧客の作成'!E14 -> 0 | G14: ='顧客-顧客の作成'!J14 -> 0 | BE14: ='顧客-顧客の作成'!K14 -> 0 | DH14: ='顧客-顧客の作成'!L14 -> 0
B15: =ROW() - 9 -> 6 | C15: ='顧客-顧客の作成'!C15 -> 0 | D15: ='顧客-顧客の作成'!D15 -> 0 | E15: ='顧客-顧客の作成'!E15 -> 0 | G15: ='顧客-顧客の作成'!J15 -> 0 | BE15: ='顧客-顧客の作成'!K15 -> 0 | DH15: ='顧客-顧客の作成'!L15 -> 0
B16: =ROW() - 9 -> 7 | C16: ='顧客-顧客の作成'!C16 -> 0 | D16: ='顧客-顧客の作成'!D16 -> 0 | E16: ='顧客-顧客の作成'!E16 -> 0 | G16: ='顧客-顧客の作成'!J16 -> 0 | BE16: ='顧客-顧客の作成'!K16 -> 0 | DH16: ='顧客-顧客の作成'!L16 -> 0
B17: =ROW() - 9 -> 8 | C17: ='顧客-顧客の作成'!C17 -> 0 | D17: ='顧客-顧客の作成'!D17 -> 0 | E17: ='顧客-顧客の作成'!E17 -> 0 | G17: ='顧客-顧客の作成'!J17 -> 0 | BE17: ='顧客-顧客の作成'!K17 -> 0 | DH17: ='顧客-顧客の作成'!L17 -> 0
B18: =ROW() - 9 -> 9 | C18: ='顧客-顧客の作成'!C18 -> 0 | D18: ='顧客-顧客の作成'!D18 -> 0 | E18: ='顧客-顧客の作成'!E18 -> 0 | G18: ='顧客-顧客の作成'!J18 -> 0 | BE18: ='顧客-顧客の作成'!K18 -> 0 | DH18: ='顧客-顧客の作成'!L18 -> 0
B19: =ROW() - 9 -> 10 | C19: ='顧客-顧客の作成'!C19 -> 0 | D19: ='顧客-顧客の作成'!D19 -> 0 | E19: ='顧客-顧客の作成'!E19 -> 0 | G19: ='顧客-顧客の作成'!J19 -> 0 | BE19: ='顧客-顧客の作成'!K19 -> 0 | DH19: ='顧客-顧客の作成'!L19 -> 0
B20: =ROW() - 9 -> 11 | C20: ='顧客-顧客の作成'!C20 -> 0 | D20: ='顧客-顧客の作成'!D20 -> 0 | E20: ='顧客-顧客の作成'!E20 -> 0 | G20: ='顧客-顧客の作成'!J20 -> 0 | BE20: ='顧客-顧客の作成'!K20 -> 0 | DH20: ='顧客-顧客の作成'!L20 -> 0
B21: =ROW() - 9 -> 12 | C21: ='顧客-顧客の作成'!C21 -> 0 | D21: ='顧客-顧客の作成'!D21 -> 0 | E21: ='顧客-顧客の作成'!E21 -> 0 | G21: ='顧客-顧客の作成'!J21 -> 0 | BE21: ='顧客-顧客の作成'!K21 -> 0 | DH21: ='顧客-顧客の作成'!L21 -> 0
... B29: =ROW() - 9 -> 20 | C29: ='顧客-顧客の作成'!C29 -> 0 | D29: ='顧客-顧客の作成'!D29 -> 0 | E29: ='顧客-顧客の作成'!E29 -> 0 | G29: ='顧客-顧客の作成'!J29 -> 0 | BE29: ='顧客-顧客の作成'!K29 -> 0 | DH29: ='顧客-顧客の作成'!L29 -> 0

Sheet 与信管理グループ
A1: 与信管理グループ
B2: 与信および回収＞設定＞与信管理設定＞与信管理グループ
B3: Credit and collections＞Setup＞Credit management setup＞Credit management groups
A4: パラメータ設定一覧へ
B5: # | C5: タブ | D5: タブ説明 | E5: 項目分類 | F5: 項目 | G5: Description（標準） | H5: 設定可能値 | I5: デフォルト値 | J5: 備考 | K5: 設定値 | L5: 設定基準
B6: =ROW() - 5 -> 1 | C6: 与信管理グループ | F6: 与信管理グループ | H6: 文字列 | I6: ー | K6: 「与信管理グループ-設定値」を参照
B7: =ROW() - 5 -> 2 | F7: 説明 | H7: 文字列 | I7: ー | K7: 「与信管理グループ-設定値」を参照

Sheet 与信管理グループ-設定値
A1: 与信管理グループ - 設定値 ※基本的には移行データを正とする
A2: ■凡例「必須：システム上必須」「必須(*)：システムで必須ではないが、トランザクション上や業務などで必須」
A3: パラメータ設定一覧へ
B4: # | C4: 与信管理グループ
C6: 与信管理グループ | D6: 説明
C7: 文字列 | D7: 文字列
C8: 必須
B9: =ROW() - 8 -> 1
B10: =ROW() - 8 -> 2
B11: =ROW() - 8 -> 3
B12: =ROW() - 8 -> 4
B13: =ROW() - 8 -> 5

Sheet 仕入先の価格割引グループ
A1: 仕入先の価格/割引グループ
B2: 調達 ＞ 価格と割引 > 価格/割引グループ > 仕入先の価格/割引グループ
B3: Procurement and sourcing > Prices and discounts > Price/discount groups > Vendor price/discount groups
A4: パラメータ設定一覧へ
B5: # | C5: タブ | D5: タブ説明 | E5: 項目分類 | F5: 項目 | G5: Description（標準） | H5: 設定可能値 | I5: デフォルト値 | J5: 備考 | K5: 設定値 | L5: 設定基準
B6: =ROW() - 5 -> 1 | C6: 仕入先の価格/割引グループ | F6: 価格グループ | H6: 文字列 | I6: ー | K6: シート「仕入先の価格割引グループ-設定値」を参照
B7: =ROW() - 5 -> 2 | F7: 名前 | H7: 文字列 | I7: ー | K7: シート「仕入先の価格割引グループ-設定値」を参照
B8: =ROW() - 5 -> 3 | F8: 価格/割引グループ タイプ | H8: 価格グループ 行割引グループ 複数行割引グループ 割引合計グループ | I8: 価格グループ | K8: シート「仕入先の価格割引グループ-設定値」を参照

Sheet 仕入先の価格割引グループ-設定値
A1: 仕入先の価格/割引グループ-設定値 ※基本的には移行データを正とする
A2: ■凡例「必須：システム上必須」「必須(*)：システムで必須ではないが、トランザクション上や業務などで必須」
A3: パラメータ設定一覧へ
B4: # | C4: 仕入先の価格/割引グループ
C5: 割引グループ | D5: 名前 | E5: 価格/割引グループ タイプ
C6: 文字列 | D6: 文字列 | E6: 価格グループ 行割引グループ 複数行割引グループ 割引合計グループ
C7: 必須 | E7: 必須
B8: =ROW() - 7 -> 1
B9: =ROW() - 7 -> 2
B10: =ROW() - 7 -> 3
B11: =ROW() - 7 -> 4
B12: =ROW() - 7 -> 5
B13: =ROW() - 7 -> 6
B14: =ROW() - 7 -> 7

Sheet 売買契約仕訳帳名 (調達)
A1: 売買契約仕訳帳名（調達）
B2: 調達 ＞ 設定 > 価格と割引 > 売買契約仕訳帳名
B3: Procurement and sourcing > Setup > Prices and discounts > Trade agreement journal name
A4: パラメータ設定一覧へ
B5: # | C5: タブ | D5: タブ説明 | E5: 項目分類 | F5: 項目 | G5: Description（標準） | H5: 設定可能値 | I5: デフォルト値 | J5: 備考 | K5: 設定値 | L5: 設定基準
B6: =ROW() - 5 -> 1 | C6: 売買契約仕訳帳名 | F6: 名前 | H6: 文字列 | I6: ー | K6: シート「売買契約仕訳帳名-設定値」を参照
B7: =ROW() - 5 -> 2 | F7: 説明 | H7: 文字列 | I7: ー | K7: シート「売買契約仕訳帳名-設定値」を参照
B8: =ROW() - 5 -> 3 | F8: 関係 | H8: 価格（購買） 行割引（仕入） 複数行割引（仕入） 割引合計（購買） 価格（販売） 行割引（販売側） 複数行割引（販売側） 割引合計（販売） 送料の割引 | I8: ー | K8: シート「売買契約仕訳帳名-設定値」を参照

Sheet 売買契約仕訳帳名-設定値 (調達)
A1: 売買契約仕訳帳名（調達）-設定値
A2: ■凡例「必須：システム上必須」「必須(*)：システムで必須ではないが、トランザクション上や業務などで必須」
A3: パラメータ設定一覧へ
B4: # | C4: 売買契約仕訳帳名
C5: 名前 | D5: 説明 | E5: 関係
C6: 文字列 | D6: 文字列 | E6: 価格（購買） 行割引（仕入） 複数行割引（仕入） 割引合計（購買） 価格（販売） 行割引（販売側） 複数行割引（販売側） 割引合計（販売） 送料の割引
C7: 必須 | E7: 必須
B8: =ROW() - 7 -> 1
B9: =ROW() - 7 -> 2
B10: =ROW() - 7 -> 3
B11: =ROW() - 7 -> 4
B12: =ROW() - 7 -> 5
B13: =ROW() - 7 -> 6
B14: =ROW() - 7 -> 7

Sheet 売買契約仕訳帳（調達）
A1: 売買契約仕訳帳（調達）
B2: 調達＞価格と割引＞売買契約仕訳帳
B3: Procurement and sourcing > Prices and discounts > Trade agreement journal
A4: パラメータ設定一覧へ
B5: # | C5: タブ | D5: タブ説明 | E5: 項目分類 | F5: 項目 | G5: Description（標準） | H5: 設定可能値 | I5: デフォルト値 | J5: 備考 | K5: 設定値 | L5: 設定基準
B6: =ROW() - 5 -> 1 | C6: 売買契約仕訳帳 | F6: 名前 | H6: 売買仕訳帳名（ユーザー定義） | I6: ー | K6: シート「売買契約仕訳帳-設定値（販売）」を参照
B7: =ROW() - 5 -> 2 | F7: 価格/割引仕訳帳番号 | H7: 自動採番 | I7: ー | J7: 番号順序の設定に準拠する | K7: シート「売買契約仕訳帳-設定値（販売）」を参照
B8: =ROW() - 5 -> 3 | F8: 説明 | H8: 文字列 | I8: ー | K8: シート「売買契約仕訳帳-設定値（販売）」を参照
B9: =ROW() - 5 -> 4 | F9: 転記済 | H9: チェック/チェック無 | I9: ー | J9: 転記したら自動で入る | K9: シート「売買契約仕訳帳-設定値（販売）」を参照
B10: =ROW() - 5 -> 5 | F10: 転記日 | H10: 日付 | I10: ー | J10: 転記したら自動で入る | K10: シート「売買契約仕訳帳-設定値（販売）」を参照
B11: =ROW() - 5 -> 6 | F11: 既定のリレーション | H11: 価格（購買） 行割引（仕入） 複数行割引（仕入） 割引合計（購買） 価格（販売） 行割引（販売側） 複数行割引（販売側） 割引合計（販売） 送料の割引 | I11: 「名前」で売買契約仕訳帳名を選択したら既定値が自動反映される | K11: シート「売買契約仕訳帳-設定値（販売）」を参照
B12: =ROW() - 5 -> 7 | F12: 現在の価格のエクスポート | H12: チェック/チェック無 | I12: チェック無 | K12: シート「売買契約仕訳帳-設定値（販売）」を参照
B13: =ROW() - 5 -> 8 | C13: 仕訳帳明細行 | E13: 概要 | F13: 変更済 | H13: （自動） | I13: ー | J13: 明細の変更によって自動で反映される | K13: シート「売買契約仕訳帳-設定値（販売）」を参照
B14: =ROW() - 5 -> 9 | F14: 関係 | G14: 購買および販売ドキュメントは売買契約を使用し、タイプに応じて価格または割引を適用します。特定の品目、特定の品目グループ、またはすべての品目に対して価格または割引を設定するために、売買契約の仕訳帳明細行を構成することができます。 | H14: 価格（購買） 行割引（仕入） 複数行割引（仕入） 割引合計（購買） 価格（販売） 行割引（販売側） 複数行割引（販売側） 割引合計（販売） 送料の割引 | I14: 「名前」で売買契約仕訳帳名を選択したら既定値が自動反映される | K14: シート「売買契約仕訳帳-設定値（販売）」を参照
B15: =ROW() - 5 -> 10 | F15: 関係者コードタイプ | H15: テーブル グループ すべて | I15: すべて | J15: テーブル：顧客個別に価格を設定する場合に選択 グループ：価格/割引グループ別に価格を設定する場合に選択 すべて：すべての顧客に対して価格を設定する場合に選択 | K15: シート「売買契約仕訳帳-設定値（販売）」を参照
B16: =ROW() - 5 -> 11 | F16: 勘定の選択 | H16: テーブル：顧客（ユーザー定義） グループ：価格/割引グループ（ユーザー定義） すべて：選択不可 | I16: ー | J16: 「関係者コードタイプ」で選択した値によって、価格の設定をする対象を選択 | K16: シート「売買契約仕訳帳-設定値（販売）」を参照
B17: =ROW() - 5 -> 12 | F17: 製品コードタイプ | H17: テーブル グループ すべて | I17: テーブル | J17: テーブル：製品個別に価格を設定する場合に選択 グループ：価格/割引グループ別に価格を設定する場合に選択 すべて：すべての製品に対して価格を設定する場合に選択 | K17: シート「売買契約仕訳帳-設定値（販売）」を参照
B18: =ROW() - 5 -> 13 | F18: 品目関係 | H18: テーブル：製品（ユーザー定義） グループ：価格/割引グループ（ユーザー定義） すべて：選択不可 | I18: ー | J18: 「製品コードタイプ」で選択した値によって、価格の設定をする対象を選択 | K18: シート「売買契約仕訳帳-設定値（販売）」を参照
B19: =ROW() - 5 -> 14 | F19: コンフィギュレーション | G19: [品目コード] フィールドで選択したタイプの品目またはタイプ グループを選択します。 | H19: （製品マスタから反映） | I19: ー | K19: シート「売買契約仕訳帳-設定値（販売）」を参照
B20: =ROW() - 5 -> 15 | F20: サイズ | H20: （製品マスタから反映） | I20: ー | K20: シート「売買契約仕訳帳-設定値（販売）」を参照
B21: =ROW() - 5 -> 16 | F21: 色 | H21: （製品マスタから反映） | I21: ー | K21: シート「売買契約仕訳帳-設定値（販売）」を参照
B22: =ROW() - 5 -> 17 | F22: スタイル | H22: （製品マスタから反映） | I22: ー | K22: シート「売買契約仕訳帳-設定値（販売）」を参照
B23: =ROW() - 5 -> 18 | F23: サイト | H23: サイト（ユーザー定義） | I23: ー | K23: シート「売買契約仕訳帳-設定値（販売）」を参照
B24: =ROW() - 5 -> 19 | F24: 倉庫 | H24: 倉庫（ユーザー定義） | I24: ー | K24: シート「売買契約仕訳帳-設定値（販売）」を参照
B25: =ROW() - 5 -> 20 | F25: 開始数量 | G25: 価格、ライン割引、マルチライン割引が適用される最小数量を入力します。 (ここに入力した数値を含みます。例: この数量が 1 に設定されている場合は、数量が 1 を含むこの値以上の場合に、この契約が適用されます) 。 この値はまた、割引合計のオーダー残高の最小値です。 | H25: 数値 | I25: 0.00 | K25: シート「売買契約仕訳帳-設定値（販売）」を参照
B26: =ROW() - 5 -> 21 | F26: 終了数量 | G26: 価格、ライン割引、マルチライン割引が適用される最大数量を入力します。 (ここに入力した数値は含まれません。例: この数量が 3.00 に設定されている場合は、2.99 までの契約が適用されます)。 この値はまた、割引合計のオーダー残高の上限値です。 | H26: 数値 | I26: ー | K26: シート「売買契約仕訳帳-設定値（販売）」を参照
B27: =ROW() - 5 -> 22 | F27: 単位 | H27: 単位（ユーザー定義） | K27: シート「売買契約仕訳帳-設定値（販売）」を参照
B28: =ROW() - 5 -> 23 | F28: 通貨金額 | H28: 数値 | I28: 0.00 | K28: シート「売買契約仕訳帳-設定値（販売）」を参照
B29: =ROW() - 5 -> 24 | F29: 通貨 | H29: 通貨（ユーザー定義） | J29: ここに設定したい価格を入力する | K29: シート「売買契約仕訳帳-設定値（販売）」を参照
B30: =ROW() - 5 -> 25 | F30: 均一層の金額 | H30: 数値 | I30: 0.00 | K30: シート「売買契約仕訳帳-設定値（販売）」を参照
B31: =ROW() - 5 -> 26 | F31: 属性ベースの価格決定ID | H31: 属性ベースの価格決定データ（ユーザー定義） | I31: ー | K31: シート「売買契約仕訳帳-設定値（販売）」を参照
B32: =ROW() - 5 -> 27 | F32: 分析コードの検証 | H32: （自動） | I32: ー | J32: 検証実施により自動で値が入る | K32: シート「売買契約仕訳帳-設定値（販売）」を参照
B33: =ROW() - 5 -> 28 | F33: 売買契約検証 | H33: （自動） | I33: ー | J33: 検証実施により自動で値が入る | K33: シート「売買契約仕訳帳-設定値（販売）」を参照
B34: =ROW() - 5 -> 29 | E34: 詳細 | F34: 開始日 | H34: 日付 | I34: ー | J34: 価格を使用する開始日を入力する | K34: シート「売買契約仕訳帳-設定値（販売）」を参照
B35: =ROW() - 5 -> 30 | F35: 終了日 | H35: 日付 | I35: ー | J35: 価格を使用する終了日を入力する | K35: シート「売買契約仕訳帳-設定値（販売）」を参照
B36: =ROW() - 5 -> 31 | F36: 諸費用価格 | G36: 価格の固定。これらの請求は請求書ごとに１回、適用されます。 | H36: 数値 | I36: 0.00 | K36: シート「売買契約仕訳帳-設定値（販売）」を参照
B37: =ROW() - 5 -> 32 | F37: 価格単位 | H37: 数値 | I37: 1.00 | K37: シート「売買契約仕訳帳-設定値（販売）」を参照
B38: =ROW() - 5 -> 33 | F38: 割引率１ | G38: 割引率１と割引率２の合計：総額 - パーセンテージ 1% - パーセンテージ 2% | H38: 数値 | I38: 0.00 | K38: シート「売買契約仕訳帳-設定値（販売）」を参照
B39: =ROW() - 5 -> 34 | F39: 割引率２ | G39: 割引率１と割引率２の合計：総額 - パーセンテージ 1% - パーセンテージ 2% | H39: 数値 | I39: 0.00 | K39: シート「売買契約仕訳帳-設定値（販売）」を参照
B40: =ROW() - 5 -> 35 | F40: リードタイム | G40: 日単位のリードタイム | H40: 数値 | I40: 0 | K40: シート「売買契約仕訳帳-設定値（販売）」を参照
B41: =ROW() - 5 -> 36 | F41: 作業日 | H41: はい/いいえ | I41: いいえ | K41: シート「売買契約仕訳帳-設定値（販売）」を参照
B42: =ROW() - 5 -> 37 | F42: リードタイムの無視 | H42: はい/いいえ | I42: はい | K42: シート「売買契約仕訳帳-設定値（販売）」を参照
B43: =ROW() - 5 -> 38 | F43: 一般通貨を含めます | G43: 売買契約を一般通貨から別の通貨に換算できることを保証するため、このオプションを選択します。このフィールドは、[リレーション] フィールドの [価格 (販売)] オプション の値を選択した場合にのみ、および通貨が [売掛金勘定パラメータ] のページの [一般通貨] のフィールドで定義された一般通貨である場合にのみ使用できます。 | H43: はい/いいえ | I43: いいえ | K43: シート「売買契約仕訳帳-設定値（販売）」を参照
B44: =ROW() - 5 -> 39 | F44: 次を検索 | G44: 割引の組み合わせの継続検索に使用されるの基準。 | H44: はい/いいえ | I44: はい | K44: シート「売買契約仕訳帳-設定値（販売）」を参照
B45: =ROW() - 5 -> 40 | E45: エラーログ | F45: ログ | H45: （自動） | I45: ー | J45: エラーが発生した場合に自動で値が入る | K45: シート「売買契約仕訳帳-設定値（販売）」を参照

Sheet 売買契約仕訳帳-設定値（調達）
A1: 売買契約仕訳帳（調達）-設定値 ※基本的には移行データを正とする
A2: ■凡例「必須：システム上必須」「必須(*)：システムで必須ではないが、トランザクション上や業務などで必須」
A3: パラメータ設定一覧へ
B4: # | C4: 売買契約仕訳帳 | J4: 仕訳帳明細行
J5: 概要 | AE5: 詳細 | AP5: エラーログ
C6: 名前 | D6: 価格/割引仕訳帳番号 | E6: 説明 | F6: 転記済 | G6: 転記日 | H6: 既定のリレーション | I6: 現在の価格のエクスポート | J6: 変更済 | K6: 関係 | L6: 関係者コードタイプ | M6: 勘定の選択 | N6: 製品コードタイプ | O6: 品目関係 | P6: コンフィギュレーション | Q6: サイズ | R6: 色 | S6: スタイル | T6: サイト | U6: 倉庫 | V6: 開始数量 | W6: 終了数量 | X6: 単位 | Y6: 通貨金額 | Z6: 通貨 | AA6: 均一層の金額 | AB6: 属性ベースの価格決定ID | AC6: 分析コードの検証 | AD6: 売買契約検証 | AE6: 開始日 | AF6: 終了日 | AG6: 諸費用価格 | AH6: 価格単位 | AI6: 割引率１ | AJ6: 割引率２ | AK6: リードタイム | AL6: 作業日 | AM6: リードタイムの無視 | AN6: 一般通貨を含めます | AO6: 次を検索 | AP6: ログ
C7: 売買仕訳帳名（ユーザー定義） | D7: 自動採番 | E7: 文字列 | F7: チェック/チェック無 | G7: 日付 | H7: 価格（購買） 行割引（仕入） 複数行割引（仕入） 割引合計（購買） 価格（販売） 行割引（販売側） 複数行割引（販売側） 割引合計（販売） 送料の割引 | I7: チェック/チェック無 | J7: （自動） | K7: 価格（購買） 行割引（仕入） 複数行割引（仕入） 割引合計（購買） 価格（販売） 行割引（販売側） 複数行割引（販売側） 割引合計（販売） 送料の割引 | L7: テーブル グループ すべて | M7: テーブル：顧客（ユーザー定義） グループ：価格/割引グループ（ユーザー定義） すべて：選択不可 | N7: テーブル グループ すべて | O7: テーブル：製品（ユーザー定義） グループ：価格/割引グループ（ユーザー定義） すべて：選択不可 | P7: （製品マスタから反映） | Q7: （製品マスタから反映） | R7: （製品マスタから反映） | S7: （製品マスタから反映） | T7: サイト（ユーザー定義） | U7: 倉庫（ユーザー定義） | V7: 数値 | W7: 数値 | X7: 単位（ユーザー定義） | Y7: 数値 | Z7: 通貨（ユーザー定義） | AA7: 数値 | AB7: 属性ベースの価格決定データ（ユーザー定義） | AC7: （自動） | AD7: （自動） | AE7: 日付 | AF7: 日付 | AG7: 数値 | AH7: 数値 | AI7: 数値 | AJ7: 数値 | AK7: 数値 | AL7: はい/いいえ | AM7: はい/いいえ | AN7: はい/いいえ | AO7: はい/いいえ | AP7: （自動）
C8: 必須 | D8: （自動） | F8: （自動） | G8: （自動） | H8: 必須 | J8: （自動） | K8: 必須(*) | L8: 必須(*) | M8: 必須(*) | N8: 必須(*) | O8: 必須(*) | Y8: 必須(*) | Z8: 必須
B9: =ROW() - 8 -> 1
B10: =ROW() - 8 -> 2
B11: =ROW() - 8 -> 3
B12: =ROW() - 8 -> 4
B13: =ROW() - 8 -> 5
B14: =ROW() - 8 -> 6
B15: =ROW() - 8 -> 7
B16: =ROW() - 8 -> 8
B17: =ROW() - 8 -> 9
B18: =ROW() - 8 -> 10
B19: =ROW() - 8 -> 11
B20: =ROW() - 8 -> 12
... B38: =ROW() - 8 -> 30

Sheet 仕入先
A1: 仕入先
B2: 買掛金管理＞仕入先＞すべての仕入先
B3: Accounts payable > Vendors > All vendors
A4: パラメータ設定一覧へ
B5: # | C5: タブ | D5: タブ説明 | E5: 項目分類 | F5: 項目 | G5: 項目説明 | H5: 設定可能値 | I5: デフォルト値 | J5: 備考 | K5: 設定値 | L5: 設定基準
B6: =ROW() - 5 -> 1 | C6: 一般 | E6: 関係者の関連付けの変更 | F6: 勘定 | H6: 入力不可 | I6: ー | K6: 「仕入先-設定値」を参照
B7: =ROW() - 5 -> 2 | F7: 関連付けられている当事者 | H7: 入力不可 | I7: ー | K7: 「仕入先-設定値」を参照
B8: =ROW() - 5 -> 3 | H8: 入力不可 | I8: ー | K8: 「仕入先-設定値」を参照
B9: =ROW() - 5 -> 4 | F9: 新しい関係者レコード | G9: 名前 | H9: 関係者（ユーザー定義） | I9: ー | K9: 「仕入先-設定値」を参照
B10: =ROW() - 5 -> 5 | H10: 入力不可 | I10: ー | K10: 「仕入先-設定値」を参照
B11: =ROW() - 5 -> 6 | E11: ID タイプ＞組織 | F11: 仕入先 | H11: 文字列 | I11: ー | J11: 番号順序の設定に準拠する | K11: 「仕入先-設定値」を参照
B12: =ROW() - 5 -> 7 | F12: タイプ | H12: 個人 組織 | I12: 個人 | K12: 「仕入先-設定値」を参照
B13: =ROW() - 5 -> 8 | F13: 支払優先順位 | G13: 支払優先順位の ID です。 | H13: 入力不可 | I13: ー | K13: 「仕入先-設定値」を参照
B14: =ROW() - 5 -> 9 | F14: 名前 | H14: 文字列 | I14: ー | K14: 「仕入先-設定値」を参照
B15: =ROW() - 5 -> 10 | F15: 検索名 | H15: 文字列 | I15: ー | K15: 「仕入先-設定値」を参照
B16: =ROW() - 5 -> 11 | F16: グループ | H16: 仕入先グループ（ユーザー定義） | I16: ー | K16: 「仕入先-設定値」を参照
B17: =ROW() - 5 -> 12 | E17: 組織の詳細 タイプ＞組織 | F17: 従業員数 | H17: 数値 | I17: ー | K17: 「仕入先-設定値」を参照
B18: =ROW() - 5 -> 13 | F18: 組織番号 | H18: 文字列 | I18: ー | K18: 「仕入先-設定値」を参照
B19: =ROW() - 5 -> 14 | F19: ABCコード | H19: なし A B C | I19: なし | K19: 「仕入先-設定値」を参照
B20: =ROW() - 5 -> 15 | F20: DUNS番号 | H20: 数値 | I20: ー | K20: 「仕入先-設定値」を参照
B21: =ROW() - 5 -> 16 | E21: その他の情報 タイプ＞組織 | F21: アドレス帳 | H21: アドレス帳（ユーザー定義） | I21: ー | K21: 「仕入先-設定値」を参照
B22: =ROW() - 5 -> 17 | F22: 呼称 | H22: 文字列 | I22: ー | K22: 「仕入先-設定値」を参照
B23: =ROW() - 5 -> 18 | F23: カナ名 | H23: 文字列 | I23: ー | K23: 「仕入先-設定値」を参照
B24: =ROW() - 5 -> 19 | F24: 言語 | H24: 言語（ユーザー定義） | K24: 「仕入先-設定値」を参照
B25: =ROW() - 5 -> 20 | E25: 仕入先コラボレーション タイプ＞組織 | F25: コラボレーションの有効化 | H25: 無効 有効（POは自動で確認されません） 有効（POが自動で確認されます） | I25: 無効 | K25: 「仕入先-設定値」を参照
B26: =ROW() - 5 -> 21 | E26: ID タイプ＞個人 | F26: 仕入先 | H26: 文字列 | I26: ー | J26: タイプ＞個人 用の設定シートなし
B27: =ROW() - 5 -> 22 | F27: タイプ | H27: 個人 組織 | I27: 個人 | J27: タイプ＞個人 用の設定シートなし
B28: =ROW() - 5 -> 23 | F28: 支払優先順位 | G28: 支払優先順位の ID です。 | H28: 入力不可 | I28: ー | J28: タイプ＞個人 用の設定シートなし
B29: =ROW() - 5 -> 24 | F29: 個人の肩書き | G29: データベースのレコードの固有 ID | H29: 名前のタイトルまたは接尾語（ユーザー定義） | I29: ー | J29: タイプ＞個人 用の設定シートなし
B30: =ROW() - 5 -> 25 | F30: 名 | H30: 文字列 | I30: ー | J30: タイプ＞個人 用の設定シートなし
B31: =ROW() - 5 -> 26 | F31: ミドルネーム | H31: 文字列 | I31: ー | J31: タイプ＞個人 用の設定シートなし
B32: =ROW() - 5 -> 27 | F32: 姓 | H32: 文字列 | I32: ー | J32: タイプ＞個人 用の設定シートなし
B33: =ROW() - 5 -> 28 | F33: 検索名 | H33: 文字列 | I33: ー | J33: タイプ＞個人 用の設定シートなし
B34: =ROW() - 5 -> 29 | F34: 個人の接尾語 | G34: データベースのレコードの固有 ID | H34: 名前のタイトルまたは接尾語（ユーザー定義） | I34: ー | J34: タイプ＞個人 用の設定シートなし
B35: =ROW() - 5 -> 30 | F35: グループ | H35: 仕入先グループ（ユーザー定義） | I35: ー | J35: タイプ＞個人 用の設定シートなし
B36: =ROW() - 5 -> 31 | E36: 名前の詳細 タイプ＞個人 | F36: イニシャル | H36: 文字列 | I36: ー | J36: タイプ＞個人 用の設定シートなし
B37: =ROW() - 5 -> 32 | F37: 呼称 | H37: 文字列 | I37: ー | J37: タイプ＞個人 用の設定シートなし
B38: =ROW() - 5 -> 33 | F38: 表示名 | G38: データベースのレコードの固有 ID | H38: 名前の順序（ユーザー定義） | I38: FirstMiddleLast | J38: タイプ＞個人 用の設定シートなし
B39: =ROW() - 5 -> 34 | F39: 職務の肩書き | H39: 文字列 | I39: ー | J39: タイプ＞個人 用の設定シートなし
B40: =ROW() - 5 -> 35 | F40: 職務の接尾語 | H40: 文字列 | I40: ー | J40: タイプ＞個人 用の設定シートなし
B41: =ROW() - 5 -> 36 | F41: 名（ふりがな） | H41: 文字列 | I41: ー | J41: タイプ＞個人 用の設定シートなし
B42: =ROW() - 5 -> 37 | F42: ミドルネーム（ふりがな） | H42: 文字列 | I42: ー | J42: タイプ＞個人 用の設定シートなし
B43: =ROW() - 5 -> 38 | F43: 姓（ふりがな） | H43: 文字列 | I43: ー | J43: タイプ＞個人 用の設定シートなし
B44: =ROW() - 5 -> 39 | E44: 個人情報 タイプ＞個人 | F44: 性別 | H44: 男性 女性 不特定 | I44: ー | J44: タイプ＞個人 用の設定シートなし
B45: =ROW() - 5 -> 40 | F45: 配偶者の有無 | H45: なし 未婚 既婚 離婚 死別 | I45: なし | J45: タイプ＞個人 用の設定シートなし
B46: =ROW() - 5 -> 41 | E46: 生年月日 タイプ＞個人 | F46: 月 | H46: 1月 2月 3月 4月 5月 6月 7月 8月 9月 10月 11月 12月 | I46: ー | J46: タイプ＞個人 用の設定シートなし
B47: =ROW() - 5 -> 42 | F47: 日 | H47: 数値 | I47: ー | J47: タイプ＞個人 用の設定シートなし
B48: =ROW() - 5 -> 43 | F48: 年 | H48: 数値 | I48: ー | J48: タイプ＞個人 用の設定シートなし
B49: =ROW() - 5 -> 44 | E49: 記念日 タイプ＞個人 | F49: 月 | H49: 1月 2月 3月 4月 5月 6月 7月 8月 9月 10月 11月 12月 | I49: ー | J49: タイプ＞個人 用の設定シートなし
B50: =ROW() - 5 -> 45 | F50: 日 | H50: 数値 | I50: ー | J50: タイプ＞個人 用の設定シートなし
B51: =ROW() - 5 -> 46 | F51: 年 | H51: 数値 | I51: ー | J51: タイプ＞個人 用の設定シートなし
B52: =ROW() - 5 -> 47 | E52: その他の情報 タイプ＞個人 | F52: アドレス帳 | H52: アドレス帳（ユーザー定義） | I52: ー | J52: タイプ＞個人 用の設定シートなし
B53: =ROW() - 5 -> 48 | F53: 言語 | H53: 言語（システム定義） | I53: ー | J53: タイプ＞個人 用の設定シートなし
B54: =ROW() - 5 -> 49 | F54: 子 | H54: 文字列 | I54: ー | J54: タイプ＞個人 用の設定シートなし
B55: =ROW() - 5 -> 50 | F55: 趣味 | H55: 文字列 | I55: ー | J55: タイプ＞個人 用の設定シートなし
B56: =ROW() - 5 -> 51 | E56: 仕入先コラボレーション タイプ＞個人 | F56: コラボレーションの有効化 | G56: 仕入先コラボレーションを有効にするかどうかを選択します。有効とする場合、仕入先が発注書を受け入れる際に、発注書が自動確認されるかどうかを選択できます。 | H56: 無効 有効（POは自動で確認されません） 有効（POが自動で確認されます） | I56: 無効 | J56: タイプ＞個人 用の設定シートなし
B57: =ROW() - 5 -> 52 | C57: 住所 | F57: 名前または説明 | H57: 文字列 | I57: ー | K57: 「仕入先-設定値」を参照
B58: =ROW() - 5 -> 53 | F58: 住所 | H58: 文字列 | I58: ー | K58: 「仕入先-設定値」を参照
B59: =ROW() - 5 -> 54 | F59: 目的 | H59: 業務 委託販売 配送 固定資産 本社 ホーム 請求書 船荷 その他 支払 実際の場所 採用 送金先 サービス 安定した組織 ステートメント SWIFT 船降 | I59: ー | K59: 「仕入先-設定値」を参照
B60: =ROW() - 5 -> 55 | F60: 主要 | H60: チェック有/チェック無 | I60: チェック無 | K60: 「仕入先-設定値」を参照
B61: =ROW() - 5 -> 56 | E61: 詳細オプション | F61: 国/地域 | H61: 国/地域（システム定義） | I61: ー | K61: 「仕入先-設定値」を参照
B62: =ROW() - 5 -> 57 | F62: 郵便番号 | H62: 文字列 | I62: ー | K62: 「仕入先-設定値」を参照
B63: =ROW() - 5 -> 58 | F63: 住所 | H63: 文字列 | I63: ー | K63: 「仕入先-設定値」を参照
B64: =ROW() - 5 -> 59 | F64: 市町村 | H64: 文字列 | I64: ー | K64: 「仕入先-設定値」を参照
B65: =ROW() - 5 -> 60 | F65: 都道府県 | H65: 文字列 | I65: ー | K65: 「仕入先-設定値」を参照
B66: =ROW() - 5 -> 61 | F66: 主要 | H66: はい/いいえ | I66: いいえ | K66: 「仕入先-設定値」を参照
B67: =ROW() - 5 -> 62 | F67: プライベート | H67: はい/いいえ | I67: いいえ | K67: 「仕入先-設定値」を参照
B68: =ROW() - 5 -> 63 | F68: 国/地域に関する基本事項 | H68: はい/いいえ | I68: いいえ | K68: 「仕入先-設定値」を参照
B69: =ROW() - 5 -> 64 | C69: 連絡先情報 | F69: 説明 | H69: 文字列 | I69: ー | K69: 「仕入先-設定値」を参照
B70: =ROW() - 5 -> 65 | F70: タイプ | H70: 電話 電子メールアドレス URL テレックス FAX Facebook Twitter LinkedIn | I70: ー | K70: 「仕入先-設定値」を参照
B71: =ROW() - 5 -> 66 | F71: 連絡先の電話番号/住所 | H71: 文字列 | I71: ー | K71: 「仕入先-設定値」を参照
B72: =ROW() - 5 -> 67 | F72: 内線 | H72: 文字列 | I72: ー | J72: タイプで以下を設定した場合に設定 電話 FAX | K72: 「仕入先-設定値」を参照
B73: =ROW() - 5 -> 68 | F73: 主要 | H73: チェック有/チェック無 | I73: チェック無 | K73: 「仕入先-設定値」を参照
B74: =ROW() - 5 -> 69 | C74: その他の詳細 | E74: 貸方 | F74: 信用格付け | H74: 文字列 | I74: ー | K74: 「仕入先-設定値」を参照
B75: =ROW() - 5 -> 70 | F75: 与信限度額 | G75: 標準通貨金額 (国の通貨) | H75: 数値 | I75: ー | K75: 「仕入先-設定値」を参照
B76: =ROW() - 5 -> 71 | E76: 管理 | F76: 購入担当グループ | H76: 購入担当グループ（ユーザー定義） | I76: ー | K76: 「仕入先-設定値」を参照
B77: =ROW() - 5 -> 72 | E77: 現在の保留状態 | F77: 仕入先保留 | H77: 入力不可 | I77: いいえ | K77: 「仕入先-設定値」を参照
B78: =ROW() - 5 -> 73 | F78: 理由コード | H78: 入力不可 | I78: ー | K78: 「仕入先-設定値」を参照
B79: =ROW() - 5 -> 74 | F79: 仕入先保留のリリース日 | H79: 入力不可 | I79: ー | K79: 「仕入先-設定値」を参照
B80: =ROW() - 5 -> 75 | E80: 会社間 | F80: 有効 | H80: はい/いいえ | I80: いいえ | K80: 「仕入先-設定値」を参照
B81: =ROW() - 5 -> 76 | F81: 会社 | G81: 選択可能な会社の ID | H81: 入力不可 | I81: ー | K81: 「仕入先-設定値」を参照
B82: =ROW() - 5 -> 77 | F82: 顧客ID | H82: 入力不可 | I82: ー | K82: 「仕入先-設定値」を参照
B83: =ROW() - 5 -> 78 | E83: リベート | F83: 仕入先リベートグループ | H83: 仕入先リベートグループ（ユーザー定義） | I83: ー | K83: 「仕入先-設定値」を参照
B84: =ROW() - 5 -> 79 | E84: 航海 | F84: 出荷タイプ | H84: なし 出荷会社 関税ブローカー エージェント | I84: なし | K84: 「仕入先-設定値」を参照
B85: =ROW() - 5 -> 80 | F85: 原価タイプグループ | H85: 原価タイプグループ（ユーザー定義） | I85: ー | K85: 「仕入先-設定値」を参照
B86: =ROW() - 5 -> 81 | F86: 出荷元港 | H86: 出荷港（ユーザー定義） | I86: ー | K86: 「仕入先-設定値」を参照
B87: =ROW() - 5 -> 82 | F87: エージェント | H87: 仕入先（ユーザー定義） | I87: ー | K87: 「仕入先-設定値」を参照
B88: =ROW() - 5 -> 83 | F88: 輸入原価仕入先 | H88: はい/いいえ | I88: いいえ | K88: 「仕入先-設定値」を参照
B89: =ROW() - 5 -> 84 | F89: 出荷会社 | H89: 仕入先（ユーザー定義） | I89: ー | K89: 「仕入先-設定値」を参照
B90: =ROW() - 5 -> 85 | F90: サービスプロバイダー | H90: はい/いいえ | I90: いいえ | K90: 「仕入先-設定値」を参照
B91: =ROW() - 5 -> 86 | F91: 過剰/過少許容範囲グループ | H91: 過剰/過少許容範囲グループ（ユーザー定義） | I91: ー | K91: 「仕入先-設定値」を参照
B92: =ROW() - 5 -> 87 | C92: 仕入先のプロファイル | F92: 入札のみ | H92: チェック有/チェック無 | I92: チェック無 | K92: 「仕入先-設定値」を参照
B93: =ROW() - 5 -> 88 | F93: 一時仕入先 | H93: チェック有/チェック無 | I93: チェック無 | K93: 「仕入先-設定値」を参照
B94: =ROW() - 5 -> 89 | F94: ローカル所有 | H94: チェック有/チェック無 | I94: チェック無 | K94: 「仕入先-設定値」を参照
B95: =ROW() - 5 -> 90 | F95: 小規模ビジネス | H95: チェック有/チェック無 | I95: チェック無 | K95: 「仕入先-設定値」を参照
B96: =ROW() - 5 -> 91 | F96: 出身民族 | H96: 入力不可 | I96: ー | K96: 「仕入先-設定値」を参照
B97: =ROW() - 5 -> 92 | F97: 所有者は退役軍人 | H97: チェック有/チェック無 | I97: チェック無 | K97: 「仕入先-設定値」を参照
B98: =ROW() - 5 -> 93 | F98: 所有者は身体障碍者 | H98: チェック有/チェック無 | I98: チェック無 | K98: 「仕入先-設定値」を参照
B99: =ROW() - 5 -> 94 | C99: 購買に関する顧客方法 | F99: 通貨 | H99: 通貨（ユーザー定義） | I99: ー | K99: 「仕入先-設定値」を参照
B100: =ROW() - 5 -> 95 | F100: 基本連絡先 | H100: 連絡先（ユーザー定義） | I100: ー | K100: 「仕入先-設定値」を参照
...

Sheet 仕入先-設定値
A1: 仕入先-設定値 ※基本的には移行データを正とする
A2: ■凡例「必須：システム上必須」「必須(*)：システムで必須ではないが、トランザクション上や業務などで必須」
A3: パラメータ設定一覧へ
B4: # | C4: 一般 | AQ4: 住所 | BC4: 連絡先情報 | BH4: その他の詳細 | BZ4: 仕入先のプロファイル | CG4: 購買に関する顧客方法 | CO4: 請求書と出荷 | DD4: 発注書の既定値 | DX4: 支払 | EM4: 小売 | FA4: 財務分析コード
C5: ID | I5: 組織の詳細 | M5: その他の情報 | Q5: 仕入先コラボレーション | R5: タイプ＞個人 | W5: タイプ＞個人＞名前の詳細情報 | AE5: タイプ＞個人＞個人情報 | AG5: タイプ＞個人＞生年月日 | AJ5: タイプ＞個人＞記念日 | AM5: タイプ＞個人＞その他の情報 | AU5: 詳細オプション | BH5: 貸方 | BK5: 現在の保留状態 | BN5: 会社間 | BQ5: リベート | BR5: 航海 | CO5: 請求書 | CS5: 相手勘定 | CU5: 配送日 | CY5: 消費税 | DB5: 源泉徴収税 | DD5: 発注書 | DO5: 割引 | DS5: 提供品 | DT5: 発注書の変更管理 | DW5: 詳細なメモ | DX5: 支払 | EK5: 中央銀行への通知 | EM5: 丸め | EQ5: 為替レート | ES5: タイプ | ET5: 小売仕入先製品階層 | EU5: バーコード | EW5: 補充 | EX5: バリアント | FA5: 既定の財務分析コード ※使用する財務分析コード分列追加
C6: 仕入先 | D6: タイプ | E6: 支払の優先順位 | F6: 名前 | G6: 検索名 | H6: グループ | I6: 従業員数 | J6: 組織番号 | K6: ABCコード | L6: DUNS番号 | M6: アドレス帳 | N6: 呼称 | O6: カナ名 | P6: 言語 | Q6: コラボレーションの有効化 | R6: 個人の肩書き | S6: 名 | T6: ミドルネーム | U6: 姓 | V6: 個人の接尾語 | W6: イニシャル | X6: 呼称 | Y6: 表示名 | Z6: 職務の肩書き | AA6: 職務の接尾語 | AB6: 名（ふりがな） | AC6: ミドルネーム（ふりがな） | AD6: 姓（ふりがな） | AE6: 性別 | AF6: 配偶者の有無 | AG6: 月 | AH6: 日 | AI6: 年 | AJ6: 月 | AK6: 日 | AL6: 年 | AM6: アドレス帳 | AN6: 言語 | AO6: 子 | AP6: 趣味 | AQ6: 名前または説明 | AR6: 住所 | AS6: 目的 | AT6: 主要 | AU6: 国/地域 | AV6: 郵便番号 | AW6: 住所 | AX6: 市町村 | AY6: 都道府県 | AZ6: 主要 | BA6: プライベート | BB6: 国/地域に関する基本事項 | BC6: 説明 | BD6: タイプ | BE6: 連絡先の電話番号/住所 | BF6: 内線 | BG6: 主要 | BH6: 信用格付け | BI6: 与信限度額 | BJ6: 購入担当者グループ | BK6: 仕入先保留 | BL6: 理由コード | BM6: 仕入先保留のリリース日 | BN6: 有効 | BO6: 会社 | BP6: 顧客ID | BQ6: 仕入先リベートグループ | BR6: 出荷タイプ | BS6: 原価タイプグループ | BT6: 出荷元港 | BU6: エージェント | BV6: 輸入原価仕入先 | BW6: 出荷会社 | BX6: サービスプロバイダー | BY6: 過剰/過少許容範囲グループ | BZ6: 入札のみ | CA6: 一時仕入先 | CB6: ローカル所有 | CC6: 小規模ビジネス | CD6: 出身民族 | CE6: 所有者は退役軍人 | CF6: 所有者は身体障碍者 | CG6: 通貨 | CH6: 基本連絡先 | CI6: 業種 | CJ6: 担当従業員 | CK6: 区分 | CL6: 小区分 | CM6: チェーン | CN6: メモ | CO6: 請求先/元 ID | CP6: 番号順序グループ | CQ6: 仕入先価格許容範囲グループ | CR6: 仕入先例外グループ | CS6: 勘定タイプ | CT6: 相手勘定 | CU6: UPSゾーン | CV6: 配送条件 | CW6: 荷渡方法 | CX6: 出荷先コード | CY6: 消費税グループ | CZ6: 税込価格 | DA6: 課税控除番号 | DB6: 源泉徴収税の計算 | DC6: 源泉徴収税グループ | DD6: 諸掛グループ | DE6: サイト | DF6: 倉庫 | DG6: 既定の在庫状態ID | DH6: 品目-仕入先グループ | DI6: 購買管理グループ | DJ6: 自社の勘定番号 | DK6: トランザクション通貨の金額 | DL6: 発注書価格/金額 | DM6: 購買カレンダー | DN6: CXML 経由で発注書を送信します | DO6: 複数行割引 | DP6: 割引合計グループ | DQ6: 価格グループ | DR6: 行割引グループ | DS6: 提供品グループ | DT6: 上書きの設定 | DU6: 変更管理の有効化 | DV6: 発注書ごとの設定の上書を許可 | DW6: 詳細なメモグループ | DX6: 支払条件 | DY6: 支払方法 | DZ6: 支払タイプ | EA6: 支払詳細 | EB6: 支払スケジュール | EC6: 現金割引 | ED6: 銀行口座 | EE6: 支払ID | EF6: 支払期日 | EG6: 銀行口座番号 | EH6: 現金割引の使用 | EI6: 仕入先が支払手数料を支払う | EJ6: 仕入先の支払手数料グループ | EK6: 中央銀行目的コード | EL6: 通知内容 | EM6: 販売価格の丸め | EN6: 丸め方法 | EO6: 価格のポイントグループ | EP6: 価格ポイントの丸め | EQ6: 固定レート | ER6: 固定為替レート | ES6: 仕入先タイプ | ET6: 階層 | EU6: 必要に応じてバーコード作成 | EV6: バーコード番号順序 | EW6: サービスカテゴリ | EX6: スタイルの接頭語 | EY6: サイズの接頭語 | EZ6: 色の接頭語 | FA6: XXXXXX | FB6: XXXXXX | FC6: XXXXXX
C7: 文字列 （番号順序の設定に準拠するため、手動入力、自動採番どちらも可能） | D7: 個人 組織 | E7: 入力不可 | F7: 文字列 | G7: 文字列 | H7: 仕入先グループ（ユーザー定義） | I7: 数値 | J7: 文字列 | K7: なし/A/B/C | L7: 数値 | M7: アドレス帳（ユーザー定義） | N7: 文字列 | O7: 文字列 | P7: 言語（ユーザー定義） | Q7: 無効 有効（POは自動で確認されません） 有効（POが自動で確認されます） | R7: 名前のタイトルまたは接尾語（ユーザー定義） | S7: 文字列 | T7: 文字列 | U7: 文字列 | V7: 名前のタイトルまたは接尾語（ユーザー定義） | W7: 文字列 | X7: 文字列 | Y7: 名前の順序（ユーザー定義） | Z7: 文字列 | AA7: 文字列 | AB7: 文字列 | AC7: 文字列 | AD7: 文字列 | AE7: 男性 女性 不特定 | AF7: なし 未婚 既婚 離婚 死別 | AG7: 1月 2月 3月 4月 5月 6月 7月 8月 9月 10月 11月 12月 | AH7: 数値 | AI7: 数値 | AJ7: 1月 2月 3月 4月 5月 6月 7月 8月 9月 10月 11月 12月 | AK7: 数値 | AL7: 数値 | AM7: アドレス帳（ユーザー定義） | AN7: 言語（システム定義） | AO7: 文字列 | AP7: 文字列 | AQ7: 文字列 | AR7: 文字列 | AT7: はい/いいえ | AU7: 国/地域（システム定義） | AV7: 文字列 | AW7: 文字列 | AX7: 文字列 | AY7: 文字列 | AZ7: はい/いいえ | BA7: はい/いいえ | BB7: はい/いいえ | BC7: 文字列 | BD7: 電話 電子メールアドレス URL テレックス FAX Facebook Twitter LinkedIn | BE7: 文字列 | BF7: 文字列 | BG7: はい/いいえ | BH7: 文字列 | BI7: 数値 | BJ7: 購入担当グループ（ユーザー定義） | BK7: 自動入力 | BL7: 入力不可 | BM7: 入力不可 | BN7: はい/いいえ | BO7: 入力不可 | BP7: 入力不可 | BQ7: 仕入先リベートグループ（ユーザー定義） | BR7: なし 出荷会社 関税ブローカー エージェント | BS7: 原価タイプグループ（ユーザー定義） | BT7: 出荷港（ユーザー定義） | BU7: 仕入先（ユーザー定義） | BV7: はい/いいえ | BW7: 仕入先（ユーザー定義） | BX7: はい/いいえ | BY7: 過剰/過少許容範囲グループ（ユーザー定義） | BZ7: チェック有/チェック無 | CA7: チェック有/チェック無 | CB7: チェック有/チェック無 | CC7: チェック有/チェック無 | CD7: 入力不可 | CE7: チェック有/チェック無 | CF7: チェック有/チェック無 | CG7: 通貨（ユーザー定義） | CH7: 連絡先（ユーザー定義） | CI7: 業種（ユーザー定義） | CJ7: 作業者（ユーザー定義） | CK7: 区分（ユーザー定義） | CL7: 小区分（ユーザー定義） | CM7: 会社グループ（ユーザー定義） | CN7: 文字列 | CO7: 仕入先（ユーザー定義） | CP7: 番号順序グループ（ユーザー定義） | CQ7: 仕入先価格許容範囲グループ（ユーザー定義） | CR7: 仕入先例外グループ（ユーザー定義） | CS7: 自動入力 | CT7: 自動入力 | CU7: 文字列 | CV7: 配送条件（ユーザー定義） | CW7: 荷渡方法（ユーザー定義） | CX7: 出荷先コード（ユーザー定義） | CY7: 消費税グループ（ユーザー定義） | CZ7: はい/いいえ | DA7: 課税控除番号（ユーザー定義） | DB7: はい/いいえ | DC7: 源泉徴収税グループ（ユーザー定義） | DD7: 諸掛グループ（ユーザー定義） | DE7: サイト（ユーザー定義） | DF7: 倉庫（ユーザー定義） | DG7: 在庫状態（ユーザー定義） | DH7: 外部品目説明グループ（ユーザー定義） | DI7: 購買管理グループ（ユーザー定義） | DJ7: 文字列 | DK7: 自動入力 | DL7: はい/いいえ | DM7: 作業時間カレンダー（ユーザー定義） | DN7: はい/いいえ | DO7: 価格/割引グループ（ユーザー定義） | DP7: 価格/割引グループ（ユーザー定義） | DQ7: 価格/割引グループ（ユーザー定義） | DR7: 価格/割引グループ（ユーザー定義） | DS7: 提供品グループ（ユーザー定義） | DT7: はい/いいえ | DU7: はい/いいえ | DV7: はい/いいえ | DW7: 詳細なメモグループ（ユーザー定義） | DX7: 支払条件（ユーザー定義） | DY7: 支払方法（ユーザー定義） | DZ7: 入力不可 | EA7: 支払詳細（ユーザー定義） | EB7: 支払スケジュール（ユーザー定義） | EC7: 現金割引（ユーザー定義） | ED7: 仕入先の銀行口座（ユーザー定義） | EE7: 文字列 | EF7: 支払期日（ユーザー定義） | EG7: 入力不可 | EH7: 標準 常時 なし | EI7: はい/いいえ | EJ7: 入力不可 | EK7: 支払目的コード（ユーザー定義） | EL7: 文字列 | EM7: なし 丸め 価格ポイント | EN7: [丸め]を選択した場合のみ ⇒文字列（ユーザー定義） | EO7: [価格ポイント]を選択した場合のみ ⇒文字列（ユーザー定義） | EP7: [価格ポイント]を選択した場合のみ ⇒ 切り上げ / 切り捨て / 四捨五入 | EQ7: はい/いいえ | ER7: 数値 | ES7: 独自 サードパーティ | ET7: カテゴリ階層（ユーザー定義） | EU7: はい/いいえ | EV7: 文字列（ユーザー定義） ※リスト選択 | EW7: サービスカテゴリ（ユーザー定義） | EX7: 文字列 | EY7: 文字列 | EZ7: 文字列
C8: 必須 | D8: 必須 | F8: 必須（タイプ：組織の場合） | H8: 必須 | S8: 必須（タイプ：個人の場合） | T8: 必須（タイプ：個人の場合） | U8: 必須（タイプ：個人の場合） | CG8: 必須 | CY8: 必須(*) | DX8: 必須(*) | DY8: 必須(*)
B9: 例 | C9: TEST_Vend-001 | D9: 組織 | F9: テスト仕入先株式会社 | H9: VG01 ※グループの設定は別途検討 | CG9: JPY | CY9: 国内仕入 ※グループの設定は別途検討 | DX9: 月末締翌月末払い | DY9: 銀行振込
B10: =ROW() - 9 -> 1
B11: =ROW() - 9 -> 2
B12: =ROW() - 9 -> 3
B13: =ROW() - 9 -> 4
B14: =ROW() - 9 -> 5
B15: =ROW() - 9 -> 6
B16: =ROW() - 9 -> 7
B17: =ROW() - 9 -> 8
B18: =ROW() - 9 -> 9
B19: =ROW() - 9 -> 10

Sheet サイト
A1: サイト
B2: 在庫管理＞設定＞在庫詳細＞サイト
B3: Inventory management > Setup > Inventory breakdown > Sites
A4: パラメータ設定一覧へ
B5: # | C5: タブ | D5: タブ説明 | E5: 項目分類 | F5: 項目 | G5: Description（標準） | H5: 設定可能値 | I5: デフォルト値 | J5: 備考 | K5: 設定値 | L5: 設定基準
B6: =ROW() - 5 -> 1 | C6: サイト | F6: サイト | G6: ー | H6: 文字列 | I6: - | K6: 「サイト-設定値」を参照
B7: =ROW() - 5 -> 2 | F7: 名前 | G7: ー | H7: 文字列 | I7: - | K7: 「サイト-設定値」を参照
B8: =ROW() - 5 -> 3 | C8: 一般 | E8: 注文入力 | F8: 注文入力期限グループ | G8: 選択したサイトに適用する注文入力期限グループを選択します。注文入力期限グループでは、特定の顧客のグループに対して注文入力期限が指定されます。 | H8: 注文入力期限グループ（ユーザー定義） | I8: - | K8: 「サイト-設定値」を参照
B9: =ROW() - 5 -> 4 | F9: タイムゾーン | G9: 選択したサイトに適用するタイム ゾーンを選択します。タイム ゾーン情報は、販売注文、販売見積、および移動オーダーの注文入力期限を出荷場所のタイム ゾーンで計算して表示するために使用されます。 | H9: 世界105カ所のタイムゾーンが選択可能 | I9: (GMT+09:00) Osaka, Sapporo, Tokyo | K9: 「サイト-設定値」を参照
B10: =ROW() - 5 -> 5 | E10: マスタープラン | F10: サイト内の移動に振替仕訳帳を使用 | G10: ー | H10: はい/いいえ | I10: いいえ | K10: 「サイト-設定値」を参照
B11: =ROW() - 5 -> 6 | C11: 住所 | F11: 名前または説明 | G11: ー | H11: 文字列 | I11: - | K11: 「サイト-設定値」を参照
B12: =ROW() - 5 -> 7 | F12: 住所 | G12: サイトに対して入力されている既定の配送先住所。住所は、[住所の設定] ページで指定された住所の形式の設定に従って表示されます。 | H12: 文字列 | I12: - | K12: 「サイト-設定値」を参照
B13: =ROW() - 5 -> 8 | F13: 目的 | G13: ー | H13: 業務 委託販売 配送 固定資産 本社 ホーム 請求書 船荷 その他 支払 実際の場所 採用 送金先 サービス 安定した組織 ステートメント SWIFT 船降 | I13: - | K13: 「サイト-設定値」を参照
B14: =ROW() - 5 -> 9 | F14: 主要 | G14: ー | H14: はい/いいえ | I14: - | K14: 「サイト-設定値」を参照
B15: =ROW() - 5 -> 10 | C15: 階層 | F15: 展開 | G15: 階層全体を展開 | H15: - | I15: - | J15: サイトを階層表示する | K15: 「サイト-設定値」を参照
B16: =ROW() - 5 -> 11 | C16: 倉庫 | F16: 既定の在庫状態ID | G16: ー | H16: 在庫状態（ユーザー定義） | I16: - | K16: 「サイト-設定値」を参照
B17: =ROW() - 5 -> 12 | F17: モバイル デバイス ユーザーが別の倉庫で入庫処理を行うことができるようにする | G17: ー | H17: はい/いいえ | I17: いいえ | K17: 「サイト-設定値」を参照

Sheet サイト-設定値
A1: サイト-設定値 ※基本的には移行データを正とする
A2: ■凡例「必須：システム上必須」「必須(*)：システムで必須ではないが、トランザクション上や業務などで必須」 | Q2: 「倉庫-設定値」参照
A3: パラメータ設定一覧へ | Q3: ↓
B4: # | C4: サイト | E4: 一般 | H4: 住所 | Q4: 階層 | R4: 倉庫
C5: サイト | D5: 名前 | E5: 注文入力＞注文入力期限グループ | F5: 注文入力＞タイムゾーン | G5: マスタープラン＞サイト内の移動に振替仕訳帳を使用 | H5: 新しい住所＞場所ID | I5: 新しい住所＞名前または説明 | J5: 新しい住所＞目的 | K5: 新しい住所＞国/地域 | L5: 新しい住所＞郵便番号 | M5: 新しい住所＞住所 | N5: 新しい住所＞市町村 | O5: 新しい住所＞都道府県 | P5: 新しい住所＞主要 | Q5: 折りたたみ | R5: 既定の在庫状態ID | S5: モバイル デバイス ユーザーが別の倉庫で入庫処理を行うことができるようにする
C6: 文字列 | D6: 文字列 | E6: 注文入力期限グループ（ユーザー定義） | F6: 世界105カ所のタイムゾーンが選択可能 | G6: はい/いいえ | H6: （システム自動入力） | I6: 文字列 | J6: 「サイト」シート参照 | K6: 国/地域（システム定義） | L6: 文字列 | M6: 文字列 | N6: 市町村（ユーザー定義） | O6: 都道府県（ユーザー定義） | P6: はい/いいえ | R6: 在庫状態（ユーザー定義） | S6: はい/いいえ
C7: 必須
B8: 例 | C8: JBS | D8: JBS用サイト
B9: =ROW() - 8 -> 1
B10: =ROW() - 8 -> 2
B11: =ROW() - 8 -> 3

Sheet 倉庫
A1: 倉庫
B2: 在庫管理>設定＞在庫詳細＞倉庫
B3: Inventory management > Setup > Inventory breakdown > Warehouse
A4: パラメータ設定一覧へ
B5: # | C5: タブ | D5: タブ説明 | E5: 項目分類 | F5: 項目 | G5: Description（標準） | H5: 設定可能値 | I5: デフォルト値 | J5: 備考 | K5: 設定値 | L5: 設定基準
B6: =ROW() - 5 -> 1 | C6: 概要 | E6: 倉庫 | F6: 倉庫 | G6: ー | H6: 文字列 | I6: ー | K6: 「倉庫-設定値」を参照
B7: =ROW() - 5 -> 2 | F7: 名前 | G7: ー | H7: 文字列 | I7: ー | K7: 「倉庫-設定値」を参照
B8: =ROW() - 5 -> 3 | C8: 一般 | F8: サイト | G8: ー | H8: サイト（ユーザー定義） | I8: ー | K8: 「倉庫-設定値」を参照
B9: =ROW() - 5 -> 4 | F9: タイプ | G9: ー | H9: 既定 検査 通過 | I9: 既定 | K9: 「倉庫-設定値」を参照
B10: =ROW() - 5 -> 5 | F10: 検査倉庫 | G10: 検査指示を作成する前に、各倉庫が個別の検査倉庫に関連付けられている必要があります。 | H10: 倉庫（ユーザー定義） | I10: ー | J10: 「タイプ：既定」の場合のみ入力可能 | K10: 「倉庫-設定値」を参照
B11: =ROW() - 5 -> 6 | F11: トランジット倉庫 | G11: 流通倉庫は、倉庫間で転送中の移動オーダーの追跡に使用されます。これにより、商品の転送中に、手持在庫情報の追跡ができます。たとえば、倉庫間で転送中である注文は、流通倉庫で手持在庫に表示されます。 | H11: 倉庫（ユーザー定義） | I11: ー | J11: 「タイプ：既定」の場合のみ入力可能 | K11: 「倉庫-設定値」を参照
B12: =ROW() - 5 -> 7 | F12: 輸送中の商品の倉庫 | G12: ー | H12: 倉庫（ユーザー定義） | I12: ー | K12: 「倉庫-設定値」を参照
B13: =ROW() - 5 -> 8 | F13: 過少配送倉庫 | G13: ー | H13: 倉庫（ユーザー定義） | I13: ー | K13: 「倉庫-設定値」を参照
B14: =ROW() - 5 -> 9 | E14: 参照 | F14: 仕入先 | G14: ー | H14: 仕入先（ユーザー定義） | I14: ー | K14: 「倉庫-設定値」を参照
B15: =ROW() - 5 -> 10 | C15: マスタープラン | E15: 品目補充 | F15: 手動 | G15: ー | H15: はい/いいえ | I15: いいえ | K15: 「倉庫-設定値」を参照
B16: =ROW() - 5 -> 11 | F16: カレンダー | G16: ー | H16: 作業時間カレンダー（ユーザー定義） | I16: ー | K16: 「倉庫-設定値」を参照
B17: =ROW() - 5 -> 12 | E17: 主要倉庫 | F17: 補充 | G17: ー | H17: はい/いいえ | I17: いいえ | K17: 「倉庫-設定値」を参照
B18: =ROW() - 5 -> 13 | F18: 主要倉庫 | G18: ー | H18: 倉庫（ユーザー定義） | I18: ー | K18: 「倉庫-設定値」を参照
B19: =ROW() - 5 -> 14 | F19: 倉庫のレベル | G19: ー | H19: 操作不可 | I19: 0 | K19: 「倉庫-設定値」を参照
B20: =ROW() - 5 -> 15 | C20: 在庫および倉庫管理 | F20: 既定の受入場所 | G20: 手持在庫が入庫プロセス中に登録されている場合に使用される場所。これは、有効な場所分析コードで保管分析コード グループを使用する品目のあるトランザクションに対しても使用される場所です。 倉庫アプリを使用する場合、場所がライセンス プレートにより制御されていることが必要です。 | H20: 在庫場所（ユーザー定義） | I20: ー | K20: 「倉庫-設定値」を参照
B21: =ROW() - 5 -> 16 | F21: 既定の払出場所 | G21: 出荷プロセス中に使用される場所。これは、有効な場所分析コードで保管分析コード グループを使用する品目のあるトランザクションに対しても使用される場所です。 高度な倉庫プロセスを使用する場合、この設定は無視されます。 | H21: 在庫場所（ユーザー定義） | I21: ー | K21: 「倉庫-設定値」を参照
B22: =ROW() - 5 -> 17 | F22: 既定の生産完成品の場所 | G22: 製造オーダーが完了すると、これは完成品に対して使用される場所です。 | H22: 在庫場所（ユーザー定義） | I22: ー | K22: 「倉庫-設定値」を参照
B23: =ROW() - 5 -> 18 | F23: 既定の生産入庫の場所 | G23: これは原材料消費が行われる場所です。 | H23: 在庫場所（ユーザー定義） | I23: ー | K23: 「倉庫-設定値」を参照
B24: =ROW() - 5 -> 19 | F24: 原材料ピッキング後の払出ステータス | G24: 原材料ピッキングが完了した場合に使用されるステータスを選択します。ピッキング済を選択すると、現物手持在庫が削減されます。引当済現物を選択する場合、材料は、倉庫作業が完了した入力の場所で引当される現物手持在庫として表示されます。 | H24: ピッキング済 引当現物 | I24: ピッキング済 | K24: 「倉庫-設定値」を参照
B25: =ROW() - 5 -> 20 | F25: 既定のかんばん完成品の場所 | G25: かんばんオーダーが完了すると、これは完成品に対して使用される場所です。 | H25: 在庫場所（ユーザー定義） | I25: ー | K25: 「倉庫-設定値」を参照
B26: =ROW() - 5 -> 21 | F26: 既定の出荷管理場所 | G26: ー | H26: 在庫場所（ユーザー定義） | I26: ー | K26: 「倉庫-設定値」を参照
B27: =ROW() - 5 -> 22 | F27: 貸方のみの返品の既定の場所 | G27: ー | H27: 入力不可 | I27: ー | K27: 「倉庫-設定値」を参照
B28: =ROW() - 5 -> 23 | F28: 既定のコンテナータイプ | G28: ライセンス プレートに使用される既定のコンテナー タイプを選択します。コンテナー タイプは、ケージ、ボックス、パレット、または出荷コンテナーなどの有形の在庫維持単位の物理的特性を定義します。 | H28: コンテナー タイプ（ユーザー定義） | I28: ー | K28: 「倉庫-設定値」を参照
B29: =ROW() - 5 -> 24 | F29: 作業処理ポリシー名 | H29: 入力不可 | I29: ー | K29: 「倉庫-設定値」を参照
B30: =ROW() - 5 -> 25 | F30: 既定の品質メンテナンスの場所 | G30: ここで指定した場所は、品質チェックが却下され、作業が作成されない場合に使用されます。在庫はすぐにこの場所に移動され、この場所を使用するように品質指示が更新されます。 | H30: 入力不可 | I30: ー | K30: 「倉庫-設定値」を参照
B31: =ROW() - 5 -> 26 | F31: 最終出荷の既定の場所 | G31: コンテナ パッキング ポリシー[倉庫] が [倉庫グループ] または [すべて] に設定されている場合に、コンテナパッキング処理で使用される既定の最終出荷場所を指定します。 | H31: 在庫場所（ユーザー定義） | I31: ー | K31: 「倉庫-設定値」を参照
B32: =ROW() - 5 -> 27 | F32: 並び替えに使用される既定の場所 | G32: コンテナパッキングポリシー [倉庫] が [倉庫グループ] または [すべて] に設定されている場合に、コンテナパッキング処理で使用する既定の仕分け場所を指定します。 | H32: 在庫場所（ユーザー定義） | I32: ー | K32: 「倉庫-設定値」を参照
B33: =ROW() - 5 -> 28 | F33: 棚卸理由コードポリシー | G33: 倉庫に割り当てられている棚卸理由コードポリシー。 | H33: 入力不可 | I33: ー | K33: 「倉庫-設定値」を参照
B34: =ROW() - 5 -> 29 | C34: 場所の名前 | E34: 通路 | F34: 通路を含める | G34: ー | H34: はい/いいえ | I34: いいえ | K34: 「倉庫-設定値」を参照
B35: =ROW() - 5 -> 30 | E35: ラック | F35: ラックを含める | G35: ー | H35: はい/いいえ | I35: いいえ | K35: 「倉庫-設定値」を参照
B36: =ROW() - 5 -> 31 | F36: 形式 | G36: ー | H36: 入力不可 | I36: ー | K36: 「倉庫-設定値」を参照
B37: =ROW() - 5 -> 32 | E37: レベル | F37: 棚を含める | G37: ー | H37: はい/いいえ | I37: いいえ | K37: 「倉庫-設定値」を参照
B38: =ROW() - 5 -> 33 | F38: 形式 | G38: ー | H38: 入力不可 | I38: ー | K38: 「倉庫-設定値」を参照
B39: =ROW() - 5 -> 34 | E39: 位置 | F39: 在庫置場を含める | G39: ー | H39: はい/いいえ | I39: いいえ | K39: 「倉庫-設定値」を参照
B40: =ROW() - 5 -> 35 | F40: 形式 | G40: ー | H40: 入力不可 | I40: ー | K40: 「倉庫-設定値」を参照
B41: =ROW() - 5 -> 36 | E41: 例 | F41: 場所 | G41: ー | H41: 入力不可 | I41: ー | K41: 「倉庫-設定値」を参照
B42: =ROW() - 5 -> 37 | C42: 住所 | F42: 名前または説明 | G42: ー | H42: 文字列 | I42: ー | K42: 「倉庫-設定値」を参照
B43: =ROW() - 5 -> 38 | F43: 住所 | G43: ー | H43: 文字列 | I43: ー | J43: 詳細より以下を入力することで反映される 国/地域 郵便番号 住所 市町村 都道府県 | K43: 「倉庫-設定値」を参照
B44: =ROW() - 5 -> 39 | F44: 目的 | G44: ー | H44: 業務 委託販売 配送 固定資産 本社 ホーム 請求書 船荷 その他 支払 実際の場所 採用 送金先 サービス 安定した組織 ステートメント SWIFT 船降 | I44: ー | K44: 「倉庫-設定値」を参照
B45: =ROW() - 5 -> 40 | F45: 主要 | G45: ー | H45: はい/いいえ | I45: ー | K45: 「倉庫-設定値」を参照
B46: =ROW() - 5 -> 41 | F46: 国/地域 | G46: ー | H46: 国/地域（システム定義） | I46: ー | J46: 「詳細」より編集可能 | K46: 「倉庫-設定値」を参照
B47: =ROW() - 5 -> 42 | F47: 郵便番号 | G47: ー | H47: 文字列 | I47: ー | J47: 「詳細」より編集可能 | K47: 「倉庫-設定値」を参照
B48: =ROW() - 5 -> 43 | F48: 住所 | G48: ー | H48: 文字列 | I48: ー | J48: 「詳細」より編集可能 | K48: 「倉庫-設定値」を参照
B49: =ROW() - 5 -> 44 | F49: 市町村 | G49: ー | H49: 市町村（ユーザー定義） | I49: ー | J49: 「詳細」より編集可能 | K49: 「倉庫-設定値」を参照
B50: =ROW() - 5 -> 45 | F50: 都道府県 | G50: ー | H50: 都道府県（ユーザー定義） | I50: ー | J50: 「詳細」より編集可能 | K50: 「倉庫-設定値」を参照
B51: =ROW() - 5 -> 46 | F51: 国/地域に関する基本事項 | G51: ー | H51: はい/いいえ | I51: ー | J51: 「詳細」より編集可能 | K51: 「倉庫-設定値」を参照
B52: =ROW() - 5 -> 47 | C52: 階層 | E52: 展開 | G52: 階層全体を展開 | K52: 「倉庫-設定値」を参照
B53: =ROW() - 5 -> 48 | C53: 小売 | E53: 場所の補充 | F53: 重量 | G53: ー | H53: 入力不可 | I53: ー | K53: 「倉庫-設定値」を参照
B54: =ROW() - 5 -> 49 | F54: 店舗 | G54: ー | H54: はい/いいえ | I54: いいえ | K54: 「倉庫-設定値」を参照
B55: =ROW() - 5 -> 50 | E55: 返品 | F55: 既定の返品場所 | G55: ー | H55: 在庫場所（ユーザー定義） | I55: ー | K55: 「倉庫-設定値」を参照
B56: =ROW() - 5 -> 51 | E56: 保管分析コード | F56: 既定の場所 | G56: ー | H56: 在庫場所（ユーザー定義） | I56: ー | K56: 「倉庫-設定値」を参照
B57: =ROW() - 5 -> 52 | E57: 情報コード | F57: 注文明細行を拒否する | G57: ー | H57: 情報コード番号（ユーザー定義） | I57: ー | K57: 「倉庫-設定値」を参照
B58: =ROW() - 5 -> 53 | C58: 倉庫 | F58: 倉庫管理プロセスの使用 | G58: 最適化された倉庫レイアウトおよび作業処理に対する倉庫アプリを使用するオプションを選択します。 | H58: はい/いいえ | I58: いいえ | K58: 「倉庫-設定値」を参照
B59: =ROW() - 5 -> 54 | F59: 出荷確認の前にBOLを印刷 | G59: Select this option if you want to print the bill of lading (BOL) before you confirm the shipment. By default, the bill of lading prints after the shipment has been confirmed. | H59: はい/いいえ | I59: いいえ | J59: 倉庫管理プロセスの使用を”はい”にすることで設定可能 | K59: 「倉庫-設定値」を参照
B60: =ROW() - 5 -> 55 | F60: 作業処理ポリシー名 | G60: ポリシーが倉庫で定義されている場合は、倉庫パラメーターで定義された既定のポリシーの代わりにそれが使用されます。 | H60: 作業処理 ポリシー（ユーザー定義） | I60: ー | J60: 倉庫管理プロセスの使用を”はい”にすることで設定可能 | K60: 「倉庫-設定値」を参照
B61: =ROW() - 5 -> 56 | F61: 出荷の自動更新 | G61: このパラメーターで出荷を自動的にいつ更新するか選択できます。販売や移動オーダー明細行の数量が減少したときに、出荷を自動的に更新するには数量減少を選択します。販売や移動オーダー明細行の数量が減少したとき、または新しい行が追加されて増加したときに、出荷を自動的に更新するには常時を選択します。 | H61: 数量減少 常時 | I61: ー | J61: 倉庫管理プロセスの使用を”はい”にすることで設定可能 | K61: 「倉庫-設定値」を参照
B62: =ROW() - 5 -> 57 | E62: 引当 | F62: 生産部品表の倉庫のみを引当 | G62: ー | H62: はい/いいえ | I62: いいえ | J62: 倉庫管理プロセスの使用を”はい”にすることで設定可能 | K62: 「倉庫-設定値」を参照
B63: =ROW() - 5 -> 58 | F63: 積荷転記時の在庫引当 | G63: 倉庫への負荷がリリースされるときに、在庫を自動的に引当するには、このオプションを選択します。 | H63: はい/いいえ | I63: いいえ | J63: 倉庫管理プロセスの使用を”はい”にすることで設定可能 | K63: 「倉庫-設定値」を参照
B64: =ROW() - 5 -> 59 | F64: バッチジョブによってオーダーがリリースされたときに引き当てる | G64: バッチ ジョブが倉庫への注文をリリースするのに使用される場合、在庫を自動的に引当するには、このオプションを選択します。 | H64: はい/いいえ | I64: いいえ | J64: 倉庫管理プロセスの使用を”はい”にすることで設定可能 | K64: 「倉庫-設定値」を参照
B65: =ROW() - 5 -> 60 | F65: 在庫引当の要件 | G65: 注文明細行の部分的なリリースを許可するかどうかを制御します。完全な予約を要求に設定すると、注文明細行が物理的に予約されない、またはクロスドッキングが計画されない場合、注文をリリースできません | H65: 該当なし 部分引当の許可 完全引当の必要 | I65: ー | J65: 倉庫管理プロセスの使用を”はい”にすることで設定可能 | K65: 「倉庫-設定値」を参照
B66: =ROW() - 5 -> 61 | F66: 不十分な数量の応答 | H66: エラーを生成 警告を生成 | I66: ー | J66: 積荷転記時の在庫引当を”はい”にすることで設定可能 | K66: 「倉庫-設定値」を参照
B67: =ROW() - 5 -> 62 | E67: マイナス在庫 | F67: 財務マイナス在庫 | G67: このオプションを使用すると、財務上更新された手持在庫が存在しない場合でも、ステータスが売却済の販売注文が請求できます。つまり、在庫がマイナスの資産になる可能性があります。このオプションを有効にすると、入庫在庫を財務上更新する前に、財務的に有効な在庫分析コードまたは倉庫間で在庫を転送する必要がある場合に便利です。 このオプションがいいえに設定されている場合、品目のすべての手持在庫が物理的に更新または入庫されていても、請求書を作成することはできません。 | H67: はい/いいえ | I67: いいえ | K67: 「倉庫-設定値」を参照
B68: =ROW() - 5 -> 63 | F68: 現物マイナス在庫 | G68: ー | H68: はい/いいえ | I68: いいえ | K68: 「倉庫-設定値」を参照
B69: =ROW() - 5 -> 64 | E69: 循環棚卸 | F69: 循環棚卸中にライセンスプレートの移動を許可する | G69: このオプションにより、ライセンス プレートが棚卸を行っている場所と異なる場所にある場合に、棚卸中に在庫移動が完了します。 | H69: はい/いいえ | I69: いいえ | K69: 「倉庫-設定値」を参照
B70: =ROW() - 5 -> 65 | E70: チェックディジット | F70: 一意のチェックディジットを使用 | G70: このオプションを選択して、場所ごとに一意のチェック ディジットがあることを確認します。 ディジットを設定するため、倉庫管理 > 設定 > 倉庫 > 場所 の順に移動します。 チェック ディジットを選択します。 | H70: はい/いいえ | I70: いいえ | K70: 「倉庫-設定値」を参照
B71: =ROW() - 5 -> 66 | E71: ピッキング済数量の削減 | F71: 減分積荷明細行 | G71: このオプションにより、ピッキング済数量が減少した場合に、積荷明細行が削減されます。 これは、ピッキング済数量が減少しても全積荷を出荷する必要がある場合に便利です。 | H71: はい/いいえ | I71: いいえ | K71: 「倉庫-設定値」を参照
B72: =ROW() - 5 -> 67 | E72: 在庫 | F72: 既定の在庫状態ID | G72: この倉庫の在庫について、発注書明細行、販売注文明細行、および移動オーダー明細行に既定で表示されるステータスを選択します。 | H72: 在庫状態（ユーザー定義） | I72: ー | K72: 「倉庫-設定値」を参照
B73: =ROW() - 5 -> 68 | F73: 既定のコンテナータイプ | G73: ライセンス プレートに使用される既定のコンテナー タイプを選択します。コンテナー タイプは、ケージ、ボックス、パレット、または出荷コンテナーなどの有形の在庫維持単位の物理的特性を定義します。 | H73: コンテナー タイプ（ユーザー定義） | I73: ー | K73: 「倉庫-設定値」を参照
B74: =ROW() - 5 -> 69 | E74: 在庫状態の変更 | F74: 引当とマーキングの削除 | G74: 在庫状態が変更した場合の、引当とマーキングの処置を選択します。 | H74: なし 引当 マーキングと引当 | I74: いいえ | K74: 「倉庫-設定値」を参照
B75: =ROW() - 5 -> 70 | F75: 在庫ブロックの削除 | G75: 在庫状態が変更された場合に在庫ブロックを削除するオプションを選択します。このオプションは、品目が消費または使用から自動的にブロックされているとき、および品質検査が終了した後に在庫のステータスが変更したときに、品質検査で使用されます。 | H75: はい/いいえ | I75: いいえ | K75: 「倉庫-設定値」を参照
B76: =ROW() - 5 -> 71 | E76: 労務標準 | F76: 労務標準の許可 | G76: この倉庫で労働基準計算を実行できるようにするには、このオプションを選択します。このオプションをはいに設定すると、倉庫でのパフォーマンスに影響があります。 | H76: はい/いいえ | I76: いいえ | K76: 「倉庫-設定値」を参照
B77: =ROW() - 5 -> 72 | F77: 倉庫プロセスに対して品質指示を有効にする | G77: 有効にすると、この倉庫で作成された品質指示で、品質品目サンプリング作業および品質指示作業を含む倉庫プロセス機能の品質指示が使用されます。無効にすると、品質指示機能はサポートされますが、倉庫作業は統合されません。 | H77: はい/いいえ | I77: いいえ | K77: 「倉庫-設定値」を参照
B78: =ROW() - 5 -> 73 | E78: 製造オーダー | F78: 一括引落しでは引当済数量を使用する必要があります | G78: このオプションは[はい]に設定すると、引当済数量の一括引落しを許可できます。 | H78: はい/いいえ | I78: いいえ | K78: 「倉庫-設定値」を参照
B79: =ROW() - 5 -> 74 | E79: 危険物レポートの言語 | F79: 危険物国内レポートの言語 | G79: 国内出荷に関連付けられている危険物レポートの既定の言語を選択します。 | H79: 言語（ユーザー定義） | I79: ー | K79: 「倉庫-設定値」を参照
B80: =ROW() - 5 -> 75 | F80: 危険物輸出レポートの言語 | G80: 国際出荷に関連付けられている危険物レポートの既定の言語を選択します。 | H80: 言語（ユーザー定義） | I80: ー | K80: 「倉庫-設定値」を参照
B81: =ROW() - 5 -> 76 | C81: ピッキングワークベンチ | F81: バッチごとのピッキングリスト数 | G81: ー | H81: 数値 | I81: 0 | K81: 「倉庫-設定値」を参照
B82: =ROW() - 5 -> 77 | F82: ピッキングリストの最大明細行 | G82: ー | H82: 数値 | I82: 0 | K82: 「倉庫-設定値」を参照
B83: =ROW() - 5 -> 78 | F83: 単独出荷で分割 | G83: ー | H83: はい/いいえ | I83: いいえ | K83: 「倉庫-設定値」を参照
B84: =ROW() - 5 -> 79 | F84: 配送モードで分割 | G84: ー | H84: はい/いいえ | I84: いいえ | K84: 「倉庫-設定値」を参照

Sheet 倉庫-設定値
A1: 倉庫-設定値 ※基本的には移行データを正とする
A2: ■凡例「必須：システム上必須」「必須(*)：システムで必須ではないが、トランザクション上や業務などで必須」 | AW2: 本シートにある倉庫列、名前列の内容参照
A3: パラメータ設定一覧へ | AW3: ↓
B4: # | C4: 概要 | E4: 一般 | L4: マスタープラン | Q4: 在庫および倉庫管理 | AE4: 場所の名前 | AM4: 住所 | AW4: 階層 | AX4: 小売 | BC4: 倉庫 | BZ4: ピッキングワークベンチ
K5: 参照 | L5: 品目補充 | N5: 主要倉庫 | AE5: 通路 | AF5: ラック | AH5: レベル | AJ5: 位置 | AL5: 例 | AX5: 場所の補充 | AZ5: 返品 | BA5: 保管分析コード | BB5: 情報コード | BG5: 引当 | BL5: マイナス在庫 | BN5: 循環棚卸 | BO5: チェックディジット | BP5: ピッキング済数量の削減 | BQ5: 在庫 | BS5: 在庫状態の確認 | BU5: 労務標準 | BW5: 製造オーダー | BX5: 危険物レポートの言語
C6: 倉庫 | D6: 名前 | E6: サイト | F6: タイプ | G6: 検査倉庫 | H6: トランジット倉庫 | I6: 輸送中の商品の倉庫 | J6: 過少配送倉庫 | K6: 仕入先 | L6: 手動 | M6: カレンダー | N6: 補充 | O6: 主要倉庫 | P6: 倉庫レベル | Q6: 既定の受入場所 | R6: 既定の払出場所 | S6: 既定の生産完成品の場所 | T6: 既定の生産入庫の場所 | U6: 原材料ピッキング後の払出ステータス | V6: 既定かんばん完成品の場所 | W6: 既定の出荷管理場所 | X6: 貸方のみの返品の既定の場所 | Y6: 既定のコンテナータイプ | Z6: 作業処理ポリシー名 | AA6: 既定の品質メンテナンスの場所 | AB6: 最終出荷の既定の場所 | AC6: 並び替えに使用される既定の場所 | AD6: 棚卸理由コードポリシー | AE6: 通路を含める | AF6: ラックを含める | AG6: 形式 | AH6: 棚を含める | AI6: 形式 | AJ6: 在庫置場を含める | AK6: 形式 | AL6: 場所 | AM6: 名前または説明 | AN6: 住所 | AO6: 目的 | AP6: 主要 | AQ6: 国/地域 | AR6: 郵便番号 | AS6: 住所 | AT6: 市町村 | AU6: 都道府県 | AV6: 国/地域に関する基本事項 | AW6: 折りたたみ | AX6: 重量 | AY6: 店舗 | AZ6: 既定の返品場所 | BA6: 既定の場所 | BB6: 注文明細行を拒否する | BC6: 倉庫管理プロセスの使用 | BD6: 出荷確認の前にBOLを印刷 | BE6: 作業処理ポリシー名 | BF6: 出荷の自動更新 | BG6: 生産部品表の倉庫のみを引当 | BH6: 積荷転記時の在庫引当 | BI6: バッチジョブによってオーダーがリリースされたときに引き当てる | BJ6: 在庫引当の要件 | BK6: 不十分な数量の応答 | BL6: 財務マイナス在庫 | BM6: 現物マイナス在庫 | BN6: 循環棚卸中にライセンスプレートの移動を許可する | BO6: 一意のチェックディジットを使用 | BP6: 減分積荷明細行 | BQ6: 既定の在庫状態ID | BR6: 既定のコンテナータイプ | BS6: 引当とマーキングの削除 | BT6: 在庫ブロックの削除 | BU6: 労務標準の許可 | BV6: 倉庫プロセスに対して品質指示を有効にする | BW6: 一括引落しでは引当済数量を使用する必要があります | BX6: 危険物国内レポートの言語 | BY6: 危険物輸出レポートの言語 | BZ6: バッチごとのピッキングリスト数 | CA6: ピッキングリストの最大明細行 | CB6: 単独出荷で分割 | CC6: 配送モードで分割
C7: 文字列 | D7: 文字列 | E7: サイト（ユーザー定義） | F7: 既定/検査/通過 | G7: 倉庫（ユーザー定義） | H7: 倉庫（ユーザー定義） | I7: 倉庫（ユーザー定義） | J7: 倉庫（ユーザー定義） | K7: 仕入先（ユーザー定義） | L7: はい/いいえ | M7: 作業時間カレンダー（ユーザー定義） | N7: はい/いいえ | O7: 倉庫（ユーザー定義） | P7: 操作不可 | Q7: 在庫場所（ユーザー定義） | R7: 在庫場所（ユーザー定義） | S7: 在庫場所（ユーザー定義） | T7: 在庫場所（ユーザー定義） | U7: ピッキング済/引当現物 | V7: 在庫場所（ユーザー定義） | W7: 在庫場所（ユーザー定義） | X7: 入力不可 | Y7: コンテナー タイプ（ユーザー定義） | Z7: 入力不可 | AA7: 入力不可 | AB7: 在庫場所（ユーザー定義） | AC7: 在庫場所（ユーザー定義） | AD7: 入力不可 | AE7: はい/いいえ | AF7: はい/いいえ | AG7: 入力不可 | AH7: はい/いいえ | AI7: 入力不可 | AJ7: はい/いいえ | AK7: 入力不可 | AL7: 入力不可 | AM7: 文字列 | AN7: 文字列 | AO7: 目的（ユーザー定義） | AP7: はい/いいえ | AQ7: 国/地域（システム定義） | AR7: 文字列 | AS7: 文字列 | AT7: 市町村（ユーザー定義） | AU7: 都道府県（ユーザー定義） | AV7: はい/いいえ | AX7: 入力不可 | AY7: はい/いいえ | AZ7: 在庫場所（ユーザー定義） | BA7: 在庫場所（ユーザー定義） | BB7: 情報コード番号（ユーザー定義） | BC7: はい/いいえ | BD7: はい/いいえ | BE7: 作業処理 ポリシー（ユーザー定義） | BF7: 数量減少 常時 | BG7: はい/いいえ | BH7: はい/いいえ | BI7: はい/いいえ | BJ7: 該当なし 部分引当の許可 完全引当の必要 | BK7: エラーを生成 警告を生成 | BL7: はい/いいえ | BM7: はい/いいえ | BN7: はい/いいえ | BO7: はい/いいえ | BP7: はい/いいえ | BQ7: 在庫状態（ユーザー定義） | BR7: コンテナー タイプ（ユーザー定義） | BS7: なし/引当/マーキングと引当 | BT7: はい/いいえ | BU7: はい/いいえ | BV7: はい/いいえ | BW7: はい/いいえ | BX7: 言語（ユーザー定義） | BY7: 言語（ユーザー定義） | BZ7: 数値 | CA7: 数値 | CB7: はい/いいえ | CC7: はい/いいえ
C8: 必須 | E8: 必須 | F8: 必須
B9: 例 | C9: 本社倉庫 | D9: JBS本社倉庫 | E9: JBS | F9: 既定
B10: =ROW() - 9 -> 1
B11: =ROW() - 9 -> 2
B12: =ROW() - 9 -> 3
B13: =ROW() - 9 -> 4
B14: =ROW() - 9 -> 5
B15: =ROW() - 9 -> 6
B16: =ROW() - 9 -> 7
B17: =ROW() - 9 -> 8
B18: =ROW() - 9 -> 9
B19: =ROW() - 9 -> 10

Sheet 通路
A1: 通路
B2: 在庫管理＞設定＞在庫詳細＞通路
B3: Inventory management > Setup > Inventory breakdown > Inventory aisles
A4: パラメータ設定一覧へ
B5: # | C5: タブ | D5: タブ説明 | E5: 項目分類 | F5: 項目 | G5: Description（標準） | H5: 設定可能値 | I5: デフォルト値 | J5: 備考 | K5: 設定値 | L5: 設定基準
B6: =ROW() - 5 -> 1 | C6: 通路 | E6: 通路 | F6: 倉庫 | G6: 通路を含む倉庫の識別子。この情報を通路の名前と組み合わせて、通路を識別します。 | H6: 倉庫（ユーザー定義） | I6: ー | K6: 「通路-設定値」を参照
B7: =ROW() - 5 -> 2 | F7: 通路 | G7: 通路の名前。この情報を倉庫のIDと組み合わせて、通路を識別します。 | H7: 文字列 | I7: ー | K7: 「通路-設定値」を参照
B8: =ROW() - 5 -> 3 | F8: 開始値 | G8: ー | H8: 数値 | I8: 0 | K8: 「通路-設定値」を参照
B9: =ROW() - 5 -> 4 | F9: 降順 | G9: このオプションを選択すると、通路内の場所がピッキングルートのために棚番号の降順で並べ替えられます。 | H9: チェック/チェック無し | I9: チェック無し | K9: 「通路-設定値」を参照
B10: =ROW() - 5 -> 5 | F10: 通路番号 | G10: 場所の並べ替えコードが更新された場合に、通路の並べ替えに使用される数値フィールド。 | H10: 数値 | I10: 0 | K10: 「通路-設定値」を参照
B11: =ROW() - 5 -> 6 | F11: 名前 | G11: ー | H11: 文字列 | I11: ー | K11: 「通路-設定値」を参照

Sheet 通路-設定値
A1: 通路-設定値 ※基本的には移行データを正とする
A2: ■凡例「必須：システム上必須」「必須(*)：システムで必須ではないが、トランザクション上や業務などで必須」
A3: パラメータ設定一覧へ
B4: # | C4: 倉庫 | D4: 通路 | E4: 開始値 | F4: 降順 | G4: 通路番号 | H4: 名前
C5: 倉庫（ユーザー定義） | D5: 文字列 | E5: 数値 | F5: チェック/チェック無し | G5: 数値 | H5: 文字列
C6: 必須 | D6: 必須
B7: 例 | C7: 本社倉庫 | D7: 16F通路
B8: =ROW() - 7 -> 1
B9: =ROW() - 7 -> 2
B10: =ROW() - 7 -> 3
B11: =ROW() - 7 -> 4
B12: =ROW() - 7 -> 5
B13: =ROW() - 7 -> 6
B14: =ROW() - 7 -> 7
B15: =ROW() - 7 -> 8
B16: =ROW() - 7 -> 9
B17: =ROW() - 7 -> 10

Sheet 在庫場所
A1: 在庫場所
B2: 在庫管理＞設定＞在庫詳細＞在庫場所
B3: Inventory management > Setup > Inventory breakdown > Inventory locations
A4: パラメータ設定一覧へ
B5: # | C5: タブ | D5: タブ説明 | E5: 項目分類 | F5: 項目 | G5: Description（標準） | H5: 設定可能値 | I5: デフォルト値 | J5: 備考 | K5: 設定値 | L5: 設定基準
B6: =ROW() - 5 -> 1 | C6: 在庫場所 | F6: 倉庫 | G6: 保管場所がある倉庫。保管場所の名前と組み合わせて、倉庫は保管場所の参照として使用されます。 | H6: 倉庫（ユーザー定義） | I6: ー | K6: 「在庫場所-設定値」を参照
B7: =ROW() - 5 -> 2 | F7: 場所 | G7: 場所の名前。倉庫と組み合わせて、保管場所の名前は保管場所の参照として使用されます。通常、場所の名前は、保管場所のコーディネーター (通路、ラック、棚、および在庫置場) に基づいて自動的に生成されます。これらの座標は、このページの設定に基づきます。名前を手動で入力するには、最初に [一般] タブの [手動更新] オプションを選択する必要があります。 | H7: （システム自動入力） ※通路を選択したら自動で反映 | I7: ー | K7: 「在庫場所-設定値」を参照
B8: =ROW() - 5 -> 3 | F8: 場所のタイプ | G8: 場所の用途を識別する、場所タイプ。次のタイプが使用できます。[入庫ドック] 品目が入庫および登録される保管場所を識別します。[出荷ドック] 品目が出荷前に収集される保管場所を識別します。[バルク場所] 品目が出荷ドックに移動されるかピッキング場所への補充に使用されるまで格納される保管場所を識別します。[ピッキング場所] 品目の固定のピッキング場所がある保管場所を識別します。この場所タイプは、出荷数量がパレット全体より少ない場合に使用されます。[検査場所] 品質管理を経なければならない品目の保管場所を識別します。[生産入庫の場所] 品質管理を経なければならない品目の保管場所を識別します。[生産入庫の場所] コンポーネントまたは製品の製造に使用される原材料の保管場所を識別します。 | H8: バルク場所 ピッキング場所 入庫ドック 出荷ドック 生産入庫の場所 検査場所 かんばんスーパーマーケット | I8: ー | K8: 「在庫場所-設定値」を参照
B9: =ROW() - 5 -> 4 | C9: 一般 | E9: ID | F9: 通路 | G9: 場所の通路座標。倉庫に対して作成された通路を選択します。 | H9: 通路（ユーザー定義） | I9: ー | K9: 「在庫場所-設定値」を参照
B10: =ROW() - 5 -> 5 | F10: ラック | H10: 数値 | I10: 0 | K10: 「在庫場所-設定値」を参照
B11: =ROW() - 5 -> 6 | F11: 棚 | H11: 数値 | I11: 0 | K11: 「在庫場所-設定値」を参照
B12: =ROW() - 5 -> 7 | F12: 在庫置場 | G12: 場所の名前を手動で指定する場合は、このオプションを選択します。このオプションをオフにすると、場所の名前は割り当てられたコーディネーターに基づいて自動的に生成されます。コーディネーターは通路、ラック、棚、および在庫置場です。倉庫と保管場所の名前の両方により、保管場所を一意に識別できます。 | H12: 数値 | I12: 0 | K12: 「在庫場所-設定値」を参照
B13: =ROW() - 5 -> 8 | F13: 手動更新 | G13: 場所の高さ。パレットで使用可能な高さを指定します。棚の間の指示構造物は含めません。 | H13: はい/いいえ | I13: いいえ | K13: 「在庫場所-設定値」を参照
B14: =ROW() - 5 -> 9 | E14: 物理的寸法 | F14: 高さ | H14: 数値 | I14: 1.00 | K14: 「在庫場所-設定値」を参照
B15: =ROW() - 5 -> 10 | F15: 幅 | H15: 数値 | I15: 1.00 | K15: 「在庫場所-設定値」を参照
B16: =ROW() - 5 -> 11 | F16: 奥行き | H16: 数値 | I16: 1.00 | K16: 「在庫場所-設定値」を参照
B17: =ROW() - 5 -> 12 | F17: 容量 | G17: 場所の容量。高さ、重量、および奥行きを使用して計算されます。 | H17: 数値 | I17: 1.00 | K17: 「在庫場所-設定値」を参照
B18: =ROW() - 5 -> 13 | F18: 絶対高度 | G18: 保管場所の地表面からの高さを入力します。この高さとフォークリフトの最大高さに基づいて、フォークリフトで扱える配送のみを確実に選択できます。 | H18: 数値 | I18: 0.00 | K18: 「在庫場所-設定値」を参照
B19: =ROW() - 5 -> 14 | C19: 負荷 | E19: 容量 | F19: 現在の量 | H19: 数値 | I19: 0.00 | K19: 「在庫場所-設定値」を参照
B20: =ROW() - 5 -> 15 | F20: 可能な量 | H20: 数値 | I20: 1.00 | K20: 「在庫場所-設定値」を参照
B21: =ROW() - 5 -> 16 | F21: 最大量 | H21: 数値 | I21: 1.00 | K21: 「在庫場所-設定値」を参照
B22: =ROW() - 5 -> 17 | E22: 重量 | F22: 現在の重量 | H22: 数値 | I22: 0.00 | K22: 「在庫場所-設定値」を参照
B23: =ROW() - 5 -> 18 | F23: 可能な重量 | H23: 数値 | I23: 0.00 | K23: 「在庫場所-設定値」を参照
B24: =ROW() - 5 -> 19 | F24: 最大重量 | H24: 数値 | I24: ー | K24: 「在庫場所-設定値」を参照
B25: =ROW() - 5 -> 20 | C25: その他 | E25: その他 | F25: チェック ディジット | H25: 文字列 | I25: ー | K25: 「在庫場所-設定値」を参照
B26: =ROW() - 5 -> 21 | F26: 行先の場所 | G26: 保管する品目の配送先。これは通常、実際の保管場所です。ただし、たとえばドライブスルー ラックに対しては品目をラックの背部で配送する必要があります。フォークリフト操縦者は、品目が受け渡されるときではなく、場所がラックの背部に指定されたときに背部に誘導されます。 | H26: 場所（ユーザー定義） | K26: 「在庫場所-設定値」を参照
B27: =ROW() - 5 -> 22 | E27: ブロック | F27: ブロックされている入荷 | G27: システムが品目の保管場所を検索するときにこの保管場所が選択されないようにするには、ブロックの原因を選択します。詳細については、「ブロックの原因 (フォーム)」を参照してください。 | H27: ブロックの原因（ユーザー定義） | K27: 「在庫場所-設定値」を参照
B28: =ROW() - 5 -> 23 | F28: ブロックされている出荷 | G28: システムが出荷を予約するときにこの保管場所が選択されないようにするには、ブロックの原因を選択します。 | H28: ブロックの原因（ユーザー定義） | K28: 「在庫場所-設定値」を参照
B29: =ROW() - 5 -> 24 | E29: 並べ替え | F29: 手動更新 | G29: 場所の名前を手動で指定する場合は、このオプションを選択します。このオプションをオフにすると、場所の名前は割り当てられたコーディネーターに基づいて自動的に生成されます。コーディネーターは通路、ラック、棚、および在庫置場です。倉庫と保管場所の名前の両方により、保管場所を一意に識別できます。 | H29: はい/いいえ | I29: いいえ | K29: 「在庫場所-設定値」を参照
B30: =ROW() - 5 -> 25 | F30: 並び替えコード | G30: ピッキング ラインを並べ替えるときに使用される並べ替えコード。このコードは在庫内の最適なピッキング ルートを示します。 | H30: 数値 | I30: 0 | K30: 「在庫場所-設定値」を参照
B31: =ROW() - 5 -> 26 | C31: ツリー構造 | E31: ツリー構造 | F31: ツリー構造 | H31: （システム自動入力） | K31: 「在庫場所-設定値」を参照
B32: =ROW() - 5 -> 27 | E32: 表示の形式 | F32: 倉庫 | H32: はい/いいえ | I32: はい | K32: 「在庫場所-設定値」を参照
B33: =ROW() - 5 -> 28 | F33: 場所 | H33: はい/いいえ | I33: はい | K33: 「在庫場所-設定値」を参照
B34: =ROW() - 5 -> 29 | F34: 場所のタイプ | H34: はい/いいえ | I34: はい | K34: 「在庫場所-設定値」を参照
B35: =ROW() - 5 -> 30 | F35: 高さ | H35: はい/いいえ | I35: いいえ | K35: 「在庫場所-設定値」を参照
B36: =ROW() - 5 -> 31 | F36: 合計 | H36: はい/いいえ | I36: いいえ | K36: 「在庫場所-設定値」を参照

Sheet 在庫場所-設定値
A1: 在庫場所-設定値 ※基本的には移行データを正とする
A2: ■凡例「必須：システム上必須」「必須(*)：システムで必須ではないが、トランザクション上や業務などで必須」
A3: パラメータ設定一覧へ
B4: # | C4: 在庫場所 | F4: 一般 | P4: 負荷 | V4: その他 | AB4: ツリー構造
F5: ID | K5: 物理的寸法 | P5: 容量 | S5: 重量 | V5: その他 | X5: ブロック | Z5: 並べ替え | AB5: ツリー構造 | AC5: 表示の形式
C6: 倉庫 | D6: 場所 | E6: 場所のタイプ | F6: 通路 | G6: ラック | H6: 棚 | I6: 在庫置場 | J6: 手動更新 | K6: 高さ | L6: 幅 | M6: 奥行き | N6: 容量 | O6: 絶対高度 | P6: 現在の量 | Q6: 可能な量 | R6: 最大量 | S6: 現在の重量 | T6: 可能な重量 | U6: 最大重量 | V6: チェック ディジット | W6: 行先の場所 | X6: ブロックされている入荷 | Y6: ブロックされている出荷 | Z6: 手動更新 | AA6: 並び替えコード | AB6: ツリー構造 | AC6: 倉庫 | AD6: 場所 | AE6: 場所のタイプ | AF6: 高さ | AG6: 合計
C7: 倉庫（ユーザー定義） | E7: バルク場所 ピッキング場所 入庫ドック 出荷ドック 生産入庫の場所 検査場所 かんばんスーパーマーケット | F7: 通路（ユーザー定義） | G7: 数値 | H7: 数値 | I7: 数値 | J7: はい/いいえ | K7: 数値 | L7: 数値 | M7: 数値 | N7: 数値 | O7: 数値 | P7: 数値 | Q7: 数値 | R7: 数値 | S7: 数値 | T7: 数値 | U7: 数値 | V7: 文字列 | W7: 場所（ユーザー定義） | X7: ブロックの原因（ユーザー定義） | Y7: ブロックの原因（ユーザー定義） | Z7: はい/いいえ | AA7: 数値 | AB7: （システム自動入力） ※自動反映 | AC7: はい/いいえ | AD7: はい/いいえ | AE7: はい/いいえ | AF7: はい/いいえ | AG7: はい/いいえ
C8: 必須 | D8: 必須 | E8: 必須 | F8: 必須
B9: 例 | C9: 本社倉庫 | D9: 16F通路A棚 | E9: バルク場所 | F9: 16F通路 | J9: はい
B10: =ROW() - 9 -> 1
B11: =ROW() - 9 -> 2
B12: =ROW() - 9 -> 3
B13: =ROW() - 9 -> 4
B14: =ROW() - 9 -> 5
B15: =ROW() - 9 -> 6
B16: =ROW() - 9 -> 7
B17: =ROW() - 9 -> 8
B18: =ROW() - 9 -> 9
B19: =ROW() - 9 -> 10

Sheet 配送日数
A1: 配送日数
B2: 在庫管理＞設定＞配分＞配送日数
B3: Inventory management > Setup > Distribution > Transport days
A4: パラメータ設定一覧へ
B5: # | C5: タブ | D5: タブ説明 | E5: 項目分類 | F5: 項目 | G5: Description（標準） | H5: 設定可能値 | I5: デフォルト値 | J5: 備考 | K5: 設定値 | L5: 設定基準
B6: =ROW() - 5 -> 1 | C6: 一般 | E6: 出荷場所 | F6: 出荷倉庫 | G6: この配送の出荷場所として使用される倉庫を選択します。倉庫の作成または編集は、倉庫ページで行います。 | H6: 倉庫（ユーザー定義） | I6: ー | K6: 「配送日数-設定値」を参照
B7: =ROW() - 5 -> 2 | E7: 配送 | F7: 配送日数 | H7: 数値 | I7: 0 | K7: 「配送日数-設定値」を参照
B8: =ROW() - 5 -> 3 | E8: 入荷場所 | F8: 入荷倉庫 | G8: この配送に対する入荷場所の倉庫の ID を選択します ([タイプ] リストで [倉庫] を選択した場合のみ関係します)。倉庫の作成または編集は、倉庫ページで行います。 | I8: ー | K8: 「配送日数-設定値」を参照
B9: =ROW() - 5 -> 4 | F9: 国/地域 | G9: この配送に対する入荷場所の国 / 地域を選択します。これは、タイプ リストで住所を選択した場合に関係します。郵便番号が選択され、国/地域を特定できる場合は、対応する国/地域が自動的に選択されます。 | H9: 国/地域（選択） | I9: ー | K9: 「配送日数-設定値」を参照
B10: =ROW() - 5 -> 5 | F10: 都道府県 | G10: この配送に対する入荷場所の都道府県を選択します ([タイプ] リストで [住所] を選択した場合のみ関係します)。郵便番号が選択され、都道府県を特定できる場合は、対応する都道府県が自動的に選択されます。 | H10: 都道府県（ユーザー定義） | I10: ー | K10: 「配送日数-設定値」を参照
B11: =ROW() - 5 -> 6 | F11: 市区群 | G11: この配送に対する入荷場所の地域 (米国の場合は市区郡) を選択します ([タイプ] リストで [住所] を選択した場合のみ関係します)。郵便番号が選択され、市区郡を特定できる場合は、対応する市区郡が自動的に選択されます。 | H11: 市区群（ユーザー定義） | I11: ー | K11: 「配送日数-設定値」を参照
B12: =ROW() - 5 -> 7 | F12: 市町村 | G12: この配送に対する入荷場所の市町村を入力します ([タイプ] リストで [住所] を選択した場合のみ関係します)。郵便番号が選択され、市町村を特定できる場合は、対応する市町村が自動的に選択されます。 | H12: 文字列 | I12: ー | K12: 「配送日数-設定値」を参照
B13: =ROW() - 5 -> 8 | F13: 郵便番号 | G13: この配送に対する入荷場所の郵便番号を選択します ([タイプ] リストで [住所] を選択した場合のみ関係します)。郵便番号を選択すると、自動的に国 / 地域、都道府県、および国または地域フィールドが設定されます。 | H13: 郵便番号（ユーザー定義） | I13: ー | K13: 「配送日数-設定値」を参照
B14: =ROW() - 5 -> 9 | C14: 荷渡方法ごとの配送日数 | F14: 荷渡方法 | G14: 配送方法を選択します。配送方法は、荷渡方法のページで作成または変更できます。 | H14: 荷渡方法（ユーザー定義） | I14: ー | K14: 「配送日数-設定値」を参照
B15: =ROW() - 5 -> 10 | F15: 説明 | G15: 荷渡方法の説明。この説明は、荷渡方法のページで作成または変更できます。 | H15: 荷渡方法マスタの「説明」が自動反映 | I15: ー | K15: 「配送日数-設定値」を参照
B16: =ROW() - 5 -> 11 | F16: 配送日数 | H16: 数値 | I16: 0 | K16: 「配送日数-設定値」を参照
B17: =ROW() - 5 -> 12 | F17: 既定 | H17: チェック/チェック無 | I17: チェック無 | K17: 「配送日数-設定値」を参照

Sheet 配送日数-設定値
A1: 配送日数-設定値 ※基本的には移行データを正とする
A2: ■凡例「必須：システム上必須」「必須(*)：システムで必須ではないが、トランザクション上や業務などで必須」
A3: パラメータ設定一覧へ
B4: # | C4: 一般 | K4: 荷渡方法ごとの配送日数
C5: 出荷場所 | D5: 配送 | E5: 入荷場所
C6: 出荷倉庫 | D6: 配送日数 | E6: 入荷倉庫 | F6: 国/地域 | G6: 都道府県 | H6: 市区群 | I6: 市町村 | J6: 郵便番号 | K6: 荷渡方法 | L6: 説明 | M6: 配送日数 | N6: 既定
C7: 倉庫（ユーザー定義） | D7: 数値 | F7: 国/地域（選択） | G7: 都道府県（ユーザー定義） | H7: 市区群（ユーザー定義） | I7: 文字列 | J7: 郵便番号（ユーザー定義） | K7: 荷渡方法（ユーザー定義） | L7: 荷渡方法マスタの「説明」が自動反映 | M7: 数値 | N7: チェック/チェック無
C8: 必須 | F8: 入荷場所タイプが住所の場合は受入国/地域の指定が必須
B9: =ROW() - 8 -> 1
B10: =ROW() - 8 -> 2
B11: =ROW() - 8 -> 3
B12: =ROW() - 8 -> 4
B13: =ROW() - 8 -> 5
B14: =ROW() - 8 -> 6
B15: =ROW() - 8 -> 7
B16: =ROW() - 8 -> 8

Sheet 出荷の配送業者
A1: 出荷の配送業者
B2: 在庫管理＞設定＞出荷の配送業者＞出荷の配送業者
B3: Inventory management > Setup > Shipping carrier > Shipping carriers
A4: パラメータ設定一覧へ
B5: # | C5: タブ | D5: タブ説明 | E5: 項目分類 | F5: 項目 | G5: Description（標準） | H5: 設定可能値 | I5: デフォルト値 | J5: 備考 | K5: 設定値 | L5: 設定基準
B6: =ROW() - 5 -> 1 | C6: ヘッダー | F6: 出荷の配送業者 | G6: ー | H6: 文字列 | I6: ー | K6: 「出荷の配送業者-設定値」を参照
B7: =ROW() - 5 -> 2 | F7: 名前 | G7: ー | H7: 文字列 | I7: ー | K7: 「出荷の配送業者-設定値」を参照
B8: =ROW() - 5 -> 3 | F8: 方法 | G8: ー | H8: 輸送方法（ユーザー定義） | I8: ー | K8: 「出荷の配送業者-設定値」を参照
B9: =ROW() - 5 -> 4 | C9: 概要 | F9: 出荷配送業者の有効化 | G9: ー | H9: はい/いいえ | I9: いいえ | K9: 「出荷の配送業者-設定値」を参照
B10: =ROW() - 5 -> 5 | F10: WebサイトURL | G10: ー | H10: 文字列 | I10: ー | K10: 「出荷の配送業者-設定値」を参照
B11: =ROW() - 5 -> 6 | F11: 追跡URL | G11: ー | H11: 文字列 | I11: ー | K11: 「出荷の配送業者-設定値」を参照
B12: =ROW() - 5 -> 7 | F12: 仕入先 | G12: ー | H12: 仕入先（ユーザー定義） | I12: ー | K12: 「出荷の配送業者-設定値」を参照
B13: =ROW() - 5 -> 8 | F13: 輸送業者タイプ | G13: 輸送業者の詳細を更新する方法を選択します。[輸送業者] ページを使用して、手動で輸送業者の詳細を更新します。[EDI] : [輸送業者] ページで電子データ交換 (EDI) を使用して、輸送業者の詳細を自動的に更新します。 | H13: なし 手動 EDI | I13: なし | K13: 「出荷の配送業者-設定値」を参照
B14: =ROW() - 5 -> 9 | F14: SCAC | G14: SCAC (Standard Carrier Alpha Code) の ID を入力します。 | H14: 文字列 | I14: ー | K14: 「出荷の配送業者-設定値」を参照
B15: =ROW() - 5 -> 10 | F15: 製品番号順序 | G15: 汎用輸送管理エンジンに関連付けられている番号順序を選択します。 | H15: 番号順序（ユーザー定義） | I15: ー | K15: 「出荷の配送業者-設定値」を参照
B16: =ROW() - 5 -> 11 | F16: 配送業者の評価をアクティブ化 | G16: ー | H16: はい/いいえ | I16: いいえ | K16: 「出荷の配送業者-設定値」を参照
B17: =ROW() - 5 -> 12 | F17: コンテナーの平均重量 | G17: ー | H17: 数値 | I17: 0 | K17: 「出荷の配送業者-設定値」を参照
B18: =ROW() - 5 -> 13 | C18: サービス | F18: 配送サービス | G18: ー | H18: 文字列 | I18: ー | K18: 「出荷の配送業者-設定値」を参照
B19: =ROW() - 5 -> 14 | F19: 名前 | G19: ー | H19: 文字列 | I19: ー | K19: 「出荷の配送業者-設定値」を参照
B20: =ROW() - 5 -> 15 | F20: 積載テンプレートID | G20: ー | H20: 積荷テンプレート（ユーザー定義） | I20: ー | K20: 「出荷の配送業者-設定値」を参照
B21: =ROW() - 5 -> 16 | F21: 輸送方法 | G21: ー | H21: 輸送方法（ユーザー定義） | I21: ー | K21: 「出荷の配送業者-設定値」を参照
B22: =ROW() - 5 -> 17 | F22: 荷渡方法 | G22: ー | H22: 入力不可 | I22: ー | J22: 出荷の配送業者+"-"+配送サービスの文字列が自動的に入力される。 | K22: 「出荷の配送業者-設定値」を参照
B23: =ROW() - 5 -> 18 | F23: 外部コード | G23: ー | H23: 文字列 | I23: ー | K23: 「出荷の配送業者-設定値」を参照
B24: =ROW() - 5 -> 19 | F24: 請求グループID | G24: ー | H24: 請求グループ（ユーザー定義） | I24: ー | K24: 「出荷の配送業者-設定値」を参照
B25: =ROW() - 5 -> 20 | F25: 容積係数 | G25: ー | H25: 数値 | I25: 0 | K25: 「出荷の配送業者-設定値」を参照
B26: =ROW() - 5 -> 21 | C26: 住所 | F26: 名前または説明 | G26: ー | H26: 文字列 | I26: ー | K26: 「出荷の配送業者-設定値」を参照
B27: =ROW() - 5 -> 22 | F27: 住所 | G27: ー | H27: 文字列 | I27: ー | J27: 詳細より以下を入力することで反映される 国/地域 郵便番号 住所 市町村 都道府県 | K27: 「出荷の配送業者-設定値」を参照
B28: =ROW() - 5 -> 23 | F28: 目的 | G28: ー | H28: 業務 委託販売 配送 固定資産 本社 ホーム 請求書 船荷 その他 支払 実際の場所 採用 送金先 サービス 安定した組織 ステートメント SWIFT 船降 | I28: ー | K28: 「出荷の配送業者-設定値」を参照
B29: =ROW() - 5 -> 24 | F29: 主要 | G29: ー | H29: はい/いいえ | I29: ー | K29: 「出荷の配送業者-設定値」を参照
B30: =ROW() - 5 -> 25 | F30: 国/地域 | G30: ー | H30: 国/地域（システム定義） | I30: ー | J30: 「詳細」より編集可能 | K30: 「出荷の配送業者-設定値」を参照
B31: =ROW() - 5 -> 26 | F31: 郵便番号 | G31: ー | H31: 文字列 | I31: ー | J31: 「詳細」より編集可能 | K31: 「出荷の配送業者-設定値」を参照
B32: =ROW() - 5 -> 27 | F32: 住所 | G32: ー | H32: 文字列 | I32: ー | J32: 「詳細」より編集可能 | K32: 「出荷の配送業者-設定値」を参照
B33: =ROW() - 5 -> 28 | F33: 市町村 | G33: ー | H33: 市町村（ユーザー定義） | I33: ー | J33: 「詳細」より編集可能 | K33: 「出荷の配送業者-設定値」を参照
B34: =ROW() - 5 -> 29 | F34: 都道府県 | G34: ー | H34: 都道府県（ユーザー定義） | I34: ー | J34: 「詳細」より編集可能 | K34: 「出荷の配送業者-設定値」を参照
B35: =ROW() - 5 -> 30 | F35: 国/地域に関する基本事項 | G35: ー | H35: はい/いいえ | I35: ー | J35: 「詳細」より編集可能 | K35: 「出荷の配送業者-設定値」を参照
B36: =ROW() - 5 -> 31 | C36: 評価プロファイル | F36: 評価プロファイル | G36: ー | H36: 文字列 | I36: ー | K36: 「出荷の配送業者-設定値」を参照
B37: =ROW() - 5 -> 32 | F37: 名前 | G37: ー | H37: 文字列 | I37: ー | K37: 「出荷の配送業者-設定値」を参照
B38: =ROW() - 5 -> 33 | F38: サイト | G38: ー | H38: サイト（ユーザー定義） | I38: ー | K38: 「出荷の配送業者-設定値」を参照
B39: =ROW() - 5 -> 34 | F39: 倉庫 | G39: ー | H39: 倉庫（ユーザー定義） | I39: ー | K39: 「出荷の配送業者-設定値」を参照
B40: =ROW() - 5 -> 35 | F40: レートエンジン | G40: ー | H40: レートエンジン（ユーザー定義） | I40: ー | K40: 「出荷の配送業者-設定値」を参照
B41: =ROW() - 5 -> 36 | F41: レートマスタ | G41: ー | H41: 入力不可 | I41: ー | K41: 「出荷の配送業者-設定値」を参照
B42: =ROW() - 5 -> 37 | F42: 輸送時間エンジン | G42: ー | H42: 輸送時間エンジン（ユーザー定義） | I42: ー | K42: 「出荷の配送業者-設定値」を参照
B43: =ROW() - 5 -> 38 | F43: 配送業者の燃料インデックス | G43: ー | H43: 配送業者の燃料インデックス（ユーザー定義） | I43: ー | K43: 「出荷の配送業者-設定値」を参照
B44: =ROW() - 5 -> 39 | F44: 有効開始日時 | G44: ー | H44: 日時 | I44: ー | K44: 「出荷の配送業者-設定値」を参照
B45: =ROW() - 5 -> 40 | F45: 有効終了日時 | G45: ー | H45: 日時 | I45: ー | K45: 「出荷の配送業者-設定値」を参照

Sheet 出荷の配送業者-設定値
A1: 出荷の配送業者-設定値 ※基本的には移行データを正とする
A2: ■凡例「必須：システム上必須」「必須(*)：システムで必須ではないが、トランザクション上や業務などで必須」
A3: パラメータ設定一覧へ
B4: # | C4: 概要 | F4: 概要 | O4: サービス | W4: 住所 | AG4: 評価プロファイル
C5: 出荷の配送業者 | D5: 名前 | E5: 方法 | F5: 出荷配送業者の有効化 | G5: WebサイトURL | H5: 追跡URL | I5: 仕入先 | J5: 輸送業者タイプ | K5: SCAC | L5: 製品番号順序 | M5: 配送業者の評価をアクティブ化 | N5: コンテナーの平均重量 | O5: 配送サービス | P5: 名前 | Q5: 積載テンプレートID | R5: 輸送方法 | S5: 荷渡方法 | T5: 外部コード | U5: 請求グループID | V5: 容積係数 | W5: 名前または説明 | X5: 住所 | Y5: 目的 | Z5: 主要 | AA5: 国/地域 | AB5: 郵便番号 | AC5: 住所 | AD5: 市町村 | AE5: 都道府県 | AF5: 国/地域に関する基本事項 | AG5: 評価プロファイル | AH5: 名前 | AI5: サイト | AJ5: 倉庫 | AK5: レートエンジン | AL5: レートマスタ | AM5: 輸送時間エンジン | AN5: 配送業者の燃料インデックス | AO5: 有効開始日時 | AP5: 有効終了日時
C6: 文字列 | D6: 文字列 | E6: 輸送方法（ユーザー定義） | F6: はい/いいえ | G6: 文字列 | H6: 文字列 | I6: 仕入先（ユーザー定義） | J6: なし 手動 EDI | K6: 文字列 | L6: 番号順序（ユーザー定義） | M6: はい/いいえ | N6: 数値 | O6: 文字列 | P6: 文字列 | Q6: 積荷テンプレート（ユーザー定義） | R6: 輸送方法（ユーザー定義） | S6: 入力不可 | T6: 文字列 | U6: 請求グループ（ユーザー定義） | V6: 数値 | W6: 文字列 | X6: 文字列 | Y6: 目的（ユーザー定義） | Z6: はい/いいえ | AA6: 国/地域（システム定義） | AB6: 文字列 | AC6: 文字列 | AD6: 市町村（ユーザー定義） | AE6: 都道府県（ユーザー定義） | AF6: はい/いいえ | AG6: 文字列 | AH6: 文字列 | AI6: サイト（ユーザー定義） | AJ6: 倉庫（ユーザー定義） | AK6: レートエンジン（ユーザー定義） | AL6: 入力不可 | AM6: 輸送時間エンジン（ユーザー定義） | AN6: 配送業者の燃料インデックス（ユーザー定義） | AO6: 日時 | AP6: 日時
C7: 必須
B8: =ROW() - 7 -> 1
B9: =ROW() - 7 -> 2
B10: =ROW() - 7 -> 3
B11: =ROW() - 7 -> 4
B12: =ROW() - 7 -> 5
B13: =ROW() - 7 -> 6
B14: =ROW() - 7 -> 7
B15: =ROW() - 7 -> 8

Sheet 製品
A1: 製品
B2: 製品情報管理＞製品＞すべての製品および製品マスター
B3: Product information management > Products > All products and product masters
A4: パラメータ設定一覧へ
B5: # | C5: タブ | D5: タブ説明 | E5: 項目分類 | F5: 項目 | G5: Description（標準） | H5: 設定可能値 | I5: デフォルト値 | J5: 備考 | K5: 設定値 | L5: 設定基準
B6: =ROW() - 5 -> 1 | C6: ※新規作成時の項目 | F6: 製品タイプ | H6: 品目/サービス | I6: 品目 | K6: 「製品-設定値」を参照
B7: =ROW() - 5 -> 2 | F7: 製品サブタイプ | H7: 製品/製品マスター | I7: 製品 | K7: 「製品-設定値」を参照
B8: =ROW() - 5 -> 3 | F8: 製品サービスタイプ | H8: 指定なし/保証 | I8: 指定なし | J8: 製品タイプ：サービス、製品サブタイプ：製品 の場合に選択可能 | K8: 「製品-設定値」を参照
B9: =ROW() - 5 -> 4 | F9: 小売カテゴリ | H9: カテゴリ階層（ユーザー定義） | I9: ー | K9: 「製品-設定値」を参照
B10: =ROW() - 5 -> 5 | F10: 製品キット | H10: はい/いいえ | I10: いいえ | J10: 製品サブタイプ：製品マスターの場合に選択可能 | K10: 「製品-設定値」を参照
B11: =ROW() - 5 -> 6 | C11: 一般 | E11: ID | F11: 製品番号 | H11: 文字列 | I11: ー | K11: 「製品-設定値」を参照
B12: =ROW() - 5 -> 7 | F12: 製品名 | G12: 生産の名前。製品名を指定しない場合、製品番号が製品名として適用されます。 | H12: 文字列 | I12: ー | K12: 「製品-設定値」を参照
B13: =ROW() - 5 -> 8 | F13: 検索名 | G13: 製品検索に使用される短い名前。検索名を指定しない場合、製品番号が検索名として適用されます。 | H13: 文字列 | I13: ー | K13: 「製品-設定値」を参照
B14: =ROW() - 5 -> 9 | F14: 説明 | G14: 製品の追加説明。製品の作成時に説明を作成および編集できます。製品をリリースすると、説明は変更できません。 | H14: 文字列 | I14: ー | K14: 「製品-設定値」を参照
B15: =ROW() - 5 -> 10 | E15: 管理 | F15: 製品分析コードグループ | G15: 製品マスターに関連付けられた製品分析コード グループ。製品分析コード グループは、作成時に製品マスターに関連付けられ、変更することはできません。 | H15: 製品分析コードグループ（ユーザー定義） | I15: ー | J15: 製品サブタイプ：製品マスターの場合に選択可能 「製品タブ＞設定＞分析コードグループ」から設定する | K15: 「製品-設定値」を参照
B16: =ROW() - 5 -> 11 | F16: 保管分析コードグループ | G16: データベースのレコードの固有ID | H16: 保管分析コードグループ（ユーザー定義） | I16: ー | J16: 倉庫管理をどこまで実施するかを設定する 例）サイトのみ、サイト＋倉庫、サイト＋倉庫＋保管場所 「製品タブ＞設定＞分析コードグループ」から設定する | K16: 「製品-設定値」を参照
B17: =ROW() - 5 -> 12 | F17: 追跡用分析コードグループ | G17: データベースのレコードの固有ID | H17: 追跡用分析コードグループ（ユーザー定義） | I17: ー | J17: 製品のロット管理などをどうするかを設定する 例）バッチ番号管理、シリアル番号管理 「製品タブ＞設定＞分析コードグループ」から設定する | K17: 「製品-設定値」を参照
B18: =ROW() - 5 -> 13 | E18: バリアント | F18: 色グループ | H18: 色グループ（ユーザー定義） | I18: ー | J18: 製品サブタイプ：製品マスターの場合に選択可能 | K18: 「製品-設定値」を参照
B19: =ROW() - 5 -> 14 | F19: スタイルグループ | I19: ー | K19: 「製品-設定値」を参照
B20: =ROW() - 5 -> 15 | F20: サイズグループ | I20: ー | K20: 「製品-設定値」を参照
B21: =ROW() - 5 -> 16 | E21: 製品バリアント | F21: コンフィギュレーションテクノロジ | H21: 事前に定義されたバリエーション 分析コードベースのコンフィギュレーション 制約ベースのコンフィギュレーション | I21: 事前に定義されたバリエーション | J21: 製品サブタイプ：製品マスターの場合に選択可能 | K21: 「製品-設定値」を参照
B22: =ROW() - 5 -> 17 | F22: 同じコンフィギュレーションを許可 | G22: 製品マスターでは、このオプションを選択して、既存の製品バリアントと同一の製品バリアントを作成することができます。このオプションは、製品マスターに対するコンフィギュレーション テクノロジが分析コードベースのコンフィギュレーションに設定されている場合にのみ使用できます。 | H22: はい/いいえ | I22: いいえ | K22: 「製品-設定値」を参照
B23: =ROW() - 5 -> 18 | F23: バリアントの自動生成 | G23: 製品マスターに製品分析コードを作成するときに新しい製品バリアントを生成するには、このオプションを選択します。このオプションは、製品マスターに対するコンフィギュレーション テクノロジが分析コードベースのコンフィギュレーションまたは事前に定義されたバリエーションに設定されている場合にのみ使用できます。 | H23: はい/いいえ | I23: いいえ | K23: 「製品-設定値」を参照
B24: =ROW() - 5 -> 19 | F24: 測定単位換算の有効化 | H24: はい/いいえ | I24: いいえ | K24: 「製品-設定値」を参照
B25: =ROW() - 5 -> 20 | F25: 番号の分類を使用 | H25: はい/いいえ | I25: いいえ | J25: 製品サブタイプ：製品マスターの場合に選択可能 | K25: 「製品-設定値」を参照
B26: =ROW() - 5 -> 21 | F26: 製品バリアント番号の分類 | G26: データベースのレコードの固有ID | H26: 製品の分類（ユーザー定義） | I26: ー | J26: 製品サブタイプ：製品マスターの場合に選択可能 | K26: 「製品-設定値」を参照
B27: =ROW() - 5 -> 22 | F27: 名前の分類を使用 | H27: はい/いいえ | I27: いいえ | J27: 製品サブタイプ：製品マスターの場合に選択可能 | K27: 「製品-設定値」を参照
B28: =ROW() - 5 -> 23 | F28: 製品バリアント名の分類 | G28: データベースのレコードの固有ID | H28: 製品の分類（ユーザー定義） | I28: ー | J28: 製品サブタイプ：製品マスターの場合に選択可能 | K28: 「製品-設定値」を参照
B29: =ROW() - 5 -> 24 | E29: CW | F29: CW製品 | G29: 製品数量は Catch Weight 単位で測定されます。 | H29: はい/いいえ | I29: いいえ | J29: 製品タイプ：品目の場合に選択可能 製品キット：はいの場合は選択不可 | K29: 「製品-設定値」を参照
B30: =ROW() - 5 -> 25 | C30: 倉庫 | E30: 全国自動車輸送品種別規則 (NMFC: NATIONAL MOTOR FREIGHT CLASSIFICATION) | F30: NMFC コード | H30: NMFC コード（ユーザー定義） | I30: ー | K30: 「製品-設定値」を参照
B31: =ROW() - 5 -> 26 | E31: 追加のコード | F31: STCC コード | H31: STCC (標準輸送商品コード)（ユーザー定義） | I31: ー | K31: 「製品-設定値」を参照
B32: =ROW() - 5 -> 27 | F32: 国際統一商品分類 | H32: 統一税率スケジュール（ユーザー定義） | I32: ー | K32: 「製品-設定値」を参照

Sheet 製品-設定値
A1: 製品-設定値 ※基本的には移行データを正とする
A2: ■凡例「必須：システム上必須」「必須(*)：システムで必須ではないが、トランザクション上や業務などで必須」
A3: パラメータ設定一覧へ
B4: # | C4: 一般 | G4: ※新規作成時の項目 | AA4: 倉庫
C5: ID | L5: 管理 | O5: バリアント | R5: 製品バリアント | Z5: CW | AA5: 全国自動車輸送品種別規則 (NMFC: NATIONAL MOTOR FREIGHT CLASSIFICATION) | AB5: 追加のコード
C6: 製品番号 | D6: 製品名 | E6: 検索名 | F6: 説明 | G6: 製品タイプ | H6: 製品サブタイプ | I6: 製品サービスタイプ | J6: 小売カテゴリ | K6: 製品キット | L6: 製品分析コードグループ | M6: 保管分析コードグループ | N6: 追跡用分析コードグループ | O6: 色グループ | P6: スタイルグループ | Q6: サイズグループ | R6: コンフィギュレーションテクノロジ | S6: 同じコンフィギュレーションを許可 | T6: バリアントの自動生成 | U6: 測定単位換算の有効化 | V6: 番号の分類を使用 | W6: 製品バリアント番号の分類 | X6: 名前の分類を使用 | Y6: 製品バリアント名の分類 | Z6: CW製品 | AA6: NMFC コード | AB6: STCC コード | AC6: 国際統一商品分類
C7: 文字列 （番号順序の設定に準拠するため、手動入力、自動採番どちらも可能） | D7: 文字列 | E7: 文字列 | F7: 文字列 | G7: 品目/サービス | H7: 製品/製品マスター | I7: 指定なし/保証 | J7: カテゴリ階層（ユーザー定義） | K7: はい/いいえ | L7: 製品分析コードグループ（ユーザー定義） | M7: 保管分析コードグループ（ユーザー定義） | N7: 追跡用分析コードグループ（ユーザー定義） | O7: 色グループ（ユーザー定義） | R7: 事前に定義されたバリエーション 分析コードベースのコンフィギュレーション 制約ベースのコンフィギュレーション | S7: はい/いいえ | T7: はい/いいえ | U7: はい/いいえ | V7: はい/いいえ | W7: 製品の分類（ユーザー定義） | X7: はい/いいえ | Y7: 製品の分類（ユーザー定義） | Z7: はい/いいえ | AA7: NMFC コード（ユーザー定義） | AB7: STCC (標準輸送商品コード)（ユーザー定義） | AC7: 統一税率スケジュール（ユーザー定義）
C8: 必須 | G8: 必須 | H8: 必須 | L8: 必須（製品サブタイプ：製品マスターの場合）
B9: 例 | C9: TEST_Prod-001 | G9: 品目 | H9: 製品
B10: =ROW() - 9 -> 1
B11: =ROW() - 9 -> 2
B12: =ROW() - 9 -> 3
B13: =ROW() - 9 -> 4
B14: =ROW() - 9 -> 5
B15: =ROW() - 9 -> 6
B16: =ROW() - 9 -> 7
B17: =ROW() - 9 -> 8
B18: =ROW() - 9 -> 9
B19: =ROW() - 9 -> 10
B20: =ROW() - 9 -> 11
B21: =ROW() - 9 -> 12
... B29: =ROW() - 9 -> 20

Sheet リリースされた製品
A1: リリースされた製品
B2: 製品情報管理＞製品＞リリースされた製品
B3: Product information management > Products > Released products
A4: パラメータ設定一覧へ
B5: # | C5: タブ | D5: タブ説明 | E5: 項目分類 | F5: 項目 | G5: Description（標準） | H5: 設定可能値 | I5: デフォルト値 | J5: 備考 | K5: 設定値 | L5: 設定基準
B6: =ROW() - 5 -> 1 | C6: 一般 | E6: ID | F6: 製品タイプ | H6: 品目/サービス | I6: 品目 | J6: 「製品」側からリリースすると、製品側での入力値が引き継がれる | K6: 「リリースされた製品-設定値」を参照
B7: =ROW() - 5 -> 2 | F7: 製品サブタイプ | H7: 製品/製品マスター | I7: 製品 | J7: 「製品」側からリリースすると、製品側での入力値が引き継がれる | K7: 「リリースされた製品-設定値」を参照
B8: =ROW() - 5 -> 3 | F8: 製品サービスタイプ | H8: ー | I8: ー | J8: 「製品」側からリリースすると、製品側での入力値が引き継がれる 製品タイプ：サービス、製品サブタイプ：製品 の場合に選択可能なため、リリースされた製品画面では入力不可 | K8: 「リリースされた製品-設定値」を参照
B9: =ROW() - 5 -> 4 | F9: 品目番号 | H9: 文字列 | I9: ー | K9: 「リリースされた製品-設定値」を参照
B10: =ROW() - 5 -> 5 | F10: 製品番号 | H10: 文字列 | I10: ー | J10: 「製品」側からリリースすると、製品側での入力値が引き継がれる | K10: 「リリースされた製品-設定値」を参照
B11: =ROW() - 5 -> 6 | E11: 詳細ID | F11: 製品名 | H11: 文字列 | I11: ー | J11: 「製品」側からリリースすると、製品側での入力値が引き継がれる | K11: 「リリースされた製品-設定値」を参照
B12: =ROW() - 5 -> 7 | F12: 検索名 | H12: 文字列 | I12: ー | J12: 「製品」側からリリースすると、製品側での入力値が引き継がれる | K12: 「リリースされた製品-設定値」を参照
B13: =ROW() - 5 -> 8 | F13: 説明 | H13: 文字列 | I13: ー | J13: 「製品」側からリリースすると、製品側での入力値が引き継がれる ※製品側のメニューからでないと変更不可 | K13: 「リリースされた製品-設定値」を参照
B14: =ROW() - 5 -> 9 | E14: 管理 | F14: 保管分析コードグループ | G14: データベースのレコードの固有ID | H14: 保管分析コードグループ（ユーザー定義） | I14: ー | J14: 倉庫管理をどこまで実施するかを設定する 例）サイトのみ、サイト＋倉庫、サイト＋倉庫＋保管場所 「製品タブ＞設定＞分析コードグループ」から設定する 「製品」側からリリースすると、製品側での入力値が引き継がれる | K14: 「リリースされた製品-設定値」を参照
B15: =ROW() - 5 -> 10 | F15: 追跡用分析コードグループ | G15: データベースのレコードの固有ID | H15: 追跡用分析コードグループ（ユーザー定義） | I15: ー | J15: 製品のロット管理などをどうするかを設定する 例）バッチ番号管理、シリアル番号管理 「製品タブ＞設定＞分析コードグループ」から設定する 「製品」側からリリースすると、製品側での入力値が引き継がれる | K15: 「リリースされた製品-設定値」を参照
B16: =ROW() - 5 -> 11 | F16: 品目モデルグループ | G16: 製品に関連付けられている品目モデル グループを表示します。品目モデル グループは、品目の受入と払出で製品をどのように処理するかをを制御します。品目モデル グループには、負の在庫を許可または禁止する設定が含まれます。小売製品では、[倉庫] ページの [財務マイナス在庫] および [現物マイナス在庫] オプションは、これらの品目モデル グループに対する設定を上書きしますが、小売店舗として指定されている倉庫に限られます。小売店舗として指定されていない倉庫に対しては、製品の品目モデル グループの設定が適用されます。 | H16: 品目モデルグループ（ユーザー定義） | I16: ー | K16: 「リリースされた製品-設定値」を参照
B17: =ROW() - 5 -> 12 | F17: 引当階層 | I17: ー | K17: 「リリースされた製品-設定値」を参照
B18: =ROW() - 5 -> 13 | F18: 棚卸理由コードポリシー | G18: 品目に割り当てられている棚卸理由コード ポリシー。 | I18: ー | K18: 「リリースされた製品-設定値」を参照
B19: =ROW() - 5 -> 14 | F19: 製品ライフサイクルの状態 | H19: 製品ライフサイクルの状態（ユーザー定義） | I19: ー | K19: 「リリースされた製品-設定値」を参照
B20: =ROW() - 5 -> 15 | F20: 詳細なメモグループ | G20: 品目が関連付けられている詳細なメモ グループ | H20: 詳細なメモグループ（ユーザー定義） | I20: ー | K20: 「リリースされた製品-設定値」を参照
B21: =ROW() - 5 -> 16 | C21: 購買 | E21: 発注書 | F21: 単位 | H21: 単位（ユーザー定義） | I21: ー | K21: 「リリースされた製品-設定値」を参照
B22: =ROW() - 5 -> 17 | F22: 超過配送 | G22: 製品受領書の数量が注文の数量を超過できる割合。 | H22: 数値 | I22: 0.00 | K22: 「リリースされた製品-設定値」を参照
B23: =ROW() - 5 -> 18 | F23: 過少配送 | G23: 製品受領書の数量が注文の数量を下回ることができる割合。 | H23: 数値 | I23: 0.00 | K23: 「リリースされた製品-設定値」を参照
B24: =ROW() - 5 -> 19 | F24: 会社間関係の停止 | G24: 会社間トランザクションを停止するには、このオプションを選択します。 | H24: はい/いいえ | I24: いいえ | K24: 「リリースされた製品-設定値」を参照
B25: =ROW() - 5 -> 20 | E25: 管理 | F25: 購入担当グループ | G25: 従業員と製品を購買と関連付けるための購入担当グループを選択します。 | H25: 購入担当グループ（ユーザー定義） | I25: ー | K25: 「リリースされた製品-設定値」を参照
B26: =ROW() - 5 -> 21 | F26: 価格許容範囲品目グループ | G26: 請求書の照合に使用する価格許容範囲品目グループを選択します。 | H26: 価格許容範囲品目グループ（ユーザー定義） | I26: ー | K26: 「リリースされた製品-設定値」を参照
B27: =ROW() - 5 -> 22 | F27: 仕入先 | H27: 仕入先（ユーザー定義） | I27: ー | J27: 既定の仕入先となる。 販売注文から発注書作成時などで、対象の製品に対して既定値としてここで設定した仕入先が入る。 | K27: 「リリースされた製品-設定値」を参照
B28: =ROW() - 5 -> 23 | E28: 課税 | F28: 品目消費税グループ | H28: 品目消費税グループ（ユーザー定義） | I28: ー | J28: 税の設定。 仕入先マスタ側に設定される消費税グループとの組み合わせで税率が決まる。 | K28: 「リリースされた製品-設定値」を参照
B29: =ROW() - 5 -> 24 | E29: 価格の更新 | F29: 最新購買価格 | G29: システムが製品の最新の発注書の単価を使用して [価格] フィールドの価格を更新することを示す場合は、このオプションを選択します。この更新は割引および雑費を除外します。[価格] フィールドの新しい値は、次回製品が発注書に含まれるときに適用される既定の単価になります。 | H29: はい/いいえ | I29: いいえ | K29: 「リリースされた製品-設定値」を参照
B30: =ROW() - 5 -> 25 | F30: 価格の日付 | G30: 製品の価格が最後に変更された日付。価格は、手動または販売注文や発注書の更新時に変更できます。 | H30: 日付 | I30: 更新日 | K30: 「リリースされた製品-設定値」を参照
B31: =ROW() - 5 -> 26 | E31: 価格 | F31: 価格 | G31: 標準通貨金額（国の通貨） | H31: 数値 | I31: 0.00 | J31: 既定の購買価格となる。 発注書作成時に対象の製品を選択すると、既定値としてここで設定した価格が入る。 | K31: 「リリースされた製品-設定値」を参照
B32: =ROW() - 5 -> 27 | F32: 価格の数量 | G32: 価格が適用される単位数を入力します。発注書明細行、販売注文明細行、および在庫仕訳帳明細行を入力すると、各明細行に指定した数量の単価が変換されます。 | H32: 数値 | I32: 1.00 | K32: 「リリースされた製品-設定値」を参照
B33: =ROW() - 5 -> 28 | E33: 諸掛 | F33: 諸費用価格 | G33: 価格に追加される固定金額。この金額は数量に関係なく追加されます。 | H33: 数値 | I33: 0.00 | K33: 「リリースされた製品-設定値」を参照
B34: =ROW() - 5 -> 29 | F34: 諸費用数量 | G34: 指定した雑費を単位あたり価格に配賦する時に使用される数量。このフィールドは、[単価に含む]オプションが選択されている場合にのみ使用されます。 | H34: 数値 | I34: 0.00 | K34: 「リリースされた製品-設定値」を参照
B35: =ROW() - 5 -> 30 | F35: 諸掛グループ | H35: 諸掛グループ（ユーザー定義） | I35: ー | K35: 「リリースされた製品-設定値」を参照
B36: =ROW() - 5 -> 31 | F36: 単価に含む | G36: 選択したオプションは、価格の請求金額が[諸費用数量]フィールドの数量で除算されることを示します。結果が[価格諸費用]フィールドの金額に追加されます。 | H36: はい/いいえ | I36: いいえ | K36: 「リリースされた製品-設定値」を参照
B37: =ROW() - 5 -> 32 | E37: 割引 | F37: 行割引グループ | G37: 製品が関連付けられている行割引グループを指定します。行割引グループは、販売注文または発注書を作成する際に割引を計算するために使用されます。行割引は、割引対象の量に比例しています。たとえば、10 単位購入した場合、50 米ドルの金額が割引されます。20 単位購入した場合、100 米ドルの金額が割引されるなど。 | H37: 行割引グループ（ユーザー定義） | I37: ー | K37: 「リリースされた製品-設定値」を参照
B38: =ROW() - 5 -> 33 | F38: 複数行割引 | G38: 製品が関連付けられている複数行割引を指定します。複数行割引グループは、販売注文または発注書を作成する際に割引を計算するために使用されます。 | H38: 複数行割引グループ（ユーザー定義） | I38: ー | K38: 「リリースされた製品-設定値」を参照
B39: =ROW() - 5 -> 34 | F39: 割引合計 | G39: 販売注文または発注書で割引合計を計算する際にこの製品を含めるには、このオプションを選択します。たとえば、10,000 米ドルを超える注文の合計は 1,000 米ドルの割引合計を促すことができます。 | H39: はい/いいえ | I39: はい | K39: 「リリースされた製品-設定値」を参照
B40: =ROW() - 5 -> 35 | F40: 提供品グループ | G40: オプション: 製品に対応する提供品グループを指定します。たとえば、100 個の製品が購買または販売されると追加の製品という形式で特典を与える場合に提供品を使用します。 | H40: 提供品グループ（ユーザー定義） | I40: ー | K40: 「リリースされた製品-設定値」を参照
B41: =ROW() - 5 -> 36 | F41: 価格決定制度 | H41: 数値 | I41: ー | K41: 「リリースされた製品-設定値」を参照
B42: =ROW() - 5 -> 37 | E42: 仕入先リベート | F42: 仕入先リベート品目グループ | H42: 仕入先リベート品目グループ（ユーザー定義） | I42: ー | K42: 「リリースされた製品-設定値」を参照
B43: =ROW() - 5 -> 38 | E43: 承認仕入先 | F43: 承認済仕入先チェックメソッド | H43: 確認なし 警告のみ 不許可 | I43: 確認なし | J43: 確認なし：発注書作成時に仕入先の確認なしで発注書作成が可能（どの仕入先でも発注可能） 警告のみ：承認済の仕入先以外で発注書作成時に警告メッセージが表示される（警告メッセージを無視すれば度の仕入先でも発注可能） 不許可：承認済の仕入先以外での発注書作成が不可となる | K43: 「リリースされた製品-設定値」を参照
B44: =ROW() - 5 -> 39 | C44: 販売促進 | E44: クーポン | F44: 除外 | G44: これは、現在のバージョンのクーポンではサポートされていないレガシーコンフィギュレーションです。 | H44: はい/いいえ | I44: いいえ | K44: 「リリースされた製品-設定値」を参照
B45: =ROW() - 5 -> 40 | C45: 出荷 | E45: 単独出荷 | F45: 単独出荷 | H45: はい/いいえ | I45: いいえ | K45: 「リリースされた製品-設定値」を参照
B46: =ROW() - 5 -> 41 | E46: 直納 | F46: 直納 | H46: はい/いいえ | I46: いいえ | K46: 「リリースされた製品-設定値」を参照
B47: =ROW() - 5 -> 42 | F47: 直納倉庫 | H47: 倉庫（ユーザー定義） | I47: ー | K47: 「リリースされた製品-設定値」を参照
B48: =ROW() - 5 -> 43 | E48: 梱包ボックス | F48: ピッキングワークベンチにボックス化ロジックを適用 | H48: はい/いいえ | I48: いいえ | K48: 「リリースされた製品-設定値」を参照
B49: =ROW() - 5 -> 44 | E49: 日付 | F49: 出荷開始日 | H49: 日付 | I49: ー | K49: 「リリースされた製品-設定値」を参照
B50: =ROW() - 5 -> 45 | C50: 販売 | E50: 販売注文 | F50: 単位 | H50: 単位（ユーザー定義） | I50: ー | K50: 「リリースされた製品-設定値」を参照
B51: =ROW() - 5 -> 46 | F51: 超過配送 | G51: 製品受領書の数量が注文の数量を超過できる割合。 | H51: 数値 | I51: 0.00 | K51: 「リリースされた製品-設定値」を参照
B52: =ROW() - 5 -> 47 | F52: 過少配送 | G52: 製品受領書の数量が注文の数量を下回ることができる割合。 | H52: 数値 | I52: 0.00 | K52: 「リリースされた製品-設定値」を参照
B53: =ROW() - 5 -> 48 | F53: 会社間関係の停止 | G53: 会社間トランザクションを停止するには、このオプションを選択します。 | H53: はい/いいえ | I53: いいえ | K53: 「リリースされた製品-設定値」を参照
B54: =ROW() - 5 -> 49 | E54: 管理 | F54: コミッショングループ | G54: 製品に関連付けられているコミッショングループ。コミッショングループは、販売を担当する営業員に与えられるコミッションを計算するために使用されます。 | H54: コミッション品目グループ（ユーザー定義） | I54: ー | K54: 「リリースされた製品-設定値」を参照
B55: =ROW() - 5 -> 50 | E55: 課税 | F55: 品目消費税グループ | H55: 品目消費税グループ（ユーザー定義） | I55: ー | J55: 税の設定。 顧客マスタ側に設定される消費税グループとの組み合わせで税率が決まる。 | K55: 「リリースされた製品-設定値」を参照
B56: =ROW() - 5 -> 51 | E56: 価格の更新 | F56: 販売価格モデル | G56: 製品の販売価格の調整を制御するために使用するモデルを選択します。[なし] に設定した場合、販売価格は生産原価および購買価格を考慮せずに変更されます。固定利益率を使用することにした場合は、[利益率] を選択します。次に、[利益率] フィールドで、販売価格の計算に使用する利益率を指定します。 | H56: なし 利益率 費用割合 | I56: なし | K56: 「リリースされた製品-設定値」を参照
B57: =ROW() - 5 -> 52 | F57: 基準価格 | G57: 販売価格の計算の基礎として購買価格または原価を使用するかどうかを選択します。[販売価格モデル] フィールドで [なし] を選択した場合、[基準価格] フィールドの値は使用されません。 | H57: 購買価格 原価 | I57: 購買価格 | K57: 「リリースされた製品-設定値」を参照
B58: =ROW() - 5 -> 53 | F58: 利益率 | G58: [販売価格モデル] フィールドで [利益率] を選択した場合に、販売価格を計算するために使用する利益率を入力します。 | H58: 数値 | I58: 0.00 | K58: 「リリースされた製品-設定値」を参照
B59: =ROW() - 5 -> 54 | F59: 費用割合 | H59: 数値 | I59: 0.00 | K59: 「リリースされた製品-設定値」を参照
B60: =ROW() - 5 -> 55 | F60: 価格の日付 | G60: 製品の価格が最後に変更された日付。価格は、手動または販売注文や発注書の更新時に変更できます。 | H60: 日付 | I60: 更新日 | K60: 「リリースされた製品-設定値」を参照
B61: =ROW() - 5 -> 56 | E61: 基準販売価格 | F61: 価格 | G61: 標準通貨金額（国の通貨） | H61: 数値 | I61: 0.00 | J61: 既定の販売価格となる。 販売注文作成時に対象の製品を選択すると、既定値としてここで設定した価格が入る。 | K61: 「リリースされた製品-設定値」を参照
B62: =ROW() - 5 -> 57 | F62: 価格の数量 | G62: 価格が適用される単位数を入力します。発注書明細行、販売注文明細行、および在庫仕訳帳明細行を入力すると、各明細行に指定した数量の単価が変換されます。 | H62: 数値 | I62: 1.00 | K62: 「リリースされた製品-設定値」を参照
B63: =ROW() - 5 -> 58 | E63: 諸掛 | F63: 諸費用価格 | G63: 価格に追加される固定金額。この金額は数量に関係なく追加されます。 | H63: 数値 | I63: 0.00 | K63: 「リリースされた製品-設定値」を参照
B64: =ROW() - 5 -> 59 | F64: 諸費用数量 | G64: 指定した雑費を単位あたり価格に配賦する時に使用される数量。このフィールドは、[単価に含む]オプションが選択されている場合にのみ使用されます。 | H64: 数値 | I64: 0.00 | K64: 「リリースされた製品-設定値」を参照
B65: =ROW() - 5 -> 60 | F65: 諸掛グループ | H65: 諸掛グループ（ユーザー定義） | I65: ー | K65: 「リリースされた製品-設定値」を参照
B66: =ROW() - 5 -> 61 | F66: 単価に含む | G66: 選択したオプションは、価格の請求金額が[諸費用数量]フィールドの数量で除算されることを示します。結果が[価格諸費用]フィールドの金額に追加されます。 | H66: はい/いいえ | I66: いいえ | K66: 「リリースされた製品-設定値」を参照
B67: =ROW() - 5 -> 62 | E67: 割引 | F67: 行割引グループ | G67: 製品が関連付けられている行割引グループを指定します。行割引グループは、販売注文または発注書を作成する際に割引を計算するために使用されます。行割引は、割引対象の量に比例しています。たとえば、10 単位購入した場合、50 米ドルの金額が割引されます。20 単位購入した場合、100 米ドルの金額が割引されるなど。 | H67: 行割引グループ（ユーザー定義） | I67: ー | K67: 「リリースされた製品-設定値」を参照
B68: =ROW() - 5 -> 63 | F68: 複数行割引 | G68: 製品が関連付けられている複数行割引を指定します。複数行割引グループは、販売注文または発注書を作成する際に割引を計算するために使用されます。 | H68: 複数行割引グループ（ユーザー定義） | I68: ー | K68: 「リリースされた製品-設定値」を参照
B69: =ROW() - 5 -> 64 | F69: 割引合計 | G69: 販売注文または発注書で割引合計を計算する際にこの製品を含めるには、このオプションを選択します。たとえば、10,000 米ドルを超える注文の合計は 1,000 米ドルの割引合計を促すことができます。 | H69: はい/いいえ | I69: はい | K69: 「リリースされた製品-設定値」を参照
B70: =ROW() - 5 -> 65 | F70: 提供品グループ | G70: オプション: 製品に対応する提供品グループを指定します。たとえば、100 個の製品が購買または販売されると追加の製品という形式で特典を与える場合に提供品を使用します。 | H70: 提供品グループ（ユーザー定義） | I70: ー | K70: 「リリースされた製品-設定値」を参照
B71: =ROW() - 5 -> 66 | E71: 代替製品 | F71: 使用時 | G71: 現在の製品に対して代替品目番号を使用する時期を指定するスケジュールを選択します。 | H71: なし 在庫なし 常時 | I71: なし | K71: 「リリースされた製品-設定値」を参照
B72: =ROW() - 5 -> 67 | F72: 代替品目番号 | G72: [使用時] フィールドで [在庫なし] または [常時] を選択した場合は、使用する代替品目番号を選択します。 | H72: リリース済製品（ユーザー定義） | I72: ー | K72: 「リリースされた製品-設定値」を参照
B73: =ROW() - 5 -> 68 | F73: コンフィギュレーション | I73: ー | K73: 「リリースされた製品-設定値」を参照
B74: =ROW() - 5 -> 69 | F74: サイズ | I74: ー | K74: 「リリースされた製品-設定値」を参照
B75: =ROW() - 5 -> 70 | F75: 色 | I75: ー | K75: 「リリースされた製品-設定値」を参照
B76: =ROW() - 5 -> 71 | F76: スタイル | I76: ー | K76: 「リリースされた製品-設定値」を参照
B77: =ROW() - 5 -> 72 | E77: 分割払い | F77: 適格な分割 | H77: はい/いいえ | I77: いいえ | K77: 「リリースされた製品-設定値」を参照
B78: =ROW() - 5 -> 73 | F78: 価格決定精度 | H78: 数値 | I78: ー | K78: 「リリースされた製品-設定値」を参照
B79: =ROW() - 5 -> 74 | E79: 通知と取消の自動処理 | F79: 自動的な通知と取消の除外 | H79: はい/いいえ | I79: いいえ | K79: 「リリースされた製品-設定値」を参照
B80: =ROW() - 5 -> 75 | E80: 価格調整 | F80: 価格調整を許可する | H80: はい/いいえ | I80: はい | K80: 「リリースされた製品-設定値」を参照
B81: =ROW() - 5 -> 76 | E81: 連続性 | F81: 連続スケジュールID | H81: スケジュールID（ユーザー定義） | I81: ー | K81: 「リリースされた製品-設定値」を参照
B82: =ROW() - 5 -> 77 | F82: イベント期間 | H82: 数値 | I82: 0 | K82: 「リリースされた製品-設定値」を参照
B83: =ROW() - 5 -> 78 | E83: 販売日付 | F83: 販売開始日 | H83: 日付 | I83: ー | K83: 「リリースされた製品-設定値」を参照
B84: =ROW() - 5 -> 79 | F84: 販売終了日 | H84: 日付 | I84: ー | K84: 「リリースされた製品-設定値」を参照
B85: =ROW() - 5 -> 80 | E85: 品目リベートグループ | F85: 品目リベートグループ | H85: 品目リベートグループ（ユーザー定義） | I85: ー | K85: 「リリースされた製品-設定値」を参照
B86: =ROW() - 5 -> 81 | E86: 運賃配賦 | F86: 運賃配賦グループ | H86: 運賃配賦グループ（ユーザー定義） | I86: ー | K86: 「リリースされた製品-設定値」を参照
B87: =ROW() - 5 -> 82 | E87: コマース在庫 | F87: 在庫バッファー | G87: 見積数量を計算するために、元の在庫数量から差し引く負でない値を指定します。これにより推定在庫数量を在庫レベル プロファイルと比較して、在庫レベルを決定します。 | H87: 数値 | I87: 0.00 | K87: 「リリースされた製品-設定値」を参照
B88: =ROW() - 5 -> 83 | F88: 在庫レベルのプロファイル | G88: 特定の数量の在庫レベルを決定する在庫レベル プロファイルを選択します。それぞれの在庫レベル プロファイルは、一連の在庫数量の範囲とそのマッピング レベル (在庫の有無など) を定義します。 | H88: 在庫レベル（ユーザー定義） | I88: ー | K88: 「リリースされた製品-設定値」を参照
B89: =ROW() - 5 -> 84 | C89: 対外貿易 | E89: デュアル ユース製品 | F89: デュアル ユース製品 | H89: はい/いいえ | I89: いいえ | K89: 「リリースされた製品-設定値」を参照
B90: =ROW() - 5 -> 85 | F90: デュアル ユースコード | H90: デュアル ユースコード（ユーザー定義） | I90: ー | K90: 「リリースされた製品-設定値」を参照
B91: =ROW() - 5 -> 86 | C91: 在庫の管理 | E91: 測定の重み付け | F91: 正味重量 | G91: 選択された在庫単位で表された正味重量。この情報は、重量が出荷情報として含まれる梱包明細票などの印刷レコードで使用されます。BOM が在庫単位に割り当てられている場合、正味重量は、BOM にある製品の正味重量の合計として計算できます。正味重量は、製品の間接原価の計算にも使用できます。 | H91: 数値 | I91: 0.00 | K91: 「リリースされた製品-設定値」を参照
B92: =ROW() - 5 -> 87 | F92: 風袋重量 | G92: 製品の１在庫あたり風袋重量。 | H92: 数値 | I92: 0.00 | K92: 「リリースされた製品-設定値」を参照
B93: =ROW() - 5 -> 88 | F93: 総重量 | H93: 数値 | I93: 0.00 | K93: 「リリースされた製品-設定値」を参照
B94: =ROW() - 5 -> 89 | E94: 現物分析コード | F94: 全体の奥行き | G94: 梱包を含む１在庫単位の奥行。 | H94: 数値 | I94: 0.00 | K94: 「リリースされた製品-設定値」を参照
B95: =ROW() - 5 -> 90 | F95: 全体の幅 | G95: 梱包を含む１在庫単位の幅。 | H95: 数値 | I95: 0.00 | K95: 「リリースされた製品-設定値」を参照
B96: =ROW() - 5 -> 91 | F96: 全体の高さ | G96: 梱包を含む１在庫単位の高さ。 | H96: 数値 | I96: 0.00 | K96: 「リリースされた製品-設定値」を参照
B97: =ROW() - 5 -> 92 | F97: 体積 | G97: 製品の 1 単位の品目の量 (在庫単位)。この情報は、梱包明細などに製品の量が示されるときに出荷情報として使用されます。量は、製品の間接原価の計算にも使用できます。 | H97: 数値 | I97: 0.00 | K97: 「リリースされた製品-設定値」を参照
B98: =ROW() - 5 -> 93 | E98: 追跡 | F98: バッチ番号グループ | H98: バッチ番号グループ（ユーザー定義） | I98: ー | J98: 追跡用分析コード グループでバッチ番号管理としており、自動採番とさせる場合は入力必須 ※「品目モデル グループ」を選択していないと入力不可 | K98: 「リリースされた製品-設定値」を参照
B99: =ROW() - 5 -> 94 | F99: シリアル番号グループ | H99: シリアル番号グループ（ユーザー定義） | I99: ー | J99: 追跡用分析コード グループでシリアル番号管理としており、自動採番とさせる場合は入力必須 ※「品目モデル グループ」を選択していないと入力不可 | K99: 「リリースされた製品-設定値」を参照
B100: =ROW() - 5 -> 95 | E100: 移動オーダー | F100: 超過配送 | G100: 製品受領書の数量が注文の数量を超過できる割合。 | H100: 数値 | I100: 0.00 | K100: 「リリースされた製品-設定値」を参照
...

Sheet リリースされた製品-設定値
A1: リリースされた製品-設定値 ※基本的には移行データを正とする
A2: ■凡例「必須：システム上必須」「必須(*)：システムで必須ではないが、トランザクション上や業務などで必須」
A3: パラメータ設定一覧へ
B4: # | C4: 一般 | R4: 購買 | AO4: 販売促進 | AP4: 出荷 | AU4: 販売 | CH4: 対外貿易 | CJ4: 在庫の管理 | DQ4: 生産 | EL4: 計画 | EM4: 原価の管理 | FB4: プロジェクトの管理 | FC4: 財務分析コード | FF4: 倉庫 | GI4: コマース | HH4: 輸送管理 | HI4: 製品バリアント
C5: ID | H5: 詳細ID | K5: 管理 | R5: 発注書 | V5: 管理 | Y5: 課税 | Z5: 価格の更新 | AB5: 価格 | AD5: 諸掛 | AH5: 割引 | AM5: 仕入先リベート | AN5: 承認仕入先 | AO5: クーポン | AP5: 単独出荷 | AQ5: 直納 | AS5: 梱包僕ス | AT5: 日付 | AU5: 販売注文 | AY5: 管理 | AZ5: 課税 | BA5: 価格の更新 | BF5: 基準販売価格 | BH5: 諸掛 | BL5: 割引 | BP5: 代替製品 | BV5: 分割払い | BX5: 通知と取消の自動処理 | BY5: 価格調整 | BZ5: 連続性 | CB5: 販売日付 | CD5: 品目リベートグループ | CE5: 運賃配賦 | CF5: コマース在庫 | CH5: デュアルユース製品 | CJ5: 測定の重み付け | CM5: 現物分析コード | CQ5: 追跡 | CS5: 移動オーダー | CU5: 在庫 | CW5: 出荷と入庫 | CY5: ポテンシー | DB5: 梱包業 | DD5: 品目データ | DH5: 歩留り | DI5: CW | DN5: 製品コンプライアンス | DP5: 危険物 | DY5: 測定 | EC5: 計算 | ED5: 生産 | EJ5: フォーミュラー計画 | EM5: 転記 | EN5: 原価設定 | EP5: 価格の更新 | ER5: 価格 | EU5: 諸掛 | EX5: ABC分類 | FC5: 既定の財務分析コード ※使用する財務分析コード分列追加 | FF5: 現物分析コード | FJ5: 説明 | FL5: 製品の固定の場所 | FO5: 製品フィルタコード | FY5: フィルターコードのグループ化 | GA5: 生産 | GD5: 全国自動車輸送品種別規則 (NMFC: NATIONAL MOTOR FREIGHT CLASSIFICATION) | GE5: 追加のコード | GH5: 倉庫にリリース | GI5: バリアント | GM5: 比較価格 | GO5: ブロック | GR5: バーコード | GT5: 有効化 | GU5: 製品の有効期間 | GX5: POSレジスター | HH5: 全般 | HI5: 製品バリアント | HM5: 既定の製品バリアント
C6: 品目番号 | D6: 製品番号 | E6: 製品タイプ | F6: 製品サブタイプ | G6: 製品サービスタイプ | H6: 製品名 | I6: 検索名 | J6: 説明 | K6: 保管分析コードグループ | L6: 追跡用分析コードグループ | M6: 品目モデルグループ | N6: 引当階層 | O6: 棚卸理由コードポリシー | P6: 製品ライフサイクルの状態 | Q6: 詳細なメモグループ | R6: 単位 | S6: 超過配送 | T6: 過少配送 | U6: 会社間関係の停止 | V6: 購入担当グループ | W6: 価格許容範囲品目グループ | X6: 仕入先 | Y6: 品目消費税グループ | Z6: 最新購買価格 | AA6: 価格の日付 | AB6: 価格 | AC6: 価格の数量 | AD6: 諸費用価格 | AE6: 諸費用数量 | AF6: 諸掛グループ | AG6: 単価に含む | AH6: 行割引グループ | AI6: 複数行割引 | AJ6: 割引合計 | AK6: 提供品グループ | AL6: 価格決定制度 | AM6: 仕入先リベート品目グループ | AN6: 承認済仕入先チェックメソッド | AO6: 除外 | AP6: 単独出荷 | AQ6: 直納 | AR6: 直納倉庫 | AS6: ピッキングワークベンチにボックス化ロジックを適用 | AT6: 出荷開始日 | AU6: 単位 | AV6: 超過配送 | AW6: 過少配送 | AX6: 会社間関係の停止 | AY6: コミッショングループ | AZ6: 品目消費税グループ | BA6: 販売価格モデル | BB6: 基準価格 | BC6: 利益率 | BD6: 費用割合 | BE6: 価格の日付 | BF6: 価格 | BG6: 価格の数量 | BH6: 諸費用価格 | BI6: 諸費用数量 | BJ6: 諸掛グループ | BK6: 単価に含む | BL6: 行割引グループ | BM6: 複数行割引 | BN6: 割引合計 | BO6: 提供品グループ | BP6: 使用時 | BQ6: 代替品目番号 | BR6: コンフィギュレーション | BS6: サイズ | BT6: 色 | BU6: スタイル | BV6: 適格な分割 | BW6: 価格決定精度 | BX6: 自動的な通知と取消の除外 | BY6: 価格調整を許可する | BZ6: 連続スケジュールID | CA6: イベント期間 | CB6: 販売開始日 | CC6: 販売終了日 | CD6: 品目リベートグループ | CE6: 運賃配賦グループ | CF6: 在庫バッファー | CG6: 在庫レベルのプロファイル | CH6: デュアルユース製品 | CI6: デュアルユースコード | CJ6: 正味重量 | CK6: 風袋重量 | CL6: 総重量 | CM6: 全体の奥行き | CN6: 全体の幅 | CO6: 全体の高さ | CP6: 体積 | CQ6: バッチ番号グループ | CR6: シリアル番号グループ | CS6: 超過配送 | CT6: 過少配送 | CU6: 棚卸グループ | CV6: 単位 | CW6: 着荷処理時間 | CX6: 並び替えコード | CY6: 基準属性 | CZ6: ターゲット | DA6: 属性値の記録タイミング | DB6: 梱包グループ | DC6: 梱包数量 | DD6: 在庫通知日（日数） | DE6: 有効期限（日数） | DF6: 出庫期限日（日数） | DG6: バッチマージ日付計算 | DH6: 歩留り率 | DI6: CW品目 | DJ6: CW単位 | DK6: 名目数量 | DL6: 最小数量 | DM6: 最大数量 | DN6: 規制製品 | DO6: 制限製品 | DP6: 危険物 | DQ6: BOM単位 | DR6: 定量仕損 | DS6: 変動仕損 | DT6: 原価計算レベル | DU6: 計画レベル | DV6: 原価計算レベル | DW6: ファントム | DX6: 自動完了報告 | DY6: 高さ | DZ6: 幅 | EA6: ツリー階層数 | EB6: 密度 | EC6: 計算グループ | ED6: 生産管理グループ | EE6: 生産グループ | EF6: プロパティ | EG6: 着荷 | EH6: 部品消費ルール | EI6: 倉庫にリリース | EJ6: 生産タイプ | EK6: 計画フォーミュラー | EL6: 補充グループ | EM6: 品目グループ | EN6: 原価グループ | EO6: バリアント別原価価格の使用 | EP6: 最新原価価格 | EQ6: 価格の日付 | ER6: 単位 | ES6: 価格 | ET6: 価格の数量 | EU6: 諸費用価格 | EV6: 諸費用数量 | EW6: 単価に含む | EX6: 値 | EY6: 保証金 | EZ6: 収益 | FA6: 在庫維持費 | FB6: プロジェクトカテゴリ | FC6: XXXXXX | FD6: XXXXXX | FE6: XXXXXX | FF6: 単位順序グループID | FG6: 最大ピック数量 | FH6: 梱包サイズカテゴリID | FI6: 現物分析コードグループID | FJ6: モバイルデバイス説明行１ | FK6: モバイルデバイス説明行２ | FL6: 倉庫 | FM6: サイト | FN6: 場所 | FO6: コード１ | FP6: コード２ | FQ6: コード３ | FR6: コード４ | FS6: コード５ | FT6: コード６ | FU6: コード７ | FV6: コード８ | FW6: コード９ | FX6: コード１０ | FY6: グループ １ | FZ6: グループ ２ | GA6: ライセンス プレートの場所での材料のピッキング | GB6: ピッキング ワーク センターでマイナスを許可します | GC6: 既定の生産または受け入れ数量 | GD6: NMFC コード | GE6: STCCコード | GF6: 統一税率スケジュール | GG6: 梱包クラスID | GH6: ユニットに対する制限 | GI6: 色グループ | GJ6: サイズグループ | GK6: スタイルグループ | GL6: バリアントの棚ラベルを印刷する | GM6: 基本比較単位 | GN6: 比較価格 | GO6: レジスターでブロック | GP6: ブロックされた日付 | GQ6: ブロックされる日付 | GR6: バーコード設定 | GS6: バーコード | GT6: 発効日 | GU6: 季節 | GV6: 発効日 | GW6: 失効日 | GX6: スケール製品 | GY6: 価格の入力 | GZ6: 数量の入力 | HA6: コメント入力が必要 | HB6: ゼロ価格は有効 | HC6: 数量がマイナスになる | HD6: すべての割引を禁止 | HE6: 手動割引を禁止 | HF6: 小売割引を禁止 | HG6: 支払/入金ベースの割引を禁止 | HH6: 輸送管理プロセスの使用 | HI6: コンフィギュレーション テクノロジ | HJ6: 同じコンフィギュレーションを許可 | HK6: バリアントの自動生成 | HL6: 製品分析コードグループ | HM6: コンフィギュレーション | HN6: サイズ | HO6: 色 | HP6: スタイル
C7: 文字列 （番号順序の設定に準拠するため、手動入力、自動採番どちらも可能） | D7: 文字列 （番号順序の設定に準拠するため、手動入力、自動採番どちらも可能） | E7: 品目/サービス | F7: 製品/製品マスター | G7: ー | H7: 文字列 | I7: 文字列 | J7: 文字列 | K7: 保管分析コードグループ（ユーザー定義） | L7: 追跡用分析コードグループ（ユーザー定義） | M7: 品目モデルグループ（ユーザー定義） | P7: 製品ライフサイクルの状態（ユーザー定義） | Q7: 詳細なメモグループ（ユーザー定義） | R7: 単位（ユーザー定義） | S7: 数値 | T7: 数値 | U7: はい/いいえ | V7: 購入担当グループ（ユーザー定義） | W7: 価格許容範囲品目グループ（ユーザー定義） | X7: 仕入先（ユーザー定義） | Y7: 品目消費税グループ（ユーザー定義） | Z7: はい/いいえ | AA7: 日付 | AB7: 数値 | AC7: 数値 | AD7: 数値 | AE7: 数値 | AF7: 諸掛グループ（ユーザー定義） | AG7: はい/いいえ | AH7: 行割引グループ（ユーザー定義） | AI7: 複数行割引グループ（ユーザー定義） | AJ7: はい/いいえ | AK7: 提供品グループ（ユーザー定義） | AL7: 数値 | AM7: 仕入先リベート品目グループ（ユーザー定義） | AN7: 確認なし 警告のみ 不許可 | AO7: はい/いいえ | AP7: はい/いいえ | AQ7: はい/いいえ | AR7: 倉庫（ユーザー定義） | AS7: はい/いいえ | AT7: 日付 | AU7: 単位（ユーザー定義） | AV7: 数値 | AW7: 数値 | AX7: はい/いいえ | AY7: コミッション品目グループ（ユーザー定義） | AZ7: 品目消費税グループ（ユーザー定義） | BA7: なし 利益率 費用割合 | BB7: 購買価格 原価 | BC7: 数値 | BD7: 数値 | BE7: 日付 | BF7: 数値 | BG7: 数値 | BH7: 数値 | BI7: 数値 | BJ7: 諸掛グループ（ユーザー定義） | BK7: はい/いいえ | BL7: 行割引グループ（ユーザー定義） | BM7: 複数行割引グループ（ユーザー定義） | BN7: はい/いいえ | BO7: 提供品グループ（ユーザー定義） | BP7: なし 在庫なし 常時 | BQ7: リリース済製品（ユーザー定義） | BV7: はい/いいえ | BW7: 数値 | BX7: はい/いいえ | BY7: はい/いいえ | BZ7: スケジュールID（ユーザー定義） | CA7: 数値 | CB7: 日付 | CC7: 日付 | CD7: 品目リベートグループ（ユーザー定義） | CE7: 運賃配賦グループ（ユーザー定義） | CF7: 数値 | CG7: 在庫レベル（ユーザー定義） | CH7: はい/いいえ | CI7: デュアルユースコード（ユーザー定義） | CJ7: 数値 | CK7: 数値 | CL7: 数値 | CM7: 数値 | CN7: 数値 | CO7: 数値 | CP7: 数値 | CQ7: バッチ番号グループ（ユーザー定義） | CR7: シリアル番号グループ（ユーザー定義） | CS7: 数値 | CT7: 数値 | CU7: 棚卸グループ（ユーザー定義） | CV7: 単位（ユーザー定義） | CW7: 時間 | CX7: 数値 | DB7: 梱包グループ（ユーザー定義） | DC7: 数値 | DD7: 数値 | DE7: 数値 | DF7: 数値 | DG7: 手動 最早 最遅 | DH7: 数値 | DI7: はい/いいえ | DJ7: 単位（ユーザー定義） | DK7: 数値 | DL7: 数値 | DM7: 数値 | DN7: はい/いいえ | DO7: はい/いいえ | DP7: はい/いいえ | DQ7: 単位（ユーザー定義） | DR7: 数値 | DS7: 数値 | DT7: 数値 | DU7: 数値 | DV7: 数値 | DW7: はい/いいえ | DX7: はい/いいえ | DY7: 数値 | DZ7: 数値 | EA7: 数値 | EB7: 数値 | EC7: 計算グループ（ユーザー定義） | ED7: 生産管理グループ（ユーザー定義） | EE7: 生産グループ（ユーザー定義） | EF7: プロパティ（ユーザー定義） | EG7: はい/いいえ | EH7: 開始 完了 手動 場所で利用可 | EI7: 部分引当の許可 完全引当が必要 | EJ7: 連産品 副産物 なし 計画品目 BOM フォーミュラ | EK7: リリース済製品（ユーザー定義） | EL7: 補充グループ（ユーザー定義） | EM7: 品目グループ（ユーザー定義） | EN7: 原価グループ（ユーザー定義） | EO7: はい/いいえ | EP7: はい/いいえ | EQ7: 日付 | ER7: 単位（ユーザー定義） | ES7: 数値 | ET7: 数値 | EU7: 数値 | EV7: 数値 | EW7: はい/いいえ | EX7: なし A B C | EY7: なし A B C | EZ7: なし A B C | FA7: なし A B C | FB7: プロジェクトカテゴリ（ユーザー定義） | FG7: 数値 | GB7: はい/いいえ | GC7: 数値 | GL7: はい/いいえ | GM7: 単位（ユーザー定義） | GN7: 数値 | GO7: はい/いいえ | GP7: 日付 | GQ7: 日付 | GR7: バーコード設定（ユーザー定義） | GT7: 日付 | GU7: 時期（ユーザー定義） | GV7: 日付 | GW7: 日付 | GX7: はい/いいえ | GY7: 必須ではない 新しい価格を入力する必要がある 現在の価格以上の価格を入力する必要がある 現在の価格以下の価格を入力する必要がある 価格を入力しない | GZ7: 必須ではない 数量を入力する必要がある 数量を入力しない | HA7: はい/いいえ | HB7: はい/いいえ | HC7: はい/いいえ | HD7: はい/いいえ | HE7: はい/いいえ | HF7: はい/いいえ | HG7: はい/いいえ | HH7: はい/いいえ | HJ7: はい/いいえ | HK7: はい/いいえ
C8: 必須 | D8: 必須 | E8: 必須 | F8: 必須 | H8: 必須(*) | K8: 必須(*) | L8: 必須(*) | M8: 必須(*) | R8: 必須(*) | Y8: 必須(*) | AU8: 必須(*) | AZ8: 必須(*) | CQ8: 必須(*)（バッチ番号管理で自動採番の場合） | CR8: 必須(*)（シリアル番号管理で自動採番の場合） | CV8: 必須(*) | EM8: 必須(*) | FB8: 必須(*)プロジェクト管理および会計のモジュールを使用する場合
B9: 例 | C9: TEST_Prod-001 | D9: TEST_Prod-001 | E9: 品目 | F9: 製品 | H9: テスト製品 | K9: SiteWH ※グループの設定は別途検討 | L9: Batch ※グループの設定は別途検討 | M9: 標準原価法 ※グループの設定は別途検討 | R9: 個 | Y9: 現行税率 ※グループの設定は別途検討 | AU9: 個 | AZ9: 現行税率 ※グループの設定は別途検討 | CQ9: バッチ自動採番 ※グループの設定は別途検討 | CV9: 個 | EM9: 在庫品 ※グループの設定は別途検討
B10: =ROW() - 9 -> 1
B11: =ROW() - 9 -> 2
B12: =ROW() - 9 -> 3
B13: =ROW() - 9 -> 4
B14: =ROW() - 9 -> 5
B15: =ROW() - 9 -> 6
B16: =ROW() - 9 -> 7
B17: =ROW() - 9 -> 8
B18: =ROW() - 9 -> 9
B19: =ROW() - 9 -> 10
B20: =ROW() - 9 -> 11
B21: =ROW() - 9 -> 12
... B29: =ROW() - 9 -> 20

Sheet カテゴリ階層 
A1: カテゴリ階層
B2: 製品情報管理＞設定 ＞ カテゴリと属性＞カテゴリ階層
B3: Product information management > Setup > Categories and attributes > Category hierarchies
A4: パラメータ設定一覧へ
B5: # | C5: タブ | D5: タブ説明 | E5: 項目分類 | F5: 項目 | G5: Description（標準） | H5: 設定可能値 | I5: デフォルト値 | J5: 備考 | K5: 設定値 | L5: 設定基準
B6: =ROW() - 5 -> 1 | C6: カテゴリ階層 | F6: 名前 | H6: 文字列 | I6: ー | K6: 「カテゴリ階層 -設定値」を参照
B7: =ROW() - 5 -> 2 | F7: 説明 | H7: 文字列 | I7: ー | K7: 「カテゴリ階層 -設定値」を参照
B8: =ROW() - 5 -> 3 | F8: 最終更新日 | H8: システム入力 | I8: 更新日時 | K8: ー
B9: =ROW() - 5 -> 4 | F9: 最終更新者 | H9: システム入力 | I9: ユーザー | K9: ー
B10: =ROW() - 5 -> 5 | C10: カテゴリノード | D10: 概要 | F10: 名前 | H10: 文字列 | I10: 新しいカテゴリ | K10: 「カテゴリノード -設定値」を参照 「カテゴリノード詳細 -設定値」を参照
B11: =ROW() - 5 -> 6 | F11: コード | H11: 文字列 | I11: ー | K11: 「カテゴリノード詳細 -設定値」を参照
B12: =ROW() - 5 -> 7 | F12: 有効 | H12: システム入力 | I12: はい | K12: 「カテゴリノード詳細 -設定値」を参照
B13: =ROW() - 5 -> 8 | F13: インポートステータス | H13: システム入力 | I13: 適用できません | K13: 「カテゴリノード詳細 -設定値」を参照
B14: =ROW() - 5 -> 9 | D14: 一般 | F14: 作成日 | H14: システム入力 | I14: 作成日時 | K14: 「カテゴリノード詳細 -設定値」を参照
B15: =ROW() - 5 -> 10 | F15: 作成者 | H15: システム入力 | I15: ユーザー | K15: 「カテゴリノード詳細 -設定値」を参照
B16: =ROW() - 5 -> 11 | F16: 更新日 | H16: システム入力 | I16: 更新日時 | K16: 「カテゴリノード詳細 -設定値」を参照
B17: =ROW() - 5 -> 12 | F17: 更新者 | H17: システム入力 | I17: ユーザー | K17: 「カテゴリノード詳細 -設定値」を参照
B18: =ROW() - 5 -> 13 | F18: 課税対象製品として分類 | H18: はい/いいえ | I18: いいえ | K18: 「カテゴリノード詳細 -設定値」を参照
B19: =ROW() - 5 -> 14 | F19: 説明 | H19: 文字列 | I19: ー | K19: 「カテゴリノード詳細 -設定値」を参照
B20: =ROW() - 5 -> 15 | F20: フレンドリ名 | H20: 文字列 | I20: 新しいカテゴリ | K20: 「カテゴリノード詳細 -設定値」を参照
B21: =ROW() - 5 -> 16 | F21: キーワード | H21: 文字列 | I21: ー | K21: 「カテゴリノード詳細 -設定値」を参照
B22: =ROW() - 5 -> 17 | F22: カテゴリの表示順序 | G22: この値は、カテゴリの並べ替え順序を決定するのに役立ちます。 | H22: 数値 | I22: 0 | K22: 「カテゴリノード詳細 -設定値」を参照
B23: =ROW() - 5 -> 18 | D23: 製品 | F23: 製品番号 | H23: 文字列（ユーザー定義） | I23: ー | K23: 「カテゴリノード詳細 -設定値」を参照
B24: =ROW() - 5 -> 19 | F24: 製品名 | H24: 文字列（ユーザー定義） | I24: ー | K24: 「カテゴリノード詳細 -設定値」を参照
B25: =ROW() - 5 -> 20 | F25: 製品の表示順序 | G25: この値は、カテゴリでの製品の並べ替え順序を決定するのに役立ちます。 | H25: 数値 | I25: 0 | K25: 「カテゴリノード詳細 -設定値」を参照
B26: =ROW() - 5 -> 21 | D26: カテゴリ属性 | F26: 親カテゴリからカテゴリ属性を継承 | H26: はい/いいえ | I26: いいえ | K26: 「カテゴリノード詳細 -設定値」を参照
B27: =ROW() - 5 -> 22 | F27: 名前 | H27: 文字列（ユーザー定義） | I27: ー | K27: 「カテゴリノード詳細 -設定値」を参照
B28: =ROW() - 5 -> 23 | F28: タイプ | H28: 文字列（ユーザー定義） | I28: ー | K28: 「カテゴリノード詳細 -設定値」を参照
B29: =ROW() - 5 -> 24 | F29: 属性タイプ | H29: 文字列（ユーザー定義） | I29: ー | K29: 「カテゴリノード詳細 -設定値」を参照
B30: =ROW() - 5 -> 25 | F30: 継承元 | H30: システム入力 | I30: ー | K30: 「カテゴリノード詳細 -設定値」を参照
B31: =ROW() - 5 -> 26 | D31: 商品コード | F31: 商品コード | H31: 文字列（ユーザー定義） | I31: ー | K31: 「カテゴリノード詳細 -設定値」を参照
B32: =ROW() - 5 -> 27 | F32: 説明 | H32: 文字列（ユーザー定義） | I32: ー | K32: 「カテゴリノード詳細 -設定値」を参照
B33: =ROW() - 5 -> 28 | F33: 階層名 | H33: 文字列（ユーザー定義） | I33: ー | K33: 「カテゴリノード詳細 -設定値」を参照
B34: =ROW() - 5 -> 29 | D34: カテゴリページ | F34: 名前 | H34: 文字列 | I34: ー | K34: 「カテゴリノード詳細 -設定値」を参照
B35: =ROW() - 5 -> 30 | F35: 説明 | H35: 文字列 | I35: ー | K35: 「カテゴリノード詳細 -設定値」を参照

Sheet カテゴリ階層 -設定値
A1: カテゴリ階層-設定値
A2: ■凡例「必須：システム上必須」「必須(*)：システムで必須ではないが、トランザクション上や業務などで必須」
A3: パラメータ設定一覧へ
B4: # | C4: カテゴリ階層
C5: 名前 | D5: 説明
C6: 文字列 | D6: 文字列
C7: 必須
B8: 例 | C8: 販売TESTカテゴリ | D8: 販売用カテゴリ階層
B9: =ROW() - 8 -> 1
B10: =ROW() - 8 -> 2
B11: =ROW() - 8 -> 3
B12: =ROW() - 8 -> 4
B13: =ROW() - 8 -> 5
B14: =ROW() - 8 -> 6
B15: =ROW() - 8 -> 7
B16: =ROW() - 8 -> 8
B17: =ROW() - 8 -> 9
B18: =ROW() - 8 -> 10

Sheet カテゴリノード -設定値
A1: カテゴリノード-設定値 ※基本的には移行データを正とする
A2: ■凡例「必須：システム上必須」「必須(*)：システムで必須ではないが、トランザクション上や業務などで必須」
A3: パラメータ設定一覧へ
B4: # | D4: 名前
C5: カテゴリ階層名 | D5: 第一階層 | E5: 第二階層 | F5: 第三階層 | G5: 第四階層 | H5: 第五階層
C6: カテゴリ階層（ユーザー定義） | D6: 文字列 | E6: 文字列 | F6: 文字列 | G6: 文字列 | H6: 文字列
B7: 例 | C7: 販売TESTカテゴリ | D7: 階層1
C8: 販売TESTカテゴリ | D8: 階層1 | E8: 階層1-1
C9: 販売TESTカテゴリ | D9: 階層1 | E9: 階層1-1 | F9: 階層1-1-A
C10: 販売TESTカテゴリ | D10: 階層1 | E10: 階層1-1 | F10: 階層1-1-B
C11: 販売TESTカテゴリ | D11: 階層1 | E11: 階層1-2
C12: 販売TESTカテゴリ | D12: 階層1 | E12: 階層1-2 | F12: 階層1-2-C
B13: =ROW() - 12 -> 1
B14: =ROW() - 12 -> 2
B15: =ROW() - 12 -> 3
B16: =ROW() - 12 -> 4
B17: =ROW() - 12 -> 5
B18: =ROW() - 12 -> 6
B19: =ROW() - 12 -> 7
B20: =ROW() - 12 -> 8
B21: =ROW() - 12 -> 9
B22: =ROW() - 12 -> 10
B23: =ROW() - 12 -> 11
B24: =ROW() - 12 -> 12
... B52: =ROW() - 12 -> 40

Sheet カテゴリノード詳細 -設定値
A1: カテゴリノード詳細-設定値 ※基本的には移行データを正とする
A2: ■凡例「必須：システム上必須」「必須(*)：システムで必須ではないが、トランザクション上や業務などで必須」
A3: パラメータ設定一覧へ
B4: # | E4: カテゴリ階層 | I4: 一般 | R4: 製品
C5: カテゴリ階層名 | D5: 上位階層 | E5: 名前 | F5: コード | G5: 有効 | H5: インポートステータス | I5: 作成日 | J5: 作成者 | K5: 更新日 | L5: 更新者 | M5: 課税対象製品として分類 | N5: 説明 | O5: フレンドリ名 | P5: キーワード | Q5: カテゴリの表示順序 | R5: 製品番号 | S5: 製品名 | T5: 製品の表示順序
C6: カテゴリ階層（ユーザー定義） | G6: はい/いいえ | M6: はい/いいえ | N6: 文字列 | Q6: 数値
C7: 必須 | E7: 必須 | G7: 必須
B8: 例 | C8: 販売TESTカテゴリ | D8: - | E8: 階層1 | G8: はい
C9: 販売TESTカテゴリ | D9: 階層1 | E9: 階層1-1 | G9: はい
C10: 販売TESTカテゴリ | D10: 階層1-1 | E10: 階層1-1-A | G10: はい
C11: 販売TESTカテゴリ | D11: 階層1-1 | E11: 階層1-1-B | G11: はい
C12: 販売TESTカテゴリ | D12: 階層1 | E12: 階層1-2 | G12: はい
C13: 販売TESTカテゴリ | D13: 階層1-2 | E13: 階層1-2-C | G13: はい
B14: =ROW() - 13 -> 1
B15: =ROW() - 13 -> 2
B16: =ROW() - 13 -> 3
B17: =ROW() - 13 -> 4
B18: =ROW() - 13 -> 5
B19: =ROW() - 13 -> 6
B20: =ROW() - 13 -> 7
B21: =ROW() - 13 -> 8
B22: =ROW() - 13 -> 9
B23: =ROW() - 13 -> 10
B24: =ROW() - 13 -> 11
B25: =ROW() - 13 -> 12
... B53: =ROW() - 13 -> 40

Sheet カテゴリ階層ロールのアソシエーション 
A1: カテゴリ階層ロールのアソシエーション
B2: 製品情報管理＞設定 ＞ カテゴリと属性＞カテゴリ階層ロールのアソシエーション
B3: Product information management > Setup > Categories and attributes > Category hierarchy role associations
A4: パラメータ設定一覧へ
B5: # | C5: タブ | D5: タブ説明 | E5: 項目分類 | F5: 項目 | G5: Description（標準） | H5: 設定可能値 | I5: デフォルト値 | J5: 備考 | K5: 設定値 | L5: 設定基準
B6: =ROW() - 5 -> 1 | C6: カテゴリ階層ロールのアソシエーション | F6: カテゴリ階層タイプ | H6: 調達カテゴリ階層 販売カテゴリ階層 コマース製品階層 商品コード階層 派生財務分析階層 補助小売階層 小売仕入先製品階層 小売チャネルナビゲーション階層 Packing material hierarchy Common Data Service 原価管理階層 | I6: ー
B7: =ROW() - 5 -> 2 | F7: カテゴリ階層 | G7: データベースのレコードの固有ID | H7: カテゴリ階層（ユーザー定義） | I7: ー

Sheet カテゴリ階層ロールのアソシエーション  -設定値
A1: カテゴリ階層ロールのアソシエーション -設定値
A2: ■凡例「必須：システム上必須」「必須(*)：システムで必須ではないが、トランザクション上や業務などで必須」
A3: パラメータ設定一覧へ
B4: # | C4: カテゴリ階層ロールのアソシエーション
C6: カテゴリ階層タイプ | D6: カテゴリ階層
C7: リスト値 | D7: カテゴリ階層（ユーザー定義）
C8: 必須 | D8: 必須
B9: =ROW() - 8 -> 1
B10: =ROW() - 8 -> 2
B11: =ROW() - 8 -> 3
B12: =ROW() - 8 -> 4
B13: =ROW() - 8 -> 5

Sheet 既定で繰延される品目
A1: 既定で繰延される品目
B2: サブスクリプション請求管理＞収益および経費の繰延＞設定＞既定で繰延される品目
B3: Subscription billing＞Revenue and expense deferrals＞Setup＞Items deferred by default
A4: パラメータ設定一覧へ
B5: # | C5: タブ | D5: タブ説明 | E5: 項目分類 | F5: 項目 | G5: Description（標準） | H5: 設定可能値 | I5: デフォルト値 | J5: 備考 | K5: 設定値 | L5: 設定基準
B6: =ROW() - 5 -> 1 | C6: 販売注文 | F6: 品目コード | G6: ー | H6: テーブル グループ カテゴリ | I6: テーブル | K6: 「既定で繰延される品目 - 設定値」参照
B7: =ROW() - 5 -> 2 | F7: 品目関係 | G7: ー | H7: 品目グループ（ユーザー定義） リリースされた製品（ユーザー定義） | I7: ー | J7: [品目コード]で[グループ]を選択したとき ⇒品目グループ（ユーザー定義） [品目コード]で[テーブル]を選択したとき ⇒リリースされた製品（ユーザー定義） [品目コード]で[すべて]または[カテゴリ]を選択したとき ⇒操作不可 | K7: 「既定で繰延される品目 - 設定値」参照
B8: =ROW() - 5 -> 3 | F8: カテゴリの関係 | G8: データベースのレコードの固有ID | H8: カテゴリ階層（ユーザー定義） | I8: ー | K8: 「既定で繰延される品目 - 設定値」参照
B9: =ROW() - 5 -> 4 | C9: 購買 | F9: 品目コード | G9: ー | H9: テーブル グループ カテゴリ | I9: テーブル | K9: 「既定で繰延される品目 - 設定値」参照
B10: =ROW() - 5 -> 5 | F10: 品目関係 | G10: ー | H10: 品目グループ（ユーザー定義） リリースされた製品（ユーザー定義） | I10: ー | J10: [品目コード]で[グループ]を選択したとき ⇒品目グループ（ユーザー定義） [品目コード]で[テーブル]を選択したとき ⇒リリースされた製品（ユーザー定義） [品目コード]で[すべて]または[カテゴリ]を選択したとき ⇒操作不可 | K10: 「既定で繰延される品目 - 設定値」参照
B11: =ROW() - 5 -> 6 | F11: カテゴリの関係 | G11: データベースのレコードの固有ID | H11: カテゴリ階層（ユーザー定義） | I11: ー | K11: 「既定で繰延される品目 - 設定値」参照

Sheet 既定で繰延される品目 - 設定値
A1: 既定で繰延される品目 - 設定値 ※基本的には移行データを正とする
A2: ■凡例「必須：システム上必須」「必須(*)：システムで必須ではないが、トランザクション上や業務などで必須」
A3: パラメータ設定一覧へ
B4: # | C4: タブ | D4: 品目コード | E4: 品目関係 | F4: カテゴリの関係
C5: 販売注文 購買 | D5: テーブル グループ カテゴリ | E5: 品目グループ（ユーザー定義） リリースされた製品（ユーザー定義） | F5: カテゴリ階層（ユーザー定義）
C6: ー | D6: 必須 | E6: 必須（品目コード：テーブル、グループ選択時） | F6: 必須（品目コード：カテゴリ選択時）
B7: =ROW() - 6 -> 1
B8: =ROW() - 6 -> 2
B9: =ROW() - 6 -> 3
B10: =ROW() - 6 -> 4
B11: =ROW() - 6 -> 5

Sheet 従業員
A1: 従業員
B2: 人事管理＞作業者＞従業員
B3: Human resources > Workers > Employees
A4: パラメータ設定一覧へ
B5: # | C5: タブ | D5: タブ説明 | E5: 項目分類 | F5: 項目 | G5: Description（標準） | H5: 設定可能値 | I5: デフォルト値 | J5: 備考 | K5: 設定値 | L5: 設定基準
B6: =ROW() - 5 -> 1 | C6: プロファイル | E6: 作業者の概要 | F6: 従業員番号 | H6: 文字列 | I6: ー | J6: 番号順序の設定に準拠する | K6: 「従業員-設定値」を参照
B7: =ROW() - 5 -> 2 | F7: 元の採用日付 | H7: 日付 | I7: ー | K7: 「従業員-設定値」を参照
B8: =ROW() - 5 -> 3 | F8: 勤続日数 | H8: 日付 | I8: ー | K8: 「従業員-設定値」を参照
B9: =ROW() - 5 -> 4 | F9: 記念日 | H9: 日付 | I9: ー | K9: 「従業員-設定値」を参照
B10: =ROW() - 5 -> 5 | F10: タイトル | G10: データベースのレコードの固有ID | H10: タイトル（ユーザー定義） | I10: ー | J10: 従業員を活用したワークフローを作成する際に、分岐の条件や、ワークフロー終了の条件などで使用可能 | K10: 「従業員-設定値」を参照
B11: =ROW() - 5 -> 6 | F11: 在宅勤務 | H11: はい/いいえ | I11: いいえ | K11: 「従業員-設定値」を参照
B12: =ROW() - 5 -> 7 | F12: 職場の場所 | H12: 文字列 | I12: ー | K12: 「従業員-設定値」を参照
B13: =ROW() - 5 -> 8 | F13: 職場の住所 | I13: ー | K13: 「従業員-設定値」を参照
B14: =ROW() - 5 -> 9 | F14: 再雇用 | G14: 作業者に再雇用資格があるかどうかを示す | H14: はい/いいえ | I14: いいえ | K14: 「従業員-設定値」を参照
B15: =ROW() - 5 -> 10 | F15: その他の情報＞アドレス帳 | G15: 作業者が所属するアドレス帳を選択します。アドレス帳は、小売作業者がログインできる店舗を管理します。作業者のアドレス帳には、店舗のアドレス帳を含める必要があります。 | H15: アドレス帳（ユーザー定義） | I15: ー | K15: 「従業員-設定値」を参照
B16: =ROW() - 5 -> 11 | F16: その他の情報＞言語 | H16: 言語（システム定義） | I16: 法人に設定された言語が入る | K16: 「従業員-設定値」を参照
B17: =ROW() - 5 -> 12 | E17: 名前の詳細 | F17: 名 | H17: 文字列 | I17: ー | K17: 「従業員-設定値」を参照
B18: =ROW() - 5 -> 13 | F18: ミドルネーム | H18: 文字列 | I18: ー | K18: 「従業員-設定値」を参照
B19: =ROW() - 5 -> 14 | F19: 姓の接頭語 | H19: 文字列 | I19: ー | K19: 「従業員-設定値」を参照
B20: =ROW() - 5 -> 15 | F20: 姓 | H20: 文字列 | I20: ー | K20: 「従業員-設定値」を参照
B21: =ROW() - 5 -> 16 | F21: 呼称 | H21: 文字列 | I21: ー | K21: 「従業員-設定値」を参照
B22: =ROW() - 5 -> 17 | F22: 検索名 | H22: 文字列 | I22: ー | K22: 「従業員-設定値」を参照
B23: =ROW() - 5 -> 18 | F23: イニシャル | H23: 文字列 | I23: ー | K23: 「従業員-設定値」を参照
B24: =ROW() - 5 -> 19 | F24: 個人の肩書き | G24: データベースのレコードの固有ID | H24: 名前のタイトルまたは接尾語（ユーザー定義） | I24: ー | K24: 「従業員-設定値」を参照
B25: =ROW() - 5 -> 20 | F25: 個人の接尾語 | G25: データベースのレコードの固有ID | H25: 名前のタイトルまたは接尾語（ユーザー定義） | K25: 「従業員-設定値」を参照
B26: =ROW() - 5 -> 21 | F26: 職務の肩書き | H26: 文字列 | I26: ー | K26: 「従業員-設定値」を参照
B27: =ROW() - 5 -> 22 | F27: 職務の接尾語 | H27: 文字列 | I27: ー | K27: 「従業員-設定値」を参照
B28: =ROW() - 5 -> 23 | F28: 名（ふりがな） | H28: 文字列 | I28: ー | K28: 「従業員-設定値」を参照
B29: =ROW() - 5 -> 24 | F29: ミドルネームネーム（ふりがな） | H29: 文字列 | I29: ー | K29: 「従業員-設定値」を参照
B30: =ROW() - 5 -> 25 | F30: 姓（フリガナ） | H30: 文字列 | I30: ー | K30: 「従業員-設定値」を参照
B31: =ROW() - 5 -> 26 | F31: 表示名 | G31: データベースのレコードの固有ID | H31: 名前の順序（ユーザー定義） | I31: グローバルアドレス帳パラメータの「名前の順序」に設定されているもの | K31: 「従業員-設定値」を参照
B32: =ROW() - 5 -> 27 | E32: 住所 | F32: 名前または説明 | H32: 文字列 | I32: ー | K32: 「従業員-設定値」を参照
B33: =ROW() - 5 -> 28 | F33: 納入先（月次締め請求書） | H33: 文字列 | I33: ー | K33: 「従業員-設定値」を参照
B34: =ROW() - 5 -> 29 | F34: 敬称 | H34: 御中 様 | I34: ー | K34: 「従業員-設定値」を参照
B35: =ROW() - 5 -> 30 | F35: 目的 | H35: 目的（ユーザー定義） | I35: ホーム | K35: 「従業員-設定値」を参照
B36: =ROW() - 5 -> 31 | F36: 国/地域 | H36: 国/地域（システム定義） | I36: 作業者のユーザーオプションに設定されている国/地域 | K36: 「従業員-設定値」を参照
B37: =ROW() - 5 -> 32 | F37: 郵便番号 | H37: 郵便番号（ユーザー定義） | I37: ー | J37: 郵便番号インポートをしているとインポートしたものから選択可能 | K37: 「従業員-設定値」を参照
B38: =ROW() - 5 -> 33 | F38: 住所 | H38: 文字列 | I38: ー | J38: 郵便番号インポートをしていると選んだ郵便番号に付随する住所ががいる | K38: 「従業員-設定値」を参照
B39: =ROW() - 5 -> 34 | F39: 市町村 | H39: 文字列 | I39: ー | J39: 郵便番号インポートをしていると選んだ郵便番号に付随する市町村ががいる | K39: 「従業員-設定値」を参照
B40: =ROW() - 5 -> 35 | F40: 都道府県 | H40: 文字列 | I40: ー | J40: 郵便番号インポートをしていると選んだ郵便番号に付随する都道府県ががいる | K40: 「従業員-設定値」を参照
B41: =ROW() - 5 -> 36 | F41: 主要 | H41: はい/いいえ | I41: はい | J41: 既に主要住所がある場合は、デフォルト値「いいえ」になる | K41: 「従業員-設定値」を参照
B42: =ROW() - 5 -> 37 | F42: プライベート | H42: はい/いいえ | I42: はい | K42: 「従業員-設定値」を参照
B43: =ROW() - 5 -> 38 | F43: 国/地域に関する基本事項 | H43: はい/いいえ | I43: はい | K43: 「従業員-設定値」を参照
B44: =ROW() - 5 -> 39 | E44: 連絡先情報 | F44: 説明 | H44: 文字列 | I44: ー | K44: 「従業員-設定値」を参照
B45: =ROW() - 5 -> 40 | F45: タイプ | H45: 電話 メールアドレス URL テレックス FAX Facebook Twitter LinkedIn | I45: 電話 | K45: 「従業員-設定値」を参照
B46: =ROW() - 5 -> 41 | F46: 連絡先の電話番号/住所 | H46: 文字列 | I46: ー | K46: 「従業員-設定値」を参照
B47: =ROW() - 5 -> 42 | F47: 内線 | H47: 文字列 | I47: ー | K47: 「従業員-設定値」を参照
B48: =ROW() - 5 -> 43 | F48: 主要 | H48: チェック/チェック無 | I48: チェック無 | K48: 「従業員-設定値」を参照
B49: =ROW() - 5 -> 44 | E49: 個人情報 | F49: ファミリ情報＞配偶者の有無 | H49: なし 既婚 未婚 死別 離婚 共有中 登録パートナーシップ 別居 シビルパートナーシップ | I49: なし | K49: 「従業員-設定値」を参照
B50: =ROW() - 5 -> 45 | F50: ファミリ情報＞相互関係の数 | H50: 数値 | I50: 0 | K50: 「従業員-設定値」を参照
B51: =ROW() - 5 -> 46 | F51: ファミリ情報＞配偶者の有無の日付 | G51: 配偶者の有無を有効にした日付。 | H51: 日付 | I51: ー | K51: 「従業員-設定値」を参照
B52: =ROW() - 5 -> 47 | F52: ファミリ情報＞出身民族 | G52: データベースのレコードの固有ID | H52: 出身民族（ユーザー定義） | I52: ー | K52: 「従業員-設定値」を参照
B53: =ROW() - 5 -> 48 | F53: ファミリ情報＞性別 | H53: 男性 女性 不特定 | I53: ー | K53: 「従業員-設定値」を参照
B54: =ROW() - 5 -> 49 | F54: ファミリ情報＞生年月日 | H54: 日付 | I54: ー | K54: 「従業員-設定値」を参照
B55: =ROW() - 5 -> 50 | F55: ファミリ情報＞年齢 | G55: 本日の時点での作業者の年齢 | H55: 数値（生年月日から自動反映） | K55: 「従業員-設定値」を参照
B56: =ROW() - 5 -> 51 | F56: ファミリ情報＞死亡日 | H56: 日付 | I56: ー | K56: 「従業員-設定値」を参照
B57: =ROW() - 5 -> 52 | F57: ファミリ情報＞母国語 | G57: データベースのレコードの固有ID | H57: 言語コード（ユーザー定義） | I57: ー | K57: 「従業員-設定値」を参照
B58: =ROW() - 5 -> 53 | F58: 教育＞フルタイム学生 | H58: はい/いいえ | I58: いいえ | K58: 「従業員-設定値」を参照
B59: =ROW() - 5 -> 54 | F59: 教育＞教育 | H59: 文字列 | I59: ー | K59: 「従業員-設定値」を参照
B60: =ROW() - 5 -> 55 | F60: 障碍＞障碍のあるユーザー | H60: はい/いいえ | I60: いいえ | K60: 「従業員-設定値」を参照
B61: =ROW() - 5 -> 56 | F61: 障碍＞確認日 | H61: 日付 | I61: ー | K61: 「従業員-設定値」を参照
B62: =ROW() - 5 -> 57 | F62: 兵役＞退役軍人のステータス | G62: データベースのレコードの固有ID | H62: 退役軍人状態（ユーザー定義） | I62: ー | K62: 「従業員-設定値」を参照
B63: =ROW() - 5 -> 58 | F63: 兵役＞兵役の開始日 | H63: 日付 | I63: ー | K63: 「従業員-設定値」を参照
B64: =ROW() - 5 -> 59 | F64: 兵役＞兵役の終了日 | H64: 日付 | I64: ー | K64: 「従業員-設定値」を参照
B65: =ROW() - 5 -> 60 | F65: 兵役＞退役傷病軍人 | H65: はい/いいえ | I65: いいえ | K65: 「従業員-設定値」を参照
B66: =ROW() - 5 -> 61 | F66: 海外駐在情報＞海外駐在ルール | H66: はい/いいえ | I66: いいえ | K66: 「従業員-設定値」を参照
B67: =ROW() - 5 -> 62 | F67: 海外駐在情報＞海外駐在ルールの開始日 | H67: 日付 | I67: ー | J67: 「海外駐在ルール」が「はい」の時入力可能 | K67: 「従業員-設定値」を参照
B68: =ROW() - 5 -> 63 | F68: 海外駐在情報＞海外駐在ルールの終了日 | H68: 日付 | I68: ー | J68: 「海外駐在ルール」が「はい」の時入力可能 | K68: 「従業員-設定値」を参照
B69: =ROW() - 5 -> 64 | F69: 国/地域＞出身国/地域 | H69: 住所の設定の国/地域（ユーザー定義） | I69: ー | K69: 「従業員-設定値」を参照
B70: =ROW() - 5 -> 65 | F70: 国/地域＞出生市町村 | H70: 住所の設定の市町村（ユーザー定義） | I70: ー | K70: 「従業員-設定値」を参照
B71: =ROW() - 5 -> 66 | F71: 国/地域＞母親の出身国/地域 | H71: 住所の設定の国/地域（ユーザー定義） | I71: ー | K71: 「従業員-設定値」を参照
B72: =ROW() - 5 -> 67 | F72: 国/地域＞父親の出身国/地域 | H72: 住所の設定の国/地域（ユーザー定義） | I72: ー | K72: 「従業員-設定値」を参照
B73: =ROW() - 5 -> 68 | F73: 国/地域＞市民権を有する国/地域 | H73: 住所の設定の国/地域（ユーザー定義） | I73: ー | K73: 「従業員-設定値」を参照
B74: =ROW() - 5 -> 69 | F74: 国/地域＞国籍 国 地域 | H74: 住所の設定の国/地域（ユーザー定義） | I74: ー | K74: 「従業員-設定値」を参照
B75: =ROW() - 5 -> 70 | E75: スキルマッピング | F75: スキルマッピングの対象に含める | H75: はい/いいえ | I75: はい | K75: 「従業員-設定値」を参照
B76: =ROW() - 5 -> 71 | F76: 理由コード | H76: 理由コード（ユーザー定義） | I76: ー | K76: 「従業員-設定値」を参照
B77: =ROW() - 5 -> 72 | C77: 作業履歴 | E77: 概要 | F77: 開始＞雇用開始日 | G77: このレコードの有効開始時刻です。 | H77: 日付時間 | I77: ー | K77: 「従業員-設定値」を参照
B78: =ROW() - 5 -> 73 | F78: 開始＞開始日 | H78: 日付時間 | I78: ー | K78: 「従業員-設定値」を参照
B79: =ROW() - 5 -> 74 | F79: 開始＞調整済開始日 | H79: 日付時間 | I79: ー | K79: 「従業員-設定値」を参照
B80: =ROW() - 5 -> 75 | F80: 開始＞猶予期間 | H80: 日付時間 | I80: ー | K80: 「従業員-設定値」を参照
B81: =ROW() - 5 -> 76 | F81: 開始＞雇用終了日 | G81: このレコードの有効終了時刻です。 | H81: 日付時間 | I81: ー | K81: 「従業員-設定値」を参照
B82: =ROW() - 5 -> 77 | F82: 終了＞最終勤務日 | H82: 日付時間 | I82: ー | K82: 「従業員-設定値」を参照
B83: =ROW() - 5 -> 78 | F83: 終了＞退職日 | H83: 日付時間 | I83: ー | K83: 「従業員-設定値」を参照
B84: =ROW() - 5 -> 79 | F84: 終了＞退職理由 | G84: データベースのレコードの固有ID | H84: 理由コード（ユーザー定義） | I84: ー | K84: 「従業員-設定値」を参照
B85: =ROW() - 5 -> 80 | E85: 従業員の詳細 | F85: 雇用カテゴリ＞雇用カテゴリ | G85: 雇用カテゴリレコードのID。 | H85: 雇用カテゴリ（ユーザー定義） | I85: ー | K85: 「従業員-設定値」を参照
B86: =ROW() - 5 -> 81 | F86: 状態＞状態 | G86: 雇用状態 | H86: なし 採用済 終了 定年退職 休暇 一時解雇 COBRAで終了 退職で終了 脂肪 一時解雇 | I86: 採用済 | K86: 「従業員-設定値」を参照
B87: =ROW() - 5 -> 82 | F87: 雇用タイプ＞雇用タイプ | G87: 雇用のID | H87: 雇用タイプ（ユーザー定義） | I87: ー | K87: 「従業員-設定値」を参照
B88: =ROW() - 5 -> 83 | F88: 雇用通知＞雇用者退職通知期間単位 | H88: 週 月 | I88: 週 | K88: 「従業員-設定値」を参照
B89: =ROW() - 5 -> 84 | F89: 雇用通知＞雇用主 | H89: 数値 | I89: 0 | K89: 「従業員-設定値」を参照
B90: =ROW() - 5 -> 85 | F90: 雇用通知＞作業者単位の通知 | H90: 週 月 | I90: 週 | K90: 「従業員-設定値」を参照
B91: =ROW() - 5 -> 86 | F91: 雇用通知＞作業者通知金額 | H91: 数値 | I91: 0 | K91: 「従業員-設定値」を参照
B92: =ROW() - 5 -> 87 | F92: カレンダー＞カレンダー | H92: 作業時間カレンダー（ユーザー定義） | I92: ー | K92: 「従業員-設定値」を参照
B93: =ROW() - 5 -> 88 | E93: 財務分析コード | F93: 既定の財務分析コード | G93: ※使用する財務分析コードがすべて出てくる | H93: ー | I93: ー | J93: 従業員（作業者）に対して既定の財務分析コードを設定する。 | K93: 「従業員-設定値」を参照
B94: =ROW() - 5 -> 89 | C94: 職位 | F94: 状態 | H94: ー | K94: 「従業員-設定値」を参照 ※職位の割り当ては「すべての職位」メニューからも可
B95: =ROW() - 5 -> 90 | F95: 職位 | G95: データベースのレコードの固有ID | H95: 職位（ユーザー定義） | I95: ー | K95: 「従業員-設定値」を参照 ※職位の割り当ては「すべての職位」メニューからも可
B96: =ROW() - 5 -> 91 | F96: 説明 | H96: 文字列 | I96: 職位の説明が自動で入る | K96: 「従業員-設定値」を参照 ※職位の割り当ては「すべての職位」メニューからも可
B97: =ROW() - 5 -> 92 | F97: 主要職位 | H97: はい/いいえ | I97: はい | J97: 既に主要職位がある場合は、デフォルト値「いいえ」になる（設定時は「主要職位にする」という項目） | K97: 「従業員-設定値」を参照 ※職位の割り当ては「すべての職位」メニューからも可
B98: =ROW() - 5 -> 93 | F98: 割り当て開始 | H98: 日付時間 | I98: 作業日の0時 | K98: 「従業員-設定値」を参照 ※職位の割り当ては「すべての職位」メニューからも可
B99: =ROW() - 5 -> 94 | F99: 割り当て終了 | H99: 日付時間 | I99: なし | K99: 「従業員-設定値」を参照 ※職位の割り当ては「すべての職位」メニューからも可
B100: =ROW() - 5 -> 95 | F100: 理由コード | G100: データベースのレコードの固有ID | H100: 理由コード（ユーザー定義） | I100: ー | K100: 「従業員-設定値」を参照 ※職位の割り当ては「すべての職位」メニューからも可
...

Sheet 従業員-設定値
A1: 従業員-設定値 ※基本的には移行データを正とする
A2: ■凡例「必須：システム上必須」「必須(*)：システムで必須ではないが、トランザクション上や業務などで必須」
A3: パラメータ設定一覧へ
B4: # | C4: プロファイル | BV4: 作業履歴 | CO4: 職位 | CX4: コマース | DM4: 時間登録 | EL4: リンク
C5: 作業者の概要 | N5: 名前の詳細 | AC5: 住所 | AO5: 連絡先情報 | AT5: 個人情報 | BT5: スキルマッピング | BV5: 概要 | CD5: 従業員の詳細 | CL5: 既定の財務分析コード ※使用する財務分析コード分列追加 | CX5: コマース | DL5: 画面レイアウト | DM5: 時間登録 | EL5: 個人へのアクション | EN5: 職位の割り当て | ES5: 雇用 | ET5: 個人情報 | FF5: 従業員報酬 | FI5: 税 | FK5: 開発 | FM5: コンピテンシー | FT5: ユーザー要求 | FV5: 休暇
C6: 従業員番号 | D6: 元の採用日付 | E6: 勤続日数 | F6: 記念日 | G6: タイトル | H6: 在宅勤務 | I6: 職場の場所 | J6: 職場の住所 | K6: 再雇用 | L6: その他の情報＞アドレス帳 | M6: その他の情報＞言語 | N6: 名 | O6: ミドルネーム | P6: 姓の接頭語 | Q6: 姓 | R6: 呼称 | S6: 検索名 | T6: イニシャル | U6: 個人の肩書き | V6: 個人の接尾語 | W6: 職務の肩書き | X6: 職務の接尾語 | Y6: 名（ふりがな） | Z6: ミドルネームネーム（ふりがな） | AA6: 姓（フリガナ） | AB6: 表示名 | AC6: 名前または説明 | AD6: 納入先（月次締め請求書） | AE6: 敬称 | AF6: 目的 | AG6: 国/地域 | AH6: 郵便番号 | AI6: 住所 | AJ6: 市町村 | AK6: 都道府県 | AL6: 主要 | AM6: プライベート | AN6: 国/地域に関する基本事項 | AO6: 説明 | AP6: タイプ | AQ6: 連絡先の電話番号/住所 | AR6: 内線 | AS6: 主要 | AT6: ファミリ情報＞配偶者の有無 | AU6: ファミリ情報＞相互関係の数 | AV6: ファミリ情報＞配偶者の有無の日付 | AW6: ファミリ情報＞出身民族 | AX6: ファミリ情報＞性別 | AY6: ファミリ情報＞生年月日 | AZ6: ファミリ情報＞年齢 | BA6: ファミリ情報＞死亡日 | BB6: ファミリ情報＞母国語 | BC6: 教育＞フルタイム学生 | BD6: 教育＞教育 | BE6: 障碍＞障碍のあるユーザー | BF6: 障碍＞確認日 | BG6: 兵役＞退役軍人のステータス | BH6: 兵役＞兵役の開始日 | BI6: 兵役＞兵役の終了日 | BJ6: 兵役＞退役傷病軍人 | BK6: 海外駐在情報＞海外駐在ルール | BL6: 海外駐在情報＞海外駐在ルールの開始日 | BM6: 海外駐在情報＞海外駐在ルールの終了日 | BN6: 国/地域＞出身国/地域 | BO6: 国/地域＞出生市町村 | BP6: 国/地域＞母親の出身国/地域 | BQ6: 国/地域＞父親の出身国/地域 | BR6: 国/地域＞市民権を有する国/地域 | BS6: 国/地域＞国籍 国 地域 | BT6: スキルマッピングの対象に含める | BU6: 理由コード | BV6: 開始＞雇用開始日 | BW6: 開始＞開始日 | BX6: 開始＞調整済開始日 | BY6: 開始＞猶予期間 | BZ6: 開始＞雇用終了日 | CA6: 終了＞最終勤務日 | CB6: 終了＞退職日 | CC6: 終了＞退職理由 | CD6: 雇用カテゴリ＞雇用カテゴリ | CE6: 状態＞状態 | CF6: 雇用タイプ＞雇用タイプ | CG6: 雇用通知＞雇用者退職通知期間単位 | CH6: 雇用通知＞雇用主 | CI6: 雇用通知＞作業者単位の通知 | CJ6: 雇用通知＞作業者通知金額 | CK6: カレンダー＞カレンダー | CL6: XXXXXX | CM6: XXXXXX | CN6: XXXXXX | CO6: 状態 | CP6: 職位 | CQ6: 説明 | CR6: 主要職位 | CS6: 割り当て開始 | CT6: 割り当て終了 | CU6: 理由コード | CV6: 職位期間（月） | CW6: 作業者 | CX6: 言語 | CY6: 雇用タイプ | CZ6: Real-time Service エラーが発生しても続行する | DA6: コミッションの売上グループ＞既定のグループ | DB6: レシート＞レシートの名前 | DC6: POS認証＞パスワード | DD6: POS認証＞POSログインのブロック | DE6: POS認証＞ユーザーは次回ログオン時にパスワードを変更する必要があります | DF6: 外部ID＞エイリアス | DG6: 外部ID＞UPN | DH6: 外部ID＞外部サブ識別子 | DI6: 情報＞トランザクション | DJ6: 情報＞店舗 | DK6: 情報＞POSアクセス許可 | DL6: 画面レイアウトID | DM6: ID | DN6: 支払ID | DO6: バッチID | DP6: バッジバージョン | DQ6: 設定＞有効 | DR6: 設定＞有効化した日 | DS6: 設定＞計算グループ | DT6: 設定＞承認グループ | DU6: 設定＞標準プロファイル | DV6: 設定＞プロファイルグループ | DW6: 設定＞新規バンドル | DX6: 設定＞カテゴリ | DY6: 設定＞タイムカードの使用 | DZ6: 設定＞コンフィギュレーション | EA6: 設定＞監修者オプション | EB6: 設定＞既定の計算グループ | EC6: 給与＞支払協定 | ED6: 給与＞勤続日数 | EE6: 給与＞期間コード | EF6: フレックスタイム＞フレックス許可済み | EG6: フレックスタイム＞フレックスグループID | EH6: フレックスタイム＞開始フレックス時間残数 | EI6: フレックスタイム＞フレックス日付 | EJ6: フレックスタイム＞フレックス時間残数 | EK6: フレックスタイム＞フィルターの設定 | EL6: 給付金への登録 | EM6: 給付金登録の結果 | EN6: 割り当てを表示 | EO6: 割り当ての追加 | EP6: 割り当ての編集 | EQ6: 割り当ての終了 | ER6: 階層での表示 | ES6: 職歴 | ET6: 名前履歴 | EU6: 特別設備 | EV6: 銀行口座 | EW6: 銀行口座出勤 | EX6: ID番号 | EY6: けが/病気インシデント | EZ6: 労働組合 | FA6: 貸与された設備 | FB6: 個人連絡先 | FC6: 福利厚生 | FD6: 審査 | FE6: 画像 | FF6: 固定プラン | FG6: 変動プラン報酬 | FH6: 変動プラン登録 | FI6: 作業者の税地域 | FJ6: Default tax region | FK6: レビュー | FL6: 目標 | FM6: 証明書 | FN6: コース | FO6: 教育 | FP6: 要職 | FQ6: テスト | FR6: 職務経験 | FS6: スキル | FT6: 作業ユーザー要求 | FU6: 作業者ユーザー要求の無効化 | FV6: 休暇の表示 | FW6: 休暇
C7: 文字列 （番号順序の設定に準拠するため、手動入力、自動採番どちらも可能） | D7: 日付 | E7: 日付 | F7: 日付 | G7: タイトル（ユーザー定義） | H7: はい/いいえ | I7: 文字列 | K7: はい/いいえ | L7: アドレス帳（ユーザー定義） | M7: 言語（システム定義） | N7: 文字列 | O7: 文字列 | P7: 文字列 | Q7: 文字列 | R7: 文字列 | S7: 文字列 | T7: 文字列 | U7: 名前のタイトルまたは接尾語（ユーザー定義） | V7: 名前のタイトルまたは接尾語（ユーザー定義） | W7: 文字列 | X7: 文字列 | Y7: 文字列 | Z7: 文字列 | AA7: 文字列 | AB7: 名前の順序（ユーザー定義） | AC7: 文字列 | AD7: 文字列 | AE7: 御中 様 | AF7: 目的（ユーザー定義） | AG7: 国/地域（システム定義） | AH7: 郵便番号（ユーザー定義） | AI7: 文字列 | AJ7: 文字列 | AK7: 文字列 | AL7: はい/いいえ | AM7: はい/いいえ | AN7: はい/いいえ | AO7: 文字列 | AP7: 電話 メールアドレス URL テレックス FAX Facebook Twitter LinkedIn | AQ7: 文字列 | AR7: 文字列 | AS7: チェック/チェック無 | AT7: なし 既婚 未婚 死別 離婚 共有中 登録パートナーシップ 別居 シビルパートナーシップ | AU7: 数値 | AV7: 日付 | AW7: 出身民族（ユーザー定義） | AX7: 男性 女性 不特定 | AY7: 日付 | AZ7: 数値（生年月日から自動反映） | BA7: 日付 | BB7: 言語コード（ユーザー定義） | BC7: はい/いいえ | BD7: 文字列 | BE7: はい/いいえ | BF7: 日付 | BG7: 退役軍人状態（ユーザー定義） | BH7: 日付 | BI7: 日付 | BJ7: はい/いいえ | BK7: はい/いいえ | BL7: 日付 | BM7: 日付 | BN7: 住所の設定の国/地域（ユーザー定義） | BO7: 住所の設定の市町村（ユーザー定義） | BP7: 住所の設定の国/地域（ユーザー定義） | BQ7: 住所の設定の国/地域（ユーザー定義） | BR7: 住所の設定の国/地域（ユーザー定義） | BS7: 住所の設定の国/地域（ユーザー定義） | BT7: はい/いいえ | BU7: 理由コード（ユーザー定義） | BV7: 日付時間 | BW7: 日付時間 | BX7: 日付時間 | BY7: 日付時間 | BZ7: 日付時間 | CA7: 日付時間 | CB7: 日付時間 | CC7: 理由コード（ユーザー定義） | CD7: 雇用カテゴリ（ユーザー定義） | CE7: なし 採用済 終了 定年退職 休暇 一時解雇 COBRAで終了 退職で終了 脂肪 一時解雇 | CF7: 雇用タイプ（ユーザー定義） | CG7: 週 月 | CH7: 数値 | CI7: 週 月 | CJ7: 数値 | CK7: 作業時間カレンダー（ユーザー定義） | CO7: ー | CP7: 職位（ユーザー定義） | CQ7: 文字列 | CR7: はい/いいえ | CS7: 日付時間 | CT7: 日付時間 | CU7: 理由コード（ユーザー定義） | CV7: 数値 | CW7: 従業員名 | CX7: 言語（ユーザー定義） | CY7: 出納係 営業員 その他 | CZ7: はい/いいえ | DA7: コミッションの売上グループ（ユーザー定義） | DB7: 文字列 | DC7: 文字列 | DD7: はい/いいえ | DE7: はい/いいえ | DF7: 文字列 | DG7: 文字列 | DH7: 文字列 | DI7: ー | DJ7: ー | DK7: ー | DL7: 画面レイアウト（ユーザー定義） | DM7: 文字列 | DN7: 文字列 | DO7: 文字列 | DP7: 文字列 | DQ7: はい/いいえ | DR7: 日付 | DS7: 計算グループ（ユーザー定義） | DT7: 承認グループ（ユーザー定義） | DU7: プロファイル（ユーザー定義） | DV7: プロファイルグループ（ユーザー定義） | DW7: はい/いいえ | DX7: プロジェクトカテゴリ（ユーザー定義） | DY7: はい/いいえ | DZ7: ジョブ カード ターミナルのコンフィギュレーション（ユーザー定義） | EA7: はい/いいえ | EB7: 計算グループ（ユーザー定義） | EC7: 支払協定（ユーザー定義） | ED7: 日付 | EE7: 期間タイプ（ユーザー定義） | EF7: はい/いいえ | EG7: フレックスグループ（ユーザー定義） | EH7: 数値 | EI7: 日付 | EJ7: 数値 | EK7: はい/いいえ
C8: 必須 | N8: 必須 | Q8: 必須 | AB8: 必須 | BV8: 必須
B9: 例 | C9: TEST_Worker-001 | M9: ja | N9: 次郎 | Q9: 検証 | AB9: LastFirst | BV9: 45017
B10: =ROW() - 9 -> 1
B11: =ROW() - 9 -> 2
B12: =ROW() - 9 -> 3
B13: =ROW() - 9 -> 4
B14: =ROW() - 9 -> 5
B15: =ROW() - 9 -> 6
B16: =ROW() - 9 -> 7
B17: =ROW() - 9 -> 8
B18: =ROW() - 9 -> 9
B19: =ROW() - 9 -> 10
B20: =ROW() - 9 -> 11
B21: =ROW() - 9 -> 12
... B39: =ROW() - 9 -> 30

Sheet 部門
A1: 部門
B2: 人事管理＞部門＞部門
B3: Human resources > Departments > Departments
A4: パラメータ設定一覧へ
B5: # | C5: タブ | D5: タブ説明 | E5: 項目分類 | F5: 項目 | G5: Description（標準） | H5: 設定可能値 | I5: デフォルト値 | J5: 備考 | K5: 設定値 | L5: 設定基準
B6: =ROW() - 5 -> 1 | C6: 作業単位 | F6: 名前 | H6: 文字列 | I6: ー | K6: 「作業単位-タ設定値」を参照
B7: =ROW() - 5 -> 2 | F7: 部門番号 | G7: 部門固有の英数字ID | H7: 英数字 | I7: 自動採番（番号順序の設定に順ずる） | J7: 採番後手動変更可能 | K7: 「作業単位-タ設定値」を参照
B8: =ROW() - 5 -> 3 | F8: 作業単位のタイプ | H8: 部門 原価部門 バリューストリーム 事業単位 すべての作業単位 小売チャネル | I8: 部門 | J8: 部門の登録する際は「部門」で登録する 一度保存した後は変更不可になる | K8: 「作業単位-タ設定値」を参照
B9: =ROW() - 5 -> 4 | E9: 一般 | F9: 検索名 | H9: 文字列 | I9: 「名前」と同様の内容が反映される | K9: 「作業単位-タ設定値」を参照
B10: =ROW() - 5 -> 5 | F10: メモ | G10: 選択した作業単位に関するメモを入力します。 | H10: 文字列 | I10: ー | K10: 「作業単位-タ設定値」を参照
B11: =ROW() - 5 -> 6 | F11: 階層 | G11: 選択したオプションは、選択した作業単位が組織階層に属していることを示します。 | H11: はい/いいえ | I11: いいえ | K11: 「作業単位-タ設定値」を参照
B12: =ROW() - 5 -> 7 | F12: DUSN番号 | H12: 数値 | I12: ー | K12: 「作業単位-タ設定値」を参照
B13: =ROW() - 5 -> 8 | F13: マネージャー | G13: データベースのレコードの固有 ID | H13: 作業者（ユーザー定義） | I13: ー | K13: 「作業単位-タ設定値」を参照
B14: =ROW() - 5 -> 9 | E14: 住所 | F14: 名前または説明 | H14: 文字列 | I14: ー | K14: 「作業単位-タ設定値」を参照
B15: =ROW() - 5 -> 10 | F15: 納入先（月次締め請求書） | H15: 文字列 | I15: ー | K15: 「作業単位-タ設定値」を参照
B16: =ROW() - 5 -> 11 | F16: 敬称 | H16: 御中 様 | I16: ー | K16: 「作業単位-タ設定値」を参照
B17: =ROW() - 5 -> 12 | F17: 目的 | H17: 目的（ユーザー定義） | I17: 業務 | K17: 「作業単位-タ設定値」を参照
B18: =ROW() - 5 -> 13 | F18: 国/地域 | H18: 国/地域（システム定義） | I18: 作業者のユーザーオプションに設定されている国/地域 | K18: 「作業単位-タ設定値」を参照
B19: =ROW() - 5 -> 14 | F19: 郵便番号 | H19: 郵便番号（ユーザー定義） | I19: ー | J19: 郵便番号インポートをしているとインポートしたものから選択可能 | K19: 「作業単位-タ設定値」を参照
B20: =ROW() - 5 -> 15 | F20: 住所 | H20: 文字列 | I20: ー | J20: 郵便番号インポートをしていると選んだ郵便番号に付随する住所ががいる | K20: 「作業単位-タ設定値」を参照
B21: =ROW() - 5 -> 16 | F21: 市町村 | H21: 文字列 | I21: ー | J21: 郵便番号インポートをしていると選んだ郵便番号に付随する市町村ががいる | K21: 「作業単位-タ設定値」を参照
B22: =ROW() - 5 -> 17 | F22: 都道府県 | H22: 文字列 | I22: ー | J22: 郵便番号インポートをしていると選んだ郵便番号に付随する都道府県ががいる | K22: 「作業単位-タ設定値」を参照
B23: =ROW() - 5 -> 18 | F23: 主要 | H23: はい/いいえ | I23: はい | J23: 既に主要住所がある場合は、デフォルト値「いいえ」になる | K23: 「作業単位-タ設定値」を参照
B24: =ROW() - 5 -> 19 | F24: プライベート | H24: はい/いいえ | I24: はい | K24: 「作業単位-タ設定値」を参照
B25: =ROW() - 5 -> 20 | F25: 国/地域に関する基本事項 | H25: はい/いいえ | I25: はい | K25: 「作業単位-タ設定値」を参照
B26: =ROW() - 5 -> 21 | E26: 連絡先情報 | F26: 説明 | H26: 文字列 | I26: ー | K26: 「作業単位-タ設定値」を参照
B27: =ROW() - 5 -> 22 | F27: タイプ | H27: 電話 メールアドレス URL テレックス FAX Facebook Twitter LinkedIn | I27: 電話 | K27: 「作業単位-タ設定値」を参照
B28: =ROW() - 5 -> 23 | F28: 連絡先の電話番号/住所 | H28: 文字列 | I28: ー | K28: 「作業単位-タ設定値」を参照
B29: =ROW() - 5 -> 24 | F29: 内線 | H29: 文字列 | I29: ー | K29: 「作業単位-タ設定値」を参照
B30: =ROW() - 5 -> 25 | F30: 主要 | H30: チェック/チェック無 | I30: チェック無 | K30: 「作業単位-タ設定値」を参照

Sheet 職務
A1: 職務
B2: 人事管理＞職務＞職務
B3: Human resources > Jobs > Jobs
A4: パラメータ設定一覧へ
B5: # | C5: タブ | D5: タブ説明 | E5: 項目分類 | F5: 項目 | G5: Description（標準） | H5: 設定可能値 | I5: デフォルト値 | J5: 備考 | K5: 設定値 | L5: 設定基準
B6: =ROW() - 5 -> 1 | C6: 一般 | F6: 職務 | H6: 文字列 | I6: ー | K6: 「職務-設定値」を参照
B7: =ROW() - 5 -> 2 | F7: 説明 | H7: 文字列 | I7: ー | K7: 「職務-設定値」を参照
B8: =ROW() - 5 -> 3 | F8: タイトル | G8: データベースのレコードの固有 ID | H8: タイトル（ユーザー定義） | I8: ー | K8: 「職務-設定値」を参照
B9: =ROW() - 5 -> 4 | F9: フルタイム相当 | G9: 0 ～ 1 の雇用係数を入力します。値 1 は、フルタイムのジョブを示します。パートタイムの雇用の場合、0 ～ 1 の間の数値を入力します。たとえば、パートタイムのジョブの場合、0.5 とします。 | H9: 数値 | I9: 1.00 | K9: 「職務-設定値」を参照
B10: =ROW() - 5 -> 5 | F10: 職位の最大数 | H10: 最大職位数/無制限 | I10: 無制限 | K10: 「職務-設定値」を参照
B11: =ROW() - 5 -> 6 | C11: 説明 | F11: 説明 | H11: 文字列 | I11: ー | K11: 「職務-設定値」を参照
B12: =ROW() - 5 -> 7 | C12: ジョブ分類 | F12: 職務 | G12: 選択したジョブに関連付ける機能を選択します。このフィールドの情報は [ジョブ機能] ページで管理されます。 | H12: 職務機能（ユーザー定義） | I12: ー | K12: 「職務-設定値」を参照
B13: =ROW() - 5 -> 8 | F13: ジョブタイプ | G13: ジョブのジョブ タイプを選択します。このフィールドの情報は [ジョブ タイプと除外ステータス] ページで管理されます。 | H13: 職務タイプ（ユーザー定義） | I13: ー | K13: 「職務-設定値」を参照
B14: =ROW() - 5 -> 9 | F14: ジョブ ファミリ | G14: データベースのレコードの固有 ID | H14: ジョブ ファミリ（ユーザー定義） | I14: ー | K14: 「職務-設定値」を参照
B15: =ROW() - 5 -> 10 | F15: POSアクセス許可グループ | G15: データベースのレコードの固有 ID | H15: POS アクセス許可グループ（ユーザー定義） | I15: ー | K15: 「職務-設定値」を参照
B16: =ROW() - 5 -> 11 | C16: 報酬 | F16: レベル | G16: データベースのレコードの固有 ID | H16: レベル（ユーザー定義） | I16: ー | K16: 「職務-設定値」を参照
B17: =ROW() - 5 -> 12 | F17: 調査会社 | G17: データベースのレコードの固有 ID | H17: 調査会社（ユーザー定義） | I17: ー | K17: 「職務-設定値」を参照
B18: =ROW() - 5 -> 13 | F18: 参照職務 | H18: 文字列 | I18: ー | K18: 「職務-設定値」を参照
B19: =ROW() - 5 -> 14 | F19: ソース | H19: 文字列 | I19: ー | K19: 「職務-設定値」を参照
B20: =ROW() - 5 -> 15 | F20: 最小しきい値 | H20: 数値 | I20: 0.0000 | K20: 「職務-設定値」を参照
B21: =ROW() - 5 -> 16 | F21: 標準職務給 | H21: 数値 | I21: 0.0000 | K21: 「職務-設定値」を参照
B22: =ROW() - 5 -> 17 | F22: 最大しきい値 | H22: 数値 | I22: 0.0000 | K22: 「職務-設定値」を参照
B23: =ROW() - 5 -> 18 | C23: スキル | F23: スキル | G23: データベースのレコードの固有 ID | H23: スキル（ユーザー定義） | I23: ー | K23: 「職務-設定値」を参照
B24: =ROW() - 5 -> 19 | F24: 説明 | H24: 文字列 | I24: ー | K24: 「職務-設定値」を参照
B25: =ROW() - 5 -> 20 | F25: レベル | G25: データベースのレコードの固有 ID | H25: 評価モデル（ユーザー定義） | I25: ー | K25: 「職務-設定値」を参照
B26: =ROW() - 5 -> 21 | F26: 重要性 | H26: なし/1-最小/2/3/4/5/6-最大 | I26: なし | K26: 「職務-設定値」を参照
B27: =ROW() - 5 -> 22 | C27: 証明書 | F27: 証明書タイプ | G27: ジョブの能力要件に追加する証明書タイプを選択します。このフィールドの情報は、[コンピテンシー - 証明書] ページで管理されます。 | H27: 証明書タイプ（ユーザー定義） | I27: ー | K27: 「職務-設定値」を参照
B28: =ROW() - 5 -> 23 | F28: 説明 | H28: 文字列 | I28: ー | K28: 「職務-設定値」を参照
B29: =ROW() - 5 -> 24 | F29: 重要性 | H29: なし/1-最小/2/3/4/5/6-最大 | I29: なし | K29: 「職務-設定値」を参照
B30: =ROW() - 5 -> 25 | C30: テスト | F30: テストタイプ | G30: ジョブの能力要件に追加するテスト タイプを選択します。このフィールドの情報は、[コンピテンシー -テスト] ページで管理されます。 | H30: テスト タイプ（ユーザー定義） | I30: ー | K30: 「職務-設定値」を参照
B31: =ROW() - 5 -> 26 | F31: 説明 | H31: 文字列 | I31: ー | K31: 「職務-設定値」を参照
B32: =ROW() - 5 -> 27 | C32: 教育 | F32: 教育 | G32: ジョブの能力要件に追加する教育訓練を選択します。このフィールドの情報は、[教育訓練] ページで管理されます。 | H32: 教育訓練（ユーザー定義） | I32: ー | K32: 「職務-設定値」を参照
B33: =ROW() - 5 -> 28 | F33: 説明 | H33: 文字列 | I33: ー | K33: 「職務-設定値」を参照
B34: =ROW() - 5 -> 29 | F34: 重要性 | H34: なし/1-最小/2/3/4/5/6-最大 | I34: なし | K34: 「職務-設定値」を参照
B35: =ROW() - 5 -> 30 | C35: 審査 | F35: 審査タイプ | G35: ジョブの能力要件に追加する審査タイプを選択します。このフィールドの情報は [審査タイプ] ページで管理されます。 | H35: 審査タイプ（ユーザー定義） | I35: ー | K35: 「職務-設定値」を参照
B36: =ROW() - 5 -> 31 | F36: 審査の説明 | H36: 文字列 | I36: ー | K36: 「職務-設定値」を参照
B37: =ROW() - 5 -> 32 | C37: 職務タスク | F37: 職務 | G37: ジョブに割り当てるジョブ タスクを選択します。このフィールドの情報は [ジョブ タスク] ページで管理されます。 | H37: 職務タスク（ユーザー定義） | I37: ー | K37: 「職務-設定値」を参照
B38: =ROW() - 5 -> 33 | F38: 説明 | H38: システム入力 | I38: ー | K38: 「職務-設定値」を参照
B39: =ROW() - 5 -> 34 | F39: 注記 | H39: 文字列 | I39: ー | K39: 「職務-設定値」を参照
B40: =ROW() - 5 -> 35 | C40: 担当領域 | F40: 担当領域 | G40: ジョブの能力要件に追加する担当領域を選択します。このフィールドの情報は、[担当領域] ページで管理されます。 | H40: 担当領域（ユーザー定義） | I40: ー | K40: 「職務-設定値」を参照
B41: =ROW() - 5 -> 36 | F41: 説明 | H41: システム入力 | I41: ー | K41: 「職務-設定値」を参照
B42: =ROW() - 5 -> 37 | F42: 注記 | H42: 文字列 | I42: ー | K42: 「職務-設定値」を参照

Sheet 職務-設定値
A1: 職務-設定値 ※基本的には移行データを正とする
A2: ■凡例「必須：システム上必須」「必須(*)：システムで必須ではないが、トランザクション上や業務などで必須」
A3: パラメータ設定一覧へ
B4: # | C4: 職務
C5: 一般 | H5: 説明 | I5: ジョブ分類 | M5: 報酬 | T5: スキル | X5: 証明書 | AA5: テスト | AC5: 教育 | AF5: 審査 | AH5: 職務タスク | AK5: 担当領域
C6: 職務 | D6: 説明 | E6: タイトル | F6: フルタイム相当 | G6: 職位の最大数 | H6: 説明 | I6: 職務 | J6: ジョブタイプ | K6: ジョブ ファミリ | L6: POSアクセス許可グループ | M6: レベル | N6: 調査会社 | O6: 参照職務 | P6: ソース | Q6: 最小しきい値 | R6: 標準職務給 | S6: 最大しきい値 | T6: スキル | U6: 説明 | V6: レベル | W6: 重要性 | X6: 証明書タイプ | Y6: 説明 | Z6: 重要性 | AA6: テストタイプ | AB6: 説明 | AC6: 教育 | AD6: 説明 | AE6: 重要性 | AF6: 審査タイプ | AG6: 審査の説明 | AH6: 職務 | AI6: 説明 | AJ6: 注記 | AK6: 担当領域 | AL6: 説明 | AM6: 注記
C7: 文字列 | D7: 文字列 | E7: タイトル（ユーザー定義） | F7: 数値 | G7: 最大職位数/無制限 | H7: 文字列 | I7: 職務機能（ユーザー定義） | J7: 職務タイプ（ユーザー定義） | K7: ジョブ ファミリ（ユーザー定義） | L7: POS アクセス許可グループ（ユーザー定義） | M7: レベル（ユーザー定義） | N7: 調査会社（ユーザー定義） | O7: 文字列 | P7: 文字列 | Q7: 数値 | R7: 数値 | S7: 数値 | T7: スキル（ユーザー定義） | U7: 文字列 | V7: 評価モデル（ユーザー定義） | W7: なし/1-最小/2/3/4/5/6-最大 | X7: 証明書タイプ（ユーザー定義） | Y7: 文字列 | Z7: なし/1-最小/2/3/4/5/6-最大 | AA7: テスト タイプ（ユーザー定義） | AB7: 文字列 | AC7: 教育訓練（ユーザー定義） | AD7: 文字列 | AE7: なし/1-最小/2/3/4/5/6-最大 | AF7: 審査タイプ（ユーザー定義） | AG7: 文字列 | AH7: 職務タスク（ユーザー定義） | AI7: システム入力 | AJ7: 文字列 | AK7: 担当領域（ユーザー定義） | AL7: システム入力 | AM7: 文字列
C8: 必須
B9: 例 | C9: 部長
B10: =ROW() - 9 -> 1
B11: =ROW() - 9 -> 2
B12: =ROW() - 9 -> 3
B13: =ROW() - 9 -> 4
B14: =ROW() - 9 -> 5

Sheet 職位
A1: 職位
B2: 人事管理＞職位＞すべての職位
B3: Human resources > Positions > All Positions
A4: パラメータ設定一覧へ
B5: # | C5: タブ | D5: タブ説明 | E5: 項目分類 | F5: 項目 | G5: Description（標準） | H5: 設定可能値 | I5: デフォルト値 | J5: 備考 | K5: 設定値 | L5: 設定基準
B6: =ROW() - 5 -> 1 | C6: 一般 | F6: 職位 | H6: 番号順序の設定に順ずる | I6: 番号順序の設定に順ずる | K6: 「職位-設定値」を参照
B7: =ROW() - 5 -> 2 | F7: 説明 | H7: 文字列 | I7: ー | K7: 「職位-設定値」を参照
B8: =ROW() - 5 -> 3 | F8: 職務 | G8: データベースのレコードの固有 ID | H8: 職務（ユーザー定義） | I8: ー | K8: 「職位-設定値」を参照
B9: =ROW() - 5 -> 4 | F9: 部門 | G9: データベースのレコードの固有 ID | H9: 部門（ユーザー定義） | I9: ー | K9: 「職位-設定値」を参照
B10: =ROW() - 5 -> 5 | F10: タイトル | G10: データベースのレコードの固有 ID | H10: タイトル（ユーザー定義） | I10: ー | J10: 職位を活用したワークフローを作成する際に、分岐の条件や、ワークフロー終了の条件などで使用可能 ※詳細は「D365FO_標準手順書_システム共通(承認ワークフロー)」参照 | K10: 「職位-設定値」を参照
B11: =ROW() - 5 -> 6 | F11: 職位タイプ | G11: データベースのレコードの固有 ID | H11: 職位タイプ（ユーザー定義） | I11: ー | K11: 「職位-設定値」を参照
B12: =ROW() - 5 -> 7 | F12: フルタイム相当 | H12: 数値 | I12: 0.00 | K12: 「職位-設定値」を参照
B13: =ROW() - 5 -> 8 | F13: 報酬地域 | G13: データベースのレコードの固有 ID | H13: 報酬い地域（ユーザー定義） | I13: ー | K13: 「職位-設定値」を参照
B14: =ROW() - 5 -> 9 | F14: 割り当てに使用可能 | G14: このレコードの有効終了時刻です。 | H14: 日付時間 | I14: ー | K14: 「職位-設定値」を参照
B15: =ROW() - 5 -> 10 | F15: ジョブファミリ | G15: データベースのレコードの固有 ID | H15: ジョブファミリ（ユーザー定義） | I15: ー | K15: 「職位-設定値」を参照
B16: =ROW() - 5 -> 11 | C16: 職位の期間 | F16: 有効化 | H16: 日付時間 | I16: 作業日の0時 | K16: 「職位-設定値」を参照
B17: =ROW() - 5 -> 12 | F17: 定年退職 | H17: 日付時間 | I17: なし | K17: 「職位-設定値」を参照
B18: =ROW() - 5 -> 13 | C18: 報告先職位 | F18: 報告先職位 | G18: データベースのレコードの固有 ID | H18: 職位（ユーザー定義） | I18: ー | K18: 「職位-設定値」を参照
B19: =ROW() - 5 -> 14 | F19: 作業者 | G19: データベースのレコードの固有 ID | H19: ー | I19: ー | J19: 報告先職位で設定した職位に紐づいた作業者の名前が自動で入る（手動変更不可） | K19: 「職位-設定値」を参照
B20: =ROW() - 5 -> 15 | F20: 有効日 | G20: このレコードの有効終了時刻です。 | H20: 日付時間 | I20: 作業日の0時 | K20: 「職位-設定値」を参照
B21: =ROW() - 5 -> 16 | F21: 有効期限 | G21: このレコードの有効開始時刻です。 | H21: 日付時間 | I21: 2154/12/31 23:59:59 | K21: 「職位-設定値」を参照
B22: =ROW() - 5 -> 17 | C22: 作業者割り当て | F22: 作業者 | G22: データベースのレコードの固有 ID | H22: 作業者（ユーザー定義） | I22: ー | K22: 「職位-設定値」を参照 ※職位の割り当ては「すべての職位」メニューからも可
B23: =ROW() - 5 -> 18 | F23: 割り当て開始 | H23: 日付時間 | I23: 作業日の0時 | K23: 「職位-設定値」を参照 ※職位の割り当ては「すべての職位」メニューからも可
B24: =ROW() - 5 -> 19 | F24: 割り当て終了 | H24: 日付時間 | I24: なし | K24: 「職位-設定値」を参照 ※職位の割り当ては「すべての職位」メニューからも可
B25: =ROW() - 5 -> 20 | F25: 理由コード | G25: データベースのレコードの固有 ID | H25: 理由コード（ユーザー定義） | I25: ー | K25: 「職位-設定値」を参照 ※職位の割り当ては「すべての職位」メニューからも可
B26: =ROW() - 5 -> 21 | F26: 主要職位にする | H26: はい/いいえ | I26: いいえ | K26: 「職位-設定値」を参照 ※職位の割り当ては「すべての職位」メニューからも可
B27: =ROW() - 5 -> 22 | C27: 給与 | F27: 支払サイクル | G27: データベースのレコードの固有 ID | H27: 支払サイクルと支払期間（ユーザー定義） | I27: ー | K27: 「職位-設定値」を参照
B28: =ROW() - 5 -> 23 | F28: 作業サイクル | G28: データベースのレコードの固有 ID | H28: 作業サイクルと作業期間（ユーザー定義） | I28: ー | K28: 「職位-設定値」を参照
B29: =ROW() - 5 -> 24 | F29: 支払者 | G29: データベースのレコードの固有 ID | H29: 法人（ユーザー定義） | I29: ー | K29: 「職位-設定値」を参照
B30: =ROW() - 5 -> 25 | F30: 組織責任者 | H30: はい/いいえ | I30: いいえ | K30: 「職位-設定値」を参照
B31: =ROW() - 5 -> 26 | F31: 年間基本勤務時間 | H31: 数値 | I31: 0.00 | K31: 「職位-設定値」を参照
B32: =ROW() - 5 -> 27 | F32: 支払期間の残業時間数 | H32: 数値 | I32: 0.00 | K32: 「職位-設定値」を参照
B33: =ROW() - 5 -> 28 | F33: 給与の生成 | H33: はい/いいえ | I33: いいえ | K33: 「職位-設定値」を参照
B34: =ROW() - 5 -> 29 | F34: スケジュールからの所得の生成 | H34: はい/いいえ | I34: いいえ | K34: 「職位-設定値」を参照
B35: =ROW() - 5 -> 30 | F35: スケジュール | H35: ー | I35: ー | K35: 「職位-設定値」を参照
B36: =ROW() - 5 -> 31 | F36: 一般賠償責任保険 | G36: データベースのレコードの固有 ID | H36: 福利厚生（ユーザー定義） | I36: ー | K36: 「職位-設定値」を参照
B37: =ROW() - 5 -> 32 | F37: 既定の所得コード | G37: データベースのレコードの固有 ID | H37: 所得コード（ユーザー定義） | I37: ー | K37: 「職位-設定値」を参照
B38: =ROW() - 5 -> 33 | C38: 関係 | F38: 階層名 | G38: データベースのレコードの固有 ID | H38: 職位階層タイプ（ユーザー定義） | I38: ー | J38: 職位を活用したワークフローを作成する際に、報告先の職位として上長の設定などが可能 ※詳細は「D365FO_標準手順書_システム共通(承認ワークフロー)」参照 | K38: 「職位-設定値」を参照
B39: =ROW() - 5 -> 34 | F39: 報告先職位 | G39: データベースのレコードの固有 ID | H39: 職位（ユーザー定義） | I39: ー | K39: 「職位-設定値」を参照
B40: =ROW() - 5 -> 35 | F40: 作業者 | G40: データベースのレコードの固有 ID | H40: ー | I40: ー | J40: 報告先職位で設定した職位に紐づいた作業者の名前が自動で入る（手動変更不可） | K40: 「職位-設定値」を参照
B41: =ROW() - 5 -> 36 | C41: 作業者の報酬 | F41: 報酬の状態 | H41: 住所の設定の都道府県（ユーザー定義） | I41: ー | K41: 「職位-設定値」を参照
B42: =ROW() - 5 -> 37 | F42: 報酬コード | G42: データベースのレコードの固有 ID | H42: 福利厚生（ユーザー定義） | I42: ー | K42: 「職位-設定値」を参照
B43: =ROW() - 5 -> 38 | C43: 労働組合 | F43: 必要な労働組合協定 | H43: はい/いいえ | I43: いいえ | K43: 「職位-設定値」を参照
B44: =ROW() - 5 -> 39 | F44: 労働組合協定 | G44: データベースのレコードの固有 ID | H44: 労働組合（ユーザー定義） | I44: ー | J44: 「必要な労働組合協定」を「はい」にした場合に入力可能 | K44: 「職位-設定値」を参照
B45: =ROW() - 5 -> 40 | F45: 労働組合 | H45: ー | I45: ー | J45: 「労働組合協定」で選択した労働組合の名前が自動で入る | K45: 「職位-設定値」を参照
B46: =ROW() - 5 -> 41 | F46: 契約の説明 | K46: 「職位-設定値」を参照
B47: =ROW() - 5 -> 42 | F47: 法人 | G47: 選択可能な会社のID | I47: ー | J47: 「労働組合協定」で選択した労働組合の法人が自動で入る | K47: 「職位-設定値」を参照
B48: =ROW() - 5 -> 43 | C48: 財務分析コード | E48: 財務分析コード | F48: 法人 | G48: データベースのレコードの固有 ID | H48: 法人（ユーザー定義） | I48: ー | K48: 「職位-設定値」を参照
B49: =ROW() - 5 -> 44 | F49: 名前 | H49: ー | I49: ー | J49: 「法人」で選択した法人名が自動的に入力される（手動変更不可） | K49: 「職位-設定値」を参照
B50: =ROW() - 5 -> 45 | F50: 配布テンプレート | G50: データベースのレコードの固有 ID | H50: 財務分析コード用の既定テンプレート（ユーザー定義） | I50: ー | K50: 「職位-設定値」を参照
B51: =ROW() - 5 -> 46 | F51: 既定の分析コード | G51: ※使用する財務分析コードがすべて出てくる | H51: ー | I51: ー | J51: 職位に対して既定の財務分析コードを設定する。 | K51: 「職位-設定値」を参照
B52: =ROW() - 5 -> 47 | E52: 予算の既定値 | F52: 予算原価要素 | G52: データベースのレコードの固有 ID | H52: 予算原価要素（ユーザー定義） | I52: ー | J52: 予算原価要素が自組織に対して有効になっていないと選択できない | K52: 「職位-設定値」を参照
B53: =ROW() - 5 -> 48 | F53: 説明 | H53: ー | I53: ー | J53: 「予算原価要素」で選択した予算原価要素の説明が自動で入力される | K53: 「職位-設定値」を参照
B54: =ROW() - 5 -> 49 | F54: 予算原価タイプ | H54: ー | I54: ー | J54: 「予算原価要素」で選択した予算原価要素の予算原価タイプが自動で入力される | K54: 「職位-設定値」を参照

Sheet 職位-設定値
A1: 職位-設定値 ※基本的には移行データを正とする（１職位に対して１従業員が割り当てられる形になるため、従業員分の登録が必要となる）
A2: ■凡例「必須：システム上必須」「必須(*)：システムで必須ではないが、トランザクション上や業務などで必須」
A3: パラメータ設定一覧へ
B4: # | C4: 一般 | M4: 職位の期間 | O4: 報告先職位 | S4: 作業者割り当て | X4: 給与 | AI4: 関係 | AL4: 作業者の報酬 | AN4: 労働組合 | AS4: 財務分析コード
AS5: 財務分析コード | AV5: 既定の財務分析コード ※使用する財務分析コード分列追加 | AY5: 予算の既定値
C6: 職位 | D6: 説明 | E6: 職務 | F6: 部門 | G6: タイトル | H6: 職位タイプ | I6: フルタイム相当 | J6: 報酬地域 | K6: 割り当てに使用可能 | L6: ジョブファミリ | M6: 有効化 | N6: 定年退職 | O6: 報告先職位 | P6: 作業者 | Q6: 有効日 | R6: 有効期限 | S6: 作業者 | T6: 割り当て開始 | U6: 割り当て終了 | V6: 理由コード | W6: 主要職位にする | X6: 支払サイクル | Y6: 作業サイクル | Z6: 支払者 | AA6: 組織責任者 | AB6: 年間基本勤務時間 | AC6: 支払期間の残業時間数 | AD6: 給与の生成 | AE6: スケジュールからの所得の生成 | AF6: スケジュール | AG6: 一般賠償責任保険 | AH6: 既定の所得コード | AI6: 階層名 | AJ6: 報告先職位 | AK6: 作業者 | AL6: 報酬の状態 | AM6: 報酬コード | AN6: 必要な労働組合協定 | AO6: 労働組合協定 | AP6: 労働組合 | AQ6: 契約の説明 | AR6: 法人 | AS6: 法人 | AT6: 名前 | AU6: 配布テンプレート | AV6: XXXXXX | AW6: XXXXXX | AX6: XXXXXX | AY6: 予算原価要素 | AZ6: 説明 | BA6: 予算原価タイプ
C7: 番号順序の設定に順ずる （番号順序の設定に準拠するため、手動入力、自動採番どちらも可能） | D7: 文字列 | E7: 職務（ユーザー定義） | F7: 部門（ユーザー定義） | G7: タイトル（ユーザー定義） | H7: 職位タイプ（ユーザー定義） | I7: 数値 | J7: 報酬い地域（ユーザー定義） | K7: 日付時間 | L7: ジョブファミリ（ユーザー定義） | M7: 日付時間 | N7: 日付時間 | O7: 職位（ユーザー定義） | P7: ー | Q7: 日付時間 | R7: 日付時間 | S7: 作業者（ユーザー定義） | T7: 日付時間 | U7: 日付時間 | V7: 理由コード（ユーザー定義） | W7: はい/いいえ | X7: 支払サイクルと支払期間（ユーザー定義） | Y7: 作業サイクルと作業期間（ユーザー定義） | Z7: 法人（ユーザー定義） | AA7: はい/いいえ | AB7: 数値 | AC7: 数値 | AD7: はい/いいえ | AE7: はい/いいえ | AF7: ー | AG7: 福利厚生（ユーザー定義） | AH7: 所得コード（ユーザー定義） | AI7: 職位階層タイプ（ユーザー定義） | AJ7: 職位（ユーザー定義） | AK7: ー | AL7: 住所の設定の都道府県（ユーザー定義） | AM7: 福利厚生（ユーザー定義） | AN7: はい/いいえ | AO7: 労働組合（ユーザー定義） | AP7: ー | AS7: 法人（ユーザー定義） | AT7: ー | AU7: 財務分析コード用の既定テンプレート（ユーザー定義） | AV7: ー | AW7: ー | AX7: ー | AY7: 予算原価要素（ユーザー定義） | AZ7: ー | BA7: ー
C8: 必須 | E8: 必須 | F8: 必須(*) | M8: 必須
B9: 例 | C9: Work-001 | E9: 部長 | F9: Dynamics部 | M9: 45017
B10: =ROW() - 9 -> 1
B11: =ROW() - 9 -> 2
B12: =ROW() - 9 -> 3
B13: =ROW() - 9 -> 4
B14: =ROW() - 9 -> 5
B15: =ROW() - 9 -> 6
B16: =ROW() - 9 -> 7
B17: =ROW() - 9 -> 8
B18: =ROW() - 9 -> 9
B19: =ROW() - 9 -> 10
B20: =ROW() - 9 -> 11
B21: =ROW() - 9 -> 12
... B29: =ROW() - 9 -> 20

Sheet リソースグループ
A1: リソースグループ
B2: 生産管理 ＞設定＞リソース＞リソースグループ
B3: Production control > Setup > Resources > Resource groups
A4: パラメータ設定一覧へ
B5: # | C5: タブ | D5: タブ説明 | E5: 項目分類 | F5: 項目 | G5: Description（標準） | H5: 設定可能値 | I5: デフォルト値 | J5: 備考 | K5: 設定値 | L5: 設定基準
B6: =ROW() - 5 -> 1 | C6: リソースグループ | D6: リソースグループ | E6: ー | F6: リソースグループ | G6: ー | H6: 文字列 | I6: ー | J6: ー | K6: 「リソースグループ-設定値」を参照
B7: =ROW() - 5 -> 2 | E7: ー | F7: 説明 | G7: ー | H7: 文字列 | I7: ー | J7: ー | K7: 「リソースグループ-設定値」を参照
B8: =ROW() - 5 -> 3 | E8: ー | F8: サイト | G8: ー | H8: サイト（ユーザー定義） | I8: ー | J8: ー | K8: 「リソースグループ-設定値」を参照
B9: =ROW() - 5 -> 4 | C9: 一般 | D9: 一般 | E9: ID | F9: 生産単位 | G9: ー | H9: 生産単位（ユーザー定義） | I9: ー | J9: ー | K9: 「リソースグループ-設定値」を参照
B10: =ROW() - 5 -> 5 | F10: 作業セル | G10: ー | H10: はい/いいえ | I10: いいえ | J10: ー | K10: 「リソースグループ-設定値」を参照
B11: =ROW() - 5 -> 6 | E11: 場所 | F11: 入庫倉庫 | G11: ー | H11: 倉庫（ユーザー定義） | I11: ー | J11: ー | K11: 「リソースグループ-設定値」を参照
B12: =ROW() - 5 -> 7 | F12: 入庫場所 | G12: ー | H12: 場所（ユーザー定義） | I12: ー | J12: ー | K12: 「リソースグループ-設定値」を参照
B13: =ROW() - 5 -> 8 | F13: 出荷倉庫 | G13: ー | H13: 倉庫（ユーザー定義） | I13: ー | K13: 「リソースグループ-設定値」を参照
B14: =ROW() - 5 -> 9 | F14: 出荷場所 | G14: ー | H14: 場所（ユーザー定義） | I14: ー | J14: ー | K14: 「リソースグループ-設定値」を参照
B15: =ROW() - 5 -> 10 | C15: 工程 | D15: 工程 | E15: 工順 | F15: 仕損率 | G15: ー | H15: 数値 | I15: 0.00 | J15: ー | K15: 「リソースグループ-設定値」を参照
B16: =ROW() - 5 -> 11 | E16: 原価カテゴリ | F16: 段取りカテゴリ | G16: ー | H16: 原価カテゴリ（ユーザー定義） | I16: ー | J16: ー | K16: 「リソースグループ-設定値」を参照
B17: =ROW() - 5 -> 12 | F17: 実行時間カテゴリ | G17: ー | H17: 原価カテゴリ（ユーザー定義） | I17: ー | J17: ー | K17: 「リソースグループ-設定値」を参照
B18: =ROW() - 5 -> 13 | F18: 数量カテゴリ | G18: ー | H18: 原価カテゴリ（ユーザー定義） | I18: ー | J18: ー | K18: 「リソースグループ-設定値」を参照
B19: =ROW() - 5 -> 14 | E19: スケジューリング | F19: 工程のスケジューリング率 | G19: ー | H19: 数値 | I19: 100.00 | J19: ー | K19: 「リソースグループ-設定値」を参照
B20: =ROW() - 5 -> 15 | F20: 有限能力 | G20: ー | H20: はい/いいえ | I20: いいえ | K20: 「リソースグループ-設定値」を参照
B21: =ROW() - 5 -> 16 | F21: ボトルネック リソース | G21: ー | H21: はい/いいえ | I21: いいえ | K21: 「リソースグループ-設定値」を参照
B22: =ROW() - 5 -> 17 | F22: 順序グループ ID | G22: ー | H22: 順序グループ（ユーザー定義） | I22: ー | K22: 「リソースグループ-設定値」を参照
B23: =ROW() - 5 -> 18 | E23: 生産能力 | F23: 能力単位 | G23: ー | H23: ストローク/時間 m/時 キログラム/時間 日/時間 | I23: ー | K23: 「リソースグループ-設定値」を参照
B24: =ROW() - 5 -> 19 | F24: 生産能力 | G24: ー | H24: 数値 | I24: 0.00 | K24: 「リソースグループ-設定値」を参照
B25: =ROW() - 5 -> 20 | F25: バッチ生産能力 | G25: ー | H25: 数値 | I25: 0.00 | K25: 「リソースグループ-設定値」を参照
B26: =ROW() - 5 -> 21 | C26: カレンダー | D26: カレンダー | F26: カレンダー | G26: ー | H26: 作業時間カレンダー（ユーザー定義） | I26: ー | J26: ー | K26: 「リソースグループ-カレンダー-設定値」を参照
B27: =ROW() - 5 -> 22 | F27: 有効期限 | G27: ー | H27: 日付 | I27: なし | J27: ー | K27: 「リソースグループ-カレンダー-設定値」を参照
B28: =ROW() - 5 -> 23 | C28: リソース | D28: リソース | E28: リソース | F28: リソース | G28: ー | H28: リソース（ユーザー定義） | I28: ー | J28: ー | K28: 「リソースグループ-リソース-設定値」を参照
B29: =ROW() - 5 -> 24 | F29: 説明 | G29: ー | H29: 文字列 | I29: ー | J29: ー | K29: 「リソースグループ-リソース-設定値」を参照
B30: =ROW() - 5 -> 25 | F30: 有効期限 | G30: ー | H30: 日付 | I30: ー | J30: ー | K30: 「リソースグループ-リソース-設定値」を参照
B31: =ROW() - 5 -> 26 | F31: 入庫倉庫 | G31: ー | H31: 倉庫（ユーザー定義） | I31: ー | K31: 「リソースグループ-リソース-設定値」を参照
B32: =ROW() - 5 -> 27 | F32: 入庫場所 | G32: ー | H32: 場所（ユーザー定義） | I32: ー | K32: 「リソースグループ-リソース-設定値」を参照
