Workbook

Sheet 表紙
B3: サンスター株式会社 御中
B10: 会計システム刷新プロジェクト（LIBRA）
B14: ToBe業務フロー（7.Branch2）
B22: ="第"&IF(COUNTA(変更履歴!BE5:BH10000)=1,"",INDIRECT("変更履歴!BE"&COUNTA(変更履歴!BE5:BH10000)+4))&"版" -> 第1.1版
B24: {=IF(OR(COUNTA(変更履歴!A:E)=3),"",INDIRECT("変更履歴!A"&COUNTA(変更履歴!A:E)+2))} -> 45846
B26: 日本ビジネスシステムズ株式会社
F29: 作成者 | O29: JBS承認者 | V29: 承認者
F30: 45650 | N30: 45650
F31: =[2]変更履歴!BA2 -> JBS北井 | N31: JBS入井

Sheet 変更履歴
A1: システム名 | F1: =表紙!B10 -> 会計システム刷新プロジェクト（LIBRA） | W1: タイトル | AR1: 日付 | BA1: 更新者
A2: 文書名 | F2: =表紙!B14 -> ToBe業務フロー（7.Branch2） | W2: =MID(CELL("filename",$A$1),FIND("]",CELL("filename",$A$1))+1,31) -> 変更履歴 | AR2: 作成 | AT2: =A6 -> 45650 | BA2: =AZ6 -> JBS北井
AR3: 更新 | AT3: {=IF(OR(COUNTA(A:E)=3),"",INDIRECT("A"&COUNTA(A:E)+2))} -> 45846 | BA3: {=IF(COUNTA(AZ5:BD100000)=1,"",INDIRECT("変更履歴!AZ"&COUNTA(AZ5:BD100000)+4))} -> JBS加藤
A5: 変更年月日 | F5: 変更箇所 | T5: 変更内容 | AZ5: 変更者 | BE5: 版数
A6: 45650 | F6: 新規作成 | T6: 新規作成 | AZ6: JBS北井 | BE6: 1.0
A7: 45846 | F7: シート：1.利益センタ・原価センタマスタ登録 | T7: １．利益センタマスタ登録 ・作業単位の登録に機能領域・事業領域も含めて記載されていたため、別プロセスに変更 ・機能名修正 ※FOメニューの機能名がわかるように修正 | AZ7: JBS加藤 | BE7: 1.1

Sheet 凡例
A1: システム名 | F1: =変更履歴!F1 -> 会計システム刷新プロジェクト（LIBRA） | V1: タイトル | AJ1: 日付 | AQ1: 更新者
A2: 文書名 | F2: =変更履歴!F2 -> ToBe業務フロー（7.Branch2） | V2: =MID(CELL("filename",$A$1),FIND("]",CELL("filename",$A$1))+1,31) -> 凡例 | AJ2: 作成 | AL2: =変更履歴!AT2 -> 45650 | AQ2: =変更履歴!BA2 -> JBS北井
AJ3: 更新 | AL3: =変更履歴!AT3 -> 45846 | AQ3: =変更履歴!BA3 -> JBS加藤
A6: 凡例
H10: ： | I10: フローの開始 | AC10: ： | AD10: フローの終了
H15: ： | I15: システムを伴わない業務 | AC15: ： | AD15: システム上での業務
H20: ： | I20: 帳票（システムで作成される帳票） | AC20: ： | AD20: 帳票（システム外で作成される帳票）
H25: ： | I25: 業務の流れ | AC25: ： | AD25: システムへの連携
H30: ： | I30: 分岐 | AC30: ： | AD30: システム
H35: ： | I35: フロー間の繋がりを示す | AC35: ： | AD35: ファイル（CSVファイル等）
A40: 凡例
B43: 社内部署 | J43: ： | K43: フローに登場する社内の部署を記載
K44: 部署内の担当者が分かれる場合は以下の通りに分ける
B46: 社内部署
B47: 担当者 | I47: 責任者
B50: 外部担当者 | J50: ： | K50: フローに登場する社外担当者の部署を記載
K51: 例）得意先、仕入先
B54: システム | J54: ： | K54: フロー上で実施されるシステムの機能を記載する列
B55: XX | K55: XXの部分にフローで登場するシステム名を記載
K56: 例は以下の通り（JBSで導入するシステム外のものは「外部システム」で統一）
B58: システム
B59: FO | I59: CE | P59: 外部システム
B62: 説明 | S62: ： | T62: フロー内容を説明する列
B66: Gap （Add-On） | J66: ： | K66: フローに対してのGapを記載する列
B70: １．パターン１ | AI70: ： | AJ70: フローのパターンごとに記載する

Sheet 1.利益センタ・原価センタマスタ登録
A1: システム名 | F1: =変更履歴!F1 -> 会計システム刷新プロジェクト（LIBRA） | V1: タイトル | AJ1: 日付 | AQ1: 更新者
A2: 文書名 | F2: =変更履歴!F2 -> ToBe業務フロー（7.Branch2） | V2: =MID(CELL("filename",$A$1),FIND("]",CELL("filename",$A$1))+1,31) -> 1.利益センタ・原価センタマスタ登録 | AJ2: 作成 | AL2: =変更履歴!AT2 -> 45650 | AQ2: =変更履歴!BA2 -> JBS北井
AJ3: 更新 | AL3: =変更履歴!AT3 -> 45846 | AQ3: =変更履歴!BA3 -> JBS加藤
A6: =RIGHT(CELL("filename",A1),LEN(CELL("filename",A1))-FIND("]",CELL("filename",A1))) -> 1.利益センタ・原価センタマスタ登録
B8: 得意先 | I8: ITDX | P8: システム | AD8: 説明 | AT8: Gap （Add-On） | BB8: サンスター 担当部署・ 担当者 | BF8: サンスターコメント (現状との違い、補足、その他気になること)
P9: FO | W9: 外部システム
B10: １．利益センタマスタ登録
AE18: １．利益センタマスタの登録
AF19: MDMにて利益センタマスタを登録する。
AE27: ２．利益センタの登録
AF28: MDMで登録した利益センタを作業単位に登録する。
AE33: ３．機能領域・事業領域の登録
AF34: MDMで登録した機能領域・事業領域を登録する。
AF35: ※新規登録がなければスキップ
AE39: 4．使用法人の設定
AF40: 登録した各種分析値について、利用する法人・しない法人
AF41: を設定する。（法人の上書きへの設定）
AF42: ＜分析軸＞
AG43: ・利益センタ
AG44: ・機能領域
AG45: ・事業領域
AE47: 5．関連分析コードの設定
AF48: 利益センタについて、関連する機能領域・事業領域を
AF49: 設定する。
B56: ２．原価センタマスタ登録
AE58: ※ | AF58: 本フローは、MDMからの取込について記載している
AF59: 利益センタは取込開始前に、手動にてFOに登録しておく
AE62: １．原価センタマスタの登録
AF63: MDMにて原価センタマスタを登録する。
AE73: ２．原価センタマスタの取込 | AT73: Gap
AF74: 外部システムより、原価センタマスタを取り込む。 | AT74: 取込機能が必要（IF）
AG75: MDMから連携

Sheet 2.品目マスタ取込
A1: システム名 | F1: =変更履歴!F1 -> 会計システム刷新プロジェクト（LIBRA） | V1: タイトル | AJ1: 日付 | AQ1: 更新者
A2: 文書名 | F2: =変更履歴!F2 -> ToBe業務フロー（7.Branch2） | V2: =MID(CELL("filename",$A$1),FIND("]",CELL("filename",$A$1))+1,31) -> 2.品目マスタ取込 | AJ2: 作成 | AL2: =変更履歴!AT2 -> 45650 | AQ2: =変更履歴!BA2 -> JBS北井
AJ3: 更新 | AL3: =変更履歴!AT3 -> 45846 | AQ3: =変更履歴!BA3 -> JBS加藤
A6: =RIGHT(CELL("filename",A1),LEN(CELL("filename",A1))-FIND("]",CELL("filename",A1))) -> 2.品目マスタ取込
B8: 得意先 | I8: ITDX | P8: システム | AD8: 説明 | AT8: Gap （Add-On） | BB8: サンスター 担当部署・ 担当者 | BF8: サンスターコメント (現状との違い、補足、その他気になること)
P9: FO | W9: 外部システム
B10: １．品目マスタ登録
AE16: １．品目マスタの登録
AF17: MDMにて品目マスタを登録する。
I22: 無 | AE22: 単位マスタ登録有無
AF23: FOの単位マスタにMDMで登録されている単位の
AF24: 登録有無を確認する。
K25: 有
AE27: ２．単位マスタの登録
AF28: FOにて単位マスタを登録する。
B36: ２．品目マスタ取込
AE38: ※ | AF38: 本フローは、MDMからの取込について記載している
AF39: 単位マスタは取込開始前に、手動にてFOに登録しておく
AE53: １．品目マスタの取込 | AT53: Gap
AF54: 外部システムより、品目マスタを取り込む | AT54: 取込機能が必要（IF）
AG55: MDMから連携

Sheet 3.販売実績データ連携
A1: システム名 | F1: =変更履歴!F1 -> 会計システム刷新プロジェクト（LIBRA） | V1: タイトル | AJ1: 日付 | AQ1: 更新者
A2: 文書名 | F2: =変更履歴!F2 -> ToBe業務フロー（7.Branch2） | V2: =MID(CELL("filename",$A$1),FIND("]",CELL("filename",$A$1))+1,31) -> 3.販売実績データ連携 | AJ2: 作成 | AL2: =変更履歴!AT2 -> 45650 | AQ2: =変更履歴!BA2 -> JBS北井
AJ3: 更新 | AL3: =変更履歴!AT3 -> 45846 | AQ3: =変更履歴!BA3 -> JBS加藤
A6: =RIGHT(CELL("filename",A1),LEN(CELL("filename",A1))-FIND("]",CELL("filename",A1))) -> 3.販売実績データ連携
B8: 得意先 | I8: ITDX | P8: システム | AD8: 説明 | AT8: Gap （Add-On） | BB8: サンスター 担当部署・ 担当者 | BF8: サンスターコメント (現状との違い、補足、その他気になること)
P9: FO | W9: 外部システム
B10: １．販売実績データ取込
AE12: ※ | AF12: 本フローは、mcframe、SEJホストで
AF13: 売上計上されたデータをFOに取込する
AE17: １．売上対象伝票の確認
AE22: ２．売上の計上
AE32: ３．販売実績データの取込 | AT32: Gap
AT33: 取込機能が必要（IF）
AF34: 外部システムより、売上実績データを取り込む
AG35: SSJ：mcframeから連携
AG36: SEJ：SEJホスト（AS400）から連携
B43: ２．販売実績データ連携
AE45: ※ | AF45: 本フローは、FOで登録された売上実績データを
AF46: i-PLATSへ連携する。
AE50: １．販売実績連携 | AT50: Gap
AT51: 取込機能が必要（IF）
AF52: 売上実績データを外部システムへ連携する
AG53: i-PLATS：FOから連携
