Workbook

Sheet 表紙
B3: サンスター株式会社 御中
B10: 会計システム刷新プロジェクト（LIBRA）
B14: ToBe業務フロー（2.グループファイナンス・資金繰り）
B22: ="第"&IF(COUNTA(変更履歴!BE5:BH9999)=1,"",INDIRECT("変更履歴!BE"&COUNTA(変更履歴!BE5:BH9999)+4))&"版" -> 第1.4版
B24: {=IF(OR(COUNTA(変更履歴!A:E)=3),"",INDIRECT("変更履歴!A"&COUNTA(変更履歴!A:E)+2))} -> 45763
B26: 日本ビジネスシステムズ株式会社
F29: 作成者 | O29: JBS承認者 | V29: 承認者
F30: 45362 | N30: 45433
F31: JBS福田 | N31: JBS加藤

Sheet 変更履歴
A1: システム名 | F1: =表紙!B10 -> 会計システム刷新プロジェクト（LIBRA） | W1: タイトル | AR1: 日付 | BA1: 更新者
A2: 文書名 | F2: =表紙!B14 -> ToBe業務フロー（2.グループファイナンス・資金繰り） | W2: =MID(CELL("filename",$A$1),FIND("]",CELL("filename",$A$1))+1,31) -> #VALUE! | AR2: 作成 | AT2: =A6 -> 45362 | BA2: =AZ6 -> JBS福田
AR3: 更新 | AT3: {=IF(OR(COUNTA(A:E)=3),"",INDIRECT("A"&COUNTA(A:E)+2))} -> 45763 | BA3: {=IF(COUNTA(AZ5:BD99999)=1,"",INDIRECT("変更履歴!AZ"&COUNTA(AZ5:BD99999)+4))} -> JBS福田
A5: 変更年月日 | F5: 変更箇所 | T5: 変更内容 | AZ5: 変更者 | BE5: 版数
A6: 45362 | F6: 新規作成 | T6: 新規作成 | AZ6: JBS福田 | BE6: 0.1
A7: 45433 | F7: 初版確定 | T7: 初版確定 | AZ7: JBS福田 | BE7: 1.0
A8: 45586 | F8: グループファイナンス(内部借入・貸付) | T8: 2．内部貸付 ＞ 3．利息仕訳計上 のプロセスに 一般仕訳帳or自由書式の請求と記載していたのを、一般仕訳帳に変更 | AZ8: JBS福田 | BE8: 1.1
A9: 45740 | F9: シート：資金予測 シート：月次グループ管理(借入預金) シート：四半期グループ管理(借入貸付) | T9: FOのスコープ外となった注記を追加 | AZ9: JBS福田 | BE9: 1.2
A10: 45740 | F10: シート：日次振伝処理(資金G) | T10: シート「日次振伝処理(資金G)」を新規追加 | AZ10: JBS福田 | BE10: 1.2
A11: 45740 | F11: シート：現預金 シート：調達・運用・通貨交換 シート：グループファイナンス(内部借入・貸付) | T11: 一般仕訳帳のWF送信/承認/自動転記バッチのプロセスについては、「日次振伝処理(資金G)」を参照する旨の注記を追加 | AZ11: JBS福田 | BE11: 1.2
A12: 45748 | F12: シート：現預金 | T12: 「2．預金管理 の標題を「2．預金管理」→「2．引落手数料と決済利息の計上」に変更 「５．残高確認」のプロセスを削除 | AZ12: JBS福田 | BE12: 1.3
A13: 45763 | F13: シート：現預金 | T13: 「4．預金決算利息仕訳計上」のコメントを修正 修正前：預金決算利息情報CSVをEXCELアドイン形式に編集して一般仕訳帳に登録する 修正後：預金決算利息情報CSVを一般仕訳帳アップロードEXCELレイアウトに編集して一般仕訳帳に登録する | AZ13: JBS福田 | BE13: 1.4

Sheet 凡例
A1: システム名 | F1: =変更履歴!F1 -> 会計システム刷新プロジェクト（LIBRA） | V1: タイトル | AJ1: 日付 | AQ1: 更新者
A2: 文書名 | F2: =変更履歴!F2 -> ToBe業務フロー（2.グループファイナンス・資金繰り） | V2: =MID(CELL("filename",$A$1),FIND("]",CELL("filename",$A$1))+1,31) -> #VALUE! | AJ2: 作成 | AL2: =変更履歴!AT2 -> 45362 | AQ2: =変更履歴!BA2 -> JBS福田
AJ3: 更新 | AL3: =変更履歴!AT3 -> 45763 | AQ3: =変更履歴!BA3 -> JBS福田
A6: 凡例
H10: ： | I10: フローの開始 | AC10: ： | AD10: フローの終了
H15: ： | I15: システムを伴わない業務 | AC15: ： | AD15: システム上での業務
H20: ： | I20: 帳票（システムで作成される帳票） | AC20: ： | AD20: 帳票（システム外で作成される帳票）
H25: ： | I25: 業務の流れ | AC25: ： | AD25: システムへの連携
H30: ： | I30: 分岐 | AC30: ： | AD30: システム
H35: ： | I35: フロー間の繋がりを示す | AC35: ： | AD35: ファイル（CSVファイル等）
A40: 凡例
B43: 社内部署 | J43: ： | K43: フローに登場する社内の部署を記載
K44: 部署内の担当者が分かれる場合は以下の通りに分ける
B46: 社内部署
B47: 担当者 | I47: 責任者
B50: 外部担当者 | J50: ： | K50: フローに登場する社外担当者の部署を記載
K51: 例）得意先、仕入先
B54: システム | J54: ： | K54: フロー上で実施されるシステムの機能を記載する列
B55: XX | K55: XXの部分にフローで登場するシステム名を記載
K56: 例は以下の通り（JBSで導入するシステム外のものは「外部システム」で統一）
B58: システム
B59: FO | I59: CE | P59: 外部システム
B62: 説明 | S62: ： | T62: フロー内容を説明する列
B66: Gap （Add-On） | J66: ： | K66: フローに対してのGapを記載する列
B70: １．パターン１ | AI70: ： | AJ70: フローのパターンごとに記載する

Sheet 日次振伝処理(資金G)
A1: システム名 | F1: =変更履歴!F1 -> 会計システム刷新プロジェクト（LIBRA） | V1: タイトル | AJ1: 日付 | AQ1: 更新者
A2: 文書名 | F2: =変更履歴!F2 -> ToBe業務フロー（2.グループファイナンス・資金繰り） | V2: =MID(CELL("filename",$A$1),FIND("]",CELL("filename",$A$1))+1,31) -> #VALUE! | AJ2: 作成 | AL2: =変更履歴!AT2 -> 45362 | AQ2: =変更履歴!BA2 -> JBS福田
AJ3: 更新 | AL3: =変更履歴!AT3 -> 45763 | AQ3: =変更履歴!BA3 -> JBS福田
A6: =RIGHT(CELL("filename",A1),LEN(CELL("filename",A1))-FIND("]",CELL("filename",A1))) -> #VALUE!
B8: 財務部 資金G | P8: ITDX | W8: システム | AD8: 説明 | AT8: Gap （Add-On） | BA8: サンスター 担当部署・ 担当者 | BE8: サンスターコメント (現状との違い、補足、その他気になること)
B9: 担当者 | I9: 責任者 | P9: 担当者 | W9: FO
B10: １．振伝処理
AE17: 1．伝票入力
AF18: 担当者は、一般仕訳帳に伝票の登録を行う。
AE23: 2．WF送信
AF24: 担当者は、登録した仕訳帳をWF送信を行う。
AE31: 3．承認
AF32: 責任者は、申請された伝票の内容を確認し、 | AT32: アドオン機能
AF33: 承認を行う。 | AT33: Req017
AT34: FO-031：仕訳帳承認対象一覧
AE39: 4．自動転記バッチ | AT39: アドオン機能
AF40: スケジュールされたバッチ処理により | AT40: Req377
AF41: 承認済仕訳帳が自動転記処理される | AT41: FO-034：自動転記バッチ
AE48: 5．残高確認・仕訳伝票照会
AF49: 転記後の残高を確認する
AF50: 転記された伝票トランザクションを確認する

Sheet 現預金
A1: システム名 | F1: =変更履歴!F1 -> 会計システム刷新プロジェクト（LIBRA） | V1: タイトル | AJ1: 日付 | AQ1: 更新者
A2: 文書名 | F2: =変更履歴!F2 -> ToBe業務フロー（2.グループファイナンス・資金繰り） | V2: =MID(CELL("filename",$A$1),FIND("]",CELL("filename",$A$1))+1,31) -> #VALUE! | AJ2: 作成 | AL2: =変更履歴!AT2 -> 45362 | AQ2: =変更履歴!BA2 -> JBS福田
AJ3: 更新 | AL3: =変更履歴!AT3 -> 45763 | AQ3: =変更履歴!BA3 -> JBS福田
A6: =RIGHT(CELL("filename",A1),LEN(CELL("filename",A1))-FIND("]",CELL("filename",A1))) -> #VALUE!
B8: カスタマーサービス | I8: 各部署 | W8: 業務部 事務管理G | AK8: 財務部 資金G | AY8: システム | BM8: 説明 | CC8: Gap （Add-On） | CJ8: サンスター 担当部署・ 担当者 | CN8: サンスターコメント (現状との違い、補足、その他気になること)
B9: 担当者 | I9: 担当者 | P9: 責任者 | W9: 担当者 | AD9: 責任者 | AK9: 担当者 | AR9: 責任者 | AY9: FO | BF9: 外部システム
B10: １．現金管理
BN23: 1．現金集計表作成
BO24: 楽楽精算から現金入金・出金の伝票を出力し集計する
BN30: 2．現金出納帳作成
BO31: 分析コード明細書で現金科目を指定して
BO32: 出力する
B40: 2．引落手数料と決済利息の計上 | CJ40: 事務管理 | CN40: 手数料、利息の計上のみのフローになっているため、標題と異なっております
CJ41: 深川 | CN41: 標題を預金管理→引落手数料と決済利息の計上に変更してください
CN42: →対応済
BN50: 1．銀行引落手数料情報出力
BO51: 資金集中管理システムから銀行引落手数料情報を
BO52: CSV出力する
BN57: 2．銀行引落手数料仕訳計上
BO58: 引落手数料情報CSVを
BO59: 一般仕訳帳アップロードEXCELレイアウトに編集して
BO60: 一般仕訳帳に登録する
BN66: 3．預金決算利息情報出力
BO67: 資金集中管理システムから預金決算利息情報を
BO68: CSV出力する
BN73: 4．預金決算利息仕訳計上
BO74: 預金決算利息情報CSVを
BO75: 一般仕訳帳アップロードEXCELレイアウトに編集して
BO76: 一般仕訳帳に登録する
CK78: 事務管理 | CO78: 手数料の計上の際は残高確認はしていません
CK79: 深川 | CO79: →対応済
B87: 3．残高管理 日別資金繰
BN99: 1．現預金残高確認
BO100: 日別資金繰管理対象口座の
BO101: 現預金残高を確認する。
BN109: 2．回収見込情報の収集
BO110: カスタマーサービスは
BO111: Mcframeの情報と得意先への問い合わせにより
BO112: 回収見込情報を収集して事務管理Gへ提出
BN121: ３．得意先別回収見込額の確認
BO122: カスタマーサービスからの情報をもとに | CC122: 確認事項
BO123: 得意先別回収見込一覧を作成 | CC123: 新システムでは
CC124: 資金Gで参照可能
CC125: になるか検討
BN129: ４．期日支払一覧の作成
BO130: 仕入先トランザクション一覧を出力して | CC130: GAP
BO131: 期日支払一覧を作成する | CC131: Req325で要件集約中
CC132: 支払方法別、仕入先別の支払基準日、支払日が確認できる帳票を開発する。
BN140: ５．資金移動仕訳計上 | CJ140: 事務管理 | CN140: 現在資金移動仕訳、残高確認は資金Gではなく事務管理で処理しています。
BO141: 資金移動仕訳を入力する | CJ141: 深川 | CN141: 残高確認の際は銀行の入出金明細も確認しています
BN150: ６．残高確認
BO151: 銀行明細を確認する

Sheet 調達・運用・通貨交換
A1: システム名 | F1: =変更履歴!F1 -> 会計システム刷新プロジェクト（LIBRA） | V1: タイトル | AJ1: 日付 | AQ1: 更新者
A2: 文書名 | F2: =変更履歴!F2 -> ToBe業務フロー（2.グループファイナンス・資金繰り） | V2: =MID(CELL("filename",$A$1),FIND("]",CELL("filename",$A$1))+1,31) -> #VALUE! | AJ2: 作成 | AL2: =変更履歴!AT2 -> 45362 | AQ2: =変更履歴!BA2 -> JBS福田
AJ3: 更新 | AL3: =変更履歴!AT3 -> 45763 | AQ3: =変更履歴!BA3 -> JBS福田
A6: =RIGHT(CELL("filename",A1),LEN(CELL("filename",A1))-FIND("]",CELL("filename",A1))) -> #VALUE!
B8: 金融機関 | P8: 財務部 資金G | AD8: システム | AR8: 説明 | BH8: Gap （Add-On） | BO8: サンスター 担当部署・ 担当者 | BS8: サンスターコメント (現状との違い、補足、その他気になること)
P9: 担当者 | W9: 責任者 | AD9: FO | AK9: 外部システム
B10: １．銀行借入
AS23: 1．借入金計上
AT24: 借入金仕訳を計上する | BH24: 20240411
BH25: 現行と同じGL勘定管理とする
AS27: ※ | AT27: D365標準機能に利息計算機能なし | BH27: GAP
AT28: 金利・金利条件・利息発生タイミング・借入期間・ | BH28: 現状ACCESS
AT29: 返済タイミングなどの情報を管理する機能なし | BH29: 処理機能部分を
BH30: 別途ソリューション検討
AS32: 2．利息額の計算
AT33: EXCEL借入金台帳で利息額を確認する
AS34: ※ | AT34: D365標準機能に利息計算機能なし | BH34: GAP
BH35: 現状ACCESS
BH36: 処理機能部分を
BH37: 別途ソリューション検討
AS39: 3．利息仕訳の計上
AT40: 利息仕訳を計上する
AS41: ※ | AT41: D365標準機能に利息自動計上機能なし | BH41: GAP
BH42: 現状ACCESS
BH43: 処理機能部分を
BH44: 別途ソリューション検討
AS45: 4．長短振替仕訳の計上
AT46: 返済期間が1年未満となった借入金を
AT47: 短期借入金に振り替える
AS48: ※ | AT48: D365標準機能に自動長短振替機能なし | BH48: GAP
BH49: 現状ACCESS
BH50: 処理機能部分を
BH51: 別途ソリューション検討
AS52: 5．返済仕訳計上
AT53: 返済仕訳を計上する
AS55: ※ | AT55: D365標準機能に自動返済仕訳作成機能なし | BH55: GAP
AS56: ※ | AT56: GL勘定管理とするかAP勘定管理とするか要検討 | BH56: 現状ACCESS
AT57: AP勘定管理とした場合、支払データ作成や消込管理が可能 | BH57: 処理機能部分を
BH58: 別途ソリューション検討
AS60: 6．支払手数料仕訳計上
AT61: 通貨交換して入出金する際の
AT62: 銀行支払手数料仕訳を計上する
AS63: ※ | AT63: D365標準機能では、通貨交換して入出金する際に、 | BH63: GAP
AT64: 銀行に支払うマージンを自動で計算・記録する機能なし | BH64: RFPの要求事項にあったが
BH65: スコープアウトとなった
AS69: 7．借入金残高確認
AT70: 借入金残高や返済履歴明細を
AT71: 試算表残高および伝票トランザクション明細で確認 | BH71: 科目
AT72: 金融機関別の残高管理をする場合、
AT73: 財務分析コードを設定する必要あり
AT74: 種類例(銀行口座or仕入先orカスタム分析コード) | BH74: 科目が金融機関別になっている
AS76: ※ | AT76: D365標準機能では、
AT77: 将来の残高/返済額/利息額が年別で表示される機能 | BH77: GAP
AT78: なし | BH78: 現状ACCESS
BH79: 処理機能部分を
BH80: 別途ソリューション検討
B83: 2．運用
AS94: 1．運用開始仕訳計上
AT95: 運用開始仕訳を計上する
AS96: ※ | AT96: D365標準機能には | BH96: GAP
AT97: 運用方法・金利などの情報を入力し、 | BH97: RFPの要求事項にあったが
AT98: 運用状況を会計システム内で管理する機能なし | BH98: スコープアウトとなった
AS105: 2．運用収益額の計算
AT106: EXCEL台帳で運用益額を確認する
AS107: ※ | AT107: D365標準機能に運用益計算機能なし | BH107: GAP
BH108: RFPの要求事項にあったが
BH109: スコープアウトとなった
AS112: 3．運用収益仕訳計上
AT113: 運用収益仕訳を計上する
AS119: 4．運用返済仕訳計上
AT120: 運用返済仕訳を計上する
AS129: 5．運用残高確認
AT130: 運用残高や収益履歴明細を
AT131: 試算表残高および伝票トランザクション明細で確認
AT132: 相手会社別・運用商品別に残高を管理する場合
AT133: 財務分析コードを設定する必要あり
AT134: 種類例(相手先or仕入先、証券コード、地域など)
BH135: 定期預金は
BH136: 科目が口座別になる
BH137: 証券については
BH138: 補助コード(財務分析コード)
BH139: を利用するか？
BH140: →現行とおなじく科目だけの管理でよい
B142: 3．通貨交換
AS154: 1．通貨交換依頼
AT155: 銀行に通貨交換依頼を行う
AS163: 2．通貨交換仕訳計上
AT164: 通貨交換仕訳を計上する

Sheet グループファイナンス(内部借入・貸付)
A1: システム名 | F1: =変更履歴!F1 -> 会計システム刷新プロジェクト（LIBRA） | V1: タイトル | AJ1: 日付 | AQ1: 更新者
A2: 文書名 | F2: =変更履歴!F2 -> ToBe業務フロー（2.グループファイナンス・資金繰り） | V2: =MID(CELL("filename",$A$1),FIND("]",CELL("filename",$A$1))+1,31) -> #VALUE! | AJ2: 作成 | AL2: =変更履歴!AT2 -> 45362 | AQ2: =変更履歴!BA2 -> JBS福田
AJ3: 更新 | AL3: =変更履歴!AT3 -> 45763 | AQ3: =変更履歴!BA3 -> JBS福田
A6: =RIGHT(CELL("filename",A1),LEN(CELL("filename",A1))-FIND("]",CELL("filename",A1))) -> #VALUE!
B8: 関連会社 | P8: 財務部 資金G | AD8: システム | AR8: 説明 | BH8: Gap （Add-On） | BO8: サンスター 担当部署・ 担当者 | BS8: サンスターコメント (現状との違い、補足、その他気になること)
P9: 担当者 | W9: 責任者 | AD9: FO | AK9: 外部システム
B10: １．内部借入
AS12: ☆ | AT12: グローバル管理法人ではなく
AT13: 通常のSSJ、SEJ、SLJ法人での処理
AS26: 1．借入金計上
AT27: 借入金仕訳を計上する | BH27: 20240411
AS28: ※ | AT28: GL勘定管理とするかAP勘定管理とするか要検討 | BH28: 現行と同じGL管理とする
AT29: AP管理とした場合、支払データ作成や消込管理が可能
AS30: ※ | AT30: D365標準機能に利息計算機能なし | BH30: GAP
AT31: 金利・金利条件・利息発生タイミング・借入期間・ | BH31: 現状ACCESS
AT32: 返済タイミングなどの情報を管理する機能なし | BH32: 処理機能部分を
BH33: 別途ソリューション提案検討
AS35: 2．利息額の計算
AT36: EXCEL借入金台帳で利息額を確認する
AS37: ※ | AT37: D365標準機能に利息計算機能なし | BH37: GAP
BH38: 現状ACCESS
BH39: 処理機能部分を
BH40: 別途ソリューション提案検討
AS42: 3．利息仕訳の計上
AT43: 利息仕訳を計上する
AS44: ※ | AT44: D365標準機能に利息自動計上機能なし | BH44: GAP
BH45: 現状ACCESS
BH46: 処理機能部分を
BH47: 別途ソリューション提案検討
AS48: 4．長短振替仕訳の計上
AT49: 返済期間が1年未満となった借入金を
AT50: 短期借入金に振り替える
AS51: ※ | AT51: D365標準機能に自動長短振替機能なし | BH51: GAP
BH52: 現状ACCESS
BH53: 処理機能部分を
BH54: 別途ソリューション提案検討
AS55: 5．返済処理
AT56: 借入金の返済処理を行う
AS62: 6．返済仕訳計上
AT63: 返済仕訳を計上する
AS65: ※ | AT65: D365標準機能に自動返済仕訳作成機能なし | BH65: GAP
AS66: ※ | AT66: GL勘定管理とするかAP勘定管理とするか要検討 | BH66: 現状ACCESS
AT67: AP勘定管理とした場合、支払データ作成や消込管理が可能 | BH67: 処理機能部分を
BH68: 別途ソリューション検討
AS70: 7．支払手数料仕訳計上
AT71: 通貨交換して入出金する際の
AT72: 銀行支払手数料仕訳を計上する
AS73: ※ | AT73: D365標準機能では、通貨交換して入出金する際に、 | BH73: GAP
AT74: 銀行に支払うマージンを自動で計算・記録する機能なし | BH74: RFPの要求事項にあったが
BH75: スコープアウトとなった
AS79: 8．借入金残高確認
AT80: 借入金残高や返済履歴明細を
AT81: 試算表残高および伝票トランザクション明細で確認
AT82: 相手会社別の残高管理をする場合、 | BH82: 科目が金融機関別になっている
AT83: 財務分析コードを設定する必要あり
AT84: 分析コード種類例(関連会社or仕入先など)
AS86: ※ | AT86: D365標準機能では、 | BH86: GAP
AT87: 将来の残高/返済額/利息額が年別で表示される機能 | BH87: 現状ACCESS
AT88: なし | BH88: 処理機能部分を
BH89: 別途ソリューション検討
B93: 2．内部貸付
AS104: 1．貸付仕訳計上
AT105: 貸付仕訳を計上する
AT106: 証票をPDF添付する | BH106: 20240411
BH107: 現行と同じGL管理とする
BH108: 科目で会社ごとに分かれている
AS109: ※ | AT109: D365標準機能には | BH109: GAP
AT110: 金利条件・利息発生タイミング・貸付期間・ | BH110: RFPの要求事項にあったが
AT111: 返済タイミングなどの情報を管理する機能なし | BH111: スコープアウトとなった
AS115: 2．利息額の計算
AT116: EXCEL貸付金台帳で利息額を確認する
AS117: ※ | AT117: D365標準機能に貸付利息計算機能なし | BH117: GAP
BH118: RFPの要求事項にあったが
BH119: スコープアウトとなった
AS123: 3．利息仕訳計上
AT124: 受取利息の請求額を計上する
AS128: ※ | AT128: D365標準機能に貸付利息仕訳自動計上機能なし | BH128: GAP
BH129: RFPの要求事項にあったが
BH130: スコープアウトとなった
AS131: 4．利息の請求書発行
AT132: 利息の請求書を発行して相手会社に送付する
AS133: ※ | AT133: FO外のEXCEL等で作成
AS138: 5．返済入金確認
AT139: 返済入金額を確認
AS145: 6．返済入金仕訳計上
AT146: 返済入金仕訳を計上する
AS148: ※ | AT148: D365標準機能に
AT149: 貸付金情報から、自動で返済仕訳を計上する機能なし | BH149: GAP
BH150: RFPの要求事項にあったが
BH151: スコープアウトとなった
AS155: 7．運用残高確認
AT156: 貸付残高や利息計上履歴明細を
AT157: 試算表残高および伝票トランザクション明細で確認
AT158: 相手会社別の残高管理をする場合、
AT159: 財務分析コードを設定する必要あり
AT160: 分析コード種類例(関連会社or顧客など)
B168: 3．配当金決済
AS180: 1．配当金入金確認
AT181: 配当金の入金を確認する
AS189: 2．配当金仕訳計上
...

Sheet 資金予測
A1: システム名 | F1: =変更履歴!F1 -> 会計システム刷新プロジェクト（LIBRA） | V1: タイトル | AJ1: 日付 | AQ1: 更新者
A2: 文書名 | F2: =変更履歴!F2 -> ToBe業務フロー（2.グループファイナンス・資金繰り） | V2: =MID(CELL("filename",$A$1),FIND("]",CELL("filename",$A$1))+1,31) -> #VALUE! | AJ2: 作成 | AL2: =変更履歴!AT2 -> 45362 | AQ2: =変更履歴!BA2 -> JBS福田
AJ3: 更新 | AL3: =変更履歴!AT3 -> 45763 | AQ3: =変更履歴!BA3 -> JBS福田
A6: =RIGHT(CELL("filename",A1),LEN(CELL("filename",A1))-FIND("]",CELL("filename",A1))) -> #VALUE!
B8: 各チャネル | P8: 財務部 資金G | AD8: システム | AR8: 説明 | BH8: Gap （Add-On） | BO8: サンスター 担当部署・ 担当者 | BS8: サンスターコメント (現状との違い、補足、その他気になること)
B9: 担当者 | I9: 責任者 | P9: 担当者 | W9: 責任者 | AD9: FO | AK9: 外部システム
B10: １．年間資金繰計画
AS13: ※ | AT13: 年度資金繰計画EXCELはD365標準機能で対応不可 | BH13: GAP
BH14: FOスコープアウト
BH15: 現状EXCEL処理を
BH16: 実現できるよう
BH17: 各新システムからの
BH18: データ取得方法を今後検討
BH19: EPMシステムやBIツール等で検討したい
AS21: 1．ベース損益用データ出力
AT22: ベース損益の元データとなる
AT23: 財務諸表データを出力する
AS28: 2．ベース損益作成
AT29: 年度資金繰計画EXCELの
AT30: ベース損益に入力する
AS34: 3．前提条件設定
AT35: 年度資金繰計画EXCELの
AT36: 前提条件を設定する
AS41: 4．各種勘定 前年実績収集
AT42: 財務諸表から
AT43: 前年度実績をデータ出力する
AS45: ※ | AT45: D365標準機能で出力できる情報では
AT46: 不足する情報を別途収集する
AS48: 5．支払/入金 予定収集
AT49: 支払/入金予定データを出力する | BH49: 検討事項
BH50: 債務と未収入金は 支払/入金予定情報を保持しているが
AS51: ※ | AT51: D365標準機能で出力できる情報では | BH51: 売掛金は仕訳情報のみ
AT52: 不足する情報を別途収集する | BH52: 売掛金の入金予定および消込実績の参照方法が課題
BH53: Mcframe参照orデータ出力して参照
BH54: またはFO連携して参照
AS55: 6．チャネル別 回収計画
AT56: 各チャネル担当者別に回収計画を入力する
AS63: 7．年間資金繰 計画作成
AT64: 回収計画を集計して
AT65: 年間資金繰計画を作成する
B71: 2．月次資金繰予実
AS74: ※ | AT74: 月別資金繰実績EXCELはD365標準機能で対応不可 | BH74: GAP
BH75: FOスコープアウト
BH76: 現状EXCEL処理を
BH77: 実現できるよう
BH78: 各新システムからの
BH79: データ取得方法を今後検討
BH80: EPMシステムやBIツール等で検討したい
AS82: 1．各種勘定 実績収集
AT83: 財務諸表から
AT84: 前年度実績をデータ出力する
AS86: ※ | AT86: D365標準機能で出力できる情報では
AT87: 不足する情報を別途収集する
AS91: 2．支払/入金 実績収集
AT92: 支払/入金実績データを出力する
AS94: ※ | AT94: D365標準機能で出力できる情報では
AT95: 不足する情報を別途収集する
AS99: 3．資金繰 実績作成
AT100: 月別資金繰実績EXCELを作成する
AS106: 4．資金繰 予実作成
AT107: 月別資金繰予実EXCELを作成する
B114: 3．日別資金繰予実
AS117: ※ | AT117: 日別資金繰実績EXCELはD365標準機能で対応不可 | BH117: GAP
BH118: FOスコープアウト
BH119: 現状EXCEL処理を
BH120: 実現できるよう
BH121: 各新システムからの
BH122: データ取得方法を今後検討
BH123: EPMシステムやBIツール等で検討したい
AS126: 1．月初見込作成
AT127: 日別資金繰実績EXCELの
AT128: 月初見込を作成する
AS133: 2．銀行口座入出金明細出力
AT134: 試算表/伝票トランザクションから
AT135: 入出金明細を出力する
AS141: 3．合計日別資金繰実績作成
AT142: 日別資金繰実績EXCELの
AT143: 口座別のシートに入力して
AT144: 日別資金繰の合計表を作成する
AS147: ※ | AT147: D365標準機能で出力できる情報では
AT148: 不足する情報を別途収集する

Sheet 月次グループ管理(借入預金)
A1: システム名 | F1: =変更履歴!F1 -> 会計システム刷新プロジェクト（LIBRA） | V1: タイトル | AJ1: 日付 | AQ1: 更新者
A2: 文書名 | F2: =変更履歴!F2 -> ToBe業務フロー（2.グループファイナンス・資金繰り） | V2: =MID(CELL("filename",$A$1),FIND("]",CELL("filename",$A$1))+1,31) -> #VALUE! | AJ2: 作成 | AL2: =変更履歴!AT2 -> 45362 | AQ2: =変更履歴!BA2 -> JBS福田
AJ3: 更新 | AL3: =変更履歴!AT3 -> 45763 | AQ3: =変更履歴!BA3 -> JBS福田
A6: =RIGHT(CELL("filename",A1),LEN(CELL("filename",A1))-FIND("]",CELL("filename",A1))) -> #VALUE!
B8: 関連会社 | P8: 財務部 資金G | AD8: システム | AR8: 説明 | BH8: Gap （Add-On） | BO8: サンスター 担当部署・ 担当者 | BS8: サンスターコメント (現状との違い、補足、その他気になること)
P9: 担当者 | W9: 責任者 | AD9: FO | AK9: 外部システム
B10: １．借入・預金管理
AS12: ☆ | AT12: グローバル管理法人での処理 | BH12: GAP
BH13: スコープアウトとなった
AS23: 1．グローバルコミットメントライン枠登録
AT24: 各社各銀行口座毎の
AT25: グローバルコミットメント枠の金額を
AT26: 予算登録エントリに登録する
AS32: 2．データの収集依頼
AT33: グローバル各社の担当者に対して、事前に登録した
AT34: 文面のメールで預金情報データと借入情報データ
AT35: を依頼する
AS36: ※ | AT36: D365標準機能に | BH36: GAP
AT37: グローバル各社の担当者に対して、事前登録メールを | BH37: スコープアウトとなった
AT38: 毎月自動送信する機能なし
AS42: 3．各社残高登録
AT43: 各社の月末預金残高と月末借入金残高を登録する
AS45: ※ | AT45: 一般仕訳に仕訳伝票として登録する
AT46: 相手科目は登録用仮勘定
AT47: ExcelAddin使用
AS53: 4．利息仕訳の計上
AT54: 利息仕訳を計上する
AS55: ※ | AT55: D365標準機能に利息自動計上機能なし | BH55: GAP
BH56: スコープアウトとなった
AS64: 5．借入金残高確認
AT65: 会社別の口座残高、借入金残高を確認する。
AT66: MRを使用して
AT67: 会社を地域等でグルーピングして参照する。
AT68: 前月と報告月の残高が横並びで比較、増減表示
AT69: 借入消費枠の管理は予実帳票を使って参照する

Sheet 四半期グループ管理(借入貸付)
A1: システム名 | F1: =変更履歴!F1 -> 会計システム刷新プロジェクト（LIBRA） | V1: タイトル | AJ1: 日付 | AQ1: 更新者
A2: 文書名 | F2: =変更履歴!F2 -> ToBe業務フロー（2.グループファイナンス・資金繰り） | V2: =MID(CELL("filename",$A$1),FIND("]",CELL("filename",$A$1))+1,31) -> #VALUE! | AJ2: 作成 | AL2: =変更履歴!AT2 -> 45362 | AQ2: =変更履歴!BA2 -> JBS福田
AJ3: 更新 | AL3: =変更履歴!AT3 -> 45763 | AQ3: =変更履歴!BA3 -> JBS福田
A6: =RIGHT(CELL("filename",A1),LEN(CELL("filename",A1))-FIND("]",CELL("filename",A1))) -> #VALUE!
B8: 関連会社 | P8: 財務部 資金G | AD8: システム | AR8: 説明 | BH8: Gap （Add-On） | BO8: サンスター 担当部署・ 担当者 | BS8: サンスターコメント (現状との違い、補足、その他気になること)
P9: 担当者 | W9: 責任者 | AD9: FO | AK9: 外部システム
B10: １．グループ間借入・貸付管理
AS12: ☆ | AT12: グローバル管理法人での処理 | BH12: GAP
BH13: スコープアウトとなった
AS22: 1．データの収集依頼
AT23: グローバル各社の担当者に対して、
AT24: 月末のグループ間借入・貸付残高データ
AT25: を依頼する
AS32: 2．各社残高登録
AT33: 各社の月末グループ間借入・貸付残高を登録する
AS35: ※ | AT35: 一般仕訳に仕訳伝票として登録する
AT36: 相手科目は登録用仮勘定
AT37: ExcelAddin使用
AS45: 3．借入金残高確認
AT46: 会社別のグループ間借入・貸付残高を確認する。
AT47: MRを使用して
AT48: 前月と当月の月末のグループ間借入・貸付残高を
AT49: 横並びで比較、増減表示
