Workbook

Sheet 表紙
B3: サンスター株式会社 御中
B10: 会計システム刷新プロジェクト（LIBRA）
B14: ToBe業務フロー（6.予算）
B22: ="第"&IF(COUNTA(変更履歴!BE5:BH10000)=1,"",INDIRECT("変更履歴!BE"&COUNTA(変更履歴!BE5:BH10000)+4))&"版" -> 第1.6版
B24: {=IF(OR(COUNTA(変更履歴!A:E)=3),"",INDIRECT("変更履歴!A"&COUNTA(変更履歴!A:E)+2))} -> 45840
B26: 日本ビジネスシステムズ株式会社
F29: 作成者 | O29: JBS承認者 | V29: 承認者
F30: 45362 | N30: 45433
F31: JBS福田 | N31: JBS加藤

Sheet 変更履歴
A1: システム名 | F1: =表紙!B10 -> 会計システム刷新プロジェクト（LIBRA） | W1: タイトル | AR1: 日付 | BA1: 更新者
A2: 文書名 | F2: =表紙!B14 -> ToBe業務フロー（6.予算） | W2: =MID(CELL("filename",$A$1),FIND("]",CELL("filename",$A$1))+1,31) -> #VALUE! | AR2: 作成 | AT2: =A6 -> 45362 | BA2: =AZ6 -> JBS福田
AR3: 更新 | AT3: {=IF(OR(COUNTA(A:E)=3),"",INDIRECT("A"&COUNTA(A:E)+2))} -> 45840 | BA3: {=IF(COUNTA(AZ5:BD100000)=1,"",INDIRECT("変更履歴!AZ"&COUNTA(AZ5:BD100000)+4))} -> JBS福田
A5: 変更年月日 | F5: 変更箇所 | T5: 変更内容 | AZ5: 変更者 | BE5: 版数
A6: 45362 | F6: 新規作成 | T6: 新規作成 | AZ6: JBS福田 | BE6: 0.1
A7: 45433 | F7: 初版確定 | T7: 初版確定 | AZ7: JBS福田 | BE7: 1.0
A8: 45629 | F8: SSJ予算作成 | T8: LIBRA-339 Branch1としての配賦処理の決定 を元に ・配賦処理をFOからJ-BASまたはAzure Synapse Analyticsに記述変更 ・使用しない予算登録エントリの一連の作業を削除 | AZ8: JBS福田 | BE8: 1.1
A9: 45629 | F9: SEJ予算作成 | T9: LIBRA-339 Branch1としての配賦処理の決定 を元に ・配賦処理をFOからJ-BASまたはAzure Synapse Analyticsに記述変更 ・使用しない予算登録エントリの一連の作業を削除 | AZ9: JBS福田 | BE9: 1.1
A10: 45629 | F10: グローバル損益管理 | T10: FO外での管理となったためシート全体を削除 | AZ10: JBS福田 | BE10: 1.1
A11: 45741 | F11: SSJ予算作成 | T11: プロセス名の変更 7．予算計画登録 → 7．売上・原価予算計画取込 10．各部課別経費予算登録 → 10．部門経費予算計画取込 | AZ11: JBS福田 | BE11: 1.2
A12: 45741 | F12: SEJ予算作成 | T12: プロセス名の変更 8．予算計画登録 → 8．売上・原価予算計画取込 10．一般経費予算登録 → 10．部門経費予算計画取込 | AZ12: JBS福田 | BE12: 1.2
A13: 45756 | F13: SSJ予算作成 SEJ予算作成 | T13: １．毎期事前登録作業 のブロックを追加作成 予算サイクル 予算計画プロセスの登録のプロセスを追加 2．予算作成以降の番号振り直し | AZ13: JBS福田 | BE13: 1.3
A14: 45778 | F14: SSJ予算作成 １．毎期事前登録作業 SEJ予算作成 １．毎期事前登録作業 | T14: 「予算計画登録」のプロセスを追加 | AZ14: JBS福田 | BE14: 1.4
A15: 45778 | F15: SSJ予算作成 7．売上・原価予算計画取込 SEJ予算作成 7．売上・原価予算計画取込 | T15: 以下のコメントを追加 ※１．毎期事前登録作業で作成した予算計画プロセスと予算計画文書番号を指定して取込実行 | AZ15: JBS福田 | BE15: 1.4
A16: 45778 | F16: SSJ予算作成 10．部門経費予算計画取込 SEJ予算作成 10．部門経費予算計画取込 | T16: 以下のコメントを追加 ※１．毎期事前登録作業で作成した予算計画文書番号をEXCEL側に指定して取込 | AZ16: JBS福田 | BE16: 1.4
A17: 45778 | F17: SSJ予算作成 SEJ予算作成 | T17: 11．MR予算帳票の予算計画名変更 のプロセスを追加 以降のプロセスの番号を振り直し | AZ17: JBS福田 | BE17: 1.4
... A19: 45840 | F19: SSJ予算作成 SEJ予算作成 | T19: 上記、2．予算作成 ＞ 13．予算計画承認 のプロセスについて、コメントで網掛け削除していたのを物理的に削除 その他、最新化にともない、要件定義時のヒアリングメモを記述していた部分を削除 | AZ19: JBS福田 | BE19: 1.6

Sheet 凡例
A1: システム名 | F1: =変更履歴!F1 -> 会計システム刷新プロジェクト（LIBRA） | V1: タイトル | AJ1: 日付 | AQ1: 更新者
A2: 文書名 | F2: =変更履歴!F2 -> ToBe業務フロー（6.予算） | V2: =MID(CELL("filename",$A$1),FIND("]",CELL("filename",$A$1))+1,31) -> #VALUE! | AJ2: 作成 | AL2: =変更履歴!AT2 -> 45362 | AQ2: =変更履歴!BA2 -> JBS福田
AJ3: 更新 | AL3: =変更履歴!AT3 -> 45840 | AQ3: =変更履歴!BA3 -> JBS福田
A6: 凡例
H10: ： | I10: フローの開始 | AC10: ： | AD10: フローの終了
H15: ： | I15: システムを伴わない業務 | AC15: ： | AD15: システム上での業務
H20: ： | I20: 帳票（システムで作成される帳票） | AC20: ： | AD20: 帳票（システム外で作成される帳票）
H25: ： | I25: 業務の流れ | AC25: ： | AD25: システムへの連携
H30: ： | I30: 分岐 | AC30: ： | AD30: システム
H35: ： | I35: フロー間の繋がりを示す | AC35: ： | AD35: ファイル（CSVファイル等）
A40: 凡例
B43: 社内部署 | J43: ： | K43: フローに登場する社内の部署を記載
K44: 部署内の担当者が分かれる場合は以下の通りに分ける
B46: 社内部署
B47: 担当者 | I47: 責任者
B50: 外部担当者 | J50: ： | K50: フローに登場する社外担当者の部署を記載
K51: 例）得意先、仕入先
B54: システム | J54: ： | K54: フロー上で実施されるシステムの機能を記載する列
B55: XX | K55: XXの部分にフローで登場するシステム名を記載
K56: 例は以下の通り（JBSで導入するシステム外のものは「外部システム」で統一）
B58: システム
B59: FO | I59: CE | P59: 外部システム
B62: 説明 | S62: ： | T62: フロー内容を説明する列
B66: Gap （Add-On） | J66: ： | K66: フローに対してのGapを記載する列
B70: １．パターン１ | AI70: ： | AJ70: フローのパターンごとに記載する

Sheet SSJ予算作成
A1: システム名 | F1: =変更履歴!F1 -> 会計システム刷新プロジェクト（LIBRA） | V1: タイトル | AJ1: 日付 | AQ1: 更新者
A2: 文書名 | F2: =変更履歴!F2 -> ToBe業務フロー（6.予算） | V2: =MID(CELL("filename",$A$1),FIND("]",CELL("filename",$A$1))+1,31) -> #VALUE! | AJ2: 作成 | AL2: =変更履歴!AT2 -> 45362 | AQ2: =変更履歴!BA2 -> JBS福田
AJ3: 更新 | AL3: =変更履歴!AT3 -> 45840 | AQ3: =変更履歴!BA3 -> JBS福田
A6: =RIGHT(CELL("filename",A1),LEN(CELL("filename",A1))-FIND("]",CELL("filename",A1))) -> #VALUE!
B8: チャネル/各部署 | P8: 経営計画G | AD8: 事業計画部 | AR8: ITDX | AY8: システム | BM8: 説明 | CC8: Gap （Add-On） | CJ8: サンスター 担当部署・ 担当者 | CN8: サンスターコメント (現状との違い、補足、その他気になること)
B9: 担当者 | I9: 責任者 | P9: 担当者 | W9: 責任者 | AD9: 担当者 | AK9: 責任者 | AR9: 担当者 | AY9: FO | BF9: 外部システム
B10: １．毎期事前登録作業
BN15: １．予算サイクル登録
BO16: 来期の予算サイクルを登録する。
BN20: 2．予算計画プロセス登録
BO21: 来期の予算計画プロセスを登録する。
BN26: 3．予算計画登録
BO27: 来期の予算計画を登録する。
BO28: 文書番号と予算計画名を決定する。
B37: 2．予算作成
BN42: １．経営計画策定
BO43: 来期の経営方針を策定する。
BN46: 2．予算編成方針策定
BO47: 来期の経営方針を受け、予算編成の方針を策定する。
BN52: 3．各チャネル予算作成/修正依頼
BO53: 各チャネルに予算作成を依頼する。
BN58: 4．各チャネル売上/原価予算作成
BO59: 各チャネル担当者はEXCELフォーマットに予算を記入して
BO60: 予算編成担当者へ
BN73: 5．売上/原価予算登録
BO74: 各チャネル担当者から回収したシートを経営計画Gで
BO75: 集計して新業務くん/Mcframeへ登録
BN84: 6．新業務くん/Mcframeデータ出力 | CC84: 注記
BO85: 新業務くん/Mcframeから予算データを出力する | CC85: 新Mcframeに予算データ出力機能を
CC86: 実装する必要あり
BN91: 7．売上・原価予算計画取込
BO92: 新業務くん/Mcframeから出力したデータを | CC92: アドオン開発
BO93: FO予算計画に登録する | CC93: FO-029_設計書_売上・原価予算計画取込
BN95: ※ | BO95: １．毎期事前登録作業で作成した
BO96: 予算計画プロセスと予算計画文書番号を指定して
BO97: 取込実行
BN101: 8．各部課別経費予算作成依頼
BO102: 各部課に経費予算作成を依頼する。
BN107: 9．各部課別経費予算作成
BO108: 各部課担当者はEXCELフォーマットに予算を記入して
BO109: 予算編成担当者へ
BO111: SSJ経費フォーマット
BN113: ※ | BO113: 現状、経費は部課別の登録のみであるが
BO114: 科目-部課-チャネル-ブランド-カテゴリ形式での
BO115: 入力方式に変更して入力
BN121: 10．部門経費予算計画取込
BO122: 各担当者から回収したシートを事業計画Gが
BO123: FO予算計画へ登録 | CC123: アドオン開発
CC124: FO-070_設計書_部門経費予算計画取込
BN125: ※ | BO125: １．毎期事前登録作業で作成した
BO126: 予算計画文書番号をEXCEL側に指定して取込
BN128: ※ | BO128: 各部署で予算計画への入力を行う案もあるが | CC128: 現行予算作成者数は155名 承認者を含めるとその倍の数
BO129: その場合、担当者分のライセンスが必要 | CC129: 必要ライセンス種類 「TeamMember 約1,500円/月」
BN135: 11．MR予算帳票の予算計画名変更
BO136: MR帳票で予算額を使用している帳票で
BO137: 列の定義に設定している予算計画名を
BO138: １．毎期事前登録作業で作成した
BO139: 予算計画名に変更します。
BO140: ※MRのReportDesignerを使用します。
BN144: 12．配賦前予算計画金額確認
BO145: 予算計画の登録内容をMR帳票で確認
BP146: Rep106一般管理費月別予算
BP147: Rep107生産経費月別予算
BP148: Rep063 生産部用経費予実
BN164: 14．予算計画BI連携 | CC164: ※仮名称
BO165: FOの予算計画をBIへ連携する | CC165: BI側機能決定後更新の必要あり
BN177: 15．予算配賦
BO178: 現行、部課別(原価センタ)予算をJGR別に配賦 | CC178: ※仮名称
BO179: 新計画では、チャネル/ブランド/カテゴリ別に配賦 | CC179: BI側機能決定後更新の必要あり
BN189: 16．配賦後予算金額確認 | CC189: ※仮名称
BO190: 配賦後予算金額を確認 | CC190: BI側機能決定後更新の必要あり
B213: 3．予実確認
BN218: １．予実確認
BO219: 各種予実帳票を出力して
BO220: 予算と実績を対比・確認する。

Sheet SSJ予算作成old
A1: システム名 | F1: =変更履歴!F1 -> 会計システム刷新プロジェクト（LIBRA） | V1: タイトル | AJ1: 日付 | AQ1: 更新者
A2: 文書名 | F2: =変更履歴!F2 -> ToBe業務フロー（6.予算） | V2: =MID(CELL("filename",$A$1),FIND("]",CELL("filename",$A$1))+1,31) -> #VALUE! | AJ2: 作成 | AL2: =変更履歴!AT2 -> 45362 | AQ2: =変更履歴!BA2 -> JBS福田
AJ3: 更新 | AL3: =変更履歴!AT3 -> 45840 | AQ3: =変更履歴!BA3 -> JBS福田
A6: =RIGHT(CELL("filename",A1),LEN(CELL("filename",A1))-FIND("]",CELL("filename",A1))) -> #VALUE!
B8: チャネル/各部署 | P8: 経営計画G | AD8: 事業計画部 | AR8: ITDX | AY8: システム | BM8: 説明 | CC8: Gap （Add-On） | CJ8: サンスター 担当部署・ 担当者 | CN8: サンスターコメント (現状との違い、補足、その他気になること)
B9: 担当者 | I9: 責任者 | P9: 担当者 | W9: 責任者 | AD9: 担当者 | AK9: 責任者 | AR9: 担当者 | AY9: FO | BF9: 外部システム
B10: １．毎期事前登録作業
BN15: １．予算サイクル登録
BO16: 来期の予算サイクルを登録する。
BN20: 2．予算計画プロセス登録
BO21: 来期の予算計画プロセスを登録する。
BN26: 3．予算計画登録
BO27: 来期の予算計画を登録する。
BO28: 文書番号と予算計画名を決定する。
B37: 2．予算作成
BN42: １．経営計画策定
BO43: 来期の経営方針を策定する。
BN46: 2．予算編成方針策定
BO47: 来期の経営方針を受け、予算編成の方針を策定する。
BN52: 3．各チャネル予算作成/修正依頼
BO53: 各チャネルに予算作成を依頼する。
BN58: 4．各チャネル売上/原価予算作成
BO59: 各チャネル担当者はEXCELフォーマットに予算を記入して
BO60: 予算編成担当者へ
BN62: ※ | BO62: SSJ損益管理フォーマットの43行目まで | CC62: 現行情報をメモ
BO63: 経費はチャネル担当は設定せずに部課別で収集して
BO64: 配賦でチャネル/ブランド/カテゴリに分解
BO66: 以下43行目までの主要内容
BO67: 売上 | BR67: チャネル/ブランド/カテゴリ
BO68: 売上値引 | BR68: チャネル別まで現場で作成 してブランド/カテゴリは配賦
BO69: 原価 | BS69: 売上×標準原価より。品種のマスターでブランドカテゴリー分解
BO70: 原価差異 | BS70: 事業別の売上配賦(売上配賦とほぼニア)
BO71: 他勘定振替 | BS71: 売上配賦の科目と商品別までの情報ある(今後の在庫の持ち方の考え方次第)
BO72: 物流費 | BS72: JGR別の情報がEDILより(JGRへの無理やり分解実施)
BO73: ロイヤリティ | BS73: 売上×ロイヤリティフラグより(得意先ごとに指定できないか？、内販分を検討する必要あり)
BO74: プロモ費用 | BS74: 現状チャネル別まで
BO75: ＰＲ費用 | BS75: 優先順位①JGR指定あり→②部課の配賦設定
BN80: 5．売上/原価予算登録
BO81: 各チャネル担当者から回収したシートを経営計画Gで
BO82: 集計して新業務くん/Mcframeへ登録
BN91: 6．新業務くん/Mcframeデータ出力 | CC91: 注記
BO92: 新業務くん/Mcframeから予算データを出力する | CC92: 新Mcframeに予算データ出力機能を
CC93: 実装する必要あり
BN98: 7．売上・原価予算計画取込
BO99: 新業務くん/Mcframeから出力したデータを | CC99: アドオン開発
BO100: FO予算計画に登録する | CC100: FO-029_設計書_売上・原価予算計画取込
BN102: ※ | BO102: １．毎期事前登録作業で作成した
BO103: 予算計画プロセスと予算計画文書番号を指定して
BO104: 取込実行
BN108: 8．各部課別経費予算作成依頼
BO109: 各部課に経費予算作成を依頼する。
BN114: 9．各部課別経費予算作成
BO115: 各部課担当者はEXCELフォーマットに予算を記入して
BO116: 予算編成担当者へ
BO118: SSJ経費フォーマット
BN120: ※ | BO120: 現状、経費は部課別の登録のみであるが
BO121: 科目-部課-チャネル-ブランド-カテゴリ形式での
BO122: 入力方式に変更して入力
BN128: 10．部門経費予算計画取込
BO129: 各担当者から回収したシートを事業計画Gが
BO130: FO予算計画へ登録 | CC130: アドオン開発
CC131: FO-070_設計書_部門経費予算計画取込
BN132: ※ | BO132: １．毎期事前登録作業で作成した
BO133: 予算計画文書番号をEXCEL側に指定して取込
BN135: ※ | BO135: 各部署で予算計画への入力を行う案もあるが | CC135: 現行予算作成者数は155名 承認者を含めるとその倍の数
BO136: その場合、担当者分のライセンスが必要 | CC136: 必要ライセンス種類 「TeamMember 約1,500円/月」
BN142: 11．MR予算帳票の予算計画名変更
BO143: MR帳票で予算額を使用している帳票で
BO144: 列の定義に設定している予算計画名を
BO145: １．毎期事前登録作業で作成した
BO146: 予算計画名に変更します。
BO147: ※MRのReportDesignerを使用します。
BN151: 12．配賦前予算計画金額確認
BO152: 予算計画の登録内容をMR帳票で確認
BP153: Rep106一般管理費月別予算
BP154: Rep107生産経費月別予算
BP155: Rep063 生産部用経費予実
BN163: 13．予算計画承認
BO164: 予算計画の登録額が確定したら
BO165: 予算計画を承認(確定)して修正できないようにします。
BO167: ※修正ガードする必要なければ当プロセスは不要
BP169: 一度
BN184: 14．予算計画BI連携 | CC184: ※未計画
BO185: FOの予算計画をBIへ連携する
BN197: 15．予算配賦
BO198: 現行、部課別(原価センタ)予算をJGR別に配賦
BO199: 新計画では、チャネル/ブランド/カテゴリ別に配賦
BN209: 16．配賦後予算金額確認
BO210: 配賦後予算金額を確認
B233: 3．予実確認
BN238: １．予実確認
BO239: 各種予実帳票を出力して
BO240: 予算と実績を対比・確認する。

Sheet SEJ予算作成
A1: システム名 | F1: =変更履歴!F1 -> 会計システム刷新プロジェクト（LIBRA） | V1: タイトル | AJ1: 日付 | AQ1: 更新者
A2: 文書名 | F2: =変更履歴!F2 -> ToBe業務フロー（6.予算） | V2: =MID(CELL("filename",$A$1),FIND("]",CELL("filename",$A$1))+1,31) -> #VALUE! | AJ2: 作成 | AL2: =変更履歴!AT2 -> 45362 | AQ2: =変更履歴!BA2 -> JBS福田
AJ3: 更新 | AL3: =変更履歴!AT3 -> 45840 | AQ3: =変更履歴!BA3 -> JBS福田
A6: =RIGHT(CELL("filename",A1),LEN(CELL("filename",A1))-FIND("]",CELL("filename",A1))) -> #VALUE!
B8: 各部署 | P8: 経営計画G | AD8: 事業計画部 | AR8: ITDX | AY8: システム | BM8: 説明 | CC8: Gap （Add-On） | CJ8: サンスター 担当部署・ 担当者 | CN8: サンスターコメント (現状との違い、補足、その他気になること)
B9: 担当者 | I9: 責任者 | P9: 担当者 | W9: 責任者 | AD9: 担当者 | AK9: 責任者 | AR9: 担当者 | AY9: FO | BF9: 外部システム
B10: １．毎期事前登録作業
BN15: １．予算サイクル登録
BO16: 来期の予算サイクルを登録する。
BN20: 2．予算計画プロセス登録
BO21: 来期の予算計画プロセスを登録する。
BN26: 3．予算計画登録
BO27: 来期の予算計画を登録する。
BO28: 文書番号と予算計画名を決定する。
B37: 2．予算作成
BN42: １．経営計画策定
BO43: 来期の経営方針を策定する。
BN46: 2．予算編成方針策定
BO47: 来期の経営方針を受け、予算編成の方針を策定する。
BN55: 3．各部署担当予算作成/修正依頼
BO56: 各部署に予算作成を依頼する。
BN58: ※ | BO58: 現行 売上／販売費／経費それぞれの入力フォーマットを配布
BO59: 必要な参考資料を作成し、予算担当者に配信している。
BN64: 4．各部署予算作成
BO65: 各部署担当者はEXCELフォーマットに予算を記入して
BO66: 予算編成担当者へ
BN70: 5．売上/販売費/経費AS400登録
BO71: 各予算担当者から回収したシートを事業計画部で
BO72: 集計して実行ファイルでAS400登録
BO75: 生産部門分は直接入力
BO76: 原価/販売費/人件費/経費
BN80: 6．生産部門予算登録
BO81: 生産部門はAS400へ直接入力する
BO82: 原価/販売費/人件費/経費
BN86: 7．AS400予算データ出力
BO87: AS400予算データを出力する | CC87: 注記
CC88: A/S400に予算データ出力機能の
CC89: 実装する必要あり
BN93: 8．売上・原価予算計画取込
BO94: AS400から出力したデータをFO予算計画に
BO95: 登録する | CC95: アドオン開発
CC96: FO-029_設計書_売上・原価予算計画取込
BN97: ※ | BO97: １．毎期事前登録作業で作成した
BO98: 予算計画プロセスと予算計画文書番号を指定して
BO99: 取込実行
BN102: 9．一般経費予算作成
BO103: 各部で一般経費予算を作成する
BN105: ※ | BO105: 生産部門のみ生産部門でAS400へ登録
BN110: 10．部門経費予算計画取込
BO111: 各部で作成した一般経費予算を事業計画部が | CC111: アドオン開発
BO112: FO予算計画に登録する | CC112: FO-070_設計書_部門経費予算計画取込
BN114: ※ | BO114: １．毎期事前登録作業で作成した
BO115: 予算計画文書番号をEXCEL側に指定して取込
BN117: ※ | BO117: 各部署で予算計画への入力を行う案もあるが
BO118: その場合、担当者分のライセンスが必要 | CC118: 必要ライセンス種類 「TeamMember 約1,500円/月」
BN122: 11．MR予算帳票の予算計画名変更
BO123: MR帳票で予算額を使用している帳票で
BO124: 列の定義に設定している予算計画名を
BO125: １．毎期事前登録作業で作成した
BO126: 予算計画名に変更します。
BO127: ※MRのReportDesignerを使用します。
BN130: 12．配賦前予算計画PL確認
BO131: 予算計画の登録内容をMR帳票で確認
BP132: Rep106一般管理費月別予算
BP133: Rep107生産経費月別予算
BP134: Rep063 生産部用経費予実
BN148: 14．予算計画BI連携 | CC148: ※仮名称
BO149: FOの予算計画をBIへ連携する | CC149: BI側機能決定後更新の必要あり
BN161: 15．予算配賦 | CC161: ※仮名称
BO162: 現行、部課別(利益センタ)予算を | CC162: BI側機能決定後更新の必要あり
BO163: 詳細部課別(利益センタ)別に配賦
BN174: 16．配賦後予算金額確認 | CC174: ※仮名称
BO175: 配賦後予算金額を確認 | CC175: BI側機能決定後更新の必要あり
B199: 3．予実確認
BN204: １．予実確認
BO205: 各種予実帳票を出力して
BO206: 予算と実績を対比・確認する。

Sheet SEJ予算作成old
A1: システム名 | F1: =変更履歴!F1 -> 会計システム刷新プロジェクト（LIBRA） | V1: タイトル | AJ1: 日付 | AQ1: 更新者
A2: 文書名 | F2: =変更履歴!F2 -> ToBe業務フロー（6.予算） | V2: =MID(CELL("filename",$A$1),FIND("]",CELL("filename",$A$1))+1,31) -> #VALUE! | AJ2: 作成 | AL2: =変更履歴!AT2 -> 45362 | AQ2: =変更履歴!BA2 -> JBS福田
AJ3: 更新 | AL3: =変更履歴!AT3 -> 45840 | AQ3: =変更履歴!BA3 -> JBS福田
A6: =RIGHT(CELL("filename",A1),LEN(CELL("filename",A1))-FIND("]",CELL("filename",A1))) -> #VALUE!
B8: 各部署 | P8: 経営計画G | AD8: 事業計画部 | AR8: ITDX | AY8: システム | BM8: 説明 | CC8: Gap （Add-On） | CJ8: サンスター 担当部署・ 担当者 | CN8: サンスターコメント (現状との違い、補足、その他気になること)
B9: 担当者 | I9: 責任者 | P9: 担当者 | W9: 責任者 | AD9: 担当者 | AK9: 責任者 | AR9: 担当者 | AY9: FO | BF9: 外部システム
B10: １．毎期事前登録作業
BN15: １．予算サイクル登録
BO16: 来期の予算サイクルを登録する。
BN20: 2．予算計画プロセス登録
BO21: 来期の予算計画プロセスを登録する。
BN26: 3．予算計画登録
BO27: 来期の予算計画を登録する。
BO28: 文書番号と予算計画名を決定する。
B37: 2．予算作成
BN42: １．経営計画策定
BO43: 来期の経営方針を策定する。
BN46: 2．予算編成方針策定
BO47: 来期の経営方針を受け、予算編成の方針を策定する。
BN55: 3．各部署担当予算作成/修正依頼
BO56: 各部署に予算作成を依頼する。
BN58: ※ | BO58: 現行 売上／販売費／経費それぞれの入力フォーマットを配布
BO59: 必要な参考資料を作成し、予算担当者に配信している。
BN64: 4．各部署予算作成
BO65: 各部署担当者はEXCELフォーマットに予算を記入して
BO66: 予算編成担当者へ
BN70: 5．売上/販売費/経費AS400登録
BO71: 各予算担当者から回収したシートを事業計画部で
BO72: 集計して実行ファイルでAS400登録
BO75: 生産部門分は直接入力
BO76: 原価/販売費/人件費/経費
BN80: 6．生産部門予算登録
BO81: 生産部門はAS400へ直接入力する
BO82: 原価/販売費/人件費/経費
BN86: 7．AS400予算データ出力
BO87: AS400予算データを出力する | CC87: 注記
CC88: A/S400に予算データ出力機能の
CC89: 実装する必要あり
BN93: 8．売上・原価予算計画取込
BO94: AS400から出力したデータをFO予算計画に
BO95: 登録する | CC95: アドオン開発
CC96: FO-029_設計書_売上・原価予算計画取込
BN97: ※ | BO97: １．毎期事前登録作業で作成した
BO98: 予算計画プロセスと予算計画文書番号を指定して
BO99: 取込実行
BN102: 9．一般経費予算作成
BO103: 各部で一般経費予算を作成する
BN105: ※ | BO105: 生産部門のみ生産部門でAS400へ登録
BN110: 10．部門経費予算計画取込
BO111: 各部で作成した一般経費予算を事業計画部が | CC111: アドオン開発
BO112: FO予算計画に登録する | CC112: FO-070_設計書_部門経費予算計画取込
BN114: ※ | BO114: １．毎期事前登録作業で作成した
BO115: 予算計画文書番号をEXCEL側に指定して取込
BN117: ※ | BO117: 各部署で予算計画への入力を行う案もあるが
BO118: その場合、担当者分のライセンスが必要 | CC118: 必要ライセンス種類 「TeamMember 約1,500円/月」
BN122: 11．MR予算帳票の予算計画名変更
BO123: MR帳票で予算額を使用している帳票で
BO124: 列の定義に設定している予算計画名を
BO125: １．毎期事前登録作業で作成した
BO126: 予算計画名に変更します。
BO127: ※MRのReportDesignerを使用します。
BN130: 12．配賦前予算計画PL確認
BO131: 予算計画の登録内容をMR帳票で確認
BP132: Rep106一般管理費月別予算
BP133: Rep107生産経費月別予算
BP134: Rep063 生産部用経費予実
BN140: 13．予算計画承認
BO141: 予算計画の登録額が確定したら
BO142: 予算計画を承認(確定)して修正できないようにします。
BO144: ※修正ガードする必要なければ当プロセスは不要
BN156: 14．予算計画BI連携 | CC156: ※未計画
BO157: FOの予算計画をBIへ連携する
BN169: 15．予算配賦
BO170: 現行、部課別(利益センタ)予算を
BO171: 詳細部課別(利益センタ)別に配賦
BN182: 16．配賦後予算金額確認
BO183: 配賦後予算金額を確認
B207: 3．予実確認
BN212: １．予実確認
BO213: 各種予実帳票を出力して
BO214: 予算と実績を対比・確認する。
