Workbook

Sheet 表紙
B3: サンスター株式会社 御中
B10: 会計システム刷新プロジェクト（LIBRA）
B14: ToBe業務フロー（5.固定資産_リース）
B22: ="第"&IF(COUNTA(変更履歴!BE5:BH10004)=1,"",INDIRECT("変更履歴!BE"&COUNTA(変更履歴!BE5:BH10004)+4))&"版" -> 第1.15版
B24: {=IF(OR(COUNTA(変更履歴!A:E)=3),"",INDIRECT("変更履歴!A"&COUNTA(変更履歴!A:E)+2))} -> 45939
B26: 日本ビジネスシステムズ株式会社
F29: 作成者 | O29: JBS承認者 | V29: 承認者
F30: 45362 | N30: 45433
F31: JBS大河原 | N31: JBS加藤

Sheet 変更履歴
A1: システム名 | F1: =表紙!B10 -> 会計システム刷新プロジェクト（LIBRA） | W1: タイトル | AR1: 日付 | BA1: 更新者
A2: 文書名 | F2: =表紙!B14 -> ToBe業務フロー（5.固定資産_リース） | W2: =MID(CELL("filename",$A$1),FIND("]",CELL("filename",$A$1))+1,31) -> #VALUE! | AR2: 作成 | AT2: =A6 -> 45362 | BA2: =AZ6 -> JBS大河原
AR3: 更新 | AT3: {=IF(OR(COUNTA(A:E)=3),"",INDIRECT("A"&COUNTA(A:E)+2))} -> 45939 | BA3: {=IF(COUNTA(AZ5:BD100004)=1,"",INDIRECT("変更履歴!AZ"&COUNTA(AZ5:BD100004)+4))} -> JBS中村
A5: 変更年月日 | F5: 変更箇所 | T5: 変更内容 | AZ5: 変更者 | BE5: 版数
A6: 45362 | F6: 新規作成 | T6: 新規作成 | AZ6: JBS大河原 | BE6: 0.1
A7: 45433 | F7: 初版確定 | T7: 初版確定 | AZ7: JBS大河原 | BE7: 1.0
A8: 45495 | F8: シート「固定資産管理」 | T8: 建設仮勘定の総額を認識するフローを修正。固定資産管理シート １．固定資産取得を修正 | AZ8: JBS大河原 | BE8: 1.1
A9: 45677 | F9: シート「固定資産管理」 | T9: 建設仮勘定に関するフローを修正。固定資産管理シート １．固定資産取得 を修正 | AZ9: JBS中村 | BE9: 1.2
A10: 45701 | F10: シート「固定資産管理」 | T10: ・固定資産の通常取得：購入と資産計上が同時期に実施される場合と建設仮勘定対応：購入と資産計上の時期にずれがある場合のフローを分離 6．固定資産現物管理(分割処理) ⇒ 修正(追記) 8．固定資産台帳（随時）⇒ 追記 9．償却シミュレーション一覧（適宜）⇒ 追記 11．月次レポート（償却資産申告書作成）⇒ 修正(追記) 12．年次レポート(償却資産税情報出力（eLTAX)) ⇒ 追記 | AZ10: JBS大河原 | BE10: 1.3
A11: 45761 | F11: シート「固定資産管理」 | T11: 固定資産取得について、下記修正・追記 ・指図は生産部・研究部門、業務推進・財務にて登録 ・各部署、生産部・研究部門、業務推進・財務それぞれで取得処理を行い、最終確認は業務推進・財務で行う ・入力部署での1段階承認とし、業務推進・財務での最終確認は承認なし ・固定資産登録：少額資産・美術品について帳簿注意、財務分析コードの指定が必要 ・決済勘定へ振替（通常取得）：楽楽精算の処理は「支払」であり、貸方は一律で「未払金(設備)」となる ・振替金額の認識（建設仮勘定対応）：指図コードがない場合は財務タグで判別する | AZ11: JBS中村 | BE11: 1.4
A12: 45762 | F12: シート「固定資産管理」 | T12: 下記フロー修正・追記 ・3．固定資産現物管理（移動）：移動概要（固定資産の場所の移動）の追記 ・4．固定資産現物管理（売却・処分）：未収入金への振替を追記 ・5．固定資産現物管理（減損処理）：一般会計・決算フローとの繋がりを追記 ・11．月次レポート（償却資産申告書作成）：固定資産移動一覧の追記 | AZ12: JBS中村 | BE12: 1.5
A13: 45769 | F13: シート「固定資産管理」 | T13: 下記フロー修正・追記 下記フロー修正・追記 ・ヘッダ部：各部署と生産部・研究部門は同一フローとなるため、同一レーンとして記載 ・1-1．固定資産取得(通常取得)：建設仮勘定対応と同様、決済勘定へ振替→固定資産マスタ登録 の流れとする ・1．固定資産取得(通常取得・建設仮勘定対応)：振替金額の認識や決済勘定へ振替は各部門で行う ・1．固定資産取得(通常取得・建設仮勘定対応)：仕訳帳全体の取消は登録部署で行う ・3．固定資産現物管理（移動）：それぞれの資産の管理部署が移動処理を行う ・4．固定資産現物管理（売却・処分）：それぞれの資産の管理部署が売却・処分処理を行う ・4．固定資産現物管理（売却・処分）：各部門で承認を行い、最終確認は業務推進・財務で行う ・5．固定資産現物管理（減損処理）：減損処理の判断はシステム外となる（FO内での減損処理判断の記載削除） ・5．固定資産現物管理（減損処理）：業務推進・財務にて入力・承認を行う ・7．固定資産現物管理（圧縮記帳処理ー直接減額方式）：業務推進・財務にて入力・承認を行う ・11．年次レポート（償却資産申告書作成）：月次ではなく年次で出力となる | AZ13: JBS中村 | BE13: 1.6
A14: 45777 | F14: シート「固定資産管理」 | T14: 6．固定資産現物管理（分割処理）について、承認フローの追記 | AZ14: JBS中村 | BE14: 1.6
A15: 45779 | F15: シート「固定資産管理」 | T15: 下記フロー修正・追記 ・ヘッダ部：各部署を記載するレーンへ「山梨設備G」を追加 ・5．固定資産現物管理（減損処理）：機能制約条件の文言を削除 ・6．固定資産現物管理（分割処理）：全部署で処理を行うようフロー変更 ・８．固定資産台帳（随時）：全部署で使用するようフロー変更 | AZ15: JBS中村 | BE15: 1.6
A16: 45784 | F16: シート「固定資産管理」 | T16: 決算Gを追加。（※決算Gが固定資産計上することは、イレギュラー） | AZ16: JBS秋信 | BE16: 1.7
A17: 45786 | F17: シート「資産リース管理」 | T17: 結合テストのシナリオ作成の業務ヒアリングの結果を受け、全体的に見直しを実施。 | AZ17: JBS秋信 | BE17: 1.7
... A25: 45939 | F25: シート「固定資産管理」 | T25: ・13．固定資産の休止 新規作成 | AZ25: JBS中村 | BE25: 1.15

Sheet 凡例
A1: システム名 | F1: =変更履歴!F1 -> 会計システム刷新プロジェクト（LIBRA） | V1: タイトル | AJ1: 日付 | AQ1: 更新者
A2: 文書名 | F2: =変更履歴!F2 -> ToBe業務フロー（5.固定資産_リース） | V2: =MID(CELL("filename",$A$1),FIND("]",CELL("filename",$A$1))+1,31) -> #VALUE! | AJ2: 作成 | AL2: =変更履歴!AT2 -> 45362 | AQ2: =変更履歴!BA2 -> JBS大河原
AJ3: 更新 | AL3: =変更履歴!AT3 -> 45939 | AQ3: =変更履歴!BA3 -> JBS中村
A6: 凡例
H10: ： | I10: フローの開始 | AC10: ： | AD10: フローの終了
H15: ： | I15: システムを伴わない業務 | AC15: ： | AD15: システム上での業務
H20: ： | I20: 帳票（システムで作成される帳票） | AC20: ： | AD20: 帳票（システム外で作成される帳票）
H25: ： | I25: 業務の流れ | AC25: ： | AD25: システムへの連携
H30: ： | I30: 分岐 | AC30: ： | AD30: システム
H35: ： | I35: フロー間の繋がりを示す | AC35: ： | AD35: ファイル（CSVファイル等）
A40: 凡例
B43: 社内部署 | J43: ： | K43: フローに登場する社内の部署を記載
K44: 部署内の担当者が分かれる場合は以下の通りに分ける
B46: 社内部署
B47: 担当者 | I47: 責任者
B50: 外部担当者 | J50: ： | K50: フローに登場する社外担当者の部署を記載
K51: 例）得意先、仕入先
B54: システム | J54: ： | K54: フロー上で実施されるシステムの機能を記載する列
B55: XX | K55: XXの部分にフローで登場するシステム名を記載
K56: 例は以下の通り（JBSで導入するシステム外のものは「外部システム」で統一）
B58: システム
B59: FO | I59: CE | P59: 外部システム
B62: 説明 | S62: ： | T62: フロー内容を説明する列
B66: Gap （Add-On） | J66: ： | K66: フローに対してのGapを記載する列
B70: １．パターン１ | AI70: ： | AJ70: フローのパターンごとに記載する

Sheet 固定資産管理
A1: システム名 | F1: =変更履歴!F1 -> 会計システム刷新プロジェクト（LIBRA） | V1: タイトル | AJ1: 日付 | AQ1: 更新者
A2: 文書名 | F2: =変更履歴!F2 -> ToBe業務フロー（5.固定資産_リース） | V2: =MID(CELL("filename",$A$1),FIND("]",CELL("filename",$A$1))+1,31) -> #VALUE! | AJ2: 作成 | AL2: =変更履歴!AT2 -> 45362 | AQ2: =変更履歴!BA2 -> JBS大河原
AJ3: 更新 | AL3: =変更履歴!AT3 -> 45939 | AQ3: =変更履歴!BA3 -> JBS中村
A6: =RIGHT(CELL("filename",A1),LEN(CELL("filename",A1))-FIND("]",CELL("filename",A1))) -> #VALUE!
B8: 高槻設備G・徳島設備G・MC生産技術G・山梨設備G CH生産技術G・CH研究戦略G・購買G・ITDXG・総務G | P8: 事務管理G・決算G | AD8: システム | AR8: 説明 | BH8: Gap （Add-On） | BO8: 質問内容 | CE8: 回答
B10: 担当者 | I10: 責任者 | P10: 担当者 | W10: 責任者 | AD10: FO | AK10: 外部システム
B11: 1-1．固定資産取得(通常取得：購入と資産計上が同時期に実施される場合)
BO12: ・ | BP12: 固定資産登録を行うのは、下記グループでしょうか？ | CE12: →
AS13: ※固定資産番号の発番はFOにて行う | BP13: （仕訳帳名の作成単位となる）
AS14: ※標準承認フローは元帳転記の承認ワークフローが存在します。 | BQ14: - | BR14: 決算G承認 | BX14: … | BY14: 各部署？←こちらはどういう意味でしょうか？ | CK14: ⇒失礼しました。固定資産関連では不要Gでした。
BQ15: - | BR15: 高槻設備G | BX15: … | BY15: 各部署？生産部・研究部門
AS16: ※ | AT16: 決算Gが固定資産計上することは、イレギュラー | BQ16: - | BR16: 徳島設備G | BX16: … | BY16: 各部署？生産部・研究部門
BQ17: - | BR17: 山梨設備G | BX17: … | BY17: 生産部・研究部門
BQ18: - | BR18: MC生産技術G | BX18: … | BY18: 生産部・研究部門
BQ19: - | BR19: CH生産技術G | BX19: … | BY19: 生産部・研究部門
BQ20: - | BR20: CH研究戦略G | BX20: … | BY20: 生産部・研究部門
BQ21: - | BR21: 購買G | BX21: … | BY21: 各部署？生産部・研究部門
BQ22: - | BR22: ITDXG | BX22: … | BY22: 各部署？→はい
BQ23: - | BR23: 業務推進事務管理G | BX23: … | BY23: 業務推進・財務
BQ24: - | BR24: 総務G | BX24: … | BY24: 各部署？→はい
BP25: ⇒ | BQ25: 取得・承認を行うのは以下Gとなり、 | CE25: ⇒ | CF25: 現状は記載頂いた括りで合っております。
AS26: １．財務分析コード値の更新(指図番号の登録) | BQ26: 各括りの定義についても、認識合っておりますでしょうか？ | CF26: 今後追加で取得・承認する部署が発生した場合は
AT27: 財務分析コード値（プロジェクト：指図コード）の登録を行う。 | BQ27: - | BR27: 各部署 | BW27: ： | BX27: ITDXG・総務G | CF27: どのようにすればいいでしょうか。
AT28: ※ | AU28: 指図マスタ情報連携により、FOで登録された指図番号が | BQ28: - | BR28: 生産部・研究部門 | BW28: ： | BX28: 高槻設備G・徳島設備G・山梨設備Ｇ | CF28: ⇒ | CG28: 各種追加設定が必要となります。
AU29: 翌日以降に各外部システムへ連携される。 | BX29: ・MC生産技術G・CH生産技術G・CH研究戦略G・購買G | CG29: ① | CH29: ライセンス足りなければ追加購入（＋FOユーザー登録）
BQ30: - | BR30: 業務推進・財務 | BW30: ： | BX30: 業務推進事務管理G | CG30: ② | CH30: ユーザーグループ作成＋責任者ユーザー追加
CG31: ③ | CH31: WF定義作成＋承認ステップで追加ユーザーグループ指定
CG32: ④ | CH32: 仕訳帳名作成
CF33: ⇒②~④の追加設定は弊社で実施するのでしょうか？
AS34: 2．決済勘定へ振替 | BO34: ・ | BP34: 各部署からの指図申請は、業務推進・財務宛てとなり、 | CG34: ⇒ | CH34: 貴社作業となりますが、権限の兼ね合いでシステム管理者(ITDX？)が行う形となり、
AT35: 未払金を決済勘定へ振り替える。 | BP35: 業務推進・財務にて登録後、各部署へ登録完了連絡を | CH35: 現場の方々が行う作業にはならないかと思われます。
AT36: ※ | AU36: 楽々精算の処理は「支払」となり、 | BP36: 行う流れのイメージでしょうか？ | CE36: → | CF36: 指図コード登録は各部署にて行う
AU37: 会計伝票情報連携により、FO一般仕訳帳のデータとなる。
AU38: 仕訳例：建物決済勘定/未払金（設備） | BO38: ・ | BP38: 楽々精算での支払処理は、 | CE38: → | CF38: 支払処理は各部署(生産、研究、総務、ＩＴなど)にて行う
BP39: 業務推進・財務のみが行う形でしょうか？
BP41: ⇒ | BQ41: 指図コード登録＝財務分析コード値の更新 や支払処理も
BQ42: 各部署で行うとのことであれば、"各部署"と"生産部・研究部門"の
BQ43: 括りを分ける必要はない（業務フローは全て同じになる）
BQ44: という認識で合っていますでしょうか？ | CE44: ⇒基本同様のフローです。
AS45: 3．固定資産登録 | CF45: (現状の運用は、SSJ生産部以外は指図コード必須ではありません。)
AT46: 固定資産マスタに取得した固定資産を登録する。
AT47: ※ | AU47: 登録を行う全部署へFOのライセンスの付与が必要
AT48: ※ | AU48: 少額資産・美術品の場合は、紐づける帳簿注意。
AT49: ※ | AU49: 財務分析コードの指定必要。
AS53: 4．取得提案
AT54: 取得提案にてトランザクション(伝票)を作成する。
AS58: 5．取得承認申請
AT59: 入力担当者が責任者に申請する。
AS64: 6．取得の承認/変更依頼
AT65: 承認者にシステムとメール上で承認依頼通知がくる。
AS73: 7．不備修正
AT74: 変更依頼された固定資産仕訳帳の取得内容を
AT75: 確認し、不備の内容を修正する。
AT76: 修正後、取得承認申請を再度行う。
AS78: ８．自動転記バッチ
AT79: スケジュールされたバッチ処置により
AT80: 承認済の固定資産仕訳帳が自動転記処理される。
AT81: 4.で作成されたトランザクションを使用し転記、固定資産を
AT82: 取得(資産計上)させる。
AT83: ⇒ | AU83: 仮勘定対応かに限らず、
AU84: 取得することで、「建物/建物決済勘定」の振替仕訳が生成される
AT86: ex | AV86: 固定資産グループ | BB86: 主勘定(借方) | BH86: 相手勘定(貸方)
AW87: 機械装置 | BA87: 1310301:機械装置 | BG87: 1310804:機械装置決済勘定
AW88: 建物 | BA88: 1310101:建物 | BG88: 1310801:建物決済勘定
AT90: 自動振替の設定は固定資産転記プロファイルで行う
AT91: ※ | AU91: 決済勘定を使用するため、固定資産グループは分割しない。
AT93: ※固定資産グループ＝資産クラスと同義
BO95: ・ | BP95: 業務推進・財務での最終確認は | CE95: → | CF95: 通常、確認作業は登録(振替、除却など)した月度に行う
AS96: 9．取得内容確認 | BP96: どのような期間で行われますでしょうか？ | CF96: ※監査等で指摘があれば年度内での修正の可能性あり
AT97: 事務管理G以外で登録された取得内容について、 | BP97: （取消処理の兼ね合い）
AT98: 事務管理Gにて最終確認を行う。
AT99: ※ | AU99: 承認機能は介さず、レポート等での確認となる。 | BO99: ・「取得された固定資産」と「固定資産仕訳帳」が外部システムの欄に | CE99: → | CF99: 失礼いたしました。
BO100: 記載されていますがこちらはどういう意味でしょうか。 | CF100: FOでのデータになりますので、記載を修正しました。
BO101: FOではないということでしょうか。
AS105: 10．仕訳帳全体の取消
AT106: 事務管理Gにて不備が見つかった場合は
AT107: 入力担当者へ連絡し、登録部署にて仕訳帳全体の取消を行う。
AT108: ※ | AU108: 月次締め処理前の仕訳帳に対して取消が可能。
AT109: ※ | AU109: 取消を行うと未取得状態に戻り、取得提案より再度行う。
B122: 1-2．固定資産取得(建設仮勘定対応：購入と資産計上の時期にずれがある場合)
AS124: ※固定資産番号の発番はFOにて行う
AS125: ※標準承認フローは元帳転記の承認ワークフローが存在します。
AS134: １．財務分析コード値の更新(指図番号の登録)
AT135: 財務分析コード値（プロジェクト：指図コード）の登録を行う。
AT136: ※ | AU136: 指図マスタ情報連携により、FOで登録された指図番号が
AU137: 翌日以降に各外部システムへ連携される。
AS140: ２．建設仮勘定仕訳入力(毎月)
AT141: 建設仮勘定に割り当てる費用を計上する。
AT142: この時費用計上の伝票には指図コードを付与して計上する
AT143: ※ | AU143: 仕訳入力は楽々精算orBtoBで行い、
AU144: 会計伝票情報連携により、FO一般仕訳帳のデータとなる。
AU145: 仕訳例：建設仮勘定/未払金（設備）
AS152: 3．振替金額の認識
AT153: 決済勘定に累積された経費の
AT154: 総額を認識する。この金額を固定資産の取得額として登録する。 | BO154: ・ | BP154: 振替金額の認識～楽々精算での振替処理は、 | CE154: → | CF154: 生産部・研究部門、各部署(総務部、ITDX部)
AT155: 検索時はメインアカウント(勘定科目)＋財務分析コード(指図番号) | BP155: 業務推進・財務のみが行う形でしょうか？ | CF155: それぞれが行う
AT156: ※ | AU156: 指図コードがない場合は、指図番号が空白となり集約されるが、
AU157: 金額を押下することで財務タグ（社内稟議番号＝伺い番号）にて判別する。
AS159: 4．決済勘定へ振替
AT160: 建設仮勘定を決済勘定へ振り替える。
...

Sheet 資産リース管理_old
A1: システム名 | F1: =変更履歴!F1 -> 会計システム刷新プロジェクト（LIBRA） | V1: タイトル | AJ1: 日付 | AQ1: 更新者
A2: 文書名 | F2: =変更履歴!F2 -> ToBe業務フロー（5.固定資産_リース） | V2: =MID(CELL("filename",$A$1),FIND("]",CELL("filename",$A$1))+1,31) -> #VALUE! | AJ2: 作成 | AL2: =変更履歴!AT2 -> 45362 | AQ2: =変更履歴!BA2 -> JBS大河原
AJ3: 更新 | AL3: =変更履歴!AT3 -> 45939 | AQ3: =変更履歴!BA3 -> JBS中村
A6: =RIGHT(CELL("filename",A1),LEN(CELL("filename",A1))-FIND("]",CELL("filename",A1))) -> #VALUE! | BK6: 登録は社員サポートグループも実施しているため
BK7: 担当グループ追加が必要
B8: 各部署 | L8: 購買部 | S8: 財務(事務管理) | AG8: システム | AN8: 説明 | BD8: Gap （Add-On）
S9: 担当者 | Z9: 責任者／役員 | AG9: FO
B10: １．資産リース取得
BJ11: ・使用権資産は総務の賃貸借契約を基に更新登録している
AO12: ※再リースはFO管理対象外とする | BJ12: ・車両リースはリース会社から届く車両入替情報を基に更新している
BJ13: ・社宅は社員サポートグループが社宅の賃貸借契約を基に更新している
AO16: 1．自動引落申請書発行
AP17: 各部署は引落申請を行う
AO21: 2．自動引落申請書の受領
AP22: 各部署からの引落申請書を受領する
AO28: 3．リース資産登録
AP29: リース情報を登録する。
AP30: ※50万以下は少額資産リースとして登録（自動判定） | BJ30: 50万円以下、もしくは12か月以下の契約は登録しない
AP31: 12か月以下は短期リースとして登録（自動判定）
AO33: 判定条件
AP34: 300万円以上のリース資産の場合、 | BJ34: 「リース料総額」が300万円以上（税抜）の場合～に変更
AP35: 日本基準・IFRSで固定資産計上 | BJ35: 50万円以上300万円未満（税抜）の資産はIFRS帳簿のみ資産計上
AO38: 4．固定資産登録 | BJ38: 正：資産リース登録
AP39: 固定資産として計上する場合は、固定資産情報 | BJ39: リース資産として登録する場合は、リース資産マスタに情報登録する
AP40: を登録する。
AP41: 登録後、固定資産番号をリース情報に登録する
AO44: 5．支払スケジュールの作成
AP45: リース会社より提示された支払スケジュールを登録
AO50: 6．支払スケジュールの確認 | BJ50: 責任者の支払スケジュール確認は不要
AP51: 作成した支払スケジュールを確認（承認）する
BJ55: 不要
AO65: 7．支払スケジュールの確認
AP66: 初年度負債計上を押下後、資産リース仕訳にて
AP67: リース資産/負債を計上する
BJ69: 担当者が登録後に責任者が承認を行う
BJ70: 責任者は、承認時に4のマスタ登録と5の支払スケジュールも併せて確認
BJ71: した上で承認を行う
B75: 2．リース支払いスケジュールの計上・転記
BJ76: 資産リース取得の5と重複している
AO82: 1．仕訳帳の作成
AP83: 仕訳帳の作成機能にて仕訳帳番号を取得する
AO89: 2．承認処理
AP90: 作成された仕訳バッチ（請求仕訳帳）の承認をおこなう
AO96: 3．転記処理
AP97: 作成された仕訳バッチ（請求仕訳帳）の転記処理を行う
B106: 3．リース資産の負債償却スケジュールの作成・転記
AO113: 1．仕訳帳の作成
AP114: 仕訳帳の作成機能にて仕訳帳番号を取得する
AO118: 2．転記処理
AP119: 生成された負債償却仕訳データを転記する。
B126: 4．リース資産の経費スケジュールの作成・転記⇒業務対象外
AO128: ※リースにかかわる費用についてはFOで計上しないとのこと⇒不要
B130: ５．リース資産現物管理（減価償却）
AO137: 1．仕訳帳の作成
AP138: 仕訳帳の作成機能にて仕訳帳番号を取得する
AO143: 2．転記処理
AP144: 生成された資産減価償却仕訳データを転記する。
AO146: ※固定資産と連携した資産リースについては固定資産機能にて
AO147: 減価償却処理が実行され資産リース側では実施できないので注意が必要
B151: 6．短期リース負債の再分類⇒業務対象外
AO153: ※長短期組替え：楽々清算にて実施のため不要
B155: 7．リース資産終了（解約・契約満了時）
AO162: 1．終了提案
AP163: リース終了トランザクションを作成する
AO168: 2．リース終了
AP169: リース終了トランザクションを実行し終了を転記する。

Sheet 資産リース管理_old20250730
A1: システム名 | F1: =変更履歴!F1 -> 会計システム刷新プロジェクト（LIBRA） | AC1: タイトル | AQ1: 日付 | AX1: 更新者
A2: 文書名 | F2: =変更履歴!F2 -> ToBe業務フロー（5.固定資産_リース） | AC2: =MID(CELL("filename",$A$1),FIND("]",CELL("filename",$A$1))+1,31) -> #VALUE! | AQ2: 作成 | AS2: =変更履歴!AT2 -> 45362 | AX2: =変更履歴!BA2 -> JBS大河原
AQ3: 更新 | AS3: =変更履歴!AT3 -> 45939 | AX3: =変更履歴!BA3 -> JBS中村
A6: =RIGHT(CELL("filename",A1),LEN(CELL("filename",A1))-FIND("]",CELL("filename",A1))) -> #VALUE!
B8: 各部署 | L8: 社員サポートG | Z8: 事務管理G | AN8: システム | AU8: 説明 | BK8: Gap （Add-On）
L9: 担当者 | S9: 責任者／役員 | Z9: 担当者 | AG9: 責任者／役員 | AN9: FO
B10: １．資産リース取得
AV12: ※再リースはFO管理対象外とする
AV14: ・使用権資産は総務の賃貸借契約を基に更新登録している
AV15: ・車両リースはリース会社から届く車両入替情報を基に更新している
AV16: ・社宅は社員サポートグループが社宅の賃貸借契約を基に更新している
AV19: 1．自動引落申請書発行
AW20: 各部署は引落申請を行う
AV24: 2．自動引落申請書の受領
AW25: 各部署からの引落申請書を受領する
AV31: 3．リース資産登録
AW32: リース情報を登録する。
AV37: 4．リースに紐づく帳簿の作成
AW38: 登録したリースに帳簿を作成する。
AV43: 支払リース料総額（税抜）が300万円以上かどうかで判断
AV44: 社員サポートGは使用権資産のみ登録
AV50: 5．不要な帳簿の削除
AW51: ファイナンスリースにおいて、300万未満のリースで
AW52: 不要な帳簿（会社会計、税務）の削除を行う。
AV59: 6．支払スケジュール確定処理
AW60: 確認バッチを使用して、登録したリースの支払スケジュール
AW61: の確定処理を行う。
AV66: 7．初期認識
AW67: 初期認識を行い、リース資産計上の仕訳登録を行う。
AW68: ※ | AX68: スケジュールの選択：初期認識
AW69: ※ | AX69: 転記：いいえ を選択
AV73: 8．リース資産計上仕訳の承認依頼
AW74: 作成されたリース資産計上の仕訳の承認依頼を行う。
AW75: ※ | AX75: 各帳簿ごとに承認依頼作業を行う。
AV82: 9．リース資産計上仕訳の承認
AW83: 責任者は作成されたリース資産計上の仕訳の承認を行う。
AW84: 責任者はマスタ登録も併せて内容確認した上で承認を行う
AW85: ※ | AX85: 各帳簿ごとに承認作業を行う。
AW86: 【仕訳例】
AW87: リース資産 | BA87: リース債務(固定)
AW88: ※ | AX88: 転記処理は自動転記バッチ(アドオン)で処理
AV95: 10．レポート内容確認
AW96: リース資産台帳、リース利息一覧で
AW97: 登録されたリース内容を確認する。
B108: 2．リース支払いスケジュールの計上・転記
AV116: 1．支払仕訳の作成・転記
AW117: バッチ仕訳の作成を使用し、支払スケジュールに
AW118: 登録されている支払仕訳の作成・転記を行う。
AW119: ※ | AX119: スケジュールの選択：支払スケジュール
AW120: ※ | AX120: 転記：はい を選択
AW121: 【仕訳例】
AW122: リース債務(固定) | BB122: 未払金(リース料)
AW124: ※ | AX124: 以下リースについては、経費スケジュールを使用して、
AX125: 未払金(リース料)から賃借料への振替作業を
AX126: 実施する。
AX127: ・300万円未満のファイナンスリース
AX128: ・オペレーティングリース
AX129: ・IFRS使用権資産
B131: 3．リース資産の負債償却スケジュールの作成・転記
AV138: 1．利息計上仕訳の作成・転記
AW139: バッチ仕訳の作成を使用し、負債償却スケジュールに
AW140: 登録されている利息計上仕訳の作成・転記を行う。
AW141: ※ | AX141: スケジュールの選択：負債償却スケジュール
AW142: ※ | AX142: 転記：はい を選択
AW143: 【仕訳例】
AW144: 支払利息(リース資産) | BC144: リース債務(固定)
B151: 4．リース資産の経費スケジュールの作成・転記
AV158: 1．振替仕訳の作成・転記
AW159: バッチ仕訳の作成を使用し、以下対象のリースは
AW160: 経費スケジュールに登録されている仕訳の作成・転記を
AW161: 行う。
AW162: ・300万円未満のファイナンスリース
AW163: ・オペレーティングリース
AW164: ・IFRS使用権資産
AW165: ※ | AX165: スケジュールの選択：経費スケジュール
AW166: ※ | AX166: 経費タイプ：リースに登録されている経費タイプ
AW167: ※ | AX167: 転記：はい を選択
AW168: 【仕訳例】
AW169: 未払金(リース料) | BB169: 賃借料
B174: ５．リース資産現物管理（減価償却）
AV182: 1．減価償却計上仕訳の作成・転記
AW183: バッチ仕訳の作成を使用し、資産減価償却スケジュールに
AW184: 登録されている減価償却計上仕訳の作成・転記を行う。
AW185: ※ | AX185: スケジュールの選択：資産減価償却スケジュール
AW186: ※ | AX186: 転記：はい を選択
AW187: 【仕訳例】
AW188: 減価償却費 | BB188: 減価償却累計額
B196: 6．短期リース負債の再分類
AV203: 1．長短振替登録
AW204: 決算時に、一般仕訳帳を使用して、
AW205: リース債務の長期から短期への振替処理を行う。
AW206: ※ | AX206: 各転記階層各帳簿（日本会計、IFRS）ごとに
AX207: 作業を行う。
AV209: 2．長短振替仕訳承認依頼
AW210: 上記で登録した仕訳の承認依頼を行う。
AW211: ※ | AX211: 各転記階層各帳簿（日本会計、IFRS）ごとに
AX212: 作業を行う。
AV216: 3．長短振替仕訳承認
AW217: 長短振替仕訳の承認を行う。
AW218: ※ | AX218: 各転記階層各帳簿（日本会計、IFRS）ごとに
...

Sheet 資産リース管理
A1: システム名 | F1: =変更履歴!F1 -> 会計システム刷新プロジェクト（LIBRA） | V1: タイトル | AJ1: 日付 | AQ1: 更新者
A2: 文書名 | F2: =変更履歴!F2 -> ToBe業務フロー（5.固定資産_リース） | V2: =MID(CELL("filename",$A$1),FIND("]",CELL("filename",$A$1))+1,31) -> #VALUE! | AJ2: 作成 | AL2: =変更履歴!AT2 -> 45362 | AQ2: =変更履歴!BA2 -> JBS大河原
AJ3: 更新 | AL3: =変更履歴!AT3 -> 45939 | AQ3: =変更履歴!BA3 -> JBS中村
A6: =RIGHT(CELL("filename",A1),LEN(CELL("filename",A1))-FIND("]",CELL("filename",A1))) -> #VALUE!
B8: 各部署 | L8: 社員サポートG | Z8: 事務管理G | AN8: ITDX | AU8: システム | BB8: 説明 | BR8: Gap （Add-On）
L9: 担当者 | S9: 責任者 | Z9: 担当者 | AG9: 責任者 | AU9: FO
B10: １．資産リース取得
BC12: ※再リースはFO管理対象外とする
BC14: ・使用権資産は総務の賃貸借契約を基に更新登録している
BC15: ・車両リースはリース会社から届く車両入替情報を基に更新している
BC16: ・社宅は社員サポートグループが社宅の賃貸借契約を基に更新している
BC18: ※2027年以降の新会計基準での対応検討が必要
BC22: 1．自動引落申請書発行
BD23: 各部署は引落申請を行う
BC27: 2．自動引落申請書の受領
BD28: 各部署からの引落申請書を受領する
BC34: 3．リース資産登録
BD35: リース情報を登録する。
BC40: 4．リースに紐づく帳簿の作成
BD41: 登録したリースに帳簿を作成する。
BC46: 支払リース料総額（税抜）が300万円以上かどうかで判断
BC47: 社員サポートGは使用権資産のみ登録
BC53: 5．不要な帳簿の削除
BD54: ファイナンスリースにおいて、300万未満のリースで
BD55: 不要な帳簿（会社会計、税務）の削除を行う。
BC62: ６．消費税額の登録
BD63: 300万以上ファイナンスリースは、リース債務を
BD64: 税込みで登録を行う。
BD65: リース資産には、消費税を含めないために、
BD66: リースインセンティブ項目を使用して、消費税金額分
BD67: 控除するよう登録を行う。
BD68: ※300万円以上のファイナンスリースは税込の
BD69: 月額リース料、見積購入価格を基に利率を算出
BC71: ７．支払スケジュール確定処理
BD72: 確認バッチを使用して、登録したリースの支払スケジュール
BD73: の確定処理を行う。
BC78: ８．初期認識
BD79: 初期認識を行い、リース資産計上の仕訳登録を行う。
BD80: ※ | BE80: スケジュールの選択：初期認識
BD81: ※ | BE81: 転記：いいえ を選択
BC85: ９．リース資産計上仕訳の承認依頼
BD86: 作成されたリース資産計上の仕訳の承認依頼を行う。
BD87: ※ | BE87: 各帳簿ごとに承認依頼作業を行う。
BC94: １０．リース資産計上仕訳の承認
BD95: 責任者は作成されたリース資産計上の仕訳の承認を行う。
BD96: 責任者はマスタ登録も併せて内容確認した上で承認を行う
BD97: ※ | BE97: 各帳簿ごとに承認作業を行う。
BC103: 11．自動転記バッチ
BD104: スケジュールされたバッチ処理により
BD105: 承認済の資産リース仕訳が自動転記処理される
BD106: 【仕訳例】
BD107: リース資産 | BH107: リース債務(固定)
BD108: ※ | BE108: 300万以上のファイナンスリース
BE109: 転記階層：日本会計、税申告、IFRS
BD110: ※ | BE110: 300万未満のファイナンスリース、
BE111: オペレーティングリース、レンタル、少額、IFRS使用権資産
BE112: 転記階層：IFRS
BD114: 【300万以上ファイナンスリースのみ発生】
BD115: 【仕訳例】
BD116: 未払金（リース料） | BJ116: リース債務(固定)
BD117: ※ | BE117: リースインセンティブ項目
BD118: ※ | BE118: 転記階層：日本会計、税申告、IFRS
BC122: １２．消費税振替登録
BD123: １０で発生した未払金を仮払消費税への
BD124: 振替登録を行う。
BC128: １３．承認
BD129: 事務管理G責任者が該当する仕訳帳の内容を
BD130: 確認し、一般仕訳帳（承認）画面から、承認を行う。
BC133: 1４．自動転記バッチ
BD134: スケジュールされたバッチ処理により
BD135: 承認済の一般仕訳帳が自動転記処理される
BD137: 【300万以上ファイナンスリースのみ登録】
BD138: 【仕訳例】
BD139: 仮払消費税 | BH139: 未払金（リース料）
BD140: ※ | BE140: 転記階層：日本会計、税申告、IFRS
BC143: 1５．レポート内容確認
BD144: リース資産台帳、リース利息一覧で
BD145: 登録されたリース内容を確認する。
B156: 2．リース支払いスケジュールの計上・転記
BC161: 1．支払仕訳の作成・転記
BD162: バッチ仕訳の作成を使用し、支払スケジュールに
BD163: 登録されている支払仕訳の作成・転記を行う。
BD164: ※ | BE164: スケジュールの選択：支払スケジュール
BD165: ※ | BE165: 転記：はい を選択
BD166: 【仕訳例】
BD167: リース債務(固定) | BI167: 未払金(リース料)
BD168: ※ | BE168: 300万以上のファイナンスリース
BE169: 転記階層：日本会計、税申告、IFRS
BD170: ※ | BE170: 300万未満のファイナンスリース、
BE171: オペレーティングリース、レンタル、少額、IFRS使用権資産
BE172: 転記階層：IFRS
BD174: ※ | BE174: 以下リースについては、一般仕訳帳アップロードを使用して、
BE175: 未払金(リース料)から賃借料への振替作業を
BE176: 実施する。
BE177: ・300万円未満のファイナンスリース
BE178: ・オペレーティングリース
BE179: ・レンタル
BE180: ・少額
BE181: ・IFRS使用権資産
B185: 3．リース資産の負債償却スケジュールの作成・転記
...

Sheet 資産リース管理 (JBS整理中)_0509
A1: システム名 | F1: =変更履歴!F1 -> 会計システム刷新プロジェクト（LIBRA） | AC1: タイトル | AQ1: 日付 | AX1: 更新者
A2: 文書名 | F2: =変更履歴!F2 -> ToBe業務フロー（5.固定資産_リース） | AC2: =MID(CELL("filename",$A$1),FIND("]",CELL("filename",$A$1))+1,31) -> #VALUE! | AQ2: 作成 | AS2: =変更履歴!AT2 -> 45362 | AX2: =変更履歴!BA2 -> JBS大河原
AQ3: 更新 | AS3: =変更履歴!AT3 -> 45939 | AX3: =変更履歴!BA3 -> JBS中村
A6: =RIGHT(CELL("filename",A1),LEN(CELL("filename",A1))-FIND("]",CELL("filename",A1))) -> #VALUE!
BQ7: 登録は社員サポートグループも実施しているため
B8: 各部署 | L8: 社員サポートG | Z8: 事務管理G | AN8: システム | AU8: 説明 | BK8: Gap （Add-On） | BQ8: 担当グループ追加が必要
L9: 担当者 | S9: 責任者／役員 | Z9: 担当者 | AG9: 責任者／役員 | AN9: FO | BQ9: ⇒JBS：スイムレーンを追加しました。
B10: １．資産リース取得
BQ11: ・使用権資産は総務の賃貸借契約を基に更新登録している
AV12: ※再リースはFO管理対象外とする | BQ12: ・車両リースはリース会社から届く車両入替情報を基に更新している
BQ13: ・社宅は社員サポートグループが社宅の賃貸借契約を基に更新している
AV16: 1．自動引落申請書発行
AW17: 各部署は引落申請を行う
AV21: 2．自動引落申請書の受領
AW22: 各部署からの引落申請書を受領する
AV28: 3．リース資産登録
AW29: リース情報を登録する。
AV34: 4．リースに紐づく帳簿の作成
AW35: 登録したリースに帳簿を作成する。
BQ39: 支払リース料総額（税抜）が300万円以上かどうかで判断
BQ41: 社員サポートGは使用権資産のみ登録のためファイナンスリース
BQ42: は登録しないため300万円の判定は不要
AV47: 5．不要な帳簿の削除
AW48: ファイナンスリースにおいて、300万未満のリースで | BQ48: IFRS帳簿のみ登録のため、会社会計、税務は登録不要
AW49: 不要な帳簿（会社会計、税務）の削除を行う。
AV56: 6．支払スケジュール確定処理
AW57: 確認バッチを使用して、登録したリースの支払スケジュール
AW58: の確定処理を行う。
AV63: 7．初期認識
AW64: 初期認識を行い、リース資産計上の仕訳登録を行う。
AW65: ※ | AX65: スケジュールの選択：初期認識
AW66: ※ | AX66: 転記：いいえ を選択
AV70: 8．リース資産計上仕訳の承認依頼
AW71: 作成されたリース資産計上の仕訳の承認依頼を行う。
AW72: ※ | AX72: 各帳簿ごとに承認依頼作業を行う。
AV79: 9．リース資産計上仕訳の承認 | BQ79: 担当者が登録後に責任者が承認を行う
AW80: 作成されたリース資産計上の仕訳の承認を行う。 | BQ80: 責任者は、承認時に5のマスタ登録も併せて内容確認した上で承認を行う
AW81: ※ | AX81: 各帳簿ごとに承認作業を行う。
AW82: 【仕訳例】
AW83: リース資産 | BA83: リース債務(固定)
AW84: ※ | AX84: 転記処理は自動転記バッチ(アドオン)で処理
B97: 2．リース支払いスケジュールの計上・転記
AV105: 1．支払仕訳の作成・転記
AW106: バッチ仕訳の作成を使用し、支払スケジュールに | BQ106: この作業は１.資産リース取得には入らずに別作業になりますか？
AW107: 登録されている支払仕訳の作成・転記を行う。 | BQ107: ⇒JBS：社員サポートGも業務を実施しますでしょうか？
AW108: ※ | AX108: スケジュールの選択：支払スケジュール | BQ108: →資産登録時に行う作業と認識しているため社員サポートG
AW109: ※ | AX109: 転記：はい を選択 | BQ109: も行う想定でおります。
AW110: 【仕訳例】 | BQ110: この作業は１.資産リース取得には入らずに別作業になりますか？
AW111: リース債務(固定) | BB111: 未払金(リース料) | BQ111: ⇒別途チャットで回答しておりますが、バッチ仕訳の作成の業務は必要になります。
BQ112: ここをすべて自動化にするには、開発が必要になってきますので、ご検討のほどよろしくお願いいたします。
AW113: ※ | AX113: 以下リースについては、経費スケジュールを使用して、 | BQ113: 対象を空欄等リースを1つずつ選択しない運用であれば、業務付加は少ないと考えております。
AX114: 未払金(リース料)から賃借料への振替作業を
AX115: 実施する。
AX116: ・300万円未満のファイナンスリース
AX117: ・オペレーティングリース
AX118: ・IFRS使用権資産
B120: 3．リース資産の負債償却スケジュールの作成・転記
BQ124: 月次転記は承認不要
BQ125: ⇒JBS：社員サポートGも業務を実施しますでしょうか？
BQ126: →実施しません
AV127: 1．利息計上仕訳の作成・転記
AW128: バッチ仕訳の作成を使用し、負債償却スケジュールに
AW129: 登録されている利息計上仕訳の作成・転記を行う。
AW130: ※ | AX130: スケジュールの選択：負債償却スケジュール
AW131: ※ | AX131: 転記：はい を選択
AW132: 【仕訳例】
AW133: 支払利息(リース資産) | BC133: リース債務(固定)
B140: 4．リース資産の経費スケジュールの作成・転記
AV147: 1．振替仕訳の作成・転記 | BQ147: 月次転記は承認不要
AW148: バッチ仕訳の作成を使用し、以下対象のリースは | BQ148: ⇒JBS：社員サポートGも業務を実施しますでしょうか？
AW149: 経費スケジュールに登録されている仕訳の作成・転記を | BQ149: →実施しません
AW150: 行う。
AW151: ・300万円未満のファイナンスリース
AW152: ・オペレーティングリース
AW153: ・IFRS使用権資産
AW154: ※ | AX154: スケジュールの選択：経費スケジュール
AW155: ※ | AX155: 経費タイプ：リースに登録されている経費タイプ
AW156: ※ | AX156: 転記：はい を選択
AW157: 【仕訳例】 | BQ157: この仕訳が計上される資産の区別（マスタにフラグを立てるなど）方法を
AW158: 未払金(リース料) | BB158: 賃借料 | BQ158: もう一度お伺いさせてください
BQ159: ⇒JBS：フラグが必要な意図を教えてください。
BR160: バッチ仕訳の作成では、経費タイプが登録されていなければ、仕訳対象外です。
BR161: （空欄にして全件にしても、経費タイプが登録されているものが仕訳作成される。）
BQ162: →下記のとおり理解しました。
B163: ５．リース資産現物管理（減価償却） | BQ163: 資産マスタの経費タイプが空欄…仕訳対象外
BQ164: 資産マスタの経費タイプに入力あり…仕訳対象
BQ165: 経費タイプはマスタ画面の入力項目かと思いますが、空欄にした場合、他への
BQ166: 影響はございますでしょうか
BQ167: ⇒JBS：影響はない理解でおります。
AV171: 1．減価償却計上仕訳の作成・転記 | BQ171: 月次転記は承認不要
AW172: バッチ仕訳の作成を使用し、資産減価償却スケジュールに | BQ172: ⇒JBS：社員サポートGも業務を実施しますでしょうか？
AW173: 登録されている減価償却計上仕訳の作成・転記を行う。 | BQ173: →実施しません
AW174: ※ | AX174: スケジュールの選択：資産減価償却スケジュール
AW175: ※ | AX175: 転記：はい を選択
AW176: 【仕訳例】
AW177: 減価償却費 | BB177: 減価償却累計額
B185: 6．短期リース負債の再分類
BQ191: ⇒JBS：社員サポートGも業務を実施しますでしょうか？
AV192: 1．長短振替登録 | BQ192: →実施しません
AW193: 決算時に、一般仕訳帳を使用して、
...
