Workbook
Name Page: #REF!
Name スコープ: マスタ!$B$18:$B$19
Name 開発: マスタ!$B$14:$B$15
Name 確認結果: マスタ!#REF!
Name 対象システム: マスタ!$B$8:$B$11
Name 優先度: マスタ!$B$2:$B$5
Name 要件区分: マスタ!#REF!

Sheet 要求事項
C1: 要求事項一覧
D2: ※１行には１要件としてください。複数要件がある場合は行を分けて記載お願いいたします。 | G2: ※追加 | K2: ※追加 | P2: ※追加
E3: 要求事項入力欄 | L3: 要求事項詳細内容確認 | N3: 要求事項内容整理 | T3: 確認欄 | V3: PMO記入欄 | Z3: 提案時
B4: 結合キー | D4: No. | E4: 要求事項 | F4: 現行業務 | G4: 業務要件回答表からの事前回答案_v1.0.xlsxより | H4: 要求者 | I4: 優先度 | J4: 対象部門 | K4: 確認先 | L4: 確認事項 | M4: 回答 | N4: 関連Req | O4: 対象システム | P4: ファイル名 | Q4: 対象業務フロー | R4: 開発 | S4: 実現案 | T4: スコープ | U4: 備考 | V4: 審査対象 | W4: コメント | X4: 列1 | Y4: 要求事項一覧 判定 | Z4: システム対応可否 | AA4: 会計システム標準機能以外の場合、実現方法詳細 | AB4: 列2 | AC4: 列3
A5: =テーブル1[[#This Row],[対象部門]]&テーブル1[[#This Row],[業務要件回答表からの事前回答案_v1.0.xlsxより]] -> 一般会計全般・決算1.1 | B5: 一般会計全般・決算1.1 | D5: Req001 | E5: 画面入力で仕訳伝票を登録できること (勘定科目を変更せず、仕訳の入力項目の修正のための振替伝票も起票可能であること) ⇒()内の記述は、登録ミスした仕訳伝票の訂正伝票の登録方法に関する記述 | F5: 仕訳伝票の登録機能 | G5: 1.1 | H5: サンスター | J5: 一般会計全般・決算 | K5: 決算G | O5: FO | Q5: 日次振伝処理 | R5: 不要 | S5: 一般仕訳帳入力で仕訳伝票の登録が可能 伝票テンプレート機能や定期伝票仕訳帳の機能あり。 登録ミスした伝票を「取消」ボタンで逆仕訳を作成する機能や、登録済伝票を呼び出して新規伝票として編集転記する機能などあり。 | T5: IN | X5: =テーブル1[[#This Row],[開発]]&テーブル1[[#This Row],[スコープ]] -> 不要IN | Y5: =IF(テーブル1[[#This Row],[列1]]="不要IN","標準",IF(テーブル1[[#This Row],[列1]]="不要OUT","スコープアウト",IF(テーブル1[[#This Row],[列1]]="必要IN","アドオン",IF(テーブル1[[#This Row],[列1]]="OUT","スコープアウト","")))) -> 標準 | Z5: =VLOOKUP($B5,Sheet1!$C$2:$L$315,9,) -> 会計システム標準機能 | AA5: =VLOOKUP($B5,Sheet1!$C$2:$L$315,10,) -> 0 | AB5: 標準 | AC5: =テーブル1[[#This Row],[要求事項一覧 判定]]=テーブル1[[#This Row],[列2]] -> TRUE
A6: =テーブル1[[#This Row],[対象部門]]&テーブル1[[#This Row],[業務要件回答表からの事前回答案_v1.0.xlsxより]] -> 一般会計全般・決算1.2 | B6: 一般会計全般・決算1.2 | D6: Req002 | E6: 多通貨で仕訳伝票が登録でき、入力通貨金額が報告通貨金額（邦貨）に換算した額も登録できること | F6: 多通貨の仕訳伝票の登録機能 | G6: 1.2 | H6: サンスター | J6: 一般会計全般・決算 | K6: 共通 | O6: FO | Q6: 日次振伝処理 | R6: 不要 | S6: 他通貨での伝票登録可能。仕訳トランザクションでは、入力通貨金額と報告通貨金額（邦貨）に換算した額を保持している。 | T6: IN | X6: =テーブル1[[#This Row],[開発]]&テーブル1[[#This Row],[スコープ]] -> 不要IN | Y6: =IF(テーブル1[[#This Row],[列1]]="不要IN","標準",IF(テーブル1[[#This Row],[列1]]="不要OUT","スコープアウト",IF(テーブル1[[#This Row],[列1]]="必要IN","アドオン",IF(テーブル1[[#This Row],[列1]]="OUT","スコープアウト","")))) -> 標準 | Z6: =VLOOKUP($B6,Sheet1!$C$2:$L$315,9,) -> 会計システム標準機能 | AA6: =VLOOKUP($B6,Sheet1!$C$2:$L$315,10,) -> 0 | AB6: 標準 | AC6: =テーブル1[[#This Row],[要求事項一覧 判定]]=テーブル1[[#This Row],[列2]] -> TRUE
A7: =テーブル1[[#This Row],[対象部門]]&テーブル1[[#This Row],[業務要件回答表からの事前回答案_v1.0.xlsxより]] -> 一般会計全般・決算1.3 | B7: 一般会計全般・決算1.3 | C7: ◎ | D7: Req003 | E7: Excelフォーマット（取引先、取引内容、部門、消費税区分、金額、伝票日付、相手科目等）のアップロード機能で仕訳作成できること ※機能通貨への換算、消費税明細計上(内税/外税)、為替差損益明細計上への対応、および相互通貨バランスチェック、最新データの取得が可能であること | F7: 仕訳アップロード機能で仕訳を作成する機能 | G7: 1.3 | H7: サンスター | J7: 一般会計全般・決算 | K7: 事務管理G | L7: 現在、SAPのEXCELバッチインプット機能は使用していますか？ | M7: 現状SAPのEXCELバッチ取込は使用していないため、新システムのやり方に合わせられるのではないか？ 大量の仕訳データの改善・検討については事務管理Gが検討（武市） | O7: FO | Q7: 日次振伝処理 | R7: 必要 | S7: ExcelアドインでExcelフォーマットでの伝票登録機能があるが、毎回仕訳帳画面からExcelフォーマットをダウンロードしてフォーマットにデータ貼り付けをして取り込むイメージのため、あらかじめ作成しておいたExcelをそのまま取り込むイメージとは少し異なる。財務分析コードの入力欄が個別にはなく、科目欄に科目コードとハイフン(-)つなぎで入力する方式のため注意が必要 ※会社間立替金で使用する想定。会社間も考慮する必要あり | T7: IN | V7: 〇 | W7: 標準のExcelアドインでのオペレーションでどれだけ不便があるか、実務でのシチュエーションと照らし合わせて要確認。 | X7: =テーブル1[[#This Row],[開発]]&テーブル1[[#This Row],[スコープ]] -> 必要IN | Y7: =IF(テーブル1[[#This Row],[列1]]="不要IN","標準",IF(テーブル1[[#This Row],[列1]]="不要OUT","スコープアウト",IF(テーブル1[[#This Row],[列1]]="必要IN","アドオン",IF(テーブル1[[#This Row],[列1]]="OUT","スコープアウト","")))) -> アドオン | Z7: =VLOOKUP($B7,Sheet1!$C$2:$L$315,9,) -> 会計システム標準機能 | AA7: =VLOOKUP($B7,Sheet1!$C$2:$L$315,10,) -> 0 | AB7: 標準 | AC7: =テーブル1[[#This Row],[要求事項一覧 判定]]=テーブル1[[#This Row],[列2]] -> FALSE
A8: =テーブル1[[#This Row],[対象部門]]&テーブル1[[#This Row],[業務要件回答表からの事前回答案_v1.0.xlsxより]] -> 一般会計全般・決算1.4 | B8: 一般会計全般・決算1.4 | C8: ◎ | D8: Req004 | E8: 勘定科目別に入力条件が設定でき、条件外の場合はエラーアラートが表示できること ⇒例えば経費科目であれば経費発生部門(原価センタ)の入力が必須になるなど、勘定科目の種類に応じて入力の必須・任意(入力フィールドの表示・非表示)をコントロールする機能のイメージです。(SAPでは項目ステータスと呼ばれる機能に該当します。) | F8: 勘定科目別に入力条件を指定する機能 | G8: 1.4 | H8: サンスター | J8: 一般会計全般・決算 | K8: 決算G | O8: FO | Q8: 日次振伝処理 | R8: 不要 | S8: 勘定構造のコンフィグレーションという機能で、勘定科目別に入力させる財務分析コードを制御することが可能。 | T8: IN | X8: =テーブル1[[#This Row],[開発]]&テーブル1[[#This Row],[スコープ]] -> 不要IN | Y8: =IF(テーブル1[[#This Row],[列1]]="不要IN","標準",IF(テーブル1[[#This Row],[列1]]="不要OUT","スコープアウト",IF(テーブル1[[#This Row],[列1]]="必要IN","アドオン",IF(テーブル1[[#This Row],[列1]]="OUT","スコープアウト","")))) -> 標準 | Z8: =VLOOKUP($B8,Sheet1!$C$2:$L$315,9,) -> 会計システム標準機能 | AA8: =VLOOKUP($B8,Sheet1!$C$2:$L$315,10,) -> 0 | AB8: 標準 | AC8: =テーブル1[[#This Row],[要求事項一覧 判定]]=テーブル1[[#This Row],[列2]] -> TRUE
A9: =テーブル1[[#This Row],[対象部門]]&テーブル1[[#This Row],[業務要件回答表からの事前回答案_v1.0.xlsxより]] -> 一般会計全般・決算1.5 | B9: 一般会計全般・決算1.5 | C9: ◎ | D9: Req005 | E9: 複数の仕訳をまとめて仕訳アップロード機能で作成することができること | F9: 複数仕訳を同時で起票できる機能 | G9: 1.5 | H9: サンスター | J9: 一般会計全般・決算 | K9: 決算G/事務管理G | M9: 大量の仕訳データの改善・検討については事務管理Gが検討（武市） | O9: FO | Q9: 日次振伝処理 | R9: 不要 | S9: Excelアドインで１仕訳内に複数伝票を登録可能。 | T9: IN | X9: =テーブル1[[#This Row],[開発]]&テーブル1[[#This Row],[スコープ]] -> 不要IN | Y9: =IF(テーブル1[[#This Row],[列1]]="不要IN","標準",IF(テーブル1[[#This Row],[列1]]="不要OUT","スコープアウト",IF(テーブル1[[#This Row],[列1]]="必要IN","アドオン",IF(テーブル1[[#This Row],[列1]]="OUT","スコープアウト","")))) -> 標準 | Z9: =VLOOKUP($B9,Sheet1!$C$2:$L$315,9,) -> 会計システム標準機能 | AA9: =VLOOKUP($B9,Sheet1!$C$2:$L$315,10,) -> 0 | AB9: 標準 | AC9: =テーブル1[[#This Row],[要求事項一覧 判定]]=テーブル1[[#This Row],[列2]] -> TRUE
A10: =テーブル1[[#This Row],[対象部門]]&テーブル1[[#This Row],[業務要件回答表からの事前回答案_v1.0.xlsxより]] -> 一般会計全般・決算1.6 | B10: 一般会計全般・決算1.6 | C10: ◎ | D10: Req006 | E10: 転記済みの仕訳をコピーして登録できること | F10: 転記済みの仕訳をコピーして一部内容を修正することで新たな仕訳として登録できる機能 | G10: 1.6 | H10: サンスター | J10: 一般会計全般・決算 | K10: 決算G | L10: 「元帳トランザクションの呼び出し」があるが、元帳タイプどうしの仕訳パターン以外のケースが対応していない。 | M10: 20240326 保留 コピー不可パターンを確認して判断 | O10: FO | Q10: 日次振伝処理 | R10: 不要 | S10: 「元帳トランザクションの呼び出し」という機能で転記済伝票を呼び出し修正して新規仕訳として登録する機能があるが、「勘定タイプ＝元帳」のみの伝票しか対象とならない。「勘定タイプ＝銀行/顧客/仕入先/固定資産」などの伝票は対応不可。 ⇒実務上は標準機能利用で対応可 | T10: IN | X10: =テーブル1[[#This Row],[開発]]&テーブル1[[#This Row],[スコープ]] -> 不要IN | Y10: =IF(テーブル1[[#This Row],[列1]]="不要IN","標準",IF(テーブル1[[#This Row],[列1]]="不要OUT","スコープアウト",IF(テーブル1[[#This Row],[列1]]="必要IN","アドオン",IF(テーブル1[[#This Row],[列1]]="OUT","スコープアウト","")))) -> 標準 | Z10: =VLOOKUP($B10,Sheet1!$C$2:$L$315,9,) -> 会計システム標準機能 | AA10: =VLOOKUP($B10,Sheet1!$C$2:$L$315,10,) -> 仕訳帳のテンプレート登録にて対応 | AB10: 標準 | AC10: =テーブル1[[#This Row],[要求事項一覧 判定]]=テーブル1[[#This Row],[列2]] -> TRUE
A11: =テーブル1[[#This Row],[対象部門]]&テーブル1[[#This Row],[業務要件回答表からの事前回答案_v1.0.xlsxより]] -> 一般会計全般・決算1.7 | B11: 一般会計全般・決算1.7 | D11: Req007 | E11: 転記前に、転記後の残高を事前にシミュレーション表示できること | F11: 登録は済んでいるが、まだ転記されていない仕訳について、転記後の残高を事前に確認できるように、シミュレーション表示できる機能 | G11: 1.7 | H11: サンスター | J11: 一般会計全般・決算 | K11: 決算G | L11: ※事前に残高シミュレーションしたいのは、特定の科目でしょうか？それとも全科目で転記前の確認対象でしょうか？ | M11: 現状の業務としては、入力後確認して間違えていたら逆仕訳をして訂正している。 今の運用イメージはなく、今後利用していきたい機能である。 対象の科目として、特定の科目があるわけではない。 | O11: FO | Q11: 日次振伝処理 | R11: 不要 | S11: 銀行口座勘定については、統制残高勘定機能により転記後の残高を確認することが可能。 その他の勘定については、仕訳帳画面の残高レポート機能で転記前に、転記後の残高を確認することが可能。 | T11: IN | X11: =テーブル1[[#This Row],[開発]]&テーブル1[[#This Row],[スコープ]] -> 不要IN | Y11: =IF(テーブル1[[#This Row],[列1]]="不要IN","標準",IF(テーブル1[[#This Row],[列1]]="不要OUT","スコープアウト",IF(テーブル1[[#This Row],[列1]]="必要IN","アドオン",IF(テーブル1[[#This Row],[列1]]="OUT","スコープアウト","")))) -> 標準 | Z11: =VLOOKUP($B11,Sheet1!$C$2:$L$315,9,) -> 会計システムアドオン | AA11: =VLOOKUP($B11,Sheet1!$C$2:$L$315,10,) -> 未転記の仕訳を選択後、ボタン押下後に転記後の残高を確認できるポップアップ画面を表示する機能を追加する | AB11: アドオン | AC11: =テーブル1[[#This Row],[要求事項一覧 判定]]=テーブル1[[#This Row],[列2]] -> FALSE
A12: =テーブル1[[#This Row],[対象部門]]&テーブル1[[#This Row],[業務要件回答表からの事前回答案_v1.0.xlsxより]] -> 一般会計全般・決算1.8 | B12: 一般会計全般・決算1.8 | D12: Req008 | E12: 定型の仕訳伝票に関して、配賦用のテンプレートを定義、繰り返し使用できること ※テンプレート項目例：配賦元部門/勘定科目/金額、配賦先部門/勘定科目金額、配賦基準(金額比、割合比等) | F12: 配賦のために定型の仕訳伝票を入力テンプレートとして定義する機能 | G12: 1.8 | H12: サンスター | J12: 一般会計全般・決算 | K12: 事務管理G | L12: 伝票テンプレート機能や科目残高にたいして配賦処理を実行する機能はあるが、伝票毎に配賦条件を設定して配賦計算を行う機能はない。 | M12: 決算チームとしては、この要件はない。 経営計画グループに、配賦の要件があるが、定型の仕訳に対してではなく科目残高に対する配賦の要件と思われる。 →2/7事務管理チームにも確認したが、伝票テンプレート機能があればよく、定型の仕訳伝票に関して、配賦用のテンプレートを定義する要件はなかった。 | O12: FO | Q12: 日次振伝処理 | R12: 不要 | S12: 定期処理仕訳帳で定型の仕訳パターンは登録可能。配賦処理の計算については、配賦ルールを登録してバッチ処理にて計算処理実行が可能(均等/割合/売上高比などの配賦方法が可能) | T12: OUT | X12: =テーブル1[[#This Row],[開発]]&テーブル1[[#This Row],[スコープ]] -> 不要OUT | Y12: =IF(テーブル1[[#This Row],[列1]]="不要IN","標準",IF(テーブル1[[#This Row],[列1]]="不要OUT","スコープアウト",IF(テーブル1[[#This Row],[列1]]="必要IN","アドオン",IF(テーブル1[[#This Row],[列1]]="OUT","スコープアウト","")))) -> スコープアウト | Z12: =VLOOKUP($B12,Sheet1!$C$2:$L$315,9,) -> 会計システム標準機能 | AA12: =VLOOKUP($B12,Sheet1!$C$2:$L$315,10,) -> 一般仕訳帳のテンプレ機能があります。（配賦のためというわけではない） | AB12: 標準 | AC12: =テーブル1[[#This Row],[要求事項一覧 判定]]=テーブル1[[#This Row],[列2]] -> FALSE
A13: =テーブル1[[#This Row],[対象部門]]&テーブル1[[#This Row],[業務要件回答表からの事前回答案_v1.0.xlsxより]] -> 一般会計全般・決算1.9 | B13: 一般会計全般・決算1.9 | C13: ◎ | D13: Req009 | E13: 定型の仕訳伝票に関して、伝票登録時の入力テンプレートを定義し、繰り返し使用できること | F13: 各会計期間で繰り返される定型の仕訳を処理するため、定型の仕訳伝票を入力テンプレートとして定義する機能 | G13: 1.9 | H13: サンスター | J13: 一般会計全般・決算 | K13: 事務管理G | O13: FO | Q13: 日次振伝処理 | R13: 不要 | S13: 定期処理仕訳帳という機能で定期的に作成される定型の伝票を登録することが可能。 | T13: IN | X13: =テーブル1[[#This Row],[開発]]&テーブル1[[#This Row],[スコープ]] -> 不要IN | Y13: =IF(テーブル1[[#This Row],[列1]]="不要IN","標準",IF(テーブル1[[#This Row],[列1]]="不要OUT","スコープアウト",IF(テーブル1[[#This Row],[列1]]="必要IN","アドオン",IF(テーブル1[[#This Row],[列1]]="OUT","スコープアウト","")))) -> 標準 | Z13: =VLOOKUP($B13,Sheet1!$C$2:$L$315,9,) -> 会計システム標準機能 | AA13: =VLOOKUP($B13,Sheet1!$C$2:$L$315,10,) -> 0 | AB13: 標準 | AC13: =テーブル1[[#This Row],[要求事項一覧 判定]]=テーブル1[[#This Row],[列2]] -> TRUE
A14: =テーブル1[[#This Row],[対象部門]]&テーブル1[[#This Row],[業務要件回答表からの事前回答案_v1.0.xlsxより]] -> 一般会計全般・決算2.1 | B14: 一般会計全般・決算2.1 | C14: ◎ | D14: Req010 | E14: 未転記の場合、登録した仕訳伝票を登録者の方から修正することができること | F14: 仕訳明細情報を訂正する機能 | G14: 2.1 | H14: サンスター | J14: 一般会計全般・決算 | K14: 決算G | O14: FO | Q14: 日次振伝処理 | R14: 不要 | S14: 未転記の伝票は登録者が修正可能。 （ワークフロー申請済未承認の場合、「申請取消」をして伝票修正可能） | T14: IN | X14: =テーブル1[[#This Row],[開発]]&テーブル1[[#This Row],[スコープ]] -> 不要IN | Y14: =IF(テーブル1[[#This Row],[列1]]="不要IN","標準",IF(テーブル1[[#This Row],[列1]]="不要OUT","スコープアウト",IF(テーブル1[[#This Row],[列1]]="必要IN","アドオン",IF(テーブル1[[#This Row],[列1]]="OUT","スコープアウト","")))) -> 標準 | Z14: =VLOOKUP($B14,Sheet1!$C$2:$L$315,9,) -> 会計システム標準機能 | AA14: =VLOOKUP($B14,Sheet1!$C$2:$L$315,10,) -> 0 | AB14: 標準 | AC14: =テーブル1[[#This Row],[要求事項一覧 判定]]=テーブル1[[#This Row],[列2]] -> TRUE
A15: =テーブル1[[#This Row],[対象部門]]&テーブル1[[#This Row],[業務要件回答表からの事前回答案_v1.0.xlsxより]] -> 一般会計全般・決算2.2 | B15: 一般会計全般・決算2.2 | C15: ◎ | D15: Req011 | E15: 未転記の場合、登録した仕訳伝票を登録者の方から削除することができること | F15: 仕訳明細情報を削除する機能 | G15: 2.2 | H15: サンスター | J15: 一般会計全般・決算 | K15: 決算G | O15: FO | Q15: 日次振伝処理 | R15: 不要 | S15: 未転記の伝票は登録者が削除可能。 （ワークフロー申請済未承認の場合、「申請取消」をして伝票削除可能） | T15: IN | X15: =テーブル1[[#This Row],[開発]]&テーブル1[[#This Row],[スコープ]] -> 不要IN | Y15: =IF(テーブル1[[#This Row],[列1]]="不要IN","標準",IF(テーブル1[[#This Row],[列1]]="不要OUT","スコープアウト",IF(テーブル1[[#This Row],[列1]]="必要IN","アドオン",IF(テーブル1[[#This Row],[列1]]="OUT","スコープアウト","")))) -> 標準 | Z15: =VLOOKUP($B15,Sheet1!$C$2:$L$315,9,) -> 会計システム標準機能 | AA15: =VLOOKUP($B15,Sheet1!$C$2:$L$315,10,) -> 0 | AB15: 標準 | AC15: =テーブル1[[#This Row],[要求事項一覧 判定]]=テーブル1[[#This Row],[列2]] -> TRUE
A16: =テーブル1[[#This Row],[対象部門]]&テーブル1[[#This Row],[業務要件回答表からの事前回答案_v1.0.xlsxより]] -> 一般会計全般・決算2.3 | B16: 一般会計全般・決算2.3 | C16: ◎ | D16: Req012 | E16: 登録した仕訳伝票を符号の変更（登録された仕訳伝票の金額をプラスからマイナスに変更）できること | F16: 逆仕訳を生成する機能 | G16: 2.3 | H16: サンスター | J16: 一般会計全般・決算 | K16: 決算G | O16: FO | Q16: 日次振伝処理 | R16: 不要 | S16: 「トランザクションの取消」という機能で符号を反転した逆仕訳を作成する機能あり。 | T16: IN | X16: =テーブル1[[#This Row],[開発]]&テーブル1[[#This Row],[スコープ]] -> 不要IN | Y16: =IF(テーブル1[[#This Row],[列1]]="不要IN","標準",IF(テーブル1[[#This Row],[列1]]="不要OUT","スコープアウト",IF(テーブル1[[#This Row],[列1]]="必要IN","アドオン",IF(テーブル1[[#This Row],[列1]]="OUT","スコープアウト","")))) -> 標準 | Z16: =VLOOKUP($B16,Sheet1!$C$2:$L$315,9,) -> 会計システム標準機能 | AA16: =VLOOKUP($B16,Sheet1!$C$2:$L$315,10,) -> 転記済み仕訳を指定し「仕訳全体の取り消し」 | AB16: 標準 | AC16: =テーブル1[[#This Row],[要求事項一覧 判定]]=テーブル1[[#This Row],[列2]] -> TRUE
A17: =テーブル1[[#This Row],[対象部門]]&テーブル1[[#This Row],[業務要件回答表からの事前回答案_v1.0.xlsxより]] -> 一般会計全般・決算3.1 | B17: 一般会計全般・決算3.1 | C17: ◎ | D17: Req013 | E17: 承認者による承認のもと、仕訳伝票を転記できること | F17: 仕訳を転記する機能 | G17: 3.1 | H17: サンスター | J17: 一般会計全般・決算 | K17: 決算G | O17: FO | Q17: 日次振伝処理 | R17: 不要 | S17: 簡易的な1段階承認が可能な機能と、多段階承認や条件分岐を追加できるようなワークフロー機能あり。 | T17: IN | X17: =テーブル1[[#This Row],[開発]]&テーブル1[[#This Row],[スコープ]] -> 不要IN | Y17: =IF(テーブル1[[#This Row],[列1]]="不要IN","標準",IF(テーブル1[[#This Row],[列1]]="不要OUT","スコープアウト",IF(テーブル1[[#This Row],[列1]]="必要IN","アドオン",IF(テーブル1[[#This Row],[列1]]="OUT","スコープアウト","")))) -> 標準 | Z17: =VLOOKUP($B17,Sheet1!$C$2:$L$315,9,) -> 会計システム標準機能 | AA17: =VLOOKUP($B17,Sheet1!$C$2:$L$315,10,) -> 0 | AB17: 標準 | AC17: =テーブル1[[#This Row],[要求事項一覧 判定]]=テーブル1[[#This Row],[列2]] -> TRUE
A18: =テーブル1[[#This Row],[対象部門]]&テーブル1[[#This Row],[業務要件回答表からの事前回答案_v1.0.xlsxより]] -> 一般会計全般・決算3.2 | B18: 一般会計全般・決算3.2 | D18: Req014 | E18: 自動で転記処理を行うために、転記承認を経ずに転記できること | F18: 自動で転記処理を行う機能 | G18: 3.2 | H18: サンスター | J18: 一般会計全般・決算 | K18: 事務管理G | L18: 定期バッチ処理で未転記伝票を転記する機能あり。承認不要な伝票は、承認設定なしの仕訳帳を設定して運用することにより承認なしで転記可能。 ※自動で転記処理を行うのはどのような種類の伝票でしょうか？ | M18: 各種自動転記機能全般のことを指しており 通常の伝票入力のなかで自動転記させる機能のことではない。 支払い処理、消費税の処理（年度末）、減価償却費、リース料など | O18: FO | Q18: 日次振伝処理 | R18: 不要 | S18: 各モジュールの仕訳が必要なプロセス処理では自動仕訳が作成される仕様となっている | T18: IN | X18: =テーブル1[[#This Row],[開発]]&テーブル1[[#This Row],[スコープ]] -> 不要IN | Y18: =IF(テーブル1[[#This Row],[列1]]="不要IN","標準",IF(テーブル1[[#This Row],[列1]]="不要OUT","スコープアウト",IF(テーブル1[[#This Row],[列1]]="必要IN","アドオン",IF(テーブル1[[#This Row],[列1]]="OUT","スコープアウト","")))) -> 標準 | Z18: =VLOOKUP($B18,Sheet1!$C$2:$L$315,9,) -> 会計システム標準機能 | AA18: =VLOOKUP($B18,Sheet1!$C$2:$L$315,10,) -> 特定金額以下であれば、承認不要（転記可能）等は設定できる。 | AB18: 標準 | AC18: =テーブル1[[#This Row],[要求事項一覧 判定]]=テーブル1[[#This Row],[列2]] -> TRUE
A19: =テーブル1[[#This Row],[対象部門]]&テーブル1[[#This Row],[業務要件回答表からの事前回答案_v1.0.xlsxより]] -> 一般会計全般・決算4.1 | B19: 一般会計全般・決算4.1 | C19: ◎ | D19: Req015 | E19: 仕訳作成者が、設定された仕訳の承認要求ができること | F19: 仕訳の承認依頼を行う機能 | G19: 4.1 | H19: サンスター | J19: 一般会計全般・決算 | K19: 決算G | O19: FO | Q19: 日次振伝処理 | R19: 不要 | S19: 承認設定した仕訳帳で入力した場合、仕訳承認要求が可能。ワークフロー機能を使用した場合、メール通知も可能。 | T19: IN | X19: =テーブル1[[#This Row],[開発]]&テーブル1[[#This Row],[スコープ]] -> 不要IN | Y19: =IF(テーブル1[[#This Row],[列1]]="不要IN","標準",IF(テーブル1[[#This Row],[列1]]="不要OUT","スコープアウト",IF(テーブル1[[#This Row],[列1]]="必要IN","アドオン",IF(テーブル1[[#This Row],[列1]]="OUT","スコープアウト","")))) -> 標準 | Z19: =VLOOKUP($B19,Sheet1!$C$2:$L$315,9,) -> 会計システム標準機能 | AA19: =VLOOKUP($B19,Sheet1!$C$2:$L$315,10,) -> 0 | AB19: 標準 | AC19: =テーブル1[[#This Row],[要求事項一覧 判定]]=テーブル1[[#This Row],[列2]] -> TRUE
A20: =テーブル1[[#This Row],[対象部門]]&テーブル1[[#This Row],[業務要件回答表からの事前回答案_v1.0.xlsxより]] -> 一般会計全般・決算4.2 | B20: 一般会計全般・決算4.2 | C20: ◎ | D20: Req016 | E20: 仕訳作成者が、設定された仕訳バッチ一覧から任意の単位で仕訳を一括に承認要求ができること | F20: 一括で仕訳の承認依頼を行う機能 | G20: 4.2 | H20: サンスター | J20: 一般会計全般・決算 | K20: 決算G | L20: 一括承認依頼の機能は無い。承認待ちリストから個別に選択して承認依頼する | M20: 現在SAPで入力したものについて一括承認はしていおらず、1件1件承認申請をしている。 楽楽精算の場合は件数が多いので一括承認機能を利用しているが、SAPは件数が少ないのでこの機能はなくてもよい。 20240326 楽々精算の振伝入力をFOで実施する場合、一括提出は不要だが一括承認が必要となる見込み R/3に代わるDynamicsでは、1件1件の伝票承認で対応可能との認識をした。 | O20: FO | Q20: 日次振伝処理 | R20: 不要 | S20: 一括承認依頼の機能は無い。承認待ちリストから個別に選択して承認依頼する | T20: OUT | X20: =テーブル1[[#This Row],[開発]]&テーブル1[[#This Row],[スコープ]] -> 不要OUT | Y20: =IF(テーブル1[[#This Row],[列1]]="不要IN","標準",IF(テーブル1[[#This Row],[列1]]="不要OUT","スコープアウト",IF(テーブル1[[#This Row],[列1]]="必要IN","アドオン",IF(テーブル1[[#This Row],[列1]]="OUT","スコープアウト","")))) -> スコープアウト | Z20: =VLOOKUP($B20,Sheet1!$C$2:$L$315,9,) -> 会計システムアドオン | AA20: =VLOOKUP($B20,Sheet1!$C$2:$L$315,10,) -> 一括で承認依頼/承認を行う機能を追加する | AB20: アドオン | AC20: =テーブル1[[#This Row],[要求事項一覧 判定]]=テーブル1[[#This Row],[列2]] -> FALSE
A21: =テーブル1[[#This Row],[対象部門]]&テーブル1[[#This Row],[業務要件回答表からの事前回答案_v1.0.xlsxより]] -> 一般会計全般・決算4.3 | B21: 一般会計全般・決算4.3 | C21: ◎ | D21: Req017 | E21: 仕訳一括承認依頼受領時に、任意の仕訳単位に対して一括で承認、否決処理ができること | F21: 一括で仕訳の承認を行う機能 | G21: 4.3 | H21: サンスター | J21: 一般会計全般・決算 | K21: 事務管理G | L21: 一括承認の機能は無い。承認待ちリストから個別に選択して承認する | M21: 現在SAPで入力したものについて一括承認はしていおらず、1件1件承認申請をしている。 楽楽精算の場合は件数が多いので一括承認機能を利用しているが、SAPは件数が少ないのでこの機能はなくてもよい。 R/3に代わるDynamicsでは、1件1件の伝票承認で対応可能との認識をした。 20240326 楽々精算の振伝入力をFOで実施する場合、一括提出は不要だが一括承認が必要となる見込み R/3に代わるDynamicsでは、1件1件の伝票承認で対応可能との認識をした。 | O21: FO | Q21: 日次振伝処理 | R21: 必要 | S21: 一括承認の機能は無い。承認待ちリストから個別に選択して承認する 20240404 楽々精算からFOで代替するケースを想定して一旦開発扱いとする。 | T21: IN | U21: 楽々精算の振伝をFOでやるかどうかにより要不要が決まる。 | V21: 〇 | W21: 振替伝票など、承認対象の伝票が多くなるケースにおいて、本アドオンでどれだけの効果が出るかを検証要 | X21: =テーブル1[[#This Row],[開発]]&テーブル1[[#This Row],[スコープ]] -> 必要IN | Y21: =IF(テーブル1[[#This Row],[列1]]="不要IN","標準",IF(テーブル1[[#This Row],[列1]]="不要OUT","スコープアウト",IF(テーブル1[[#This Row],[列1]]="必要IN","アドオン",IF(テーブル1[[#This Row],[列1]]="OUT","スコープアウト","")))) -> アドオン | Z21: =VLOOKUP($B21,Sheet1!$C$2:$L$315,9,) -> 会計システムアドオン | AA21: =VLOOKUP($B21,Sheet1!$C$2:$L$315,10,) -> 4.3の範囲にて対応。 | AB21: アドオン | AC21: =テーブル1[[#This Row],[要求事項一覧 判定]]=テーブル1[[#This Row],[列2]] -> TRUE
A22: =テーブル1[[#This Row],[対象部門]]&テーブル1[[#This Row],[業務要件回答表からの事前回答案_v1.0.xlsxより]] -> 一般会計全般・決算5.1 | B22: 一般会計全般・決算5.1 | C22: ◎ | D22: Req018 | E22: 仕訳入力者を区分として、仕訳のステータスが未承認または承認依頼未済である仕訳の仕訳明細情報を一覧で、画面照会および帳票出力できること | F22: 承認依頼時に、依頼者別の未承認または承認依頼未済の仕訳明細情報を一覧で出力する機能 | G22: 5.1 | H22: サンスター | J22: 一般会計全般・決算 | K22: 決算G | L22: 一般仕訳帳画面で未転記状態の仕訳帳を一覧表示可能、ワークフローの承認状態も表示可能だが、ヘッダ情報のみ。 帳票では、「未転記の一般仕訳入力」が未転記の仕訳明細を確認できるが承認状態が確認できない。 | M22: 上長が承認したのか、未転記か転記済みかだけがわかればよいので提示いただいている機能だけでもよいと考えている。 | O22: FO | Q22: 日次振伝処理 | R22: 不要 | S22: 一般仕訳帳画面で未転記状態の仕訳帳を一覧表示可能、 | T22: IN | X22: =テーブル1[[#This Row],[開発]]&テーブル1[[#This Row],[スコープ]] -> 不要IN | Y22: =IF(テーブル1[[#This Row],[列1]]="不要IN","標準",IF(テーブル1[[#This Row],[列1]]="不要OUT","スコープアウト",IF(テーブル1[[#This Row],[列1]]="必要IN","アドオン",IF(テーブル1[[#This Row],[列1]]="OUT","スコープアウト","")))) -> 標準 | Z22: =VLOOKUP($B22,Sheet1!$C$2:$L$315,9,) -> 会計システム標準機能 | AA22: =VLOOKUP($B22,Sheet1!$C$2:$L$315,10,) -> 0 | AB22: 標準 | AC22: =テーブル1[[#This Row],[要求事項一覧 判定]]=テーブル1[[#This Row],[列2]] -> TRUE
A23: =テーブル1[[#This Row],[対象部門]]&テーブル1[[#This Row],[業務要件回答表からの事前回答案_v1.0.xlsxより]] -> 一般会計全般・決算5.2 | B23: 一般会計全般・決算5.2 | C23: ◎ | D23: Req019 | E23: 承認依頼が必要な未承認の仕訳を勘定科目別に集計した一覧で、画面照会および帳票出力できること | F23: 承認依頼が必要な仕訳を勘定科目別に集計した一覧を出力する機能 | G23: 5.2 | H23: サンスター | J23: 一般会計全般・決算 | K23: 決算G | L23: 仕訳帳明細を未承認のものに絞って出力することはできるが、科目別に集計されていない。CSV出力後に集計を行う必要あり。 | M23: 転記後の金額がわかればよいので機能としては不要である。 | O23: FO | Q23: 日次振伝処理 | R23: 不要 | S23: 仕訳帳明細を未承認のものに絞って出力することはできるが、科目別に集計されていない。CSV出力後に集計を行う必要あり。 | T23: OUT | X23: =テーブル1[[#This Row],[開発]]&テーブル1[[#This Row],[スコープ]] -> 不要OUT | Y23: =IF(テーブル1[[#This Row],[列1]]="不要IN","標準",IF(テーブル1[[#This Row],[列1]]="不要OUT","スコープアウト",IF(テーブル1[[#This Row],[列1]]="必要IN","アドオン",IF(テーブル1[[#This Row],[列1]]="OUT","スコープアウト","")))) -> スコープアウト | Z23: =VLOOKUP($B23,Sheet1!$C$2:$L$315,9,) -> 会計システムアドオン | AA23: =VLOOKUP($B23,Sheet1!$C$2:$L$315,10,) -> 新規画面として、承認依頼が必要な仕訳を勘定科目別に集計した一覧を出力する画面を作成。帳票に関しては、現時点では標準機能のExcelファイルエクスポート機能を使用予定。要件次第で開発とする。 | AB23: アドオン | AC23: =テーブル1[[#This Row],[要求事項一覧 判定]]=テーブル1[[#This Row],[列2]] -> FALSE
A24: =テーブル1[[#This Row],[対象部門]]&テーブル1[[#This Row],[業務要件回答表からの事前回答案_v1.0.xlsxより]] -> 一般会計全般・決算6.1 | B24: 一般会計全般・決算6.1 | D24: Req020 | E24: 前日、前月末までの借方貸方の累計と残高を集計し、画面照会および帳票出力ができること | F24: 指定時点での科目別残高一覧を出力する機能 | G24: 6.1 | H24: サンスター | J24: 一般会計全般・決算 | K24: 決算G | O24: FO | Q24: 日次振伝処理 | R24: 不要 | S24: 試算表で日付指定して科目残高確認可能。 | T24: IN | X24: =テーブル1[[#This Row],[開発]]&テーブル1[[#This Row],[スコープ]] -> 不要IN | Y24: =IF(テーブル1[[#This Row],[列1]]="不要IN","標準",IF(テーブル1[[#This Row],[列1]]="不要OUT","スコープアウト",IF(テーブル1[[#This Row],[列1]]="必要IN","アドオン",IF(テーブル1[[#This Row],[列1]]="OUT","スコープアウト","")))) -> 標準 | Z24: =VLOOKUP($B24,Sheet1!$C$2:$L$315,9,) -> 会計システム標準機能 | AA24: =VLOOKUP($B24,Sheet1!$C$2:$L$315,10,) -> 0 | AB24: 標準 | AC24: =テーブル1[[#This Row],[要求事項一覧 判定]]=テーブル1[[#This Row],[列2]] -> TRUE
A25: =テーブル1[[#This Row],[対象部門]]&テーブル1[[#This Row],[業務要件回答表からの事前回答案_v1.0.xlsxより]] -> 一般会計全般・決算6.2 | B25: 一般会計全般・決算6.2 | D25: Req021 | E25: 指定された会計期間において発生した任意の勘定科目の残高明細情報を、画面照会および帳票出力できること | F25: 科目別残高明細一覧を出力する機能 | G25: 6.2 | H25: サンスター | J25: 一般会計全般・決算 | K25: 決算G | O25: FO | Q25: 日次振伝処理 | R25: 不要 | S25: 試算表で日付指定して科目残高確認可能。 分析コード明細書で日付指定および合計指定することで帳票出力可能。 | T25: IN | X25: =テーブル1[[#This Row],[開発]]&テーブル1[[#This Row],[スコープ]] -> 不要IN | Y25: =IF(テーブル1[[#This Row],[列1]]="不要IN","標準",IF(テーブル1[[#This Row],[列1]]="不要OUT","スコープアウト",IF(テーブル1[[#This Row],[列1]]="必要IN","アドオン",IF(テーブル1[[#This Row],[列1]]="OUT","スコープアウト","")))) -> 標準 | Z25: =VLOOKUP($B25,Sheet1!$C$2:$L$315,9,) -> 会計システム標準機能 | AA25: =VLOOKUP($B25,Sheet1!$C$2:$L$315,10,) -> 0 | AB25: 標準 | AC25: =テーブル1[[#This Row],[要求事項一覧 判定]]=テーブル1[[#This Row],[列2]] -> TRUE
A26: =テーブル1[[#This Row],[対象部門]]&テーブル1[[#This Row],[業務要件回答表からの事前回答案_v1.0.xlsxより]] -> 一般会計全般・決算6.3 | B26: 一般会計全般・決算6.3 | D26: Req022 | E26: 前期末の残高明細情報と比較できること | F26: 前年同期比で残高の比較照合ができる機能 | G26: 6.3 | H26: サンスター | J26: 一般会計全般・決算 | K26: 決算G | O26: FO | Q26: 月次決算処理 | R26: 必要 | S26: 標準の帳票作成ツールManagementReporterを使って、前年同期比帳票を作成すれば参照可能。 | T26: IN | V26: × | W26: MRでできるのであれば審査対象外 | X26: =テーブル1[[#This Row],[開発]]&テーブル1[[#This Row],[スコープ]] -> 必要IN | Y26: =IF(テーブル1[[#This Row],[列1]]="不要IN","標準",IF(テーブル1[[#This Row],[列1]]="不要OUT","スコープアウト",IF(テーブル1[[#This Row],[列1]]="必要IN","アドオン",IF(テーブル1[[#This Row],[列1]]="OUT","スコープアウト","")))) -> アドオン | Z26: =VLOOKUP($B26,Sheet1!$C$2:$L$315,9,) -> 会計システム標準機能 | AA26: =VLOOKUP($B26,Sheet1!$C$2:$L$315,10,) -> MRで対応 | AB26: 標準 | AC26: =テーブル1[[#This Row],[要求事項一覧 判定]]=テーブル1[[#This Row],[列2]] -> FALSE
A27: =テーブル1[[#This Row],[対象部門]]&テーブル1[[#This Row],[業務要件回答表からの事前回答案_v1.0.xlsxより]] -> 一般会計全般・決算6.4 | B27: 一般会計全般・決算6.4 | D27: Req023 | E27: 特定の会計期間において勘定科目別、貨幣別等で各残高を集計して、画面照会および帳票出力ができること | F27: 特定の会計期間において勘定科目別の残高を指定した一定の条件別に一覧化して集計する機能 | G27: 6.4 | H27: サンスター | J27: 一般会計全般・決算 | K27: 決算G | L27: 外貨建ての入力と通貨別残高参照画面はある。ただし一覧形式での参照機能がほしい場合、アドオンが必要。 標準の帳票作成ツールManagementReporterを使って、ある程度の条件別の帳票が作成可能であるが、制限あり。 ※MRの場合、貨幣別は明細での出力は可能だが残高集計すると邦貨で集計される制限あり ※試算表画面の邦貨での一覧表示から、貨幣別算高画面へ遷移して確認できるが、 科目を個別指定して表示する方式のため該当科目を一覧表示で貨幣別に表示する機能がない。 | M27: 決算では外貨建てで管理しているものはない。外貨は円換算して決算しているので決算チームとしては不要である。 今後は、外貨建て運用する方針。 2024/04/11 試算表の通貨別画面で個別科目ごとに確認することは可能であるが、一覧性がないため帳票を開発するか議論したが、試算表の通貨別画面で個別に確認する運用対応とし開発対象外となった。 | O27: FO | Q27: 月次決算処理 | R27: 不要 | S27: 外貨建ての入力と通貨別残高参照画面はある。ただし一覧形式での参照機能がほしい場合、アドオンが必要。 | T27: IN | U27: 2024/04/11 試算表の通貨別画面で個別科目ごとに確認することは可能であるが、一覧性がないため帳票を開発するか議論したが、試算表の通貨別画面で個別に確認する運用対応とし開発対象外となった。 | X27: =テーブル1[[#This Row],[開発]]&テーブル1[[#This Row],[スコープ]] -> 不要IN | Y27: =IF(テーブル1[[#This Row],[列1]]="不要IN","標準",IF(テーブル1[[#This Row],[列1]]="不要OUT","スコープアウト",IF(テーブル1[[#This Row],[列1]]="必要IN","アドオン",IF(テーブル1[[#This Row],[列1]]="OUT","スコープアウト","")))) -> 標準 | Z27: =VLOOKUP($B27,Sheet1!$C$2:$L$315,9,) -> 会計システム標準機能 | AA27: =VLOOKUP($B27,Sheet1!$C$2:$L$315,10,) -> 0 | AB27: 標準 | AC27: =テーブル1[[#This Row],[要求事項一覧 判定]]=テーブル1[[#This Row],[列2]] -> TRUE
A28: =テーブル1[[#This Row],[対象部門]]&テーブル1[[#This Row],[業務要件回答表からの事前回答案_v1.0.xlsxより]] -> 一般会計全般・決算6.5 | B28: 一般会計全般・決算6.5 | D28: Req024 | E28: 各勘定科目の残高を確認し、残高がマイナスである科目がある場合、該当科目別の残高を通貨・会社毎にリストとして、画面照会および帳票出力ができること | F28: 残高がマイナスである科目を一覧で出力する機能 | G28: 6.5 | H28: サンスター | J28: 一般会計全般・決算 | K28: 決算G | L28: 試算表(科目残高参照機能)で「-1以下」の条件でフィルタすることができるが、 試算表画面では、規定の表示方法として貸方勘定の残高がーで表示されるため、要件を満たせない。 ManagementReporterで貸方科目もプラス残で表示する残高リストを作成して、出力した残高リストでマイナス残の科目を抽出する。 | M28: 現状SAPから出てくる試算表で確認できているので、マイナス分のみの一覧表は不要である。 | O28: FO | Q28: 月次決算処理 | R28: 不要 | S28: 通常の試算表で確認 | T28: OUT | X28: =テーブル1[[#This Row],[開発]]&テーブル1[[#This Row],[スコープ]] -> 不要OUT | Y28: =IF(テーブル1[[#This Row],[列1]]="不要IN","標準",IF(テーブル1[[#This Row],[列1]]="不要OUT","スコープアウト",IF(テーブル1[[#This Row],[列1]]="必要IN","アドオン",IF(テーブル1[[#This Row],[列1]]="OUT","スコープアウト","")))) -> スコープアウト | Z28: =VLOOKUP($B28,Sheet1!$C$2:$L$315,9,) -> 会計システム標準機能 | AA28: =VLOOKUP($B28,Sheet1!$C$2:$L$315,10,) -> 勘定科目一覧画面で、金額欄にマイナス金額のフィルタを使用 | AB28: 標準 | AC28: =テーブル1[[#This Row],[要求事項一覧 判定]]=テーブル1[[#This Row],[列2]] -> FALSE
A29: =テーブル1[[#This Row],[対象部門]]&テーブル1[[#This Row],[業務要件回答表からの事前回答案_v1.0.xlsxより]] -> 一般会計全般・決算6.6 | B29: 一般会計全般・決算6.6 | D29: Req025 | E29: 決算時の通過勘定科目の残高を確認し、残高が0円以外の科目がある場合、該当科目別の残高を通貨・会社毎にリストとして、画面照会および帳票出力ができること | F29: 決算時において0円である必要がある勘定科目(通過勘定科目)に対し未整理の残高が存在する場合、対象の残高情報を一覧で出力する機能 | G29: 6.6 | H29: サンスター | J29: 一般会計全般・決算 | K29: 決算G | M29: 現状SAPから出てくる試算表で確認できているので、特定科目分のみの一覧表は不要である。 会社ごとにしか確認していないので、特別な機能は必要ない。 | O29: FO | Q29: 月次決算処理 | R29: 不要 | S29: 通常の試算表で確認 | T29: OUT | X29: =テーブル1[[#This Row],[開発]]&テーブル1[[#This Row],[スコープ]] -> 不要OUT | Y29: =IF(テーブル1[[#This Row],[列1]]="不要IN","標準",IF(テーブル1[[#This Row],[列1]]="不要OUT","スコープアウト",IF(テーブル1[[#This Row],[列1]]="必要IN","アドオン",IF(テーブル1[[#This Row],[列1]]="OUT","スコープアウト","")))) -> スコープアウト | Z29: =VLOOKUP($B29,Sheet1!$C$2:$L$315,9,) -> 会計システム標準機能 | AA29: =VLOOKUP($B29,Sheet1!$C$2:$L$315,10,) -> 伝票トランザクションにてフィルタしてExcel出力での対応 | AB29: 標準 | AC29: =テーブル1[[#This Row],[要求事項一覧 判定]]=テーブル1[[#This Row],[列2]] -> FALSE
A30: =テーブル1[[#This Row],[対象部門]]&テーブル1[[#This Row],[業務要件回答表からの事前回答案_v1.0.xlsxより]] -> 一般会計全般・決算7.1 | B30: 一般会計全般・決算7.1 | D30: Req026 | E30: 指定された会計期間時点での以下の財務諸表を、全社、部門別で、画面照会および帳票出力できること ・貸借対照表(BS) ・損益計算書(PL累計) ・株主資本等変動計算書(SS) ・注記表 ・キャッシュフロー計算書(CF) ・製造原価報告書 ・労務費及び生産費明細表 ・営業費明細表 ・研究費明細表 | F30: 財務諸表をを全社/各社別に作成・出力する機能(BS/PLについては開示用科目(親科目)と集計元科目(子科目)単位でそれぞれ閲覧できること) | G30: 7.1 | H30: サンスター | J30: 一般会計全般・決算 | K30: 決算G | L30: 標準の帳票作成ツールManagementReportを使って、全社、部門別に帳票作成可能。 ※・注記表 ・キャッシュフロー計算書(CF)は、ロジックしだいでアドオンが必要。 | M30: 製造原価報告書が直接出力されているわけではない。 労務費及び生産費明細表は、SAPから経費実績表の合計数字をExcelに転記している。元データ出力ができればよいと考えている。 SEJはR/3からホストで出てきた製造原価が出てこない。 決算調整の数字はホストに反映されない問題がある。SAPでは製造原価が出せていないため、手作業で数字の調整をしないといけない。 株主資本等変動計算書、注記表、キャッシュフロー計算書は手作業が必要になる想定。 どこまでコストをかけて必要なのか検討が必要。 | O30: FO | Q30: 月次決算処理 | R30: 必要 | S30: 標準の帳票作成ツールManagementReportを使って出力可能な帳票は作成。 株主資本等変動計算書、注記表、キャッシュフロー計算書は手作業が必要。 | T30: IN | V30: × | W30: MRでできるのであれば審査対象外 株主資本等変動計算書、注記表、キャッシュフロー計算書はシステム化対象外 | X30: =テーブル1[[#This Row],[開発]]&テーブル1[[#This Row],[スコープ]] -> 必要IN | Y30: =IF(テーブル1[[#This Row],[列1]]="不要IN","標準",IF(テーブル1[[#This Row],[列1]]="不要OUT","スコープアウト",IF(テーブル1[[#This Row],[列1]]="必要IN","アドオン",IF(テーブル1[[#This Row],[列1]]="OUT","スコープアウト","")))) -> アドオン | Z30: =VLOOKUP($B30,Sheet1!$C$2:$L$315,9,) -> 会計システム標準機能 | AA30: =VLOOKUP($B30,Sheet1!$C$2:$L$315,10,) -> 「注記表」以外につきましては、FO標準機能の財務諸表で対応可能と考えております。ただ、「注記表」については、標準機能のWordテンプレートを使用して、帳票出力を検討しております。ただし、要件次第では、開発が必要となる場合もございます。 | AB30: 標準 | AC30: =テーブル1[[#This Row],[要求事項一覧 判定]]=テーブル1[[#This Row],[列2]] -> FALSE
A31: =テーブル1[[#This Row],[対象部門]]&テーブル1[[#This Row],[業務要件回答表からの事前回答案_v1.0.xlsxより]] -> 一般会計全般・決算7.2 | B31: 一般会計全般・決算7.2 | D31: Req027 | E31: 各財務諸表類の前年度比較ができること | F31: 前年同期比で各財務諸表類の比較照合ができる機能 | G31: 7.2 | H31: サンスター | J31: 一般会計全般・決算 | K31: 決算G | M31: 単年度があればよい、前年度の比較は不要。 | O31: FO | Q31: 月次決算処理 | R31: 不要 | T31: OUT | X31: =テーブル1[[#This Row],[開発]]&テーブル1[[#This Row],[スコープ]] -> 不要OUT | Y31: =IF(テーブル1[[#This Row],[列1]]="不要IN","標準",IF(テーブル1[[#This Row],[列1]]="不要OUT","スコープアウト",IF(テーブル1[[#This Row],[列1]]="必要IN","アドオン",IF(テーブル1[[#This Row],[列1]]="OUT","スコープアウト","")))) -> スコープアウト | Z31: =VLOOKUP($B31,Sheet1!$C$2:$L$315,9,) -> 会計システム標準機能 | AA31: =VLOOKUP($B31,Sheet1!$C$2:$L$315,10,) -> MRで対応 | AB31: 標準 | AC31: =テーブル1[[#This Row],[要求事項一覧 判定]]=テーブル1[[#This Row],[列2]] -> FALSE
A32: =テーブル1[[#This Row],[対象部門]]&テーブル1[[#This Row],[業務要件回答表からの事前回答案_v1.0.xlsxより]] -> 一般会計全般・決算7.3 | B32: 一般会計全般・決算7.3 | D32: Req028 | E32: 年次毎に下記の決算開示書類を作成すること ・計算書類 ・附属明細書 ・決算短信 ・事業報告書 ・勘定明細 | F32: 決算開示書類を作成・出力する機能 | G32: 7.3 | H32: サンスター | J32: 一般会計全般・決算 | K32: 決算G | L32: 決算開示書類向けのローデータを出力することは可能であるが、各表毎の仕訳トランザクションから取得できない情報については、別途追加編集が必要。 | M32: 仕訳トランザクションから取得できない情報については別途検討が必要。 | O32: FO | Q32: 月次決算処理 | R32: 不要 | S32: 決算開示書類向けのローデータを出力して、各表毎の仕訳トランザクションから取得できない情報については、別途追加編集を行う。 | T32: IN | X32: =テーブル1[[#This Row],[開発]]&テーブル1[[#This Row],[スコープ]] -> 不要IN | Y32: =IF(テーブル1[[#This Row],[列1]]="不要IN","標準",IF(テーブル1[[#This Row],[列1]]="不要OUT","スコープアウト",IF(テーブル1[[#This Row],[列1]]="必要IN","アドオン",IF(テーブル1[[#This Row],[列1]]="OUT","スコープアウト","")))) -> 標準 | Z32: =VLOOKUP($B32,Sheet1!$C$2:$L$315,9,) -> 会計システムアドオン | AA32: =VLOOKUP($B32,Sheet1!$C$2:$L$315,10,) -> 下記帳票類の作成 ・計算書類 ・附属明細書 ・決算短信 ・事業報告書 ・勘定明細 | AB32: アドオン | AC32: =テーブル1[[#This Row],[要求事項一覧 判定]]=テーブル1[[#This Row],[列2]] -> FALSE
A33: =テーブル1[[#This Row],[対象部門]]&テーブル1[[#This Row],[業務要件回答表からの事前回答案_v1.0.xlsxより]] -> 一般会計全般・決算7.4 | B33: 一般会計全般・決算7.4 | D33: Req029 | E33: 決算開示書類の計算書類や付属明細書、勘定明細書の前年度比較ができること | F33: 前年同期比で各決算開示書類の比較照合ができる機能 | G33: 7.4 | H33: サンスター | J33: 一般会計全般・決算 | K33: 決算G | L33: 決算開示書類向けのローデータを出力することは可能であるが、各表毎の仕訳トランザクションから取得できない情報については、別途追加編集が必要。 | M33: BSに関しては出力可能、PLは出力ができていない状況。BSはSAPの中で比較することはなく、Excelで各社2期比較のBS/PLを作成している。 決算開示書類も現状、Excelで作成している。 計算書類、出力明細、勘定明細の前年度比較ができることとなっているが、帳票としてはそれぞれの単年度の数字だけでいい。 BS、PLの前年比較ができれば決算開示書類の前年比較はできなくても差し支えないと考えている。 | O33: FO | Q33: 月次決算処理 | R33: 不要 | S33: 決算開示書類向けのローデータを出力し、各表毎の仕訳トランザクションから取得できない情報については、別途追加編集を行う | T33: IN | X33: =テーブル1[[#This Row],[開発]]&テーブル1[[#This Row],[スコープ]] -> 不要IN | Y33: =IF(テーブル1[[#This Row],[列1]]="不要IN","標準",IF(テーブル1[[#This Row],[列1]]="不要OUT","スコープアウト",IF(テーブル1[[#This Row],[列1]]="必要IN","アドオン",IF(テーブル1[[#This Row],[列1]]="OUT","スコープアウト","")))) -> 標準 | Z33: =VLOOKUP($B33,Sheet1!$C$2:$L$315,9,) -> 会計システムアドオン | AA33: =VLOOKUP($B33,Sheet1!$C$2:$L$315,10,) -> 下記帳票類の履歴管理機能 ・計算書類 ・附属明細書 ・決算短信 ・事業報告書 ・勘定明細 | AB33: アドオン | AC33: =テーブル1[[#This Row],[要求事項一覧 判定]]=テーブル1[[#This Row],[列2]] -> FALSE
A34: =テーブル1[[#This Row],[対象部門]]&テーブル1[[#This Row],[業務要件回答表からの事前回答案_v1.0.xlsxより]] -> 一般会計全般・決算7.5 | B34: 一般会計全般・決算7.5 | D34: Req030 | E34: 指定された会計期間時点での以下の帳簿類を、全社、部門別で、画面照会および出力できること。また、これらの帳簿を指定した日にシステムから指定したデータを自動で保存できること。 定期的に静止データとして帳票等に自動保存させたい ・仕訳帳 （仕訳のステータス(未承認、転記済み、エラー)を区分として、仕訳帳が画面照会および帳票出力でき、仕訳一覧から、ドリルダウンして明細情報が確認できること） ・総勘定元帳 （指定された会計期間(月次/年度等)における、仕訳明細情報(借方、貸方、残高)が、勘定科目別、伝票日付別、転記処理日別、仕訳ソース別、仕訳カテゴリー別等に集計された一覧） （指定された会計期間(月次/年度等)における、仕訳明細情報(借方、貸方、残高)が、勘定科目別、伝票日付別、転記処理日別、仕訳ソース別、仕訳カテゴリー別等に集計された一覧） ・補助簿（固定資産台帳を含む） （指定された会計期間(月次/年度等)における、仕訳の明細情報の勘定科目別、伝票日付別、取引先別等の一覧） ・勘定残高表 （指定された会計期間(月次/年度等)における、指定された勘定科目の残高(前期末残高、借方、貸方)が集計された一覧） ・消費税台帳 （指定された会計期間(月次/年度等)における、売上高・仕入高と消費税額がで集計された一覧） | F34: 仕訳帳、総勘定元帳、補助記入帳、補助元帳、勘定残高表、消費税台帳等を出力、また、指定日に応じて自動保存する機能 | G34: 7.5 | H34: サンスター | J34: 一般会計全般・決算 | K34: 決算G | L34: 標準の帳票作成ツールManagementReporterを使って、スケジュールバッチ出力ができるが、MRでは、出力指示や表示内容に制限があるので、各帳票ごとに検討が必要。 固定資産台帳や消費税台帳は、ManagementReportでの出力は不可。 | M34: 決算チームでは、通常の帳票出力機能で問題ない定期的な自動保存などの要件はない。 2/7 事務管理チーム確認 月次で3社のBSとPLを期間指定して手動で保存し、各社の勘定照合を行っている。よって、画面で必要な期間指定にて照会できれば、 自動保存は不要。最低レベルで、手動で出力したものを保管できれば良い。自動でできればなお良い。 過去のデータを使用するなど、自動でマクロを読んで貼り付けすることなども行っているのでExcelに出力できれば良い。 | O34: FO | Q34: 月次決算処理 | R34: 不要 | S34: ManagementReporterで、バッチスケジュール可能なものは自動スケジュール出力。 それ以外の帳票は、手動で出力したものを保管する。 | T34: IN | X34: =テーブル1[[#This Row],[開発]]&テーブル1[[#This Row],[スコープ]] -> 不要IN | Y34: =IF(テーブル1[[#This Row],[列1]]="不要IN","標準",IF(テーブル1[[#This Row],[列1]]="不要OUT","スコープアウト",IF(テーブル1[[#This Row],[列1]]="必要IN","アドオン",IF(テーブル1[[#This Row],[列1]]="OUT","スコープアウト","")))) -> 標準 | Z34: =VLOOKUP($B34,Sheet1!$C$2:$L$315,9,) -> 会計システム標準機能 | AA34: =VLOOKUP($B34,Sheet1!$C$2:$L$315,10,) -> 伝票トランザクションにてフィルタしてExcel出力での対応 | AB34: 標準 | AC34: =テーブル1[[#This Row],[要求事項一覧 判定]]=テーブル1[[#This Row],[列2]] -> TRUE
A35: =テーブル1[[#This Row],[対象部門]]&テーブル1[[#This Row],[業務要件回答表からの事前回答案_v1.0.xlsxより]] -> 一般会計全般・決算7.6 | B35: 一般会計全般・決算7.6 | D35: Req031 | E35: 当日を含め指定した特定の日付に転記された伝票明細表が画面照会および帳票出力できること ※伝票の仕訳情報の一覧 | F35: 当日を含め指定した特定の日付に転記された伝票の明細表を出力する機能 | G35: 7.6 | H35: サンスター | J35: 一般会計全般・決算 | K35: 決算G | O35: FO | Q35: 月次決算処理 | R35: 不要 | S35: 伝票トランザクション(伝票明細確認画面)にてフィルタ指定で伝票の検索および明細出力が可能 | T35: IN | X35: =テーブル1[[#This Row],[開発]]&テーブル1[[#This Row],[スコープ]] -> 不要IN | Y35: =IF(テーブル1[[#This Row],[列1]]="不要IN","標準",IF(テーブル1[[#This Row],[列1]]="不要OUT","スコープアウト",IF(テーブル1[[#This Row],[列1]]="必要IN","アドオン",IF(テーブル1[[#This Row],[列1]]="OUT","スコープアウト","")))) -> 標準 | Z35: =VLOOKUP($B35,Sheet1!$C$2:$L$315,9,) -> 会計システム標準機能 | AA35: =VLOOKUP($B35,Sheet1!$C$2:$L$315,10,) -> 伝票トランザクションにてフィルタしてExcel出力での対応 | AB35: 標準 | AC35: =テーブル1[[#This Row],[要求事項一覧 判定]]=テーブル1[[#This Row],[列2]] -> TRUE
A36: =テーブル1[[#This Row],[対象部門]]&テーブル1[[#This Row],[業務要件回答表からの事前回答案_v1.0.xlsxより]] -> 一般会計全般・決算7.7 | B36: 一般会計全般・決算7.7 | D36: Req032 | E36: 当日を含め指定した特定の日付に転記された伝票集計表が画面照会および帳票出力できること ※伝票の仕訳情報が勘定科目等別に集計された一覧 | F36: 当日を含め指定した特定の日付に転記された伝票の集計表を出力する機能 | G36: 7.7 | H36: サンスター | J36: 一般会計全般・決算 | K36: 決算G | O36: FO | Q36: 月次決算処理 | R36: 不要 | S36: 伝票トランザクション(伝票明細確認画面)のフィルタし結果をExcel出力して科目集計。 または、分析コード明細書で「合計」モードで科目残高を出力 | T36: IN | X36: =テーブル1[[#This Row],[開発]]&テーブル1[[#This Row],[スコープ]] -> 不要IN | Y36: =IF(テーブル1[[#This Row],[列1]]="不要IN","標準",IF(テーブル1[[#This Row],[列1]]="不要OUT","スコープアウト",IF(テーブル1[[#This Row],[列1]]="必要IN","アドオン",IF(テーブル1[[#This Row],[列1]]="OUT","スコープアウト","")))) -> 標準 | Z36: =VLOOKUP($B36,Sheet1!$C$2:$L$315,9,) -> 会計システム標準機能 | AA36: =VLOOKUP($B36,Sheet1!$C$2:$L$315,10,) -> 伝票トランザクションにてフィルタしてExcel出力での対応 | AB36: 標準 | AC36: =テーブル1[[#This Row],[要求事項一覧 判定]]=テーブル1[[#This Row],[列2]] -> TRUE
A37: =テーブル1[[#This Row],[対象部門]]&テーブル1[[#This Row],[業務要件回答表からの事前回答案_v1.0.xlsxより]] -> 一般会計全般・決算7.8 | B37: 一般会計全般・決算7.8 | D37: Req033 | E37: 売上高明細表・仕入高明細表が画面照会および帳票出力できること ※指定された会計期間における、売上仕入対象勘定科目の仕訳明細情報の一覧 | F37: 売上仕入対象勘定の実績から売上高明細表・仕入高明細表を出力する機能 | G37: 7.8 | H37: サンスター | J37: 一般会計全般・決算 | K37: 決算G | O37: FO | Q37: 月次決算処理 | R37: 不要 | S37: 伝票トランザクション(伝票明細確認画面)にてフィルタ指定で売上高明細、仕入高明細の確認が可能。 | T37: IN | X37: =テーブル1[[#This Row],[開発]]&テーブル1[[#This Row],[スコープ]] -> 不要IN | Y37: =IF(テーブル1[[#This Row],[列1]]="不要IN","標準",IF(テーブル1[[#This Row],[列1]]="不要OUT","スコープアウト",IF(テーブル1[[#This Row],[列1]]="必要IN","アドオン",IF(テーブル1[[#This Row],[列1]]="OUT","スコープアウト","")))) -> 標準 | Z37: =VLOOKUP($B37,Sheet1!$C$2:$L$315,9,) -> 会計システム標準機能 | AA37: =VLOOKUP($B37,Sheet1!$C$2:$L$315,10,) -> 伝票トランザクションにてフィルタしてExcel出力での対応 | AB37: 標準 | AC37: =テーブル1[[#This Row],[要求事項一覧 判定]]=テーブル1[[#This Row],[列2]] -> TRUE
A38: =テーブル1[[#This Row],[対象部門]]&テーブル1[[#This Row],[業務要件回答表からの事前回答案_v1.0.xlsxより]] -> 一般会計全般・決算7.9 | B38: 一般会計全般・決算7.9 | D38: Req034 | E38: 売上高集計表、仕入高集計表が画面照会および帳票出力できること ※指定された会計期間における、売上対象勘定科目・仕入対象勘定科目の実績が集計された一覧 | F38: 売上仕入対象勘定の実績から売上高集計表・仕入高集計表を出力する機能 | G38: 7.9 | H38: サンスター | J38: 一般会計全般・決算 | K38: 決算G | O38: FO | Q38: 月次決算処理 | R38: 不要 | S38: 試算表で対象科目をフィルタすることで、売上高集計表・仕入高集計表を出力可能 または、ManagementReportで残高表を作成 | T38: IN | X38: =テーブル1[[#This Row],[開発]]&テーブル1[[#This Row],[スコープ]] -> 不要IN | Y38: =IF(テーブル1[[#This Row],[列1]]="不要IN","標準",IF(テーブル1[[#This Row],[列1]]="不要OUT","スコープアウト",IF(テーブル1[[#This Row],[列1]]="必要IN","アドオン",IF(テーブル1[[#This Row],[列1]]="OUT","スコープアウト","")))) -> 標準 | Z38: =VLOOKUP($B38,Sheet1!$C$2:$L$315,9,) -> 会計システム標準機能 | AA38: =VLOOKUP($B38,Sheet1!$C$2:$L$315,10,) -> 伝票トランザクションにてフィルタしてExcel出力での対応 | AB38: 標準 | AC38: =テーブル1[[#This Row],[要求事項一覧 判定]]=テーブル1[[#This Row],[列2]] -> TRUE
A39: =テーブル1[[#This Row],[対象部門]]&テーブル1[[#This Row],[業務要件回答表からの事前回答案_v1.0.xlsxより]] -> 一般会計全般・決算8.1 | B39: 一般会計全般・決算8.1 | D39: Req035 | E39: 接待交際費集計表が画面照会および帳票出力できること ※指定された会計期間(月次/年度等)における接待交際費の仕訳明細情報が、勘定科目、細目、月別等に集計された一覧 | F39: 接待交際費集計表を出力する機能 | G39: 8.1 | H39: サンスター | J39: 一般会計全般・決算 | K39: 決算G | M39: 楽楽精算で帳票出力しているが、財務分析コードに交際費分類を設定も可か。楽楽精算から補助科目でIF？（武市） | O39: FO | Q39: 税務 | R39: 不要 | S39: 試算表で対象科目をフィルタすることで、科目集計表を出力可能 または、ManagementReportで残高表を作成 | T39: IN | X39: =テーブル1[[#This Row],[開発]]&テーブル1[[#This Row],[スコープ]] -> 不要IN | Y39: =IF(テーブル1[[#This Row],[列1]]="不要IN","標準",IF(テーブル1[[#This Row],[列1]]="不要OUT","スコープアウト",IF(テーブル1[[#This Row],[列1]]="必要IN","アドオン",IF(テーブル1[[#This Row],[列1]]="OUT","スコープアウト","")))) -> 標準 | Z39: =VLOOKUP($B39,Sheet1!$C$2:$L$315,9,) -> 会計システム標準機能 | AA39: =VLOOKUP($B39,Sheet1!$C$2:$L$315,10,) -> 伝票トランザクションにてフィルタしてExcel出力での対応 | AB39: 標準 | AC39: =テーブル1[[#This Row],[要求事項一覧 判定]]=テーブル1[[#This Row],[列2]] -> TRUE
A40: =テーブル1[[#This Row],[対象部門]]&テーブル1[[#This Row],[業務要件回答表からの事前回答案_v1.0.xlsxより]] -> 一般会計全般・決算8.2 | B40: 一般会計全般・決算8.2 | D40: Req036 | E40: 消費税申告書と申告書作成に必要なデータが作成・出力できること | F40: 消費税申告書を作成・出力する機能 | G40: 8.2 | H40: サンスター | J40: 一般会計全般・決算 | K40: 決算G | M40: 現状、税務会計ソフト側で申告書を作成しているので その元データが出力できればよい。 | O40: FO | Q40: 税務 | R40: 不要 | T40: OUT | X40: =テーブル1[[#This Row],[開発]]&テーブル1[[#This Row],[スコープ]] -> 不要OUT | Y40: =IF(テーブル1[[#This Row],[列1]]="不要IN","標準",IF(テーブル1[[#This Row],[列1]]="不要OUT","スコープアウト",IF(テーブル1[[#This Row],[列1]]="必要IN","アドオン",IF(テーブル1[[#This Row],[列1]]="OUT","スコープアウト","")))) -> スコープアウト | Z40: =VLOOKUP($B40,Sheet1!$C$2:$L$315,9,) -> 会計システム標準機能 | AA40: =VLOOKUP($B40,Sheet1!$C$2:$L$315,10,) -> MRで対応 | AB40: 標準 | AC40: =テーブル1[[#This Row],[要求事項一覧 判定]]=テーブル1[[#This Row],[列2]] -> FALSE
A41: =テーブル1[[#This Row],[対象部門]]&テーブル1[[#This Row],[業務要件回答表からの事前回答案_v1.0.xlsxより]] -> 一般会計全般・決算8.3 | B41: 一般会計全般・決算8.3 | D41: Req037 | E41: 消費税の申告を行うこと | F41: 税務会計ソフトに消費税申告書作成に必要なデータを連携する機能 | G41: 8.3 | H41: サンスター | J41: 一般会計全般・決算 | K41: 決算G | L41: 標準の消費税トランザクションレポートをEXCEL出力して税務会計ソフトの取込フォーマットに変換して連携することが考えられるが、集計作業をEXCELで行う必要があり、データ量がおおいので、データ出力機能をアドオンすることを推奨 サンプル受領「SEJ2023年12月度_消費税申告書.xlsx」 | M41: SAPから出力したものをそのまま使用しているわけではなく、Excelで加工を行っているので この作業がシステムでカバーできるのであれば入力は複雑ではないので、データの連携はできなくてもよい。 算出に時間がかかっているので現状のレポートを確認して検討する。 | O41: FO | Q41: 税務 | R41: 必要 | S41: FOの消費税レコード情報を税務会計ソフトの取込フォーマットに変換して出力するようなアドオン機能が必要 | T41: IN | U41: SEJ2023年12月度_消費税申告書.xlsxの申告書フォームを想定した帳票出力 | V41: 〇 | W41: 標準機能で出せる元情報では難しいのか、要確認 | X41: =テーブル1[[#This Row],[開発]]&テーブル1[[#This Row],[スコープ]] -> 必要IN | Y41: =IF(テーブル1[[#This Row],[列1]]="不要IN","標準",IF(テーブル1[[#This Row],[列1]]="不要OUT","スコープアウト",IF(テーブル1[[#This Row],[列1]]="必要IN","アドオン",IF(テーブル1[[#This Row],[列1]]="OUT","スコープアウト","")))) -> アドオン | Z41: =VLOOKUP($B41,Sheet1!$C$2:$L$315,9,) -> 会計システム標準機能 | AA41: =VLOOKUP($B41,Sheet1!$C$2:$L$315,10,) -> 伝票トランザクションにてフィルタしてExcel出力での対応 | AB41: 標準 | AC41: =テーブル1[[#This Row],[要求事項一覧 判定]]=テーブル1[[#This Row],[列2]] -> FALSE
A42: =テーブル1[[#This Row],[対象部門]]&テーブル1[[#This Row],[業務要件回答表からの事前回答案_v1.0.xlsxより]] -> 一般会計全般・決算8.4 | B42: 一般会計全般・決算8.4 | D42: Req038 | E42: 法人税申告書と申告書作成に必要なデータが作成・出力できること | F42: 法人税申告書を作成・出力する機能 | G42: 8.4 | H42: サンスター | J42: 一般会計全般・決算 | K42: 決算G | M42: 現状、税務会計ソフト側で申告書を作成しているので その元データが出力できればよい。 | O42: FO | Q42: 税務 | R42: 不要 | T42: OUT | X42: =テーブル1[[#This Row],[開発]]&テーブル1[[#This Row],[スコープ]] -> 不要OUT | Y42: =IF(テーブル1[[#This Row],[列1]]="不要IN","標準",IF(テーブル1[[#This Row],[列1]]="不要OUT","スコープアウト",IF(テーブル1[[#This Row],[列1]]="必要IN","アドオン",IF(テーブル1[[#This Row],[列1]]="OUT","スコープアウト","")))) -> スコープアウト | Z42: =VLOOKUP($B42,Sheet1!$C$2:$L$315,9,) -> 会計システム標準機能 | AA42: =VLOOKUP($B42,Sheet1!$C$2:$L$315,10,) -> MRで対応 | AB42: 標準 | AC42: =テーブル1[[#This Row],[要求事項一覧 判定]]=テーブル1[[#This Row],[列2]] -> FALSE
A43: =テーブル1[[#This Row],[対象部門]]&テーブル1[[#This Row],[業務要件回答表からの事前回答案_v1.0.xlsxより]] -> 一般会計全般・決算8.5 | B43: 一般会計全般・決算8.5 | D43: Req039 | E43: 法人税の申告を行うこと | F43: 税務会計ソフトに法人税申告書作成に必要なデータを連携する機能 | G43: 8.5 | H43: サンスター | J43: 一般会計全般・決算 | K43: 決算G | L43: サンプル受領「202312_SEJ_税金計算ファイル(会計Final)」 へのインプットデータは、試算表データのイメージでよいか？ | M43: サンプル受領「202312_SEJ_税金計算ファイル(会計Final)」 会社によって出力が違うので、会計ソフトで連動が難しいと考えている。現在、手作業で加工しているものが一部ある。 Excel加工後のものが出力できるとよい。 2024/03/26 EXCEL上での加工作業が細かいので、Excel各シート加工後のものの出力までは不要。 各種対象科目の残高と明細を出力する機能があればよい。 | O43: FO | Q43: 税務 | R43: 必要 | S43: 現在、手作業でEXCEL加工しているデータを作成するアドオンを検討 試算表データイメージの出力でよいか？ | T43: IN | U43: 各種対象科目の残高と明細を出力するMR設定を検討 MRでは集計表からドリルダウンして明細を表示する機能はあるが最初から明細表を出力する機能がないのでアドオン検討 | V43: 〇 | W43: 標準機能で出せる元情報では難しいのか、要確認 | X43: =テーブル1[[#This Row],[開発]]&テーブル1[[#This Row],[スコープ]] -> 必要IN | Y43: =IF(テーブル1[[#This Row],[列1]]="不要IN","標準",IF(テーブル1[[#This Row],[列1]]="不要OUT","スコープアウト",IF(テーブル1[[#This Row],[列1]]="必要IN","アドオン",IF(テーブル1[[#This Row],[列1]]="OUT","スコープアウト","")))) -> アドオン | Z43: =VLOOKUP($B43,Sheet1!$C$2:$L$315,9,) -> 会計システム標準機能 | AA43: =VLOOKUP($B43,Sheet1!$C$2:$L$315,10,) -> 伝票トランザクションにてフィルタしてExcel出力での対応 | AB43: 標準 | AC43: =テーブル1[[#This Row],[要求事項一覧 判定]]=テーブル1[[#This Row],[列2]] -> FALSE
A44: =テーブル1[[#This Row],[対象部門]]&テーブル1[[#This Row],[業務要件回答表からの事前回答案_v1.0.xlsxより]] -> 一般会計全般・決算8.6 | B44: 一般会計全般・決算8.6 | D44: Req040 | E44: 事業税申告書と申告書作成に必要なデータが作成・出力できること | F44: 事業税申告書を作成・出力する機能 | G44: 8.6 | H44: サンスター | J44: 一般会計全般・決算 | K44: 決算G | M44: 現状、税務会計ソフト側で申告書を作成しているので その元データが出力できればよい。 | O44: FO | Q44: 税務 | R44: 不要 | T44: OUT | X44: =テーブル1[[#This Row],[開発]]&テーブル1[[#This Row],[スコープ]] -> 不要OUT | Y44: =IF(テーブル1[[#This Row],[列1]]="不要IN","標準",IF(テーブル1[[#This Row],[列1]]="不要OUT","スコープアウト",IF(テーブル1[[#This Row],[列1]]="必要IN","アドオン",IF(テーブル1[[#This Row],[列1]]="OUT","スコープアウト","")))) -> スコープアウト | Z44: =VLOOKUP($B44,Sheet1!$C$2:$L$315,9,) -> 会計システム標準機能 | AA44: =VLOOKUP($B44,Sheet1!$C$2:$L$315,10,) -> MRで対応 | AB44: 標準 | AC44: =テーブル1[[#This Row],[要求事項一覧 判定]]=テーブル1[[#This Row],[列2]] -> FALSE
A45: =テーブル1[[#This Row],[対象部門]]&テーブル1[[#This Row],[業務要件回答表からの事前回答案_v1.0.xlsxより]] -> 一般会計全般・決算8.7 | B45: 一般会計全般・決算8.7 | D45: Req041 | E45: 事業税の申告を行うこと | F45: 税務会計ソフトに事業税申告書作成に必要なデータを連携する機能 | G45: 8.7 | H45: サンスター | J45: 一般会計全般・決算 | K45: 決算G | L45: サンプル受領「202312 外形標準資料」 対象勘定明細出力（相手勘定あり） 業務委託料や支払賃料 | M45: 会社によって出力が違うので、会計ソフトで連動が難しいと考えている。現在、手作業で加工しているものが一部ある。 Excel加工後のものが出力できるとよい。 | O45: FO | Q45: 税務 | R45: 必要 | S45: 現在、手作業でEXCEL加工しているデータを作成するアドオンを検討 対象勘定明細出力（相手勘定あり） 業務委託料や支払賃料 | T45: IN | U45: 原価要素と相手先の明細出力から 集計のキーとなる項目を追加してピポット集計を行っている。 業務受託料 派遣者員 相手先別に集計 支払賃料 事業所別に集計（相手勘定名称から事業所を判断） シート「資料 受取賃料」 シート「資料 業務委託 派遣社員」 シート「資料 支払賃料」 を作成するイメージ ※事業所コードの判定用テーブルの検討、相手先(仕入先マスタ)財務分析コードに設定するか？部門コードの集計構造で事業所が判断できるか？ | V45: 〇 | W45: 標準機能で出せる元情報では難しいのか、要確認 | X45: =テーブル1[[#This Row],[開発]]&テーブル1[[#This Row],[スコープ]] -> 必要IN | Y45: =IF(テーブル1[[#This Row],[列1]]="不要IN","標準",IF(テーブル1[[#This Row],[列1]]="不要OUT","スコープアウト",IF(テーブル1[[#This Row],[列1]]="必要IN","アドオン",IF(テーブル1[[#This Row],[列1]]="OUT","スコープアウト","")))) -> アドオン | Z45: =VLOOKUP($B45,Sheet1!$C$2:$L$315,9,) -> 会計システム標準機能 | AA45: =VLOOKUP($B45,Sheet1!$C$2:$L$315,10,) -> 伝票トランザクションにてフィルタしてExcel出力での対応 | AB45: 標準 | AC45: =テーブル1[[#This Row],[要求事項一覧 判定]]=テーブル1[[#This Row],[列2]] -> FALSE
A46: =テーブル1[[#This Row],[対象部門]]&テーブル1[[#This Row],[業務要件回答表からの事前回答案_v1.0.xlsxより]] -> 一般会計全般・決算9.1 | B46: 一般会計全般・決算9.1 | D46: Req042 | E46: 監査用に必要な資料を出力できること | F46: 監査用に必要な資料を出力する機能 | G46: 9.1 | H46: サンスター | J46: 一般会計全般・決算 | K46: 決算G | M46: 監査用の帳票があるわけではない。 監査法人に求められた資料を提出できればよいので、データが出力できれば良い。 | O46: FO | Q46: 税務 | R46: 不要 | S46: 試算表、伝票トランザクション、財務諸表等の機能を監査担当が参照可能となるロール設定を行う | T46: IN | X46: =テーブル1[[#This Row],[開発]]&テーブル1[[#This Row],[スコープ]] -> 不要IN | Y46: =IF(テーブル1[[#This Row],[列1]]="不要IN","標準",IF(テーブル1[[#This Row],[列1]]="不要OUT","スコープアウト",IF(テーブル1[[#This Row],[列1]]="必要IN","アドオン",IF(テーブル1[[#This Row],[列1]]="OUT","スコープアウト","")))) -> 標準 | Z46: =VLOOKUP($B46,Sheet1!$C$2:$L$315,9,) -> 会計システム標準機能 | AA46: =VLOOKUP($B46,Sheet1!$C$2:$L$315,10,) -> MRで対応 | AB46: 標準 | AC46: =テーブル1[[#This Row],[要求事項一覧 判定]]=テーブル1[[#This Row],[列2]] -> TRUE
A47: =テーブル1[[#This Row],[対象部門]]&テーブル1[[#This Row],[業務要件回答表からの事前回答案_v1.0.xlsxより]] -> 一般会計全般・決算9.2 | B47: 一般会計全般・決算9.2 | D47: Req043 | E47: 監査用に必要な増減調査用の資料を出力できること | F47: 監査用に必要な増減調査用の資料を出力できる機能 | G47: 9.2 | H47: サンスター | J47: 一般会計全般・決算 | K47: 決算G | M47: 監査用の帳票があるわけではない。 監査法人に求められた資料を提出できればよいので、データが出力できれば良い。 | O47: FO | Q47: 税務 | R47: 不要 | S47: 試算表、伝票トランザクション、財務諸表等の機能を監査担当が参照可能となるロール設定を行う | T47: IN | X47: =テーブル1[[#This Row],[開発]]&テーブル1[[#This Row],[スコープ]] -> 不要IN | Y47: =IF(テーブル1[[#This Row],[列1]]="不要IN","標準",IF(テーブル1[[#This Row],[列1]]="不要OUT","スコープアウト",IF(テーブル1[[#This Row],[列1]]="必要IN","アドオン",IF(テーブル1[[#This Row],[列1]]="OUT","スコープアウト","")))) -> 標準 | Z47: =VLOOKUP($B47,Sheet1!$C$2:$L$315,9,) -> 会計システムアドオン | AA47: =VLOOKUP($B47,Sheet1!$C$2:$L$315,10,) -> 新規帳票を開発。 | AB47: アドオン | AC47: =テーブル1[[#This Row],[要求事項一覧 判定]]=テーブル1[[#This Row],[列2]] -> FALSE
A48: =テーブル1[[#This Row],[対象部門]]&テーブル1[[#This Row],[業務要件回答表からの事前回答案_v1.0.xlsxより]] -> 一般会計全般・決算10.1 | B48: 一般会計全般・決算10.1 | D48: Req044 | E48: 月末・期末レートが定義できること | F48: 月末・期末レートを定義する機能 | G48: 10.1 | H48: サンスター | J48: 一般会計全般・決算 | K48: 事務管理G | M48: 通貨別入力とするため、レート定義が必要（武市） 日本3社については、外貨口座はUSドルのみであるため、USドルは外貨建てで入力する。 ※技研はホストにUSドルとユーロの換算レートを登録している→受注登録時の変換用 通常月は月末レートを翌月に適用するが、決算月は決算用と翌月用の2つで運用している。→適用レートを日付でコントロールできれば問題なし | O48: FO | Q48: 外貨再評価 | R48: 不要 | S48: 通貨の為替レート画面で登録。 | T48: IN | X48: =テーブル1[[#This Row],[開発]]&テーブル1[[#This Row],[スコープ]] -> 不要IN | Y48: =IF(テーブル1[[#This Row],[列1]]="不要IN","標準",IF(テーブル1[[#This Row],[列1]]="不要OUT","スコープアウト",IF(テーブル1[[#This Row],[列1]]="必要IN","アドオン",IF(テーブル1[[#This Row],[列1]]="OUT","スコープアウト","")))) -> 標準 | Z48: =VLOOKUP($B48,Sheet1!$C$2:$L$315,9,) -> 会計システム標準機能 | AA48: =VLOOKUP($B48,Sheet1!$C$2:$L$315,10,) -> 0 | AB48: 標準 | AC48: =テーブル1[[#This Row],[要求事項一覧 判定]]=テーブル1[[#This Row],[列2]] -> TRUE
A49: =テーブル1[[#This Row],[対象部門]]&テーブル1[[#This Row],[業務要件回答表からの事前回答案_v1.0.xlsxより]] -> 一般会計全般・決算10.2 | B49: 一般会計全般・決算10.2 | D49: Req045 | E49: 通貨毎に月末・期末レートを自動設定できること | F49: 指定された通貨の期末レートを自動設定する機能 | G49: 10.2 | H49: サンスター | J49: 一般会計全般・決算 | K49: 事務管理G | L49: 自動設定機能はない。 ※銀行WEBからのダウンロードデータのインポート機能を想定か？ ヨーロッパ中央銀行、ロシア中央銀行、OANDA Ratesの為替レートデータのインポート機能はあり。 | M49: R/3では日本円のみを扱っているため、決算チームでは為替レートの登録作業はない。 Dynamicsでは外貨を入れていきたいと考えている。 財務の方針としては外貨建てが必要、自動登録機能については今後検討予定。 会計システムの、為替レートの管理部署、登録部署も含めて確認する。 （12/30付レートをどう取得するかは別途検討） | O49: FO | Q49: 外貨再評価 | R49: 不要 | S49: 通貨の為替レート画面にEXCELアドインで登録。 | T49: IN | X49: =テーブル1[[#This Row],[開発]]&テーブル1[[#This Row],[スコープ]] -> 不要IN | Y49: =IF(テーブル1[[#This Row],[列1]]="不要IN","標準",IF(テーブル1[[#This Row],[列1]]="不要OUT","スコープアウト",IF(テーブル1[[#This Row],[列1]]="必要IN","アドオン",IF(テーブル1[[#This Row],[列1]]="OUT","スコープアウト","")))) -> 標準 | Z49: =VLOOKUP($B49,Sheet1!$C$2:$L$315,9,) -> 会計システム標準機能 | AA49: =VLOOKUP($B49,Sheet1!$C$2:$L$315,10,) -> 0 | AB49: 標準 | AC49: =テーブル1[[#This Row],[要求事項一覧 判定]]=テーブル1[[#This Row],[列2]] -> TRUE
A50: =テーブル1[[#This Row],[対象部門]]&テーブル1[[#This Row],[業務要件回答表からの事前回答案_v1.0.xlsxより]] -> 一般会計全般・決算11.1 | B50: 一般会計全般・決算11.1 | D50: Req046 | E50: 会計スケジュールをもとに、会計カレンダーが設定できること | F50: 会計スケジュールをもとに、会計カレンダーが設定する機能 | G50: 11.1 | H50: サンスター | J50: 一般会計全般・決算 | K50: 決算G | O50: FO | Q50: 月次決算処理 | R50: 不要 | S50: 会計カレンダー/元帳カレンダー機能あり。 | T50: IN | X50: =テーブル1[[#This Row],[開発]]&テーブル1[[#This Row],[スコープ]] -> 不要IN | Y50: =IF(テーブル1[[#This Row],[列1]]="不要IN","標準",IF(テーブル1[[#This Row],[列1]]="不要OUT","スコープアウト",IF(テーブル1[[#This Row],[列1]]="必要IN","アドオン",IF(テーブル1[[#This Row],[列1]]="OUT","スコープアウト","")))) -> 標準 | Z50: =VLOOKUP($B50,Sheet1!$C$2:$L$315,9,) -> 会計システム標準機能 | AA50: =VLOOKUP($B50,Sheet1!$C$2:$L$315,10,) -> 0 | AB50: 標準 | AC50: =テーブル1[[#This Row],[要求事項一覧 判定]]=テーブル1[[#This Row],[列2]] -> TRUE
A51: =テーブル1[[#This Row],[対象部門]]&テーブル1[[#This Row],[業務要件回答表からの事前回答案_v1.0.xlsxより]] -> 一般会計全般・決算11.2 | B51: 一般会計全般・決算11.2 | D51: Req047 | E51: 会計スケジュールをもとに、会計処理をオープン・クローズできること | F51: 会計スケジュールをもとに、会計処理をオープン・クローズする機能 | G51: 11.2 | H51: サンスター | J51: 一般会計全般・決算 | K51: 決算G | O51: FO | Q51: 月次決算処理 | R51: 不要 | S51: 元帳カレンダー画面で各会計月のオープン・クローズ処理が可能。 | T51: IN | X51: =テーブル1[[#This Row],[開発]]&テーブル1[[#This Row],[スコープ]] -> 不要IN | Y51: =IF(テーブル1[[#This Row],[列1]]="不要IN","標準",IF(テーブル1[[#This Row],[列1]]="不要OUT","スコープアウト",IF(テーブル1[[#This Row],[列1]]="必要IN","アドオン",IF(テーブル1[[#This Row],[列1]]="OUT","スコープアウト","")))) -> 標準 | Z51: =VLOOKUP($B51,Sheet1!$C$2:$L$315,9,) -> 会計システム標準機能 | AA51: =VLOOKUP($B51,Sheet1!$C$2:$L$315,10,) -> 0 | AB51: 標準 | AC51: =テーブル1[[#This Row],[要求事項一覧 判定]]=テーブル1[[#This Row],[列2]] -> TRUE
A52: =テーブル1[[#This Row],[対象部門]]&テーブル1[[#This Row],[業務要件回答表からの事前回答案_v1.0.xlsxより]] -> 一般会計全般・決算11.3 | B52: 一般会計全般・決算11.3 | D52: Req048 | E52: 機能(帳票閲覧権限等）をユーザ別に制限できること | F52: 機能をユーザ別に制限する機能 | G52: 11.3 | H52: サンスター | J52: 一般会計全般・決算 | K52: 決算G | O52: FO | Q52: 月次決算処理 | R52: 不要 | S52: ロールセキュリティ機能とManagementReport上での設定により権限設定が可能。 | T52: IN | X52: =テーブル1[[#This Row],[開発]]&テーブル1[[#This Row],[スコープ]] -> 不要IN | Y52: =IF(テーブル1[[#This Row],[列1]]="不要IN","標準",IF(テーブル1[[#This Row],[列1]]="不要OUT","スコープアウト",IF(テーブル1[[#This Row],[列1]]="必要IN","アドオン",IF(テーブル1[[#This Row],[列1]]="OUT","スコープアウト","")))) -> 標準 | Z52: =VLOOKUP($B52,Sheet1!$C$2:$L$315,9,) -> 会計システム標準機能 | AA52: =VLOOKUP($B52,Sheet1!$C$2:$L$315,10,) -> 標準レポートは制限可能。MR機能で作成した追加帳票は制限不可 | AB52: 標準 | AC52: =テーブル1[[#This Row],[要求事項一覧 判定]]=テーブル1[[#This Row],[列2]] -> TRUE
A53: =テーブル1[[#This Row],[対象部門]]&テーブル1[[#This Row],[業務要件回答表からの事前回答案_v1.0.xlsxより]] -> 一般会計全般・決算11.4 | B53: 一般会計全般・決算11.4 | D53: Req049 | E53: 承認依頼受領時に、アラートで通知できること | F53: 承認依頼受領時に、アラートで通知する機能 | G53: 11.4 | H53: サンスター | J53: 一般会計全般・決算 | K53: 決算G | O53: FO | Q53: 日次振伝処理 | R53: 不要 | S53: FOの画面上での通知とメールでの通知が可能。 | T53: IN | X53: =テーブル1[[#This Row],[開発]]&テーブル1[[#This Row],[スコープ]] -> 不要IN | Y53: =IF(テーブル1[[#This Row],[列1]]="不要IN","標準",IF(テーブル1[[#This Row],[列1]]="不要OUT","スコープアウト",IF(テーブル1[[#This Row],[列1]]="必要IN","アドオン",IF(テーブル1[[#This Row],[列1]]="OUT","スコープアウト","")))) -> 標準 | Z53: =VLOOKUP($B53,Sheet1!$C$2:$L$315,9,) -> 会計システム標準機能 | AA53: =VLOOKUP($B53,Sheet1!$C$2:$L$315,10,) -> 0 | AB53: 標準 | AC53: =テーブル1[[#This Row],[要求事項一覧 判定]]=テーブル1[[#This Row],[列2]] -> TRUE
A54: =テーブル1[[#This Row],[対象部門]]&テーブル1[[#This Row],[業務要件回答表からの事前回答案_v1.0.xlsxより]] -> 一般会計全般・決算11.5 | B54: 一般会計全般・決算11.5 | D54: Req050 | E54: 仕訳承認時に組織階層、レポートラインに沿った承認ルート設定ができ、自動で承認を流すことができること | F54: 仕訳承認時の組織階層、レポートラインに沿った承認ルートを設定する機能 | G54: 11.5 | H54: サンスター | J54: 一般会計全般・決算 | K54: 決算G | O54: FO | Q54: 日次振伝処理 | R54: 不要 | S54: 仕訳帳毎に承認ルートを設定可能。 | T54: IN | X54: =テーブル1[[#This Row],[開発]]&テーブル1[[#This Row],[スコープ]] -> 不要IN | Y54: =IF(テーブル1[[#This Row],[列1]]="不要IN","標準",IF(テーブル1[[#This Row],[列1]]="不要OUT","スコープアウト",IF(テーブル1[[#This Row],[列1]]="必要IN","アドオン",IF(テーブル1[[#This Row],[列1]]="OUT","スコープアウト","")))) -> 標準 | Z54: =VLOOKUP($B54,Sheet1!$C$2:$L$315,9,) -> 会計システム標準機能 | AA54: =VLOOKUP($B54,Sheet1!$C$2:$L$315,10,) -> 承認依頼ボタンの押下は必要 | AB54: 標準 | AC54: =テーブル1[[#This Row],[要求事項一覧 判定]]=テーブル1[[#This Row],[列2]] -> TRUE
A55: =テーブル1[[#This Row],[対象部門]]&テーブル1[[#This Row],[業務要件回答表からの事前回答案_v1.0.xlsxより]] -> 一般会計全般・決算11.6 | B55: 一般会計全般・決算11.6 | D55: Req051 | E55: 承認者が代理承認者を任意で設定でき、レポートラインが代理の場合設定できること | F55: 代理承認者を指定できる機能 | G55: 11.6 | H55: サンスター | J55: 一般会計全般・決算 | K55: 決算G | O55: FO | Q55: 日次振伝処理 | R55: 不要 | S55: 仕訳帳毎に承認ルートを設定可能。代理承認の設定も可能。 | T55: IN | X55: =テーブル1[[#This Row],[開発]]&テーブル1[[#This Row],[スコープ]] -> 不要IN | Y55: =IF(テーブル1[[#This Row],[列1]]="不要IN","標準",IF(テーブル1[[#This Row],[列1]]="不要OUT","スコープアウト",IF(テーブル1[[#This Row],[列1]]="必要IN","アドオン",IF(テーブル1[[#This Row],[列1]]="OUT","スコープアウト","")))) -> 標準 | Z55: =VLOOKUP($B55,Sheet1!$C$2:$L$315,9,) -> 会計システム標準機能 | AA55: =VLOOKUP($B55,Sheet1!$C$2:$L$315,10,) -> 承認者変更の機能はある | AB55: 標準 | AC55: =テーブル1[[#This Row],[要求事項一覧 判定]]=テーブル1[[#This Row],[列2]] -> TRUE
A56: =テーブル1[[#This Row],[対象部門]]&テーブル1[[#This Row],[業務要件回答表からの事前回答案_v1.0.xlsxより]] -> 一般会計全般・決算11.7 | B56: 一般会計全般・決算11.7 | D56: Req052 | E56: 勘定科目を定義できること | F56: 勘定科目を定義する機能 | G56: 11.7 | H56: サンスター | J56: 一般会計全般・決算 | K56: 決算G | O56: FO | Q56: 日次振伝処理 | R56: 不要 | S56: 勘定科目表 主勘定マスタ で定義可能。 | T56: IN | X56: =テーブル1[[#This Row],[開発]]&テーブル1[[#This Row],[スコープ]] -> 不要IN | Y56: =IF(テーブル1[[#This Row],[列1]]="不要IN","標準",IF(テーブル1[[#This Row],[列1]]="不要OUT","スコープアウト",IF(テーブル1[[#This Row],[列1]]="必要IN","アドオン",IF(テーブル1[[#This Row],[列1]]="OUT","スコープアウト","")))) -> 標準 | Z56: =VLOOKUP($B56,Sheet1!$C$2:$L$315,9,) -> 会計システム標準機能 | AA56: =VLOOKUP($B56,Sheet1!$C$2:$L$315,10,) -> 0 | AB56: 標準 | AC56: =テーブル1[[#This Row],[要求事項一覧 判定]]=テーブル1[[#This Row],[列2]] -> TRUE
A57: =テーブル1[[#This Row],[対象部門]]&テーブル1[[#This Row],[業務要件回答表からの事前回答案_v1.0.xlsxより]] -> 一般会計全般・決算11.8 | B57: 一般会計全般・決算11.8 | D57: Req053 | E57: 勘定科目に対して紐づく部門、取引先、取引内容等を設定できること | F57: 勘定科目によって入力項目を制限できる機能 | G57: 11.8 | H57: サンスター | J57: 一般会計全般・決算 | K57: 決算G | O57: FO | Q57: 日次振伝処理 | R57: 不要 | S57: 勘定構造のコンフィグレーションで入力制御が可能。 | T57: IN | X57: =テーブル1[[#This Row],[開発]]&テーブル1[[#This Row],[スコープ]] -> 不要IN | Y57: =IF(テーブル1[[#This Row],[列1]]="不要IN","標準",IF(テーブル1[[#This Row],[列1]]="不要OUT","スコープアウト",IF(テーブル1[[#This Row],[列1]]="必要IN","アドオン",IF(テーブル1[[#This Row],[列1]]="OUT","スコープアウト","")))) -> 標準 | Z57: =VLOOKUP($B57,Sheet1!$C$2:$L$315,9,) -> 会計システム標準機能 | AA57: =VLOOKUP($B57,Sheet1!$C$2:$L$315,10,) -> 財務分析コードを使用して対応可能 | AB57: 標準 | AC57: =テーブル1[[#This Row],[要求事項一覧 判定]]=テーブル1[[#This Row],[列2]] -> TRUE
A58: =テーブル1[[#This Row],[対象部門]]&テーブル1[[#This Row],[業務要件回答表からの事前回答案_v1.0.xlsxより]] -> 一般会計全般・決算12.1 | B58: 一般会計全般・決算12.1 | D58: Req054 | E58: 月次毎に下記の仕訳を登録できること ・消費税、印紙税納付 ・監査報酬月次計上 ・持株会拠出、購入 | F58: 月次毎に決算仕訳が登録できる機能 | G58: 12.1 | H58: サンスター | J58: 一般会計全般・決算 | K58: 決算G | O58: FO | Q58: 月次決算処理 | R58: 不要 | S58: 一般仕訳帳で登録可能。 | T58: IN | X58: =テーブル1[[#This Row],[開発]]&テーブル1[[#This Row],[スコープ]] -> 不要IN | Y58: =IF(テーブル1[[#This Row],[列1]]="不要IN","標準",IF(テーブル1[[#This Row],[列1]]="不要OUT","スコープアウト",IF(テーブル1[[#This Row],[列1]]="必要IN","アドオン",IF(テーブル1[[#This Row],[列1]]="OUT","スコープアウト","")))) -> 標準 | Z58: =VLOOKUP($B58,Sheet1!$C$2:$L$315,9,) -> 会計システム標準機能 | AA58: =VLOOKUP($B58,Sheet1!$C$2:$L$315,10,) -> 一般的な仕訳等の登録用と異なるレイヤー(仕訳帳)に仕訳登録し、レポート側でどのレイヤーを出力するかの定義で対応可能 | AB58: 標準 | AC58: =テーブル1[[#This Row],[要求事項一覧 判定]]=テーブル1[[#This Row],[列2]] -> TRUE
A59: =テーブル1[[#This Row],[対象部門]]&テーブル1[[#This Row],[業務要件回答表からの事前回答案_v1.0.xlsxより]] -> 一般会計全般・決算12.2 | B59: 一般会計全般・決算12.2 | D59: Req055 | E59: 半期毎に以下の仕訳を登録できること ・資産除去債務・償却費計上 ・投資有価証券時価洗替 ・ECサイト売上計上 ・減損計上 ・ゴルフ会員権評価損の貸倒引当 ・在庫評価減・原価差額振替 | F59: 半期毎に決算仕訳が登録できる機能 | G59: 12.2 | H59: サンスター | J59: 一般会計全般・決算 | K59: 決算G | L59: 一般仕訳帳で登録可能。 ※月次決算伝票登録前試算表と登録後試算表の出力を切り替えたいなどの要件があるか | M59: 12.1,12.2に記載してある伝票については基本、楽楽精算に入れている。Dynamicsに入れる想定はない。 減損の計上、在庫の評価減・原価差額振替についてはSAPで処理をしている。 減損については固定資産台帳で処理をするとSAPに反映されるようになっている。 在庫の評価減・原価差額振替についてはSSJは一部SAPで行っているので、その部分の登録ができればよい。 楽楽精算の振替伝票をこの機会になくそうと検討している。 ※決算伝票登録前試算表と登録後試算表の出力を切り替えたいなどの要件はない。 | O59: FO | Q59: 半期決算処理 | R59: 不要 | S59: 一般仕訳帳で登録可能。 | T59: IN | X59: =テーブル1[[#This Row],[開発]]&テーブル1[[#This Row],[スコープ]] -> 不要IN | Y59: =IF(テーブル1[[#This Row],[列1]]="不要IN","標準",IF(テーブル1[[#This Row],[列1]]="不要OUT","スコープアウト",IF(テーブル1[[#This Row],[列1]]="必要IN","アドオン",IF(テーブル1[[#This Row],[列1]]="OUT","スコープアウト","")))) -> 標準 | Z59: =VLOOKUP($B59,Sheet1!$C$2:$L$315,9,) -> 会計システム標準機能 | AA59: =VLOOKUP($B59,Sheet1!$C$2:$L$315,10,) -> 一般的な仕訳等の登録用と異なるレイヤー(仕訳帳)に仕訳登録し、レポート側でどのレイヤーを出力するかの定義で対応可能 | AB59: 標準 | AC59: =テーブル1[[#This Row],[要求事項一覧 判定]]=テーブル1[[#This Row],[列2]] -> TRUE
A60: =テーブル1[[#This Row],[対象部門]]&テーブル1[[#This Row],[業務要件回答表からの事前回答案_v1.0.xlsxより]] -> 一般会計全般・決算12.3 | B60: 一般会計全般・決算12.3 | D60: Req056 | E60: 半期毎に以下の税金計算に関わる仕訳を登録できること ・未払消費税照合・計上 ・法人税等計算 ・税効果計算 ・税金伝票入力 | F60: 半期毎に税金計算に関わる仕訳が登録できる機能 | G60: 12.3 | H60: サンスター | J60: 一般会計全般・決算 | K60: 決算G | L60: 一般仕訳帳で登録可能。 ※半期決算伝票登録前試算表と登録後試算表の出力を切り替えたいなどの要件があるか | M60: 同上 ※決算伝票登録前試算表と登録後試算表の出力を切り替えたいなどの要件はない。 | O60: FO | Q60: 半期決算処理 | R60: 不要 | S60: 一般仕訳帳で登録可能。 | T60: IN | X60: =テーブル1[[#This Row],[開発]]&テーブル1[[#This Row],[スコープ]] -> 不要IN | Y60: =IF(テーブル1[[#This Row],[列1]]="不要IN","標準",IF(テーブル1[[#This Row],[列1]]="不要OUT","スコープアウト",IF(テーブル1[[#This Row],[列1]]="必要IN","アドオン",IF(テーブル1[[#This Row],[列1]]="OUT","スコープアウト","")))) -> 標準 | Z60: =VLOOKUP($B60,Sheet1!$C$2:$L$315,9,) -> 会計システム標準機能 | AA60: =VLOOKUP($B60,Sheet1!$C$2:$L$315,10,) -> 一般的な仕訳等の登録用と異なるレイヤー(仕訳帳)に仕訳登録し、レポート側でどのレイヤーを出力するかの定義で対応可能 | AB60: 標準 | AC60: =テーブル1[[#This Row],[要求事項一覧 判定]]=テーブル1[[#This Row],[列2]] -> TRUE
A61: =テーブル1[[#This Row],[対象部門]]&テーブル1[[#This Row],[業務要件回答表からの事前回答案_v1.0.xlsxより]] -> 一般会計全般・決算13.1 | B61: 一般会計全般・決算13.1 | D61: Req057 | E61: 外貨建てのB/S科目を、期末レートで未実現為替差損益を再計算できること | F61: 未実現為替差損益を算定するために、外貨建てのB/S科目を期末レートで再計算する機能 | G61: 13.1 | H61: サンスター | J61: 一般会計全般・決算 | K61: 決算G | O61: FO | Q61: 外貨再評価 | R61: 不要 | S61: 外貨再評価機能あり。 | T61: IN | X61: =テーブル1[[#This Row],[開発]]&テーブル1[[#This Row],[スコープ]] -> 不要IN | Y61: =IF(テーブル1[[#This Row],[列1]]="不要IN","標準",IF(テーブル1[[#This Row],[列1]]="不要OUT","スコープアウト",IF(テーブル1[[#This Row],[列1]]="必要IN","アドオン",IF(テーブル1[[#This Row],[列1]]="OUT","スコープアウト","")))) -> 標準 | Z61: =VLOOKUP($B61,Sheet1!$C$2:$L$315,9,) -> 会計システム標準機能 | AA61: =VLOOKUP($B61,Sheet1!$C$2:$L$315,10,) -> 0 | AB61: 標準 | AC61: =テーブル1[[#This Row],[要求事項一覧 判定]]=テーブル1[[#This Row],[列2]] -> TRUE
A62: =テーブル1[[#This Row],[対象部門]]&テーブル1[[#This Row],[業務要件回答表からの事前回答案_v1.0.xlsxより]] -> 一般会計全般・決算13.2 | B62: 一般会計全般・決算13.2 | D62: Req058 | E62: 外貨建て取引残高を勘定科目別に画面照会および帳票出力できること | F62: 期末評価替え後の通貨別残高を把握するために、勘定科目別に外貨建て取引の残高を出力する機能 | G62: 13.2 | H62: サンスター | J62: 一般会計全般・決算 | K62: 決算G | N62: Req159 | O62: FO | Q62: 外貨再評価 | R62: 不要 | S62: 試算表照会画面で通貨別残高の確認が可能。 B/S科目だけでなく、PL科目についても外貨建てで登録する必要があるか確認要 20240411 決算・資金・事務管理G確認 標準機能で対応する方針となった | T62: IN | X62: =テーブル1[[#This Row],[開発]]&テーブル1[[#This Row],[スコープ]] -> 不要IN | Y62: =IF(テーブル1[[#This Row],[列1]]="不要IN","標準",IF(テーブル1[[#This Row],[列1]]="不要OUT","スコープアウト",IF(テーブル1[[#This Row],[列1]]="必要IN","アドオン",IF(テーブル1[[#This Row],[列1]]="OUT","スコープアウト","")))) -> 標準 | Z62: =VLOOKUP($B62,Sheet1!$C$2:$L$315,9,) -> 会計システム標準機能 | AA62: =VLOOKUP($B62,Sheet1!$C$2:$L$315,10,) -> 0 | AB62: 標準 | AC62: =テーブル1[[#This Row],[要求事項一覧 判定]]=テーブル1[[#This Row],[列2]] -> TRUE
A63: =テーブル1[[#This Row],[対象部門]]&テーブル1[[#This Row],[業務要件回答表からの事前回答案_v1.0.xlsxより]] -> 一般会計全般・決算14.1 | B63: 一般会計全般・決算14.1 | D63: Req059 | E63: 会計システム内で月次の試算表/PL/BSと各種勘定残高明細を参照し、月次締め処理ができること | F63: 月次の締め処理を行う機能 | G63: 14.1 | H63: サンスター | J63: 一般会計全般・決算 | K63: 決算G | O63: FO | Q63: 月次決算処理 | R63: 不要 | S63: 試算表で残高および明細確認可能。 元帳カレンダーで月次締め処理が可能。 | T63: IN | X63: =テーブル1[[#This Row],[開発]]&テーブル1[[#This Row],[スコープ]] -> 不要IN | Y63: =IF(テーブル1[[#This Row],[列1]]="不要IN","標準",IF(テーブル1[[#This Row],[列1]]="不要OUT","スコープアウト",IF(テーブル1[[#This Row],[列1]]="必要IN","アドオン",IF(テーブル1[[#This Row],[列1]]="OUT","スコープアウト","")))) -> 標準 | Z63: =VLOOKUP($B63,Sheet1!$C$2:$L$315,9,) -> 会計システム標準機能 | AA63: =VLOOKUP($B63,Sheet1!$C$2:$L$315,10,) -> 0 | AB63: 標準 | AC63: =テーブル1[[#This Row],[要求事項一覧 判定]]=テーブル1[[#This Row],[列2]] -> TRUE
A64: =テーブル1[[#This Row],[対象部門]]&テーブル1[[#This Row],[業務要件回答表からの事前回答案_v1.0.xlsxより]] -> 一般会計全般・決算14.2 | B64: 一般会計全般・決算14.2 | D64: Req060 | E64: 会計システム内で年次の試算表/PL/BSと各種勘定残高明細を参照し、年次締め処理ができること | F64: 会計年度の締め処理を行う機能 | G64: 14.2 | H64: サンスター | J64: 一般会計全般・決算 | K64: 決算G | O64: FO | Q64: 年次決算処理 | R64: 不要 | S64: 試算表で残高および明細確認可能。 年度末決算で年次締め処理が可能。 | T64: IN | X64: =テーブル1[[#This Row],[開発]]&テーブル1[[#This Row],[スコープ]] -> 不要IN | Y64: =IF(テーブル1[[#This Row],[列1]]="不要IN","標準",IF(テーブル1[[#This Row],[列1]]="不要OUT","スコープアウト",IF(テーブル1[[#This Row],[列1]]="必要IN","アドオン",IF(テーブル1[[#This Row],[列1]]="OUT","スコープアウト","")))) -> 標準 | Z64: =VLOOKUP($B64,Sheet1!$C$2:$L$315,9,) -> 会計システム標準機能 | AA64: =VLOOKUP($B64,Sheet1!$C$2:$L$315,10,) -> 0 | AB64: 標準 | AC64: =テーブル1[[#This Row],[要求事項一覧 判定]]=テーブル1[[#This Row],[列2]] -> TRUE
A65: =テーブル1[[#This Row],[対象部門]]&テーブル1[[#This Row],[業務要件回答表からの事前回答案_v1.0.xlsxより]] -> 一般会計全般・決算14.3 | B65: 一般会計全般・決算14.3 | D65: Req061 | E65: 前年度末の残高を翌年度の期首残高として自動で行うことができること クローズする年度の処理(残高繰越、年度クローズ)と、オープンする年度の処理(開始残高設定、年度オープン)をそれぞれの視点で記載しております。 | F65: 会計年度の切替において期首残高を自動で繰越する機能 | G65: 14.3 | H65: サンスター | J65: 一般会計全般・決算 | K65: 決算G | O65: FO | Q65: 年次決算処理 | R65: 不要 | S65: 年度末決算機能で繰越残高は自動設定される。 | T65: IN | X65: =テーブル1[[#This Row],[開発]]&テーブル1[[#This Row],[スコープ]] -> 不要IN | Y65: =IF(テーブル1[[#This Row],[列1]]="不要IN","標準",IF(テーブル1[[#This Row],[列1]]="不要OUT","スコープアウト",IF(テーブル1[[#This Row],[列1]]="必要IN","アドオン",IF(テーブル1[[#This Row],[列1]]="OUT","スコープアウト","")))) -> 標準 | Z65: =VLOOKUP($B65,Sheet1!$C$2:$L$315,9,) -> 会計システム標準機能 | AA65: =VLOOKUP($B65,Sheet1!$C$2:$L$315,10,) -> 0 | AB65: 標準 | AC65: =テーブル1[[#This Row],[要求事項一覧 判定]]=テーブル1[[#This Row],[列2]] -> TRUE
A66: =テーブル1[[#This Row],[対象部門]]&テーブル1[[#This Row],[業務要件回答表からの事前回答案_v1.0.xlsxより]] -> 一般会計全般・決算14.4 | B66: 一般会計全般・決算14.4 | D66: Req062 | E66: 当会計年度で会計処理を開始できるように期首残高を自動で設定することができること | F66: 会計年度の開始できるように期首残高を自動で設定する機能 | G66: 14.4 | H66: サンスター | J66: 一般会計全般・決算 | K66: 決算G | O66: FO | Q66: 年次決算処理 | R66: 不要 | S66: 年度末決算機能で繰越残高は自動設定される。 | T66: IN | X66: =テーブル1[[#This Row],[開発]]&テーブル1[[#This Row],[スコープ]] -> 不要IN | Y66: =IF(テーブル1[[#This Row],[列1]]="不要IN","標準",IF(テーブル1[[#This Row],[列1]]="不要OUT","スコープアウト",IF(テーブル1[[#This Row],[列1]]="必要IN","アドオン",IF(テーブル1[[#This Row],[列1]]="OUT","スコープアウト","")))) -> 標準 | Z66: =VLOOKUP($B66,Sheet1!$C$2:$L$315,9,) -> 会計システム標準機能 | AA66: =VLOOKUP($B66,Sheet1!$C$2:$L$315,10,) -> 0 | AB66: 標準 | AC66: =テーブル1[[#This Row],[要求事項一覧 判定]]=テーブル1[[#This Row],[列2]] -> TRUE
A67: =テーブル1[[#This Row],[対象部門]]&テーブル1[[#This Row],[業務要件回答表からの事前回答案_v1.0.xlsxより]] -> 一般会計全般・決算15.1 | B67: 一般会計全般・決算15.1 | D67: Req063 | E67: 半期毎に倉庫一覧データと在庫データを用いて在庫の棚卸を実施し、棚卸差損益を計上できること 会計システムでは在庫管理を実施しないため、棚卸結果を仕訳データとして反映するというご理解で合っています。 | F67: 半期末時点における棚卸差損益を登録できる機能 | G67: 15.1 | H67: サンスター | J67: 一般会計全般・決算 | K67: 決算G | O67: FO | Q67: 半期決算処理 | R67: 不要 | S67: 一般仕訳帳で登録可能。 | T67: IN | X67: =テーブル1[[#This Row],[開発]]&テーブル1[[#This Row],[スコープ]] -> 不要IN | Y67: =IF(テーブル1[[#This Row],[列1]]="不要IN","標準",IF(テーブル1[[#This Row],[列1]]="不要OUT","スコープアウト",IF(テーブル1[[#This Row],[列1]]="必要IN","アドオン",IF(テーブル1[[#This Row],[列1]]="OUT","スコープアウト","")))) -> 標準 | Z67: =VLOOKUP($B67,Sheet1!$C$2:$L$315,9,) -> 会計システム標準機能 | AA67: =VLOOKUP($B67,Sheet1!$C$2:$L$315,10,) -> 外部ツールでの作成された棚卸結果の金額のみ、仕訳伝票登録する | AB67: 標準 | AC67: =テーブル1[[#This Row],[要求事項一覧 判定]]=テーブル1[[#This Row],[列2]] -> TRUE
A68: =テーブル1[[#This Row],[対象部門]]&テーブル1[[#This Row],[業務要件回答表からの事前回答案_v1.0.xlsxより]] -> 一般会計全般・決算15.2 | B68: 一般会計全般・決算15.2 | D68: Req064 | E68: 配当金支払の仕訳を登録できること | F68: 配当金支払の仕訳を登録できる機能 | G68: 15.2 | H68: サンスター | J68: 一般会計全般・決算 | K68: 決算G | O68: FO | Q68: 半期決算処理 | R68: 不要 | S68: 一般仕訳帳で登録可能。 | T68: IN | X68: =テーブル1[[#This Row],[開発]]&テーブル1[[#This Row],[スコープ]] -> 不要IN | Y68: =IF(テーブル1[[#This Row],[列1]]="不要IN","標準",IF(テーブル1[[#This Row],[列1]]="不要OUT","スコープアウト",IF(テーブル1[[#This Row],[列1]]="必要IN","アドオン",IF(テーブル1[[#This Row],[列1]]="OUT","スコープアウト","")))) -> 標準 | Z68: =VLOOKUP($B68,Sheet1!$C$2:$L$315,9,) -> 会計システム標準機能 | AA68: =VLOOKUP($B68,Sheet1!$C$2:$L$315,10,) -> 繰越利益剰余金の仕訳処理等を含め、マニュアルで仕訳登録いただく前提 | AB68: 標準 | AC68: =テーブル1[[#This Row],[要求事項一覧 判定]]=テーブル1[[#This Row],[列2]] -> TRUE
A69: =テーブル1[[#This Row],[対象部門]]&テーブル1[[#This Row],[業務要件回答表からの事前回答案_v1.0.xlsxより]] -> 一般会計全般・決算15.3 | B69: 一般会計全般・決算15.3 | D69: Req065 | E69: 受取配当金の計上仕訳を登録できること | F69: 受取配当金の計上仕訳を登録できる機能 | G69: 15.3 | H69: サンスター | J69: 一般会計全般・決算 | K69: 決算G | O69: FO | Q69: 半期決算処理 | R69: 不要 | S69: 一般仕訳帳で登録可能。 | T69: IN | X69: =テーブル1[[#This Row],[開発]]&テーブル1[[#This Row],[スコープ]] -> 不要IN | Y69: =IF(テーブル1[[#This Row],[列1]]="不要IN","標準",IF(テーブル1[[#This Row],[列1]]="不要OUT","スコープアウト",IF(テーブル1[[#This Row],[列1]]="必要IN","アドオン",IF(テーブル1[[#This Row],[列1]]="OUT","スコープアウト","")))) -> 標準 | Z69: =VLOOKUP($B69,Sheet1!$C$2:$L$315,9,) -> 会計システム標準機能 | AA69: =VLOOKUP($B69,Sheet1!$C$2:$L$315,10,) -> 税金処理等を含め、マニュアルで仕訳登録いただく前提 | AB69: 標準 | AC69: =テーブル1[[#This Row],[要求事項一覧 判定]]=テーブル1[[#This Row],[列2]] -> TRUE
A70: =テーブル1[[#This Row],[対象部門]]&テーブル1[[#This Row],[業務要件回答表からの事前回答案_v1.0.xlsxより]] -> 一般会計全般・決算16.1 | B70: 一般会計全般・決算16.1 | D70: Req066 | E70: 日本基準/IFRS/税務でそれぞれ異なる基準で帳簿作成・保存できること (Ex.日本基準とIFRSで固定資産台帳を別々で作成できること等) | F70: 日本基準/IFRS/税務用の帳簿が作成できること | G70: 16.1 | H70: サンスター | J70: 一般会計全般・決算 | K70: 決算G | O70: FO | Q70: IFRS伝票処理 | R70: 必要 | S70: 転記階層機能を使用することで、日本基準用のトランザクションとは別にIFRSまたは税務用の仕訳伝票の登録が可能。 試算表照会画面やManagementReport帳票で日本基準伝票とIFRS調整伝票とを合計して出力表示可能。 | T70: IN | V70: × | W70: MRでできるのであれば審査対象外 | X70: =テーブル1[[#This Row],[開発]]&テーブル1[[#This Row],[スコープ]] -> 必要IN | Y70: =IF(テーブル1[[#This Row],[列1]]="不要IN","標準",IF(テーブル1[[#This Row],[列1]]="不要OUT","スコープアウト",IF(テーブル1[[#This Row],[列1]]="必要IN","アドオン",IF(テーブル1[[#This Row],[列1]]="OUT","スコープアウト","")))) -> アドオン | Z70: =VLOOKUP($B70,Sheet1!$C$2:$L$315,9,) -> 会計システム標準機能 | AA70: =VLOOKUP($B70,Sheet1!$C$2:$L$315,10,) -> 一般的な仕訳等の登録用と異なるレイヤー(仕訳帳)に仕訳登録し、レポート側でどのレイヤーを出力するかの定義で対応可能 | AB70: 標準 | AC70: =テーブル1[[#This Row],[要求事項一覧 判定]]=テーブル1[[#This Row],[列2]] -> FALSE
A71: =テーブル1[[#This Row],[対象部門]]&テーブル1[[#This Row],[業務要件回答表からの事前回答案_v1.0.xlsxより]] -> 一般会計全般・決算16.2 | B71: 一般会計全般・決算16.2 | D71: Req067 | E71: 連結決算用のIFRSベースのTBを作成できること | F71: IFRSベースのTBの作成機能(IFRS開示用科目(親科目)とIFRS集計元科目(子科目)単位でそれぞれ閲覧できること) | G71: 16.2 | H71: サンスター | J71: 一般会計全般・決算 | K71: 決算G | O71: FO | Q71: IFRS伝票処理 | R71: 必要 | S71: ManagementReportでIFRSベースの帳票を作成 | T71: IN | V71: × | W71: MRでできるのであれば審査対象外 | X71: =テーブル1[[#This Row],[開発]]&テーブル1[[#This Row],[スコープ]] -> 必要IN | Y71: =IF(テーブル1[[#This Row],[列1]]="不要IN","標準",IF(テーブル1[[#This Row],[列1]]="不要OUT","スコープアウト",IF(テーブル1[[#This Row],[列1]]="必要IN","アドオン",IF(テーブル1[[#This Row],[列1]]="OUT","スコープアウト","")))) -> アドオン | Z71: =VLOOKUP($B71,Sheet1!$C$2:$L$315,9,) -> 会計システム標準機能 | AA71: =VLOOKUP($B71,Sheet1!$C$2:$L$315,10,) -> TB(残高試算表）はMRで対応 | AB71: 標準 | AC71: =テーブル1[[#This Row],[要求事項一覧 判定]]=テーブル1[[#This Row],[列2]] -> FALSE
A72: =テーブル1[[#This Row],[対象部門]]&テーブル1[[#This Row],[業務要件回答表からの事前回答案_v1.0.xlsxより]] -> 一般会計全般・決算16.3 | B72: 一般会計全般・決算16.3 | D72: Req068 | E72: 年次毎に以下のIFRS調整仕訳を登録できること ・貯蔵品（販促物） ・有給休暇引当金 ・総平均→FIFO（SEJのみ） ・在庫評価減（SSJのみ） ・有価証券売却益振替 ・減損総額表示 | F72: IFRSの調整仕訳を登録できる機能 | G72: 16.3 | H72: サンスター | J72: 一般会計全般・決算 | K72: 決算G | O72: FO | Q72: IFRS伝票処理 | R72: 不要 | S72: 転記階層機能を使用することで、日本基準用のトランザクションとは別にIFRSまたは税務用の仕訳伝票の登録が可能。 | T72: IN | X72: =テーブル1[[#This Row],[開発]]&テーブル1[[#This Row],[スコープ]] -> 不要IN | Y72: =IF(テーブル1[[#This Row],[列1]]="不要IN","標準",IF(テーブル1[[#This Row],[列1]]="不要OUT","スコープアウト",IF(テーブル1[[#This Row],[列1]]="必要IN","アドオン",IF(テーブル1[[#This Row],[列1]]="OUT","スコープアウト","")))) -> 標準 | Z72: =VLOOKUP($B72,Sheet1!$C$2:$L$315,9,) -> 会計システム標準機能 | AA72: =VLOOKUP($B72,Sheet1!$C$2:$L$315,10,) -> 一般的な仕訳等の登録用と異なるレイヤー(仕訳帳)に仕訳登録し、レポート側でどのレイヤーを出力するかの定義で対応可能 | AB72: 標準 | AC72: =テーブル1[[#This Row],[要求事項一覧 判定]]=テーブル1[[#This Row],[列2]] -> TRUE
A73: =テーブル1[[#This Row],[対象部門]]&テーブル1[[#This Row],[業務要件回答表からの事前回答案_v1.0.xlsxより]] -> 一般会計全般・決算17.1 | B73: 一般会計全般・決算17.1 | D73: Req069 | E73: 連結会計システムへデータのアップロードができること | F73: 連結会計システムへデータ連携できる機能 | G73: 17.1 | H73: サンスター | J73: 一般会計全般・決算 | K73: 決算G | O73: FO | Q73: IFRS伝票処理 | R73: 不要 | S73: ManagementReporterで連結会計システム向けのデータ出力レイアウト帳票を作成することを想定。 取り込みフォーマットまで加工したものが欲しい場合、アドオンが必要。 Req067のIFRS用TBをマクロで加工して連結取込をするので、REQ069としての開発は不要。 | T73: IN | X73: =テーブル1[[#This Row],[開発]]&テーブル1[[#This Row],[スコープ]] -> 不要IN | Y73: =IF(テーブル1[[#This Row],[列1]]="不要IN","標準",IF(テーブル1[[#This Row],[列1]]="不要OUT","スコープアウト",IF(テーブル1[[#This Row],[列1]]="必要IN","アドオン",IF(テーブル1[[#This Row],[列1]]="OUT","スコープアウト","")))) -> 標準 | Z73: =VLOOKUP($B73,Sheet1!$C$2:$L$315,9,) -> 会計システム標準機能 | AA73: =VLOOKUP($B73,Sheet1!$C$2:$L$315,10,) -> 0 | AB73: 標準 | AC73: =テーブル1[[#This Row],[要求事項一覧 判定]]=テーブル1[[#This Row],[列2]] -> TRUE
A74: =テーブル1[[#This Row],[対象部門]]&テーブル1[[#This Row],[業務要件回答表からの事前回答案_v1.0.xlsxより]] -> 一般会計全般・決算17.2 | B74: 一般会計全般・決算17.2 | D74: Req070 | E74: 連結会計システムへデータを連携した後、エラーを確認し、必要に応じて修正できること | F74: 連結会計システムへデータ連携後、修正できる機能 | G74: 17.2 | H74: サンスター | J74: 一般会計全般・決算 | K74: 決算G | O74: FO | Q74: IFRS伝票処理 | R74: 不要 | S74: 一般仕訳帳で修正伝票を登録後、データ再出力を想定。 | T74: IN | X74: =テーブル1[[#This Row],[開発]]&テーブル1[[#This Row],[スコープ]] -> 不要IN | Y74: =IF(テーブル1[[#This Row],[列1]]="不要IN","標準",IF(テーブル1[[#This Row],[列1]]="不要OUT","スコープアウト",IF(テーブル1[[#This Row],[列1]]="必要IN","アドオン",IF(テーブル1[[#This Row],[列1]]="OUT","スコープアウト","")))) -> 標準 | Z74: =VLOOKUP($B74,Sheet1!$C$2:$L$315,9,) -> 会計システム標準機能 | AA74: =VLOOKUP($B74,Sheet1!$C$2:$L$315,10,) -> 0 | AB74: 標準 | AC74: =テーブル1[[#This Row],[要求事項一覧 判定]]=テーブル1[[#This Row],[列2]] -> TRUE
A75: =テーブル1[[#This Row],[対象部門]]&テーブル1[[#This Row],[業務要件回答表からの事前回答案_v1.0.xlsxより]] -> 一般会計全般・決算17.3 | B75: 一般会計全般・決算17.3 | D75: Req071 | E75: 連結会計システムへデータを連携した後、CFを確認し、必要に応じて修正できること | F75: 連結会計システムへデータ連携後、CFを修正できる機能 | G75: 17.3 | H75: サンスター | J75: 一般会計全般・決算 | K75: 決算G | O75: FO | Q75: IFRS伝票処理 | R75: 不要 | S75: 一般仕訳帳で修正伝票を登録後、データ再出力を想定。 | T75: IN | X75: =テーブル1[[#This Row],[開発]]&テーブル1[[#This Row],[スコープ]] -> 不要IN | Y75: =IF(テーブル1[[#This Row],[列1]]="不要IN","標準",IF(テーブル1[[#This Row],[列1]]="不要OUT","スコープアウト",IF(テーブル1[[#This Row],[列1]]="必要IN","アドオン",IF(テーブル1[[#This Row],[列1]]="OUT","スコープアウト","")))) -> 標準 | Z75: =VLOOKUP($B75,Sheet1!$C$2:$L$315,9,) -> 会計システム標準機能 | AA75: =VLOOKUP($B75,Sheet1!$C$2:$L$315,10,) -> 0 | AB75: 標準 | AC75: =テーブル1[[#This Row],[要求事項一覧 判定]]=テーブル1[[#This Row],[列2]] -> TRUE
A76: =テーブル1[[#This Row],[対象部門]]&テーブル1[[#This Row],[業務要件回答表からの事前回答案_v1.0.xlsxより]] -> 一般会計全般・決算18.1 | B76: 一般会計全般・決算18.1 | D76: Req072 | E76: 年次毎に例えば以下のIFRS明細を作成できること (日本基準/IFRSで複数明細が保持できること) ・IFRS固定資産明細(圧縮記帳含む) ・IFRS減損資料 ・IFRS税効果会計資料 ・IFRS有価証券明細 ・IFRS金融負債明細 | F76: IFRSベースの各明細を作成・出力できる機能 | G76: 18.1 | H76: サンスター | J76: 一般会計全般・決算 | K76: 決算G | L76: ManagementReportでIFRS伝票を出力する帳票を作成することを想定。 | M76: 固定資産明細のなかで、増減累計がわかればよい。 サンプル受領予定 | O76: FO | Q76: IFRS伝票処理 | R76: 不要 | S76: 固定資産モジュールでIFRS用に設定した帳簿の仕訳の作成先をカスタムレイヤ1に設定することで、日本基準用(現行)とIFRS用(カスタムレイヤ1)とで別別に確認可能 | T76: IN | X76: =テーブル1[[#This Row],[開発]]&テーブル1[[#This Row],[スコープ]] -> 不要IN | Y76: =IF(テーブル1[[#This Row],[列1]]="不要IN","標準",IF(テーブル1[[#This Row],[列1]]="不要OUT","スコープアウト",IF(テーブル1[[#This Row],[列1]]="必要IN","アドオン",IF(テーブル1[[#This Row],[列1]]="OUT","スコープアウト","")))) -> 標準 | Z76: =VLOOKUP($B76,Sheet1!$C$2:$L$315,9,) -> 会計システムアドオン | AA76: =VLOOKUP($B76,Sheet1!$C$2:$L$315,10,) -> IFRSに対応した仕訳登録は、FO標準機能「一般仕訳帳」にて転記階層を変更して登録することで通常の仕訳、残高に影響なく登録可能。ただし、下記帳票類については別途開発が必要となります。 ・IFRS固定資産明細(圧縮記帳含む) ・IFRS減損資料 ・IFRS税効果会計資料 ・IFRS有価証券明細 ・IFRS金融負債明細 | AB76: アドオン | AC76: =テーブル1[[#This Row],[要求事項一覧 判定]]=テーブル1[[#This Row],[列2]] -> FALSE
A77: =テーブル1[[#This Row],[対象部門]]&テーブル1[[#This Row],[業務要件回答表からの事前回答案_v1.0.xlsxより]] -> 債権管理1.1 | B77: 債権管理1.1 | D77: Req073 | E77: 取引の発生によって各上流システムで計上した売掛金データを連携できること | F77: 上流から計上された売掛金データを連携して受け取る機能 | G77: 1.1 | H77: サンスター | J77: 債権管理 | K77: IT | L77: IF機能 | O77: FO | P77: 債権 | Q77: 1.SSJ・SEJ売上計上・請求処理 (売掛金) 2.SLJ売上計上・請求処理 (売掛金) | R77: 必要 | S77: 外部システム（mcframe、SEJホスト）で計上された伝票情報をIF取込する | T77: IN | V77: × | W77: 必要 | X77: =テーブル1[[#This Row],[開発]]&テーブル1[[#This Row],[スコープ]] -> 必要IN | Y77: =IF(テーブル1[[#This Row],[列1]]="不要IN","標準",IF(テーブル1[[#This Row],[列1]]="不要OUT","スコープアウト",IF(テーブル1[[#This Row],[列1]]="必要IN","アドオン",IF(テーブル1[[#This Row],[列1]]="OUT","スコープアウト","")))) -> アドオン | Z77: =VLOOKUP($B77,Sheet1!$C$2:$L$315,9,) -> 会計システム標準機能 | AA77: =VLOOKUP($B77,Sheet1!$C$2:$L$315,10,) -> 上流システムより債権データをExcelエクスポート。DIXFまたはExcelアドインにてインポート | AB77: 標準 | AC77: =テーブル1[[#This Row],[要求事項一覧 判定]]=テーブル1[[#This Row],[列2]] -> FALSE
A78: =テーブル1[[#This Row],[対象部門]]&テーブル1[[#This Row],[業務要件回答表からの事前回答案_v1.0.xlsxより]] -> 債権管理2.1 | B78: 債権管理2.1 | D78: Req074 | E78: 通販ダイレクトの預り金の発生履歴と処理方法を管理する台帳を作成できること | F78: 預り金の発生履歴と処理方法を台帳に作成する機能 | G78: 2.1 | H78: サンスター | J78: 債権管理 | K78: 事務管理G | M78: 2/1セッションにて 通販ダイレクト昨年9月25日より、システムが変更しており、内容が大きく変更になっている。 後払いという支払方法があり、入金が重複して過入金、預り売掛で処理をしていた。 システム変更に伴い、債権譲渡になり、後払いの機能がなくなった。 2.1のような問題の発生頻度は減ったが、0ではない。 台帳に関しては、Excelで管理台帳を作成して管理するで問題ないと思っているため、アドオンは不要の認識。 処理についてもアドオンは不要と考える。 | O78: FO | P78: 債権 | Q78: 7.その他取引計上 ・2. 預り金処理 台帳作成 | R78: 不要 | S78: 「試算表」「伝票トランザクション」を使用し、預り金情報を抽出する。 抽出した情報を基に台帳を作成する。 ※顧客毎に処理方法（返金、翌月支払いへの振替）を記載する ※預り金仕訳登録時に、財務分析コード「顧客」に対象顧客をセットする前提 | T78: IN | X78: =テーブル1[[#This Row],[開発]]&テーブル1[[#This Row],[スコープ]] -> 不要IN | Y78: =IF(テーブル1[[#This Row],[列1]]="不要IN","標準",IF(テーブル1[[#This Row],[列1]]="不要OUT","スコープアウト",IF(テーブル1[[#This Row],[列1]]="必要IN","アドオン",IF(テーブル1[[#This Row],[列1]]="OUT","スコープアウト","")))) -> 標準 | Z78: =VLOOKUP($B78,Sheet1!$C$2:$L$315,9,) -> 会計システム標準機能 | AA78: =VLOOKUP($B78,Sheet1!$C$2:$L$315,10,) -> 伝票トランザクションにてフィルタしてExcel出力での対応 | AB78: 標準 | AC78: =テーブル1[[#This Row],[要求事項一覧 判定]]=テーブル1[[#This Row],[列2]] -> TRUE
A79: =テーブル1[[#This Row],[対象部門]]&テーブル1[[#This Row],[業務要件回答表からの事前回答案_v1.0.xlsxより]] -> 債権管理2.2 | B79: 債権管理2.2 | D79: Req075 | E79: 預り金の発生した顧客毎に処理方法（返金、翌月支払いへの振替）を確認できること | F79: 預り金の発生顧客毎に処理方法を確認する機能 | G79: 2.2 | H79: サンスター | J79: 債権管理 | K79: 事務管理G | O79: FO | P79: 債権 | Q79: 7.その他取引計上 ・2. 預り金処理 台帳作成 | R79: 不要 | S79: Req074で作成した台帳を確認する。 | T79: IN | X79: =テーブル1[[#This Row],[開発]]&テーブル1[[#This Row],[スコープ]] -> 不要IN | Y79: =IF(テーブル1[[#This Row],[列1]]="不要IN","標準",IF(テーブル1[[#This Row],[列1]]="不要OUT","スコープアウト",IF(テーブル1[[#This Row],[列1]]="必要IN","アドオン",IF(テーブル1[[#This Row],[列1]]="OUT","スコープアウト","")))) -> 標準 | Z79: =VLOOKUP($B79,Sheet1!$C$2:$L$315,9,) -> 会計システム標準機能 | AA79: =VLOOKUP($B79,Sheet1!$C$2:$L$315,10,) -> 処理方法の情報が連携される仕訳データに付与される前提 | AB79: 標準 | AC79: =テーブル1[[#This Row],[要求事項一覧 判定]]=テーブル1[[#This Row],[列2]] -> TRUE
A80: =テーブル1[[#This Row],[対象部門]]&テーブル1[[#This Row],[業務要件回答表からの事前回答案_v1.0.xlsxより]] -> 債権管理2.3 | B80: 債権管理2.3 | D80: Req076 | E80: 預り金の返金処理をする場合、返金し預り金の消込できること | F80: 預り金の消込仕訳が作成する機能 | G80: 2.3 | H80: サンスター | J80: 債権管理 | K80: 事務管理G | O80: FO | P80: 債権 | Q80: 7.その他取引計上 | R80: 不要 | S80: 「仕入先支払仕訳帳」を使用し、返金・消込仕訳の登録を行う。 ※預り金仕訳登録時に、財務分析コード「顧客」に対象顧客をセットする前提 | T80: IN | X80: =テーブル1[[#This Row],[開発]]&テーブル1[[#This Row],[スコープ]] -> 不要IN | Y80: =IF(テーブル1[[#This Row],[列1]]="不要IN","標準",IF(テーブル1[[#This Row],[列1]]="不要OUT","スコープアウト",IF(テーブル1[[#This Row],[列1]]="必要IN","アドオン",IF(テーブル1[[#This Row],[列1]]="OUT","スコープアウト","")))) -> 標準 | Z80: =VLOOKUP($B80,Sheet1!$C$2:$L$315,9,) -> 会計システム標準機能 | AA80: =VLOOKUP($B80,Sheet1!$C$2:$L$315,10,) -> 預かり金は消し込みしない。 | AB80: 標準 | AC80: =テーブル1[[#This Row],[要求事項一覧 判定]]=テーブル1[[#This Row],[列2]] -> TRUE
A81: =テーブル1[[#This Row],[対象部門]]&テーブル1[[#This Row],[業務要件回答表からの事前回答案_v1.0.xlsxより]] -> 債権管理2.4 | B81: 債権管理2.4 | D81: Req077 | E81: 預り金を翌月以降の支払に充てる場合、預り金を売掛金に振替できること | F81: 預り金を売掛金に振り替えができる機能 | G81: 2.4 | H81: サンスター | J81: 債権管理 | K81: 事務管理G | O81: FO | P81: 債権 | Q81: 7.その他取引計上 | R81: 不要 | S81: 「一般仕訳帳」を使用し、振替仕訳を登録する。 | T81: IN | X81: =テーブル1[[#This Row],[開発]]&テーブル1[[#This Row],[スコープ]] -> 不要IN | Y81: =IF(テーブル1[[#This Row],[列1]]="不要IN","標準",IF(テーブル1[[#This Row],[列1]]="不要OUT","スコープアウト",IF(テーブル1[[#This Row],[列1]]="必要IN","アドオン",IF(テーブル1[[#This Row],[列1]]="OUT","スコープアウト","")))) -> 標準 | Z81: =VLOOKUP($B81,Sheet1!$C$2:$L$315,9,) -> 会計システム標準機能 | AA81: =VLOOKUP($B81,Sheet1!$C$2:$L$315,10,) -> マニュアルで仕訳を登録 | AB81: 標準 | AC81: =テーブル1[[#This Row],[要求事項一覧 判定]]=テーブル1[[#This Row],[列2]] -> TRUE
A82: =テーブル1[[#This Row],[対象部門]]&テーブル1[[#This Row],[業務要件回答表からの事前回答案_v1.0.xlsxより]] -> 債権管理3.1 | B82: 債権管理3.1 | D82: Req078 | E82: SSJの費用のうち、SEJの業務委託費に該当する費用を出力できること | F82: SSJで発生している費用を画面で確認する機能 | G82: 3.1 | H82: サンスター | J82: 債権管理 | K82: 受注管理G | O82: FO | P82: 債権 | Q82: 7.その他取引計上 | R82: 不要 | S82: 試算表、伝票トランザクション | T82: IN | U82: 受注や債権に特化した機能ではなく、計上した費用と摘要の確認をしていますので標準機能でOK。（武市） | X82: =テーブル1[[#This Row],[開発]]&テーブル1[[#This Row],[スコープ]] -> 不要IN | Y82: =IF(テーブル1[[#This Row],[列1]]="不要IN","標準",IF(テーブル1[[#This Row],[列1]]="不要OUT","スコープアウト",IF(テーブル1[[#This Row],[列1]]="必要IN","アドオン",IF(テーブル1[[#This Row],[列1]]="OUT","スコープアウト","")))) -> 標準 | Z82: =VLOOKUP($B82,Sheet1!$C$2:$L$315,9,) -> 会計システム標準機能 | AA82: =VLOOKUP($B82,Sheet1!$C$2:$L$315,10,) -> 特定権限の人は他法人の画面を表示可能にする | AB82: 標準 | AC82: =テーブル1[[#This Row],[要求事項一覧 判定]]=テーブル1[[#This Row],[列2]] -> TRUE
A83: =テーブル1[[#This Row],[対象部門]]&テーブル1[[#This Row],[業務要件回答表からの事前回答案_v1.0.xlsxより]] -> 債権管理3.2 | B83: 債権管理3.2 | D83: Req079 | E83: SEJの業務委託費用をSSJからSEJの人件費に振替できること | F83: 会社間を跨いで費用の振り替えができる機能 | G83: 3.2 | H83: サンスター | J83: 債権管理 | K83: 事務管理G | M83: 会社間振替処理機能が利用できるのであれば、活用したい（武市） | O83: FO | P83: 債権 | Q83: 7.その他取引計上 | R83: 不要 | S83: 「一般仕訳帳」を使用し、振替仕訳を登録する。 ※会社間会計機能を使用 | T83: IN | U83: ①立替金 / 消込費用 ②費用 / 未払金 ③当座 / 立替金 | X83: =テーブル1[[#This Row],[開発]]&テーブル1[[#This Row],[スコープ]] -> 不要IN | Y83: =IF(テーブル1[[#This Row],[列1]]="不要IN","標準",IF(テーブル1[[#This Row],[列1]]="不要OUT","スコープアウト",IF(テーブル1[[#This Row],[列1]]="必要IN","アドオン",IF(テーブル1[[#This Row],[列1]]="OUT","スコープアウト","")))) -> 標準 | Z83: =VLOOKUP($B83,Sheet1!$C$2:$L$315,9,) -> 会計システム標準機能 | AA83: =VLOOKUP($B83,Sheet1!$C$2:$L$315,10,) -> 会社間会計で対応可能 | AB83: 標準 | AC83: =テーブル1[[#This Row],[要求事項一覧 判定]]=テーブル1[[#This Row],[列2]] -> TRUE
A84: =テーブル1[[#This Row],[対象部門]]&テーブル1[[#This Row],[業務要件回答表からの事前回答案_v1.0.xlsxより]] -> 債権管理4.1 | B84: 債権管理4.1 | D84: Req080 | E84: 取引の発生によって各上流システムでその他の債権等を計上できること | F84: 上流から計上されたその他債権データを連携して受け取る機能 | G84: 4.1 | H84: サンスター | J84: 債権管理 | K84: IT | L84: IF機能 | M84: その他の債権＝未収入金であれば、楽楽精算入力時に取引先コード入力必須となっているので、IF時に留意 | O84: FO | P84: 債権 | Q84: 7.その他取引計上 | R84: 必要 | S84: 楽楽精算で計上された伝票情報をIF取込する | T84: IN | V84: × | W84: 必要 | X84: =テーブル1[[#This Row],[開発]]&テーブル1[[#This Row],[スコープ]] -> 必要IN | Y84: =IF(テーブル1[[#This Row],[列1]]="不要IN","標準",IF(テーブル1[[#This Row],[列1]]="不要OUT","スコープアウト",IF(テーブル1[[#This Row],[列1]]="必要IN","アドオン",IF(テーブル1[[#This Row],[列1]]="OUT","スコープアウト","")))) -> アドオン | Z84: =VLOOKUP($B84,Sheet1!$C$2:$L$315,9,) -> 会計システム標準機能 | AA84: =VLOOKUP($B84,Sheet1!$C$2:$L$315,10,) -> 上流システムより債権データをExcelエクスポート。DIXFまたはExcelアドインにてインポート | AB84: 標準 | AC84: =テーブル1[[#This Row],[要求事項一覧 判定]]=テーブル1[[#This Row],[列2]] -> FALSE
A85: =テーブル1[[#This Row],[対象部門]]&テーブル1[[#This Row],[業務要件回答表からの事前回答案_v1.0.xlsxより]] -> 債権管理5.1 | B85: 債権管理5.1 | D85: Req081 | E85: 請求回収支援システムから請求データを受領、連携できること すみません、こちらの要件は会計システム要件ではないため無視してください。 | F85: 請求回収支援システムから請求情報をAPI連携する機能 | G85: 5.1 | H85: サンスター | J85: 債権管理 | K85: 受注管理G | L85: 会計システム要件外のためスコープアウト | M85: 要件対象外（武市） | P85: 債権 | Q85: - | R85: 不要 | T85: OUT | X85: =テーブル1[[#This Row],[開発]]&テーブル1[[#This Row],[スコープ]] -> 不要OUT | Y85: =IF(テーブル1[[#This Row],[列1]]="不要IN","標準",IF(テーブル1[[#This Row],[列1]]="不要OUT","スコープアウト",IF(テーブル1[[#This Row],[列1]]="必要IN","アドオン",IF(テーブル1[[#This Row],[列1]]="OUT","スコープアウト","")))) -> スコープアウト | Z85: =VLOOKUP($B85,Sheet1!$C$2:$L$315,9,) -> 会計システム標準機能 | AA85: =VLOOKUP($B85,Sheet1!$C$2:$L$315,10,) -> 0 | AB85: 標準 | AC85: =テーブル1[[#This Row],[要求事項一覧 判定]]=テーブル1[[#This Row],[列2]] -> FALSE
A86: =テーブル1[[#This Row],[対象部門]]&テーブル1[[#This Row],[業務要件回答表からの事前回答案_v1.0.xlsxより]] -> 債権管理6.1 | B86: 債権管理6.1 | D86: Req082 | E86: 支払明細書を基に、当月の入金予定金額をW1毎に請求回収システムに登録できること すみません、こちらの要件は会計システム要件ではないため無視してください。 | F86: 入金予定金額を登録できる機能 | G86: 6.1 | H86: サンスター | J86: 債権管理 | K86: 受注管理G | L86: 会計システム要件外のためスコープアウト | M86: 要件対象外（武市） | P86: 債権 | Q86: - | R86: 不要 | T86: OUT | X86: =テーブル1[[#This Row],[開発]]&テーブル1[[#This Row],[スコープ]] -> 不要OUT | Y86: =IF(テーブル1[[#This Row],[列1]]="不要IN","標準",IF(テーブル1[[#This Row],[列1]]="不要OUT","スコープアウト",IF(テーブル1[[#This Row],[列1]]="必要IN","アドオン",IF(テーブル1[[#This Row],[列1]]="OUT","スコープアウト","")))) -> スコープアウト | Z86: =VLOOKUP($B86,Sheet1!$C$2:$L$315,9,) -> 会計システム標準機能 | AA86: =VLOOKUP($B86,Sheet1!$C$2:$L$315,10,) -> 0 | AB86: 標準 | AC86: =テーブル1[[#This Row],[要求事項一覧 判定]]=テーブル1[[#This Row],[列2]] -> FALSE
A87: =テーブル1[[#This Row],[対象部門]]&テーブル1[[#This Row],[業務要件回答表からの事前回答案_v1.0.xlsxより]] -> 債権管理7.1 | B87: 債権管理7.1 | D87: Req083 | E87: 通販以外の取引における小切手・手形分の入金を入力できること （AsIsでは販売管理システムに入力） 現在、三菱UFJに限らず入金消込は会計システムでは実施していませんが、今後入金消込を会計システムで実施する前提であるという内容と理解してください。(「三菱UFJ以外」といった記載は現在入金消込をしている別システムでの内容なので、ここでは気にしないでください) | F87: 小切手・手形分の入金を入力できる機能 | G87: 7.1 | H87: サンスター | J87: 債権管理 | K87: 受注管理G | M87: 要件対象外（武市） | O87: FO | P87: 債権 | Q87: 14.手形管理 | R87: 不要 | S87: 一般仕訳帳 ※FO側はAR管理しない想定のため、FO標準の手形機能は使用せずに、一般仕訳帳で登録となる。 | T87: IN | X87: =テーブル1[[#This Row],[開発]]&テーブル1[[#This Row],[スコープ]] -> 不要IN | Y87: =IF(テーブル1[[#This Row],[列1]]="不要IN","標準",IF(テーブル1[[#This Row],[列1]]="不要OUT","スコープアウト",IF(テーブル1[[#This Row],[列1]]="必要IN","アドオン",IF(テーブル1[[#This Row],[列1]]="OUT","スコープアウト","")))) -> 標準 | Z87: =VLOOKUP($B87,Sheet1!$C$2:$L$315,9,) -> 会計システム標準機能 | AA87: =VLOOKUP($B87,Sheet1!$C$2:$L$315,10,) -> 転記プロファイルを使用してマニュアルで仕訳を登録 | AB87: 標準 | AC87: =テーブル1[[#This Row],[要求事項一覧 判定]]=テーブル1[[#This Row],[列2]] -> TRUE
A88: =テーブル1[[#This Row],[対象部門]]&テーブル1[[#This Row],[業務要件回答表からの事前回答案_v1.0.xlsxより]] -> 債権管理7.2 | B88: 債権管理7.2 | D88: Req084 | E88: 通販以外の取引における売掛金に対する三菱UFJ以外の入金を入力できること （AsIsではSSJの場合は販売管理システム、SEJの場合は請求回収支援システムに入力） | F88: 預金口座へ入金を入力できる機能 | G88: 7.2 | H88: サンスター | J88: 債権管理 | K88: 受注管理G | L88: 売掛金の入金は外部システムで実施するためスコープアウト（FO以外での対応） | M88: 要件対象外（武市） | P88: 債権 | R88: 不要 | T88: OUT | X88: =テーブル1[[#This Row],[開発]]&テーブル1[[#This Row],[スコープ]] -> 不要OUT | Y88: =IF(テーブル1[[#This Row],[列1]]="不要IN","標準",IF(テーブル1[[#This Row],[列1]]="不要OUT","スコープアウト",IF(テーブル1[[#This Row],[列1]]="必要IN","アドオン",IF(テーブル1[[#This Row],[列1]]="OUT","スコープアウト","")))) -> スコープアウト | Z88: =VLOOKUP($B88,Sheet1!$C$2:$L$315,9,) -> 会計システム標準機能 | AA88: =VLOOKUP($B88,Sheet1!$C$2:$L$315,10,) -> 0 | AB88: 標準 | AC88: =テーブル1[[#This Row],[要求事項一覧 判定]]=テーブル1[[#This Row],[列2]] -> FALSE
A89: =テーブル1[[#This Row],[対象部門]]&テーブル1[[#This Row],[業務要件回答表からの事前回答案_v1.0.xlsxより]] -> 債権管理8.1 | B89: 債権管理8.1 | D89: Req085 | E89: クレジット会社からの入金を振替処理できること | F89: クレジット会社からの入金と売掛金を振替処理できる機能 | G89: 8.1 | H89: サンスター | J89: 債権管理 | K89: 受注管理G | L89: 売掛金の入金は外部システムで実施するためスコープアウト（FO以外での対応） | M89: 要件対象外（武市） | P89: 債権 | R89: 不要 | T89: OUT | X89: =テーブル1[[#This Row],[開発]]&テーブル1[[#This Row],[スコープ]] -> 不要OUT | Y89: =IF(テーブル1[[#This Row],[列1]]="不要IN","標準",IF(テーブル1[[#This Row],[列1]]="不要OUT","スコープアウト",IF(テーブル1[[#This Row],[列1]]="必要IN","アドオン",IF(テーブル1[[#This Row],[列1]]="OUT","スコープアウト","")))) -> スコープアウト | Z89: =VLOOKUP($B89,Sheet1!$C$2:$L$315,9,) -> 会計システム標準機能 | AA89: =VLOOKUP($B89,Sheet1!$C$2:$L$315,10,) -> マニュアルで仕訳を登録 | AB89: 標準 | AC89: =テーブル1[[#This Row],[要求事項一覧 判定]]=テーブル1[[#This Row],[列2]] -> FALSE
A90: =テーブル1[[#This Row],[対象部門]]&テーブル1[[#This Row],[業務要件回答表からの事前回答案_v1.0.xlsxより]] -> 債権管理8.2 | B90: 債権管理8.2 | D90: Req086 | E90: リクルートポイント利用分によるリクルートからの入金を振替処理できること | F90: 他社からの入金と売掛金を振替処理できる機能 | G90: 8.2 | H90: サンスター | J90: 債権管理 | K90: 受注管理G | L90: 売掛金の入金は外部システムで実施するためスコープアウト（FO以外での対応） | M90: 要件対象外（武市） | P90: 債権 | R90: 不要 | T90: OUT | X90: =テーブル1[[#This Row],[開発]]&テーブル1[[#This Row],[スコープ]] -> 不要OUT | Y90: =IF(テーブル1[[#This Row],[列1]]="不要IN","標準",IF(テーブル1[[#This Row],[列1]]="不要OUT","スコープアウト",IF(テーブル1[[#This Row],[列1]]="必要IN","アドオン",IF(テーブル1[[#This Row],[列1]]="OUT","スコープアウト","")))) -> スコープアウト | Z90: =VLOOKUP($B90,Sheet1!$C$2:$L$315,9,) -> 会計システム標準機能 | AA90: =VLOOKUP($B90,Sheet1!$C$2:$L$315,10,) -> マニュアルで仕訳を登録 | AB90: 標準 | AC90: =テーブル1[[#This Row],[要求事項一覧 判定]]=テーブル1[[#This Row],[列2]] -> FALSE
A91: =テーブル1[[#This Row],[対象部門]]&テーブル1[[#This Row],[業務要件回答表からの事前回答案_v1.0.xlsxより]] -> 債権管理8.3 | B91: 債権管理8.3 | D91: Req087 | E91: 直営店の売上報告(基本形)、ヤマトHPよりダウンロードした精算明細書(代引)を基に入金処理できること （AsIsでは販売管理システムに入力） | F91: 他社からの入金と売掛金を振替処理できる機能 | G91: 8.3 | H91: サンスター | J91: 債権管理 | K91: 受注管理G | L91: 売掛金の入金は外部システムで実施するためスコープアウト（FO以外での対応） | M91: 要件対象外（武市） | P91: 債権 | R91: 不要 | T91: OUT | X91: =テーブル1[[#This Row],[開発]]&テーブル1[[#This Row],[スコープ]] -> 不要OUT | Y91: =IF(テーブル1[[#This Row],[列1]]="不要IN","標準",IF(テーブル1[[#This Row],[列1]]="不要OUT","スコープアウト",IF(テーブル1[[#This Row],[列1]]="必要IN","アドオン",IF(テーブル1[[#This Row],[列1]]="OUT","スコープアウト","")))) -> スコープアウト | Z91: =VLOOKUP($B91,Sheet1!$C$2:$L$315,9,) -> 会計システム標準機能 | AA91: =VLOOKUP($B91,Sheet1!$C$2:$L$315,10,) -> マニュアルで仕訳を登録 | AB91: 標準 | AC91: =テーブル1[[#This Row],[要求事項一覧 判定]]=テーブル1[[#This Row],[列2]] -> FALSE
A92: =テーブル1[[#This Row],[対象部門]]&テーブル1[[#This Row],[業務要件回答表からの事前回答案_v1.0.xlsxより]] -> 債権管理8.4 | B92: 債権管理8.4 | D92: Req088 | E92: 自動入金エラーリストの入金について入金処理できること （AsIsでは販売管理システムに入力） | F92: 自動入金処理がエラーとなっていた入金について手動で入金入力できる機能 | G92: 8.4 | H92: サンスター | J92: 債権管理 | K92: 受注管理G | L92: 売掛金の入金は外部システムで実施するためスコープアウト（FO以外での対応） | M92: 要件対象外（武市） | P92: 債権 | R92: 不要 | T92: OUT | X92: =テーブル1[[#This Row],[開発]]&テーブル1[[#This Row],[スコープ]] -> 不要OUT | Y92: =IF(テーブル1[[#This Row],[列1]]="不要IN","標準",IF(テーブル1[[#This Row],[列1]]="不要OUT","スコープアウト",IF(テーブル1[[#This Row],[列1]]="必要IN","アドオン",IF(テーブル1[[#This Row],[列1]]="OUT","スコープアウト","")))) -> スコープアウト | Z92: =VLOOKUP($B92,Sheet1!$C$2:$L$315,9,) -> 会計システム標準機能 | AA92: =VLOOKUP($B92,Sheet1!$C$2:$L$315,10,) -> マニュアルで仕訳を登録 | AB92: 標準 | AC92: =テーブル1[[#This Row],[要求事項一覧 判定]]=テーブル1[[#This Row],[列2]] -> FALSE
A93: =テーブル1[[#This Row],[対象部門]]&テーブル1[[#This Row],[業務要件回答表からの事前回答案_v1.0.xlsxより]] -> 債権管理8.5 | B93: 債権管理8.5 | D93: Req089 | E93: 郵便振込、代引き、CVS、銀行振込、クレジット分、入金明細をもとに入金処理できること | F93: 郵便振込、代引き、CVS、銀行振込、クレジット支払いの入金明細を出力できる機能 | G93: 8.5 | H93: サンスター | J93: 債権管理 | K93: 受注管理G | L93: 売掛金の入金は外部システムで実施するためスコープアウト（FO以外での対応） | M93: 2/1セッションにて 入金処理する際に、郵便振込は勘定科目が当座預金の銀行コードをゆうちょにしており、 代引き、CVS、銀行振込は、備考欄に記載に記載しているため、特別アドオンは必要ないと考えている。 SAPで確認はしていない。備考欄に入金方法に情報が持てればよい。 | P93: 債権 | R93: 不要 | T93: OUT | X93: =テーブル1[[#This Row],[開発]]&テーブル1[[#This Row],[スコープ]] -> 不要OUT | Y93: =IF(テーブル1[[#This Row],[列1]]="不要IN","標準",IF(テーブル1[[#This Row],[列1]]="不要OUT","スコープアウト",IF(テーブル1[[#This Row],[列1]]="必要IN","アドオン",IF(テーブル1[[#This Row],[列1]]="OUT","スコープアウト","")))) -> スコープアウト | Z93: =VLOOKUP($B93,Sheet1!$C$2:$L$315,9,) -> 会計システム標準機能 | AA93: =VLOOKUP($B93,Sheet1!$C$2:$L$315,10,) -> マニュアルで仕訳を登録 | AB93: 標準 | AC93: =テーブル1[[#This Row],[要求事項一覧 判定]]=テーブル1[[#This Row],[列2]] -> FALSE
A94: =テーブル1[[#This Row],[対象部門]]&テーブル1[[#This Row],[業務要件回答表からの事前回答案_v1.0.xlsxより]] -> 債権管理8.6 | B94: 債権管理8.6 | D94: Req090 | E94: 委託販売先からの入金を受けて、売上計上できること Amazonや楽天などの通販業者に販売を委託するケースで、販売管理システムを通して会計システムに売上が計上されます。請求書発行等の考慮は不要です。 | F94: 委託販売先からの入金を受けて、売上計上できる機能 | G94: 8.6 | H94: サンスター | J94: 債権管理 | K94: 受注管理G | L94: 売掛金の入金は外部システムで実施するためスコープアウト（FO以外での対応） | P94: 債権 | R94: 不要 | T94: OUT | X94: =テーブル1[[#This Row],[開発]]&テーブル1[[#This Row],[スコープ]] -> 不要OUT | Y94: =IF(テーブル1[[#This Row],[列1]]="不要IN","標準",IF(テーブル1[[#This Row],[列1]]="不要OUT","スコープアウト",IF(テーブル1[[#This Row],[列1]]="必要IN","アドオン",IF(テーブル1[[#This Row],[列1]]="OUT","スコープアウト","")))) -> スコープアウト | Z94: =VLOOKUP($B94,Sheet1!$C$2:$L$315,9,) -> 会計システムアドオン | AA94: =VLOOKUP($B94,Sheet1!$C$2:$L$315,10,) -> 仕訳帳IF共通のアドオン | AB94: アドオン | AC94: =テーブル1[[#This Row],[要求事項一覧 判定]]=テーブル1[[#This Row],[列2]] -> FALSE
A95: =テーブル1[[#This Row],[対象部門]]&テーブル1[[#This Row],[業務要件回答表からの事前回答案_v1.0.xlsxより]] -> 債権管理9.1 | B95: 債権管理9.1 | D95: Req091 | E95: 得意先より期日払いの支払明細が届いたら入金入力できること | F95: 期日払いの支払明細を受けて入金入力できる機能 | G95: 9.1 | H95: サンスター | J95: 債権管理 | K95: 受注管理G | L95: 売掛金の入金は外部システムで実施するためスコープアウト（FO以外での対応） | P95: 債権 | R95: 不要 | T95: OUT | X95: =テーブル1[[#This Row],[開発]]&テーブル1[[#This Row],[スコープ]] -> 不要OUT | Y95: =IF(テーブル1[[#This Row],[列1]]="不要IN","標準",IF(テーブル1[[#This Row],[列1]]="不要OUT","スコープアウト",IF(テーブル1[[#This Row],[列1]]="必要IN","アドオン",IF(テーブル1[[#This Row],[列1]]="OUT","スコープアウト","")))) -> スコープアウト | Z95: =VLOOKUP($B95,Sheet1!$C$2:$L$315,9,) -> 会計システム標準機能 | AA95: =VLOOKUP($B95,Sheet1!$C$2:$L$315,10,) -> マニュアルで仕訳を登録 | AB95: 標準 | AC95: =テーブル1[[#This Row],[要求事項一覧 判定]]=テーブル1[[#This Row],[列2]] -> FALSE
A96: =テーブル1[[#This Row],[対象部門]]&テーブル1[[#This Row],[業務要件回答表からの事前回答案_v1.0.xlsxより]] -> 債権管理9.2 | B96: 債権管理9.2 | D96: Req092 | E96: ファクタリングの支払明細がFAXで届いたら入金入力できること | F96: ファクタリングの入金入力できる機能 | G96: 9.2 | H96: サンスター | J96: 債権管理 | K96: 受注管理G | L96: 売掛金の入金は外部システムで実施するためスコープアウト（FO以外での対応） | P96: 債権 | R96: 不要 | T96: OUT | X96: =テーブル1[[#This Row],[開発]]&テーブル1[[#This Row],[スコープ]] -> 不要OUT | Y96: =IF(テーブル1[[#This Row],[列1]]="不要IN","標準",IF(テーブル1[[#This Row],[列1]]="不要OUT","スコープアウト",IF(テーブル1[[#This Row],[列1]]="必要IN","アドオン",IF(テーブル1[[#This Row],[列1]]="OUT","スコープアウト","")))) -> スコープアウト | Z96: =VLOOKUP($B96,Sheet1!$C$2:$L$315,9,) -> 会計システム標準機能 | AA96: =VLOOKUP($B96,Sheet1!$C$2:$L$315,10,) -> マニュアルで仕訳を登録 | AB96: 標準 | AC96: =テーブル1[[#This Row],[要求事項一覧 判定]]=テーブル1[[#This Row],[列2]] -> FALSE
A97: =テーブル1[[#This Row],[対象部門]]&テーブル1[[#This Row],[業務要件回答表からの事前回答案_v1.0.xlsxより]] -> 債権管理9.3 | B97: 債権管理9.3 | D97: Req093 | E97: 電子ファクタリングの支払明細がFAXで届いたら入金入力後、科目振替できること | F97: 電子ファクタリングの入金入力できる機能 | G97: 9.3 | H97: サンスター | J97: 債権管理 | K97: 受注管理G | L97: 売掛金の入金は外部システムで実施するためスコープアウト（FO以外での対応） | P97: 債権 | R97: 不要 | T97: OUT | X97: =テーブル1[[#This Row],[開発]]&テーブル1[[#This Row],[スコープ]] -> 不要OUT | Y97: =IF(テーブル1[[#This Row],[列1]]="不要IN","標準",IF(テーブル1[[#This Row],[列1]]="不要OUT","スコープアウト",IF(テーブル1[[#This Row],[列1]]="必要IN","アドオン",IF(テーブル1[[#This Row],[列1]]="OUT","スコープアウト","")))) -> スコープアウト | Z97: =VLOOKUP($B97,Sheet1!$C$2:$L$315,9,) -> 会計システム標準機能 | AA97: =VLOOKUP($B97,Sheet1!$C$2:$L$315,10,) -> マニュアルで仕訳を登録 | AB97: 標準 | AC97: =テーブル1[[#This Row],[要求事項一覧 判定]]=テーブル1[[#This Row],[列2]] -> FALSE
A98: =テーブル1[[#This Row],[対象部門]]&テーブル1[[#This Row],[業務要件回答表からの事前回答案_v1.0.xlsxより]] -> 債権管理9.4 | B98: 債権管理9.4 | D98: Req094 | E98: 入金処理を基に会計システムで入金消込の仕訳を起票できること 消込管理と仕訳計上を行う想定です。 | F98: 会計システムへ入金情報を入力できる機能 | G98: 9.4 | H98: サンスター | J98: 債権管理 | K98: 受注管理G | L98: 売掛金の入金は外部システムで実施するためスコープアウト（FO以外での対応） | P98: 債権 | R98: 不要 | T98: OUT | X98: =テーブル1[[#This Row],[開発]]&テーブル1[[#This Row],[スコープ]] -> 不要OUT | Y98: =IF(テーブル1[[#This Row],[列1]]="不要IN","標準",IF(テーブル1[[#This Row],[列1]]="不要OUT","スコープアウト",IF(テーブル1[[#This Row],[列1]]="必要IN","アドオン",IF(テーブル1[[#This Row],[列1]]="OUT","スコープアウト","")))) -> スコープアウト | Z98: =VLOOKUP($B98,Sheet1!$C$2:$L$315,9,) -> 会計システム標準機能 | AA98: =VLOOKUP($B98,Sheet1!$C$2:$L$315,10,) -> 0 | AB98: 標準 | AC98: =テーブル1[[#This Row],[要求事項一覧 判定]]=テーブル1[[#This Row],[列2]] -> FALSE
A99: =テーブル1[[#This Row],[対象部門]]&テーブル1[[#This Row],[業務要件回答表からの事前回答案_v1.0.xlsxより]] -> 債権管理10.1 | B99: 債権管理10.1 | D99: Req095 | E99: すぐに通販顧客と断定できない入金があった際に、通販管理プラットフォームで確認できること 不明な入金があった場合に売掛金と照合するための機能(先進的な機能を含む)がもしあればご提案いただければと思います。 | F99: 不明入金の調査ができる機能 | G99: 10.1 | H99: サンスター | J99: 債権管理 | K99: 受注管理G | L99: 売掛金の入金は外部システムで実施するためスコープアウト（FO以外での対応） | P99: 債権 | R99: 不要 | T99: OUT | X99: =テーブル1[[#This Row],[開発]]&テーブル1[[#This Row],[スコープ]] -> 不要OUT | Y99: =IF(テーブル1[[#This Row],[列1]]="不要IN","標準",IF(テーブル1[[#This Row],[列1]]="不要OUT","スコープアウト",IF(テーブル1[[#This Row],[列1]]="必要IN","アドオン",IF(テーブル1[[#This Row],[列1]]="OUT","スコープアウト","")))) -> スコープアウト | Z99: =VLOOKUP($B99,Sheet1!$C$2:$L$315,9,) -> 会計システム標準機能 | AA99: =VLOOKUP($B99,Sheet1!$C$2:$L$315,10,) -> 0 | AB99: 標準 | AC99: =テーブル1[[#This Row],[要求事項一覧 判定]]=テーブル1[[#This Row],[列2]] -> FALSE
A100: =テーブル1[[#This Row],[対象部門]]&テーブル1[[#This Row],[業務要件回答表からの事前回答案_v1.0.xlsxより]] -> 債権管理10.2 | B100: 債権管理10.2 | D100: Req096 | E100: 直営店の入金処理管理表を作成できること 店舗別に入金明細が確認できれば良い | F100: 入金処理管理表を作成できる機能 | G100: 10.2 | H100: サンスター | J100: 債権管理 | K100: 受注管理G | L100: 売掛金の入金は外部システムで実施するためスコープアウト（FO以外での対応） | P100: 債権 | R100: 不要 | T100: OUT | X100: =テーブル1[[#This Row],[開発]]&テーブル1[[#This Row],[スコープ]] -> 不要OUT | Y100: =IF(テーブル1[[#This Row],[列1]]="不要IN","標準",IF(テーブル1[[#This Row],[列1]]="不要OUT","スコープアウト",IF(テーブル1[[#This Row],[列1]]="必要IN","アドオン",IF(テーブル1[[#This Row],[列1]]="OUT","スコープアウト","")))) -> スコープアウト | Z100: =VLOOKUP($B100,Sheet1!$C$2:$L$315,9,) -> 会計システム標準機能 | AA100: =VLOOKUP($B100,Sheet1!$C$2:$L$315,10,) -> 0 | AB100: 標準 | AC100: =テーブル1[[#This Row],[要求事項一覧 判定]]=テーブル1[[#This Row],[列2]] -> FALSE
...

Sheet Sheet1
D1: 業務内容 | K1: RFP回答
C2: 結合キー | D2: Lv1 | E2: Lv2 | F2: Lv3 | G2: Lv4 | H2: No | I2: 業務概要 | J2: 対応機能 | K2: システム対応可否 | L2: 会計システム標準機能以外の場合、実現方法詳細
A3: 一般会計全般・決算 | B3: =A3&H3 -> 一般会計全般・決算1.1 | C3: 一般会計全般・決算1.1 | D3: 一般会計全般 | E3: 仕訳処理 | F3: 仕訳データ入力 | G3: 仕訳入力 | H3: 1.1 | I3: 画面入力で仕訳伝票を登録できること (勘定科目を変更せず、仕訳の入力項目の修正のための振替伝票も起票可能であること) ⇒()内の記述は、登録ミスした仕訳伝票の訂正伝票の登録方法に関する記述 | J3: 仕訳伝票の登録機能 | K3: 会計システム標準機能
A4: 一般会計全般・決算 | B4: =A4&H4 -> 一般会計全般・決算1.2 | C4: 一般会計全般・決算1.2 | D4: 一般会計全般 | E4: 仕訳処理 | F4: 仕訳データ入力 | G4: 仕訳入力 | H4: 1.2 | I4: 多通貨で仕訳伝票が登録でき、入力通貨金額が報告通貨金額（邦貨）に換算した額も登録できること | J4: 多通貨の仕訳伝票の登録機能 | K4: 会計システム標準機能
A5: 一般会計全般・決算 | B5: =A5&H5 -> 一般会計全般・決算1.3 | C5: 一般会計全般・決算1.3 | D5: 一般会計全般 | E5: 仕訳処理 | F5: 仕訳データ入力 | G5: 仕訳入力 | H5: 1.3 | I5: Excelフォーマット（取引先、取引内容、部門、消費税区分、金額、伝票日付、相手科目等）のアップロード機能で仕訳作成できること ※機能通貨への換算、消費税明細計上(内税/外税)、為替差損益明細計上への対応、および相互通貨バランスチェック、最新データの取得が可能であること | J5: 仕訳アップロード機能で仕訳を作成する機能 | K5: 会計システム標準機能
A6: 一般会計全般・決算 | B6: =A6&H6 -> 一般会計全般・決算1.4 | C6: 一般会計全般・決算1.4 | D6: 一般会計全般 | E6: 仕訳処理 | F6: 仕訳データ入力 | G6: 仕訳入力 | H6: 1.4 | I6: 勘定科目別に入力条件が設定でき、条件外の場合はエラーアラートが表示できること ⇒例えば経費科目であれば経費発生部門(原価センタ)の入力が必須になるなど、勘定科目の種類に応じて入力の必須・任意(入力フィールドの表示・非表示)をコントロールする機能のイメージです。(SAPでは項目ステータスと呼ばれる機能に該当します。) | J6: 勘定科目別に入力条件を指定する機能 | K6: 会計システム標準機能
A7: 一般会計全般・決算 | B7: =A7&H7 -> 一般会計全般・決算1.5 | C7: 一般会計全般・決算1.5 | D7: 一般会計全般 | E7: 仕訳処理 | F7: 仕訳データ入力 | G7: 仕訳入力 | H7: 1.5 | I7: 複数の仕訳をまとめて仕訳アップロード機能で作成することができること | J7: 複数仕訳を同時で起票できる機能 | K7: 会計システム標準機能
A8: 一般会計全般・決算 | B8: =A8&H8 -> 一般会計全般・決算1.6 | C8: 一般会計全般・決算1.6 | D8: 一般会計全般 | E8: 仕訳処理 | F8: 仕訳データ入力 | G8: 仕訳入力 | H8: 1.6 | I8: 転記済みの仕訳をコピーして登録できること | J8: 転記済みの仕訳をコピーして一部内容を修正することで新たな仕訳として登録できる機能 | K8: 会計システム標準機能 | L8: 仕訳帳のテンプレート登録にて対応
A9: 一般会計全般・決算 | B9: =A9&H9 -> 一般会計全般・決算1.7 | C9: 一般会計全般・決算1.7 | D9: 一般会計全般 | E9: 仕訳処理 | F9: 仕訳データ入力 | G9: 仕訳入力 | H9: 1.7 | I9: 転記前に、転記後の残高を事前にシミュレーション表示できること | J9: 登録は済んでいるが、まだ転記されていない仕訳について、転記後の残高を事前に確認できるように、シミュレーション表示できる機能 | K9: 会計システムアドオン | L9: 未転記の仕訳を選択後、ボタン押下後に転記後の残高を確認できるポップアップ画面を表示する機能を追加する
A10: 一般会計全般・決算 | B10: =A10&H10 -> 一般会計全般・決算1.8 | C10: 一般会計全般・決算1.8 | D10: 一般会計全般 | E10: 仕訳処理 | F10: 仕訳データ入力 | G10: 定型仕訳 | H10: 1.8 | I10: 定型の仕訳伝票に関して、配賦用のテンプレートを定義、繰り返し使用できること ※テンプレート項目例：配賦元部門/勘定科目/金額、配賦先部門/勘定科目金額、配賦基準(金額比、割合比等) | J10: 配賦のために定型の仕訳伝票を入力テンプレートとして定義する機能 | K10: 会計システム標準機能 | L10: 一般仕訳帳のテンプレ機能があります。（配賦のためというわけではない）
A11: 一般会計全般・決算 | B11: =A11&H11 -> 一般会計全般・決算1.9 | C11: 一般会計全般・決算1.9 | D11: 一般会計全般 | E11: 仕訳処理 | F11: 仕訳データ入力 | G11: 定型仕訳 | H11: 1.9 | I11: 定型の仕訳伝票に関して、伝票登録時の入力テンプレートを定義し、繰り返し使用できること | J11: 各会計期間で繰り返される定型の仕訳を処理するため、定型の仕訳伝票を入力テンプレートとして定義する機能 | K11: 会計システム標準機能
A12: 一般会計全般・決算 | B12: =A12&H12 -> 一般会計全般・決算2.1 | C12: 一般会計全般・決算2.1 | D12: 一般会計全般 | E12: 仕訳処理 | F12: 仕訳データ修正 | G12: 修正仕訳 | H12: 2.1 | I12: 未転記の場合、登録した仕訳伝票を登録者の方から修正することができること | J12: 仕訳明細情報を訂正する機能 | K12: 会計システム標準機能
A13: 一般会計全般・決算 | B13: =A13&H13 -> 一般会計全般・決算2.2 | C13: 一般会計全般・決算2.2 | D13: 一般会計全般 | E13: 仕訳処理 | F13: 仕訳データ修正 | G13: 修正仕訳 | H13: 2.2 | I13: 未転記の場合、登録した仕訳伝票を登録者の方から削除することができること | J13: 仕訳明細情報を削除する機能 | K13: 会計システム標準機能
A14: 一般会計全般・決算 | B14: =A14&H14 -> 一般会計全般・決算2.3 | C14: 一般会計全般・決算2.3 | D14: 一般会計全般 | E14: 仕訳処理 | F14: 仕訳データ修正 | G14: 逆仕訳 | H14: 2.3 | I14: 登録した仕訳伝票を符号の変更（登録された仕訳伝票の金額をプラスからマイナスに変更）できること | J14: 逆仕訳を生成する機能 | K14: 会計システム標準機能 | L14: 転記済み仕訳を指定し「仕訳全体の取り消し」
A15: 一般会計全般・決算 | B15: =A15&H15 -> 一般会計全般・決算3.1 | C15: 一般会計全般・決算3.1 | D15: 一般会計全般 | E15: 仕訳処理 | F15: 仕訳の転記 | G15: 仕訳の転記 | H15: 3.1 | I15: 承認者による承認のもと、仕訳伝票を転記できること | J15: 仕訳を転記する機能 | K15: 会計システム標準機能
A16: 一般会計全般・決算 | B16: =A16&H16 -> 一般会計全般・決算3.2 | C16: 一般会計全般・決算3.2 | D16: 一般会計全般 | E16: 仕訳処理 | F16: 仕訳の転記 | G16: 仕訳の転記 | H16: 3.2 | I16: 自動で転記処理を行うために、転記承認を経ずに転記できること | J16: 自動で転記処理を行う機能 | K16: 会計システム標準機能 | L16: 特定金額以下であれば、承認不要（転記可能）等は設定できる。
A17: 一般会計全般・決算 | B17: =A17&H17 -> 一般会計全般・決算4.1 | C17: 一般会計全般・決算4.1 | D17: 一般会計全般 | E17: 仕訳処理 | F17: 仕訳の承認 | G17: 仕訳の承認 | H17: 4.1 | I17: 仕訳作成者が、設定された仕訳の承認要求ができること | J17: 仕訳の承認依頼を行う機能 | K17: 会計システム標準機能
A18: 一般会計全般・決算 | B18: =A18&H18 -> 一般会計全般・決算4.2 | C18: 一般会計全般・決算4.2 | D18: 一般会計全般 | E18: 仕訳処理 | H18: 4.2 | I18: 仕訳作成者が、設定された仕訳バッチ一覧から任意の単位で仕訳を一括に承認要求ができること | J18: 一括で仕訳の承認依頼を行う機能 | K18: 会計システムアドオン | L18: 一括で承認依頼/承認を行う機能を追加する
A19: 一般会計全般・決算 | B19: =A19&H19 -> 一般会計全般・決算4.3 | C19: 一般会計全般・決算4.3 | D19: 一般会計全般 | E19: 仕訳処理 | F19: 仕訳の承認 | G19: 仕訳の承認 | H19: 4.3 | I19: 仕訳一括承認依頼受領時に、任意の仕訳単位に対して一括で承認、否決処理ができること | J19: 一括で仕訳の承認を行う機能 | K19: 会計システムアドオン | L19: 4.3の範囲にて対応。
A20: 一般会計全般・決算 | B20: =A20&H20 -> 一般会計全般・決算5.1 | C20: 一般会計全般・決算5.1 | D20: 一般会計全般 | E20: 仕訳処理 | F20: 未転記の仕訳管理 | G20: 未転記の仕訳管理 | H20: 5.1 | I20: 仕訳入力者を区分として、仕訳のステータスが未承認または承認依頼未済である仕訳の仕訳明細情報を一覧で、画面照会および帳票出力できること | J20: 承認依頼時に、依頼者別の未承認または承認依頼未済の仕訳明細情報を一覧で出力する機能 | K20: 会計システム標準機能
A21: 一般会計全般・決算 | B21: =A21&H21 -> 一般会計全般・決算5.2 | C21: 一般会計全般・決算5.2 | D21: 一般会計全般 | E21: 仕訳処理 | F21: 未転記の仕訳管理 | G21: 未転記の仕訳管理 | H21: 5.2 | I21: 承認依頼が必要な未承認の仕訳を勘定科目別に集計した一覧で、画面照会および帳票出力できること | J21: 承認依頼が必要な仕訳を勘定科目別に集計した一覧を出力する機能 | K21: 会計システムアドオン | L21: 新規画面として、承認依頼が必要な仕訳を勘定科目別に集計した一覧を出力する画面を作成。帳票に関しては、現時点では標準機能のExcelファイルエクスポート機能を使用予定。要件次第で開発とする。
A22: 一般会計全般・決算 | B22: =A22&H22 -> 一般会計全般・決算6.1 | C22: 一般会計全般・決算6.1 | D22: 一般会計全般 | E22: 残高確認 | F22: 残高照会 | G22: 帳票・明細出力 | H22: 6.1 | I22: 前日、前月末までの借方貸方の累計と残高を集計し、画面照会および帳票出力ができること | J22: 指定時点での科目別残高一覧を出力する機能 | K22: 会計システム標準機能
A23: 一般会計全般・決算 | B23: =A23&H23 -> 一般会計全般・決算6.2 | C23: 一般会計全般・決算6.2 | D23: 一般会計全般 | E23: 残高確認 | F23: 残高照会 | G23: 帳票・明細出力 | H23: 6.2 | I23: 指定された会計期間において発生した任意の勘定科目の残高明細情報を、画面照会および帳票出力できること | J23: 科目別残高明細一覧を出力する機能 | K23: 会計システム標準機能
A24: 一般会計全般・決算 | B24: =A24&H24 -> 一般会計全般・決算6.3 | C24: 一般会計全般・決算6.3 | D24: 一般会計全般 | E24: 残高確認 | F24: 残高照会 | G24: 帳票・明細出力 | H24: 6.3 | I24: 前期末の残高明細情報と比較できること | J24: 前年同期比で残高の比較照合ができる機能 | K24: 会計システム標準機能 | L24: MRで対応
A25: 一般会計全般・決算 | B25: =A25&H25 -> 一般会計全般・決算6.4 | C25: 一般会計全般・決算6.4 | D25: 一般会計全般 | E25: 残高確認 | F25: 残高照会 | G25: 帳票・明細出力 | H25: 6.4 | I25: 特定の会計期間において勘定科目別、貨幣別等で各残高を集計して、画面照会および帳票出力ができること | J25: 特定の会計期間において勘定科目別の残高を指定した一定の条件別に一覧化して集計する機能 | K25: 会計システム標準機能
A26: 一般会計全般・決算 | B26: =A26&H26 -> 一般会計全般・決算6.5 | C26: 一般会計全般・決算6.5 | D26: 一般会計全般 | E26: 残高確認 | F26: 残高照会 | G26: 赤残チェック | H26: 6.5 | I26: 各勘定科目の残高を確認し、残高がマイナスである科目がある場合、該当科目別の残高を通貨・会社毎にリストとして、画面照会および帳票出力ができること | J26: 残高がマイナスである科目を一覧で出力する機能 | K26: 会計システム標準機能 | L26: 勘定科目一覧画面で、金額欄にマイナス金額のフィルタを使用
A27: 一般会計全般・決算 | B27: =A27&H27 -> 一般会計全般・決算6.6 | C27: 一般会計全般・決算6.6 | D27: 一般会計全般 | E27: 残高確認 | F27: 残高照会 | G27: 赤残チェック | H27: 6.6 | I27: 決算時の通過勘定科目の残高を確認し、残高が0円以外の科目がある場合、該当科目別の残高を通貨・会社毎にリストとして、画面照会および帳票出力ができること | J27: 決算時において0円である必要がある勘定科目(通過勘定科目)に対し未整理の残高が存在する場合、対象の残高情報を一覧で出力する機能 | K27: 会計システム標準機能 | L27: 伝票トランザクションにてフィルタしてExcel出力での対応
A28: 一般会計全般・決算 | B28: =A28&H28 -> 一般会計全般・決算7.1 | C28: 一般会計全般・決算7.1 | D28: 一般会計全般 | E28: レポート・伝票 | F28: 会計・単体決算用 | G28: 財務諸表 | H28: 7.1 | I28: 指定された会計期間時点での以下の財務諸表を、全社、部門別で、画面照会および帳票出力できること ・貸借対照表(BS) ・損益計算書(PL累計) ・株主資本等変動計算書(SS) ・注記表 ・キャッシュフロー計算書(CF) ・製造原価報告書 ・労務費及び生産費明細表 ・営業費明細表 ・研究費明細表 | J28: 財務諸表をを全社/各社別に作成・出力する機能(BS/PLについては開示用科目(親科目)と集計元科目(子科目)単位でそれぞれ閲覧できること) | K28: 会計システム標準機能 | L28: 「注記表」以外につきましては、FO標準機能の財務諸表で対応可能と考えております。ただ、「注記表」については、標準機能のWordテンプレートを使用して、帳票出力を検討しております。ただし、要件次第では、開発が必要となる場合もございます。
A29: 一般会計全般・決算 | B29: =A29&H29 -> 一般会計全般・決算7.2 | C29: 一般会計全般・決算7.2 | D29: 一般会計全般 | E29: レポート・伝票 | F29: 会計・単体決算用 | G29: 財務諸表作成 | H29: 7.2 | I29: 各財務諸表類の前年度比較ができること | J29: 前年同期比で各財務諸表類の比較照合ができる機能 | K29: 会計システム標準機能 | L29: MRで対応
A30: 一般会計全般・決算 | B30: =A30&H30 -> 一般会計全般・決算7.3 | C30: 一般会計全般・決算7.3 | D30: 一般会計全般 | E30: レポート・伝票 | F30: 会計・単体決算用 | G30: 決算開示書類 | H30: 7.3 | I30: 年次毎に下記の決算開示書類を作成すること ・計算書類 ・附属明細書 ・決算短信 ・事業報告書 ・勘定明細 | J30: 決算開示書類を作成・出力する機能 | K30: 会計システムアドオン | L30: 下記帳票類の作成 ・計算書類 ・附属明細書 ・決算短信 ・事業報告書 ・勘定明細
A31: 一般会計全般・決算 | B31: =A31&H31 -> 一般会計全般・決算7.4 | C31: 一般会計全般・決算7.4 | D31: 一般会計全般 | E31: レポート・伝票 | F31: 会計・単体決算用 | G31: 決算開示書類 | H31: 7.4 | I31: 決算開示書類の計算書類や付属明細書、勘定明細書の前年度比較ができること | J31: 前年同期比で各決算開示書類の比較照合ができる機能 | K31: 会計システムアドオン | L31: 下記帳票類の履歴管理機能 ・計算書類 ・附属明細書 ・決算短信 ・事業報告書 ・勘定明細
A32: 一般会計全般・決算 | B32: =A32&H32 -> 一般会計全般・決算7.5 | C32: 一般会計全般・決算7.5 | D32: 一般会計全般 | E32: レポート・伝票 | F32: 会計・単体決算用 | G32: 帳簿 | H32: 7.5 | I32: 指定された会計期間時点での以下の帳簿類を、全社、部門別で、画面照会および出力できること。また、これらの帳簿を指定した日にシステムから指定したデータを自動で保存できること。 ・仕訳帳 （仕訳のステータス(未承認、転記済み、エラー)を区分として、仕訳帳が画面照会および帳票出力でき、仕訳一覧から、ドリルダウンして明細情報が確認できること） ・総勘定元帳 （指定された会計期間(月次/年度等)における、仕訳明細情報(借方、貸方、残高)が、勘定科目別、伝票日付別、転記処理日別、仕訳ソース別、仕訳カテゴリー別等に集計された一覧） （指定された会計期間(月次/年度等)における、仕訳明細情報(借方、貸方、残高)が、勘定科目別、伝票日付別、転記処理日別、仕訳ソース別、仕訳カテゴリー別等に集計された一覧） ・補助簿（固定資産台帳を含む） （指定された会計期間(月次/年度等)における、仕訳の明細情報の勘定科目別、伝票日付別、取引先別等の一覧） ・勘定残高表 （指定された会計期間(月次/年度等)における、指定された勘定科目の残高(前期末残高、借方、貸方)が集計された一覧） ・消費税台帳 （指定された会計期間(月次/年度等)における、売上高・仕入高と消費税額がで集計された一覧） | J32: 仕訳帳、総勘定元帳、補助記入帳、補助元帳、勘定残高表、消費税台帳等を出力、また、指定日に応じて自動保存する機能 | K32: 会計システム標準機能 | L32: 伝票トランザクションにてフィルタしてExcel出力での対応
A33: 一般会計全般・決算 | B33: =A33&H33 -> 一般会計全般・決算7.6 | C33: 一般会計全般・決算7.6 | D33: 一般会計全般 | E33: レポート・伝票 | F33: 会計・単体決算用 | G33: 伝票 | H33: 7.6 | I33: 当日を含め指定した特定の日付に転記された伝票明細表が画面照会および帳票出力できること ※伝票の仕訳情報の一覧 | J33: 当日を含め指定した特定の日付に転記された伝票の明細表を出力する機能 | K33: 会計システム標準機能 | L33: 伝票トランザクションにてフィルタしてExcel出力での対応
A34: 一般会計全般・決算 | B34: =A34&H34 -> 一般会計全般・決算7.7 | C34: 一般会計全般・決算7.7 | D34: 一般会計全般 | E34: レポート・伝票 | F34: 会計・単体決算用 | G34: 伝票 | H34: 7.7 | I34: 当日を含め指定した特定の日付に転記された伝票集計表が画面照会および帳票出力できること ※伝票の仕訳情報が勘定科目等別に集計された一覧 | J34: 当日を含め指定した特定の日付に転記された伝票の集計表を出力する機能 | K34: 会計システム標準機能 | L34: 伝票トランザクションにてフィルタしてExcel出力での対応
A35: 一般会計全般・決算 | B35: =A35&H35 -> 一般会計全般・決算7.8 | C35: 一般会計全般・決算7.8 | D35: 一般会計全般 | E35: レポート・伝票 | F35: 会計・単体決算用 | G35: 売上高/仕入高の明細・集計 | H35: 7.8 | I35: 売上高明細表・仕入高明細表が画面照会および帳票出力できること ※指定された会計期間における、売上仕入対象勘定科目の仕訳明細情報の一覧 | J35: 売上仕入対象勘定の実績から売上高明細表・仕入高明細表を出力する機能 | K35: 会計システム標準機能 | L35: 伝票トランザクションにてフィルタしてExcel出力での対応
A36: 一般会計全般・決算 | B36: =A36&H36 -> 一般会計全般・決算7.9 | C36: 一般会計全般・決算7.9 | D36: 一般会計全般 | E36: レポート・伝票 | F36: 会計・単体決算用 | G36: 売上高/仕入高の明細・集計 | H36: 7.9 | I36: 売上高集計表、仕入高集計表が画面照会および帳票出力できること ※指定された会計期間における、売上対象勘定科目・仕入対象勘定科目の実績が集計された一覧 | J36: 売上仕入対象勘定の実績から売上高集計表・仕入高集計表を出力する機能 | K36: 会計システム標準機能 | L36: 伝票トランザクションにてフィルタしてExcel出力での対応
A37: 一般会計全般・決算 | B37: =A37&H37 -> 一般会計全般・決算8.1 | C37: 一般会計全般・決算8.1 | D37: 一般会計全般 | E37: レポート・伝票 | F37: 税務用 | G37: 接待交際費 | H37: 8.1 | I37: 接待交際費集計表が画面照会および帳票出力できること ※指定された会計期間(月次/年度等)における接待交際費の仕訳明細情報が、勘定科目、細目、月別等に集計された一覧 | J37: 接待交際費集計表を出力する機能 | K37: 会計システム標準機能 | L37: 伝票トランザクションにてフィルタしてExcel出力での対応
... A45: 一般会計全般・決算 | B45: =A45&H45 -> 一般会計全般・決算9.2 | C45: 一般会計全般・決算9.2 | D45: 一般会計全般 | E45: レポート・伝票 | F45: 監査用 | G45: 増減調査＆資料作成 | H45: 9.2 | I45: 監査用に必要な増減調査用の資料を出力できること | J45: 監査用に必要な増減調査用の資料を出力できる機能 | K45: 会計システムアドオン | L45: 新規帳票を開発。
A46: 一般会計全般・決算 | B46: =A46&H46 -> 一般会計全般・決算10.1 | C46: 一般会計全般・決算10.1 | D46: 一般会計全般 | E46: その他 | F46: レート | G46: レート設定 | H46: 10.1 | I46: 月末・期末レートが定義できること | J46: 月末・期末レートを定義する機能 | K46: 会計システム標準機能
A47: 一般会計全般・決算 | B47: =A47&H47 -> 一般会計全般・決算10.2 | C47: 一般会計全般・決算10.2 | D47: 一般会計全般 | E47: その他 | F47: レート | G47: レート設定 | H47: 10.2 | I47: 通貨毎に月末・期末レートを自動設定できること | J47: 指定された通貨の期末レートを自動設定する機能 | K47: 会計システム標準機能
A48: 一般会計全般・決算 | B48: =A48&H48 -> 一般会計全般・決算11.1 | C48: 一般会計全般・決算11.1 | D48: 一般会計全般 | E48: その他 | F48: セットアップ | G48: 会計カレンダ設定 | H48: 11.1 | I48: 会計スケジュールをもとに、会計カレンダーが設定できること | J48: 会計スケジュールをもとに、会計カレンダーが設定する機能 | K48: 会計システム標準機能
A49: 一般会計全般・決算 | B49: =A49&H49 -> 一般会計全般・決算11.2 | C49: 一般会計全般・決算11.2 | D49: 一般会計全般 | E49: その他 | F49: セットアップ | G49: 会計カレンダ設定 | H49: 11.2 | I49: 会計スケジュールをもとに、会計処理をオープン・クローズできること | J49: 会計スケジュールをもとに、会計処理をオープン・クローズする機能 | K49: 会計システム標準機能
A50: 一般会計全般・決算 | B50: =A50&H50 -> 一般会計全般・決算11.3 | C50: 一般会計全般・決算11.3 | D50: 一般会計全般 | E50: その他 | F50: セットアップ | G50: アクセス制限 | H50: 11.3 | I50: 機能(帳票閲覧権限等）をユーザ別に制限できること | J50: 機能をユーザ別に制限する機能 | K50: 会計システム標準機能 | L50: 標準レポートは制限可能。MR機能で作成した追加帳票は制限不可
A51: 一般会計全般・決算 | B51: =A51&H51 -> 一般会計全般・決算11.4 | C51: 一般会計全般・決算11.4 | D51: 一般会計全般 | E51: その他 | F51: セットアップ | G51: ワークフロー関連 | H51: 11.4 | I51: 承認依頼受領時に、アラートで通知できること | J51: 承認依頼受領時に、アラートで通知する機能 | K51: 会計システム標準機能
A52: 一般会計全般・決算 | B52: =A52&H52 -> 一般会計全般・決算11.5 | C52: 一般会計全般・決算11.5 | D52: 一般会計全般 | E52: その他 | F52: セットアップ | G52: ワークフロー関連 | H52: 11.5 | I52: 仕訳承認時に組織階層、レポートラインに沿った承認ルート設定ができ、自動で承認を流すことができること | J52: 仕訳承認時の組織階層、レポートラインに沿った承認ルートを設定する機能 | K52: 会計システム標準機能 | L52: 承認依頼ボタンの押下は必要
A53: 一般会計全般・決算 | B53: =A53&H53 -> 一般会計全般・決算11.6 | C53: 一般会計全般・決算11.6 | D53: 一般会計全般 | E53: その他 | F53: セットアップ | G53: ワークフロー関連 | H53: 11.6 | I53: 承認者が代理承認者を任意で設定でき、レポートラインが代理の場合設定できること | J53: 代理承認者を指定できる機能 | K53: 会計システム標準機能 | L53: 承認者変更の機能はある
A54: 一般会計全般・決算 | B54: =A54&H54 -> 一般会計全般・決算11.7 | C54: 一般会計全般・決算11.7 | D54: 一般会計全般 | E54: その他 | F54: セットアップ | G54: 勘定科目 | H54: 11.7 | I54: 勘定科目を定義できること | J54: 勘定科目を定義する機能 | K54: 会計システム標準機能
A55: 一般会計全般・決算 | B55: =A55&H55 -> 一般会計全般・決算11.8 | C55: 一般会計全般・決算11.8 | D55: 一般会計全般 | E55: その他 | F55: セットアップ | G55: 勘定科目 | H55: 11.8 | I55: 勘定科目に対して紐づく部門、取引先、取引内容等を設定できること | J55: 勘定科目によって入力項目を制限できる機能 | K55: 会計システム標準機能 | L55: 財務分析コードを使用して対応可能
A56: 一般会計全般・決算 | B56: =A56&H56 -> 一般会計全般・決算12.1 | C56: 一般会計全般・決算12.1 | D56: 決算業務 | E56: 単体決算 | F56: 決算仕訳 | G56: 月次決算仕訳 | H56: 12.1 | I56: 月次毎に下記の仕訳を登録できること ・消費税、印紙税納付 ・監査報酬月次計上 ・持株会拠出、購入 | J56: 月次毎に決算仕訳が登録できる機能 | K56: 会計システム標準機能 | L56: 一般的な仕訳等の登録用と異なるレイヤー(仕訳帳)に仕訳登録し、レポート側でどのレイヤーを出力するかの定義で対応可能
A57: 一般会計全般・決算 | B57: =A57&H57 -> 一般会計全般・決算12.2 | C57: 一般会計全般・決算12.2 | D57: 決算業務 | E57: 単体決算 | F57: 決算仕訳 | G57: 半期決算仕訳 | H57: 12.2 | I57: 半期毎に以下の仕訳を登録できること ・資産除去債務・償却費計上 ・投資有価証券時価洗替 ・ECサイト売上計上 ・減損計上 ・ゴルフ会員権評価損の貸倒引当 ・在庫評価減・原価差額振替 | J57: 半期毎に決算仕訳が登録できる機能 | K57: 会計システム標準機能 | L57: 一般的な仕訳等の登録用と異なるレイヤー(仕訳帳)に仕訳登録し、レポート側でどのレイヤーを出力するかの定義で対応可能
A58: 一般会計全般・決算 | B58: =A58&H58 -> 一般会計全般・決算12.3 | C58: 一般会計全般・決算12.3 | D58: 決算業務 | E58: 単体決算 | F58: 決算仕訳 | G58: 税金計算仕訳 | H58: 12.3 | I58: 半期毎に以下の税金計算に関わる仕訳を登録できること ・未払消費税照合・計上 ・法人税等計算 ・税効果計算 ・税金伝票入力 | J58: 半期毎に税金計算に関わる仕訳が登録できる機能 | K58: 会計システム標準機能 | L58: 一般的な仕訳等の登録用と異なるレイヤー(仕訳帳)に仕訳登録し、レポート側でどのレイヤーを出力するかの定義で対応可能
A59: 一般会計全般・決算 | B59: =A59&H59 -> 一般会計全般・決算13.1 | C59: 一般会計全般・決算13.1 | D59: 決算業務 | E59: 単体決算 | F59: 為替評価 | G59: 期末残高再評価 | H59: 13.1 | I59: 外貨建てのB/S科目を、期末レートで未実現為替差損益を再計算できること | J59: 未実現為替差損益を算定するために、外貨建てのB/S科目を期末レートで再計算する機能 | K59: 会計システム標準機能
A60: 一般会計全般・決算 | B60: =A60&H60 -> 一般会計全般・決算13.2 | C60: 一般会計全般・決算13.2 | D60: 決算業務 | E60: 単体決算 | F60: 為替評価 | G60: 期末残高再評価 | H60: 13.2 | I60: 外貨建て取引残高を勘定科目別に画面照会および帳票出力できること | J60: 期末評価替え後の通貨別残高を把握するために、勘定科目別に外貨建て取引の残高を出力する機能 | K60: 会計システム標準機能
A61: 一般会計全般・決算 | B61: =A61&H61 -> 一般会計全般・決算14.1 | C61: 一般会計全般・決算14.1 | D61: 決算業務 | E61: 単体決算 | F61: 決算締め | G61: 月次締め処理 | H61: 14.1 | I61: 会計システム内で月次の試算表/PL/BSと各種勘定残高明細を参照し、月次締め処理ができること | J61: 月次の締め処理を行う機能 | K61: 会計システム標準機能
A62: 一般会計全般・決算 | B62: =A62&H62 -> 一般会計全般・決算14.2 | C62: 一般会計全般・決算14.2 | D62: 決算業務 | E62: 単体決算 | F62: 決算締め | G62: 年次締め処理 | H62: 14.2 | I62: 会計システム内で年次の試算表/PL/BSと各種勘定残高明細を参照し、年次締め処理ができること | J62: 会計年度の締め処理を行う機能 | K62: 会計システム標準機能
A63: 一般会計全般・決算 | B63: =A63&H63 -> 一般会計全般・決算14.3 | C63: 一般会計全般・決算14.3 | D63: 決算業務 | E63: 単体決算 | F63: 決算締め | G63: 次年度繰越 | H63: 14.3 | I63: 前年度末の残高を翌年度の期首残高として自動で行うことができること | J63: 会計年度の切替において期首残高を自動で繰越する機能 | K63: 会計システム標準機能
A64: 一般会計全般・決算 | B64: =A64&H64 -> 一般会計全般・決算14.4 | C64: 一般会計全般・決算14.4 | D64: 決算業務 | E64: 単体決算 | F64: 決算締め | G64: 期首残設定 | H64: 14.4 | I64: 当会計年度で会計処理を開始できるように期首残高を自動で設定することができること | J64: 会計年度の開始できるように期首残高を自動で設定する機能 | K64: 会計システム標準機能
A65: 一般会計全般・決算 | B65: =A65&H65 -> 一般会計全般・決算15.1 | C65: 一般会計全般・決算15.1 | D65: 決算業務 | E65: 単体決算 | F65: その他決算作業 | G65: 在庫棚卸 | H65: 15.1 | I65: 半期毎に倉庫一覧データと在庫データを用いて在庫の棚卸を実施し、棚卸差損益を計上できること | J65: 半期末時点における棚卸差損益を登録できる機能 | K65: 会計システム標準機能 | L65: 外部ツールでの作成された棚卸結果の金額のみ、仕訳伝票登録する
A66: 一般会計全般・決算 | B66: =A66&H66 -> 一般会計全般・決算15.2 | C66: 一般会計全般・決算15.2 | D66: 決算業務 | E66: 単体決算 | F66: その他決算作業 | G66: 配当金支払 | H66: 15.2 | I66: 配当金支払の仕訳を登録できること | J66: 配当金支払の仕訳を登録できる機能 | K66: 会計システム標準機能 | L66: 繰越利益剰余金の仕訳処理等を含め、マニュアルで仕訳登録いただく前提
A67: 一般会計全般・決算 | B67: =A67&H67 -> 一般会計全般・決算15.3 | C67: 一般会計全般・決算15.3 | D67: 決算業務 | E67: 単体決算 | F67: その他決算作業 | G67: 受取配当金計上 | H67: 15.3 | I67: 受取配当金の計上仕訳を登録できること | J67: 受取配当金の計上仕訳を登録できる機能 | K67: 会計システム標準機能 | L67: 税金処理等を含め、マニュアルで仕訳登録いただく前提
A68: 一般会計全般・決算 | B68: =A68&H68 -> 一般会計全般・決算16.1 | C68: 一般会計全般・決算16.1 | D68: 決算業務 | E68: 連結決算 | F68: IFRS | G68: 複数帳簿 | H68: 16.1 | I68: 日本基準/IFRS/税務でそれぞれ異なる基準で帳簿作成・保存できること (Ex.日本基準とIFRSで固定資産台帳を別々で作成できること等) | J68: 日本基準/IFRS/税務用の帳簿が作成できること | K68: 会計システム標準機能 | L68: 一般的な仕訳等の登録用と異なるレイヤー(仕訳帳)に仕訳登録し、レポート側でどのレイヤーを出力するかの定義で対応可能
A69: 一般会計全般・決算 | B69: =A69&H69 -> 一般会計全般・決算16.2 | C69: 一般会計全般・決算16.2 | D69: 決算業務 | E69: 連結決算 | F69: IFRS | G69: TB作成 | H69: 16.2 | I69: 連結決算用のIFRSベースのTBを作成できること | J69: IFRSベースのTBの作成機能(IFRS開示用科目(親科目)とIFRS集計元科目(子科目)単位でそれぞれ閲覧できること) | K69: 会計システム標準機能 | L69: TB(残高試算表）はMRで対応
A70: 一般会計全般・決算 | B70: =A70&H70 -> 一般会計全般・決算16.3 | C70: 一般会計全般・決算16.3 | D70: 決算業務 | E70: 連結決算 | F70: IFRS | G70: 調整仕訳登録 | H70: 16.3 | I70: 年次毎に以下のIFRS調整仕訳を登録できること ・貯蔵品（販促物） ・有給休暇引当金 ・総平均→FIFO（SEJのみ） ・在庫評価減（SSJのみ） ・有価証券売却益振替 ・減損総額表示 | J70: IFRSの調整仕訳を登録できる機能 | K70: 会計システム標準機能 | L70: 一般的な仕訳等の登録用と異なるレイヤー(仕訳帳)に仕訳登録し、レポート側でどのレイヤーを出力するかの定義で対応可能
A71: 一般会計全般・決算 | B71: =A71&H71 -> 一般会計全般・決算17.1 | C71: 一般会計全般・決算17.1 | D71: 決算業務 | E71: 連結決算 | F71: 連結会計システムへ連携 | G71: 連結会計システムへアップロード | H71: 17.1 | I71: 連結会計システムへデータのアップロードができること | J71: 連結会計システムへデータ連携できる機能 | K71: 会計システム標準機能
A72: 一般会計全般・決算 | B72: =A72&H72 -> 一般会計全般・決算17.2 | C72: 一般会計全般・決算17.2 | D72: 決算業務 | E72: 連結決算 | F72: 連結会計システムへ連携 | G72: 連結会計システムエラー確認・修正 | H72: 17.2 | I72: 連結会計システムへデータを連携した後、エラーを確認し、必要に応じて修正できること | J72: 連結会計システムへデータ連携後、修正できる機能 | K72: 会計システム標準機能
A73: 一般会計全般・決算 | B73: =A73&H73 -> 一般会計全般・決算17.3 | C73: 一般会計全般・決算17.3 | D73: 決算業務 | E73: 連結決算 | F73: 連結会計システムへ連携 | G73: 連結会計システムCF確認・修正 | H73: 17.3 | I73: 連結会計システムへデータを連携した後、CFを確認し、必要に応じて修正できること | J73: 連結会計システムへデータ連携後、CFを修正できる機能 | K73: 会計システム標準機能
A74: 一般会計全般・決算 | B74: =A74&H74 -> 一般会計全般・決算18.1 | C74: 一般会計全般・決算18.1 | D74: 決算業務 | E74: 連結決算 | F74: 連結決算用レポート | G74: 明細作成 | H74: 18.1 | I74: 年次毎に例えば以下のIFRS明細を作成できること (日本基準/IFRSで複数明細が保持できること) ・IFRS固定資産明細(圧縮記帳含む) ・IFRS減損資料 ・IFRS税効果会計資料 ・IFRS有価証券明細 ・IFRS金融負債明細 | J74: IFRSベースの各明細を作成・出力できる機能 | K74: 会計システムアドオン | L74: IFRSに対応した仕訳登録は、FO標準機能「一般仕訳帳」にて転記階層を変更して登録することで通常の仕訳、残高に影響なく登録可能。ただし、下記帳票類については別途開発が必要となります。 ・IFRS固定資産明細(圧縮記帳含む) ・IFRS減損資料 ・IFRS税効果会計資料 ・IFRS有価証券明細 ・IFRS金融負債明細
A75: 固定資産管理 | B75: =A75&H75 -> 固定資産管理1.1 | C75: 固定資産管理1.1 | D75: 固定資産管理 | E75: 固定資産 | F75: 取得 | G75: 取得登録 | H75: 1.1 | I75: 固定資産取得(本勘定振替)に必要な情報を入力したうえ、登録処理できること | J75: 固定資産の取得に必要な情報を入力・登録する機能 | K75: 会計システム標準機能
A76: 固定資産管理 | B76: =A76&H76 -> 固定資産管理1.2 | C76: 固定資産管理1.2 | D76: 固定資産管理 | E76: 固定資産 | F76: 取得 | G76: 取得登録 | H76: 1.2 | I76: 固定資産取得伝票が確認・出力できること | J76: 固定資産の取得時の伝票を出力する機能 | K76: 会計システム標準機能
A77: 固定資産管理 | B77: =A77&H77 -> 固定資産管理1.3 | C77: 固定資産管理1.3 | D77: 固定資産管理 | E77: 固定資産 | F77: 取得 | G77: 取得登録 | H77: 1.3 | I77: 固定資産取得(本勘定振替)処理に伴う仕訳が生成できること | J77: 固定資産の取得処理に伴う仕訳を生成する機能 | K77: 会計システム標準機能
A78: 固定資産管理 | B78: =A78&H78 -> 固定資産管理1.4 | C78: 固定資産管理1.4 | D78: 固定資産管理 | E78: 固定資産 | F78: 取得 | G78: 取得登録 | H78: 1.4 | I78: 建設仮勘定の消費税を別の仮勘定へ振替できること | J78: 建設仮勘定の本体価額とそれに付随する仮払消費税額を識別できる機能 | K78: 会計システム標準機能 | L78: 一般仕訳帳で対応
A79: 固定資産管理 | B79: =A79&H79 -> 固定資産管理1.5 | C79: 固定資産管理1.5 | D79: 固定資産管理 | E79: 固定資産 | F79: 取得 | G79: 取得情報修正 | H79: 1.5 | I79: 資産情報の変更ができること | J79: 資産分類、耐用年数、償却方法等を変更する機能 | K79: 会計システム標準機能
A80: 固定資産管理 | B80: =A80&H80 -> 固定資産管理1.6 | C80: 固定資産管理1.6 | D80: 固定資産管理 | E80: 固定資産 | F80: 取得 | G80: 取得情報修正 | H80: 1.6 | I80: 取得資産増減処理の同年度内で過去遡及ができること | J80: 取得資産の増減処理を同年度内過去に遡って実施する機能 | K80: 会計システムアドオン | L80: 取得資産の増減処理を同年度内過去に遡って実施する機能を開発。
A81: 固定資産管理 | B81: =A81&H81 -> 固定資産管理1.7 | C81: 固定資産管理1.7 | D81: 固定資産管理 | E81: 固定資産 | F81: 取得 | G81: 取得情報修正 | H81: 1.7 | I81: 資産情報の登録内容を確認できること | J81: 部課コードの設定状況等、修正したい各情報の登録状況を確認する機能 | K81: 会計システム標準機能
A82: 固定資産管理 | B82: =A82&H82 -> 固定資産管理2.1 | C82: 固定資産管理2.1 | D82: 固定資産管理 | E82: 固定資産 | F82: 資産除去債務 | G82: 資産除去債務 | H82: 2.1 | I82: 資産除去債務の登録ができ、利息計算ができること | J82: 資産除去債務の登録と利息計算をする機能 | K82: 会計システム標準機能
A83: 固定資産管理 | B83: =A83&H83 -> 固定資産管理3.1 | C83: 固定資産管理3.1 | D83: 固定資産管理 | E83: 固定資産 | F83: 圧縮記帳 | G83: 圧縮記帳 | H83: 3.1 | I83: 圧縮記帳ができること | J83: 圧縮記帳を行う機能 | K83: 会計システム標準機能
A84: 固定資産管理 | B84: =A84&H84 -> 固定資産管理4.1 | C84: 固定資産管理4.1 | D84: 固定資産管理 | E84: 固定資産 | F84: 減価償却 | G84: 減価償却費計上 | H84: 4.1 | I84: 資産の減価償却・除却処理内容を更新できること | J84: 償却方法、耐用年数、組織、遊休設定、増加償却率等の資産に紐付く情報を変更する機能 | K84: 会計システム標準機能
A85: 固定資産管理 | B85: =A85&H85 -> 固定資産管理4.2 | C85: 固定資産管理4.2 | D85: 固定資産管理 | E85: 固定資産 | F85: 減価償却 | G85: 減価償却費計上 | H85: 4.2 | I85: 償却額を自動計算できること | J85: 定率法・定額法・月割償却・定額切替・均等償却・即時償却・非償却・リース期間定額法・任意償却といった一般的な償却計算方法で償却計算を行う機能 | K85: 会計システム標準機能
A86: 固定資産管理 | B86: =A86&H86 -> 固定資産管理4.3 | C86: 固定資産管理4.3 | D86: 固定資産管理 | E86: 固定資産 | F86: 減価償却 | G86: 減価償却費計上 | H86: 4.3 | I86: 償却額を自動再計算できること | J86: 取得価額が増減した場合に、償却額を再計算する機能 | K86: 会計システム標準機能
A87: 固定資産管理 | B87: =A87&H87 -> 固定資産管理4.4 | C87: 固定資産管理4.4 | D87: 固定資産管理 | E87: 固定資産 | F87: 減価償却 | G87: 減価償却費計上 | H87: 4.4 | I87: 増加償却できること | J87: 増加償却を行う機能 | K87: 会計システム標準機能
A88: 固定資産管理 | B88: =A88&H88 -> 固定資産管理4.5 | C88: 固定資産管理4.5 | D88: 固定資産管理 | E88: 固定資産 | F88: 減価償却 | G88: 減価償却費計上 | H88: 4.5 | I88: 特別償却、割増償却できること | J88: 特別償却、割増償却を行う機能 | K88: 会計システム標準機能
A89: 固定資産管理 | B89: =A89&H89 -> 固定資産管理4.6 | C89: 固定資産管理4.6 | D89: 固定資産管理 | E89: 固定資産 | F89: 減価償却 | G89: 減価償却費計上 | H89: 4.6 | I89: 遊休設定(償却停止)できること | J89: 各資産毎に遊休設定し、償却費を発生させない機能 | K89: 会計システム標準機能 | L89: ブロックする
A90: 固定資産管理 | B90: =A90&H90 -> 固定資産管理4.7 | C90: 固定資産管理4.7 | D90: 固定資産管理 | E90: 固定資産 | F90: 減価償却 | G90: 減価償却費計上 | H90: 4.7 | I90: 償却費を複数部門に配賦できること | J90: 償却費を複数部門に配賦する機能 | K90: 会計システム標準機能 | L90: 紐づく財務分析コードを振り返る仕訳で対応可能
A91: 固定資産管理 | B91: =A91&H91 -> 固定資産管理4.8 | C91: 固定資産管理4.8 | D91: 固定資産管理 | E91: 固定資産 | F91: 減価償却 | G91: 減価償却費計上 | H91: 4.8 | I91: 複数期間の償却費を出力できること | J91: 既存資産の月毎、四半期毎、半期毎、年毎の償却費を出力する機能 | K91: 会計システム標準機能 | L91: FO標準機能の財務諸表にて対応
A92: 固定資産管理 | B92: =A92&H92 -> 固定資産管理4.9 | C92: 固定資産管理4.9 | D92: 固定資産管理 | E92: 固定資産 | F92: 減価償却 | G92: 償却シミュレーション | H92: 4.9 | I92: 取得予定、除却予定、減損予定、移動予定を加味して既存資産・新規資産の減価償却費のシミュレーションができること | J92: 取得予定、除却予定、減損予定、移動予定を加味した償却シミュレーションする機能 | K92: 会計システムアドオン | L92: 各予定をFO標準機能を利用して登録した後、償却シミュレーション機能については開発。
A93: 固定資産管理 | B93: =A93&H93 -> 固定資産管理5.1 | C93: 固定資産管理5.1 | D93: 固定資産管理 | E93: 固定資産 | F93: 減損 | G93: 減損処理 | H93: 5.1 | I93: 減損処理できること | J93: 減損処理を行う機能 | K93: 会計システム標準機能
A94: 固定資産管理 | B94: =A94&H94 -> 固定資産管理5.2 | C94: 固定資産管理5.2 | D94: 固定資産管理 | E94: 固定資産 | F94: 減損 | G94: 減損額の配分 | H94: 5.2 | I94: 減損損失額の資産別配分できること | J94: 減損損失額を資産別に配分する機能 | K94: 会計システム標準機能 | L94: 固定資産ごとに財務分析コードを設定し、対応する
A95: 固定資産管理 | B95: =A95&H95 -> 固定資産管理6.1 | C95: 固定資産管理6.1 | D95: 固定資産管理 | E95: 固定資産 | F95: 移動 | G95: 移動処理 | H95: 6.1 | I95: 資産の移動登録ができること | J95: 資産の移動を登録する機能 | K95: 会計システム標準機能
A96: 固定資産管理 | B96: =A96&H96 -> 固定資産管理6.2 | C96: 固定資産管理6.2 | D96: 固定資産管理 | E96: 固定資産 | F96: 移動 | G96: 一括移動 | H96: 6.2 | I96: 複数資産の一括移動処理ができること | J96: 複数資産を一括で移動処理する機能 | K96: 会計システムアドオン | L96: 一括移動処理機能を開発。
A97: 固定資産管理 | B97: =A97&H97 -> 固定資産管理7.1 | C97: 固定資産管理7.1 | D97: 固定資産管理 | E97: 固定資産 | F97: 分割 | G97: 分割処理 | H97: 7.1 | I97: 資産の分割処理できること | J97: 資産を分割し登録する機能 | K97: 会計システム標準機能 | L97: 新規登録と変更のマニュアル処理
A98: 固定資産管理 | B98: =A98&H98 -> 固定資産管理8.1 | C98: 固定資産管理8.1 | D98: 固定資産管理 | E98: 固定資産 | F98: 除売却 | G98: 除売却処理 | H98: 8.1 | I98: 資産の除売却登録ができること | J98: 資産の除売却を登録する機能 | K98: 会計システム標準機能
A99: 固定資産管理 | B99: =A99&H99 -> 固定資産管理8.2 | C99: 固定資産管理8.2 | D99: 固定資産管理 | E99: 固定資産 | F99: 除売却 | G99: 除売却処理 | H99: 8.2 | I99: 除売却に伴う仕訳を自動生成できること | J99: 除売却に伴う仕訳を自動生成する機能 | K99: 会計システム標準機能 | L99: 固定資産仕訳帳を登録する(自動ではない）
A100: 固定資産管理 | B100: =A100&H100 -> 固定資産管理9.1 | C100: 固定資産管理9.1 | D100: 固定資産管理 | E100: 固定資産 | F100: 償却資産税申告 | G100: 申告書作成 | H100: 9.1 | I100: 償却資産申告用帳簿管理できること | J100: 財務帳簿、税務帳簿とは別に償却資産申告用に耐用年数、資産の種類、取得価額を保持し、その値を変更する機能 | K100: 会計システムアドオン | L100: 償却資産申告用に耐用年数、資産の種類、取得価額を保持し、その値を変更する機能を開発。
A101: 固定資産管理 | B101: =A101&H101 -> 固定資産管理9.2 | C101: 固定資産管理9.2 | D101: 固定資産管理 | E101: 固定資産 | F101: 償却資産税申告 | G101: 申告書作成 | H101: 9.2 | I101: 償却資産申告書出力できること | J101: 償却資産申告書（課税台帳）を出力する機能 | K101: 会計システムアドオン | L101: 償却資産申告書（課税台帳）の帳票機能を開発。
A102: 固定資産管理 | B102: =A102&H102 -> 固定資産管理9.3 | C102: 固定資産管理9.3 | D102: 固定資産管理 | E102: 固定資産 | F102: 償却資産税申告 | G102: 申告書作成 | H102: 9.3 | I102: 種類別明細書出力できること | J102: 種類別明細書(全資産用・増加資産用・減少資産用)を出力する機能 | K102: 会計システムアドオン | L102: 種類別明細書(全資産用・増加資産用・減少資産用)の帳票機能を開発。
A103: 固定資産管理 | B103: =A103&H103 -> 固定資産管理9.4 | C103: 固定資産管理9.4 | D103: 固定資産管理 | E103: 固定資産 | F103: 償却資産税申告 | G103: 申告書作成 | H103: 9.4 | I103: 過年度分の償却資産申告書、種類別明細書出力できること | J103: 償却資産申告書、種類別明細書を過年度分も出力する機能 | K103: 会計システムアドオン | L103: 償却資産申告書、種類別明細書を過年度分の帳票機能を開発。
A104: 固定資産管理 | B104: =A104&H104 -> 固定資産管理9.5 | C104: 固定資産管理9.5 | D104: 固定資産管理 | E104: 固定資産 | F104: 償却資産税申告 | G104: 税額計算 | H104: 9.5 | I104: 税額計算用の償却計算できること | J104: 会計期間とは別に1月-12月のサイクルで償却計算を行い、自治体別の償却資産税額を計算する機能 | K104: 会計システムアドオン | L104: 会計期間とは別に1月-12月のサイクルで償却計算を行い、自治体別の償却資産税額を計算する機能を開発。
A105: 固定資産管理 | B105: =A105&H105 -> 固定資産管理10.1 | C105: 固定資産管理10.1 | D105: 固定資産管理 | E105: 固定資産 | F105: レポーティング | G105: 台帳 | H105: 10.1 | I105: 固定資産台帳を出力・管理できること | J105: 固定資産台帳を出力・管理する機能 | K105: 会計システム標準機能
A106: 固定資産管理 | B106: =A106&H106 -> 固定資産管理10.2 | C106: 固定資産管理10.2 | D106: 固定資産管理 | E106: 固定資産 | F106: レポーティング | G106: 明細 | H106: 10.2 | I106: 固定資産の詳細情報をそのまま、または、複数条件で集計して出力できること | J106: 部門、種類、構造用途、分類、設置場所、資産番号等の項目を集計キーとして集計し出力する機能 | K106: 会計システム標準機能
A107: 固定資産管理 | B107: =A107&H107 -> 固定資産管理10.3 | C107: 固定資産管理10.3 | D107: 固定資産管理 | E107: 固定資産 | F107: レポーティング | G107: 増減明細 | H107: 10.3 | I107: 固定資産の処理区分(移動、分割、除却等)毎に明細を出力できること | J107: 固定資産の処理区分(移動、分割、除却等)毎に明細を出力する機能 | K107: 会計システム標準機能
...

Sheet マスタ
B1: 優先度
B2: S | C2: 業務が停止してしまうので必須
B3: A | C3: 運用回避が可能だが、業務負荷が大きいもの
B4: B | C4: 運用回避が可能で、業務負荷がそれほど大きくないもの
B5: C | C5: 便利機能としての要求事項
B7: 対象システム
B8: FO
B9: CRM
B10: その他
B11: -
B13: 開発
B14: 必要
B15: 不要
B17: スコープ
B18: IN
B19: OUT
